Workbook

Sheet Necesidades Trimestrales (2)
B2: Pedido de Necesidades Trimestrales
A4: JURISDICCION: | C4: 70 - MINISTERIO DE CIENCIA E INNOVACION TECNOLOGICA
A5: SAF N°: | C5: 20 - MINISTERIO DE CIENCIA E INNOVACION TECNOLOGICA
A6: EJERCICIO: | C6: 2021
A7: TRIMESTRE: | C7: 3
A9: ID | B9: CODIGO ITEM | C9: RUBRO DE COMPRA | D9: I.P.P. | E9: DESCRIPCION | F9: UNIDAD DE MEDIDA | G9: CANTIDAD | H9: PRECIO UNITARIO ESTIMADO | I9: IMPORTE TOTAL ESTIMADO
A10: 1 | B10: 4.3.6-6160.208 | C10: INFORMATICA | D10: =LEFT(B10,5) -> 4.3.6 | E10: COMPUTADORAS; TIPO: NOTEBOOK, CODIGO ETAP: PC-008, VERSION ETAP: 22.0 | F10: UNIDAD | G10: 22 | H10: 125000 | I10: =H10*G10 -> 2750000 | L10: =I10+I11+I12+#REF!+#REF! -> #REF!
A11: 2 | B11: 4.3.6-6160.221 | C11: INFORMATICA | D11: =LEFT(B11,5) -> 4.3.6 | E11: COMPUTADORAS; TIPO: DE ESCRITORIO, CODIGO ETAP: PC-002-00, VERSION ETAP: 23.0 | F11: UNIDAD | G11: 8 | H11: 140000 | I11: =H11*G11 -> 1120000
A12: 3 | B12: 4.3.6-9604.3 | C12: INFORMATICA | D12: =LEFT(B12,5) -> 4.3.6 | E12: TABLETA PC; RESOLUCION: 1280 X 800 PXL, PANTALLA: 9,4 pulg, MEMORIA: 32 Gb, MEMORIA RAM: 32 Gb | F12: UNIDAD | G12: 15 | H12: 40000 | I12: =H12*G12 -> 600000
E13: Costo total estimado: INFORMATICA | I13: =SUM(I10:I12) -> 4470000
A15: 4 | B15: 4.3.6-9707.20 | C15: EQUIPO | D15: =LEFT(B15,5) -> 4.3.6 | E15: IMPRESORA 3D; TIPO: FDM, DIMENSION: 220 X 220 X 260mm, RESOLUCION: SEGÚN PLIEGO, PRECISION: SEGÚN PLIEGO, ESPESOR CAPA: SEGÚN PLIEGO | F15: UNIDAD | G15: 13 | H15: 150000 | I15: =H15*G15 -> 1950000
A16: 5 | B16: 4.3.6-9707.21 | C16: EQUIPO | D16: =LEFT(B16,5) -> 4.3.6 | E16: IMPRESORA 3D; TIPO: LAPICES 3D, DIMENSION: 17.5 CM x 1.7 CM x 2CM, TEMPERATURA AJUSTABLE: 130-235 GRADOS, MATERIAL DE IMPRESION: ABS Y PLA, VOLTAJE: DC 5V 2A 10W | F16: UNIDAD | G16: 10 | H16: 6000 | I16: =H16*G16 -> 60000
A17: 6 | B17: 4.3.5-1615.69 | C17: EQUIPO | D17: =LEFT(B17,5) -> 4.3.5 | E17: PROYECTORES; PANTALLA: SIN, RESOLUCION: 800 X 600 SVGA, LENTE: FIJO ZOOM | F17: UNIDAD | G17: 8 | H17: 77000 | I17: =H17*G17 -> 616000
A18: 7 | B18: 4.3.5-9163.80 | C18: EQUIPO | D18: =LEFT(B18,5) -> 4.3.5 | E18: EQUIPOS DIDACTICOS TECNICOS; NOMBRE: LENTES, TIPO: REALIDAD VIRTUAL | F18: UNIDAD | G18: 10 | H18: 187000 | I18: =H18*G18 -> 1870000
A19: 8 | B19: 4.3.5-9163.90 | C19: EQUIPO | D19: =LEFT(B19,5) -> 4.3.5 | E19: EQUIPOS DIDACTICOS TECNICOS; NOMBRE: KIT EXPERIMENTAL , TIPO: SEGÚN PLIEGO | F19: UNIDAD | G19: 10 | H19: 190000 | I19: =H19*G19 -> 1900000
A20: 9 | B20: 4.3.5-9163.90 | C20: EQUIPO | D20: =LEFT(B20,5) -> 4.3.5 | E20: EQUIPOS DIDACTICOS TECNICOS; NOMBRE: KIT EXPERIMENTAL , TIPO: SEGÚN PLIEGO | F20: UNIDAD | G20: 4 | H20: 310000 | I20: =H20*G20 -> 1240000
A21: 10 | B21: 4.3.5-9163.90 | C21: EQUIPO | D21: =LEFT(B21,5) -> 4.3.5 | E21: EQUIPOS DIDACTICOS TECNICOS; NOMBRE: KIT EXPERIMENTAL , TIPO: SEGÚN PLIEGO | F21: UNIDAD | G21: 20 | H21: 60000 | I21: =H21*G21 -> 1200000
A22: 11 | B22: 4.3.5-9163.90 | C22: EQUIPO | D22: =LEFT(B22,5) -> 4.3.5 | E22: EQUIPOS DIDACTICOS TECNICOS; NOMBRE: KIT EXPERIMENTAL , TIPO: SEGÚN PLIEGO | F22: UNIDAD | G22: 30 | H22: 16000 | I22: =H22*G22 -> 480000
A23: 12 | B23: 4.3.5-9163.90 | C23: EQUIPO | D23: =LEFT(B23,5) -> 4.3.5 | E23: EQUIPOS DIDACTICOS TECNICOS; NOMBRE: KIT EXPERIMENTAL , TIPO: SEGÚN PLIEGO | F23: UNIDAD | G23: 60 | H23: 15000 | I23: =H23*G23 -> 900000
A24: 13 | B24: 4.3.5-9163.90 | C24: EQUIPO | D24: =LEFT(B24,5) -> 4.3.5 | E24: EQUIPOS DIDACTICOS TECNICOS; NOMBRE: KIT EXPERIMENTAL , TIPO: SEGÚN PLIEGO | F24: UNIDAD | G24: 40 | H24: 61000 | I24: =H24*G24 -> 2440000
A25: 14 | B25: 4.3.5-9163.64 | C25: EQUIPO | D25: =LEFT(B25,5) -> 4.3.5 | E25: EQUIPOS DIDACTICOS TECNICOS; NOMBRE: SISTEMA DE SONIDO, TIPO: ESTEREO | F25: UNIDAD | G25: 5 | H25: 130000 | I25: =H25*G25 -> 650000
A26: 15 | B26: 4.3.5-9138.2 | C26: EQUIPO | D26: =LEFT(B26,5) -> 4.3.5 | E26: PIZARRAS INTERACTIVAS; DIMENSION: 170 X 120 X 12 Cm, SOFTWARE: SMART BOARD, RESOLUCION: 6000 X 6000 | F26: UNIDAD | G26: 4 | H26: 95000 | I26: =H26*G26 -> 380000
... A29: 18 | B29: 2.9.3-6368.12 | C29: EQUIPO | D29: =LEFT(B29,5) -> 2.9.3 | E29: CONTROLADORES DE PROCESO; TIPO: MODULO DE EXPANSION, SALIDA: SIN, FORMATO: MODULAR, ALIMENTACION: 24 VCC, INDICADOR: A LED, TIPO DE ENTRADA: DISCRETA | F29: UNIDAD | G29: 30 | H29: 3200 | I29: =H29*G29 -> 96000
E30: Costo total estimado:EQUIPOS | I30: =SUM(I15:I29) -> 13889000
A32: 19 | B32: 4.3.2-8803.26 | C32: TRANSPORTE Y DEPOSITO | D32: =LEFT(B32,5) -> 4.3.2 | E32: AERONAVES; TIPO: NO TRIPULADA, ENVERGADURA: 350 mm, POTENCIA: 100 W, VELOCIDAD MAXIMA: 20 M/SEG | F32: UNIDAD | G32: 5 | H32: 30000 | I32: =H32*G32 -> 150000
A33: 20 | B33: 4.3.2-8803.25 | C33: TRANSPORTE Y DEPOSITO | D33: =LEFT(B33,5) -> 4.3.2 | E33: AERONAVES; TIPO: NO TRIPULADA, ENVERGADURA: 80 Cm, POTENCIA: SIN, VELOCIDAD MAXIMA: 50 Km/h | F33: UNIDAD | G33: 1 | H33: 105000 | I33: =H33*G33 -> 105000
A34: Costo total estimado: TRANSPORTE Y DEPOSITO | I34: =SUM(I32:I33) -> 255000
I37: =I34+I30+I13 -> 18614000
B38: Especificidades Item N° 1:
B40: Descripción técnica
C41: NOTEBOOK - alto rendimiento – Pantalla HD 14” Resolución 1366px x 768px mínimo. Procesador Tipo Intel Core i5-8265U 4.2 GHz. Memoria del Sistema 8 GB. DDR4 SDRAM. Conectividad Lector de Tarjeta 4 en 1. HDMI. USB 4 (2X 3.29), (2X3.2 Type C). DISCO RIGIDO 256 GB SSD mínimo. Sistema Operativo WINDOWS 10 Pro. Batería de 65 Wh mínimo. Wifi.
B42: Plazos y lugares de entrega
C43: El plazo de entrega no podrá ser superior a los diez (10) días hábiles a partir de la fecha de recepción de la respectiva Orden de Compra en el domicilio especial electrónico constituido, en virtud del método de contratación. La entrega de dichos bienes se realizará en el Ministerio de Ciencia e Innovación Tecnologica, sito en Avenida Belgrano N° 1494 - CAPE- Pabellón N° 26 San Fernando del Valle de Catamarca. Se presentará Remito que deberá cumplimentar lo dispuesto por la R.G. AFIP 1415/03, sin excepción.
B45: Calidad Minima esperada
B47: Mantenimiento: treinta (30) dias corridos
B49: Garantia
C50: Garantía del fabricante minima de un (1) año.
B53: Especificidades Item N° 2:
B55: Descripción técnica
C56: COMPUTADORA ESTÁNDAR - alto rendimiento - CPU: CORE I7 10700F * Motherboard: MSI H310M PRO-VHD PLUS * Memoria RAM Memoria Ddr4 8Gb 2666Mhz (CB8GU2666) * Video: Intel HD 630 (Integrado) * DISCO RIGIDO: 1TB 7200RPM SATA3 * Fuente: 500W (c/Gabinete) * TECLADO+MOUSE+PARLANTES * Placa WiFi USB DUAL Frecuencias 2,4 y 5 Ghz *. Monitor LED 19” mínimo Resolución de 1366px-768px.
B57: Plazos y lugares de entrega
C58: El plazo de entrega no podrá ser superior a los diez (10) días hábiles a partir de la fecha de recepción de la respectiva Orden de Compra en el domicilio especial electrónico constituido, en virtud del método de contratación. La entrega de dichos bienes se realizará en el Ministerio de Ciencia e Innovación Tecnologica, sito en Avenida Belgrano N° 1494 - CAPE- Pabellón N° 26 San Fernando del Valle de Catamarca. Se presentará Remito que deberá cumplimentar lo dispuesto por la R.G. AFIP 1415/03, sin excepción.
B60: Calidad Minima esperada
B62: Mantenimiento: treinta (30) dias corridos
B64: Garantia
C65: Garantía del fabricante minima de un (1) año.
B69: Especificidades Item N° 3:
B71: Descripción técnica
C72: TABLET: Sistema operativo: Android. Con procesador de 2GHz. ○ Resolución de pantalla de 1280px x 800px. Con lector microSD. 32 gb de almacenamiento ○ Memoria expandible. ○Sistema de altavoces.
B73: Plazos y lugares de entrega
C74: El plazo de entrega no podrá ser superior a los diez (10) días hábiles a partir de la fecha de recepción de la respectiva Orden de Compra en el domicilio especial electrónico constituido, en virtud del método de contratación. La entrega de dichos bienes se realizará en el Ministerio de Ciencia e Innovación Tecnologica, sito en Avenida Belgrano N° 1494 - CAPE- Pabellón N° 26 San Fernando del Valle de Catamarca. Se presentará Remito que deberá cumplimentar lo dispuesto por la R.G. AFIP 1415/03, sin excepción.
B76: Calidad Minima esperada
B78: Mantenimiento: treinta (30) dias corridos
B80: Garantia
C81: Garantía del fabricante minima de seis (6) meses.
B85: Especificidades Item N° 4:
B87: Descripción técnica
C88: Tecnología de Impresión 3D: FDM. Cantidad de extrusores: 2. Apta para filamentos ABS, PLA y Nylon. Largo de la zona de impresión: 220mm. Ancho de la zona de impresión: 220mm. Altura de la zona de impresión: 260mm. Resolución mínima y máxima de la capa: 390um – 100um. Temperatura máxima de la cama caliente: 110°C
B89: Plazos y lugares de entrega
C90: El plazo de entrega no podrá ser superior a los diez (10) días hábiles a partir de la fecha de recepción de la respectiva Orden de Compra en el domicilio especial electrónico constituido, en virtud del método de contratación. La entrega de dichos bienes se realizará en el Ministerio de Ciencia e Innovación Tecnologica, sito en Avenida Belgrano N° 1494 - CAPE- Pabellón N° 26 San Fernando del Valle de Catamarca. Se presentará Remito que deberá cumplimentar lo dispuesto por la R.G. AFIP 1415/03, sin excepción.
B92: Calidad Minima esperada
B94: Mantenimiento: treinta (30) dias corridos
B96: Garantia
C97: Garantía del fabricante minima de un (1) año.
B100: Especificidades Item N° 5:
B102: Descripción técnica
C103: Lápiz 3D. Modo de extrusión: automático. Temperatura Ajustable: 130-235 grados. Debe tener un Diseño ergonómico. Debe ser Fácil de usar, práctico y liviano. Área de impresión: ilimitada. Debe ser utilizado con filamento PLA de 1,75 mm
B104: Plazos y lugares de entrega
C105: El plazo de entrega no podrá ser superior a los diez (10) días hábiles a partir de la fecha de recepción de la respectiva Orden de Compra en el domicilio especial electrónico constituido, en virtud del método de contratación. La entrega de dichos bienes se realizará en el Ministerio de Ciencia e Innovación Tecnologica, sito en Avenida Belgrano N° 1494 - CAPE- Pabellón N° 26 San Fernando del Valle de Catamarca. Se presentará Remito que deberá cumplimentar lo dispuesto por la R.G. AFIP 1415/03, sin excepción.
B107: Calidad Minima esperada
B109: Mantenimiento: treinta (30) dias corridos
B111: Garantia
C112: Garantía del fabricante minima de un (1) año.
B115: Especificidades Item N° 6:
B117: Descripción técnica
C118: #Sistema de proyección: 0.55" SVGA. Resolución nativa: 800x600. Tipo DC: DC3. Brillo: 3600lm. Relación de contraste con modo SuperEco: 22000:1. Visualización de colores: 1,07 mil millones de colores. Distancia de alcance: 1.19m-13.11m (100" @3.98m). Compatibilidad con HDTV: 480i, 480p, 576i, 576p, 720p, 1080i, 1080p.
B119: Plazos y lugares de entrega
C120: El plazo de entrega no podrá ser superior a los diez (10) días hábiles a partir de la fecha de recepción de la respectiva Orden de Compra en el domicilio especial electrónico constituido, en virtud del método de contratación. La entrega de dichos bienes se realizará en el Ministerio de Ciencia e Innovación Tecnologica, sito en Avenida Belgrano N° 1494 - CAPE- Pabellón N° 26 San Fernando del Valle de Catamarca. Se presentará Remito que deberá cumplimentar lo dispuesto por la R.G. AFIP 1415/03, sin excepción.
B122: Calidad Minima esperada
B124: Mantenimiento: treinta (30) dias corridos
B126: Garantia
C127: Garantía del fabricante minima de un (1) año.
B130: Especificidades Item N° 7:
B132: Descripción técnica
C133: Lentes ajustables OLED de 1.600 x 1.400 píxeles. Debe contar con sensores externos de movimiento. Tasa de refresco de 60Hz. Dimensiones Aproximadas: 190x105x115mm. Peso: 468 gramos. Sonido integrado en correas de ajuste. Conexiones: micro-USB y minijack para auriculares externos. Sistema operativo basado en Android. Bluetooth integrado.
B134: Plazos y lugares de entrega
C135: El plazo de entrega no podrá ser superior a los diez (10) días hábiles a partir de la fecha de recepción de la respectiva Orden de Compra en el domicilio especial electrónico constituido, en virtud del método de contratación. La entrega de dichos bienes se realizará en el Ministerio de Ciencia e Innovación Tecnologica, sito en Avenida Belgrano N° 1494 - CAPE- Pabellón N° 26 San Fernando del Valle de Catamarca. Se presentará Remito que deberá cumplimentar lo dispuesto por la R.G. AFIP 1415/03, sin excepción.
B137: Calidad Minima esperada
B139: Mantenimiento: treinta (30) dias corridos
B141: Garantia
C142: Garantía del fabricante minima de un (1) año.
B145: Especificidades Item N° 8:
B147: Descripción técnica
C148: Súper Kit de la robótica educativa. • 800 componentes estructurales y de movimiento. • 4 motores inteligentes, 7 sensores (2 de contacto, 1 de distancia, 1 giroscopio, 1 de color, 2 touch LED). • 1 cerebro del robot, control remoto y baterías incluidas. • Caja contenedora y bandeja de almacenamiento incluidas para el almacenamiento organizado de todas las piezas.
B149: Plazos y lugares de entrega
C150: El plazo de entrega no podrá ser superior a los diez (10) días hábiles a partir de la fecha de recepción de la respectiva Orden de Compra en el domicilio especial electrónico constituido, en virtud del método de contratación. La entrega de dichos bienes se realizará en el Ministerio de Ciencia e Innovación Tecnologica, sito en Avenida Belgrano N° 1494 - CAPE- Pabellón N° 26 San Fernando del Valle de Catamarca. Se presentará Remito que deberá cumplimentar lo dispuesto por la R.G. AFIP 1415/03, sin excepción.
B152: Calidad Minima esperada
B154: Mantenimiento: treinta (30) dias corridos
B156: Garantia
C157: Garantía del fabricante minima de un (1) año.
...

Sheet  NotaPedido
A1: NOTA DE PEDIDO | J1: N° | K1: 026/2021
A3: JURISDICCIÓN: | D3: 70 - MINISTERIO DE CIENCIA E INNOVACION TECNOLOGICA
A4: SAF: | D4: 20 - MINISTERIO DE CIENCIA E INNOVACION TECNOLOGICA
A5: UNIDAD EJECUTORA: | D5: SECRETARIA DE INNOVACION TECNOLOGICA
A6: DEPENDENCIA SOLICITANTE: | D6: DIRECCION PROVINCIAL DE GESTION ADMINISTRATIVA RECURSOS HUMANOS
A7: PERIODO UTILIZACIÓN: | D7: 3° TRIMESTRE 2021
A8: OBJETO: | D8: ADQUISICIÓN DE DIVERSOS EQUIPOS DESTINADO A LA SECRETARIA INNOVACIÓN TECNOLOGICA DEPENDIENTE DEL MINISTERIO DE CIENCIA E INNOVACIÓN TECNOLOGICA.-
A10: Ítem | B10: Codigo Item | C10: DESCRIPCIÓN | H10: Adjunta Detalle Técnico | I10: Unidad Medida | J10: Precio Unitario Estimado | K10: Cantidad Solicitada
A12: 1 | B12: 4.3.6-6160.208 | C12: COMPUTADORAS; TIPO: NOTEBOOK, CODIGO ETAP: PC-008, VERSION ETAP: 22.0 | D12: COMPUTADORAS; TIPO: NOTEBOOK, CODIGO ETAP: PC-008, VERSION ETAP: 22.0 | E12: COMPUTADORAS; TIPO: NOTEBOOK, CODIGO ETAP: PC-008, VERSION ETAP: 22.0 | F12: COMPUTADORAS; TIPO: NOTEBOOK, CODIGO ETAP: PC-008, VERSION ETAP: 22.0 | G12: COMPUTADORAS; TIPO: NOTEBOOK, CODIGO ETAP: PC-008, VERSION ETAP: 22.0 | H12: SI | I12: UNIDAD | J12: 125000 | K12: 22
A13: 2 | B13: 4.3.6-6160.221 | C13: COMPUTADORAS; TIPO: DE ESCRITORIO, CODIGO ETAP: PC-002-00, VERSION ETAP: 23.0 | D13: COMPUTADORAS; TIPO: DE ESCRITORIO, CODIGO ETAP: PC-002-00, VERSION ETAP: 23.0 | E13: COMPUTADORAS; TIPO: DE ESCRITORIO, CODIGO ETAP: PC-002-00, VERSION ETAP: 23.0 | F13: COMPUTADORAS; TIPO: DE ESCRITORIO, CODIGO ETAP: PC-002-00, VERSION ETAP: 23.0 | G13: COMPUTADORAS; TIPO: DE ESCRITORIO, CODIGO ETAP: PC-002-00, VERSION ETAP: 23.0 | H13: SI | I13: UNIDAD | J13: 140000 | K13: 5
A14: 3 | B14: 4.3.6-9604.3 | C14: TABLETA PC; RESOLUCION: 1280 X 800 PXL, PANTALLA: 9,4 pulg, MEMORIA: 32 Gb, MEMORIA RAM: 32 Gb | D14: TABLETA PC; RESOLUCION: 1280 X 800 PXL, PANTALLA: 9,4 pulg, MEMORIA: 32 Gb, MEMORIA RAM: 32 Gb | E14: TABLETA PC; RESOLUCION: 1280 X 800 PXL, PANTALLA: 9,4 pulg, MEMORIA: 32 Gb, MEMORIA RAM: 32 Gb | F14: TABLETA PC; RESOLUCION: 1280 X 800 PXL, PANTALLA: 9,4 pulg, MEMORIA: 32 Gb, MEMORIA RAM: 32 Gb | G14: TABLETA PC; RESOLUCION: 1280 X 800 PXL, PANTALLA: 9,4 pulg, MEMORIA: 32 Gb, MEMORIA RAM: 32 Gb | H14: SI | I14: UNIDAD | J14: 40000 | K14: 15
A15: 4 | B15: 4.3.6-9707.20 | C15: IMPRESORA 3D; TIPO: FDM, DIMENSION: 220 X 220 X 260mm, RESOLUCION: SEGÚN PLIEGO, PRECISION: SEGÚN PLIEGO, ESPESOR CAPA: SEGÚN PLIEGO | D15: IMPRESORA 3D; TIPO: FDM, DIMENSION: 220 X 220 X 260mm, RESOLUCION: SEGÚN PLIEGO, PRECISION: SEGÚN PLIEGO, ESPESOR CAPA: SEGÚN PLIEGO | E15: IMPRESORA 3D; TIPO: FDM, DIMENSION: 220 X 220 X 260mm, RESOLUCION: SEGÚN PLIEGO, PRECISION: SEGÚN PLIEGO, ESPESOR CAPA: SEGÚN PLIEGO | F15: IMPRESORA 3D; TIPO: FDM, DIMENSION: 220 X 220 X 260mm, RESOLUCION: SEGÚN PLIEGO, PRECISION: SEGÚN PLIEGO, ESPESOR CAPA: SEGÚN PLIEGO | G15: IMPRESORA 3D; TIPO: FDM, DIMENSION: 220 X 220 X 260mm, RESOLUCION: SEGÚN PLIEGO, PRECISION: SEGÚN PLIEGO, ESPESOR CAPA: SEGÚN PLIEGO | H15: SI | I15: UNIDAD | J15: 150000 | K15: 5
A16: 5 | B16: 4.3.6-9707.21 | C16: IMPRESORA 3D; TIPO: LAPICES 3D, DIMENSION: 17.5 CM x 1.7 CM x 2CM, TEMPERATURA AJUSTABLE: 130-235 GRADOS, MATERIAL DE IMPRESION: ABS Y PLA, VOLTAJE: DC 5V 2A 10W | D16: IMPRESORA 3D; TIPO: LAPICES 3D, DIMENSION: 17.5 CM x 1.7 CM x 2CM, TEMPERATURA AJUSTABLE: 130-235 GRADOS, MATERIAL DE IMPRESION: ABS Y PLA, VOLTAJE: DC 5V 2A 10W | E16: IMPRESORA 3D; TIPO: LAPICES 3D, DIMENSION: 17.5 CM x 1.7 CM x 2CM, TEMPERATURA AJUSTABLE: 130-235 GRADOS, MATERIAL DE IMPRESION: ABS Y PLA, VOLTAJE: DC 5V 2A 10W | F16: IMPRESORA 3D; TIPO: LAPICES 3D, DIMENSION: 17.5 CM x 1.7 CM x 2CM, TEMPERATURA AJUSTABLE: 130-235 GRADOS, MATERIAL DE IMPRESION: ABS Y PLA, VOLTAJE: DC 5V 2A 10W | G16: IMPRESORA 3D; TIPO: LAPICES 3D, DIMENSION: 17.5 CM x 1.7 CM x 2CM, TEMPERATURA AJUSTABLE: 130-235 GRADOS, MATERIAL DE IMPRESION: ABS Y PLA, VOLTAJE: DC 5V 2A 10W | H16: SI | I16: UNIDAD | J16: 6000 | K16: 10
A17: 6 | B17: 4.3.5-1615.69 | C17: PROYECTORES; PANTALLA: SIN, RESOLUCION: 800 X 600 SVGA, LENTE: FIJO ZOOM | D17: PROYECTORES; PANTALLA: SIN, RESOLUCION: 800 X 600 SVGA, LENTE: FIJO ZOOM | E17: PROYECTORES; PANTALLA: SIN, RESOLUCION: 800 X 600 SVGA, LENTE: FIJO ZOOM | F17: PROYECTORES; PANTALLA: SIN, RESOLUCION: 800 X 600 SVGA, LENTE: FIJO ZOOM | G17: PROYECTORES; PANTALLA: SIN, RESOLUCION: 800 X 600 SVGA, LENTE: FIJO ZOOM | H17: SI | I17: UNIDAD | J17: 77000 | K17: 4
A18: 7 | B18: 4.3.5-9163.80 | C18: EQUIPOS DIDACTICOS TECNICOS; NOMBRE: LENTES, TIPO: REALIDAD VIRTUAL | D18: EQUIPOS DIDACTICOS TECNICOS; NOMBRE: LENTES, TIPO: REALIDAD VIRTUAL | E18: EQUIPOS DIDACTICOS TECNICOS; NOMBRE: LENTES, TIPO: REALIDAD VIRTUAL | F18: EQUIPOS DIDACTICOS TECNICOS; NOMBRE: LENTES, TIPO: REALIDAD VIRTUAL | G18: EQUIPOS DIDACTICOS TECNICOS; NOMBRE: LENTES, TIPO: REALIDAD VIRTUAL | H18: SI | I18: UNIDAD | J18: 187000 | K18: 5
A19: 8 | B19: 4.3.5-9163.90 | C19: EQUIPOS DIDACTICOS TECNICOS; NOMBRE: KIT EXPERIMENTAL , TIPO: SEGÚN PLIEGO | D19: EQUIPOS DIDACTICOS TECNICOS; NOMBRE: KIT EXPERIMENTAL , TIPO: SEGÚN PLIEGO | E19: EQUIPOS DIDACTICOS TECNICOS; NOMBRE: KIT EXPERIMENTAL , TIPO: SEGÚN PLIEGO | F19: EQUIPOS DIDACTICOS TECNICOS; NOMBRE: KIT EXPERIMENTAL , TIPO: SEGÚN PLIEGO | G19: EQUIPOS DIDACTICOS TECNICOS; NOMBRE: KIT EXPERIMENTAL , TIPO: SEGÚN PLIEGO | H19: SI | I19: UNIDAD | J19: 190000 | K19: 10
A20: 9 | B20: 4.3.5-9163.90 | C20: EQUIPOS DIDACTICOS TECNICOS; NOMBRE: KIT EXPERIMENTAL , TIPO: SEGÚN PLIEGO | D20: EQUIPOS DIDACTICOS TECNICOS; NOMBRE: KIT EXPERIMENTAL , TIPO: SEGÚN PLIEGO | E20: EQUIPOS DIDACTICOS TECNICOS; NOMBRE: KIT EXPERIMENTAL , TIPO: SEGÚN PLIEGO | F20: EQUIPOS DIDACTICOS TECNICOS; NOMBRE: KIT EXPERIMENTAL , TIPO: SEGÚN PLIEGO | G20: EQUIPOS DIDACTICOS TECNICOS; NOMBRE: KIT EXPERIMENTAL , TIPO: SEGÚN PLIEGO | H20: SI | I20: UNIDAD | J20: 310000 | K20: 4
A21: 10 | B21: 4.3.5-9163.90 | C21: EQUIPOS DIDACTICOS TECNICOS; NOMBRE: KIT EXPERIMENTAL , TIPO: SEGÚN PLIEGO | D21: EQUIPOS DIDACTICOS TECNICOS; NOMBRE: KIT EXPERIMENTAL , TIPO: SEGÚN PLIEGO | E21: EQUIPOS DIDACTICOS TECNICOS; NOMBRE: KIT EXPERIMENTAL , TIPO: SEGÚN PLIEGO | F21: EQUIPOS DIDACTICOS TECNICOS; NOMBRE: KIT EXPERIMENTAL , TIPO: SEGÚN PLIEGO | G21: EQUIPOS DIDACTICOS TECNICOS; NOMBRE: KIT EXPERIMENTAL , TIPO: SEGÚN PLIEGO | H21: SI | I21: UNIDAD | J21: 60000 | K21: 10
A22: 11 | B22: 4.3.5-9163.90 | C22: EQUIPOS DIDACTICOS TECNICOS; NOMBRE: KIT EXPERIMENTAL , TIPO: SEGÚN PLIEGO | D22: EQUIPOS DIDACTICOS TECNICOS; NOMBRE: KIT EXPERIMENTAL , TIPO: SEGÚN PLIEGO | E22: EQUIPOS DIDACTICOS TECNICOS; NOMBRE: KIT EXPERIMENTAL , TIPO: SEGÚN PLIEGO | F22: EQUIPOS DIDACTICOS TECNICOS; NOMBRE: KIT EXPERIMENTAL , TIPO: SEGÚN PLIEGO | G22: EQUIPOS DIDACTICOS TECNICOS; NOMBRE: KIT EXPERIMENTAL , TIPO: SEGÚN PLIEGO | H22: SI | I22: UNIDAD | J22: 16000 | K22: 20
A23: 12 | B23: 4.3.5-9163.90 | C23: EQUIPOS DIDACTICOS TECNICOS; NOMBRE: KIT EXPERIMENTAL , TIPO: SEGÚN PLIEGO | D23: EQUIPOS DIDACTICOS TECNICOS; NOMBRE: KIT EXPERIMENTAL , TIPO: SEGÚN PLIEGO | E23: EQUIPOS DIDACTICOS TECNICOS; NOMBRE: KIT EXPERIMENTAL , TIPO: SEGÚN PLIEGO | F23: EQUIPOS DIDACTICOS TECNICOS; NOMBRE: KIT EXPERIMENTAL , TIPO: SEGÚN PLIEGO | G23: EQUIPOS DIDACTICOS TECNICOS; NOMBRE: KIT EXPERIMENTAL , TIPO: SEGÚN PLIEGO | H23: SI | I23: UNIDAD | J23: 15000 | K23: 10
... A31: 20 | B31: 2.9.3-6368.12 | C31: CONTROLADORES DE PROCESO; TIPO: MODULO DE EXPANSION, SALIDA: SIN, FORMATO: MODULAR, ALIMENTACION: 24 VCC, INDICADOR: A LED, TIPO DE ENTRADA: DISCRETA | D31: CONTROLADORES DE PROCESO; TIPO: MODULO DE EXPANSION, SALIDA: SIN, FORMATO: MODULAR, ALIMENTACION: 24 VCC, INDICADOR: A LED, TIPO DE ENTRADA: DISCRETA | E31: CONTROLADORES DE PROCESO; TIPO: MODULO DE EXPANSION, SALIDA: SIN, FORMATO: MODULAR, ALIMENTACION: 24 VCC, INDICADOR: A LED, TIPO DE ENTRADA: DISCRETA | F31: CONTROLADORES DE PROCESO; TIPO: MODULO DE EXPANSION, SALIDA: SIN, FORMATO: MODULAR, ALIMENTACION: 24 VCC, INDICADOR: A LED, TIPO DE ENTRADA: DISCRETA | G31: CONTROLADORES DE PROCESO; TIPO: MODULO DE EXPANSION, SALIDA: SIN, FORMATO: MODULAR, ALIMENTACION: 24 VCC, INDICADOR: A LED, TIPO DE ENTRADA: DISCRETA | H31: SI | I31: UNIDAD | J31: 3200 | K31: 5
A32: Costo total estimado: PESOS DOCE MILLONES TRESCIENTOS SETENTA Y DOS MIL CON 00/100.- | J32: =SUMPRODUCT(J12:J31,K12:K31) -> 12372000

Sheet Autor Gastar
A1: EJERCICIO: | D1: 2021 | P1: AUTORIZACION PARA GASTAR
A4: JURISDICCIÓN: | G4: =' NotaPedido'!D3 -> 70 - MINISTERIO DE CIENCIA E INNOVACION TECNOLOGICA
A5: SAF: | G5: =' NotaPedido'!D4 -> 20 - MINISTERIO DE CIENCIA E INNOVACION TECNOLOGICA
A6: UNIDAD EJECUTORA: | G6: =' NotaPedido'!D5 -> SECRETARIA DE INNOVACION TECNOLOGICA
A7: DEPENDENCIA SOLICITANTE: | G7: =' NotaPedido'!D6 -> DIRECCION PROVINCIAL DE GESTION ADMINISTRATIVA RECURSOS HUMANOS
A8: AUTORIZACIÓN:
A9: Señor Jefe de Servicio Administrativo Financiero:
A10: ="Autorizo la realización de los trámites correspondientes, a fin de proveer a este Organismo los bienes y/o servicios que se detallan en Nota de Pedido N° " & ' NotaPedido'!K1&", afectando la erogación resultante a los créditos presupuestarios aprobados a favor de esta Unidad Ejecutora, conforme al siguiente detalle:" -> Autorizo la realización de los trámites correspondientes, a fin de proveer a este Organismo los bienes y/o servicios que se detallan en Nota de Pedido N° 026/2021, afectando la erogación resultante a los créditos presupuestarios aprobados a favor de esta Unidad Ejecutora, conforme al siguiente detalle:
A12: IMPUTACIÓN PRESUPUESTARIA
A13: CÓDIGO | O13: DENOMINACIÓN DE LA PARTIDA PRESUPUESTARIA | Q13: IMPORTE
A14: PR | B14: SB | C14: PY | D14: AC | E14: OB | F14: UG | G14: FIN | H14: FUN | I14: I | J14: P | K14: P | L14: SubP | M14: M | N14: FF
A15: 3 | B15: 0 | C15: 0 | D15: 1 | E15: 0 | F15: 4901 | G15: 3 | H15: 5 | I15: 4 | J15: 3 | K15: 6 | L15: 0 | M15: 1 | N15: 1.1 | O15: Equipos para Computación | Q15: 4860000
A16: 3 | B16: 0 | C16: 0 | D16: 1 | E16: 0 | F16: 4901 | G16: 3 | H16: 5 | I16: 4 | J16: 3 | K16: 5 | L16: 0 | M16: 1 | N16: 1.1 | O16: Equipo Educacional y Recreativo | Q16: 7176000
A17: 3 | B17: 0 | C17: 0 | D17: 1 | E17: 0 | F17: 4901 | G17: 3 | H17: 5 | I17: 4 | J17: 3 | K17: 2 | L17: 0 | M17: 1 | N17: 1.1 | O17: Equipo de Transporte, Tracción y Elevación | Q17: 255000
A18: 3 | B18: 0 | C18: 0 | D18: 1 | E18: 0 | F18: 4901 | G18: 3 | H18: 5 | I18: 4 | J18: 3 | K18: 9 | L18: 0 | M18: 1 | N18: 1.1 | O18: Equipos Varios | Q18: 65000
A19: 3 | B19: 0 | C19: 0 | D19: 1 | E19: 0 | F19: 4901 | G19: 3 | H19: 5 | I19: 2 | J19: 9 | K19: 3 | L19: 0 | M19: 1 | N19: 1.1 | O19: Útiles y Materiales eléctricos | Q19: 16000
A23: PESOS: DOCE MILLONES TRESCIENTOS SETENTA Y DOS MIL CON 00/100.- | Q23: =SUM(Q15:Q22) -> 12372000
A25: JUSTIFICACIÓN:
A26: ADQUISICIÓN DE DIVERSOS EQUIPOS DESTINADO A LA SECRETARIA INNOVACIÓN TECNOLOGICA DEPENDIENTE DEL MINISTERIO DE CIENCIA E INNOVACIÓN TECNOLOGICA.-

Sheet Nota de Pedido
A1: NOTA DE PEDIDO | J1: N° | K1: 025/2021
A3: JURISDICCIÓN: | D3: 70 - MINISTERIO DE CIENCIA E INNOVACION TECNOLOGICA
A4: SAF: | D4: 20 - MINISTERIO DE CIENCIA E INNOVACION TECNOLOGICA
A5: UNIDAD EJECUTORA: | D5: SECRETARIA DE CIENCIA Y TECNOLOGIA
A6: DEPENDENCIA SOLICITANTE: | D6: DIRECCION PROVINCIAL DE GESTION ADMINISTRATIVA RECURSOS HUMANOS
A7: PERIODO UTILIZACIÓN: | D7: 3° TRIMESTRE 2021
A8: OBJETO: | D8: ADQUISICIÓN DE DIVERSOS EQUIPOS DESTINADO A LA SECRETARIA DE CIENCIA Y TECNNOLOGIA DEPENDIENTE DEL MINISTERIO DE CIENCIA E INNOVACIÓN TECNOLOGICA.-
A10: Ítem | B10: Codigo Item | C10: DESCRIPCIÓN | H10: Adjunta Detalle Técnico | I10: Unidad Medida | J10: Precio Unitario Estimado | K10: Cantidad Solicitada
A12: 1 | B12: 4.3.6-6160.221 | C12: COMPUTADORAS; TIPO: DE ESCRITORIO, CODIGO ETAP: PC-002-00, VERSION ETAP: 23.0 | D12: COMPUTADORAS; TIPO: DE ESCRITORIO, CODIGO ETAP: PC-002-00, VERSION ETAP: 23.0 | E12: COMPUTADORAS; TIPO: DE ESCRITORIO, CODIGO ETAP: PC-002-00, VERSION ETAP: 23.0 | F12: COMPUTADORAS; TIPO: DE ESCRITORIO, CODIGO ETAP: PC-002-00, VERSION ETAP: 23.0 | G12: COMPUTADORAS; TIPO: DE ESCRITORIO, CODIGO ETAP: PC-002-00, VERSION ETAP: 23.0 | H12: SI | I12: UNIDAD | J12: 140000 | K12: 3
A13: 2 | B13: 4.3.6-9707.20 | C13: IMPRESORA 3D; TIPO: FDM, DIMENSION: 220 X 220 X 260mm, RESOLUCION: SEGÚN PLIEGO, PRECISION: SEGÚN PLIEGO, ESPESOR CAPA: SEGÚN PLIEGO | D13: IMPRESORA 3D; TIPO: FDM, DIMENSION: 220 X 220 X 260mm, RESOLUCION: SEGÚN PLIEGO, PRECISION: SEGÚN PLIEGO, ESPESOR CAPA: SEGÚN PLIEGO | E13: IMPRESORA 3D; TIPO: FDM, DIMENSION: 220 X 220 X 260mm, RESOLUCION: SEGÚN PLIEGO, PRECISION: SEGÚN PLIEGO, ESPESOR CAPA: SEGÚN PLIEGO | F13: IMPRESORA 3D; TIPO: FDM, DIMENSION: 220 X 220 X 260mm, RESOLUCION: SEGÚN PLIEGO, PRECISION: SEGÚN PLIEGO, ESPESOR CAPA: SEGÚN PLIEGO | G13: IMPRESORA 3D; TIPO: FDM, DIMENSION: 220 X 220 X 260mm, RESOLUCION: SEGÚN PLIEGO, PRECISION: SEGÚN PLIEGO, ESPESOR CAPA: SEGÚN PLIEGO | H13: SI | I13: UNIDAD | J13: 150000 | K13: 8
A14: 3 | B14: 4.3.5-1615.69 | C14: PROYECTORES; PANTALLA: SIN, RESOLUCION: 800 X 600 SVGA, LENTE: FIJO ZOOM | D14: PROYECTORES; PANTALLA: SIN, RESOLUCION: 800 X 600 SVGA, LENTE: FIJO ZOOM | E14: PROYECTORES; PANTALLA: SIN, RESOLUCION: 800 X 600 SVGA, LENTE: FIJO ZOOM | F14: PROYECTORES; PANTALLA: SIN, RESOLUCION: 800 X 600 SVGA, LENTE: FIJO ZOOM | G14: PROYECTORES; PANTALLA: SIN, RESOLUCION: 800 X 600 SVGA, LENTE: FIJO ZOOM | H14: SI | I14: UNIDAD | J14: 77000 | K14: 4
A15: 4 | B15: 4.3.5-9163.80 | C15: EQUIPOS DIDACTICOS TECNICOS; NOMBRE: LENTES, TIPO: REALIDAD VIRTUAL | D15: EQUIPOS DIDACTICOS TECNICOS; NOMBRE: LENTES, TIPO: REALIDAD VIRTUAL | E15: EQUIPOS DIDACTICOS TECNICOS; NOMBRE: LENTES, TIPO: REALIDAD VIRTUAL | F15: EQUIPOS DIDACTICOS TECNICOS; NOMBRE: LENTES, TIPO: REALIDAD VIRTUAL | G15: EQUIPOS DIDACTICOS TECNICOS; NOMBRE: LENTES, TIPO: REALIDAD VIRTUAL | H15: SI | I15: UNIDAD | J15: 187000 | K15: 5
A16: 5 | B16: 4.3.5-9163.90 | C16: EQUIPOS DIDACTICOS TECNICOS; NOMBRE: KIT EXPERIMENTAL , TIPO: SEGÚN PLIEGO | D16: EQUIPOS DIDACTICOS TECNICOS; NOMBRE: KIT EXPERIMENTAL , TIPO: SEGÚN PLIEGO | E16: EQUIPOS DIDACTICOS TECNICOS; NOMBRE: KIT EXPERIMENTAL , TIPO: SEGÚN PLIEGO | F16: EQUIPOS DIDACTICOS TECNICOS; NOMBRE: KIT EXPERIMENTAL , TIPO: SEGÚN PLIEGO | G16: EQUIPOS DIDACTICOS TECNICOS; NOMBRE: KIT EXPERIMENTAL , TIPO: SEGÚN PLIEGO | H16: SI | I16: UNIDAD | J16: 60000 | K16: 10
A17: 6 | B17: 4.3.5-9163.90 | C17: EQUIPOS DIDACTICOS TECNICOS; NOMBRE: KIT EXPERIMENTAL , TIPO: SEGÚN PLIEGO | D17: EQUIPOS DIDACTICOS TECNICOS; NOMBRE: KIT EXPERIMENTAL , TIPO: SEGÚN PLIEGO | E17: EQUIPOS DIDACTICOS TECNICOS; NOMBRE: KIT EXPERIMENTAL , TIPO: SEGÚN PLIEGO | F17: EQUIPOS DIDACTICOS TECNICOS; NOMBRE: KIT EXPERIMENTAL , TIPO: SEGÚN PLIEGO | G17: EQUIPOS DIDACTICOS TECNICOS; NOMBRE: KIT EXPERIMENTAL , TIPO: SEGÚN PLIEGO | H17: SI | I17: UNIDAD | J17: 16000 | K17: 10
A18: 7 | B18: 4.3.5-9163.90 | C18: EQUIPOS DIDACTICOS TECNICOS; NOMBRE: KIT EXPERIMENTAL , TIPO: SEGÚN PLIEGO | D18: EQUIPOS DIDACTICOS TECNICOS; NOMBRE: KIT EXPERIMENTAL , TIPO: SEGÚN PLIEGO | E18: EQUIPOS DIDACTICOS TECNICOS; NOMBRE: KIT EXPERIMENTAL , TIPO: SEGÚN PLIEGO | F18: EQUIPOS DIDACTICOS TECNICOS; NOMBRE: KIT EXPERIMENTAL , TIPO: SEGÚN PLIEGO | G18: EQUIPOS DIDACTICOS TECNICOS; NOMBRE: KIT EXPERIMENTAL , TIPO: SEGÚN PLIEGO | H18: SI | I18: UNIDAD | J18: 15000 | K18: 50
A19: 8 | B19: 4.3.5-9163.90 | C19: EQUIPOS DIDACTICOS TECNICOS; NOMBRE: KIT EXPERIMENTAL , TIPO: SEGÚN PLIEGO | D19: EQUIPOS DIDACTICOS TECNICOS; NOMBRE: KIT EXPERIMENTAL , TIPO: SEGÚN PLIEGO | E19: EQUIPOS DIDACTICOS TECNICOS; NOMBRE: KIT EXPERIMENTAL , TIPO: SEGÚN PLIEGO | F19: EQUIPOS DIDACTICOS TECNICOS; NOMBRE: KIT EXPERIMENTAL , TIPO: SEGÚN PLIEGO | G19: EQUIPOS DIDACTICOS TECNICOS; NOMBRE: KIT EXPERIMENTAL , TIPO: SEGÚN PLIEGO | H19: SI | I19: UNIDAD | J19: 61000 | K19: 20
A20: 9 | B20: 4.3.5-9163.64 | C20: EQUIPOS DIDACTICOS TECNICOS; NOMBRE: SISTEMA DE SONIDO, TIPO: ESTEREO | D20: EQUIPOS DIDACTICOS TECNICOS; NOMBRE: SISTEMA DE SONIDO, TIPO: ESTEREO | E20: EQUIPOS DIDACTICOS TECNICOS; NOMBRE: SISTEMA DE SONIDO, TIPO: ESTEREO | F20: EQUIPOS DIDACTICOS TECNICOS; NOMBRE: SISTEMA DE SONIDO, TIPO: ESTEREO | G20: EQUIPOS DIDACTICOS TECNICOS; NOMBRE: SISTEMA DE SONIDO, TIPO: ESTEREO | H20: SI | I20: UNIDAD | J20: 130000 | K20: 2
A21: 10 | B21: 4.3.5-9138.2 | C21: PIZARRAS INTERACTIVAS; DIMENSION: 170 X 120 X 12 Cm, SOFTWARE: SMART BOARD, RESOLUCION: 6000 X 6000 | D21: PIZARRAS INTERACTIVAS; DIMENSION: 170 X 120 X 12 Cm, SOFTWARE: SMART BOARD, RESOLUCION: 6000 X 6000 | E21: PIZARRAS INTERACTIVAS; DIMENSION: 170 X 120 X 12 Cm, SOFTWARE: SMART BOARD, RESOLUCION: 6000 X 6000 | F21: PIZARRAS INTERACTIVAS; DIMENSION: 170 X 120 X 12 Cm, SOFTWARE: SMART BOARD, RESOLUCION: 6000 X 6000 | G21: PIZARRAS INTERACTIVAS; DIMENSION: 170 X 120 X 12 Cm, SOFTWARE: SMART BOARD, RESOLUCION: 6000 X 6000 | H21: SI | I21: UNIDAD | J21: 95000 | K21: 3
A22: 11 | B22: 4.3.5-5563.16 | C22: PIZARRONES; MATERIAL: LAMINADO PLASTICO, TAMAÑO: 200 X 120 Cm, SOPORTE: SOBRE PARED, DIMENSION PLANO: 200 X 120 Cm | D22: PIZARRONES; MATERIAL: LAMINADO PLASTICO, TAMAÑO: 200 X 120 Cm, SOPORTE: SOBRE PARED, DIMENSION PLANO: 200 X 120 Cm | E22: PIZARRONES; MATERIAL: LAMINADO PLASTICO, TAMAÑO: 200 X 120 Cm, SOPORTE: SOBRE PARED, DIMENSION PLANO: 200 X 120 Cm | F22: PIZARRONES; MATERIAL: LAMINADO PLASTICO, TAMAÑO: 200 X 120 Cm, SOPORTE: SOBRE PARED, DIMENSION PLANO: 200 X 120 Cm | G22: PIZARRONES; MATERIAL: LAMINADO PLASTICO, TAMAÑO: 200 X 120 Cm, SOPORTE: SOBRE PARED, DIMENSION PLANO: 200 X 120 Cm | H22: SI | I22: UNIDAD | J22: 6000 | K22: 4
A23: 12 | B23: 2.9.3-6368.12 | C23: CONTROLADORES DE PROCESO; TIPO: MODULO DE EXPANSION, SALIDA: SIN, FORMATO: MODULAR, ALIMENTACION: 24 VCC, INDICADOR: A LED, TIPO DE ENTRADA: DISCRETA | D23: CONTROLADORES DE PROCESO; TIPO: MODULO DE EXPANSION, SALIDA: SIN, FORMATO: MODULAR, ALIMENTACION: 24 VCC, INDICADOR: A LED, TIPO DE ENTRADA: DISCRETA | E23: CONTROLADORES DE PROCESO; TIPO: MODULO DE EXPANSION, SALIDA: SIN, FORMATO: MODULAR, ALIMENTACION: 24 VCC, INDICADOR: A LED, TIPO DE ENTRADA: DISCRETA | F23: CONTROLADORES DE PROCESO; TIPO: MODULO DE EXPANSION, SALIDA: SIN, FORMATO: MODULAR, ALIMENTACION: 24 VCC, INDICADOR: A LED, TIPO DE ENTRADA: DISCRETA | G23: CONTROLADORES DE PROCESO; TIPO: MODULO DE EXPANSION, SALIDA: SIN, FORMATO: MODULAR, ALIMENTACION: 24 VCC, INDICADOR: A LED, TIPO DE ENTRADA: DISCRETA | H23: SI | I23: UNIDAD | J23: 3200 | K23: 25
A24: Costo total estimado: PESOS SEIS MILLONES DOSCIENTOS CUARENTA Y DOS MIL CON 00/100.- | J24: =SUMPRODUCT(J12:J23,K12:K23) -> 6242000

Sheet Autor Gastar 
A1: EJERCICIO: | D1: 2021 | P1: AUTORIZACION PARA GASTAR
A4: JURISDICCIÓN: | G4: =' NotaPedido'!D3 -> 70 - MINISTERIO DE CIENCIA E INNOVACION TECNOLOGICA
A5: SAF: | G5: =' NotaPedido'!D4 -> 20 - MINISTERIO DE CIENCIA E INNOVACION TECNOLOGICA
A6: UNIDAD EJECUTORA: | G6: SECRETARIA DE CIENCIA Y TECNOLOGIA
A7: DEPENDENCIA SOLICITANTE: | G7: =' NotaPedido'!D6 -> DIRECCION PROVINCIAL DE GESTION ADMINISTRATIVA RECURSOS HUMANOS
A8: AUTORIZACIÓN:
A9: Señor Jefe de Servicio Administrativo Financiero:
A10: Autorizo la realización de los trámites correspondientes, a fin de proveer a este Organismo los bienes y/o servicios que se detallan en Nota de Pedido N° 25/2021, afectando la erogación resultante a los créditos presupuestarios aprobados a favor de esta Unidad Ejecutora, conforme al siguiente detalle:
A12: IMPUTACIÓN PRESUPUESTARIA
A13: CÓDIGO | O13: DENOMINACIÓN DE LA PARTIDA PRESUPUESTARIA | Q13: IMPORTE
A14: PR | B14: SB | C14: PY | D14: AC | E14: OB | F14: UG | G14: FIN | H14: FUN | I14: I | J14: P | K14: P | L14: SubP | M14: M | N14: FF
A15: 2 | B15: 0 | C15: 0 | D15: 1 | E15: 0 | F15: 4901 | G15: 3 | H15: 5 | I15: 4 | J15: 3 | K15: 6 | L15: 0 | M15: 1 | N15: 1.1 | O15: Equipos para Computación | Q15: 1620000
A16: 2 | B16: 0 | C16: 0 | D16: 1 | E16: 0 | F16: 4901 | G16: 3 | H16: 5 | I16: 4 | J16: 3 | K16: 5 | L16: 0 | M16: 1 | N16: 1.1 | O16: Equipo Educacional y Recreativo | Q16: 4542000
A17: 2 | B17: 0 | C17: 0 | D17: 1 | E17: 0 | F17: 4901 | G17: 3 | H17: 5 | I17: 2 | J17: 9 | K17: 3 | L17: 0 | M17: 1 | N17: 1.1 | O17: Útiles y Materiales eléctricos | Q17: 80000
A21: PESOS: SEIS MILLONES DOSCIENTOS CUARENTA Y DOS MIL CON 00/100.- | Q21: =SUM(Q15:Q20) -> 6242000
A23: JUSTIFICACIÓN:
A24: ADQUISICIÓN DE DIVERSOS EQUIPOS DESTINADO A LA SECRETARIA SECRETARIA DE CIENCIA Y TECNOLOGIA DEPENDIENTE DEL MINISTERIO DE CIENCIA E INNOVACIÓN TECNOLOGICA.-
