Workbook

Sheet Necesidades Trimestrales
B2: Pedido de Necesidades Trimestrales
A4: JURISDICCION: | C4: 45- Ministerio de Desarrollo Social y Deporte
A5: SAF N°: | C5: 25- Direccion Provincial de Gestion Administrativa y RRHH
A6: EJERCICIO: | C6: 2021
A7: TRIMESTRE: | C7: 4
A9: ID | B9: CODIGO ITEM | C9: RUBRO DE COMPRA | D9: I.P.P. | E9: DESCRIPCION | F9: UNIDAD DE MEDIDA | G9: CANTIDAD | H9: PRECIO UNITARIO ESTIMADO | I9: IMPORTE TOTAL ESTIMADO
A10: 1 | B10: 2.1.1-478.65 | C10: ALIMENTOS | D10: 2.1.1 | E10: AGUA MINERAL; TIPO: SIN GAS BAJA EN SODIO, PRESENTACION: ENVASE X 20 L, MATERIAL ENVASE: PLASTICO 1-PET, TIPO ENVASE: RETORNABLE, ELEM. TRANSPORTE: SIN, MATERIAL ELEM. TRANSPORTE: SIN | F10: UNIDADES | G10: 8736 | H10: 400.64 | I10: =+H10*G10 -> 3499991
B18: Especificidades Item N° 1:
B20: Descripción técnica
C21: SE UTILIZARAN 728 BIDONES POR SEMANA, DURANTE TRES MESES. LOS MISMOS DEBERIAN INCLUIR 104 DISPENSER, REPARTIDOS EN LAS DISTINTAS DEPDENCIAS DEL MINISTERIO DE DESARROLLO SOCIAL Y DEPORTE. DEBERAN SER DE AGUA FRIA Y CALIENTE, INCLUYENDO EL MANTENIMIENTO DE LOS MISMOS, HASTA 15 DIAS POSTERIORES A LA ULTIMA ENTREGA DE BIDONES. EL Oferente debe contar con las maquinarias de proceso y acreditar los controles exigidos por el Codigo Alimentario de la Actividad ; la Certificacion de Laboratorio de Analisis Bacteriologico y Certificacion de Analisis Fisico-Quimico Vigentes.-
B22: Plazos y lugares de entrega
C23: Plazo de Entrega: Semanal y pago Mensual.-
C24: Lugar y Forma de Entrega: DE MANERA SEMANAL, Durante 3 meses se Entregara bidones en las distintas dependencias del Ministerio de Desarrollo Social y Deporte (SEGUN ANEXO I), libre de flete, acarreo y Embalaje, y libre de cualquier riesgo de perdida o destruccion total o parcial por causas ajenas a la instalacion.
B25: Calidad Minima esperada
C26: Alta
B27: Mantenimiento
C28: Plazo de Mantinimiento 60 dias
B29: Garantia

Sheet ANEXO I
A2: ANEXO I (LUGAR Y ENTREGA)
A4: DEPENDENCIA | B4: DOMICILIO | C4: CANTIDAD DISPENSER POR DEPENDENCIA | D4: ENTREGA SEMANAL | E4: ENTREGA MENSUAL | F4: ENTREGA TRIMESTRAL
A5: OFICINA MINISTRO | B5: AV. REPUBLICA DE VENEZUELA – CAPE – PAB. 25 | C5: 1 | D5: 7 | E5: =+D5*4 -> 28 | F5: =+E5*3 -> 84
A6: SECRETARIA PRIVADA MINISTRO | B6: AV. REPUBLICA DE VENEZUELA – CAPE – PAB. 25 | C6: 1 | D6: 7 | E6: =+D6*4 -> 28 | F6: =+E6*3 -> 84
A7: SECRETARIA DE GESTION ADMINISTRATIVA Y RR.HH. | B7: AV. REPUBLICA DE VENEZUELA – CAPE – PAB. 25 | C7: 1 | D7: 7 | E7: =+D7*4 -> 28 | F7: =+E7*3 -> 84
A8: DIRECCION DE DESPACHO | B8: AV. REPUBLICA DE VENEZUELA – CAPE – PAB. 25 | C8: 1 | D8: 7 | E8: =+D8*4 -> 28 | F8: =+E8*3 -> 84
A9: DIRECCION PROVINCIAL DE GESTION ADMINISTRATIVA Y RR.HH | B9: AV. REPUBLICA DE VENEZUELA – CAPE – PAB. 25 | C9: 1 | D9: 7 | E9: =+D9*4 -> 28 | F9: =+E9*3 -> 84
A10: DIVISION CONTABLE | B10: AV. REPUBLICA DE VENEZUELA – CAPE – PAB. 25 | C10: 1 | D10: 7 | E10: =+D10*4 -> 28 | F10: =+E10*3 -> 84
A11: DIRECCION CONTABLE | B11: AV. REPUBLICA DE VENEZUELA – CAPE – PAB. 25 | C11: 1 | D11: 7 | E11: =+D11*4 -> 28 | F11: =+E11*3 -> 84
A12: DIVSION TESORERIA | B12: AV. REPUBLICA DE VENEZUELA – CAPE – PAB. 25 | C12: 3 | D12: 21 | E12: =+D12*4 -> 84 | F12: =+E12*3 -> 252
A13: DIVISION LICITACIONES COMPRAS Y PATRIMONIO | B13: AV. REPUBLICA DE VENEZUELA – CAPE – PAB. 25 | C13: 2 | D13: 14 | E13: =+D13*4 -> 56 | F13: =+E13*3 -> 168
A14: DIRECCION PROVINCIAL DE AUDITORIA INTERNA | B14: AV. REPUBLICA DE VENEZUELA – CAPE – PAB. 25 | C14: 1 | D14: 7 | E14: =+D14*4 -> 28 | F14: =+E14*3 -> 84
A15: DIVISION PERSONAL | B15: AV. REPUBLICA DE VENEZUELA – CAPE – PAB. 25 | C15: 1 | D15: 7 | E15: =+D15*4 -> 28 | F15: =+E15*3 -> 84
A16: ASESORIAL LEGAL | B16: AV. REPUBLICA DE VENEZUELA – CAPE – PAB. 25 | C16: 3 | D16: 21 | E16: =+D16*4 -> 84 | F16: =+E16*3 -> 252
... A59: ESTADIO PROVINCIAL BINCENTENARIO | B59: PARAGUAY 1812 - FRENTE PREDIO FERIAL | C59: 5 | D59: 35 | E59: =+D59*4 -> 140 | F59: =+E59*3 -> 420
A60: TOTALES | C60: =SUM(C5:C59) -> 104 | D60: =SUM(D5:D59) -> 728 | E60: =SUM(E5:E59) -> 2912 | F60: =SUM(F5:F59) -> 8736

Sheet  NotaPedido
A1: NOTA DE PEDIDO | J1: N° | K1: 724/2021
A3: JURISDICCIÓN: | D3: ='Necesidades Trimestrales'!C4 -> 45- Ministerio de Desarrollo Social y Deporte
A4: SAF: | D4: ='Necesidades Trimestrales'!C5 -> 25- Direccion Provincial de Gestion Administrativa y RRHH
A5: UNIDAD EJECUTORA: | D5: 01- Ministerio de Desarrollo Social y Deporte
A6: DEPENDENCIA SOLICITANTE: | D6: 01- Actividad Central
A7: PERIODO UTILIZACIÓN: | D7: ='Necesidades Trimestrales'!C7 & "° Trimestre - Año " & 'Necesidades Trimestrales'!C6 -> 4° Trimestre - Año 2021
A8: OBJETO: | D8: Adquisición de Bidones de 20Lts de Agua Mineral que seran destinadas a las distintas dependencias del Ministerio de Desarrollo Social y Deporte.
A10: Ítem | B10: Codigo Item | C10: DESCRIPCIÓN | H10: Adjunta Detalle Técnico | I10: Unidad Medida | J10: Precio Unitario Estimado | K10: Cantidad Solicitada
A12: 1 | B12: ='Necesidades Trimestrales'!B10 -> 2.1.1-478.65 | C12: ='Necesidades Trimestrales'!E10 -> AGUA MINERAL; TIPO: SIN GAS BAJA EN SODIO, PRESENTACION: ENVASE X 20 L, MATERIAL ENVASE: PLASTICO 1-PET, TIPO ENVASE: RETORNABLE, ELEM. TRANSPORTE: SIN, MATERIAL ELEM. TRANSPORTE: SIN | H12: SI | I12: ='Necesidades Trimestrales'!F10 -> UNIDADES | J12: 400.64 | K12: =+'Necesidades Trimestrales'!G10 -> 8736
A13: 2
A14: 3
A18: Costo total estimado: TRES MILLONES CUATROCIENTOS NOVENTA Y NUEVE MIL NOVECIENTROS NOVENTA Y UNO CON 04/100.- | J18: =+J12*K12 -> 3499991

Sheet Autor Gastar
A1: EJERCICIO: | D1: ='Necesidades Trimestrales'!C6 -> 2021 | P1: AUTORIZACION PARA GASTAR
A4: JURISDICCIÓN: | G4: =' NotaPedido'!D3 -> 45- Ministerio de Desarrollo Social y Deporte
A5: SAF: | G5: =' NotaPedido'!D4 -> 25- Direccion Provincial de Gestion Administrativa y RRHH
A6: UNIDAD EJECUTORA: | G6: 01- Ministerio de Desarrollo Social y Deportes
A7: DEPENDENCIA SOLICITANTE: | G7: 01- Actividad Central
A8: AUTORIZACIÓN:
A9: Señor Jefe de Servicio Administrativo Financiero:
A10: ="Autorizo la realización de los trámites correspondientes, a fin de proveer a este Organismo los bienes y/o servicios que se detallan en Nota de Pedido N° " & ' NotaPedido'!K1&", afectando la erogación resultante a los créditos presupuestarios aprobados a favor de esta Unidad Ejecutora, conforme al siguiente detalle:" -> Autorizo la realización de los trámites correspondientes, a fin de proveer a este Organismo los bienes y/o servicios que se detallan en Nota de Pedido N° 724/2021, afectando la erogación resultante a los créditos presupuestarios aprobados a favor de esta Unidad Ejecutora, conforme al siguiente detalle:
A12: IMPUTACIÓN PRESUPUESTARIA
A13: CÓDIGO | O13: DENOMINACIÓN DE LA PARTIDA PRESUPUESTARIA | Q13: IMPORTE
A14: PR | B14: SB | C14: PY | D14: AC | E14: OB | F14: UG | G14: FIN | H14: FUN | I14: I | J14: P | K14: P | L14: SubP | M14: M | N14: FF
A15: 1 | D15: 1 | F15: 4901 | G15: 1 | H15: 3 | I15: =LEFT('Necesidades Trimestrales'!D10,1) -> 2 | J15: 1 | K15: 1 | M15: 1 | N15: 1.1 | O15: Alimentos para Personas | Q15: 3499991
A20: TOTAL DE PESOS: TRES MILLONES CUATROCIENTOS NOVENTA Y NUEVE MIL NOVECIENTROS NOVENTA Y UNO CON 04/100.- | Q20: =SUM(Q15:Q19) -> 3499991
A22: JUSTIFICACIÓN:
A23: Adquisición de Bidones de 20Lts de Agua Mineral que seran destinadas a las distintas dependencias del Ministerio de Desarrollo Social y Deporte.
