Workbook

Sheet Necesidades Trimestrales
B2: Pedido de Necesidades Trimestrales
A4: JURISDICCION: | C4: 12 -Ministerio de Trabajo y Recursos Humanos
A5: SAF N°: | C5: 22 - Secretaria de Administración del Ministerio de Trabajo y Recursos Humanos
A6: EJERCICIO: | C6: 2021
A7: TRIMESTRE: | C7: 2
A9: ID | B9: CODIGO ITEM | C9: RUBRO DE COMPRA | D9: I.P.P. | E9: DESCRIPCION | F9: UNIDAD DE MEDIDA | G9: CANTIDAD | H9: PRECIO UNITARIO ESTIMADO | I9: IMPORTE TOTAL ESTIMADO
A10: 1 | B10: 2.9.6-401.1097 | C10: REPUESTOS | D10: =+LEFT(B10,5) -> 2.9.6 | E10: CARTUCHOS DE TONER; CODIGO: CB435A, USO: HEWLETT PACKARD | F10: UNIDAD | G10: 20 | H10: 590.35 | I10: =+H10*G10 -> 11807
A11: 2 | B11: 2.9.6-401.1501 | C11: REPUESTOS | D11: =+LEFT(B11,5) -> 2.9.6 | E11: CARTUCHOS DE TONER; CODIGO: 1130D, USO: RICOH | F11: UNIDAD | G11: 4 | H11: 779 | I11: =+H11*G11 -> 3116
A12: 3 | B12: 2.9.6-1355.1139 | C12: REPUESTOS | D12: =+LEFT(B12,5) -> 2.9.6 | E12: CARTUCHOS DE TINTA; CODIGO: C9351AL, DESCRIPCION: SIN VALOR, COLOR: SIN VALOR, USO: HEWLETT PACKARD | F12: UNIDAD | G12: 4 | H12: 3029 | I12: =+H12*G12 -> 12116
A13: 4 | B13: 2.9.6-401.2202 | C13: REPUESTOS | D13: =+LEFT(B13,5) -> 2.9.6 | E13: CARTUCHOS DE TONER; CODIGO: 87X, USO: LASERJET CF287A | F13: UNIDAD | G13: 10 | H13: 3616.85 | I13: =+H13*G13 -> 36168.5
A14: 5 | B14: 2.9.6-401.1859 | C14: REPUESTOS | D14: =+LEFT(B14,5) -> 2.9.6 | E14: CARTUCHOS DE TONER; CODIGO: MLT-D101S, USO: SAMSUNG 2165 | F14: UNIDAD | G14: 16 | H14: 1059.73 | I14: =+H14*G14 -> 16955.68
A15: 6 | B15: 2.9.6-401.952 | C15: REPUESTOS | D15: =+LEFT(B15,5) -> 2.9.6 | E15: CARTUCHOS DE TONER; CODIGO: Q7553A, COLOR: SIN VALOR, DESCRIPCION: SIN VALOR, USO: HEWLETT PACKARD | F15: UNIDAD | G15: 3 | H15: 5747 | I15: =+H15*G15 -> 17241
A16: 7 | B16: 2.9.6-401.2045 | C16: REPUESTOS | D16: =+LEFT(B16,5) -> 2.9.6 | E16: CARTUCHOS DE TONER; CODIGO: TN 1060, USO: BROTHER | F16: UNIDAD | G16: 6 | H16: 545.21 | I16: =+H16*G16 -> 3271.26
A17: 8 | B17: 2.9.6-401.2294 | C17: REPUESTOS | D17: =+LEFT(B17,5) -> 2.9.6 | E17: CARTUCHOS DE TONER; CODIGO: TN-3479, USO: BROTHER | F17: UNIDAD | G17: 4 | H17: 1279.99 | I17: =+H17*G17 -> 5119.96
A18: 9 | B18: 2.9.6-401.2024 | C18: REPUESTOS | D18: =+LEFT(B18,5) -> 2.9.6 | E18: CARTUCHOS DE TONER; CODIGO: MLT-D111S, USO: SAMSUNG | F18: UNIDAD | G18: 50 | H18: 1290 | I18: =+H18*G18 -> 64500
A19: 10 | B19: 2.9.6-1355.1961 | C19: REPUESTOS | D19: =+LEFT(B19,5) -> 2.9.6 | E19: CARTUCHOS DE TINTA; CODIGO: CZ104AL, USO: HEWLETT PACKARD | F19: UNIDAD | G19: 4 | H19: 1150 | I19: =+H19*G19 -> 4600
A20: 11 | B20: 2.9.6-401.1557 | C20: REPUESTOS | D20: =+LEFT(B20,5) -> 2.9.6 | E20: CARTUCHOS DE TONER; CODIGO: TN 360, USO: BROTHER | F20: UNIDAD | G20: 8 | H20: 1020.57 | I20: =+H20*G20 -> 8164.56
A21: 12 | B21: 2.9.6-401.1362 | C21: REPUESTOS | D21: =+LEFT(B21,5) -> 2.9.6 | E21: CARTUCHOS DE TONER; CODIGO: CE285A, USO: HEWLETT PACKARD | F21: UNIDAD | G21: 16 | H21: 590.35 | I21: =+H21*G21 -> 9445.6
... A25: 16 | B25: 2.9.6-401.2377 | C25: REPUESTOS | D25: =+LEFT(B25,5) -> 2.9.6 | E25: CARTUCHOS DE TONER; CODIGO: CF279A, USO: HEWLETT PACKARD | F25: UNIDAD | G25: 16 | H25: 695.05 | I25: =+H25*G25 -> 11120.8
A26: COSTO TOTAL ESTIMADO: DOSCIENTOS SESENTA Y SIETE MIL OCHOSCIENTOS TREINTA Y DOS CON 60/100 | I26: =SUM(I10:I25) -> 267832.6
B29: Especificidades PARA TODOS LOS ITEMS:
B31: Descripción técnica
C32: LOS CARTUCHOS TONER Y CARTUCHOS DE TINTA PODRAN SER ALTERNATIVOS QUE SEAN COMPATIBLES PARA LA DESCRIPCION SOLICITADA DE ACUERDO AL LISTADO DE IMPRESORAS QUE SE ADJUNTA COMO DETALLE.
B35: Plazos y lugares de entrega
C36: a) LUGAR DE ENTREGA: Pabellón Nº 20 Ministerio de Trabajo y Recursos Humanos (CAPE), sito en Av. Presidente Castillo y Av. Venezuela - Capital - De 08 a 12 horas. b) FORMA DE LA ENTREGA: Libre de flete, acarreo y embalaje, como así también, de todo riesgo de pérdida o destrucción total o parcial, por causas ajenas a la Institución. c) PLAZO DE ENTREGA: El Oferente deberá establecer plazo de entrega de los elementos cotizados, debiendo ser expresado en días hábiles; que no podrá ser superior a cinco (5) días hábiles, contados a partir de la recepción de la comunicación prevista en el Artículo en el Reglamento Parcial N° 2 de la ley 4938.
B38: Calidad Mínima esperada
C39: Que Cumpla con lo Solicitado de Forma Integra.
B40: Mantenimiento
C41: 30 (treinta) días
B42: Garantía

Sheet  NotaPedido
A1: NOTA DE PEDIDO | J1: N° | K1: 004/2021
A3: JURISDICCIÓN: | D3: ='Necesidades Trimestrales'!C4 -> 12 -Ministerio de Trabajo y Recursos Humanos
A4: SAF: | D4: ='Necesidades Trimestrales'!C5 -> 22 - Secretaria de Administración del Ministerio de Trabajo y Recursos Humanos
A5: UNIDAD EJECUTORA: | D5: Secretaria de Administracion
A6: DEPENDENCIA SOLICITANTE: | D6: Secretaria de Administracion
A7: PERIODO UTILIZACIÓN: | D7: ='Necesidades Trimestrales'!C7 & "° Trimestre - Año " & 'Necesidades Trimestrales'!C6 -> 2° Trimestre - Año 2021
A8: OBJETO: | D8: Adquisición de CARTUCHOS TONER para las impresoras y fotocopiadoras de las distintas reparticiones de este Ministerio.
A10: Ítem | B10: Codigo Item | C10: DESCRIPCIÓN | H10: Adjunta Detalle Técnico | I10: Unidad Medida | J10: Precio Unitario Estimado | K10: Cantidad Solicitada
A12: =+'Necesidades Trimestrales'!A10 -> 1 | B12: =+'Necesidades Trimestrales'!B10 -> 2.9.6-401.1097 | C12: =+'Necesidades Trimestrales'!E10 -> CARTUCHOS DE TONER; CODIGO: CB435A, USO: HEWLETT PACKARD | H12: SI | I12: =+'Necesidades Trimestrales'!F10 -> UNIDAD | J12: =+'Necesidades Trimestrales'!H10 -> 590.35 | K12: =+'Necesidades Trimestrales'!G10 -> 20
A13: =+'Necesidades Trimestrales'!A11 -> 2 | B13: =+'Necesidades Trimestrales'!B11 -> 2.9.6-401.1501 | C13: =+'Necesidades Trimestrales'!E11 -> CARTUCHOS DE TONER; CODIGO: 1130D, USO: RICOH | H13: SI | I13: =+'Necesidades Trimestrales'!F11 -> UNIDAD | J13: =+'Necesidades Trimestrales'!H11 -> 779 | K13: =+'Necesidades Trimestrales'!G11 -> 4
A14: =+'Necesidades Trimestrales'!A12 -> 3 | B14: =+'Necesidades Trimestrales'!B12 -> 2.9.6-1355.1139 | C14: =+'Necesidades Trimestrales'!E12 -> CARTUCHOS DE TINTA; CODIGO: C9351AL, DESCRIPCION: SIN VALOR, COLOR: SIN VALOR, USO: HEWLETT PACKARD | H14: SI | I14: =+'Necesidades Trimestrales'!F12 -> UNIDAD | J14: =+'Necesidades Trimestrales'!H12 -> 3029 | K14: =+'Necesidades Trimestrales'!G12 -> 4
A15: =+'Necesidades Trimestrales'!A13 -> 4 | B15: =+'Necesidades Trimestrales'!B13 -> 2.9.6-401.2202 | C15: =+'Necesidades Trimestrales'!E13 -> CARTUCHOS DE TONER; CODIGO: 87X, USO: LASERJET CF287A | H15: SI | I15: =+'Necesidades Trimestrales'!F13 -> UNIDAD | J15: =+'Necesidades Trimestrales'!H13 -> 3616.85 | K15: =+'Necesidades Trimestrales'!G13 -> 10
A16: =+'Necesidades Trimestrales'!A14 -> 5 | B16: =+'Necesidades Trimestrales'!B14 -> 2.9.6-401.1859 | C16: =+'Necesidades Trimestrales'!E14 -> CARTUCHOS DE TONER; CODIGO: MLT-D101S, USO: SAMSUNG 2165 | H16: SI | I16: =+'Necesidades Trimestrales'!F14 -> UNIDAD | J16: =+'Necesidades Trimestrales'!H14 -> 1059.73 | K16: =+'Necesidades Trimestrales'!G14 -> 16
A17: =+'Necesidades Trimestrales'!A15 -> 6 | B17: =+'Necesidades Trimestrales'!B15 -> 2.9.6-401.952 | C17: =+'Necesidades Trimestrales'!E15 -> CARTUCHOS DE TONER; CODIGO: Q7553A, COLOR: SIN VALOR, DESCRIPCION: SIN VALOR, USO: HEWLETT PACKARD | H17: SI | I17: =+'Necesidades Trimestrales'!F15 -> UNIDAD | J17: =+'Necesidades Trimestrales'!H15 -> 5747 | K17: =+'Necesidades Trimestrales'!G15 -> 3
A18: =+'Necesidades Trimestrales'!A16 -> 7 | B18: =+'Necesidades Trimestrales'!B16 -> 2.9.6-401.2045 | C18: =+'Necesidades Trimestrales'!E16 -> CARTUCHOS DE TONER; CODIGO: TN 1060, USO: BROTHER | H18: SI | I18: =+'Necesidades Trimestrales'!F16 -> UNIDAD | J18: =+'Necesidades Trimestrales'!H16 -> 545.21 | K18: =+'Necesidades Trimestrales'!G16 -> 6
A19: =+'Necesidades Trimestrales'!A17 -> 8 | B19: =+'Necesidades Trimestrales'!B17 -> 2.9.6-401.2294 | C19: =+'Necesidades Trimestrales'!E17 -> CARTUCHOS DE TONER; CODIGO: TN-3479, USO: BROTHER | H19: SI | I19: =+'Necesidades Trimestrales'!F17 -> UNIDAD | J19: =+'Necesidades Trimestrales'!H17 -> 1279.99 | K19: =+'Necesidades Trimestrales'!G17 -> 4
A20: =+'Necesidades Trimestrales'!A18 -> 9 | B20: =+'Necesidades Trimestrales'!B18 -> 2.9.6-401.2024 | C20: =+'Necesidades Trimestrales'!E18 -> CARTUCHOS DE TONER; CODIGO: MLT-D111S, USO: SAMSUNG | H20: SI | I20: =+'Necesidades Trimestrales'!F18 -> UNIDAD | J20: =+'Necesidades Trimestrales'!H18 -> 1290 | K20: =+'Necesidades Trimestrales'!G18 -> 50
A21: =+'Necesidades Trimestrales'!A19 -> 10 | B21: =+'Necesidades Trimestrales'!B19 -> 2.9.6-1355.1961 | C21: =+'Necesidades Trimestrales'!E19 -> CARTUCHOS DE TINTA; CODIGO: CZ104AL, USO: HEWLETT PACKARD | H21: SI | I21: =+'Necesidades Trimestrales'!F19 -> UNIDAD | J21: =+'Necesidades Trimestrales'!H19 -> 1150 | K21: =+'Necesidades Trimestrales'!G19 -> 4
A22: =+'Necesidades Trimestrales'!A20 -> 11 | B22: =+'Necesidades Trimestrales'!B20 -> 2.9.6-401.1557 | C22: =+'Necesidades Trimestrales'!E20 -> CARTUCHOS DE TONER; CODIGO: TN 360, USO: BROTHER | H22: SI | I22: =+'Necesidades Trimestrales'!F20 -> UNIDAD | J22: =+'Necesidades Trimestrales'!H20 -> 1020.57 | K22: =+'Necesidades Trimestrales'!G20 -> 8
A23: =+'Necesidades Trimestrales'!A21 -> 12 | B23: =+'Necesidades Trimestrales'!B21 -> 2.9.6-401.1362 | C23: =+'Necesidades Trimestrales'!E21 -> CARTUCHOS DE TONER; CODIGO: CE285A, USO: HEWLETT PACKARD | H23: SI | I23: =+'Necesidades Trimestrales'!F21 -> UNIDAD | J23: =+'Necesidades Trimestrales'!H21 -> 590.35 | K23: =+'Necesidades Trimestrales'!G21 -> 16
... A27: =+'Necesidades Trimestrales'!A25 -> 16 | B27: =+'Necesidades Trimestrales'!B25 -> 2.9.6-401.2377 | C27: =+'Necesidades Trimestrales'!E25 -> CARTUCHOS DE TONER; CODIGO: CF279A, USO: HEWLETT PACKARD | H27: SI | I27: =+'Necesidades Trimestrales'!F25 -> UNIDAD | J27: =+'Necesidades Trimestrales'!H25 -> 695.05 | K27: =+'Necesidades Trimestrales'!G25 -> 16
A28: =+'Necesidades Trimestrales'!A26:H26 -> COSTO TOTAL ESTIMADO: DOSCIENTOS SESENTA Y SIETE MIL OCHOSCIENTOS TREINTA Y DOS CON 60/100 | J28: =SUMPRODUCT(J12:J27,K12:K27) -> 267832.6

Sheet Autor Gastar
A1: EJERCICIO: | D1: ='Necesidades Trimestrales'!C6 -> 2021 | P1: AUTORIZACION PARA GASTAR
A4: JURISDICCIÓN: | G4: =' NotaPedido'!D3 -> 12 -Ministerio de Trabajo y Recursos Humanos
A5: SAF: | G5: =' NotaPedido'!D4 -> 22 - Secretaria de Administración del Ministerio de Trabajo y Recursos Humanos
A6: UNIDAD EJECUTORA: | G6: Ministerio de Trabajo y Reursos Humanos
A7: DEPENDENCIA SOLICITANTE: | G7: =' NotaPedido'!D6 -> Secretaria de Administracion
A8: AUTORIZACIÓN:
A9: Señor Jefe de Servicio Administrativo Financiero:
A10: ="Autorizo la realización de los trámites correspondientes, a fin de proveer a este Organismo los bienes y/o servicios que se detallan en Nota de Pedido N° " & ' NotaPedido'!K1&", afectando la erogación resultante a los créditos presupuestarios aprobados a favor de esta Unidad Ejecutora, conforme al siguiente detalle:" -> Autorizo la realización de los trámites correspondientes, a fin de proveer a este Organismo los bienes y/o servicios que se detallan en Nota de Pedido N° 004/2021, afectando la erogación resultante a los créditos presupuestarios aprobados a favor de esta Unidad Ejecutora, conforme al siguiente detalle:
A12: IMPUTACIÓN PRESUPUESTARIA
A13: CÓDIGO | O13: DENOMINACIÓN DE LA PARTIDA PRESUPUESTARIA | Q13: IMPORTE
A14: PR | B14: SB | C14: PY | D14: AC | E14: OB | F14: UG | G14: FIN | H14: FUN | I14: I | J14: P | K14: P | L14: SubP | M14: M | N14: FF
A15: 1 | B15: 0 | C15: 0 | D15: 1 | E15: 0 | F15: 4901 | G15: 3 | H15: 6 | I15: 2 | J15: 9 | K15: 6 | L15: 0 | M15: 1 | N15: 1.1 | O15: REPUESTOS Y ACCESORIOS | Q15: 167510.6
A16: 3 | B16: 0 | C16: 0 | D16: 1 | E16: 0 | F16: 4901 | G16: 1 | H16: 3 | I16: 2 | J16: 9 | K16: 6 | L16: 0 | M16: 1 | N16: 1.1 | O16: REPUESTOS Y ACCESORIOS | Q16: 10000
A17: 6 | B17: 0 | C17: 0 | D17: 1 | E17: 0 | F17: 4901 | G17: 1 | H17: 3 | I17: 2 | J17: 9 | K17: 6 | L17: 0 | M17: 1 | N17: 1.1 | O17: REPUESTOS Y ACCESORIOS | Q17: 40000
A18: 6 | B18: 0 | C18: 0 | D18: 2 | E18: 0 | F18: 4901 | G18: 1 | H18: 3 | I18: 2 | J18: 9 | K18: 6 | L18: 0 | M18: 1 | N18: 1.1 | O18: REPUESTOS Y ACCESORIOS | Q18: 1843
A19: 6 | B19: 0 | C19: 0 | D19: 3 | E19: 0 | F19: 4901 | G19: 1 | H19: 8 | I19: 2 | J19: 9 | K19: 6 | L19: 0 | M19: 1 | N19: 1.1 | O19: REPUESTOS Y ACCESORIOS | Q19: 6255
A20: 6 | B20: 0 | C20: 0 | D20: 4 | E20: 0 | F20: 4901 | G20: 3 | H20: 4 | I20: 2 | J20: 9 | K20: 6 | L20: 0 | M20: 1 | N20: 1.1 | O20: REPUESTOS Y ACCESORIOS | Q20: 10000
A21: 6 | B21: 0 | C21: 0 | D21: 5 | E21: 0 | F21: 4901 | G21: 3 | H21: 1 | I21: 2 | J21: 9 | K21: 6 | L21: 0 | M21: 1 | N21: 1.1 | O21: REPUESTOS Y ACCESORIOS | Q21: 6554
A22: 7 | B22: 0 | C22: 0 | D22: 1 | E22: 0 | F22: 4901 | G22: 1 | H22: 3 | I22: 2 | J22: 9 | K22: 6 | L22: 0 | M22: 1 | N22: 1.1 | O22: REPUESTOS Y ACCESORIOS | Q22: 20000
A23: 8 | B23: 0 | C23: 0 | D23: 1 | E23: 0 | F23: 4901 | G23: 3 | H23: 6 | I23: 2 | J23: 9 | K23: 6 | L23: 0 | M23: 1 | N23: 1.1 | O23: REPUESTOS Y ACCESORIOS | Q23: 5670
A24: =+' NotaPedido'!A28:I28 -> COSTO TOTAL ESTIMADO: DOSCIENTOS SESENTA Y SIETE MIL OCHOSCIENTOS TREINTA Y DOS CON 60/100 | Q24: =SUM(Q15:Q23) -> 267832.6
A26: JUSTIFICACIÓN:
A27: =' NotaPedido'!D8 -> Adquisición de CARTUCHOS TONER para las impresoras y fotocopiadoras de las distintas reparticiones de este Ministerio.

Sheet DETALLE IMPRESORAS
A4: SECRETARIA | B4: REPARTICION | C4: SECTOR | D4: ESPECIE | E4: DETALLE | F4: CANTIDAD | G4: UBICACIÓN
A5: DIRECCION PROVINCIAL CONTROL Y GESTION | B5: DIRECCION PROVINCIAL CONTROL Y GESTION | C5: DIRECCION PROVINCIAL CONTROL Y GESTION | D5: IMPRESORA LASER | E5: HP LASERJET PRO 400 | F5: 1 | G5: PABELLON 20
A6: DIRECCION PROVINCIAL DE ASESORIA LEGAL Y TECNICA | B6: DIRECCION PROVINCIAL DE ASESORIA LEGAL Y TECNICA | C6: DIRECCION PROVINCIAL DE ASESORIA LEGAL Y TECNICA | D6: IMPRESORA LASER | E6: HP LASERJET 1020 | F6: 1 | G6: PABELLON 20
A7: DIRECCION PROVINCIAL SUMARIO DOCENTE | B7: DIRECCION PROVINCIAL SUMARIO DOCENTE | C7: DIRECCION PROVINCIAL SUMARIO DOCENTE | D7: IMPRESORA LASER | E7: BROTHER HL1212W | F7: 1 | G7: PABELLON 12
A8: DIRECCION PROVINCIAL SUMARIO DOCENTE | B8: DIRECCION PROVINCIAL SUMARIO DOCENTE | C8: DIRECCION PROVINCIAL SUMARIO DOCENTE | D8: IMPRESORA LASER | E8: BROTHER HL1212W | F8: 1 | G8: PABELLON 12
A9: DIRECCION PROVINCIAL SUMARIO DOCENTE | B9: DIRECCION PROVINCIAL SUMARIO DOCENTE | C9: DIRECCION PROVINCIAL SUMARIO DOCENTE | D9: IMPRESORA LASER | E9: SAMSUNG ML2165W | F9: 1 | G9: PABELLON 12
A10: DIRECCION PROVINCIAL SUMARIO DOCENTE | B10: DIRECCION PROVINCIAL SUMARIO DOCENTE | C10: DIRECCION PROVINCIAL SUMARIO DOCENTE | D10: IMPRESORA LASER | E10: HP LASERJET P1005 | F10: 1 | G10: PABELLON 12
A11: DIRECCION PROVINCIAL SUMARIO DOCENTE | B11: DIRECCION PROVINCIAL SUMARIO DOCENTE | C11: DIRECCION PROVINCIAL SUMARIO DOCENTE | D11: IMPRESORA LASER | E11: HP LASERJET P1102W | F11: 1 | G11: PABELLON 12
A12: DIRECCION PROVINCIAL SUMARIO DOCENTE | B12: DIRECCION PROVINCIAL SUMARIO DOCENTE | C12: DIRECCION PROVINCIAL SUMARIO DOCENTE | D12: IMPRESORA LASER | E12: HP LASERJET P1102W | F12: 1 | G12: PABELLON 12
A13: OFICINA DEL MINISTRO | B13: OFICINA DEL MINISTRO | C13: OFICINA DEL MINISTRO | D13: IMPRESORA LASER | E13: HP LASERJET P1006 | F13: 1 | G13: PABELLON 20
A14: SECRETARIA DE RECURSOS HUMANOS DOCENTES | B14: DIRECCION PROVINCIAL DE RECURSOS HUMANOS Y GESTION DOCENTE | C14: SECRETARIA | D14: IMPRESORA LASER | E14: HP LASERJET P1102W | F14: 1 | G14: PABELLON 10
A15: SECRETARIA DE RECURSOS HUMANOS DOCENTES | B15: DIRECCION PROVINCIAL DE RECURSOS HUMANOS Y GESTION DOCENTE | C15: SUMINISTROS | D15: IMPRESORA LASER | E15: HP LASERJET P2014 | F15: 1 | G15: PABELLON 10
A16: SECRETARIA DE RECURSOS HUMANOS DOCENTES | B16: DIRECCION PROVINCIAL DE RECURSOS HUMANOS Y GESTION DOCENTE | C16: MESA DE ENTRADA | D16: IMPRESORA LASER | E16: HP LASERJET PRO 400 | F16: 1 | G16: PABELLON 10
... A46: SUBSECRETARIA RECONOCIMIENTO MEDICO | B46: DIRECCION PROVINCIAL DE RECONOCIMIENTO MEDICO DOCENTE | C46: CONSULTORIOS | D46: IMPRESORA LASER | E46: HP LASERJET P1102W | F46: 2 | G46: EX SAN JUAN BAUTISTA
