Workbook

Sheet Necesidades Trimestrales
B2: Pedido de Necesidades Trimestrales
A3: JURISDICCION: | C3: 90 - Ministerio de Seguridad
A4: SAF N°: | C4: 7- Dirección Provincial de Administración de la Policía de la Provincia de Catamarca
A5: EJERCICIO: | C5: 2021
A6: TRIMESTRE: | C6: 4
A8: ID | B8: CODIGO ITEM | C8: RUBRO DE COMPRA | D8: I.P.P. | E8: DESCRIPCION | F8: UNIDAD DE MEDIDA | G8: CANTIDAD | H8: PRECIO UNITARIO ESTIMADO | I8: IMPORTE TOTAL ESTIMADO
A9: 1 | B9: 3.5.4-2065.1 | C9: BANCOS Y SEGUROS | D9: =LEFT(B9,5) -> 3.5.4 | E9: SEGURO DE RESPONSABILIDAD; DESCRIPCION: SEGURO DE RESPONSABILIDAD | F9: UNIDAD | G9: 1 | H9: 90297.39 | I9: =H9*G9 -> 90297.39
A10: 2 | B10: 3.5.4-2065.1 | C10: BANCOS Y SEGUROS | D10: =LEFT(B10,5) -> 3.5.4 | E10: SEGURO DE RESPONSABILIDAD; DESCRIPCION: SEGURO DE RESPONSABILIDAD | F10: UNIDAD | G10: 1 | H10: 126203.32 | I10: =H10*G10 -> 126203.32
A11: 3 | B11: 3.5.4-2065.1 | C11: BANCOS Y SEGUROS | D11: =LEFT(B11,5) -> 3.5.4 | E11: SEGURO DE RESPONSABILIDAD; DESCRIPCION: SEGURO DE RESPONSABILIDAD | F11: UNIDAD | G11: 1 | H11: 996677.21 | I11: =H11*G11 -> 996677.21
A12: 4 | B12: 3.5.4-2065.1 | C12: BANCOS Y SEGUROS | D12: =LEFT(B12,5) -> 3.5.4 | E12: SEGURO DE RESPONSABILIDAD; DESCRIPCION: SEGURO DE RESPONSABILIDAD | F12: UNIDAD | G12: 1 | H12: 63014.35 | I12: =H12*G12 -> 63014.35
A13: 5 | B13: 3.5.4-2065.1 | C13: BANCOS Y SEGUROS | D13: =LEFT(B13,5) -> 3.5.4 | E13: SEGURO DE RESPONSABILIDAD; DESCRIPCION: SEGURO DE RESPONSABILIDAD | F13: UNIDAD | G13: 1 | H13: 137591.67 | I13: =H13*G13 -> 137591.67
A14: 6 | B14: 3.5.4-2065.1 | C14: BANCOS Y SEGUROS | D14: =LEFT(B14,5) -> 3.5.4 | E14: SEGURO DE RESPONSABILIDAD; DESCRIPCION: SEGURO DE RESPONSABILIDAD | F14: UNIDAD | G14: 1 | H14: 1644973.5 | I14: =H14*G14 -> 1644973.5
A15: 7 | B15: 3.5.4-2065.1 | C15: BANCOS Y SEGUROS | D15: =LEFT(B15,5) -> 3.5.4 | E15: SEGURO DE RESPONSABILIDAD; DESCRIPCION: SEGURO DE RESPONSABILIDAD | F15: UNIDAD | G15: 1 | H15: 71123.52 | I15: =H15*G15 -> 71123.52
I16: =SUM(I9:I15) -> 3129880.9
B18: Especificidades Item N° 1:
C19: CARACTERÍSTICAS: “Seguro Obligatorio de Responsabilidad Civil del Automotor conforme Res. SSN N° 35.863, 36.100 y modificatorias. Responsabilidad Civil con límites, en la República Argentina y países limítrofes: por lesiones y/o muerte y daños a cosas de terceros no transportados por acontecimientos hasta la suma de pesos 6.000.000,00. Extensión a países limítrofes sin cargo” de VEHICULO: AUTO; TOTAL DE VEHICULOS: 09 (NUEVE) que integran el Parque Automotor Policial, cuyos datos se detallan en Anexo. VIGENCIA: desde el 30/12/2021 al 30/12/2022. (ANUAL- 12 MESES)
B20: Especificidades Item N° 2:
C21: CARACTERÍSTICAS: “Seguro Obligatorio de Responsabilidad Civil del Automotor conforme Res. SSN N° 35.863, 36.100 y modificatorias. Responsabilidad Civil con límites, en la República Argentina y países limítrofes: por lesiones y/o muerte y daños a cosas de terceros no transportados por acontecimientos hasta la suma de pesos 6.000.000,00. Extensión a países limítrofes sin cargo” de VEHICULO: MOTOS; TOTAL DE VEHICULOS: 76 (SETENTA Y SEIS) que integran el Parque Automotor Policial, cuyos datos se detallan en Anexo. VIGENCIA: desde el 30/12/2021 al 30/12/2022. (ANUAL- 12 MESES)
B22: Especificidades Item N° 3:
C23: CARACTERÍSTICAS: “Seguro Obligatorio de Responsabilidad Civil del Automotor conforme Res. SSN N° 35.863, 36.100 y modificatorias. Responsabilidad Civil con límites, en la República Argentina y países limítrofes: por lesiones y/o muerte y daños a cosas de terceros no transportados por acontecimientos hasta la suma de pesos 6.000.000,00. Extensión a países limítrofes sin cargo” de VEHICULO: CAMIONETA; TOTAL DE VEHICULOS: 83 (OCHENTA Y TRES) que integran el Parque Automotor Policial, cuyos datos se detallan en Anexo. VIGENCIA: desde el 30/12/2021 al 30/12/2022. (ANUAL- 12 MESES)
B24: Especificidades Item N° 4:
C25: CARACTERÍSTICAS: “Seguro Obligatorio de Responsabilidad Civil del Automotor conforme Res. SSN N° 35.863, 36.100 y modificatorias. Responsabilidad Civil con límites, en la República Argentina y países limítrofes: por lesiones y/o muerte y daños a cosas de terceros no transportados por acontecimientos hasta la suma de pesos 6.000.000,00. Extensión a países limítrofes sin cargo” de VEHICULO: UTILITARIO; TOTAL DE VEHICULOS: 05 (CINCO) que integran el Parque Automotor Policial, cuyos datos se detallan en Anexo. VIGENCIA: desde el 30/12/2021 al 30/12/2022. (ANUAL- 12 MESES)
B26: Especificidades Item N° 5:
C27: CARACTERÍSTICAS: “Seguro Obligatorio de Responsabilidad Civil del Automotor conforme Res. SSN N° 35.863, 36.100 y modificatorias. Responsabilidad Civil con límites, en la República Argentina y países limítrofes: por lesiones y/o muerte y daños a cosas de terceros no transportados por acontecimientos hasta la suma de pesos 6.000.000,00. Extensión a países limítrofes sin cargo” de VEHICULO: CAMIONES: TOTAL DE VEHICULOS: 07 (SIETE) que integran el Parque Automotor Policial, cuyos datos se detallan en Anexo. VIGENCIA: desde el 30/12/2021 al 30/12/2022.. (ANUAL- 12 MESES)
B28: Especificidades Item N° 6:
C29: CARACTERÍSTICAS: “Seguro Obligatorio de Responsabilidad Civil del Automotor conforme Res. SSN N° 35.863, 36.100 y modificatorias. Responsabilidad Civil con límites, en la República Argentina y países limítrofes: por lesiones y/o muerte y daños a cosas de terceros no transportados por acontecimientos hasta la suma de pesos 6.000.000,00. Extensión a países limítrofes sin cargo, CON COBERTURA DE: rotura o rajadura de cristales, vidrios, de Parabrisas y luneta SIN LÍMITE DE ACONTECIMIENTOS NI EVENTOS, incluyendo los gastos normales de colocación” de VEHICULO: CAMIONETAS: TOTAL DE VEHICULOS: 24 (VEINTICUATRO) que integran el Parque Automotor Policial, cuyos datos se detallan en Anexo. VIGENCIA: desde el 30/12/2021 al 30/12/2022. (ANUAL- 12 MESES)
B30: Especificidades Item N° 7:
C31: CARACTERÍSTICAS: “Seguro Obligatorio de Responsabilidad Civil del Automotor conforme Res. SSN N° 35.863, 36.100 y modificatorias. Responsabilidad Civil con límites, en la República Argentina y países limítrofes: por lesiones y/o muerte y daños a cosas de terceros no transportados por acontecimientos hasta la suma de pesos 6.000.000,00. Extensión a países limítrofes sin cargo, CON COBERTURA DE: rotura o rajadura de cristales, vidrios, de Parabrisas y luneta SIN LÍMITE DE ACONTECIMIENTOS NI EVENTOS, incluyendo los gastos normales de colocación” de VEHICULO: UTILITARIO: TOTAL DE VEHICULOS: UNO (UNO) que integran el Parque Automotor Policial, cuyos datos se detallan en Anexo. VIGENCIA: desde el 30/12/2021 al 30/12/2022. (ANUAL- 12 MESES)
B32: Plazos y lugares de entrega
C33: a) LUGAR DE ENTREGA: SECCION CONTROL PATRIMONIAL (Dpto Logística), sito en Chacabuco N° 809 - Capital - De 08 a 12 horas. b) FORMA DE LA ENTREGA: Las Pólizas deben entregarse detallando el vehículo que está cubriendo el seguro contratado. c) PLAZO DE ENTREGA: El Oferente deberá establecer plazo de entrega de los elementos cotizados, debiendo ser expresado en días hábiles; que no podrá ser superior a cinco (5) días hábiles, contados a partir de la recepción de la comunicación prevista en el Artículo 80° de del Reglamento Parcial N° 2 de la ley 4938.
B34: Calidad Minima esperada
C35: Que cumpla íntegramente con lo solicitado por cada renglon.
B36: Mantenimiento
C37: 30 (treinta) días
B38: Garantia

Sheet PQUE_AUTOMOTOR SAF7 2021
A1: ORDEN | B1: TIPO | C1: DOMINIO | D1: MARCA | E1: MODELO | F1: AÑO | G1: MOTOR | H1: CHASIS
A2: 01 | B2: ACOPLADO | C2: OHQ-771 | D2: NO VISIBLE | E2: NO VISIBLE | F2: 2014 | G2: S/MOTOR | H2: C14ACG4149
A3: 02 | B3: AUTO | C3: PHO-195 | D3: FIAT | E3: PALIO ATTRACTIVE 1,4 | F3: 2015 | G3: 327A0552366431 | H3: 8AP196475F4124427
A4: 03 | B4: AUTO | C4: PHO-196 | D4: FIAT | E4: PALIO ATTRACTIVE 1,4 | F4: 2015 | G4: 327A0552346624 | H4: 8AP196475F4123099
A5: 04 | B5: AUTO | C5: KAW-919 | D5: FIAT | E5: FIAT-LINEA ESSENCE | F5: 2012
A6: 05 | B6: AUTO | C6: AB-322-SC | D6: TOYOTA | E6: ETIOS X 1,5 M/T 5P | F6: 2017 | G6: 2NR4073730 | H6: 9BRK29BT9H0111908
A7: 06 | B7: AUTO | C7: OAU-662 | D7: FIAT | E7: SIENA | F7: 2014 | G7: 310A20111946352 | H7: 8AP372316E6089443
A8: 07 | B8: AUTO | C8: ONU-184 | D8: VOLKSWAGEN | E8: GOL TREND 1,6 T SEDAN 5 PTAS | F8: 2015 | G8: CFZN67663 | H8: 9BWAB45U7F9118246
A9: 08 | B9: AUTO | C9: OSL-109 | D9: TOYOTA | E9: ETIOS X 1,5 M/T 5P | F9: 2015 | G9: 2NRV274614 | H9: 9BRK29BT3F0055994
A10: 09 | B10: AUTO | C10: OSL-113 | D10: TOYOTA | E10: ETIOS X 1,5 M/T 5P | F10: 2015 | G10: 2NRV275538 | H10: 9BRK29BT6F0056217
A11: 10 | B11: AUTO | C11: OSL-114 | D11: TOYOTA | E11: ETIOS X 1,5 M/T 5P | F11: 2015 | G11: 2NRV276309 | H11: 9BRK29BT8F0056476
A12: 11 | B12: AUTO | C12: OSL-115 | D12: TOYOTA | E12: ETIOS X 1,5 M/T 5P | F12: 2015 | G12: 2NRV273984 | H12: 9BRK29BT1F0055816
A13: 12 | B13: AUTO | C13: OSL-134 | D13: TOYOTA | E13: ETIOS X 1,5 M/T 5P | F13: 2015 | G13: 2NRV277684 | H13: 9BRK29BT3F0056904
A14: 13 | B14: AUTO | C14: OSP-830 | D14: TOYOTA | E14: ETIOS X 1,5 M/T 5P | F14: 2015 | G14: 2NRV276886 | H14: 9BRK29BTXF0056687
A15: 14 | B15: AUTO | C15: OSP-866 | D15: TOYOTA | E15: ETIOS X 1,5 M/T 5P | F15: 2015 | G15: 2NRV279308 | H15: 9BRK29BT9F0057359
A16: 15 | B16: AUTO | C16: AB-538-JJ | D16: CHEVROLET | E16: PRISMA JOY LS | F16: 2017 | G16: GFK038284 | H16: 9BGKL69THG251124
A17: 16 | B17: AUTO | C17: AD-601-IW | D17: CHEVROLET | E17: ONIX JOY 5P 1,4 N LS MT | F17: 2019 | G17: GFK129810 | H17: 9BGKL48T0JG
... A33: 32 | B33: AUTOBOMBA B-12 | C33: AD-016-LU | D33: FORD | E33: CARGO 1119-42 | F33: 2018 | G33: 36585550 | H33: 9BFWEA7B4JBS44819
A34: 33 | B34: AUTOBOMBA B-8 | C34: HVU-684 | D34: VOLKSWAGEN | F34: 2009 | G34: G1T110738 | H34: 9BWB172S89R905534
A35: 34 | B35: AUTOBOMBA B-9 | C35: IFJ-295 | D35: FORD | E35: CARGO 1832 | F35: 2009 | G35: 36047899 | H35: 9BFYCAWYO9BB16113
A36: 35 | B36: CAMION JAULA | C36: FZT-783 | D36: MERCEDEZ BENZ | E36: L-1218,6L | F36: 2007 | G36: 904938U0701544 | H36: 9BM6940007B503596
A37: 36 | B37: CAMION JAULA | C37: VII-506 | D37: MERCEDEZ BENZ | E37: 1215 | F37: 1980 | G37: 3491200607013 | H37: 341042-10-03300
A38: 37 | B38: CAMION RAMPA 9150 | C38: HVU-681 | D38: VOLKSWAGEN | F38: 2009 | G38: 36057009 | H38: 9BWAA52R39R848365
A39: 38 | B39: CAMION TERMICO 9150E | C39: HVU-682 | D39: VOLKSWAGEN | F39: 2009 | G39: 36059297 | H39: 9BWAA52R09R850042
A40: 39 | B40: CAMION VOLCADOR | C40: HVU-683 | D40: VOLKSWAGEN | F40: 2009 | G40: G1T111162 | H40: 9BWB172S09R907813
A41: 40 | B41: CAMIONETA | C41: AD-922-FC | D41: CHEVROLET | E41: S-10 STD 4X2 | F41: 2019 | G41: LWNF190981126 | H41: 9BG148CK0LC401677
A42: 41 | B42: CAMIONETA | C42: AD-922-FD | D42: CHEVROLET | E42: S-10 STD 4X2 | F42: 2019 | G42: LWNF190851068 | H42: 9BG148CK0LC400227
A43: 42 | B43: CAMIONETA | C43: AD-922-FE | D43: CHEVROLET | E43: S-10 STD 4X2 | F43: 2019 | G43: LWNF190981178 | H43: 9BG148CK0LC401661
A44: 43 | B44: CAMIONETA | C44: AD-922-FF | D44: CHEVROLET | E44: S-10 STD 4X2 | F44: 2019 | G44: LWNF190991016 | H44: 9BG148CK0LC401741
A45: 44 | B45: CAMIONETA | C45: AD-922-FG | D45: CHEVROLET | E45: S-10 STD 4X2 | F45: 2019 | G45: LWNF190981077 | H45: 9BG148CK0LC401672
A46: 45 | B46: CAMIONETA | C46: AD-922-FH | D46: CHEVROLET | E46: S-10 STD 4X2 | F46: 2019 | G46: LWNF190861066 | H46: 9BG148CK0LC400210
A47: 46 | B47: CAMIONETA | C47: AD-922-FI | D47: CHEVROLET | E47: S-10 STD 4X2 | F47: 2019 | G47: LWNF190981110 | H47: 9BG148CK0LC401737
A48: 47 | B48: CAMIONETA | C48: AD-922-FJ | D48: CHEVROLET | E48: S-10 STD 4X2 | F48: 2019 | G48: LWNF190851062 | H48: 9BG148CK0LC400218
A49: 48 | B49: CAMIONETA | C49: AD-922-FK | D49: CHEVROLET | E49: S-10 STD 4X2 | F49: 2019 | G49: LWNF190981134 | H49: 9BG148CK0LC401732
A50: 49 | B50: CAMIONETA | C50: AD-922-FL | D50: CHEVROLET | E50: S-10 STD 4X2 | F50: 2019 | G50: LWNF190301017 | H50: 9BG148CK0LC400188
A51: 50 | B51: CAMIONETA | C51: AD939YR | D51: TOYOTA | E51: HILUX 4X2 | G51: 2GD-C415935 | H51: 8AJCB8DDXK4002884
A52: 51 | B52: CAMIONETA | C52: AE 744 PP | D52: TOYOTA | E52: HILUX 4X4 C/D DX 2.4 TDI 6 M/T | F52: 2021 | G52: 2GD-0711132 | H52: 8AJDB3CD7L1305018
A53: 52 | B53: CAMIONETA | C53: AE 744 PQ | D53: TOYOTA | E53: HILUX 4X4 C/D DX 2.4 TDI 6 M/T | F53: 2021 | G53: 2GD-0711124 | H53: 8AJDB3CD9L1305019
A54: 53 | B54: CAMIONETA | C54: AE 744 PR | D54: TOYOTA | E54: HILUX 4X4 C/D DX 2.4 TDI 6 M/T | F54: 2021 | G54: 2GD-G196216 | H54: 8AJDB3CD8M1305188
A55: 54 | B55: CAMIONETA | C55: AE 744 PS | D55: TOYOTA | E55: HILUX 4X4 C/D DX 2.4 TDI 6 M/T | F55: 2021 | G55: 2GD-0867167 | H55: 8AJDB3CDXL1305014
A56: 55 | B56: CAMIONETA | C56: AE 744 PT | D56: TOYOTA | E56: HILUX 4X4 C/D DX 2.4 TDI 6 M/T | F56: 2021 | G56: 2GD-G196284 | H56: 8AJDB3CD8M1305191
A57: 56 | B57: CAMIONETA | C57: AE-180-RS | D57: RENAULT | E57: DUSTER OROCH OUTSIDER 1,6 | F57: 2019 | G57: K4M2842Q249921 | H57: 93Y9SR095LJ276131
A58: 57 | B58: CAMIONETA | C58: AE-290-OT | D58: TOYOTA | E58: HILUX 4X2 D/C PACK DX 2,5 TDI | F58: 2020 | G58: 2GD-G156129 | H58: 8AJDB3CD2L1302799
A59: 58 | B59: CAMIONETA | C59: AE-290-OU | D59: TOYOTA | E59: HILUX 4X2 D/C PACK DX 2,5 TDI | F59: 2020 | G59: 2GD-0743967 | H59: 8AJDB3CD9L1301813
A60: 59 | B60: CAMIONETA | C60: AE-290-OV | D60: TOYOTA | E60: HILUX 4X2 D/C PACK DX 2,5 TDI | F60: 2020 | G60: 2GD-0753555 | H60: 8AJDB3CDXL1302145
A61: 60 | B61: CAMIONETA | C61: AE-290-OW | D61: TOYOTA | E61: HILUX 4X2 D/C PACK DX 2,5 TDI | F61: 2020 | G61: 2GD-G164416 | H61: 8AJDB3CD9L1303092
A62: 61 | B62: CAMIONETA | C62: AE-290-OX | D62: TOYOTA | E62: HILUX 4X2 D/C PACK DX 2,5 TDI | F62: 2020 | G62: 2GD-G156166 | H62: 8AJDB3CD5L1302800
A63: 62 | B63: CAMIONETA | C63: AE-290-OY | D63: TOYOTA | E63: HILUX 4X2 D/C PACK DX 2,5 TDI | F63: 2020 | G63: 2GD-G164667 | H63: 8AJDB3CD7L1303110
... A183: 182 | B183: CARRO | C183: S/DOM. 101 PIQ-547 (FICTICIA) | D183: NO VISIBLE | E183: NO VISIBLE | F183: 2013 | G183: S/MOTOR | H183: NO UBICADO
A184: 183 | B184: CARRO - TRAILER | C184: S/DOM. QPT-805 | D184: NO VISIBLE | E184: NO VISIBLE | G184: S/MOTOR | H184: NO UBICADO
A185: 184 | B185: CARRO ohq 711(ver) | C185: S/DOM. 101 PIO-395 | D185: NO VISIBLE | E185: NO VISIBLE | F185: 2013 | G185: S/MOTOR | H185: NO UBICADO
A186: 185 | B186: CARRO TRAILER P/CUATRICICLO | C186: 101 QAL-390 | D186: NO VISIBLE | E186: NO VISIBLE | F186: 2015 | G186: S/MOTOR | H186: NO UBICADO
A187: 186 | B187: CASILLA 1 | C187: 01 QAL-205 (FICTICIA) | D187: NO VISIBLE | E187: NO VISIBLE | G187: S/MOTOR | H187: NO UBICADO
A188: 187 | B188: CASILLA 2 | C188: 101 PIO-400 (FICTICIA) | D188: NO VISIBLE | E188: NO VISIBLE | G188: S/MOTOR | H188: NO UBICADO
A189: 188 | B189: CASILLA 3 | C189: 101 QAL-206 (FICTICIA) | D189: NO VISIBLE | E189: NO VISIBLE | G189: S/MOTOR | H189: NO UBICADO
A190: 189 | B190: CASILLA 4 | C190: 101 QAL-207 (FICTICIA) | D190: E.T. MANQUE | E190: NO VISIBLE | F190: 2008 | G190: S/MOTOR | H190: REEVER
A191: 190 | B191: CUATRICICLO | C191: 046-DXP | D191: HONDA | E191: TRX 500 | F191: 2008 | G191: TE31E-8310887 | H191: 1HFTE31U084300651
A192: 191 | B192: CUATRICICLO | C192: 047-DXP | D192: HONDA | E192: TRX 500 | F192: 2008 | G192: TE31E-8310850 | H192: 1HRTE31U884300655
A193: 192 | B193: MINIBUS | C193: AD-363-UL | D193: FORD | E193: TRANSIT BUS 2.2L 460E (CAP. 16 PERS.) | F193: 2018 | G193: UHR5JTS31196 | H193: WF0DXMTTGJTS31196
A194: 193 | B194: MINIBUS | C194: HEM-458 | D194: MERCEDEZ BENZ | E194: BUS (CAP. 16 PERS.) | F194: 2008 | G194: 611982E13 | H194: 8AC9046638A979055
A195: 194 | B195: MOTOCICLETA | C195: 028-JHC | D195: HONDA | E195: XR125 L | F195: 2013 | G195: JC30E-6775813 | H195: 8CHJD19A6DL004550
A196: 195 | B196: MOTOCICLETA | C196: A-140-REJ | D196: BENELLI | E196: TRK 502 | F196: 2021 | G196: BJ269MR-A*08925065* | H196: 8ELB09ANAMB008716
A197: 196 | B197: MOTOCICLETA | C197: A-140-REH | D197: BENELLI | E197: TRK 502 | F197: 2021 | G197: BJ269MR-A*11504546* | H197: 8ELB09ANAMB029437
A198: 197 | B198: MOTOCICLETA | C198: A-140-REI | D198: BENELLI | E198: TRK 502 | F198: 2021 | G198: BJ269MR-A*08935832* | H198: 8ELB09ANAMB020048
A199: 198 | B199: MOTOCICLETA | C199: A-140-REK | D199: BENELLI | E199: TRK 502 | F199: 2021 | G199: BJ269MR-A*08935806* | H199: 8ELB09ANAMB020052
A200: 199 | B200: MOTOCICLETA | C200: A-140-REL | D200: BENELLI | E200: TRK 502 | F200: 2021 | G200: BJ269MR-A*08936136* | H200: 8ELB09ANAMB034293
A201: 200 | B201: MOTOCICLETA | C201: 013-JHC | D201: HONDA | E201: XR 250 TORNADO | F201: 2013 | G201: MD34E-D703414 | H201: 8CHMD3400DL003025
... A514: 513 | B514: MOTOCICLETA | C514: A134PKH | D514: GILERA | E514: SMX 200 | F514: 2021 | G514: AD163FML*M0000084* | H514: 8EGSMX200MNK03026
A515: 514 | B515: MOTOCICLETA | C515: M-001-BXY | D515: KAWASAKI | E515: 650CC | G515: KL650AEA34656 | H515: JKAKLEA147DA34656
A516: 515 | B516: MOTOCICLETA | C516: 228-KQC | D516: HONDA | E516: XR125 L | F516: 2014 | G516: JD21E-2193879 | H516: 8CHJD19A6EL002911
A517: 516 | B517: MVH (CONTEINERS) C/RUEDAS.- | C517: 101 QAL-208 | D517: NO VISIBLE | E517: NO VISIBLE | F517: 2008 | G517: S/MOTOR | H517: NO UBICADO
A518: 517 | B518: TANQUETA 3 | C518: QPT-806 | D518: NO VISIBLE | E518: NO VISIBLE | G518: S/MOTOR | H518: NO UBICADO
A519: 518 | B519: TRAILER GOMON | C519: 101 PIO-390 | D519: MERCURI | E519: SEMI RIGIDO - BIM SR LIGERO 43 - 40HP.- | F519: 2005 | G519: FUERA DE BORDA | H519: SERIE "C" N° AA18B5737CC00
A520: 519 | B520: UTILITARIO | C520: AD-016-LM | D520: FIAT | E520: FIORINO FURGONETA | F520: 2018 | G520: 327A0553238892 | H520: 9BD265524J9099595
A521: 520 | B521: UTILITARIO | C521: HKX-860 | D521: CITROEN | E521: BERLINGO | F521: 2008 | G521: 10DXBE0049260 | H521: 8BCMFWJZF9G503429
A522: 521 | B522: UTILITARIO | C522: HKX-863 | D522: CITROEN | E522: BERLINGO | F522: 2008 | G522: 10DXBE0047228 | H522: 8BCMBWJZF9G555587
A523: 522 | B523: UTILITARIO | C523: HKX-864 | D523: CITROEN | E523: BERLINGO | F523: 2008 | G523: 10DXBE0049749 | H523: 8BCMBWJZF9G504328
A524: 523 | B524: UTILITARIO | C524: HMW-858 | D524: RENAULT | E524: MASTER DCI 120 | F524: 2008 | G524: G9UA724CO41695 | H524: 93YCDDUH59J082362
A525: 524 | B525: UTILITARIO | C525: OOT-964 | D525: FIAT | E525: DUCATO MAXICARGO | F525: 2014 | G525: 7185440 | H525: 93W245G84E2120321
A526: 525 | B526: UTILITARIO | C526: OPX-343 | D526: RENAULT | E526: KANGOO | F526: 2015 | G526: K4MJ730Q153135 | H526: 8A1FC1315FL738957
A527: 526 | B527: UTILITARIO | C527: OPX-344 | D527: RENAULT | E527: KANGOO | F527: 2015 | G527: K4MJ730Q144802 | H527: 8A1FC1315FL498441

Sheet  NotaPedido
A1: NOTA DE PEDIDO | J1: N° | K1: 41/2020
A3: JURISDICCIÓN: | D3: ='Necesidades Trimestrales'!#REF! -> #REF!
A4: SAF: | D4: ='Necesidades Trimestrales'!#REF! -> #REF!
A5: UNIDAD EJECUTORA: | D5: Jefatura de Policía de la Provincia de Catamarca
A6: DEPENDENCIA SOLICITANTE: | D6: Sección Control Patrimonial - Dpto. Logistica (D-4)
A7: PERIODO UTILIZACIÓN: | D7: ='Necesidades Trimestrales'!C6 & "° Trimestre - Año " & 'Necesidades Trimestrales'!C5 -> 4° Trimestre - Año 2021
A8: OBJETO: | D8: Renovacion de Seguro Obligatorio de Responsabilidad Civil del Automotor
A10: Ítem | B10: Codigo Item | C10: DESCRIPCIÓN | H10: Adjunta Detalle Técnico | I10: Unidad Medida | J10: Precio Unitario Estimado | K10: Cantidad Solicitada
A12: 1 | B12: ='Necesidades Trimestrales'!B9 -> 3.5.4-2065.1 | C12: ='Necesidades Trimestrales'!E9 -> SEGURO DE RESPONSABILIDAD; DESCRIPCION: SEGURO DE RESPONSABILIDAD | H12: SI | I12: ='Necesidades Trimestrales'!F9 -> UNIDAD | J12: ='Necesidades Trimestrales'!H9 -> 90297.39 | K12: ='Necesidades Trimestrales'!G9 -> 1
A13: Costo total estimado: | D13: Un Millon Quinientos Diecisiete Mil Cientoo Noventa y Nuene con 57/100 | J13: ='Necesidades Trimestrales'!I9 -> 90297.39

Sheet Autor Gastar
A1: EJERCICIO: | D1: ='Necesidades Trimestrales'!C5 -> 2021 | P1: AUTORIZACION PARA GASTAR
A4: JURISDICCIÓN: | G4: =' NotaPedido'!D3 -> #REF!
A5: SAF: | G5: =' NotaPedido'!D4 -> #REF!
A6: UNIDAD EJECUTORA: | G6: =' NotaPedido'!D5 -> Jefatura de Policía de la Provincia de Catamarca
A7: DEPENDENCIA SOLICITANTE: | G7: =' NotaPedido'!D6 -> Sección Control Patrimonial - Dpto. Logistica (D-4)
A8: AUTORIZACIÓN:
A9: Señor Jefe de Servicio Administrativo Financiero:
A10: ="Autorizo la realización de los trámites correspondientes, a fin de proveer a este Organismo los bienes y/o servicios que se detallan en Nota de Pedido N° " & ' NotaPedido'!K1&", afectando la erogación resultante a los créditos presupuestarios aprobados a favor de esta Unidad Ejecutora, conforme al siguiente detalle:" -> Autorizo la realización de los trámites correspondientes, a fin de proveer a este Organismo los bienes y/o servicios que se detallan en Nota de Pedido N° 41/2020, afectando la erogación resultante a los créditos presupuestarios aprobados a favor de esta Unidad Ejecutora, conforme al siguiente detalle:
A12: IMPUTACIÓN PRESUPUESTARIA
A13: CÓDIGO | O13: DENOMINACIÓN DE LA PARTIDA PRESUPUESTARIA | Q13: IMPORTE
A14: PR | B14: SB | C14: PY | D14: AC | E14: OB | F14: UG | G14: FIN | H14: FUN | I14: I | J14: P | K14: P | L14: SubP | M14: M | N14: FF
A15: 16 | B15: 0 | C15: 0 | D15: 1 | E15: 0 | F15: 10 | G15: 2 | H15: 1 | I15: =LEFT('Necesidades Trimestrales'!D9,1) -> 3 | J15: =MID('Necesidades Trimestrales'!D9,3,1) -> 5 | K15: =RIGHT('Necesidades Trimestrales'!D9,1) -> 4 | L15: 0 | M15: 1 | N15: 1.1 | O15: PRIMAS Y GASTOS DE SEGUROS | Q15: ='Necesidades Trimestrales'!I9 -> 90297.39
A16: TOTAL DE PESOS: | Q16: =SUM(Q15) -> 90297.39
A17: =' NotaPedido'!D13 -> Un Millon Quinientos Diecisiete Mil Cientoo Noventa y Nuene con 57/100
A19: JUSTIFICACIÓN:
A20: Para la Renovaciòn de Seguro Obligatorio de Responsabilidad Civil del Automotor para los vehiculos pertenecientes a la Institucion Policial.-
