Workbook

Sheet SAF 011
A1: 2022
B2: Pedido de Necesidades Trimestrales
A4: JURISDICCION: | C4: 040 - MINISTERIO DE SALUD
A5: SAF N°: | C5: 011 - DIRECCION PROVINCIAL DE ADMINISTRACION - MINISTERIO DE SALUD
A6: EJERCICIO: | C6: 2022
A7: TRIMESTRE: | C7: PRIMERO
A9: ID | B9: CODIGO ITEM | C9: RUBRO DE COMPRA | D9: I.P.P. | E9: DESCRIPCION | F9: UNIDAD DE MEDIDA | G9: SECRETARIA DE ADMINISTRACION | H9: TOTAL S.A. | I9: SMPyPS | J9: TOTAL SMPyPS | K9: DIR. LAB. CENTRAL | L9: TOTAL DE LAB CENTRAL | M9: BCO DE SANGRE | N9: TOTAL BANCO DE SANGRE | O9: APS | P9: TOTAL A.P.S. | Q9: DIR DE CANCER | R9: TOTAL DE DIR DE CANCER | S9: FARMACIA | T9: TOTAL FARMACIA | U9: ODONTOLOGIA | V9: TOTAL DE ODONTOLOG | W9: SAME | X9: TOTAL SAME | Y9: HPTAL MALBRAN | Z9: TOTAL HPTAL MALBRAN | AA9: MATERNIDAD E INFANCIA | AB9: TOTAL MATERNIDAD E INFANCIA | AC9: SASP | AD9: TOTAL SASP | AE9: SALUD Y MEDIO AMBIENTE | AF9: TOTAL SALUD Y MEDIO AMBIENTE | AG9: VECTORES Y ZOONOSIS | AH9: TOTAL DE VECT Y ZOON | AI9: CRONICAS | AJ9: TOTAL CRONICAS | AK9: CUR | AL9: TOTAL CUR | AM9: SPyGS | AN9: TOTAL SPyGS | AO9: SALUD MENTAL | AP9: TOTAL SALUD MENTAL | AQ9: AREAS Y DPAS | AR9: TOTAL DPAS | AS9: EPIDEMIOLOGIA | AT9: TOTAL EPIDEMIOLOGIA | AU9: AREA 1 | AV9: TOTAL AREA 1 | AW9: CANTIDAD TOTAL | AX9: PRECIO UNITARIO ESTIMADO | AY9: IMPORTE TOTAL ESTIMADO | AZ9: ESPECIFICACION TECNICA | BB9: ESPECIFICACION TECNICA PROGRAMACION | BC9: DESCRIPCION | BE9: IPP | BG9: UNIDAD DE MEDIDA | BI9: PRECIO UNITARIO ESTIMADO
A10: 1 | B10: 2.5.2-710.4 | C10: PROD. MEDICO/FARMACEUTICOS/LAB | D10: 252 | E10: AGUA OXIGENADA; CAPACIDAD: 1000 CM3, VOLUMEN: 10, PRESENTACION: ENVASE X 1000 CM3 | F10: BOTELLA | L10: =+K10*AX10 -> 0 | N10: =+M10*AX10 -> 0 | S10: 1000 | T10: =+S10*AX10 -> 128590 | V10: =+U10*AX10 -> 0 | W10: 30 | X10: =+W10*AX10 -> 3857.7 | AW10: =+AQ10+AO10+AM10+AK10+AI10+AG10+AE10+AC10+AA10+Y10+W10+U10+S10+Q10+O10+M10+K10+I10+AS10+G10+AU10 -> 1030 | AX10: 128.59 | AY10: =+AW10*AX10 -> 132447.7 | BC10: AGUA OXIGENADA; CAPACIDAD: 1000 CM3, VOLUMEN: 10, PRESENTACION: ENVASE X 1000 CM3 | BD10: =E10=BC10 -> TRUE | BE10: =+VLOOKUP(E10,'[1]Necesidades Trimestrales'!$H$10:$I$43,2,0) -> 252 | BF10: =BE10=D10 -> TRUE | BG10: =+VLOOKUP(E10,'[1]Necesidades Trimestrales'!$H$10:$K$43,4,0) -> BOTELLA | BH10: =BG10=F10 -> TRUE | BI10: =+VLOOKUP(E10,'[1]Necesidades Trimestrales'!$H$10:$M$43,6,0) -> 128.59 | BJ10: =BI10=AX10 -> TRUE | BK10: =+AW10*AX10-AY10 -> 0
A11: 2 | B11: 2.5.2-711.41 | C11: PROD. MEDICO/FARMACEUTICOS/LAB | D11: 252 | E11: ALCOHOL USO MEDICINAL; PUREZA: 70 %, PRESENTACION: GEL ENVASE X 250 CM3 | F11: UNIDAD | L11: =+K11*AX11 -> 0 | M11: 120 | N11: =+M11*AX11 -> 18960 | T11: =+S11*AX11 -> 0 | V11: =+U11*AX11 -> 0 | X11: =+W11*AX11 -> 0 | AW11: =+AQ11+AO11+AM11+AK11+AI11+AG11+AE11+AC11+AA11+Y11+W11+U11+S11+Q11+O11+M11+K11+I11+AS11+G11+AU11 -> 120 | AX11: 158 | AY11: =+AW11*AX11 -> 18960 | BC11: ALCOHOL USO MEDICINAL; PUREZA: 70 %, PRESENTACION: GEL ENVASE X 250 CM3 | BD11: =E11=BC11 -> TRUE | BE11: =+VLOOKUP(E11,'[1]Necesidades Trimestrales'!$H$10:$I$43,2,0) -> 252 | BF11: =BE11=D11 -> TRUE | BG11: =+VLOOKUP(E11,'[1]Necesidades Trimestrales'!$H$10:$K$43,4,0) -> UNIDAD | BH11: =BG11=F11 -> TRUE | BI11: =+VLOOKUP(E11,'[1]Necesidades Trimestrales'!$H$10:$M$43,6,0) -> 158 | BJ11: =BI11=AX11 -> TRUE | BK11: =+AW11*AX11-AY11 -> 0
A12: 3 | B12: 2.5.2-711.32 | C12: PROD. MEDICO/FARMACEUTICOS/LAB | D12: 252 | E12: ALCOHOL USO MEDICINAL; PUREZA: 96 %, PRESENTACION: ENVASE X 1000 CM3 | F12: BOTELLA | K12: 400 | L12: =+K12*AX12 -> 80400 | N12: =+M12*AX12 -> 0 | T12: =+S12*AX12 -> 0 | V12: =+U12*AX12 -> 0 | X12: =+W12*AX12 -> 0 | AW12: =+AQ12+AO12+AM12+AK12+AI12+AG12+AE12+AC12+AA12+Y12+W12+U12+S12+Q12+O12+M12+K12+I12+AS12+G12+AU12 -> 400 | AX12: 201 | AY12: =+AW12*AX12 -> 80400 | BC12: ALCOHOL USO MEDICINAL; PUREZA: 96 %, PRESENTACION: ENVASE X 1000 CM3 | BD12: =E12=BC12 -> TRUE | BE12: =+VLOOKUP(E12,'[1]Necesidades Trimestrales'!$H$10:$I$43,2,0) -> 252 | BF12: =BE12=D12 -> TRUE | BG12: =+VLOOKUP(E12,'[1]Necesidades Trimestrales'!$H$10:$K$43,4,0) -> BOTELLA | BH12: =BG12=F12 -> TRUE | BI12: =+VLOOKUP(E12,'[1]Necesidades Trimestrales'!$H$10:$M$43,6,0) -> 201 | BJ12: =BI12=AX12 -> TRUE | BK12: =+AW12*AX12-AY12 -> 0
A13: 4 | B13: 2.5.2-711.1 | C13: PROD. MEDICO/FARMACEUTICOS/LAB | D13: 252 | E13: ALCOHOL USO MEDICINAL; PUREZA: 96 %, PRESENTACION: ENVASE X 500 CM3, CAPACIDAD: 500 CM3 | F13: BOTELLA | L13: =+K13*AX13 -> 0 | M13: 300 | N13: =+M13*AX13 -> 32400 | T13: =+S13*AX13 -> 0 | V13: =+U13*AX13 -> 0 | X13: =+W13*AX13 -> 0 | AW13: =+AQ13+AO13+AM13+AK13+AI13+AG13+AE13+AC13+AA13+Y13+W13+U13+S13+Q13+O13+M13+K13+I13+AS13+G13+AU13 -> 300 | AX13: 108 | AY13: =+AW13*AX13 -> 32400 | BC13: ALCOHOL USO MEDICINAL; PUREZA: 96 %, PRESENTACION: ENVASE X 500 CM3, CAPACIDAD: 500 CM3 | BD13: =E13=BC13 -> TRUE | BE13: =+VLOOKUP(E13,'[1]Necesidades Trimestrales'!$H$10:$I$43,2,0) -> 252 | BF13: =BE13=D13 -> TRUE | BG13: =+VLOOKUP(E13,'[1]Necesidades Trimestrales'!$H$10:$K$43,4,0) -> BOTELLA | BH13: =BG13=F13 -> TRUE | BI13: =+VLOOKUP(E13,'[1]Necesidades Trimestrales'!$H$10:$M$43,6,0) -> 108 | BJ13: =BI13=AX13 -> TRUE | BK13: =+AW13*AX13-AY13 -> 0
A14: 5 | B14: 2.5.2-1723.50 | C14: PROD. MEDICO/FARMACEUTICOS/LAB | D14: 252 | E14: ANTISEPTICOS LOCALES P/PERSONA; DROGA GENERICA: IODOPOVIDONA 10%, FORMA FARMACEUTICA: SOLUCION, PRESENTACION: ENVASE X 1 L, TIPO: MONODROGA | F14: BOTELLA | L14: =+K14*AX14 -> 0 | N14: =+M14*AX14 -> 0 | S14: 350 | T14: =+S14*AX14 -> 200550 | V14: =+U14*AX14 -> 0 | W14: 15 | X14: =+W14*AX14 -> 8595 | AW14: =+AQ14+AO14+AM14+AK14+AI14+AG14+AE14+AC14+AA14+Y14+W14+U14+S14+Q14+O14+M14+K14+I14+AS14+G14+AU14 -> 365 | AX14: 573 | AY14: =+AW14*AX14 -> 209145 | AZ14: con valvula atomizadora | BB14: =+VLOOKUP(E14,'[1]Necesidades Trimestrales'!$H$10:$J$43,3,0) -> con valvula atomizadora | BC14: ANTISEPTICOS LOCALES P/PERSONA; DROGA GENERICA: IODOPOVIDONA 10%, FORMA FARMACEUTICA: SOLUCION, PRESENTACION: ENVASE X 1 L, TIPO: MONODROGA | BD14: =E14=BC14 -> TRUE | BE14: =+VLOOKUP(E14,'[1]Necesidades Trimestrales'!$H$10:$I$43,2,0) -> 252 | BF14: =BE14=D14 -> TRUE | BG14: =+VLOOKUP(E14,'[1]Necesidades Trimestrales'!$H$10:$K$43,4,0) -> BOTELLA | BH14: =BG14=F14 -> TRUE | BI14: =+VLOOKUP(E14,'[1]Necesidades Trimestrales'!$H$10:$M$43,6,0) -> 573 | BJ14: =BI14=AX14 -> TRUE | BK14: =+AW14*AX14-AY14 -> 0
A15: 6 | B15: 2.5.2-1723.173 | C15: PROD. MEDICO/FARMACEUTICOS/LAB | D15: 295 | E15: ANTISEPTICOS LOCALES P/PERSONA; TIPO: MONODROGA, DROGA GENERICA: IODOFORMADA AL 10% , FORMA FARMACEUTICA: GASA, PRESENTACION: DE 10X10, 15 UNIDADES POR PACK | F15: CAJA | L15: =+K15*AX15 -> 0 | N15: =+M15*AX15 -> 0 | T15: =+S15*AX15 -> 0 | U15: 50 | V15: =+U15*AX15 -> 47500 | X15: =+W15*AX15 -> 0 | AW15: =+AQ15+AO15+AM15+AK15+AI15+AG15+AE15+AC15+AA15+Y15+W15+U15+S15+Q15+O15+M15+K15+I15+AS15+G15+AU15 -> 50 | AX15: 950 | AY15: =+AW15*AX15 -> 47500 | BC15: ANTISEPTICOS LOCALES P/PERSONA; TIPO: MONODROGA, DROGA GENERICA: IODOFORMADA AL 10% , FORMA FARMACEUTICA: GASA, PRESENTACION: DE 10X10, 15 UNIDADES POR PACK | BD15: =E15=BC15 -> TRUE | BE15: =+VLOOKUP(E15,'[1]Necesidades Trimestrales'!$H$10:$I$43,2,0) -> 295 | BF15: =BE15=D15 -> TRUE | BG15: =+VLOOKUP(E15,'[1]Necesidades Trimestrales'!$H$10:$K$43,4,0) -> CAJA | BH15: =BG15=F15 -> TRUE | BI15: =+VLOOKUP(E15,'[1]Necesidades Trimestrales'!$H$10:$M$43,6,0) -> 950 | BJ15: =BI15=AX15 -> TRUE | BK15: =+AW15*AX15-AY15 -> 0
A16: 7 | B16: 2.5.2-1723.30 | C16: PROD. MEDICO/FARMACEUTICOS/LAB | D16: 252 | E16: ANTISEPTICOS LOCALES P/PERSONA; TIPO: MONODROGA, DROGA GENERICA: IODOPOVIDONA, FORMA FARMACEUTICA: SOLUCION, PRESENTACION: BIDON X 5 L | F16: BIDON | L16: =+K16*AX16 -> 0 | N16: =+M16*AX16 -> 0 | S16: 50 | T16: =+S16*AX16 -> 112500 | V16: =+U16*AX16 -> 0 | X16: =+W16*AX16 -> 0 | AW16: =+AQ16+AO16+AM16+AK16+AI16+AG16+AE16+AC16+AA16+Y16+W16+U16+S16+Q16+O16+M16+K16+I16+AS16+G16+AU16 -> 50 | AX16: 2250 | AY16: =+AW16*AX16 -> 112500 | BC16: ANTISEPTICOS LOCALES P/PERSONA; TIPO: MONODROGA, DROGA GENERICA: IODOPOVIDONA, FORMA FARMACEUTICA: SOLUCION, PRESENTACION: BIDON X 5 L | BD16: =E16=BC16 -> TRUE | BE16: =+VLOOKUP(E16,'[1]Necesidades Trimestrales'!$H$10:$I$43,2,0) -> 252 | BF16: =BE16=D16 -> TRUE | BG16: =+VLOOKUP(E16,'[1]Necesidades Trimestrales'!$H$10:$K$43,4,0) -> BIDON | BH16: =BG16=F16 -> TRUE | BI16: =+VLOOKUP(E16,'[1]Necesidades Trimestrales'!$H$10:$M$43,6,0) -> 2250 | BJ16: =BI16=AX16 -> TRUE | BK16: =+AW16*AX16-AY16 -> 0
A17: 8 | B17: 2.5.2-1723.35 | C17: PROD. MEDICO/FARMACEUTICOS/LAB | D17: 252 | E17: ANTISEPTICOS LOCALES P/PERSONA; TIPO: MONODROGA, DROGA GENERICA: NITROFURAZONA, FORMA FARMACEUTICA: SOLUCION, PRESENTACION: FRASCO X 1 L | F17: BOTELLA | L17: =+K17*AX17 -> 0 | N17: =+M17*AX17 -> 0 | S17: 40 | T17: =+S17*AX17 -> 34360 | V17: =+U17*AX17 -> 0 | X17: =+W17*AX17 -> 0 | AW17: =+AQ17+AO17+AM17+AK17+AI17+AG17+AE17+AC17+AA17+Y17+W17+U17+S17+Q17+O17+M17+K17+I17+AS17+G17+AU17 -> 40 | AX17: 859 | AY17: =+AW17*AX17 -> 34360 | BC17: ANTISEPTICOS LOCALES P/PERSONA; TIPO: MONODROGA, DROGA GENERICA: NITROFURAZONA, FORMA FARMACEUTICA: SOLUCION, PRESENTACION: FRASCO X 1 L | BD17: =E17=BC17 -> TRUE | BE17: =+VLOOKUP(E17,'[1]Necesidades Trimestrales'!$H$10:$I$43,2,0) -> 252 | BF17: =BE17=D17 -> TRUE | BG17: =+VLOOKUP(E17,'[1]Necesidades Trimestrales'!$H$10:$K$43,4,0) -> BOTELLA | BH17: =BG17=F17 -> TRUE | BI17: =+VLOOKUP(E17,'[1]Necesidades Trimestrales'!$H$10:$M$43,6,0) -> 859 | BJ17: =BI17=AX17 -> TRUE | BK17: =+AW17*AX17-AY17 -> 0
A18: 9 | B18: 2.9.1-6956.122 | C18: ELEMENTOS DE LIMPIEZA | D18: 252 | E18: ARTICULOS DE TOCADOR; TIPO: JABON LIQUIDO HIPOALERGENICO, PRESENTACION: ENVASE X 800 ML BAG IN BOX | F18: BAG IN BOX | L18: =+K18*AX18 -> 0 | N18: =+M18*AX18 -> 0 | S18: 100 | T18: =+S18*AX18 -> 115000 | V18: =+U18*AX18 -> 0 | X18: =+W18*AX18 -> 0 | AW18: =+AQ18+AO18+AM18+AK18+AI18+AG18+AE18+AC18+AA18+Y18+W18+U18+S18+Q18+O18+M18+K18+I18+AS18+G18+AU18 -> 100 | AX18: 1150 | AY18: =+AW18*AX18 -> 115000 | AZ18: Jabón Líquido hipoalergenico. Ph Dérmico. No contiene cloruro de sodio, ni parabenos. Envase BAG IN BOX por 800 ml.Tipo JL4 ADOX. | BB18: =+VLOOKUP(E18,'[1]Necesidades Trimestrales'!$H$10:$J$43,3,0) -> Jabón Líquido hipoalergenico. Ph Dérmico. No contiene cloruro de sodio, ni parabenos. Envase BAG IN BOX por 800 ml.Tipo JL4 ADOX. | BC18: ARTICULOS DE TOCADOR; TIPO: JABON LIQUIDO HIPOALERGENICO, PRESENTACION: ENVASE X 800 ML BAG IN BOX | BD18: =E18=BC18 -> TRUE | BE18: =+VLOOKUP(E18,'[1]Necesidades Trimestrales'!$H$10:$I$43,2,0) -> 252 | BF18: =BE18=D18 -> TRUE | BG18: =+VLOOKUP(E18,'[1]Necesidades Trimestrales'!$H$10:$K$43,4,0) -> BAG IN BOX | BH18: =BG18=F18 -> TRUE | BI18: =+VLOOKUP(E18,'[1]Necesidades Trimestrales'!$H$10:$M$43,6,0) -> 1150 | BJ18: =BI18=AX18 -> TRUE | BK18: =+AW18*AX18-AY18 -> 0
A19: 10 | B19: 2.5.1-9065.27 | C19: QUIMICOS | D19: 251 | E19: DESINFECTANTES Y DETERGENTES; PRINCIPIO ACTIVO: AMONIO CUATERNARIO, CALIDAD: COMERCIAL, CONCENTRACION/PUREZA: 99 %, PRESENTACION: ENVASE X 5 L | F19: BIDON | L19: =+K19*AX19 -> 0 | N19: =+M19*AX19 -> 0 | T19: =+S19*AX19 -> 0 | U19: 50 | V19: =+U19*AX19 -> 461460 | X19: =+W19*AX19 -> 0 | AW19: =+AQ19+AO19+AM19+AK19+AI19+AG19+AE19+AC19+AA19+Y19+W19+U19+S19+Q19+O19+M19+K19+I19+AS19+G19+AU19 -> 50 | AX19: 9229.2 | AY19: =+AW19*AX19 -> 461460 | AZ19: USO HOSPITALARIO. Limpiador para areas criticas en base a amonios cuaternarios de 4TA Generacion.Dilucion 2,5 ml/ litro .Aprobacion ANMAT | BB19: =+VLOOKUP(E19,'[1]Necesidades Trimestrales'!$H$10:$J$43,3,0) -> USO HOSPITALARIO. Limpiador para areas criticas en base a amonios cuaternarios de 4TA Generacion.Dilucion 2,5 ml/ litro .Aprobacion ANMAT | BC19: DESINFECTANTES Y DETERGENTES; PRINCIPIO ACTIVO: AMONIO CUATERNARIO, CALIDAD: COMERCIAL, CONCENTRACION/PUREZA: 99 %, PRESENTACION: ENVASE X 5 L | BD19: =E19=BC19 -> TRUE | BE19: =+VLOOKUP(E19,'[1]Necesidades Trimestrales'!$H$10:$I$43,2,0) -> 251 | BF19: =BE19=D19 -> TRUE | BG19: =+VLOOKUP(E19,'[1]Necesidades Trimestrales'!$H$10:$K$43,4,0) -> BIDON | BH19: =BG19=F19 -> TRUE | BI19: =+VLOOKUP(E19,'[1]Necesidades Trimestrales'!$H$10:$M$43,6,0) -> 9229.2 | BJ19: =BI19=AX19 -> TRUE | BK19: =+AW19*AX19-AY19 -> 0
A20: 11 | B20: 2.5.1-9065.53 | C20: QUIMICOS | D20: 251 | E20: DESINFECTANTES Y DETERGENTES; PRINCIPIO ACTIVO: GLUTARALDEHIDO CON SULFACTANTE, CALIDAD: BIOLOGIA MOLECULAR, CONCENTRACION/PUREZA: 2 %, PRESENTACION: ENVASE X 4 L | F20: BIDON | L20: =+K20*AX20 -> 0 | N20: =+M20*AX20 -> 0 | S20: 50 | T20: =+S20*AX20 -> 84000 | V20: =+U20*AX20 -> 0 | X20: =+W20*AX20 -> 0 | AW20: =+AQ20+AO20+AM20+AK20+AI20+AG20+AE20+AC20+AA20+Y20+W20+U20+S20+Q20+O20+M20+K20+I20+AS20+G20+AU20 -> 50 | AX20: 1680 | AY20: =+AW20*AX20 -> 84000 | BC20: DESINFECTANTES Y DETERGENTES; PRINCIPIO ACTIVO: GLUTARALDEHIDO CON SULFACTANTE, CALIDAD: BIOLOGIA MOLECULAR, CONCENTRACION/PUREZA: 2 %, PRESENTACION: ENVASE X 4 L | BD20: =E20=BC20 -> TRUE | BE20: =+VLOOKUP(E20,'[1]Necesidades Trimestrales'!$H$10:$I$43,2,0) -> 251 | BF20: =BE20=D20 -> TRUE | BG20: =+VLOOKUP(E20,'[1]Necesidades Trimestrales'!$H$10:$K$43,4,0) -> BIDON | BH20: =BG20=F20 -> TRUE | BI20: =+VLOOKUP(E20,'[1]Necesidades Trimestrales'!$H$10:$M$43,6,0) -> 1680 | BJ20: =BI20=AX20 -> TRUE | BK20: =+AW20*AX20-AY20 -> 0
A21: 12 | B21: 2.5.2-1726.492 | C21: PROD. MEDICO/FARMACEUTICOS/LAB | D21: 251 | E21: SOLUCIONES P/MEDICINA; TIPO: FORMOL AL 40 %, PRESENTACION: ENVASE X 1 L | F21: BOTELLA | L21: =+K21*AX21 -> 0 | N21: =+M21*AX21 -> 0 | S21: 10 | T21: =+S21*AX21 -> 6610 | V21: =+U21*AX21 -> 0 | X21: =+W21*AX21 -> 0 | AW21: =+AQ21+AO21+AM21+AK21+AI21+AG21+AE21+AC21+AA21+Y21+W21+U21+S21+Q21+O21+M21+K21+I21+AS21+G21+AU21 -> 10 | AX21: 661 | AY21: =+AW21*AX21 -> 6610 | BC21: SOLUCIONES P/MEDICINA; TIPO: FORMOL AL 40 %, PRESENTACION: ENVASE X 1 L | BD21: =E21=BC21 -> TRUE | BE21: =+VLOOKUP(E21,'[1]Necesidades Trimestrales'!$H$10:$I$43,2,0) -> 251 | BF21: =BE21=D21 -> TRUE | BG21: =+VLOOKUP(E21,'[1]Necesidades Trimestrales'!$H$10:$K$43,4,0) -> BOTELLA | BH21: =BG21=F21 -> TRUE | BI21: =+VLOOKUP(E21,'[1]Necesidades Trimestrales'!$H$10:$M$43,6,0) -> 661 | BJ21: =BI21=AX21 -> TRUE | BK21: =+AW21*AX21-AY21 -> 0
E22: TOTAL RUBRO ANTISEPTICOS Y DESINFECTANTES | L22: =SUM(L10:L21) -> 80400 | N22: =SUM(N10:N21) -> 51360 | T22: =SUM(T10:T21) -> 681610 | V22: =SUM(V10:V21) -> 508960 | X22: =SUM(X10:X21) -> 12452.7 | AY22: =SUM(AY10:AY21) -> 1334782.7
C24: DETALLE TECNICO Y ESPECIFICACIONES ITEMS 1 AL 12 | D24: ANEXO 1-Para oferentes de la Provincia de Catamarca deberán presentar Habilitación Provincial para comercializar el producto que cotizan. 2-Para el resto de oferentes deberán presentar Certificado de Inscripción de ANMAT vigente al momento de la oferta, el mismo deberá ser correspondiente al objeto de la contratación y de encontrarse vencido adjuntar la solicitud de renovación. 3-No se aceptarán ofertas de productos no registrados y autorizada su venta por ANMAT. Se deberá especificar en cada ítem de la propuesta, marca y número de certificado otorgado por dicho ente regulador. 4-Los productos deberán tener un vencimiento posterior a doce (12) meses a partir de la fecha de su recepción.
C26: Plazos de entrega | D26: veinte (20) dias habiles
C28: Lugar de Entrega: | D28: DIR. PROV. DE FARMACIA E INSUMOS - CHACABUCO N° 169 - en el horario de 8:00hs a 12:00hs de lunes a viernes
C30: Calidad Minima esperada
C32: Mantenimiento | D32: cuarenta y cinco (45) días
C33: Especificidades Item N° 5:
C34: Descripción técnica: con valvula atomizadora
C36: Especificidades Item N° 9:
C37: Descripción técnica: Jabón Líquido hipoalergenico. Ph Dérmico. No contiene cloruro de sodio, ni parabenos. Envase BAG IN BOX por 800 ml.Tipo JL4 ADOX.
C39: Especificidades Item N° 10:
C40: Descripción técnica: USO HOSPITALARIO. Limpiador para areas criticas en base a amonios cuaternarios de 4TA Generacion.Dilucion 2,5 ml/ litro .Aprobacion ANMAT

Sheet NP FARMACIA
A1: NOTA DE PEDIDO | J1: N° | K1: 12/2022
A3: JURISDICCIÓN: | D3: ='SAF 011'!C4 -> 040 - MINISTERIO DE SALUD
A4: SAF: | D4: ='SAF 011'!C5 -> 011 - DIRECCION PROVINCIAL DE ADMINISTRACION - MINISTERIO DE SALUD
A5: UNIDAD EJECUTORA: | D5: DIRECCION PROVINCIAL DE FARMACIA E INSUMOS
A6: DEPENDENCIA SOLICITANTE: | D6: DIRECCION PROVINCIAL DE FARMACIA E INSUMOS
A7: PERIODO UTILIZACIÓN: | D7: SEMESTRAL
A8: OBJETO: | D8: ADQUISICION DEL RUBRO ANTISEPTICOS Y DESINFECTANTES
A10: Ítem | B10: Codigo Item | C10: DESCRIPCIÓN | H10: Adjunta Detalle Técnico | I10: Unidad Medida | J10: Precio Unitario Estimado | K10: Cantidad Solicitada
A12: 1 | B12: ='SAF 011'!B10 -> 2.5.2-710.4 | C12: ='SAF 011'!E10 -> AGUA OXIGENADA; CAPACIDAD: 1000 CM3, VOLUMEN: 10, PRESENTACION: ENVASE X 1000 CM3 | H12: SI | I12: ='SAF 011'!F10 -> BOTELLA | J12: ='SAF 011'!AX10 -> 128.59 | K12: ='SAF 011'!S10 -> 1000 | L12: 252 | M12: =B12='SAF 011'!B10 -> TRUE | N12: =+J12*K12 -> 128590 | O12: =C12='SAF 011'!E10 -> TRUE
A13: 2 | B13: ='SAF 011'!B14 -> 2.5.2-1723.50 | C13: ='SAF 011'!E14 -> ANTISEPTICOS LOCALES P/PERSONA; DROGA GENERICA: IODOPOVIDONA 10%, FORMA FARMACEUTICA: SOLUCION, PRESENTACION: ENVASE X 1 L, TIPO: MONODROGA | H13: SI | I13: ='SAF 011'!F14 -> BOTELLA | J13: ='SAF 011'!AX14 -> 573 | K13: ='SAF 011'!S14 -> 350 | L13: 252 | M13: =B13='SAF 011'!B14 -> TRUE | N13: =+J13*K13 -> 200550 | O13: =C13='SAF 011'!E14 -> TRUE
A14: 3 | B14: ='SAF 011'!B16 -> 2.5.2-1723.30 | C14: ='SAF 011'!E16 -> ANTISEPTICOS LOCALES P/PERSONA; TIPO: MONODROGA, DROGA GENERICA: IODOPOVIDONA, FORMA FARMACEUTICA: SOLUCION, PRESENTACION: BIDON X 5 L | H14: SI | I14: ='SAF 011'!F16 -> BIDON | J14: ='SAF 011'!AX16 -> 2250 | K14: ='SAF 011'!S16 -> 50 | L14: 252 | M14: =B14='SAF 011'!B16 -> TRUE | N14: =+J14*K14 -> 112500 | O14: =C14='SAF 011'!E16 -> TRUE
A15: 4 | B15: ='SAF 011'!B17 -> 2.5.2-1723.35 | C15: ='SAF 011'!E17 -> ANTISEPTICOS LOCALES P/PERSONA; TIPO: MONODROGA, DROGA GENERICA: NITROFURAZONA, FORMA FARMACEUTICA: SOLUCION, PRESENTACION: FRASCO X 1 L | H15: SI | I15: ='SAF 011'!F17 -> BOTELLA | J15: ='SAF 011'!AX17 -> 859 | K15: ='SAF 011'!S17 -> 40 | L15: 252 | M15: =B15='SAF 011'!B17 -> TRUE | N15: =+J15*K15 -> 34360 | O15: =C15='SAF 011'!E17 -> TRUE
A16: 5 | B16: ='SAF 011'!B18 -> 2.9.1-6956.122 | C16: ='SAF 011'!E18 -> ARTICULOS DE TOCADOR; TIPO: JABON LIQUIDO HIPOALERGENICO, PRESENTACION: ENVASE X 800 ML BAG IN BOX | H16: SI | I16: ='SAF 011'!F18 -> BAG IN BOX | J16: ='SAF 011'!AX18 -> 1150 | K16: ='SAF 011'!S18 -> 100 | L16: 252 | M16: =B16='SAF 011'!B18 -> TRUE | N16: =+J16*K16 -> 115000 | O16: =C16='SAF 011'!E18 -> TRUE
A17: 6 | B17: ='SAF 011'!B20 -> 2.5.1-9065.53 | C17: ='SAF 011'!E20 -> DESINFECTANTES Y DETERGENTES; PRINCIPIO ACTIVO: GLUTARALDEHIDO CON SULFACTANTE, CALIDAD: BIOLOGIA MOLECULAR, CONCENTRACION/PUREZA: 2 %, PRESENTACION: ENVASE X 4 L | H17: SI | I17: ='SAF 011'!F20 -> BIDON | J17: ='SAF 011'!AX20 -> 1680 | K17: ='SAF 011'!S20 -> 50 | L17: 251 | M17: =B17='SAF 011'!B20 -> TRUE | N17: =+J17*K17 -> 84000 | O17: =C17='SAF 011'!E20 -> TRUE
A18: 7 | B18: ='SAF 011'!B21 -> 2.5.2-1726.492 | C18: ='SAF 011'!E21 -> SOLUCIONES P/MEDICINA; TIPO: FORMOL AL 40 %, PRESENTACION: ENVASE X 1 L | H18: SI | I18: ='SAF 011'!F21 -> BOTELLA | J18: ='SAF 011'!AX21 -> 661 | K18: ='SAF 011'!S21 -> 10 | L18: 251 | M18: =B18='SAF 011'!B21 -> TRUE | N18: =+J18*K18 -> 6610 | O18: =C18='SAF 011'!E21 -> TRUE
A20: Costo total estimado: SEISCIENTOS OCHENTA Y UN MIL SEISCIENTOS DIEZ CON 00/100.- | J20: =+N20 -> 681610 | N20: =SUM(N12:N19) -> 681610
K22: 252 | L22: =+J12*K12+J13*K13+J14*K14+J15*K15+J16*K16 -> 591000 | M22: =+L22+80400+51360 -> 722760 | N22: =+N20-N16-N17 -> 482610
K23: 251 | L23: =+J17*K17+J18*K18 -> 90610 | M23: =+L23 -> 90610
M24: =+M22+M23 -> 813370
M25: =+M24-681610-80400-51360 -> 0

Sheet NP LABORATORIO
A1: NOTA DE PEDIDO | J1: N° | K1: 02/2022
A3: JURISDICCIÓN: | D3: ='SAF 011'!C4 -> 040 - MINISTERIO DE SALUD
A4: SAF: | D4: ='SAF 011'!C5 -> 011 - DIRECCION PROVINCIAL DE ADMINISTRACION - MINISTERIO DE SALUD
A5: UNIDAD EJECUTORA: | D5: DIRECCION PROVINCIAL DE LABORATORIO
A6: DEPENDENCIA SOLICITANTE: | D6: DIRECCION PROVINCIAL DE LABORATORIO
A7: PERIODO UTILIZACIÓN: | D7: SEMESTRAL
A8: OBJETO: | D8: ADQUISICION DEL RUBRO ANTISEPTICOS Y DESINFECTANTES
A10: Ítem | B10: Codigo Item | C10: DESCRIPCIÓN | H10: Adjunta Detalle Técnico | I10: Unidad Medida | J10: Precio Unitario Estimado | K10: Cantidad Solicitada
A12: 1 | B12: ='SAF 011'!B12 -> 2.5.2-711.32 | C12: ='SAF 011'!E12 -> ALCOHOL USO MEDICINAL; PUREZA: 96 %, PRESENTACION: ENVASE X 1000 CM3 | H12: SI | I12: ='SAF 011'!F12 -> BOTELLA | J12: ='SAF 011'!AX12 -> 201 | K12: ='SAF 011'!K12 -> 400 | L12: 252 | M12: =B12='SAF 011'!B12 -> TRUE | N12: =+J12*K12 -> 80400 | O12: =C12='SAF 011'!E12 -> TRUE
A14: Costo total estimado: OCHENTA MIL CUATROCIENTOS CON 00/100.- | J14: =+N14 -> 80400 | N14: =SUM(N12:N13) -> 80400
K16: =+J12*K12 -> 80400

Sheet NP BANCO DE SANGRE
A1: NOTA DE PEDIDO | J1: N° | K1: 03/2022
A3: JURISDICCIÓN: | D3: ='SAF 011'!C4 -> 040 - MINISTERIO DE SALUD
A4: SAF: | D4: ='SAF 011'!C5 -> 011 - DIRECCION PROVINCIAL DE ADMINISTRACION - MINISTERIO DE SALUD
A5: UNIDAD EJECUTORA: | D5: DIRECCION PROVINCIAL BANCO DE SANGRE
A6: DEPENDENCIA SOLICITANTE: | D6: DIRECCION PROVINCIAL BANCO DE SANGRE
A7: PERIODO UTILIZACIÓN: | D7: SEMESTRAL
A8: OBJETO: | D8: ADQUISICION DEL RUBRO ANTISEPTICOS Y DESINFECTANTES
A10: Ítem | B10: Codigo Item | C10: DESCRIPCIÓN | H10: Adjunta Detalle Técnico | I10: Unidad Medida | J10: Precio Unitario Estimado | K10: Cantidad Solicitada
A12: 1 | B12: ='SAF 011'!B11 -> 2.5.2-711.41 | C12: ='SAF 011'!E11 -> ALCOHOL USO MEDICINAL; PUREZA: 70 %, PRESENTACION: GEL ENVASE X 250 CM3 | H12: SI | I12: ='SAF 011'!F11 -> UNIDAD | J12: ='SAF 011'!AX11 -> 158 | K12: ='SAF 011'!M11 -> 120 | L12: 252 | M12: ='SAF 011'!B11=B12 -> TRUE | N12: =+J12*K12 -> 18960 | O12: =C12='SAF 011'!E11 -> TRUE
A13: 2 | B13: ='SAF 011'!B13 -> 2.5.2-711.1 | C13: ='SAF 011'!E13 -> ALCOHOL USO MEDICINAL; PUREZA: 96 %, PRESENTACION: ENVASE X 500 CM3, CAPACIDAD: 500 CM3 | H13: SI | I13: ='SAF 011'!F13 -> BOTELLA | J13: ='SAF 011'!AX13 -> 108 | K13: ='SAF 011'!M13 -> 300 | L13: 252 | M13: =B13='SAF 011'!B13 -> TRUE | N13: =+J13*K13 -> 32400 | O13: ='SAF 011'!E13=C13 -> TRUE
A15: Costo total estimado: CINCUENTA Y UN MIL TRESCIENTOS SESENTA CON 00/100.- | J15: =+N15 -> 51360 | N15: =SUM(N12:N14) -> 51360
J17: =+J12*K12+J13*K13 -> 51360

Sheet APG FARMACIA
A1: EJERCICIO: | D1: 2022 | P1: AUTORIZACION PARA GASTAR
A4: JURISDICCIÓN: | G4: ='NP FARMACIA'!D3 -> 040 - MINISTERIO DE SALUD
A5: SAF: | G5: ='NP FARMACIA'!D4 -> 011 - DIRECCION PROVINCIAL DE ADMINISTRACION - MINISTERIO DE SALUD
A6: UNIDAD EJECUTORA: | G6: ='NP FARMACIA'!D5 -> DIRECCION PROVINCIAL DE FARMACIA E INSUMOS
A7: DEPENDENCIA SOLICITANTE: | G7: ='NP FARMACIA'!D6 -> DIRECCION PROVINCIAL DE FARMACIA E INSUMOS
A8: AUTORIZACIÓN:
A9: Señor Director de Administración o Titular del Servicio Administrativo Financiero:
A10: Autorizo la realización de los trámites correspondientes, a fin de proveer a este Organismo los bienes que se detallan en Nota de Pedido N° D.P.F.e I. 12/2022 - D.P.L. 02/2022 - D.P.B.S. 03/2022 afectando la erogación resultante a los créditos presupuestarios aprobados a favor de esta Unidad Ejecutora, conforme al siguiente detalle:
A12: IMPUTACIÓN PRESUPUESTARIA
A13: CÓDIGO | O13: DENOMINACIÓN DE LA PARTIDA PRESUPUESTARIA | Q13: IMPORTE
A14: PR | B14: SB | C14: PY | D14: AC | E14: OB | F14: UG | G14: FIN | H14: FUN | I14: I | J14: P | K14: P | L14: SubP | M14: M | N14: FF
A15: 30 | D15: 1 | F15: 4901 | G15: 3 | H15: 1 | I15: 2 | J15: 5 | K15: 1 | M15: 1 | N15: 1.1 | O15: COMPUESTOS QUIMICOS | Q15: =+'NP FARMACIA'!L23 -> 90610
A16: 30 | D16: 1 | F16: 4901 | G16: 3 | H16: 1 | I16: 2 | J16: 5 | K16: 2 | M16: 1 | N16: 1.1 | O16: PRODUCTOS FARMACEUTICOS Y MEDICINALES | Q16: =+'NP FARMACIA'!L22+'NP LABORATORIO'!K16+'NP BANCO DE SANGRE'!J17 -> 722760
A38: TOTAL DE PESOS: OCHOCIENTOS TRECE MIL TRESCIENTOS SETENTA CON 00/100.- | Q38: =SUM(Q15:Q37) -> 813370
A40: JUSTIFICACIÓN:
A41: ='NP FARMACIA'!D8 -> ADQUISICION DEL RUBRO ANTISEPTICOS Y DESINFECTANTES

Sheet NP ODONTOLOGIA
A1: NOTA DE PEDIDO | J1: N° | K1: 02/2022
A3: JURISDICCIÓN: | D3: ='SAF 011'!C4 -> 040 - MINISTERIO DE SALUD
A4: SAF: | D4: ='SAF 011'!C5 -> 011 - DIRECCION PROVINCIAL DE ADMINISTRACION - MINISTERIO DE SALUD
A5: UNIDAD EJECUTORA: | D5: DIRECCION PROVINCIAL DE ODONTOLOGIA
A6: DEPENDENCIA SOLICITANTE: | D6: DIRECCION PROVINCIAL DE ODONTOLOGIA
A7: PERIODO UTILIZACIÓN: | D7: SEMESTRAL
A8: OBJETO: | D8: ADQUISICION DEL RUBRO ANTISEPTICOS Y DESINFECTANTES
A10: Ítem | B10: Codigo Item | C10: DESCRIPCIÓN | H10: Adjunta Detalle Técnico | I10: Unidad Medida | J10: Precio Unitario Estimado | K10: Cantidad Solicitada
A12: 1 | B12: ='SAF 011'!B15 -> 2.5.2-1723.173 | C12: ='SAF 011'!E15 -> ANTISEPTICOS LOCALES P/PERSONA; TIPO: MONODROGA, DROGA GENERICA: IODOFORMADA AL 10% , FORMA FARMACEUTICA: GASA, PRESENTACION: DE 10X10, 15 UNIDADES POR PACK | H12: SI | I12: ='SAF 011'!F15 -> CAJA | J12: ='SAF 011'!AX15 -> 950 | K12: ='SAF 011'!U15 -> 50 | L12: 295 | M12: =B12='SAF 011'!B15 -> TRUE | N12: =+J12*K12 -> 47500 | O12: ='SAF 011'!E15=C12 -> TRUE
A13: 2 | B13: ='SAF 011'!B19 -> 2.5.1-9065.27 | C13: ='SAF 011'!E19 -> DESINFECTANTES Y DETERGENTES; PRINCIPIO ACTIVO: AMONIO CUATERNARIO, CALIDAD: COMERCIAL, CONCENTRACION/PUREZA: 99 %, PRESENTACION: ENVASE X 5 L | H13: SI | I13: ='SAF 011'!F19 -> BIDON | J13: ='SAF 011'!AX19 -> 9229.2 | K13: ='SAF 011'!U19 -> 50 | L13: 251 | M13: ='SAF 011'!B19=B13 -> TRUE | N13: =+J13*K13 -> 461460 | O13: =C13='SAF 011'!E19 -> TRUE
A15: Costo total estimado: QUINIENTOS OCHO MIL NOVECIENTOS SESENTA CON 00/100.- | J15: =+N15 -> 508960 | N15: =SUM(N12:N14) -> 508960
K18: =+K12*J12 -> 47500
K19: =+J13*K13 -> 461460

Sheet APG ODONTOLOGIA
A1: EJERCICIO: | D1: 2022 | P1: AUTORIZACION PARA GASTAR
A4: JURISDICCIÓN: | G4: ='NP ODONTOLOGIA'!D3 -> 040 - MINISTERIO DE SALUD
A5: SAF: | G5: ='NP ODONTOLOGIA'!D4 -> 011 - DIRECCION PROVINCIAL DE ADMINISTRACION - MINISTERIO DE SALUD
A6: UNIDAD EJECUTORA: | G6: ='NP ODONTOLOGIA'!D5 -> DIRECCION PROVINCIAL DE ODONTOLOGIA
A7: DEPENDENCIA SOLICITANTE: | G7: ='NP ODONTOLOGIA'!D6 -> DIRECCION PROVINCIAL DE ODONTOLOGIA
A8: AUTORIZACIÓN:
A9: Señor Director de Administración o Titular del Servicio Administrativo Financiero:
A10: Autorizo la realización de los trámites correspondientes, a fin de proveer a este Organismo los bienes que se detallan en Nota de Pedido N° 02/2022 afectando la erogación resultante a los créditos presupuestarios aprobados a favor de esta Unidad Ejecutora, conforme al siguiente detalle:
A12: IMPUTACIÓN PRESUPUESTARIA
A13: CÓDIGO | O13: DENOMINACIÓN DE LA PARTIDA PRESUPUESTARIA | Q13: IMPORTE
A14: PR | B14: SB | C14: PY | D14: AC | E14: OB | F14: UG | G14: FIN | H14: FUN | I14: I | J14: P | K14: P | L14: SubP | M14: M | N14: FF
A15: 29 | D15: 1 | F15: 4901 | G15: 3 | H15: 1 | I15: 2 | J15: 5 | K15: 1 | M15: 1 | N15: 1.1 | O15: COMPUESTOS QUIMICOS | Q15: ='NP ODONTOLOGIA'!N13 -> 461460
A16: 29 | D16: 1 | F16: 4901 | G16: 3 | H16: 1 | I16: 2 | J16: 9 | K16: 5 | M16: 1 | N16: 1.1 | O16: UTILES MENORES MEDICOS, QUIRURGICOS Y DE LABORATORIO | Q16: ='NP ODONTOLOGIA'!N12 -> 47500
A38: TOTAL DE PESOS: QUINIENTOS OCHO MIL NOVECIENTOS SESENTA CON 00/100.- | Q38: =SUM(Q15:Q37) -> 508960
A40: JUSTIFICACIÓN:
A41: ='NP ODONTOLOGIA'!D8 -> ADQUISICION DEL RUBRO ANTISEPTICOS Y DESINFECTANTES

Sheet NP SAME
A1: NOTA DE PEDIDO | J1: N° | K1: 03/2022
A3: JURISDICCIÓN: | D3: ='SAF 011'!C4 -> 040 - MINISTERIO DE SALUD
A4: SAF: | D4: ='SAF 011'!C5 -> 011 - DIRECCION PROVINCIAL DE ADMINISTRACION - MINISTERIO DE SALUD
A5: UNIDAD EJECUTORA: | D5: DIRECCION PROVINCIAL SISTEMA DE ATENCION MEDICA DE EMERGENCIA
A6: DEPENDENCIA SOLICITANTE: | D6: DIRECCION PROVINCIAL SISTEMA DE ATENCION MEDICA DE EMERGENCIA
A7: PERIODO UTILIZACIÓN: | D7: SEMESTRAL
A8: OBJETO: | D8: ADQUISICION DEL RUBRO ANTISEPTICOS Y DESINFECTANTES
A10: Ítem | B10: Codigo Item | C10: DESCRIPCIÓN | H10: Adjunta Detalle Técnico | I10: Unidad Medida | J10: Precio Unitario Estimado | K10: Cantidad Solicitada
A12: 1 | B12: ='SAF 011'!B10 -> 2.5.2-710.4 | C12: ='SAF 011'!E10 -> AGUA OXIGENADA; CAPACIDAD: 1000 CM3, VOLUMEN: 10, PRESENTACION: ENVASE X 1000 CM3 | H12: SI | I12: ='SAF 011'!F10 -> BOTELLA | J12: ='SAF 011'!AX10 -> 128.59 | K12: ='SAF 011'!W10 -> 30 | L12: 252 | M12: =+J12*K12 -> 3857.7
A13: 2 | B13: ='SAF 011'!B14 -> 2.5.2-1723.50 | C13: ='SAF 011'!E14 -> ANTISEPTICOS LOCALES P/PERSONA; DROGA GENERICA: IODOPOVIDONA 10%, FORMA FARMACEUTICA: SOLUCION, PRESENTACION: ENVASE X 1 L, TIPO: MONODROGA | H13: SI | I13: ='SAF 011'!F14 -> BOTELLA | J13: ='SAF 011'!AX14 -> 573 | K13: ='SAF 011'!W14 -> 15 | L13: 252 | M13: =+J13*K13 -> 8595
A15: Costo total estimado: DOCE MIL CUATROCIENTOS CINCUENTA Y DOS CON 70/100.- | J15: =+M15 -> 12452.7 | M15: =SUM(M12:M14) -> 12452.7

Sheet APG SAME
A1: EJERCICIO: | D1: 2022 | P1: AUTORIZACION PARA GASTAR
A4: JURISDICCIÓN: | G4: ='NP SAME'!D3 -> 040 - MINISTERIO DE SALUD
A5: SAF: | G5: ='NP SAME'!D4 -> 011 - DIRECCION PROVINCIAL DE ADMINISTRACION - MINISTERIO DE SALUD
A6: UNIDAD EJECUTORA: | G6: ='NP SAME'!D5 -> DIRECCION PROVINCIAL SISTEMA DE ATENCION MEDICA DE EMERGENCIA
A7: DEPENDENCIA SOLICITANTE: | G7: ='NP SAME'!D6 -> DIRECCION PROVINCIAL SISTEMA DE ATENCION MEDICA DE EMERGENCIA
A8: AUTORIZACIÓN:
A9: Señor Director de Administración o Titular del Servicio Administrativo Financiero:
A10: Autorizo la realización de los trámites correspondientes, a fin de proveer a este Organismo los bienes que se detallan en Nota de Pedido N° 03/2022 afectando la erogación resultante a los créditos presupuestarios aprobados a favor de esta Unidad Ejecutora, conforme al siguiente detalle:
A12: IMPUTACIÓN PRESUPUESTARIA
A13: CÓDIGO | O13: DENOMINACIÓN DE LA PARTIDA PRESUPUESTARIA | Q13: IMPORTE
A14: PR | B14: SB | C14: PY | D14: AC | E14: OB | F14: UG | G14: FIN | H14: FUN | I14: I | J14: P | K14: P | L14: SubP | M14: M | N14: FF
A15: 31 | D15: 1 | F15: 4901 | G15: 3 | H15: 1 | I15: 2 | J15: 5 | K15: 2 | M15: 1 | N15: 1.1 | O15: PRODUCTOS FARMACEUTICOS Y MEDICINALES | Q15: ='NP SAME'!M15 -> 12452.7
A37: TOTAL DE PESOS: DOCE MIL CUATROCIENTOS CINCUENTA Y DOS CON 70/100.- | Q37: =SUM(Q15:Q36) -> 12452.7
A39: JUSTIFICACIÓN:
A40: ='NP SAME'!D8 -> ADQUISICION DEL RUBRO ANTISEPTICOS Y DESINFECTANTES
