Workbook

Sheet Necesidades Trimestrales
B2: Pedido de Necesidades Trimestrales
A4: JURISDICCION: | C4: 40 - MINISTERIO DE SALUD
A5: SAF N°: | C5: 024 - Hospital Interzonal de Niños
A6: EJERCICIO: | C6: 2022
A7: TRIMESTRE: | C7: 2 ( SEMESTRAL )
A9: ID | B9: CODIGO ITEM | C9: RUBRO DE COMPRA | D9: I.P.P. | E9: DESCRIPCION | F9: UNIDAD DE MEDIDA | G9: CANTIDAD | H9: PRECIO UNITARIO ESTIMADO | I9: IMPORTE TOTAL ESTIMADO
A10: 1 | B10: 2.9.5-3474.17 | C10: PROD. MEDICO/FARMACEUTICOS/LAB | D10: 2.9.5 | E10: SET P/BOMBA DE INFUSION; MARCA EQUIPO: ICUMEDICAL, MODELO EQUIPO: PLUM 360 - DOBLE CANAL | F10: UNIDAD | G10: =475*6 -> 2850 | H10: 1391 | I10: =+G10*H10 -> 3964350
A11: 2 | B11: 2.9.5-3474.17 | C11: PROD. MEDICO/FARMACEUTICOS/LAB | D11: 2.9.5 | E11: SET P/BOMBA DE INFUSION; MARCA EQUIPO: ICUMEDICAL, MODELO EQUIPO: PLUM 360 - DOBLE CANAL | F11: UNIDAD | G11: =20*6 -> 120 | H11: 1512.5 | I11: =+G11*H11 -> 181500
A12: 3 | B12: 2.9.5-3474.17 | C12: PROD. MEDICO/FARMACEUTICOS/LAB | D12: 2.9.5 | E12: SET P/BOMBA DE INFUSION; MARCA EQUIPO: ICUMEDICAL, MODELO EQUIPO: PLUM 360 - DOBLE CANAL | F12: UNIDAD | G12: =5*6 -> 30 | H12: 1643.2 | I12: =+G12*H12 -> 49296
D13: =LEFT(B13,5) | F13: UNIDAD | I13: =H13*G13 -> 0
D14: =LEFT(B14,5) | F14: UNIDAD | I14: =H14*G14 -> 0
B17: Especificidades Item N° 1 : | C17: SET DE BOMBA PARA INFUSION ENDOVENOSA.
B19: :Plazos y lugares de entrega: | C19: Diez (10) dias habiles. HOSPITAL INT. DE NIÑOS -SERVICIO DE FARMACIA - AV. VIRGEN DEL VALLE N° 1050-CATAMARCA DE 8:00 A 12:00HS
B21: Plazo de Mantenimiento de oferta: | C21: Treinta (30) días habiles.
B23: Condiciones de calidad: | C23: Ver ANEXO I
B26: Especificidades Item N° 2 : | C26: SET DE BOMBA PARA ALIMENTACION ENTERAL CON PUNSON SIN PUERTO EN Y.
B28: Plazos y lugares de entrega: | C28: Diez (10) dias habiles. HOSPITAL INT. DE NIÑOS -SERVICIO DE FARMACIA - AV. VIRGEN DEL VALLE N° 1050-CATAMARCA DE 8:00 A 12:00HS
B30: Plazo de Mantenimiento de oferta: | C30: Treinta (30) días habiles.
B32: Condiciones de calidad: | C32: Ver ANEXO I
B36: Especificidades Item N° 3 : | C36: SET DE BOMBA PARA INFUSION ENDOVENOSA con TUBO REVESTIDO RESISTENTE A LA LUZ.
B38: Plazos y lugares de entrega: | C38: Diez (10) dias habiles. HOSPITAL INT. DE NIÑOS -SERVICIO DE FARMACIA - AV. VIRGEN DEL VALLE N° 1050-CATAMARCA DE 8:00 A 12:00HS
B40: Plazo de Mantenimiento de oferta: | C40: Treinta (30) días habiles.
B42: Condiciones de calidad: | C42: Ver ANEXO I
B46: Plazos y lugares de entrega
B47: Lugar de Entrega: SERVICIO DE FARMACIA -HOSPITAL INT. DE NIÑOS – AV. VIRGEN DEL VALLE N° 1050-CATAMARCA DE 8:00 A 12:00HS., DEBIENDO CORRER LOS GASTOS DE FLETES, ACARREO, CARGA, DESCARGA Y SEGURO A CARGO DEL ADJUDICATARIO.
B49: Plazo de entrega: Dentro de los diez (10) días habiles de notificada la Orden de Compra
B50: Mantenimiento de Oferta: Cuarenta y Cinco (45) dias habiles.
B51: Forma de Pago: Treinta (30) dias habiles.

Sheet  NotaPedido
A1: NOTA DE PEDIDO | J1: N° | K1: 76/2022
A3: JURISDICCIÓN: | D3: ='[1]Necesidades Trimestrales'!C4 -> 040 - Ministerio de Salud
A4: SAF: | D4: ='[1]Necesidades Trimestrales'!C5 -> 024 - Hospital Interzonal de Niños
A5: UNIDAD EJECUTORA: | D5: 024 - Hospital Interzonal de Niños
A6: DEPENDENCIA SOLICITANTE: | D6: Farmacia
A7: PERIODO UTILIZACIÓN: | D7: =+'Necesidades Trimestrales'!C7 -> 2 ( SEMESTRAL )
A8: OBJETO: | D8: Set/ para bombas de infusión
A10: Ítem | B10: Codigo Item | C10: DESCRIPCIÓN | H10: Adjunta Detalle Técnico | I10: Unidad Medida | J10: Precio Unitario Estimado | K10: Cantidad Solicitada
A12: 1 | B12: =+'Necesidades Trimestrales'!B10 -> 2.9.5-3474.17 | C12: =+'Necesidades Trimestrales'!E10 -> SET P/BOMBA DE INFUSION; MARCA EQUIPO: ICUMEDICAL, MODELO EQUIPO: PLUM 360 - DOBLE CANAL | H12: NO | I12: =+'[1]Necesidades Trimestrales'!F10 -> unidad | J12: =+'Necesidades Trimestrales'!H10 -> 1391 | K12: =+'Necesidades Trimestrales'!G10 -> 2850
A13: 2 | B13: =+'Necesidades Trimestrales'!B11 -> 2.9.5-3474.17 | C13: =+'Necesidades Trimestrales'!E11 -> SET P/BOMBA DE INFUSION; MARCA EQUIPO: ICUMEDICAL, MODELO EQUIPO: PLUM 360 - DOBLE CANAL | H13: NO | I13: =+'[1]Necesidades Trimestrales'!F11 -> unidad | J13: =+'Necesidades Trimestrales'!H11 -> 1512.5 | K13: =+'Necesidades Trimestrales'!G11 -> 120
A14: 3 | B14: =+'Necesidades Trimestrales'!B12 -> 2.9.5-3474.17 | C14: =+'Necesidades Trimestrales'!E12 -> SET P/BOMBA DE INFUSION; MARCA EQUIPO: ICUMEDICAL, MODELO EQUIPO: PLUM 360 - DOBLE CANAL | H14: NO | I14: =+'[1]Necesidades Trimestrales'!F12 -> unidad | J14: =+'Necesidades Trimestrales'!H12 -> 1643.2 | K14: =+'Necesidades Trimestrales'!G12 -> 30
A15: Costo total estimado: Cuatro Millones Ciento noventa y cinco Mil ciento cuarenta y seis con 00/100. | J15: =SUMPRODUCT(J12:J14,K12:K14) -> 4195146

Sheet Autor Gastar
A1: EJERCICIO: | D1: ='[1]Necesidades Trimestrales'!C6 -> 2022 | P1: AUTORIZACION PARA GASTAR
A4: JURISDICCIÓN: | G4: =' NotaPedido'!D3 -> 040 - Ministerio de Salud
A5: SAF: | G5: =' NotaPedido'!D4 -> 024 - Hospital Interzonal de Niños
A6: UNIDAD EJECUTORA: | G6: =' NotaPedido'!D5 -> 024 - Hospital Interzonal de Niños
A7: DEPENDENCIA SOLICITANTE: | G7: =' NotaPedido'!D6 -> Farmacia
A8: AUTORIZACIÓN:
A9: Señor Jefe de Servicio Administrativo Financiero:
A10: ="Autorizo la realización de los trámites correspondientes, a fin de proveer a este Organismo los bienes y/o servicios que se detallan en Nota de Pedido N° " & ' NotaPedido'!K1&", afectando la erogación resultante a los créditos presupuestarios aprobados a favor de esta Unidad Ejecutora, conforme al siguiente detalle:" -> Autorizo la realización de los trámites correspondientes, a fin de proveer a este Organismo los bienes y/o servicios que se detallan en Nota de Pedido N° 76/2022, afectando la erogación resultante a los créditos presupuestarios aprobados a favor de esta Unidad Ejecutora, conforme al siguiente detalle:
A12: IMPUTACIÓN PRESUPUESTARIA
A13: CÓDIGO | O13: DENOMINACIÓN DE LA PARTIDA PRESUPUESTARIA | Q13: IMPORTE
A14: PR | B14: SB | C14: PY | D14: AC | E14: OB | F14: UG | G14: FIN | H14: FUN | I14: I | J14: P | K14: P | L14: SubP | M14: M | N14: FF
A15: 36 | D15: 1 | F15: 4901 | G15: 3 | H15: 310 | I15: 2 | J15: 9 | K15: 5 | M15: 1 | N15: 1.1 | O15: Utiles Menores Medico, Quirurgico y de Laboratorio | Q15: 4195146
A18: TOTAL DE PESOS: Cuatro Millones Ciento noventa y cinco Mil ciento cuarenta y seis con 00/100. | Q18: =SUM(Q15:Q17) -> 4195146
A20: JUSTIFICACIÓN:
A21: Para la adquisición de Set/ para bombas de infusión, destinados al servico de Farmacia del Hospital Interzonal de Niños.
