Workbook

Sheet SAF 011
A1: 2022
B2: Pedido de Necesidades Trimestrales
A4: JURISDICCION: | C4: 040 - MINISTERIO DE SALUD
A5: SAF N°: | C5: 011 - DIRECCION PROVINCIAL DE ADMINISTRACION - MINISTERIO DE SALUD
A6: EJERCICIO: | C6: 2022
A7: TRIMESTRE: | C7: PRIMERO
A9: ID | B9: CODIGO ITEM | C9: RUBRO DE COMPRA | D9: I.P.P. | E9: DESCRIPCION | F9: UNIDAD DE MEDIDA | G9: CANTIDAD TOTAL | H9: PRECIO UNITARIO ESTIMADO | I9: IMPORTE TOTAL ESTIMADO | J9: ESPECIFICACION TECNICA
A10: 1 | B10: 2.5.1-9009.29 | C10: QUIMICOS | D10: 2.5.1 | E10: ACIDOS; COMPUESTO QUIMICO: AC. CLORHIDRICO, ESTADO: SOLUCION, CALIDAD: PRO ANALISIS, CONCENTRACION/PUREZA: 37 %, PRESENTACION: ENVASE X 1 L | F10: UNIDAD | G10: 2 | H10: 1268.76 | I10: =G10*H10 -> 2537.52
A11: 2 | B11: 2.5.1-9009.99 | C11: QUIMICOS | D11: 2.5.1 | E11: ACIDOS; COMPUESTO QUIMICO: AC. SULFURICO, ESTADO: LIQUIDO, CALIDAD: PRO ANALISIS, CONCENTRACION/PUREZA: 98 %, PRESENTACION: ENVASE X 1 L | F11: UNIDAD | G11: 2 | H11: 1282.07 | I11: =G11*H11 -> 2564.14
A12: 3 | B12: 2.5.1-9013.22 | C12: QUIMICOS | D12: 2.5.1 | E12: ALDEHIDOS Y CETONAS; COMPUESTO QUIMICO: ACETONA, ESTADO: LIQUIDO, CALIDAD: PRO ANALISIS, CONCENTRACION/PUREZA: 99 %, PRESENTACION: ENVASE X 1 L | F12: UNIDAD | G12: 2 | H12: 7458.08 | I12: =G12*H12 -> 14916.16
A13: 4 | B13: 2.5.1-9015.66 | C13: QUIMICOS | D13: 2.5.1 | E13: BASES; COMPUESTO QUIMICO: HIDROXIDO DE POTASIO, ESTADO: SOLIDO, CALIDAD: FARMACOPEA, CONCENTRACION/PUREZA: 98 %, PRESENTACION: ENVASE X 1 Kg | F13: UNIDAD | G13: 2 | H13: 783.6 | I13: =G13*H13 -> 1567.2
A14: 5 | B14: 2.5.1-9015.52 | C14: QUIMICOS | D14: 2.5.1 | E14: BASES; COMPUESTO QUIMICO: HIDROXIDO DE SODIO, ESTADO: SOLUCION, CALIDAD: PRO ANALISIS, CONCENTRACION/PUREZA: 0,1 N, PRESENTACION: ENVASE X 1 L | F14: UNIDAD | G14: 2 | H14: 747.6 | I14: =G14*H14 -> 1495.2
A15: 6 | B15: 2.5.1-8976.27 | C15: QUIMICOS | D15: 2.5.1 | E15: HIDROCARBUROS; COMPUESTO QUIMICO: CICLOHEXANO, ESTADO: LIQUIDO, CONCENTRACION/PUREZA: 100 %, PRESENTACION: ENVASE X 1 L, CALIDAD: PRO ANALISIS | F15: UNIDAD | G15: 2 | H15: 6387.6 | I15: =G15*H15 -> 12775.2
A16: 7 | B16: 2.5.1-9016.184 | C16: QUÍMICOS | D16: 2.5.1 | E16: MEDIOS DE CULTIVO Y SUPLEMENTO; NOMBRE DEL PRODUCTO: AGAR BAIRD PARKER, ESTADO: SOLIDO, PRESENTACION: ENVASE X 500 GR | F16: UNIDAD | G16: 1 | H16: 19988.51 | I16: =G16*H16 -> 19988.51
A17: 8 | B17: 2.5.1-9016.774 | C17: QUÍMICOS | D17: 2.5.1 | E17: MEDIOS DE CULTIVO Y SUPLEMENTO; NOMBRE DEL PRODUCTO: AGAR BASE BACILLUS CEREUS, ESTADO: SOLIDO, PRESENTACION: ENVASE X 500 GR | F17: UNIDAD | G17: 2 | H17: 20640.91 | I17: =G17*H17 -> 41281.82
A18: 9 | B18: 2.5.1-9016.200 | C18: QUÍMICOS | D18: 2.5.1 | E18: MEDIOS DE CULTIVO Y SUPLEMENTO; NOMBRE DEL PRODUCTO: AGAR BASE SANGRE, ESTADO: SOLIDO, PRESENTACION: ENVASE X 500 Ml | F18: UNIDAD | G18: 1 | H18: 6360 | I18: =G18*H18 -> 6360
A19: 10 | B19: 2.5.1-9016.205 | C19: QUÍMICOS | D19: 2.5.1 | E19: MEDIOS DE CULTIVO Y SUPLEMENTO; NOMBRE DEL PRODUCTO: AGAR BILIS ESCULINA AZIDA, ESTADO: SOLIDO, PRESENTACION: ENVASE X 100 GR | F19: UNIDAD | G19: 1 | H19: 12526.18 | I19: =G19*H19 -> 12526.18
A20: 11 | B20: 2.5.1-9016.78 | C20: QUÍMICOS | D20: 2.5.1 | E20: MEDIOS DE CULTIVO Y SUPLEMENTO; NOMBRE DEL PRODUCTO: AGAR CETRIMIDA, ESTADO: SOLIDO, PRESENTACION: ENVASE X 500 GR | F20: UNIDAD | G20: 1 | H20: 24630.92 | I20: =G20*H20 -> 24630.92
A21: 12 | B21: 2.5.1-9016.646 | C21: QUÍMICOS | D21: 2.5.1 | E21: MEDIOS DE CULTIVO Y SUPLEMENTO; NOMBRE DEL PRODUCTO: AGAR EMB, ESTADO: SOLIDO, PRESENTACION: ENVASE X 100 GR | F21: UNIDAD | G21: 2 | H21: 23746.3 | I21: =G21*H21 -> 47492.6
... A61: 52 | B61: 2.5.1-9004.334 | C61: QUÍMICOS | D61: 2.5.1 | E61: SALES; COMPUESTO QUIMICO: TELURITO DE POTASIO, ESTADO: SOLIDO, CALIDAD: PRO ANALISIS, CONCENTRACION/PUREZA: 99 %, PRESENTACION: ENVASE X 25 GR, GRADO HIDRATACION: ANHIDRO | F61: UNIDAD | G61: 2 | H61: 2238.46 | I61: =G61*H61 -> 4476.92
E62: TOTAL RUBRO QUIMICOS PARA AGUA | I62: =+SUM(I10:I61) -> 1117679.5
B64: DETALLE TECNICO Y ESPECIFICACIONES
B66: Plazos de entrega | C66: veinte (20) dias habiles
B68: Lugar de Entrega: | C68: Avenida Enrique Ocampo N° 257, Capital Catamarca. - en el horario de 8:00hs a 12:00hs de lunes a viernes
B70: Calidad Minima esperada
B72: Mantenimiento | C72: cuarenta y cinco (45) días

Sheet NP
A1: NOTA DE PEDIDO | J1: N° | K1: 01/2022
A3: JURISDICCIÓN: | D3: ='SAF 011'!C4 -> 040 - MINISTERIO DE SALUD
A4: SAF: | D4: ='SAF 011'!C5 -> 011 - DIRECCION PROVINCIAL DE ADMINISTRACION - MINISTERIO DE SALUD
A5: UNIDAD EJECUTORA: | D5: DIRECCION PROVINCIAL DE SALUD Y MEDIO AMBIENTE
A6: DEPENDENCIA SOLICITANTE: | D6: DIRECCION PROVINCIAL DE SALUD Y MEDIO AMBIENTE
A7: PERIODO UTILIZACIÓN: | D7: 1° TRIMESTRE 2022
A8: OBJETO: | D8: ADQUISICION DEL RUBRO REACTIVOS PARA AGUA
A10: Ítem | B10: Codigo Item | C10: DESCRIPCIÓN | H10: Adjunta Detalle Técnico | I10: Unidad Medida | J10: Precio Unitario Estimado | K10: Cantidad Solicitada
A12: 1 | B12: ='SAF 011'!B10 -> 2.5.1-9009.29 | C12: ='SAF 011'!E10 -> ACIDOS; COMPUESTO QUIMICO: AC. CLORHIDRICO, ESTADO: SOLUCION, CALIDAD: PRO ANALISIS, CONCENTRACION/PUREZA: 37 %, PRESENTACION: ENVASE X 1 L | H12: NO | I12: ='SAF 011'!F10 -> UNIDAD | J12: ='SAF 011'!H10 -> 1268.76 | K12: ='SAF 011'!#REF! -> #REF! | M12: =+J12*K12 -> #REF!
A13: 2 | B13: ='SAF 011'!B11 -> 2.5.1-9009.99 | C13: ='SAF 011'!E11 -> ACIDOS; COMPUESTO QUIMICO: AC. SULFURICO, ESTADO: LIQUIDO, CALIDAD: PRO ANALISIS, CONCENTRACION/PUREZA: 98 %, PRESENTACION: ENVASE X 1 L | H13: NO | I13: ='SAF 011'!F11 -> UNIDAD | J13: ='SAF 011'!H11 -> 1282.07 | K13: ='SAF 011'!#REF! -> #REF! | M13: =+J13*K13 -> #REF!
A14: 3 | B14: ='SAF 011'!B12 -> 2.5.1-9013.22 | C14: ='SAF 011'!E12 -> ALDEHIDOS Y CETONAS; COMPUESTO QUIMICO: ACETONA, ESTADO: LIQUIDO, CALIDAD: PRO ANALISIS, CONCENTRACION/PUREZA: 99 %, PRESENTACION: ENVASE X 1 L | H14: NO | I14: ='SAF 011'!F12 -> UNIDAD | J14: ='SAF 011'!H12 -> 7458.08 | K14: ='SAF 011'!#REF! -> #REF! | M14: =+J14*K14 -> #REF!
A15: 4 | B15: ='SAF 011'!B13 -> 2.5.1-9015.66 | C15: ='SAF 011'!E13 -> BASES; COMPUESTO QUIMICO: HIDROXIDO DE POTASIO, ESTADO: SOLIDO, CALIDAD: FARMACOPEA, CONCENTRACION/PUREZA: 98 %, PRESENTACION: ENVASE X 1 Kg | H15: NO | I15: ='SAF 011'!F13 -> UNIDAD | J15: ='SAF 011'!H13 -> 783.6 | K15: ='SAF 011'!#REF! -> #REF! | M15: =+J15*K15 -> #REF!
A16: 5 | B16: ='SAF 011'!B14 -> 2.5.1-9015.52 | C16: ='SAF 011'!E14 -> BASES; COMPUESTO QUIMICO: HIDROXIDO DE SODIO, ESTADO: SOLUCION, CALIDAD: PRO ANALISIS, CONCENTRACION/PUREZA: 0,1 N, PRESENTACION: ENVASE X 1 L | H16: NO | I16: ='SAF 011'!F14 -> UNIDAD | J16: ='SAF 011'!H14 -> 747.6 | K16: ='SAF 011'!#REF! -> #REF! | M16: =+J16*K16 -> #REF!
A17: 6 | B17: ='SAF 011'!B15 -> 2.5.1-8976.27 | C17: ='SAF 011'!E15 -> HIDROCARBUROS; COMPUESTO QUIMICO: CICLOHEXANO, ESTADO: LIQUIDO, CONCENTRACION/PUREZA: 100 %, PRESENTACION: ENVASE X 1 L, CALIDAD: PRO ANALISIS | H17: NO | I17: ='SAF 011'!F15 -> UNIDAD | J17: ='SAF 011'!H15 -> 6387.6 | K17: ='SAF 011'!#REF! -> #REF! | M17: =+J17*K17 -> #REF!
A18: 7 | B18: ='SAF 011'!B16 -> 2.5.1-9016.184 | C18: ='SAF 011'!E16 -> MEDIOS DE CULTIVO Y SUPLEMENTO; NOMBRE DEL PRODUCTO: AGAR BAIRD PARKER, ESTADO: SOLIDO, PRESENTACION: ENVASE X 500 GR | H18: NO | I18: ='SAF 011'!F16 -> UNIDAD | J18: ='SAF 011'!H16 -> 19988.51 | K18: ='SAF 011'!#REF! -> #REF! | M18: =+J18*K18 -> #REF!
A19: 8 | B19: ='SAF 011'!B17 -> 2.5.1-9016.774 | C19: ='SAF 011'!E17 -> MEDIOS DE CULTIVO Y SUPLEMENTO; NOMBRE DEL PRODUCTO: AGAR BASE BACILLUS CEREUS, ESTADO: SOLIDO, PRESENTACION: ENVASE X 500 GR | H19: NO | I19: ='SAF 011'!F17 -> UNIDAD | J19: ='SAF 011'!H17 -> 20640.91 | K19: ='SAF 011'!#REF! -> #REF! | M19: =+J19*K19 -> #REF!
A20: 9 | B20: ='SAF 011'!B18 -> 2.5.1-9016.200 | C20: ='SAF 011'!E18 -> MEDIOS DE CULTIVO Y SUPLEMENTO; NOMBRE DEL PRODUCTO: AGAR BASE SANGRE, ESTADO: SOLIDO, PRESENTACION: ENVASE X 500 Ml | H20: NO | I20: ='SAF 011'!F18 -> UNIDAD | J20: ='SAF 011'!H18 -> 6360 | K20: ='SAF 011'!#REF! -> #REF! | M20: =+J20*K20 -> #REF!
A21: 10 | B21: ='SAF 011'!B19 -> 2.5.1-9016.205 | C21: ='SAF 011'!E19 -> MEDIOS DE CULTIVO Y SUPLEMENTO; NOMBRE DEL PRODUCTO: AGAR BILIS ESCULINA AZIDA, ESTADO: SOLIDO, PRESENTACION: ENVASE X 100 GR | H21: NO | I21: ='SAF 011'!F19 -> UNIDAD | J21: ='SAF 011'!H19 -> 12526.18 | K21: ='SAF 011'!#REF! -> #REF! | M21: =+J21*K21 -> #REF!
A22: 11 | B22: ='SAF 011'!B20 -> 2.5.1-9016.78 | C22: ='SAF 011'!E20 -> MEDIOS DE CULTIVO Y SUPLEMENTO; NOMBRE DEL PRODUCTO: AGAR CETRIMIDA, ESTADO: SOLIDO, PRESENTACION: ENVASE X 500 GR | H22: NO | I22: ='SAF 011'!F20 -> UNIDAD | J22: ='SAF 011'!H20 -> 24630.92 | K22: ='SAF 011'!#REF! -> #REF! | M22: =+J22*K22 -> #REF!
A23: 12 | B23: ='SAF 011'!B21 -> 2.5.1-9016.646 | C23: ='SAF 011'!E21 -> MEDIOS DE CULTIVO Y SUPLEMENTO; NOMBRE DEL PRODUCTO: AGAR EMB, ESTADO: SOLIDO, PRESENTACION: ENVASE X 100 GR | H23: NO | I23: ='SAF 011'!F21 -> UNIDAD | J23: ='SAF 011'!H21 -> 23746.3 | K23: ='SAF 011'!#REF! -> #REF! | M23: =+J23*K23 -> #REF!
... A63: 52 | B63: ='SAF 011'!B61 -> 2.5.1-9004.334 | C63: ='SAF 011'!E61 -> SALES; COMPUESTO QUIMICO: TELURITO DE POTASIO, ESTADO: SOLIDO, CALIDAD: PRO ANALISIS, CONCENTRACION/PUREZA: 99 %, PRESENTACION: ENVASE X 25 GR, GRADO HIDRATACION: ANHIDRO | H63: NO | I63: ='SAF 011'!F61 -> UNIDAD | J63: ='SAF 011'!H61 -> 2238.46 | K63: ='SAF 011'!#REF! -> #REF! | M63: =+J63*K63 -> #REF!
A65: Costo total estimado: UN MILLON CIENTO DIECISIETE MIL SEISCIENTOS SETENTA Y NUEVE CON 48/100.- | J65: =+M65 -> #REF! | M65: =SUM(M12:M64) -> #REF!

Sheet APG
A1: EJERCICIO: | D1: 2022 | P1: AUTORIZACION PARA GASTAR
A4: JURISDICCIÓN: | G4: =NP!D3 -> 040 - MINISTERIO DE SALUD
A5: SAF: | G5: =NP!D4 -> 011 - DIRECCION PROVINCIAL DE ADMINISTRACION - MINISTERIO DE SALUD
A6: UNIDAD EJECUTORA: | G6: =NP!D5 -> DIRECCION PROVINCIAL DE SALUD Y MEDIO AMBIENTE
A7: DEPENDENCIA SOLICITANTE: | G7: =NP!D6 -> DIRECCION PROVINCIAL DE SALUD Y MEDIO AMBIENTE
A8: AUTORIZACIÓN:
A9: Señor Director de Administración o Titular del Servicio Administrativo Financiero:
A10: Autorizo la realización de los trámites correspondientes, a fin de proveer a este Organismo los bienes que se detallan en Nota de Pedido N° 01/2022 afectando la erogación resultante a los créditos presupuestarios aprobados a favor de esta Unidad Ejecutora, conforme al siguiente detalle:
A12: IMPUTACIÓN PRESUPUESTARIA
A13: CÓDIGO | O13: DENOMINACIÓN DE LA PARTIDA PRESUPUESTARIA | Q13: IMPORTE
A14: PR | B14: SB | C14: PY | D14: AC | E14: OB | F14: UG | G14: FIN | H14: FUN | I14: I | J14: P | K14: P | L14: SubP | M14: M | N14: FF
A15: 22 | D15: 1 | F15: 4901 | G15: 4 | H15: 4 | I15: 2 | J15: 5 | K15: 1 | M15: 1 | N15: 1.1 | O15: COMPUESTOS QUIMICOS | Q15: =NP!J65 -> #REF!
A38: TOTAL DE PESOS: UN MILLON CIENTO DIECISIETE MIL SEISCIENTOS SETENTA Y NUEVE CON 48/100.- | Q38: =SUM(Q15:Q37) -> #REF!
A40: JUSTIFICACIÓN:
A41: =NP!D8 -> ADQUISICION DEL RUBRO REACTIVOS PARA AGUA
