Workbook

Sheet Necesidades Trimestrales
B2: Pedido de Necesidades Trimestrales
A4: JURISDICCION: | C4: 90 - Ministerio de Seguridad
A5: SAF N°: | C5: 7 - Direccion Provincial de Administracion de la Policia de Catamarca
A6: EJERCICIO: | C6: 2022
A7: TRIMESTRE: | C7: 4
A9: ID | B9: CODIGO ITEM | C9: RUBRO DE COMPRA | D9: I.P.P. | E9: DESCRIPCION | F9: UNIDAD DE MEDIDA | G9: CANTIDAD | H9: PRECIO UNITARIO ESTIMADO | I9: IMPORTE TOTAL ESTIMADO
A10: 1 | B10: 4.4.0-1735.13 | C10: EQUIPO MILITAR Y DE SEGURIDAD | D10: 4.4.0 | E10: CHALECOS ANTIBALA; PROTECCION: PECHO, ESPALDA Y COSTADOS, NIVEL: RB3, TALLE: SIN VALOR | F10: UNIDAD | G10: 200 | H10: 155900 | I10: =+H10*G10 -> 31180000
A11: 2 | B11: 4.4.0-1735.13 | C11: EQUIPO MILITAR Y DE SEGURIDAD | D11: 4.4.0 | E11: CHALECOS ANTIBALA; PROTECCION: PECHO, ESPALDA Y COSTADOS, NIVEL: RB3, TALLE: SIN VALOR | F11: UNIDAD | G11: 100 | H11: 198500 | I11: =+H11*G11 -> 19850000
I12: =+I11+I10 -> 51030000
B13: Especificidades Ítem
B15: Descripción técnica ítem 1
C16: CHALECO ANTIBALAS - NIVEL RB3 - PROYECTILES CALIBRE .44 MG Y 9 MM DE ALTA VELOCIDAD CON COBERTURA 360° PROTECCION: PANEL PECHO, ESPALDA Y COSTADOS, Las prendas balísticas deberán ser nuevas, sin uso y deberá poseer una Garantía de fábrica de por lo menos 5 años. 100 (Cien) Chalecos para uso Masculino TALLES “L”; 100 (Cien) Chalecos para uso Masculino TALLES “XL” -Ver anexo de especificaciones.
B17: Descripción técnica ítem 2
C18: CHALECO ANTIBALAS - NIVEL RB3 , PROYECTILES CALIBRE .44 MG Y 9 MM DE ALTA VELOCIDAD CON COBERTURA 360° ; PROTECCION: PANEL PECHO, ESPALDA Y COSTADOS, , TALLE: SIN VALOR; Las prendas balísticas deberán ser nuevas, sin uso y deberá poseer una Garantía de fábrica de por lo menos 5 años. 50 (Cincuenta) Chalecos para uso Femenino TALLES “L”; 50 (Cincuenta) Chalecos para uso Femenino TALLES “XL”. Ver anexo de especificaciones.
C19: **Ademas se solicita que en la factura se consigne como destinatario de los mismos a la Policia de la Provincia de Catamarca N° de leg. Usuario Colectivo: 4-9162000.-
B20: Plazos y lugares de entrega
C21: a) LUGAR DE ENTREGA: DIVISIÓN ARMAMENTO Y MUNICIONES (Dpto. Logística), sito en Chacabuco N° 809 - Capital - De 08 a 12 horas. b) FORMA DE LA ENTREGA: Libre de flete, acarreo y embalaje, como así también, de todo riesgo de pérdida o destrucción total o parcial, por causas ajenas a la Institución. c) PLAZO DE ENTREGA: El Oferente deberá establecer plazo de entrega de los elementos cotizados, debiendo ser expresado en días hábiles; que no podrá ser superior a Quince (15) días hábiles, contados a partir de la recepción de la comunicación prevista en el Artículo 80° de del Reglamento Parcial N° 2 de la ley 4938.
B23: Calidad Mínima esperada
C24: Que Cumpla con lo Solicitado de Forma Integra.
B25: Mantenimiento
C26: 30 (treinta) días
B27: Garantía
C28: Garantía de fábrica de por lo menos 5 años, comenzando a correr dicha garantía desde que es recibida y aceptada. La antigüedad en la fabricación no podrá ser superior al año inmediato anterior al de la entrega.

Sheet  NotaPedido
A1: NOTA DE PEDIDO | J1: N° | K1: 32/2020
A3: JURISDICCIÓN: | D3: ='Necesidades Trimestrales'!C4 -> 90 - Ministerio de Seguridad
A4: SAF: | D4: ='Necesidades Trimestrales'!C5 -> 7 - Direccion Provincial de Administracion de la Policia de Catamarca
A5: UNIDAD EJECUTORA: | D5: Jefatura de Policía de la Provincia de Catamarca
A6: DEPENDENCIA SOLICITANTE: | D6: División Transporte- Dpto. Logistica (D-4)
A7: PERIODO UTILIZACIÓN: | D7: ='Necesidades Trimestrales'!C7 & "° Trimestre - Año " & 'Necesidades Trimestrales'!C6 -> 4° Trimestre - Año 2022
A8: OBJETO: | D8: Adquisición de CUBIERTAS destinadas a las Unidades Moviles de la Policia de Catamarca.-
A10: Ítem | B10: Codigo Item | C10: DESCRIPCIÓN | H10: Adjunta Detalle Técnico | I10: Unidad Medida | J10: Precio Unitario Estimado | K10: Cantidad Solicitada
A12: 1 | B12: ='Necesidades Trimestrales'!B11 -> 4.4.0-1735.13 | C12: ='Necesidades Trimestrales'!E11 -> CHALECOS ANTIBALA; PROTECCION: PECHO, ESPALDA Y COSTADOS, NIVEL: RB3, TALLE: SIN VALOR | H12: SI | I12: UNIDAD | J12: ='Necesidades Trimestrales'!H11 -> 198500 | K12: ='Necesidades Trimestrales'!G11 -> 100
A13: 2 | B13: ='Necesidades Trimestrales'!#REF! -> #REF! | C13: ='Necesidades Trimestrales'!#REF! -> #REF! | H13: SI | I13: UNIDAD | J13: ='Necesidades Trimestrales'!#REF! -> #REF! | K13: ='Necesidades Trimestrales'!#REF! -> #REF!
A14: 3 | B14: ='Necesidades Trimestrales'!#REF! -> #REF! | C14: ='Necesidades Trimestrales'!#REF! -> #REF! | H14: SI | I14: UNIDAD | J14: ='Necesidades Trimestrales'!#REF! -> #REF! | K14: ='Necesidades Trimestrales'!#REF! -> #REF!
A15: 4 | B15: ='Necesidades Trimestrales'!#REF! -> #REF! | C15: ='Necesidades Trimestrales'!#REF! -> #REF! | H15: SI | I15: UNIDAD | J15: ='Necesidades Trimestrales'!#REF! -> #REF! | K15: ='Necesidades Trimestrales'!#REF! -> #REF!
A16: 5 | B16: ='Necesidades Trimestrales'!#REF! -> #REF! | C16: ='Necesidades Trimestrales'!#REF! -> #REF! | H16: SI | I16: UNIDAD | J16: ='Necesidades Trimestrales'!#REF! -> #REF! | K16: ='Necesidades Trimestrales'!#REF! -> #REF!
A17: 6 | B17: ='Necesidades Trimestrales'!#REF! -> #REF! | C17: ='Necesidades Trimestrales'!#REF! -> #REF! | H17: SI | I17: UNIDAD | J17: ='Necesidades Trimestrales'!#REF! -> #REF! | K17: ='Necesidades Trimestrales'!#REF! -> #REF!
A18: 7 | B18: ='Necesidades Trimestrales'!#REF! -> #REF! | C18: ='Necesidades Trimestrales'!#REF! -> #REF! | H18: SI | I18: UNIDAD | J18: ='Necesidades Trimestrales'!#REF! -> #REF! | K18: ='Necesidades Trimestrales'!#REF! -> #REF!
A19: 8 | B19: ='Necesidades Trimestrales'!#REF! -> #REF! | C19: ='Necesidades Trimestrales'!#REF! -> #REF! | H19: SI | I19: UNIDAD | J19: ='Necesidades Trimestrales'!#REF! -> #REF! | K19: ='Necesidades Trimestrales'!#REF! -> #REF!
A20: 9 | B20: ='Necesidades Trimestrales'!#REF! -> #REF! | C20: ='Necesidades Trimestrales'!#REF! -> #REF! | H20: SI | I20: UNIDAD | J20: ='Necesidades Trimestrales'!#REF! -> #REF! | K20: ='Necesidades Trimestrales'!#REF! -> #REF!
A21: 10 | B21: ='Necesidades Trimestrales'!#REF! -> #REF! | C21: ='Necesidades Trimestrales'!#REF! -> #REF! | H21: SI | I21: UNIDAD | J21: ='Necesidades Trimestrales'!#REF! -> #REF! | K21: ='Necesidades Trimestrales'!#REF! -> #REF!
A22: 11 | B22: ='Necesidades Trimestrales'!#REF! -> #REF! | C22: ='Necesidades Trimestrales'!#REF! -> #REF! | H22: SI | I22: UNIDAD | J22: ='Necesidades Trimestrales'!#REF! -> #REF! | K22: ='Necesidades Trimestrales'!#REF! -> #REF!
A23: 12 | B23: ='Necesidades Trimestrales'!#REF! -> #REF! | C23: ='Necesidades Trimestrales'!#REF! -> #REF! | H23: SI | I23: UNIDAD | J23: ='Necesidades Trimestrales'!#REF! -> #REF! | K23: ='Necesidades Trimestrales'!#REF! -> #REF!
A24: 13 | B24: ='Necesidades Trimestrales'!#REF! -> #REF! | C24: ='Necesidades Trimestrales'!#REF! -> #REF! | H24: SI | I24: UNIDAD | J24: ='Necesidades Trimestrales'!#REF! -> #REF! | K24: ='Necesidades Trimestrales'!#REF! -> #REF!
... A29: 18 | B29: ='Necesidades Trimestrales'!#REF! -> #REF! | C29: ='Necesidades Trimestrales'!#REF! -> #REF! | H29: SI | I29: UNIDAD | J29: ='Necesidades Trimestrales'!#REF! -> #REF! | K29: ='Necesidades Trimestrales'!#REF! -> #REF!
A30: Costo total estimado: Pesos . | D30: Trece Millones Quinientos Cuatro Mil Doscientos Cuatro con 00/100. | J30: =SUMPRODUCT(J12:J29,K12:K29) -> #REF!

Sheet Autor Gastar
A1: EJERCICIO: | D1: ='[1]Necesidades Trimestrales'!C6 -> 2021 | P1: AUTORIZACION PARA GASTAR
A4: JURISDICCIÓN: | G4: =' NotaPedido'!D3 -> 90 - Ministerio de Seguridad
A5: SAF: | G5: =' NotaPedido'!D4 -> 7 - Direccion Provincial de Administracion de la Policia de Catamarca
A6: UNIDAD EJECUTORA: | G6: =' NotaPedido'!D5 -> Jefatura de Policía de la Provincia de Catamarca
A7: DEPENDENCIA SOLICITANTE: | G7: =' NotaPedido'!D6 -> División Transporte- Dpto. Logistica (D-4)
A8: AUTORIZACIÓN:
A9: Señor Jefe de Servicio Administrativo Financiero:
A10: ="Autorizo la realización de los trámites correspondientes, a fin de proveer a este Organismo los bienes y/o servicios que se detallan en Nota de Pedido N° " & ' NotaPedido'!K1&", afectando la erogación resultante a los créditos presupuestarios aprobados a favor de esta Unidad Ejecutora, conforme al siguiente detalle:" -> Autorizo la realización de los trámites correspondientes, a fin de proveer a este Organismo los bienes y/o servicios que se detallan en Nota de Pedido N° 32/2020, afectando la erogación resultante a los créditos presupuestarios aprobados a favor de esta Unidad Ejecutora, conforme al siguiente detalle:
A12: IMPUTACIÓN PRESUPUESTARIA
A13: CÓDIGO | O13: DENOMINACIÓN DE LA PARTIDA PRESUPUESTARIA | Q13: IMPORTE
A14: PR | B14: SB | C14: PY | D14: AC | E14: OB | F14: UG | G14: FIN | H14: FUN | I14: I | J14: P | K14: P | L14: SubP | M14: M | N14: FF
A15: 16 | B15: 0 | C15: 0 | D15: 1 | E15: 0 | F15: 10 | G15: 2 | H15: 1 | I15: 2 | J15: 4 | K15: 4 | L15: 0 | M15: 1 | N15: 1.1 | O15: CUBIERTAS Y CAMARAS DE AIRE | Q15: ='Necesidades Trimestrales'!#REF! -> #REF!
A16: TOTAL DE PESOS | Q16: =+Q15 -> #REF!
E17: =' NotaPedido'!D30 -> Trece Millones Quinientos Cuatro Mil Doscientos Cuatro con 00/100.
A18: JUSTIFICACIÓN:
A19: =' NotaPedido'!D8 -> Adquisición de CUBIERTAS destinadas a las Unidades Moviles de la Policia de Catamarca.-
