Workbook

Sheet SAF 011
A1: 2022
B2: Pedido de Necesidades Trimestrales
A4: JURISDICCION: | C4: 040 - MINISTERIO DE SALUD
A5: SAF N°: | C5: 011 - DIRECCION PROVINCIAL DE ADMINISTRACION - MINISTERIO DE SALUD
A6: EJERCICIO: | C6: 2022
A7: TRIMESTRE: | C7: PRIMERO
A9: ID | B9: CODIGO ITEM | C9: RUBRO DE COMPRA | D9: I.P.P. | E9: DESCRIPCION | F9: UNIDAD DE MEDIDA | G9: SECRETARIA DE ADMINISTRACION | H9: TOTAL S.A. | I9: SMPyPS | J9: TOTAL SMPyPS | K9: DIR. LAB. CENTRAL | L9: TOTAL DE LAB CENTRAL | M9: BCO DE SANGRE | N9: TOTAL BANCO DE SANGRE | O9: APS | P9: TOTAL A.P.S. | Q9: DIR DE CANCER | R9: TOTAL DE DIR DE CANCER | S9: FARMACIA | T9: TOTAL FARMACIA | U9: ODONTOLOGIA | V9: TOTAL DE ODONTOLOG | W9: SAME | X9: TOTAL SAME | Y9: HPTAL MALBRAN | Z9: TOTAL HPTAL MALBRAN | AA9: MATERNIDAD E INFANCIA | AB9: TOTAL MATERNIDAD E INFANCIA | AC9: SASP | AD9: TOTAL SASP | AE9: SALUD Y MEDIO AMBIENTE | AF9: TOTAL SALUD Y MEDIO AMBIENTE | AG9: VECTORES Y ZOONOSIS | AH9: TOTAL DE VECT Y ZOON | AI9: CRONICAS | AJ9: TOTAL CRONICAS | AK9: CUR | AL9: TOTAL CUR | AM9: SPyGS | AN9: TOTAL SPyGS | AO9: SALUD MENTAL | AP9: TOTAL SALUD MENTAL | AQ9: AREAS Y DPAS | AR9: TOTAL DPAS | AS9: EPIDEMIOLOGIA | AT9: TOTAL EPIDEMIOLOGIA | AU9: AREA 1 | AV9: TOTAL AREA 1 | AW9: CANTIDAD TOTAL | AX9: PRECIO UNITARIO ESTIMADO | AY9: IMPORTE TOTAL ESTIMADO | AZ9: ESPECIFICACION TECNICA
A10: 1 | B10: 2.1.1-705.137 | C10: ALIMENTOS | D10: 2.1.1 | E10: LECHE; ESTADO: POLVO, TIPO: ENTERA, PROCESO: PASTEURIZADA, AGREGADO: HIERRO, ZINC Y ACIDO ASCORBICO, PRESENTACION: SIN, MATERIAL ENVASE: SIN, ELEM. TRANSPORTE: SIN, MATERIAL ELEM. TRANSPORTE: SIN, CERTIFICADO FORESTAL (GFS): SIN, LIBRE DE GLUTEN: SIN VALOR | F10: UNIDAD | X10: =+W10*AX10 -> 0 | AA10: 5000 | AB10: =+AA10*AX10 -> 4000000 | AW10: =+AQ10+AO10+AM10+AK10+AI10+AG10+AE10+AC10+AA10+Y10+W10+U10+S10+Q10+O10+M10+K10+I10+AS10+G10+AU10 -> 5000 | AX10: 800 | AY10: =+AW10*AX10 -> 4000000 | AZ10: Se hará constar con caracteres bien visibles. - Leche apta para niños a partir de un año hasta los seis años. -Composición química porcentual. - Solubilidad. - Forma de reconstitución para obtener la leche fluida correspondiente. - Mantenerse en lugar fresco, seco, oscuro y recipiente cerrado, en envase trilaminado de aluminio y envasado al vacío. - Mes y año de elaboración. - Fecha de vencimiento: No inferior a 12 (doce) meses a partir de la fecha de recepción. - Identificación de partida y/o número de lote. - ROTULACION: para determinar la procedencia del producto, gratuidad, prohibición de su venta o canje, los envases deberán contener la siguiente leyenda: "DIRECCION PROVINCIAL MATERNO INFANTIL - SECRETARÍA DE MEDICINA PREVENTIVA Y PROMOCION EN SALUD - MINISTERIO DE SALUD DE CATAMARCA - PROHIBIDA SU VENTA" (Impresión con letras mayúsculas, Arial, visibles no menores a fuente 16 y en negritas), la que tendrá que ir de forma impresa en el estuche, deberá estar en forma expresa en el envase, libre de todo gasto para el Ministerio de Salud.
E11: TOTAL RUBRO ALIMENTOS | L11: =+K11*AX11 -> 0 | N11: =+M11*AX11 -> 0 | AY11: =+SUM(AY10:AY10) -> 4000000
C13: ITEM 1 DETALLE TECNICO Y ESPECIFICACIONES | D13: VER ANEXO I
C15: Plazos de entrega | D15: diez (10) dias habiles
C17: Lugar de Entrega: | D17: DIR. PROV. DE MATERNIDAD, INFANCIA Y ADOLESCENCIA - CHACABUCO N° 169 - en el horario de 8:00hs a 12:00hs de lunes a viernes
C19: Calidad Minima esperada
C21: Mantenimiento | D21: cuarenta y cinco (45) días

Sheet NP
A1: NOTA DE PEDIDO | J1: N° | K1: 01/2022
A3: JURISDICCIÓN: | D3: ='SAF 011'!C4 -> 040 - MINISTERIO DE SALUD
A4: SAF: | D4: ='SAF 011'!C5 -> 011 - DIRECCION PROVINCIAL DE ADMINISTRACION - MINISTERIO DE SALUD
A5: UNIDAD EJECUTORA: | D5: DIRECCION PROVINCIAL MATERNIDAD, INFANCIA Y ADOLESCENCIA
A6: DEPENDENCIA SOLICITANTE: | D6: DIRECCION PROVINCIAL MATERNIDAD, INFANCIA Y ADOLESCENCIA
A7: PERIODO UTILIZACIÓN: | D7: 1° TRIMESTRE 2022
A8: OBJETO: | D8: ADQUISICION DEL RUBRO ALIMENTOS PARA PERSONAS (LECHE FORTIFICADA)
A10: Ítem | B10: Codigo Item | C10: DESCRIPCIÓN | H10: Adjunta Detalle Técnico | I10: Unidad Medida | J10: Precio Unitario Estimado | K10: Cantidad Solicitada
A12: 1 | B12: ='SAF 011'!B10 -> 2.1.1-705.137 | C12: ='SAF 011'!E10 -> LECHE; ESTADO: POLVO, TIPO: ENTERA, PROCESO: PASTEURIZADA, AGREGADO: HIERRO, ZINC Y ACIDO ASCORBICO, PRESENTACION: SIN, MATERIAL ENVASE: SIN, ELEM. TRANSPORTE: SIN, MATERIAL ELEM. TRANSPORTE: SIN, CERTIFICADO FORESTAL (GFS): SIN, LIBRE DE GLUTEN: SIN VALOR | H12: SI | I12: ='SAF 011'!F10 -> UNIDAD | J12: ='SAF 011'!AX10 -> 800 | K12: ='SAF 011'!AW10 -> 5000 | M12: =+J12*K12 -> 4000000
A14: Costo total estimado: CUATRO MILLONES CON 00/100.- | J14: =+M12 -> 4000000

Sheet APG
A1: EJERCICIO: | D1: 2022 | P1: AUTORIZACION PARA GASTAR
A4: JURISDICCIÓN: | G4: =NP!D3 -> 040 - MINISTERIO DE SALUD
A5: SAF: | G5: =NP!D4 -> 011 - DIRECCION PROVINCIAL DE ADMINISTRACION - MINISTERIO DE SALUD
A6: UNIDAD EJECUTORA: | G6: =NP!D5 -> DIRECCION PROVINCIAL MATERNIDAD, INFANCIA Y ADOLESCENCIA
A7: DEPENDENCIA SOLICITANTE: | G7: =NP!D6 -> DIRECCION PROVINCIAL MATERNIDAD, INFANCIA Y ADOLESCENCIA
A8: AUTORIZACIÓN:
A9: Señor Director de Administración o Titular del Servicio Administrativo Financiero:
A10: Autorizo la realización de los trámites correspondientes, a fin de proveer a este Organismo los bienes que se detallan en Nota de Pedido N° 01/2022 afectando la erogación resultante a los créditos presupuestarios aprobados a favor de esta Unidad Ejecutora, conforme al siguiente detalle:
A12: IMPUTACIÓN PRESUPUESTARIA
A13: CÓDIGO | O13: DENOMINACIÓN DE LA PARTIDA PRESUPUESTARIA | Q13: IMPORTE
A14: PR | B14: SB | C14: PY | D14: AC | E14: OB | F14: UG | G14: FIN | H14: FUN | I14: I | J14: P | K14: P | L14: SubP | M14: M | N14: FF
A15: 20 | D15: 1 | F15: 4901 | G15: 3 | H15: 1 | I15: 2 | J15: 1 | K15: 1 | M15: 1 | N15: 1.1 | O15: ALIMENTOS PARA PERSONAS | Q15: =NP!M12 -> 4000000
A38: TOTAL DE PESOS: CUATRO MILLONES CON 00/100.- | Q38: =SUM(Q15:Q37) -> 4000000
A40: JUSTIFICACIÓN:
A41: =NP!D8 -> ADQUISICION DEL RUBRO ALIMENTOS PARA PERSONAS (LECHE FORTIFICADA)
