Workbook

Sheet Necesidades Trimestrales
B2: Pedido de Necesidades Trimestrales
A4: JURISDICCION: | C4: 40 - Ministerio de Salud
A5: SAF N°: | C5: 23 - Hospital Interzonal San Juan Bautista
A6: EJERCICIO: | C6: 2022
A7: TRIMESTRE: | C7: 3
A9: ID | B9: CODIGO ITEM | C9: RUBRO DE COMPRA | D9: I.P.P. | E9: DESCRIPCION | F9: UNIDAD DE MEDIDA | G9: CANTIDAD | H9: PRECIO UNITARIO ESTIMADO | I9: IMPORTE TOTAL ESTIMADO
A10: 1 | B10: 2.9.1-6951.28 | C10: ELEMENTOS DE LIMPIEZA | D10: 2.9.1 | E10: LIMPIADORES; TIPO: LAVANDINA, PRESENTACION: ENVASE X 1 L | F10: LITRO | G10: 3000 | H10: 98 | I10: =G10*H10 -> 294000
A11: 2 | B11: 2.9.1-6951.28 | C11: ELEMENTOS DE LIMPIEZA | D11: 2.9.1 | E11: LIMPIADORES; TIPO: LAVANDINA, PRESENTACION: ENVASE X 1 L | F11: LITRO | G11: 200 | H11: 120 | I11: =G11*H11 -> 24000
A12: 3 | B12: 2.9.1-6951.203 | C12: ELEMENTOS DE LIMPIEZA | D12: 2.9.1 | E12: LIMPIADORES; TIPO: DESODORANTE LIQUIDO , PRESENTACION: ENVASE X 1 L | F12: LITRO | G12: 3500 | H12: 144 | I12: =G12*H12 -> 504000
A13: 4 | B13: 2.9.1-6951.214 | C13: ELEMENTOS DE LIMPIEZA | D13: 2.9.1 | E13: LIMPIADORES; TIPO: DETERGENTE NEUTRO, PRESENTACION: ENVASE X 5 L | F13: LITRO | G13: 80 | H13: 1895 | I13: =G13*H13 -> 151600
A14: 5 | B14: 2.9.1-6952.61 | C14: ELEMENTOS DE LIMPIEZA | D14: 2.9.1 | E14: CEPILLOS; TIPO: ESCOBA REFORZADA, MATERIAL: PLASTICO | F14: UNIDAD | G14: 20 | H14: 328 | I14: =G14*H14 -> 6560
A15: 6 | B15: 2.9.1-1083.10 | C15: ELEMENTOS DE LIMPIEZA | D15: 2.9.1 | E15: ESPONJA DE ACERO; PESO: 80 GR, MATERIAL: ACERO INOXIDABLE | F15: UNIDAD | G15: 150 | H15: 58.5 | I15: =G15*H15 -> 8775
A16: 7 | B16: 2.9.1-1164.10 | C16: ELEMENTOS DE LIMPIEZA | D16: 2.9.1 | E16: ESPONJAS; MATERIAL: ESPONJA NATURAL, USO: P/COCINA, FORMA: RECTANGULAR, COLOR: AMARILLO, ADITAMENTO: SIN VALOR, LARGO X ANCHO X ESP: 9,7 X 5,7 Cm | F16: UNIDAD | G16: 200 | H16: 49.5 | I16: =G16*H16 -> 9900
A17: 8 | B17: 2.9.1-714.3 | C17: ELEMENTOS DE LIMPIEZA | D17: 2.9.1 | E17: FRANELAS; DIMENSION: 50 X 45 Cm | F17: UNIDAD | G17: 150 | H17: 155 | I17: =G17*H17 -> 23250
A18: 9 | B18: 2.9.1-761.5 | C18: ELEMENTOS DE LIMPIEZA | D18: =LEFT(B18,5) -> 2.9.1 | E18: GUANTES P/LIMPIEZA; TAMAÑO: GRANDE, MATERIAL: LATEX C/FELPA INTERIOR | F18: PAR | G18: 175 | H18: 240 | I18: =G18*H18 -> 42000
A19: 10 | B19: 2.9.1-761.8 | C19: ELEMENTOS DE LIMPIEZA | D19: =LEFT(B19,5) -> 2.9.1 | E19: GUANTES P/LIMPIEZA; TAMAÑO: EXTRA GRANDE, MATERIAL: LATEX C/FELPA INTERIOR | F19: PAR | G19: 75 | H19: 240 | I19: =G19*H19 -> 18000
A20: 11 | B20: 2.5.1-9004.1235 | C20: QUIMICOS | D20: =LEFT(B20,5) -> 2.5.1 | E20: SALES; COMPUESTO QUIMICO: HIPOCLORITO DE SODIO, ESTADO: SOLUCION, CALIDAD: COMERCIAL, CONCENTRACION/PUREZA: 100 GR/L, PRESENTACION: ENVASE X 5 L, GRADO HIDRATACION: SOLUCION | F20: LITRO | G20: 200 | H20: 405 | I20: =G20*H20 -> 81000
A21: 12 | B21: 2.9.4-719.7 | C21: BAZAR Y MENAJE | D21: =LEFT(B21,5) -> 2.9.4 | E21: JARRAS; CAPACIDAD: 1000 mL, MATERIAL: PLASTICO | F21: UNIDAD | G21: 30 | H21: 800 | I21: =G21*H21 -> 24000
A22: 13 | B22: 2.9.1-6960.27 | C22: ELEMENTOS DE LIMPIEZA | D22: =LEFT(B22,5) -> 2.9.1 | E22: ELEM. LIMPIEZA P/INDUMENTARIA; TIPO: JABON EN PAN, PRESENTACION: 200 GR | F22: UNIDAD | G22: 70 | H22: 115 | I22: =G22*H22 -> 8050
A23: 14 | B23: 2.9.1-6956.73 | C23: ELEMENTOS DE LIMPIEZA | D23: =LEFT(B23,5) -> 2.9.1 | E23: ARTICULOS DE TOCADOR; TIPO: JABON LIQUIDO, PRESENTACION: ENVASE X 5 L | F23: LITRO | G23: 60 | H23: 648 | I23: =G23*H23 -> 38880
A24: 15 | B24: 2.9.1-6960.20 | C24: ELEMENTOS DE LIMPIEZA | D24: =LEFT(B24,5) -> 2.9.1 | E24: ELEM. LIMPIEZA P/INDUMENTARIA; TIPO: JABON EN POLVO, PRESENTACION: ENVASE X 3 Kg | F24: PAQUETE | G24: 200 | H24: 1500 | I24: =G24*H24 -> 300000
A25: 16 | B25: 2.5.4-505.13 | C25: ELEMENTOS DE LIMPIEZA | D25: =LEFT(B25,5) -> 2.5.4 | E25: DESINFECTANTES; CAPACIDAD: 5 L, USO P/CONTROL: BACTERIAS, PRINCIPIO ACTIVO: SAL AMONIO CUATERNARIO, PRESENTACION: ENVASE X 5 L, CONTROL: BACTERIAS | F25: LITRO | G25: 25 | H25: 708.5 | I25: =G25*H25 -> 17712.5
A26: 17 | B26: 2.9.1-6951.116 | C26: ELEMENTOS DE LIMPIEZA | D26: =LEFT(B26,5) -> 2.9.1 | E26: LIMPIADORES; TIPO: LIMPIAVIDRIOS, PRESENTACION: ENVASE X 5 L | F26: LITRO | G26: 7 | H26: 470 | I26: =G26*H26 -> 3290
A27: 18 | B27: 2.9.1-6951.110 | C27: ELEMENTOS DE LIMPIEZA | D27: =LEFT(B27,5) -> 2.9.1 | E27: LIMPIADORES; TIPO: SECUESTRANTE DE POLVO, PRESENTACION: ENVASE X 5 L | F27: LITRO | G27: 25 | H27: 3150 | I27: =G27*H27 -> 78750
A28: 19 | B28: 2.9.1-6950.30 | C28: ELEMENTOS DE LIMPIEZA | D28: =LEFT(B28,5) -> 2.9.1 | E28: LUSTRADORES; TIPO: LUSTRAMUEBLES, PRESENTACION: AEROSOL X 360 CM3 | F28: UNIDAD | G28: 25 | H28: 295 | I28: =G28*H28 -> 7375
A29: 20 | B29: 2.9.1-544.12 | C29: ELEMENTOS DE LIMPIEZA | D29: =LEFT(B29,5) -> 2.9.1 | E29: DESODORANTES DE AMBIENTE; CONTENIDO: 440 CM3, FRAGANCIA: CAMPOS DE LAVANDA, FORMATO: AEROSOL, PRESENTACION: CAJA X 24, LIBRE DE CFC: SI | F29: CAJA | G29: 4 | H29: 9276 | I29: =G29*H29 -> 37104
... A51: 42 | B51: 2.3.4-783.25 | C51: ELEMENTOS DE LIMPIEZA | D51: =LEFT(B51,5) -> 2.3.4 | E51: TOALLAS DE PAPEL; MATERIAL: PAPEL TISSUE, GRAMAJE: 50/55 GR/M2, DIMENSION: 22 X 36 Cm, COLOR: BLANCO, PRESENTACION: CAJA X 10 PAQ. 250 USOS | F51: CAJA | G51: 300 | H51: 1800 | I51: =G51*H51 -> 540000
B53: Plazo de entrega: 15 dias corridos
B54: Lugar de entrega: Sección Deposito Central - Avda. Illia y Mariano Moreno
B55: Mantenimiento de Oferta: 45 dias habiles
B57: Especificidades Item N° 1:
B59: Descripción técnica
C60: 55 GRAMOS DE CLORO POR LITRO - DEBIDAMENTE ETIQUETADO CADA BOTELLA
B61: Plazos y lugares de entrega
C62: 15 dias - Deposito Central del HISJB
B64: Calidad Minima esperada
B66: Mantenimiento
C67: 45 dias habiles
B68: Garantia
B72: Especificidades Item N° 2:
B74: Descripción técnica
C75: 55 A 60 GRAMOS DE CLORO POR LITRO - DEBIDAMENTE ETIQUETADA CADA BOTELLA
B76: Plazos y lugares de entrega
C77: 15 dias - Deposito Central del HISJB
B79: Calidad Minima esperada
B81: Mantenimiento
C82: 45 dias habiles
B83: Garantia
B88: Especificidades Item N° 3:
B90: Descripción técnica
C91: AROMAS CHERRY, LAVANDA O CITRONELA - DEBIDAMENTE ETIQUETADA CADA ENVASE
B92: Plazos y lugares de entrega
C93: 15 dias - Deposito Central del HISJB
B95: Calidad Minima esperada
B97: Mantenimiento
C98: 45 dias habiles
B99: Garantia
B104: Especificidades Item N° 4:
B106: Descripción técnica
C107: 15 % DE MATERIA ACTIVA POR BIDON DE 5 LITROS
B108: Plazos y lugares de entrega
C109: 15 dias - Deposito Central del HISJB
B111: Calidad Minima esperada
B113: Mantenimiento
C114: 45 dias habiles
B115: Garantia
B120: Especificidades Item N° 9:
B122: Descripción técnica
C123: Tamaño Grande ; Color Amarillo o Naranjado
B124: Plazos y lugares de entrega
C125: 15 dias - Deposito Central del HISJB
B127: Calidad Minima esperada
B129: Mantenimiento
C130: 45 dias habiles
B131: Garantia
B136: Especificidades Item N° 10:
B138: Descripción técnica
C139: Tamaño Grande ; Color Amarillo o Naranjado
B140: Plazos y lugares de entrega
C141: 15 dias - Deposito Central del HISJB
B143: Calidad Minima esperada
B145: Mantenimiento
C146: 45 dias habiles
B147: Garantia
B152: Especificidades Item N° 11:
B154: Descripción técnica
C155: EN ENVASE OSCURO Y ESTIBADO EN CAJAS
B156: Plazos y lugares de entrega
C157: 15 dias - Deposito Central del HISJB
B159: Calidad Minima esperada
B161: Mantenimiento
C162: 45 dias habiles
B163: Garantia
B168: Especificidades Item N° 13:
B170: Descripción técnica
C171: JABON NEUTRO
B172: Plazos y lugares de entrega
C173: 15 dias - Deposito Central del HISJB
B175: Calidad Minima esperada
B177: Mantenimiento
...

Sheet NotaPedido
A1: NOTA DE PEDIDO 86 | J1: N° | K1: DOCFI-2022-01238708-CAT-DMAN#HSJB
A3: JURISDICCIÓN: | D3: ='Necesidades Trimestrales'!C4 -> 40 - Ministerio de Salud
A4: SAF: | D4: ='Necesidades Trimestrales'!C5 -> 23 - Hospital Interzonal San Juan Bautista
A5: UNIDAD EJECUTORA: | D5: 237 - Direccion de Mantenimiento
A6: DEPENDENCIA SOLICITANTE: | D6: Deposito Central
A7: PERIODO UTILIZACIÓN: | D7: ='Necesidades Trimestrales'!C7 & "° Trimestre - Año " & 'Necesidades Trimestrales'!C6 -> 3° Trimestre - Año 2022
A8: OBJETO: | D8: Adquisición de Elementos de limpieza
A10: Ítem | B10: Codigo Item | C10: DESCRIPCIÓN | H10: Adjunta Detalle Técnico | I10: Unidad Medida | J10: Precio Unitario Estimado | K10: Cantidad Solicitada
A12: 1 | B12: ='Necesidades Trimestrales'!B10 -> 2.9.1-6951.28 | C12: ='Necesidades Trimestrales'!E10 -> LIMPIADORES; TIPO: LAVANDINA, PRESENTACION: ENVASE X 1 L | H12: SI | I12: ='Necesidades Trimestrales'!F10 -> LITRO | J12: ='Necesidades Trimestrales'!H10 -> 98 | K12: ='Necesidades Trimestrales'!G10 -> 3000
A13: 2 | B13: ='Necesidades Trimestrales'!B11 -> 2.9.1-6951.28 | C13: ='Necesidades Trimestrales'!E11 -> LIMPIADORES; TIPO: LAVANDINA, PRESENTACION: ENVASE X 1 L | H13: SI | I13: ='Necesidades Trimestrales'!F11 -> LITRO | J13: ='Necesidades Trimestrales'!H11 -> 120 | K13: ='Necesidades Trimestrales'!G11 -> 200
A14: 3 | B14: ='Necesidades Trimestrales'!B12 -> 2.9.1-6951.203 | C14: ='Necesidades Trimestrales'!E12 -> LIMPIADORES; TIPO: DESODORANTE LIQUIDO , PRESENTACION: ENVASE X 1 L | H14: SI | I14: ='Necesidades Trimestrales'!F12 -> LITRO | J14: ='Necesidades Trimestrales'!H12 -> 144 | K14: ='Necesidades Trimestrales'!G12 -> 3500
A15: 4 | B15: ='Necesidades Trimestrales'!B13 -> 2.9.1-6951.214 | C15: ='Necesidades Trimestrales'!E13 -> LIMPIADORES; TIPO: DETERGENTE NEUTRO, PRESENTACION: ENVASE X 5 L | H15: SI | I15: ='Necesidades Trimestrales'!F13 -> LITRO | J15: ='Necesidades Trimestrales'!H13 -> 1895 | K15: ='Necesidades Trimestrales'!G13 -> 80
A16: 5 | B16: ='Necesidades Trimestrales'!B14 -> 2.9.1-6952.61 | C16: ='Necesidades Trimestrales'!E14 -> CEPILLOS; TIPO: ESCOBA REFORZADA, MATERIAL: PLASTICO | H16: NO | I16: ='Necesidades Trimestrales'!F14 -> UNIDAD | J16: ='Necesidades Trimestrales'!H14 -> 328 | K16: ='Necesidades Trimestrales'!G14 -> 20
A17: 6 | B17: ='Necesidades Trimestrales'!B15 -> 2.9.1-1083.10 | C17: ='Necesidades Trimestrales'!E15 -> ESPONJA DE ACERO; PESO: 80 GR, MATERIAL: ACERO INOXIDABLE | H17: NO | I17: ='Necesidades Trimestrales'!F15 -> UNIDAD | J17: ='Necesidades Trimestrales'!H15 -> 58.5 | K17: ='Necesidades Trimestrales'!G15 -> 150
A18: 7 | B18: ='Necesidades Trimestrales'!B16 -> 2.9.1-1164.10 | C18: ='Necesidades Trimestrales'!E16 -> ESPONJAS; MATERIAL: ESPONJA NATURAL, USO: P/COCINA, FORMA: RECTANGULAR, COLOR: AMARILLO, ADITAMENTO: SIN VALOR, LARGO X ANCHO X ESP: 9,7 X 5,7 Cm | H18: NO | I18: ='Necesidades Trimestrales'!F16 -> UNIDAD | J18: ='Necesidades Trimestrales'!H16 -> 49.5 | K18: ='Necesidades Trimestrales'!G16 -> 200
A19: 8 | B19: ='Necesidades Trimestrales'!B17 -> 2.9.1-714.3 | C19: ='Necesidades Trimestrales'!E17 -> FRANELAS; DIMENSION: 50 X 45 Cm | H19: NO | I19: ='Necesidades Trimestrales'!F17 -> UNIDAD | J19: ='Necesidades Trimestrales'!H17 -> 155 | K19: ='Necesidades Trimestrales'!G17 -> 150
A20: 9 | B20: ='Necesidades Trimestrales'!B18 -> 2.9.1-761.5 | C20: ='Necesidades Trimestrales'!E18 -> GUANTES P/LIMPIEZA; TAMAÑO: GRANDE, MATERIAL: LATEX C/FELPA INTERIOR | H20: SI | I20: ='Necesidades Trimestrales'!F18 -> PAR | J20: ='Necesidades Trimestrales'!H18 -> 240 | K20: ='Necesidades Trimestrales'!G18 -> 175
A21: 10 | B21: ='Necesidades Trimestrales'!B19 -> 2.9.1-761.8 | C21: ='Necesidades Trimestrales'!E19 -> GUANTES P/LIMPIEZA; TAMAÑO: EXTRA GRANDE, MATERIAL: LATEX C/FELPA INTERIOR | H21: SI | I21: ='Necesidades Trimestrales'!F19 -> PAR | J21: ='Necesidades Trimestrales'!H19 -> 240 | K21: ='Necesidades Trimestrales'!G19 -> 75
A22: 11 | B22: ='Necesidades Trimestrales'!B20 -> 2.5.1-9004.1235 | C22: ='Necesidades Trimestrales'!E20 -> SALES; COMPUESTO QUIMICO: HIPOCLORITO DE SODIO, ESTADO: SOLUCION, CALIDAD: COMERCIAL, CONCENTRACION/PUREZA: 100 GR/L, PRESENTACION: ENVASE X 5 L, GRADO HIDRATACION: SOLUCION | H22: SI | I22: ='Necesidades Trimestrales'!F20 -> LITRO | J22: ='Necesidades Trimestrales'!H20 -> 405 | K22: ='Necesidades Trimestrales'!G20 -> 200
A23: 12 | B23: ='Necesidades Trimestrales'!B21 -> 2.9.4-719.7 | C23: ='Necesidades Trimestrales'!E21 -> JARRAS; CAPACIDAD: 1000 mL, MATERIAL: PLASTICO | H23: NO | I23: ='Necesidades Trimestrales'!F21 -> UNIDAD | J23: ='Necesidades Trimestrales'!H21 -> 800 | K23: ='Necesidades Trimestrales'!G21 -> 30
... A53: 42 | B53: ='Necesidades Trimestrales'!B51 -> 2.3.4-783.25 | C53: ='Necesidades Trimestrales'!E51 -> TOALLAS DE PAPEL; MATERIAL: PAPEL TISSUE, GRAMAJE: 50/55 GR/M2, DIMENSION: 22 X 36 Cm, COLOR: BLANCO, PRESENTACION: CAJA X 10 PAQ. 250 USOS | H53: NO | I53: ='Necesidades Trimestrales'!F51 -> CAJA | J53: ='Necesidades Trimestrales'!H51 -> 1800 | K53: ='Necesidades Trimestrales'!G51 -> 300
A54: Costo total estimado: CUATRO MILLONES DOCIENTOS CUARENTA Y CINCO MIL CUATROACIENTOS DOCE CON 50/100.-- | J54: =SUMPRODUCT(J12:J53,K12:K53) -> 4245412.5

Sheet Autor Gastar
A1: EJERCICIO: | D1: ='Necesidades Trimestrales'!C6 -> 2022 | P1: AUTORIZACION PARA GASTAR
A4: JURISDICCIÓN: | G4: =NotaPedido!D3 -> 40 - Ministerio de Salud
A5: SAF: | G5: =NotaPedido!D4 -> 23 - Hospital Interzonal San Juan Bautista
A6: UNIDAD EJECUTORA: | G6: =NotaPedido!D5 -> 237 - Direccion de Mantenimiento
A7: DEPENDENCIA SOLICITANTE: | G7: =NotaPedido!D6 -> Deposito Central
A8: AUTORIZACIÓN:
A9: Señor Jefe de Servicio Administrativo Financiero:
A10: ="Autorizo la realización de los trámites correspondientes, a fin de proveer a este Organismo los bienes y/o servicios que se detallan en Nota de Pedido N° " & NotaPedido!K1&", afectando la erogación resultante a los créditos presupuestarios aprobados a favor de esta Unidad Ejecutora, conforme al siguiente detalle:" -> Autorizo la realización de los trámites correspondientes, a fin de proveer a este Organismo los bienes y/o servicios que se detallan en Nota de Pedido N° DOCFI-2022-01238708-CAT-DMAN#HSJB, afectando la erogación resultante a los créditos presupuestarios aprobados a favor de esta Unidad Ejecutora, conforme al siguiente detalle:
A12: IMPUTACIÓN PRESUPUESTARIA
A13: CÓDIGO | O13: DENOMINACIÓN DE LA PARTIDA PRESUPUESTARIA | Q13: IMPORTE
A14: PR | B14: SB | C14: PY | D14: AC | E14: OB | F14: UG | G14: FIN | H14: FUN | I14: I | J14: P | K14: P | L14: SubP | M14: M | N14: FF
A15: 33 | D15: 4 | F15: 4901 | G15: 3 | H15: 3.1 | I15: 2 | J15: 3 | K15: 4 | M15: 1 | N15: 1.1 | O15: Productos de papel y cartón | Q15: 1001250
A16: 33 | D16: 4 | F16: 4901 | G16: 3 | H16: 3.1 | I16: 2 | J16: 5 | K16: 1 | M16: 1 | N16: 1.1 | O16: Compuestos Quimicos | Q16: 81000
A17: 33 | D17: 4 | F17: 4901 | G17: 3 | H17: 3.1 | I17: 2 | J17: 5 | K17: 4 | M17: 1 | N17: 1.1 | O17: Insecticida, fumigantes y otros | Q17: 17712.5
A18: 33 | D18: 4 | F18: 4901 | G18: 3 | H18: 3.1 | I18: 2 | J18: 5 | K18: 8 | M18: 1 | N18: 1.1 | O18: Productos de material plástico | Q18: 197100
A19: 33 | D19: 4 | F19: 4901 | G19: 3 | H19: 3.1 | I19: 2 | J19: 9 | K19: 1 | M19: 1 | N19: 1.1 | O19: Elementos de Limpieza | Q19: 2924350
A20: 33 | D20: 4 | F20: 4901 | G20: 3 | H20: 3.1 | I20: 2 | J20: 9 | K20: 4 | M20: 1 | N20: 1.1 | O20: Utensillos de cocina y comedor | Q20: 24000
A23: TOTAL DE PESOS: CUATRO MILLONES DOSCIENTOS CUARENTA Y CINCO MIL CUATROCIENTOS DOCE CON 50/100.--- | Q23: =+SUM(Q15:Q21) -> 4245412.5
A25: JUSTIFICACIÓN:
A26: ="Para la "& NotaPedido!D8 &" para ser destinados al " & NotaPedido!D6 &" del HISJB del Ministerio de Salud." -> Para la Adquisición de Elementos de limpieza para ser destinados al Deposito Central del HISJB del Ministerio de Salud.
