Workbook

Sheet Necesidades Trimestrales
B2: Pedido de Necesidades Trimestrales
A4: JURISDICCION: | C4: 40 - Ministerio de Salud
A5: SAF N°: | C5: 23 - Hospital Interzonal San Juan Bautista
A6: EJERCICIO: | C6: 2022
A7: TRIMESTRE: | C7: 3
A9: ID | B9: CODIGO ITEM | C9: RUBRO DE COMPRA | D9: I.P.P. | E9: DESCRIPCION | F9: UNIDAD DE MEDIDA | G9: CANTIDAD | H9: PRECIO UNITARIO ESTIMADO | I9: IMPORTE TOTAL ESTIMADO
A10: 1 | B10: 2.5.1-9004.770 | C10: QUIMICOS | D10: 251 | E10: SALES; COMPUESTO QUIMICO: CLORURO DE SODIO, ESTADO: SOLIDO, CALIDAD: INDUSTRIAL, CONCENTRACION/PUREZA: 99 %, PRESENTACION: ENVASE X 25 Kg, GRADO HIDRATACION: ANHIDRIDO | F10: BOLSA | G10: 10 | H10: 1500 | I10: =G10*H10 -> 15000
A11: 2 | B11: 2.2.2-808.30 | C11: PROD.MEDICO/FARMACEUTICOS/LAB | D11: 295 | E11: CAMISOLINES DE CIRUGIA; TELA: BRIN SANFORIZADA PRE ENCOGIDO | F11: UNIDAD | G11: 250 | H11: 3560 | I11: =G11*H11 -> 890000
A12: 3 | B12: 2.9.5-2620.6 | C12: PROD.MEDICO/FARMACEUTICOS/LAB | D12: 259 | E12: INDICADORES DE ESTERILIZACION; METODO DE ESTERILIZACION: AUTOCLAVE DE VAPOR, TIPO DE INDICADOR: CINTA INDICADORA, PRESENTACION: ROLLO, METODO: AUTOCLAVE DE VAPOR, INDICADOR: CINTA INDICADORA | F12: ROLLO | G12: 100 | H12: 420 | I12: =G12*H12 -> 42000
A13: 4 | B13: 2.9.5-2620.7 | C13: PROD.MEDICO/FARMACEUTICOS/LAB | D13: 259 | E13: INDICADORES DE ESTERILIZACION; METODO DE ESTERILIZACION: CALOR SECO, PRESENTACION: ROLLO, METODO: CALOR SECO, INDICADOR: CINTA INDICADORA, TIPO DE INDICADOR: CINTA INDICADORA | F13: ROLLO | G13: 30 | H13: 570 | I13: =G13*H13 -> 17100
A14: 5 | B14: 2.9.5-473.89 | C14: PROD.MEDICO/FARMACEUTICOS/LAB | D14: 295 | E14: GASAS; TIPO: HIDROFILA HIDROSAN, PRESENTACION: PIEZA 1,8 KGS | F14: UNIDAD | G14: 700 | H14: 3100 | I14: =G14*H14 -> 2170000
A15: 6 | B15: 2.9.5-1909.225 | C15: PROD.MEDICO/FARMACEUTICOS/LAB | D15: 295 | E15: GUANTES USO MEDICINAL; TIPO: P/QUIMICOS, TAMAÑO: MEDIANO CAÑA LARGA, MATERIAL: NITRILO, PRESENTACION: X PAR | F15: PAR | G15: 2 | H15: 528 | I15: =G15*H15 -> 1056
A16: 7 | B16: 2.9.5-2620.78 | C16: PROD.MEDICO/FARMACEUTICOS/LAB | D16: 251 | E16: INDICADORES DE ESTERILIZACION; PRESENTACION: UNIDAD, METODO: AUTOCLAVE DE VAPOR, INDICADOR: TESTIGO BIOLOGICO, PRESENTACION: ENVASE X 100 | F16: CAJA | G16: 1 | H16: 21500 | I16: =G16*H16 -> 21500
A17: 8 | B17: 2.9.5-2620.2 | C17: PROD.MEDICO/FARMACEUTICOS/LAB | D17: 251 | E17: INDICADORES DE ESTERILIZACION; TIPO DE INDICADOR: TIRAS INTEGRADORAS, PRESENTACION: CAJA X 100 UN, METODO: OXIDO DE ETILENO, METODO DE ESTERILIZACION: OXIDO DE ETILENO, INDICADOR: TIRAS INTEGRADORAS | F17: CAJA | G17: 10 | H17: 1960 | I17: =G17*H17 -> 19600
A18: 9 | B18: 2.9.5-2554.39 | C18: PROD.MEDICO/FARMACEUTICOS/LAB | D18: 259 | E18: PAPELES P/ESTERILIZACION; TIPO: GRADO MEDICO, PRESENTACION: 120 CM X 100 M | F18: BOBINA | G18: 80 | H18: 8200 | I18: =G18*H18 -> 656000
A19: 10 | B19: 2.9.5-2554.26 | C19: PROD.MEDICO/FARMACEUTICOS/LAB | D19: 259 | E19: PAPELES P/ESTERILIZACION; TIPO: GRADO MEDICO, PRESENTACION: ROLLO X 60 CM X 200 M | F19: BOBINA | G19: 80 | H19: 6800 | I19: =G19*H19 -> 544000
A20: 11 | B20: 2.9.5-2554.33 | C20: PROD.MEDICO/FARMACEUTICOS/LAB | D20: 259 | E20: PAPELES P/ESTERILIZACION; TIPO: GRADO MEDICO, PRESENTACION: 80 X 333 Cm | F20: BOBINA | G20: 20 | H20: 9282 | I20: =G20*H20 -> 185640
A21: 12 | B21: 2.9.5-2554.9 | C21: PROD.MEDICO/FARMACEUTICOS/LAB | D21: 259 | E21: PAPELES P/ESTERILIZACION; TIPO: POUCH, PRESENTACION: ROLLO X 10 CM X 200 M | F21: ROLLO | G21: 3 | H21: 4305 | I21: =G21*H21 -> 12915
... A23: 14 | B23: 2.9.5-7694.39 | C23: PROD. MEDICO/FARMACEUTICOS/LAB | D23: 295 | E23: SET DE CIRUGIA; COMPONENTES: 17, USO: CIRUGIA GENERAL - ROPA DESCARTABLE ESTERIL | F23: PAQUETE | G23: 400 | H23: 5405.52 | I23: =G23*H23 -> 2162208
B26: Presentar copia certificada de Resolución de Habilitación expedida por la Subsecretaria de Asistencia en Salud Publica o copia certificada de Certificado de Habilitación de Establecimiento y/o copia certificada de Certificado de Transito Interjurisdiccional emitido por A.N.M.A.T, el que correspondiere conforme a la situación de cada establecimiento cotizante (Laboratorio, Droguería, etc.), en caso de corresponder. Indicar Marca y Numero de Certificado de ANMAT por ítem. VENCIMIENTO DE LOS PRESENTES INSUMOS: UN PLAZO NO MENOR A 12 MESES DE LA FECHA DE RECEPCION
B27: PLAZO DE MANTENIMIENTO DE LA OFERTA: 45 DIAS HABILES
B28: PLAZO DE ENTREGA: 15 DIAS HABILES - SERVICIO DE FARMACIA - ADVA. ILLIA Y MARIANO MORENO - DE LUNES A VIERNES DE 08:00 A 11:00 HORAS DEBIENDO CORRER LOS GASTOS DE FLETES, ACARREO, CARGA, DESCARGA Y SEGURO A CARGO DEL ADJUDICATARIO.
B30: Especificidades ITEMS NUM 5 : Pieza de 80 cm por 40 m. Con hilado no menor de 24/1. - Deberá ser de algodón, doble punto cadena, sin defectos en el plegado, ni en la trama, con 15 hilos/cm2 ( +/- 1),sumando pasadas y cadenas. Hilado no menor de 24/1, con 80 cm de ancho cada cara y 40 m de largo. Peso de 1800 gramos por pieza. Acondicionada en envase individual transparente de polietileno no menor de 70 micrones, herméticamente cerrado y rotulado Cumple con Farmacopea Argentina VI Edición

Sheet NotaPedido
A1: NOTA DE PEDIDO 107 | J1: N° | K1: DOCFI-2022-01527755-CAT-DASIS#HSJB
A3: JURISDICCIÓN: | D3: ='Necesidades Trimestrales'!C4 -> 40 - Ministerio de Salud
A4: SAF: | D4: ='Necesidades Trimestrales'!C5 -> 23 - Hospital Interzonal San Juan Bautista
A5: UNIDAD EJECUTORA: | D5: 168 - Direccion Asistencial
A6: DEPENDENCIA SOLICITANTE: | D6: Servicio de Farmacia
A7: PERIODO UTILIZACIÓN: | D7: SEMESTRAL
A8: OBJETO: | D8: Adquisición de Insumos de Esterilización
A10: Ítem | B10: Codigo Item | C10: DESCRIPCIÓN | H10: Adjunta Detalle Técnico | I10: Unidad Medida | J10: Precio Unitario Estimado | K10: Cantidad Solicitada
A12: 1 | B12: ='Necesidades Trimestrales'!B10 -> 2.5.1-9004.770 | C12: ='Necesidades Trimestrales'!E10 -> SALES; COMPUESTO QUIMICO: CLORURO DE SODIO, ESTADO: SOLIDO, CALIDAD: INDUSTRIAL, CONCENTRACION/PUREZA: 99 %, PRESENTACION: ENVASE X 25 Kg, GRADO HIDRATACION: ANHIDRIDO | H12: NO | I12: ='Necesidades Trimestrales'!F10 -> BOLSA | J12: ='Necesidades Trimestrales'!H10 -> 1500 | K12: ='Necesidades Trimestrales'!G10 -> 10
A13: 2 | B13: ='Necesidades Trimestrales'!B11 -> 2.2.2-808.30 | C13: ='Necesidades Trimestrales'!E11 -> CAMISOLINES DE CIRUGIA; TELA: BRIN SANFORIZADA PRE ENCOGIDO | H13: NO | I13: ='Necesidades Trimestrales'!F11 -> UNIDAD | J13: ='Necesidades Trimestrales'!H11 -> 3560 | K13: ='Necesidades Trimestrales'!G11 -> 250
A14: 3 | B14: ='Necesidades Trimestrales'!B12 -> 2.9.5-2620.6 | C14: ='Necesidades Trimestrales'!E12 -> INDICADORES DE ESTERILIZACION; METODO DE ESTERILIZACION: AUTOCLAVE DE VAPOR, TIPO DE INDICADOR: CINTA INDICADORA, PRESENTACION: ROLLO, METODO: AUTOCLAVE DE VAPOR, INDICADOR: CINTA INDICADORA | H14: NO | I14: ='Necesidades Trimestrales'!F12 -> ROLLO | J14: ='Necesidades Trimestrales'!H12 -> 420 | K14: ='Necesidades Trimestrales'!G12 -> 100
A15: 4 | B15: ='Necesidades Trimestrales'!B13 -> 2.9.5-2620.7 | C15: ='Necesidades Trimestrales'!E13 -> INDICADORES DE ESTERILIZACION; METODO DE ESTERILIZACION: CALOR SECO, PRESENTACION: ROLLO, METODO: CALOR SECO, INDICADOR: CINTA INDICADORA, TIPO DE INDICADOR: CINTA INDICADORA | H15: NO | I15: ='Necesidades Trimestrales'!F13 -> ROLLO | J15: ='Necesidades Trimestrales'!H13 -> 570 | K15: ='Necesidades Trimestrales'!G13 -> 30
A16: 5 | B16: ='Necesidades Trimestrales'!B14 -> 2.9.5-473.89 | C16: ='Necesidades Trimestrales'!E14 -> GASAS; TIPO: HIDROFILA HIDROSAN, PRESENTACION: PIEZA 1,8 KGS | H16: SI | I16: ='Necesidades Trimestrales'!F14 -> UNIDAD | J16: ='Necesidades Trimestrales'!H14 -> 3100 | K16: ='Necesidades Trimestrales'!G14 -> 700
A17: 6 | B17: ='Necesidades Trimestrales'!B15 -> 2.9.5-1909.225 | C17: ='Necesidades Trimestrales'!E15 -> GUANTES USO MEDICINAL; TIPO: P/QUIMICOS, TAMAÑO: MEDIANO CAÑA LARGA, MATERIAL: NITRILO, PRESENTACION: X PAR | H17: NO | I17: ='Necesidades Trimestrales'!F15 -> PAR | J17: ='Necesidades Trimestrales'!H15 -> 528 | K17: ='Necesidades Trimestrales'!G15 -> 2
A18: 7 | B18: ='Necesidades Trimestrales'!B16 -> 2.9.5-2620.78 | C18: ='Necesidades Trimestrales'!E16 -> INDICADORES DE ESTERILIZACION; PRESENTACION: UNIDAD, METODO: AUTOCLAVE DE VAPOR, INDICADOR: TESTIGO BIOLOGICO, PRESENTACION: ENVASE X 100 | H18: NO | I18: ='Necesidades Trimestrales'!F16 -> CAJA | J18: ='Necesidades Trimestrales'!H16 -> 21500 | K18: ='Necesidades Trimestrales'!G16 -> 1
A19: 8 | B19: ='Necesidades Trimestrales'!B17 -> 2.9.5-2620.2 | C19: ='Necesidades Trimestrales'!E17 -> INDICADORES DE ESTERILIZACION; TIPO DE INDICADOR: TIRAS INTEGRADORAS, PRESENTACION: CAJA X 100 UN, METODO: OXIDO DE ETILENO, METODO DE ESTERILIZACION: OXIDO DE ETILENO, INDICADOR: TIRAS INTEGRADORAS | H19: NO | I19: ='Necesidades Trimestrales'!F17 -> CAJA | J19: ='Necesidades Trimestrales'!H17 -> 1960 | K19: ='Necesidades Trimestrales'!G17 -> 10
A20: 9 | B20: ='Necesidades Trimestrales'!B18 -> 2.9.5-2554.39 | C20: ='Necesidades Trimestrales'!E18 -> PAPELES P/ESTERILIZACION; TIPO: GRADO MEDICO, PRESENTACION: 120 CM X 100 M | H20: NO | I20: ='Necesidades Trimestrales'!F18 -> BOBINA | J20: ='Necesidades Trimestrales'!H18 -> 8200 | K20: ='Necesidades Trimestrales'!G18 -> 80
A21: 10 | B21: ='Necesidades Trimestrales'!B19 -> 2.9.5-2554.26 | C21: ='Necesidades Trimestrales'!E19 -> PAPELES P/ESTERILIZACION; TIPO: GRADO MEDICO, PRESENTACION: ROLLO X 60 CM X 200 M | H21: NO | I21: ='Necesidades Trimestrales'!F19 -> BOBINA | J21: ='Necesidades Trimestrales'!H19 -> 6800 | K21: ='Necesidades Trimestrales'!G19 -> 80
A22: 11 | B22: ='Necesidades Trimestrales'!B20 -> 2.9.5-2554.33 | C22: ='Necesidades Trimestrales'!E20 -> PAPELES P/ESTERILIZACION; TIPO: GRADO MEDICO, PRESENTACION: 80 X 333 Cm | H22: NO | I22: ='Necesidades Trimestrales'!F20 -> BOBINA | J22: ='Necesidades Trimestrales'!H20 -> 9282 | K22: ='Necesidades Trimestrales'!G20 -> 20
A23: 12 | B23: ='Necesidades Trimestrales'!B21 -> 2.9.5-2554.9 | C23: ='Necesidades Trimestrales'!E21 -> PAPELES P/ESTERILIZACION; TIPO: POUCH, PRESENTACION: ROLLO X 10 CM X 200 M | H23: NO | I23: ='Necesidades Trimestrales'!F21 -> ROLLO | J23: ='Necesidades Trimestrales'!H21 -> 4305 | K23: ='Necesidades Trimestrales'!G21 -> 3
... A25: 14 | B25: ='Necesidades Trimestrales'!B23 -> 2.9.5-7694.39 | C25: ='Necesidades Trimestrales'!E23 -> SET DE CIRUGIA; COMPONENTES: 17, USO: CIRUGIA GENERAL - ROPA DESCARTABLE ESTERIL | H25: NO | I25: ='Necesidades Trimestrales'!F23 -> PAQUETE | J25: ='Necesidades Trimestrales'!H23 -> 5405.52 | K25: ='Necesidades Trimestrales'!G23 -> 400
A26: Costo total estimado: PESOS SEIS MILLONES SETECIENTOS CINCUENTA Y NUEVE MIL DOSCIENTOS DIECINUEVE CON 00/100.- | J26: =SUMPRODUCT(J12:J25,K12:K25) -> 6759219

Sheet Autor Gastar
A1: EJERCICIO: | D1: ='Necesidades Trimestrales'!C6 -> 2022 | P1: AUTORIZACION PARA GASTAR
A4: JURISDICCIÓN: | G4: =NotaPedido!D3 -> 40 - Ministerio de Salud
A5: SAF: | G5: =NotaPedido!D4 -> 23 - Hospital Interzonal San Juan Bautista
A6: UNIDAD EJECUTORA: | G6: =NotaPedido!D5 -> 168 - Direccion Asistencial
A7: DEPENDENCIA SOLICITANTE: | G7: =NotaPedido!D6 -> Servicio de Farmacia
A8: AUTORIZACIÓN:
A9: Señor Jefe de Servicio Administrativo Financiero:
A10: ="Autorizo la realización de los trámites correspondientes, a fin de proveer a este Organismo los bienes y/o servicios que se detallan en Nota de Pedido N° " & NotaPedido!K1&", afectando la erogación resultante a los créditos presupuestarios aprobados a favor de esta Unidad Ejecutora, conforme al siguiente detalle:" -> Autorizo la realización de los trámites correspondientes, a fin de proveer a este Organismo los bienes y/o servicios que se detallan en Nota de Pedido N° DOCFI-2022-01527755-CAT-DASIS#HSJB, afectando la erogación resultante a los créditos presupuestarios aprobados a favor de esta Unidad Ejecutora, conforme al siguiente detalle:
A12: IMPUTACIÓN PRESUPUESTARIA
A13: CÓDIGO | O13: DENOMINACIÓN DE LA PARTIDA PRESUPUESTARIA | Q13: IMPORTE
A14: PR | B14: SB | C14: PY | D14: AC | E14: OB | F14: UG | G14: FIN | H14: FUN | I14: I | J14: P | K14: P | L14: SubP | M14: M | N14: FF
A15: 33 | D15: 2 | F15: 4901 | G15: 3 | H15: 3.1 | I15: 2 | J15: 5 | K15: 1 | M15: 1 | N15: 1.1 | O15: Compuestos Quimicos | Q15: 56100
A16: 33 | D16: 2 | F16: 4901 | G16: 3 | H16: 3.1 | I16: 2 | J16: 5 | K16: 9 | M16: 1 | N16: 1.1 | O16: Otros NEP | Q16: 1479855
A17: 33 | D17: 2 | F17: 4901 | G17: 3 | H17: 3.1 | I17: 2 | J17: 9 | K17: 5 | M17: 1 | N17: 1.1 | O17: Utiles Menores Med. Quir. y de Lab. | Q17: 5223264
A22: TOTAL DE PESOS: SEIS MILLONES SETECIENTOS CINCUENTA Y NUEVE MIL DOSCIENTOS DIECINUEVE CON 00/100.- | Q22: =SUM(Q15:Q21) -> 6759219
A24: JUSTIFICACIÓN:
A25: ="Para la "& NotaPedido!D8 &" para ser destinados al " & NotaPedido!D6 &" del HISJB del Ministerio de Salud." -> Para la Adquisición de Insumos de Esterilización para ser destinados al Servicio de Farmacia del HISJB del Ministerio de Salud.
