Workbook

Sheet Necesidades Trimestrales
B2: Pedido de Necesidades Trimestrales
A4: JURISDICCION: | C4: 95 - Ministerio de Cultura, Turismo y Deporte.-
A5: SAF N°: | C5: 18 - Secretaria de Administración y Recursos Humanos.-
A6: EJERCICIO: | C6: 2022
A7: TRIMESTRE: | C7: 2° Trimestre
A10: ID | B10: CODIGO ITEM | C10: RUBRO DE COMPRA | D10: I.P.P. | E10: DESCRIPCION | F10: UNIDAD DE MEDIDA | G10: CANTIDAD | H10: PRECIO UNITARIO ESTIMADO | I10: IMPORTE TOTAL ESTIMADO
A11: 1 | B11: 2.9.1-6951.303 | C11: ELEMENTOS DE LIMPIEZA | D11: =LEFT(B11,5) -> 2.9.1 | E11: LIMPIADORES; TIPO: LIMPIA MUEBLES, PRESENTACION: AEROSOL X 360 CM3, BIODEGRADABLE: SI | F11: UNIDAD | G11: 30 | H11: 207.9 | I11: =G11*H11 -> 6237
A12: 2 | B12: 2.9.1-6951.41 | C12: ELEMENTOS DE LIMPIEZA | D12: =LEFT(B12,5) -> 2.9.1 | E12: LIMPIADORES; TIPO: DESINFECTANTE P/PISO, PRESENTACION: ENVASE X 5 L | F12: UNIDAD | G12: 80 | H12: 253.6 | I12: =G12*H12 -> 20288
A13: 3 | B13: 2.9.1-6956.27 | C13: ELEMENTOS DE LIMPIEZA | D13: =LEFT(B13,5) -> 2.9.1 | E13: ARTICULOS DE TOCADOR; TIPO: JABON DE TOCADOR LIQUIDO, PRESENTACION: ENVASE X 5 L | F13: UNIDAD | G13: 30 | H13: 724.5 | I13: =G13*H13 -> 21735
A14: 4 | B14: 2.9.1-564.23 | C14: ELEMENTOS DE LIMPIEZA | D14: =LEFT(B14,5) -> 2.9.1 | E14: BALDES DE PLASTICO; CAPACIDAD: 12 L, TIPO DE PLASTICO: POLIPROPILENO | F14: UNIDAD | G14: 30 | H14: 491.7 | I14: =G14*H14 -> 14751
A15: 5 | B15: 2.9.1-646.32 | C15: ELEMENTOS DE LIMPIEZA | D15: =LEFT(B15,5) -> 2.9.1 | E15: BOLSAS DE RESIDUOS; DIMENSION: 120 X 90 Cm, PRESENTACION: BOLSA X 100, ESPESOR: 60 Mn, COLOR: NEGRO | F15: BOLSA | G15: 30 | H15: 353.7 | I15: =G15*H15 -> 10611
A16: 6 | B16: 2.9.1-646.98 | C16: ELEMENTOS DE LIMPIEZA | D16: =LEFT(B16,5) -> 2.9.1 | E16: BOLSAS DE RESIDUOS; DIMENSION: 90 X 60 Cm, PRESENTACION: ENVASE X 50 UN, ESPESOR: 120 Mn | F16: BOLSA | G16: 30 | H16: 116 | I16: =G16*H16 -> 3480
A17: 7 | B17: 2.9.1-6952.75 | C17: ELEMENTOS DE LIMPIEZA | D17: =LEFT(B17,5) -> 2.9.1 | E17: CEPILLOS; TIPO: ESCOBA BARREHOJAS, MATERIAL: CERDAS METALICAS | F17: UNIDAD | G17: 40 | H17: 681.1 | I17: =G17*H17 -> 27244
A18: 8 | B18: 2.9.1-6952.29 | C18: ELEMENTOS DE LIMPIEZA | D18: =LEFT(B18,5) -> 2.9.1 | E18: CEPILLOS; TIPO: ESCOBILLA LIMPIA INODORO, MATERIAL: PLASTICO | F18: UNIDAD | G18: 50 | H18: 222.6 | I18: =G18*H18 -> 11130
A19: 9 | B19: 2.9.1-6952.45 | C19: ELEMENTOS DE LIMPIEZA | D19: =LEFT(B19,5) -> 2.9.1 | E19: CEPILLOS; TIPO: ESCOBILLA LIMPIAVIDRIOS, MATERIAL: PLASTICO Y GOMA | F19: UNIDAD | G19: 25 | H19: 476.1 | I19: =G19*H19 -> 11902.5
A20: 10 | B20: 2.9.1-544.64 | C20: ELEMENTOS DE LIMPIEZA | D20: =LEFT(B20,5) -> 2.9.1 | E20: DESODORANTES DE AMBIENTE; FORMATO: AEROSOL, FRAGANCIA: CAMPOS DE JAZMIN, PRESENTACION: ENVASE X 360 CM3, LIBRE DE CFC: SI | F20: UNIDAD | G20: 200 | H20: 203.6 | I20: =G20*H20 -> 40720
A21: 11 | B21: 2.9.1-6961.27 | C21: ELEMENTOS DE LIMPIEZA | D21: =LEFT(B21,5) -> 2.9.1 | E21: ELEM. P/LIMPIEZA SANITARIOS; TIPO: BOLILLA P/MINGITORIO, PRESENTACION: ENVASE X 480 GR | F21: UNIDAD | G21: 50 | H21: 196.7 | I21: =G21*H21 -> 9835
A22: 12 | B22: 2.9.1-6961.23 | C22: ELEMENTOS DE LIMPIEZA | D22: =LEFT(B22,5) -> 2.9.1 | E22: ELEM. P/LIMPIEZA SANITARIOS; TIPO: SODA CAUSTICA, PRESENTACION: ENVASE X 1 Kg | F22: UNIDAD | G22: 50 | H22: 900 | I22: =G22*H22 -> 45000
... A37: 27 | B37: 2.5.4-505.13 | C37: ELEMENTOS DE LIMPIEZA | D37: =LEFT(B37,5) -> 2.5.4 | E37: DESINFECTANTES; CAPACIDAD: 5 L, USO P/CONTROL: BACTERIAS, PRINCIPIO ACTIVO: SAL AMONIO CUATERNARIO, PRESENTACION: ENVASE X 5 L, CONTROL: BACTERIAS | F37: UNIDAD | G37: 150 | H37: 1200 | I37: =G37*H37 -> 180000
I38: =SUM(I11:I37) -> 860183.5
B40: Especificidades Item N° 2, 3, 13, 16, 17, 22, 27 :
B42: Descripción técnica:
C43: NO SE ACEPTARAN PRODUCTOS PARA DILUIR, SOLO SE TENDRAN EN CUENTA PRODUCTOS PREPARADOS SOLO LISTOS PARA SU USO.-
B44: Especificidades Item N° 15:
B46: Descripción técnica:
C47: DETERGENTE BIODEGRADABLE CONCENTRADO 15% DE MATERIA ACTIVA EN ENVASE DE 5 L. Y ETIQUETADO.-
B48: Plazo y Lugar de entrega:
C49: El plazo de entrega no podrá ser superior a los Diez (10) días hábiles a partir de la fecha de recepción de la respectiva Orden de Compra. La entrega de dichos bienes se realizará en la Secretaria de Administracion y Recursos Humanos, sito en Avda. Mexico S/N° - Predio Ferial Catamarca, en la ciudad de San Fernando del Valle de Catamarca de 8:00hs. a 13:00hs. debiendo correr los gastos de fletes, acarreo, carga, descarga y seguro a cargo del adjudicatario. Se presentará Remito que deberá cumplimentar lo dispuesto por la R.G. AFIP 1415/03, sin excepción.
B50: Calidad Minima esperada:
B52: Mantenimiento:
C53: Treinta (30) días hábiles.-
B54: Garantia:

Sheet Nota Pedido
A1: NOTA DE PEDIDO | J1: N° | K1: 005/2022
A3: JURISDICCIÓN: | D3: ='Necesidades Trimestrales'!C4 -> 95 - Ministerio de Cultura, Turismo y Deporte.-
A4: SAF: | D4: ='Necesidades Trimestrales'!C5 -> 18 - Secretaria de Administración y Recursos Humanos.-
A5: UNIDAD EJECUTORA: | D5: Secretaria de Administración y Recursos Humanos.-
A6: DEPENDENCIA SOLICITANTE: | D6: Ministerio de Cultura, Turismo y Deporte.-
A7: PERIODO UTILIZACIÓN: | D7: ='Necesidades Trimestrales'!C7 & " - Año " & 'Necesidades Trimestrales'!C6 -> 2° Trimestre - Año 2022
A8: OBJETO: | D8: Compra de elementos de limpieza para ser usadas por las distintas áreas y dependencias del Ministerio de Cultura, Turismo y Deporte.-
A10: Ítem | B10: Codigo Item | C10: DESCRIPCIÓN | H10: Adjunta Detalle Técnico | I10: Unidad Medida | J10: Cantidad Solicitada | K10: Precio Unitario Estimado
A12: 1 | B12: ='Necesidades Trimestrales'!B11 -> 2.9.1-6951.303 | C12: ='Necesidades Trimestrales'!E11 -> LIMPIADORES; TIPO: LIMPIA MUEBLES, PRESENTACION: AEROSOL X 360 CM3, BIODEGRADABLE: SI | H12: NO | I12: ='Necesidades Trimestrales'!F11 -> UNIDAD | J12: ='Necesidades Trimestrales'!G11 -> 30 | K12: ='Necesidades Trimestrales'!H11 -> 207.9
A13: 2 | B13: ='Necesidades Trimestrales'!B12 -> 2.9.1-6951.41 | C13: ='Necesidades Trimestrales'!E12 -> LIMPIADORES; TIPO: DESINFECTANTE P/PISO, PRESENTACION: ENVASE X 5 L | H13: NO | I13: ='Necesidades Trimestrales'!F12 -> UNIDAD | J13: ='Necesidades Trimestrales'!G12 -> 80 | K13: ='Necesidades Trimestrales'!H12 -> 253.6
A14: 3 | B14: ='Necesidades Trimestrales'!B13 -> 2.9.1-6956.27 | C14: ='Necesidades Trimestrales'!E13 -> ARTICULOS DE TOCADOR; TIPO: JABON DE TOCADOR LIQUIDO, PRESENTACION: ENVASE X 5 L | H14: NO | I14: ='Necesidades Trimestrales'!F13 -> UNIDAD | J14: ='Necesidades Trimestrales'!G13 -> 30 | K14: ='Necesidades Trimestrales'!H13 -> 724.5
A15: 4 | B15: ='Necesidades Trimestrales'!B14 -> 2.9.1-564.23 | C15: ='Necesidades Trimestrales'!E14 -> BALDES DE PLASTICO; CAPACIDAD: 12 L, TIPO DE PLASTICO: POLIPROPILENO | H15: NO | I15: ='Necesidades Trimestrales'!F14 -> UNIDAD | J15: ='Necesidades Trimestrales'!G14 -> 30 | K15: ='Necesidades Trimestrales'!H14 -> 491.7
A16: 5 | B16: ='Necesidades Trimestrales'!B15 -> 2.9.1-646.32 | C16: ='Necesidades Trimestrales'!E15 -> BOLSAS DE RESIDUOS; DIMENSION: 120 X 90 Cm, PRESENTACION: BOLSA X 100, ESPESOR: 60 Mn, COLOR: NEGRO | H16: NO | I16: ='Necesidades Trimestrales'!F15 -> BOLSA | J16: ='Necesidades Trimestrales'!G15 -> 30 | K16: ='Necesidades Trimestrales'!H15 -> 353.7
A17: 6 | B17: ='Necesidades Trimestrales'!B16 -> 2.9.1-646.98 | C17: ='Necesidades Trimestrales'!E16 -> BOLSAS DE RESIDUOS; DIMENSION: 90 X 60 Cm, PRESENTACION: ENVASE X 50 UN, ESPESOR: 120 Mn | H17: NO | I17: ='Necesidades Trimestrales'!F16 -> BOLSA | J17: ='Necesidades Trimestrales'!G16 -> 30 | K17: ='Necesidades Trimestrales'!H16 -> 116
A18: 7 | B18: ='Necesidades Trimestrales'!B17 -> 2.9.1-6952.75 | C18: ='Necesidades Trimestrales'!E17 -> CEPILLOS; TIPO: ESCOBA BARREHOJAS, MATERIAL: CERDAS METALICAS | H18: NO | I18: ='Necesidades Trimestrales'!F17 -> UNIDAD | J18: ='Necesidades Trimestrales'!G17 -> 40 | K18: ='Necesidades Trimestrales'!H17 -> 681.1
A19: 8 | B19: ='Necesidades Trimestrales'!B18 -> 2.9.1-6952.29 | C19: ='Necesidades Trimestrales'!E18 -> CEPILLOS; TIPO: ESCOBILLA LIMPIA INODORO, MATERIAL: PLASTICO | H19: NO | I19: ='Necesidades Trimestrales'!F18 -> UNIDAD | J19: ='Necesidades Trimestrales'!G18 -> 50 | K19: ='Necesidades Trimestrales'!H18 -> 222.6
A20: 9 | B20: ='Necesidades Trimestrales'!B19 -> 2.9.1-6952.45 | C20: ='Necesidades Trimestrales'!E19 -> CEPILLOS; TIPO: ESCOBILLA LIMPIAVIDRIOS, MATERIAL: PLASTICO Y GOMA | H20: NO | I20: ='Necesidades Trimestrales'!F19 -> UNIDAD | J20: ='Necesidades Trimestrales'!G19 -> 25 | K20: ='Necesidades Trimestrales'!H19 -> 476.1
A21: 10 | B21: ='Necesidades Trimestrales'!B20 -> 2.9.1-544.64 | C21: ='Necesidades Trimestrales'!E20 -> DESODORANTES DE AMBIENTE; FORMATO: AEROSOL, FRAGANCIA: CAMPOS DE JAZMIN, PRESENTACION: ENVASE X 360 CM3, LIBRE DE CFC: SI | H21: NO | I21: ='Necesidades Trimestrales'!F20 -> UNIDAD | J21: ='Necesidades Trimestrales'!G20 -> 200 | K21: ='Necesidades Trimestrales'!H20 -> 203.6
A22: 11 | B22: ='Necesidades Trimestrales'!B21 -> 2.9.1-6961.27 | C22: ='Necesidades Trimestrales'!E21 -> ELEM. P/LIMPIEZA SANITARIOS; TIPO: BOLILLA P/MINGITORIO, PRESENTACION: ENVASE X 480 GR | H22: NO | I22: ='Necesidades Trimestrales'!F21 -> UNIDAD | J22: ='Necesidades Trimestrales'!G21 -> 50 | K22: ='Necesidades Trimestrales'!H21 -> 196.7
A23: 12 | B23: ='Necesidades Trimestrales'!B22 -> 2.9.1-6961.23 | C23: ='Necesidades Trimestrales'!E22 -> ELEM. P/LIMPIEZA SANITARIOS; TIPO: SODA CAUSTICA, PRESENTACION: ENVASE X 1 Kg | H23: NO | I23: ='Necesidades Trimestrales'!F22 -> UNIDAD | J23: ='Necesidades Trimestrales'!G22 -> 50 | K23: ='Necesidades Trimestrales'!H22 -> 900
... A38: 27 | B38: ='Necesidades Trimestrales'!B37 -> 2.5.4-505.13 | C38: ='Necesidades Trimestrales'!E37 -> DESINFECTANTES; CAPACIDAD: 5 L, USO P/CONTROL: BACTERIAS, PRINCIPIO ACTIVO: SAL AMONIO CUATERNARIO, PRESENTACION: ENVASE X 5 L, CONTROL: BACTERIAS | H38: NO | I38: ='Necesidades Trimestrales'!F37 -> UNIDAD | J38: ='Necesidades Trimestrales'!G37 -> 150 | K38: ='Necesidades Trimestrales'!H37 -> 1200
A40: Costo total estimado: | C40: OCHOCIENTOS SESENTA MIL CIENTO OCHENTA Y TRES CON 50/100 CENTAVOS.- | J40: =SUMPRODUCT(J12:J39*K12:K39) -> 860183.5

Sheet APG
A1: EJERCICIO: | D1: ='Necesidades Trimestrales'!C6 -> 2022 | P1: AUTORIZACION PARA GASTAR
A4: JURISDICCIÓN: | G4: ='Nota Pedido'!D3 -> 95 - Ministerio de Cultura, Turismo y Deporte.-
A5: SAF: | G5: ='Nota Pedido'!D4 -> 18 - Secretaria de Administración y Recursos Humanos.-
A6: UNIDAD EJECUTORA: | G6: ='Nota Pedido'!D5 -> Secretaria de Administración y Recursos Humanos.-
A7: DEPENDENCIA SOLICITANTE: | G7: ='Nota Pedido'!D6 -> Ministerio de Cultura, Turismo y Deporte.-
A8: AUTORIZACIÓN:
A9: Señor Jefe de Servicio Administrativo Financiero:
A10: ="Autorizo la realización de los trámites correspondientes, a fin de proveer a este Organismo los bienes y/o servicios que se detallan en Nota de Pedido N° "&'Nota Pedido'!K1&", afectando la erogación resultante a los créditos presupuestarios aprobados a favor de esta Unidad Ejecutora, conforme al siguiente detalle:" -> Autorizo la realización de los trámites correspondientes, a fin de proveer a este Organismo los bienes y/o servicios que se detallan en Nota de Pedido N° 005/2022, afectando la erogación resultante a los créditos presupuestarios aprobados a favor de esta Unidad Ejecutora, conforme al siguiente detalle:
A12: IMPUTACIÓN PRESUPUESTARIA
A13: CÓDIGO | O13: DENOMINACIÓN DE LA PARTIDA PRESUPUESTARIA | Q13: IMPORTE
A14: PR | B14: SB | C14: PY | D14: AC | E14: OB | F14: UG | G14: FIN | H14: FUN | I14: I | J14: P | K14: P | L14: SubP | M14: M | N14: FF
A15: 4 | B15: 0 | C15: 0 | D15: 1 | E15: 0 | F15: 4901 | G15: 1 | H15: 6 | I15: 2 | J15: 9 | K15: 1 | L15: 0 | M15: 1 | N15: 1.1 | O15: Elementos de Limpieza.- | Q15: 576183.5
A16: 4 | B16: 0 | C16: 0 | D16: 1 | E16: 0 | F16: 4901 | G16: 1 | H16: 6 | I16: 2 | J16: 3 | K16: 4 | L16: 0 | M16: 1 | N16: 1.1 | O16: Productos de papel y carton.- | Q16: 87500
A17: 4 | B17: 0 | C17: 0 | D17: 1 | E17: 0 | F17: 4901 | G17: 1 | H17: 6 | I17: 2 | J17: 5 | K17: 4 | L17: 0 | M17: 1 | N17: 1.1 | O17: Insecticidas, fumigantes y otros.- | Q17: 180000
A18: 4 | B18: 0 | C18: 0 | D18: 1 | E18: 0 | F18: 4901 | G18: 1 | H18: 6 | I18: 2 | J18: 7 | K18: 5 | L18: 0 | M18: 1 | N18: 1.1 | O18: Herramientas Menores.- | Q18: 16500
A21: ="TOTAL DE PESOS: " & 'Nota Pedido'!C40 -> TOTAL DE PESOS: OCHOCIENTOS SESENTA MIL CIENTO OCHENTA Y TRES CON 50/100 CENTAVOS.- | Q21: =SUM(Q15:Q20) -> 860183.5
A23: JUSTIFICACIÓN:
A24: =+'Nota Pedido'!D8 -> Compra de elementos de limpieza para ser usadas por las distintas áreas y dependencias del Ministerio de Cultura, Turismo y Deporte.-
