Workbook

Sheet Necesidades Trimestrales
B2: Pedido de Necesidades Trimestrales
A4: JURISDICCION: | D4: 040 - Ministerio de Salud
A5: SAF N°: | D5: 024 - Hospital Interzonal de Niños
A6: EJERCICIO: | D6: 2021
A7: TRIMESTRE: | D7: 1
A9: ID | B9: IPP | C9: CODIGO ITEM | D9: RUBRO DE COMPRA | E9: DESCRIPCION | F9: UNIDAD DE MEDIDA | G9: CANTIDAD | H9: PRECIO UNITARIO ESTIMADO | I9: IMPORTE TOTAL ESTIMADO
A10: 1 | B10: 295 | D10: PROD. MEDICO/FARMACEUTICOS/LAB | E10: BARBIJOS TRICAPA C/PLIEG.RECT Y ELST.X 1 | F10: UNIDAD | G10: 10000 | H10: 14.98 | I10: =+G10*H10 -> 149800
A11: 2 | B11: 295 | D11: PROD. MEDICO/FARMACEUTICOS/LAB | E11: GORRO P/CIRUJANO S/FRONTO EST.X 1 T/COFIA C/ ELAST. | F11: UNIDAD | G11: 8000 | H11: 5.8 | I11: =G11*H11 -> 46400
A12: 3 | B12: 295 | D12: PROD. MEDICO/FARMACEUTICOS/LAB | E12: GUANTES DE NITRILO TALLE S X 100 UNID. | F12: UNIDAD | G12: 10 | H12: 1490 | I12: =G12*H12 -> 14900
A13: 4 | B13: 295 | D13: PROD. MEDICO/FARMACEUTICOS/LAB | E13: GUANTES DE POLIET.(MANOPLAS) X 100 UNID. | F13: UNIDAD | G13: 300 | H13: 194.95 | I13: =+G13*H13 -> 58485
A14: 5 | B14: 295 | D14: PROD. MEDICO/FARMACEUTICOS/LAB | E14: OVATA DE ALGODON 10 CM X 3 MTS. X 1 | F14: UNIDAD | G14: 5000 | H14: 106.29 | I14: =+G14*H14 -> 531450
A15: 6 | B15: 295 | D15: PROD. MEDICO/FARMACEUTICOS/LAB | E15: TELA ADHE.HIPOALERG.TRANS.5CM X 9MT ROLLO X 1 | F15: UNIDAD | G15: 1500 | H15: 268.4 | I15: =+G15*H15 -> 402600
A16: 7 | B16: 295 | D16: PROD. MEDICO/FARMACEUTICOS/LAB | E16: VENDA CAMBRIC 5 CM.X 1 | F16: UNIDAD | G16: 1000 | H16: 36.59 | I16: =+G16*H16 -> 36590
A17: 8 | B17: 295 | D17: PROD. MEDICO/FARMACEUTICOS/LAB | E17: VENDA CAMBRIC 7 CM.X 1 | F17: UNIDAD | G17: 1000 | H17: 48.48 | I17: =+G17*H17 -> 48480
A18: 9 | B18: 295 | D18: PROD. MEDICO/FARMACEUTICOS/LAB | E18: VENDA CAMBRIC 10 CM.X 1 | F18: UNIDAD | G18: 1000 | H18: 74.6 | I18: =+G18*H18 -> 74600
A19: 10 | B19: 295 | D19: PROD. MEDICO/FARMACEUTICOS/LAB | E19: VENDA COBAN 10CM T/3M | F19: UNIDAD | G19: 20 | H19: 425.55 | I19: =+G19*H19 -> 8511
A20: 11 | B20: 295 | D20: PROD. MEDICO/FARMACEUTICOS/LAB | E20: VENDA DE SMARCH X 10 CM. | F20: UNIDAD | G20: 20 | H20: 720.01 | I20: =+G20*H20 -> 14400.2
A21: 12 | B21: 295 | D21: PROD. MEDICO/FARMACEUTICOS/LAB | E21: VENDA ELASTICA 10 CM.ROLLO X 25MTS. | F21: UNIDAD | G21: 3 | H21: 1540 | I21: =+G21*H21 -> 4620
A22: 13 | B22: 295 | D22: PROD. MEDICO/FARMACEUTICOS/LAB | E22: VENDA YESO F/RAPIDO 20X4 MT.ROLLO X 1 T/FAVE | F22: UNIDAD | G22: 300 | H22: 340.91 | I22: =+G22*H22 -> 102273
B25: Plazos y lugares de entrega
B26: Lugar de Entrega: SERVICIO DE FARMACIA -HOSPITAL INT. DE NIÑOS – AV. VIRGEN DEL VALLE N° 1050-CATAMARCA DE 8:00 A 12:00HS., DEBIENDO CORRER LOS GASTOS DE FLETES, ACARREO, CARGA, DESCARGA Y SEGURO A CARGO DEL ADJUDICATARIO.
B28: Plazo de vencimiento de los bienes ofrecidos: No podrán ser inferior a los 18 meses.
B29: Plazo de entrega: Dentro de los 7 días de notificada la Orden de Compra
B30: Mantenimiento de Oferta:
D31: 45 dias habiles

Sheet  NotaPedido
A1: NOTA DE PEDIDO | F1: N° | G1: 022/2021
A3: JURISDICCIÓN: | D3: ='[1]Necesidades Trimestrales'!C4 -> 040 - Ministerio de Salud
A4: SAF: | D4: ='[1]Necesidades Trimestrales'!C5 -> 024 - Hospital Interzonal de Niños
A5: UNIDAD EJECUTORA: | D5: 024 - Hospital Interzonal de Niños
A6: DEPENDENCIA SOLICITANTE: | D6: Servicio de Farmacia
A7: PERIODO UTILIZACIÓN: | D7: 1er TRIMESTRE - 2021
A8: OBJETO: | D8: Adquisición de Medicamentos
A10: Ítem | B10: Codigo Item | C10: DESCRIPCIÓN | D10: Adjunta Detalle Técnico | E10: Unidad Medida | F10: Precio Unitario Estimado | G10: Cantidad Solicitada
A12: 1 | C12: ='Necesidades Trimestrales'!E10 -> BARBIJOS TRICAPA C/PLIEG.RECT Y ELST.X 1 | D12: NO | E12: ='Necesidades Trimestrales'!F10 -> UNIDAD | F12: =+'Necesidades Trimestrales'!H10 -> 14.98 | G12: =+'Necesidades Trimestrales'!G10 -> 10000
A13: 2 | C13: ='Necesidades Trimestrales'!E11 -> GORRO P/CIRUJANO S/FRONTO EST.X 1 T/COFIA C/ ELAST. | D13: NO | E13: ='Necesidades Trimestrales'!F11 -> UNIDAD | F13: =+'Necesidades Trimestrales'!H11 -> 5.8 | G13: =+'Necesidades Trimestrales'!G11 -> 8000
A14: 3 | C14: ='Necesidades Trimestrales'!E12 -> GUANTES DE NITRILO TALLE S X 100 UNID. | D14: NO | E14: ='Necesidades Trimestrales'!F12 -> UNIDAD | F14: =+'Necesidades Trimestrales'!H12 -> 1490 | G14: =+'Necesidades Trimestrales'!G12 -> 10
A15: 4 | C15: ='Necesidades Trimestrales'!E13 -> GUANTES DE POLIET.(MANOPLAS) X 100 UNID. | D15: NO | E15: ='Necesidades Trimestrales'!F13 -> UNIDAD | F15: =+'Necesidades Trimestrales'!H13 -> 194.95 | G15: =+'Necesidades Trimestrales'!G13 -> 300
A16: 5 | C16: ='Necesidades Trimestrales'!E14 -> OVATA DE ALGODON 10 CM X 3 MTS. X 1 | D16: NO | E16: ='Necesidades Trimestrales'!F14 -> UNIDAD | F16: =+'Necesidades Trimestrales'!H14 -> 106.29 | G16: =+'Necesidades Trimestrales'!G14 -> 5000
A17: 6 | C17: ='Necesidades Trimestrales'!E15 -> TELA ADHE.HIPOALERG.TRANS.5CM X 9MT ROLLO X 1 | D17: NO | E17: ='Necesidades Trimestrales'!F15 -> UNIDAD | F17: =+'Necesidades Trimestrales'!H15 -> 268.4 | G17: =+'Necesidades Trimestrales'!G15 -> 1500
A18: 7 | C18: ='Necesidades Trimestrales'!E16 -> VENDA CAMBRIC 5 CM.X 1 | D18: NO | E18: ='Necesidades Trimestrales'!F16 -> UNIDAD | F18: =+'Necesidades Trimestrales'!H16 -> 36.59 | G18: =+'Necesidades Trimestrales'!G16 -> 1000
A19: 8 | C19: ='Necesidades Trimestrales'!E17 -> VENDA CAMBRIC 7 CM.X 1 | D19: NO | E19: ='Necesidades Trimestrales'!F17 -> UNIDAD | F19: =+'Necesidades Trimestrales'!H17 -> 48.48 | G19: =+'Necesidades Trimestrales'!G17 -> 1000
A20: 9 | C20: ='Necesidades Trimestrales'!E18 -> VENDA CAMBRIC 10 CM.X 1 | D20: NO | E20: ='Necesidades Trimestrales'!F18 -> UNIDAD | F20: =+'Necesidades Trimestrales'!H18 -> 74.6 | G20: =+'Necesidades Trimestrales'!G18 -> 1000
A21: 10 | C21: ='Necesidades Trimestrales'!E19 -> VENDA COBAN 10CM T/3M | D21: NO | E21: ='Necesidades Trimestrales'!F19 -> UNIDAD | F21: =+'Necesidades Trimestrales'!H19 -> 425.55 | G21: =+'Necesidades Trimestrales'!G19 -> 20
A22: 11 | C22: ='Necesidades Trimestrales'!E20 -> VENDA DE SMARCH X 10 CM. | D22: NO | E22: ='Necesidades Trimestrales'!F20 -> UNIDAD | F22: =+'Necesidades Trimestrales'!H20 -> 720.01 | G22: =+'Necesidades Trimestrales'!G20 -> 20
A23: 12 | C23: ='Necesidades Trimestrales'!E21 -> VENDA ELASTICA 10 CM.ROLLO X 25MTS. | D23: NO | E23: ='Necesidades Trimestrales'!F21 -> UNIDAD | F23: =+'Necesidades Trimestrales'!H21 -> 1540 | G23: =+'Necesidades Trimestrales'!G21 -> 3
A24: 13 | C24: ='Necesidades Trimestrales'!E22 -> VENDA YESO F/RAPIDO 20X4 MT.ROLLO X 1 T/FAVE | D24: NO | E24: ='Necesidades Trimestrales'!F22 -> UNIDAD | F24: =+'Necesidades Trimestrales'!H22 -> 340.91 | G24: =+'Necesidades Trimestrales'!G22 -> 300
A25: COSTO TOTAL ESTIMADO | F25: =SUMPRODUCT(F12:F24,G12:G24) -> 1493109.2

Sheet Autor Gastar
A1: EJERCICIO: | D1: ='Necesidades Trimestrales'!D6 -> 2021 | P1: AUTORIZACION PARA GASTAR
A4: JURISDICCIÓN: | G4: 040 - Ministerio de Salud
A5: SAF: | G5: 024 - Hospital Interzonal de Niños
A6: UNIDAD EJECUTORA: | G6: 024 - Hospital Interzonal de Niños
A7: DEPENDENCIA SOLICITANTE: | G7: Servicio De Farmacia
A8: AUTORIZACIÓN:
A9: Señor Jefe de Servicio Administrativo Financiero:
A10: ="Autorizo la realización de los trámites correspondientes, a fin de proveer a este Organismo los bienes y/o servicios que se detallan en Nota de Pedido N° " & ' NotaPedido'!G1&", afectando la erogación resultante a los créditos presupuestarios aprobados a favor de esta Unidad Ejecutora, conforme al siguiente detalle:" -> Autorizo la realización de los trámites correspondientes, a fin de proveer a este Organismo los bienes y/o servicios que se detallan en Nota de Pedido N° 022/2021, afectando la erogación resultante a los créditos presupuestarios aprobados a favor de esta Unidad Ejecutora, conforme al siguiente detalle:
A12: IMPUTACIÓN PRESUPUESTARIA
A13: CÓDIGO | O13: DENOMINACIÓN DE LA PARTIDA PRESUPUESTARIA | Q13: IMPORTE
A14: PR | B14: SB | C14: PY | D14: AC | E14: OB | F14: UG | G14: FIN | H14: FUN | I14: I | J14: P | K14: P | L14: SubP | M14: M | N14: FF
A15: 36 | D15: 1 | F15: 4901 | G15: 3 | H15: 310 | I15: 2 | J15: 9 | K15: 5 | M15: 1 | N15: 1.1 | O15: Productos Farmaceuticos y Medicinales | Q15: 1493109.2
A22: TOTAL DE PESOS: Un millon cuatrocientos noventa y tres mil ciento nueve CON 20/100. | Q22: =SUM(Q15:Q21) -> 1493109.2
A24: JUSTIFICACIÓN:
A25: Para la adquisición de Materiales de Curación destinados al servico de Farmacia del Hospital Interzonal de Niños Eva Peron, para el normal funcionamiento del organismo.
