Workbook

Sheet Necesidades Trimestrales
B2: Pedido de Necesidades Trimestrales
A4: JURISDICCION: | E4: 90 - Ministerio de Seguridad
A5: SAF N°: | E5: 7- Dirección Provincial de Administración de la Policía de la Provincia de Catamarca
A6: EJERCICIO: | E6: 2022
A7: TRIMESTRE: | E7: 2
A9: ID | B9: CODIGO ITEM | C9: RUBRO | D9: IPP | E9: DESCRIPCION | F9: UNIDAD DE MEDIDA | G9: CANTIDAD | H9: PRECIO UNITARIO ESTIMADO | I9: IMPORTE TOTAL ESTIMADO
A10: 1 | B10: 2.1.1-481.38 | C10: ALIMENTOS | D10: 2.1.1 | E10: AZUCARES; TIPO: "A" COMUN, ESTADO: MOLIDA, PESO: 1 Kg, MATERIAL ENVASE: PLASTICO, CERTIFICADO FORESTAL (GFS): SIN, ELEM. TRANSPORTE: SIN, MATERIAL ELEM. TRANSPORTE: SIN | F10: UNIDAD | G10: 2000 | H10: 120 | I10: =(G10*H10) -> 240000
A11: 2 | B11: 2.1.1-454.25 | C11: ALIMENTOS | D11: 2.1.1 | E11: YERBAS; PALO: CON, PESO: 1 Kg, MATERIAL ENVASE : PAPEL, CERTIFICADO FORESTAL (GFS): CON, ELEM. TRANSPORTE: SIN, MATERIAL ELEM. TRANSPORTE: SIN, LIBRE DE GLUTEN: SI | F11: UNIDAD | G11: 900 | H11: 480 | I11: =(G11*H11) -> 432000
A12: 3 | B12: 2.1.1-439.67 | C12: ALIMENTOS | D12: 2.1.1 | E12: ACEITES COMESTIBLES; TIPO: GIRASOL, PRESENTACION: ENVASE X 900 CM3, MATERIAL ENVASE: PLASTICO 1 (PET), ELEM. TRANSPORTE: SIN, MATERIAL ELEM. TRANSPORTE : SIN, LIBRE DE GLUTEN: NO | F12: UNIDAD | G12: 600 | H12: 395 | I12: =(G12*H12) -> 237000
A13: 4 | B13: 2.1.1-708.23 | C13: ALIMENTOS | D13: 2.1.1 | E13: CONSERVAS PESCADO Y FRUTOS MAR; ESTADO: AL NATURAL, PESO: 380 GR, ENVASE: LATA, TIPO: CABALLA, ESPECIE: CABALLA | F13: UNIDAD | G13: 800 | H13: 520 | I13: =(G13*H13) -> 416000
A14: 5 | B14: 2.1.1-6546.5 | C14: ALIMENTOS | D14: 2.1.1 | E14: VERDURAS Y HORTALIZAS; PRESENTACION: BOTELLA, VARIEDAD: TOMATE PERITA, ESTADO: TRITURADO, PESO: 970 GR | F14: UNIDAD | G14: 500 | H14: 230 | I14: =(G14*H14) -> 115000
A15: 6 | B15: 2.1.1-6547.84 | C15: ALIMENTOS | D15: 2.1.1 | E15: LEGUMBRES; VARIEDAD: ARVEJAS, ESTADO: CONSERVA, PRESENTACION: LATA, PESO: 350 GR, MATERIAL ENVASE: METAL, ELEM. TRANSPORTE: SIN, MATERIAL ELEM. TRANSPORTE: SIN, LIBRE DE GLUTEN: NO | F15: UNIDAD | G15: 500 | H15: 75 | I15: =(G15*H15) -> 37500
A16: 7 | B16: 2.1.1-2868.78 | C16: ALIMENTOS | D16: 2.1.1 | E16: FIDEOS SECOS; LIBRE DE GLUTEN: NO, CERTIFICADO FORESTAL (GFS): SIN, MATERIAL ELEM. TRANSPORTE: SIN, ELEM. TRANSPORTE: SIN, MATERIAL ENVASE: POLIETILENO, PRESENTACION: ENVASE X 500 GR, RELLENO: SIN, VARIEDAD: TALLARIN | F16: UNIDAD | G16: 800 | H16: 90 | I16: =(G16*H16) -> 72000
A17: 8 | B17: 2.1.1-2868.76 | C17: ALIMENTOS | D17: 2.1.1 | E17: FIDEOS SECOS; LIBRE DE GLUTEN: NO, CERTIFICADO FORESTAL (GFS): SIN, MATERIAL ELEM. TRANSPORTE: SIN, ELEM. TRANSPORTE: SIN, MATERIAL ENVASE: POLIETILENO, PRESENTACION: ENVASE X 500 GR, RELLENO: SIN, VARIEDAD: GUISERO | F17: UNIDAD | G17: 800 | H17: 90 | I17: =(G17*H17) -> 72000
A18: 9 | B18: 2.1.1-2868.77 | C18: ALIMENTOS | D18: 2.1.1 | E18: FIDEOS SECOS; LIBRE DE GLUTEN: NO, CERTIFICADO FORESTAL (GFS): SIN, MATERIAL ELEM. TRANSPORTE: SIN, ELEM. TRANSPORTE: SIN, MATERIAL ENVASE: POLIETILENO, PRESENTACION: ENVASE X 500 GR, RELLENO: SIN, VARIEDAD: SOPERO | F18: UNIDAD | G18: 800 | H18: 90 | I18: =(G18*H18) -> 72000
A19: 10 | B19: 2.1.1-435.60 | C19: ALIMENTOS | D19: 2.1.1 | E19: ARROZ; TIPO GRANO: LARGO-FINO, TIPO: BLANCO, PROCESO: SIN CASCARA, PRESENTACION: BOLSA X 1 Kg, MATERIAL ENVASE: PLASTICO, CERTIFICADO FORESTAL (GFS): SIN, ELEM. TRANSPORTE: SIN, MATERIAL ELEM. TRANSPORTE: SIN, LIBRE DE GLUTEN: SI | F19: UNIDAD | G19: 2000 | H19: 120 | I19: =(G19*H19) -> 240000
A20: 11 | B20: 2.1.1-514.2 | C20: ALIMENTOS | D20: 2.1.1 | E20: SAL DE MESA; CONSISTENCIA: FINA, PESO: 500 GR, TIPO: SIN VALOR, ENVASE: PAQUETE | F20: UNIDAD | G20: 300 | H20: 50 | I20: =(G20*H20) -> 15000
A21: 12 | B21: 2.1.1-514.14 | C21: ALIMENTOS | D21: 2.1.1 | E21: SAL DE MESA; ENVASE: BOLSA, PESO: 5 Kg, CONSISTENCIA: GRUESA, TIPO: SIN VALOR | F21: UNIDAD | G21: 300 | H21: 500 | I21: =(G21*H21) -> 150000
... A47: 38 | B47: 2.1.1-489.68 | C47: ALIMENTOS | D47: 2.1.1 | E47: ESPECIAS; PRESENTACION: BOLSA DE 1 Kg, TIPO: AJI MOLIDO | F47: UNIDAD | G47: 50 | H47: 900 | I47: =(G47*H47) -> 45000
I48: =SUM(I10:I47) -> 5781400
B49: Especificidades:
E50: DESCRIPCION ITEM 35: ENVASE BOLSA
E51: DESCRIPCION ITEM 36: PRESENTACION SAQUITOS
E52: ITEM 1 AL 38 : Se requieren las siguientes consideraciones en los alimentos no perecederos: “Todos los productos deberán presentar en el envase el rótulo bien legible y responder a toda la información establecida en el Código Alimentario Argentino – Cap. V: “Normas para la Rotulación y Publicidad de Alimentos”. ANEXO Reglamento Técnico MERCOSUR para la rotulación de Alimentos Envasados – Inciso 5: Información Obligatoria: Denominación de venta del alimento; Lista de ingredientes; Contenidos netos; Identificación del origen; Nombre o razón social y dirección del importador, para alimentos importados; Identificación del lote; Fecha de duración mínima; Instrucción de uso del alimento, cuando corresponda. La fecha de vencimiento de los productos adjudicados debe ser mayor a 6 (seis) meses al momento de ser bajada en el lugar de entrega y responder a las marcas y características presentadas en la oferta de la presente contratación. Además, debe presentarse el envase en óptimas condiciones de higiene e integridad del mismo.
B58: Plazos y lugares de entrega
E59: a) LUGAR DE ENTREGA: En la Escuela de Cadetes de Policía– sito en Av. Acosta Villafañez al 1.500 de la ciudad de San Fernando del Valle de Catamarca. b) FORMA DE LA ENTREGA: Libre de flete, acarreo y embalaje, como así también, de todo riesgo de pérdida o destrucción total o parcial, por causas ajenas a la Institución. c) PLAZO DE ENTREGA: Las entregas se realizarán a requerimiento de acuerdo, a las Solicitudes de Provisión que se realicen. Se estima emitir una cantidad aproximada de 2 (Dos) Solicitudes de Provisión de 1/2 aprox. de la cantidad solicitada, en un plazo de 2 (Dos) meses: 1° Solic.de Provisión: aprox.a los 2 (Dos) dias hábiles de la firma del instrumento contractual, 2° Solic.de Provisión: al mes de la firma del instrumento contractual. Plazo de cumplimiento de cada Solicitud de Provisión: a los 5 días hábiles de notificada la misma, según necesidades del Organismo solicitante. Forma de Pago: Se solicita Pagos parciales por cada Solicitud de Provisión emitida, una vez finalizada la entrega de las cantidades contenidas en la misma.
B61: Calidad Minima esperada
E62: Que cumpla con lo solicitado en forma íntegra. Presentar muestras para los ítems 1 al 38, en su envase original, en el cual se pueda observar de forma clara la marca del mismo y sus características. La recepción de las muestras se realizará en el Departamento Logística (D-4) de la Policía de Catamarca, hasta el momentos de la apertura, sito en Ruta Provincial N° 33-sumalao-Valle Viejo. Provincia de Catamarca. Las muestras deben estar debidamente rotuladas por ítems e identificando claramente el oferente cotizante. No se aceptan muestras distinto a lo cotizado.
B65: Mantenimiento
E66: 30 días
B67: Garantia
E68: *

Sheet  NotaPedido
A1: NOTA DE PEDIDO | J1: N° | K1: 81/2021
A3: JURISDICCIÓN: | D3: ='Necesidades Trimestrales'!E4 -> 90 - Ministerio de Seguridad
A4: SAF: | D4: ='Necesidades Trimestrales'!E5 -> 7- Dirección Provincial de Administración de la Policía de la Provincia de Catamarca
A5: UNIDAD EJECUTORA: | D5: Policía de la Provincia de Catamarca
A6: DEPENDENCIA SOLICITANTE: | D6: División Intendencia, Departamento Logística
A7: PERIODO UTILIZACIÓN: | D7: 3er trimestre Año 2021.-
A8: OBJETO: | D8: Adquisición de Uniformes de Fajina para el personal policial.
A10: Ítem | B10: Codigo Item | C10: DESCRIPCIÓN | H10: Adjunta Detalle Técnico | I10: Unidad Medida | J10: Precio Unitario Estimado | K10: Cantidad Solicitada
A12: 1 | B12: ='Necesidades Trimestrales'!#REF! -> #REF! | C12: ='Necesidades Trimestrales'!#REF! -> #REF! | H12: SI | I12: ='Necesidades Trimestrales'!#REF! -> #REF! | J12: ='Necesidades Trimestrales'!#REF! -> #REF! | K12: ='Necesidades Trimestrales'!#REF! -> #REF!
B13: ='Necesidades Trimestrales'!#REF! -> #REF! | C13: ='Necesidades Trimestrales'!#REF! -> #REF! | H13: SI | I13: ='Necesidades Trimestrales'!#REF! -> #REF! | J13: ='Necesidades Trimestrales'!#REF! -> #REF! | K13: ='Necesidades Trimestrales'!#REF! -> #REF!
A14: 3 | B14: ='Necesidades Trimestrales'!#REF! -> #REF! | C14: ='Necesidades Trimestrales'!#REF! -> #REF! | H14: SI | I14: ='Necesidades Trimestrales'!#REF! -> #REF! | J14: ='Necesidades Trimestrales'!#REF! -> #REF! | K14: ='Necesidades Trimestrales'!#REF! -> #REF!
A15: Costo total estimado: Pesos Cinco Millones Doscientos Mil con 00/100.- | J15: ='Necesidades Trimestrales'!I14 -> 115000

Sheet Autor Gastar
A1: EJERCICIO: | D1: ='Necesidades Trimestrales'!E6 -> 2022 | P1: AUTORIZACION PARA GASTAR
A4: JURISDICCIÓN: | G4: =' NotaPedido'!D3 -> 90 - Ministerio de Seguridad
A5: SAF: | G5: =' NotaPedido'!D4 -> 7- Dirección Provincial de Administración de la Policía de la Provincia de Catamarca
A6: UNIDAD EJECUTORA: | G6: =' NotaPedido'!D5 -> Policía de la Provincia de Catamarca
A7: DEPENDENCIA SOLICITANTE: | G7: =' NotaPedido'!D6 -> División Intendencia, Departamento Logística
A8: AUTORIZACIÓN:
A9: Señor Jefe de Servicio Administrativo Financiero:
A10: ="Autorizo la realización de los trámites correspondientes, a fin de proveer a este Organismo los bienes y/o servicios que se detallan en Nota de Pedido N° " &' NotaPedido'!K1&", afectando la erogación resultante a los créditos presupuestarios aprobados a favor de esta Unidad Ejecutora, conforme al siguiente detalle:" -> Autorizo la realización de los trámites correspondientes, a fin de proveer a este Organismo los bienes y/o servicios que se detallan en Nota de Pedido N° 81/2021, afectando la erogación resultante a los créditos presupuestarios aprobados a favor de esta Unidad Ejecutora, conforme al siguiente detalle:
A12: IMPUTACIÓN PRESUPUESTARIA
A13: CÓDIGO | O13: DENOMINACIÓN DE LA PARTIDA PRESUPUESTARIA | Q13: IMPORTE
A14: PR | B14: SB | C14: PY | D14: AC | E14: OB | F14: UG | G14: FIN | H14: FUN | I14: I | J14: P | K14: P | L14: SubP | M14: M | N14: FF
A15: 16 | B15: 0 | C15: 0 | D15: 1 | E15: 0 | F15: 10 | G15: 2 | H15: 210 | I15: 2 | J15: 9 | K15: 1 | L15: 0 | M15: 1 | N15: 1.1 | O15: ='Necesidades Trimestrales'!#REF! -> #REF! | Q15: =' NotaPedido'!J15 -> 115000
A16: TOTAL DE PESOS: Treinta y Cuatro Mil Novecientos Cincuenta con 00/100.- | Q16: =Q15 -> 115000
A18: JUSTIFICACIÓN:
A19: =' NotaPedido'!D8 -> Adquisición de Uniformes de Fajina para el personal policial.
