Workbook

Sheet SAF 011
A1: 2022
B2: Pedido de Necesidades Trimestrales
A4: JURISDICCION: | C4: 040 - MINISTERIO DE SALUD
A5: SAF N°: | C5: 011 - DIRECCION PROVINCIAL DE ADMINISTRACION - MINISTERIO DE SALUD
A6: EJERCICIO: | C6: 2022
A7: TRIMESTRE: | C7: PRIMERO
A9: ID | B9: CODIGO ITEM | C9: RUBRO DE COMPRA | D9: I.P.P. | E9: DESCRIPCION | F9: UNIDAD DE MEDIDA | G9: SECRETARIA DE ADMINISTRACION | H9: TOTAL S.A. | I9: SMPyPS | J9: TOTAL SMPyPS | K9: DIR. LAB. CENTRAL | L9: TOTAL DE LAB CENTRAL | M9: BCO DE SANGRE | N9: TOTAL BANCO DE SANGRE | O9: APS | P9: TOTAL A.P.S. | Q9: DIR DE CANCER | R9: TOTAL DE DIR DE CANCER | S9: FARMACIA | T9: TOTAL FARMACIA | U9: ODONTOLOGIA | V9: TOTAL DE ODONTOLOG | W9: SAME | X9: TOTAL SAME | Y9: HPTAL MALBRAN | Z9: TOTAL HPTAL MALBRAN | AA9: MATERNIDAD E INFANCIA | AB9: TOTAL MATERNIDAD E INFANCIA | AC9: SASP | AD9: TOTAL SASP | AE9: SALUD Y MEDIO AMBIENTE | AF9: TOTAL SALUD Y MEDIO AMBIENTE | AG9: VECTORES Y ZOONOSIS | AH9: TOTAL DE VECT Y ZOON | AI9: CRONICAS | AJ9: TOTAL CRONICAS | AK9: CUR | AL9: TOTAL CUR | AM9: SPyGS | AN9: TOTAL SPyGS | AO9: SALUD MENTAL | AP9: TOTAL SALUD MENTAL | AQ9: AREAS Y DPAS | AR9: TOTAL DPAS | AS9: EPIDEMIOLOGIA | AT9: TOTAL EPIDEMIOLOGIA | AU9: AREA 1 | AV9: TOTAL AREA 1 | AW9: CANTIDAD TOTAL | AX9: PRECIO UNITARIO ESTIMADO | AY9: IMPORTE TOTAL ESTIMADO | AZ9: ESPECIFICACION TECNICA
A10: 1 | B10: 2.1.1-2456.8 | C10: ALIMENTOS | D10: 2.1.1 | E10: RACIONAMIENTO; DESCRIPCION: ALMUERZO | F10: RACION | W10: 2700 | X10: =+W10*AX10 -> 864000 | AW10: =+AQ10+AO10+AM10+AK10+AI10+AG10+AE10+AC10+AA10+Y10+W10+U10+S10+Q10+O10+M10+K10+I10+AS10+G10+AU10 -> 2700 | AX10: 320 | AY10: =+AW10*AX10 -> 864000 | AZ10: ALMUERZOS: una ración de carne con guarnición y postre: CARNES: carne vacuna, carne de cerdo, pescado y carne de pollo. Deberá proveerse en la semana dos raciones de carne vacuna, dos raciones de carne de cerdo, dos raciones de carne de pescado y una ración de carne de pollo. GUARNICION: ensaladas de verduras variadas alternadas que contengan: tomate, lechuga, repollo, rucula, zapallitos tiernos hervidos, remolacha, huevo duro, zanahoria rallada, entre otros. Además, Puré de papas, papas fritas o papas al horno. POSTRE: una fruta por persona por día: una pera, manzana o banana (mediana). El peso de la ración debe ser no menor a 400 gr. Deben ser entregadas en bandejas plásticas de 18x25x5 cm. Recubiertas de papel film.
A11: 2 | B11: 2.1.1-2456.10 | C11: ALIMENTOS | D11: 2.1.1 | E11: RACIONAMIENTO; DESCRIPCION: CENA | F11: RACION | W11: 2700 | X11: =+W11*AX11 -> 864000 | AW11: =+AQ11+AO11+AM11+AK11+AI11+AG11+AE11+AC11+AA11+Y11+W11+U11+S11+Q11+O11+M11+K11+I11+AS11+G11+AU11 -> 2700 | AX11: 320 | AY11: =+AW11*AX11 -> 864000 | AZ11: CENAS: una ración de Pastas: ravioles, ñoquis, fideos tirabuzón, fideos espagueti o sorrentinos, con salsa bolognesa con carne vacuna o pollo, 4 quesos o salsa blanca. Una pasta distinta por día, alternando a su vez las salsas y repitiéndose los sorrentinos o ravioles para completar la semana. POSTRE: una fruta por persona por día: una pera, manzana o banana (mediana). El peso de la ración debe ser no menor a 400 gr. Deben ser entregadas en bandejas plásticas de 18x25x5 cm. Recubiertas de papel film
E12: TOTAL RUBRO ALIMENTOS | L12: =+K12*AX12 -> 0 | N12: =+M12*AX12 -> 0 | AY12: =+SUM(AY10:AY11) -> 1728000
C15: Especificidades: ITEM 1 Y 2 | D15: VER ANEXO I
C17: CANTIDAD POR MES: | D17: NOVECIENTOS (900) RACIONES DE ALMUERZOS Y NOVECIENTOS (900) RACIONES CENAS x MES,
C18: Duración contrato: | D18: DURANTE 90 (noventa) DIAS CORRIDOS, CON OPCION A PRORROGA POR IGUAL PERIODO.
C19: Plazos de entrega: | D19: DENTRO DE LOS 5 (CINCO) DIAS DE LA RECEPCION DEL INSTRUMENTO RESPECTIVO.
C21: Lugar de Entrega: | D21: S.A.M.E. - Caseros N° 864 en la forma y horarios establecidos en ANEXO I.
C22: Forma de Pago: | D22: El pago se realizará en forma mensual dentro de losTREINTA (30) días corridos de la recepciones definitivas de cada 30 (treinta) raciones de Almuerzo y Cena respectivamente, de los items contratados.
C23: Calidad Minima esperada: | D23: que cumpla con todo lo solicitado en ANEXO I.
C25: Mantenimiento de Oferta: | D25: cuarenta y cinco (45) días

Sheet ANEXO I
A1: ANEXO I
A3: ESPECIFICACIONES: ALIMENTOS PARA PERSONAS
A5: Se deberá entregar treinta (30) raciones de ALMUERZOS por día y treinta (30) raciones de CENAS por día, durante un plazo de 90 (noventa) días corridos en forma continua e ininterrumpida en virtud del Servicio de Atención de Emergencias que presta dicho Organismo (SAME).
A7: Totalizando novecientas (900) raciones por mes de ALMUERZOS Y novecientas (900) raciones por mes de CENAS, durante el plazo antes
A8: mencionado.
A9: ALMUERZOS: una ración de carne con guarnición y postre:
A10: CARNES: carne vacuna, carne de cerdo, pescado y carne de pollo. Deberá proveerse en la semana dos raciones de carne vacuna, dos raciones de carne de cerdo, dos raciones de carne de pescado y una ración de carne de pollo. GUARNICION: ensaladas de verduras variadas alternadas que contengan: tomate, lechuga, repollo, rucula, zapallitos tiernos hervidos, remolacha, huevo duro, zanahoria rallada, entre otros. Además, Puré de papas, papas fritas o papas al horno. POSTRE: una fruta por persona por día: una pera, manzana o banana (mediana). El peso de la ración debe ser no menor a 400 gr. Deben ser entregadas en bandejas plásticas de 18x25x5 cm. Recubiertas de papel film.
A11: ALMUERZOS: HORARIO DE ENTREGA 12:00 HS.
A13: CENAS: una ración de Pastas con salsa y postre:
A14: PASTAS: ravioles, ñoquis, fideos tirabuzón, fideos espagueti o sorrentinos, con salsa bolognesa con carne vacuna o pollo, 4 quesos o salsa blanca. Una pasta distinta por día, alternando a su vez las salsas y repitiéndose los sorrentinos o ravioles para completar la semana. POSTRE: una fruta por persona por día: una pera, manzana o banana (mediana).
A15: CENAS: HORARIO DE ENTREGA 20:00 HS.
A17: El peso de la ración debe ser no menor a 400 gr. Deben ser entregadas en bandejas plásticas de 18x25x5 cm. Recubiertas de papel film, corriendo los gastos de flete, acarreo, carga, descarga y seguro (de corresponder) por cuenta del adjudicatario. Las personas designadas para la recepción de dichas bandejas de alimento son: • Lencina Eugenia - DNI 23854289 • Sánchez Gisella - DNI 26815200 • Toledo María Alejandra - DNI 24843448

Sheet NP
A1: NOTA DE PEDIDO | J1: N° | K1: 05/2022
A3: JURISDICCIÓN: | D3: ='SAF 011'!C4 -> 040 - MINISTERIO DE SALUD
A4: SAF: | D4: ='SAF 011'!C5 -> 011 - DIRECCION PROVINCIAL DE ADMINISTRACION - MINISTERIO DE SALUD
A5: UNIDAD EJECUTORA: | D5: DIRECCION PROVINCIAL SISTEMA DE ATENCION MEDICA DE EMERGENCIA
A6: DEPENDENCIA SOLICITANTE: | D6: DIRECCION PROVINCIAL SISTEMA DE ATENCION MEDICA DE EMERGENCIA
A7: PERIODO UTILIZACIÓN: | D7: 1° TRIMESTRE 2022
A8: OBJETO: | D8: ADQUISICION DEL RUBRO ALIMENTOS PARA PERSONAS (RACIONES DE ALMUERZO Y CENA - SAME)
A10: Ítem | B10: Codigo Item | C10: DESCRIPCIÓN | H10: Adjunta Detalle Técnico | I10: Unidad Medida | J10: Precio Unitario Estimado | K10: Cantidad Solicitada
A12: 1 | B12: ='SAF 011'!B10 -> 2.1.1-2456.8 | C12: ='SAF 011'!E10 -> RACIONAMIENTO; DESCRIPCION: ALMUERZO | H12: NO | I12: ='SAF 011'!F10 -> RACION | J12: ='SAF 011'!AX10 -> 320 | K12: ='SAF 011'!W10 -> 2700 | M12: =+J12*K12 -> 864000
A13: 2 | B13: ='SAF 011'!B11 -> 2.1.1-2456.10 | C13: ='SAF 011'!E11 -> RACIONAMIENTO; DESCRIPCION: CENA | H13: NO | I13: ='SAF 011'!F11 -> RACION | J13: ='SAF 011'!AX11 -> 320 | K13: ='SAF 011'!W11 -> 2700 | M13: =+J13*K13 -> 864000
A15: Costo total estimado: UN MILLON SETECIENTOS VEINTIOCHO MIL CON 00/100.- | J15: =+M15 -> 1728000 | M15: =SUM(M12:M14) -> 1728000

Sheet APG
A1: EJERCICIO: | D1: 2022 | P1: AUTORIZACION PARA GASTAR
A4: JURISDICCIÓN: | G4: =NP!D3 -> 040 - MINISTERIO DE SALUD
A5: SAF: | G5: =NP!D4 -> 011 - DIRECCION PROVINCIAL DE ADMINISTRACION - MINISTERIO DE SALUD
A6: UNIDAD EJECUTORA: | G6: =NP!D5 -> DIRECCION PROVINCIAL SISTEMA DE ATENCION MEDICA DE EMERGENCIA
A7: DEPENDENCIA SOLICITANTE: | G7: =NP!D6 -> DIRECCION PROVINCIAL SISTEMA DE ATENCION MEDICA DE EMERGENCIA
A8: AUTORIZACIÓN:
A9: Señor Director de Administración o Titular del Servicio Administrativo Financiero:
A10: Autorizo la realización de los trámites correspondientes, a fin de proveer a este Organismo los bienes/servicios que se detallan en Nota de Pedido N° 05/2022 afectando la erogación resultante a los créditos presupuestarios aprobados a favor de esta Unidad Ejecutora, conforme al siguiente detalle:
A12: IMPUTACIÓN PRESUPUESTARIA
A13: CÓDIGO | O13: DENOMINACIÓN DE LA PARTIDA PRESUPUESTARIA | Q13: IMPORTE
A14: PR | B14: SB | C14: PY | D14: AC | E14: OB | F14: UG | G14: FIN | H14: FUN | I14: I | J14: P | K14: P | L14: SubP | M14: M | N14: FF
A15: 31 | D15: 1 | F15: 4901 | G15: 3 | H15: 1 | I15: 2 | J15: 1 | K15: 1 | M15: 1 | N15: 1.1 | O15: ALIMENTOS PARA PERSONAS | Q15: =NP!M15 -> 1728000
A23: TOTAL DE PESOS: UN MILLON SETECIENTOS VEINTIOCHO MIL CON 00/100.- | Q23: =SUM(Q15:Q22) -> 1728000
A25: JUSTIFICACIÓN:
A26: =NP!D8 -> ADQUISICION DEL RUBRO ALIMENTOS PARA PERSONAS (RACIONES DE ALMUERZO Y CENA - SAME)
