Workbook

Sheet Necesidades Trimestrales
B2: Pedido de Necesidades Trimestrales
A4: JURISDICCION: | C4: 70 - MINISTERIO DE CIENCIA E INNOVACION TECNOLOGICA
A5: SAF N°: | C5: 20 - MINISTERIO DE CIENCIA E INNOVACION TECNOLOGICA
A6: EJERCICIO: | C6: 2020
A7: TRIMESTRE: | C7: 4
A9: ID | B9: CODIGO ITEM | C9: RUBRO DE COMPRA | D9: I.P.P. | E9: DESCRIPCION | F9: UNIDAD DE MEDIDA | G9: CANTIDAD | H9: PRECIO UNITARIO ESTIMADO | I9: IMPORTE TOTAL ESTIMADO
A10: 1 | B10: 4.3.9-491.107 | C10: INDUMENT TEXTIL Y CONFECCIONES | D10: =LEFT(B10,5) -> 4.3.9 | E10: CARPAS; TIPO: ESTRUCTURAL - DOMO, DIMENSION: SEGÚN PLIEGO, PESO:SEGÚN PLIEGO, CANTIDAD DE PERSONAS: SIN DEFINIR | F10: UNIDAD | G10: 1 | H10: 308000 | I10: =G10*H10 -> 308000
A11: 2 | B11: 4.3.9-491.107 | C11: INDUMENT TEXTIL Y CONFECCIONES | D11: =LEFT(B11,5) -> 4.3.9 | E11: CARPAS; TIPO: ESTRUCTURAL - DOMO, DIMENSION: SEGÚN PLIEGO, PESO:SEGÚN PLIEGO, CANTIDAD DE PERSONAS: SIN DEFINIR | F11: UNIDAD | G11: 1 | H11: 368109.53 | I11: =G11*H11 -> 368109.53
A12: 3 | B12: 4.3.9-491.106 | C12: INDUMENT TEXTIL Y CONFECCIONES | D12: =LEFT(B12,5) -> 4.3.9 | E12: CARPAS; TIPO: ESTRUCTURAL - TUNEL, DIMENSION: SEGÚN PLIEGO, PESO: SEGÚN PLIEGO, CANTIDAD DE PERSONAS: SIN DEFINIR | F12: UNIDAD | G12: 1 | H12: 182000 | I12: =G12*H12 -> 182000
A13: 4 | B13: 2.4.3-742.39 | C13: MATERIALES DE CONSTRUCCION | D13: =LEFT(B13,5) -> 2.4.3 | E13: PISOS EN ROLLO; MATERIAL: GOMA HOMOGENEO, TIPO: ALTO TRANSITO, ANCHO: 2M, LARGO: 20M | F13: UNIDAD | G13: 3 | H13: 142800 | I13: =G13*H13 -> 428400
A14: 5 | B14: 4.3.7-1362.65 | C14: EQUIPO DE OFICINA Y MUEBLES | D14: 4.3.7 | E14: MESAS CURVAS; CURVA: SEMICIRCULAR, DIMENSION: SEGÚN PLIEGO, MATERIAL: MELAMINA, TERMINACION: SIN VALOR, COLOR: SIN VALOR, ANGULOS: SIN, ALTURA: SEGÚN PLIEGO, ESTANTE: SIN | F14: UNIDAD | G14: 2 | H14: 42280 | I14: =G14*H14 -> 84560
A15: 6 | B15: 4.3.7-5851.21 | C15: CARPINTERIA | D15: 4.3.7 | E15: TARIMAS; TIPO: SEMICIRCULAR, MATERIAL: METAL, DIMENSION: SIN VALOR | F15: UNIDAD | G15: 1 | H15: 432460 | I15: =G15*H15 -> 432460
A16: 7 | B16: 4.3.7-45.486 | C16: EQUIPO DE OFICINA Y MUEBLES | D16: 4.3.7 | E16: SILLAS; MATERIAL ESTRUCTURA: METAL, TAPIZADO: TELA, ALTURA: 0,85 M, GIRATORIA: NO | F16: UNIDAD | G16: 4 | H16: 16800 | I16: =G16*H16 -> 67200
A17: 8 | B17: 4.3.5-9472.2 | C17: EQUIPOS | D17: 4.3.5 | E17: PLANETARIO DIGITAL; TIPO: ALTA DEFINICION, RESOLUCION: SEGÚN PLIEGO | F17: UNIDAD | G17: 1 | H17: 1330000 | I17: =G17*H17 -> 1330000
A18: 9 | B18: 4.3.5-9163.90 | C18: EQUIPOS | D18: 4.3.5 | E18: EQUIPOS DIDACTICOS TECNICOS; NOMBRE: KIT EXPERIMENTAL , TIPO: SEGÚN PLIEGO | F18: UNIDAD | G18: 1 | H18: 5600 | I18: =G18*H18 -> 5600
A19: 10 | B19: 4.3.5-9163.90 | C19: EQUIPOS | D19: 4.3.5 | E19: EQUIPOS DIDACTICOS TECNICOS; NOMBRE: KIT EXPERIMENTAL , TIPO: SEGÚN PLIEGO | F19: UNIDAD | G19: 1 | H19: 5600 | I19: =G19*H19 -> 5600
A20: 11 | B20: 4.3.5-9163.90 | C20: EQUIPOS | D20: 4.3.5 | E20: EQUIPOS DIDACTICOS TECNICOS; NOMBRE: KIT EXPERIMENTAL , TIPO: SEGÚN PLIEGO | F20: UNIDAD | G20: 1 | H20: 5600 | I20: =G20*H20 -> 5600
A21: 12 | B21: 4.3.5-9163.90 | C21: EQUIPOS | D21: 4.3.5 | E21: EQUIPOS DIDACTICOS TECNICOS; NOMBRE: KIT EXPERIMENTAL , TIPO: SEGÚN PLIEGO | F21: UNIDAD | G21: 1 | H21: 5600 | I21: =G21*H21 -> 5600
A22: 13 | B22: 4.3.5-9163.90 | C22: EQUIPOS | D22: 4.3.5 | E22: EQUIPOS DIDACTICOS TECNICOS; NOMBRE: KIT EXPERIMENTAL , TIPO: SEGÚN PLIEGO | F22: UNIDAD | G22: 1 | H22: 5600 | I22: =G22*H22 -> 5600
A23: 14 | B23: 4.3.5-9163.90 | C23: EQUIPOS | D23: 4.3.5 | E23: EQUIPOS DIDACTICOS TECNICOS; NOMBRE: KIT EXPERIMENTAL , TIPO: SEGÚN PLIEGO | F23: UNIDAD | G23: 1 | H23: 5600 | I23: =G23*H23 -> 5600
A24: 15 | B24: 4.3.5-9163.90 | C24: EQUIPOS | D24: 4.3.5 | E24: EQUIPOS DIDACTICOS TECNICOS; NOMBRE: KIT EXPERIMENTAL , TIPO: SEGÚN PLIEGO | F24: UNIDAD | G24: 1 | H24: 5600 | I24: =G24*H24 -> 5600
A25: 16 | B25: 4.3.5-9163.90 | C25: EQUIPOS | D25: 4.3.5 | E25: EQUIPOS DIDACTICOS TECNICOS; NOMBRE: KIT EXPERIMENTAL , TIPO: SEGÚN PLIEGO | F25: UNIDAD | G25: 1 | H25: 5600 | I25: =G25*H25 -> 5600
... A30: 21 | B30: 3.3.1-2244.11 | C30: ELECTRICIDAD Y TELEFONIA | D30: 3.3.1 | E30: INSTALACIONES ELECTRICAS; DESCRIPCION: INSTALACIONES ELECTRICAS, CRITERIO SOCIAL: DECRETO 312/2010 | F30: SERVICIO | G30: 1 | H30: 259000 | I30: =G30*H30 -> 259000
B32: Especificidades Item N° 1:
B34: Descripción técnica
C35: Domos de estructura de acero Galvanizado. Tubos de 38mm. Para altas exigencias. Y Cobertura y/o Lona Anti desgarro Pesada, burlonería templada. Domo Área 27 m2 - Diámetro 5,8 ml.-Altura en el ápice 3,5 ml. - Volumen interior 63 m3 –Entradas: 1 - Peso de la estructura 229Kg. Conformada por tubos de 38 mm. de diámetro (1,5”) de acero galvanizado estructural con protección anticorrosiva de 30 micrones de zinc - Normas de fabricación de la estructura IRAM-IAS-U-500-2592- ASTM A513 Peso de la cobertura 45 Kg. Peso por m2: 660 grs./m2 de PVC laminado en dos caras. Reforzada con trama poliéster anti desgarro. Color a elección. Impermeable. Resiste vientos de hasta 150km/h. Incluye: Construcción, Armado, Instalación y puesta en funcionamiento.-
B36: Plazos y lugares de entrega
C37: El plazo de entrega no podrá ser superior a los veinte (20) días hábiles a partir de la fecha de recepción de la respectiva Orden de Compra, en el domicilio especial electrónico constituido, en virtud del método de contratación. La entrega de dichos bienes se realizará en el Dique El Jumeal sito en AV. Juan Pablo Segundo S/N. Se presentará remito que deberá cumplimentar lo dispuesto por la r.g. AFIP 1415/03, sin excepción.
B39: Calidad Minima esperada
B41: Mantenimiento: Treinta (30) Días hábiles.
B43: Garantia
C44: Garantía del fabricante minima de un (1) año.
B47: Especificidades Item N° 2:
B49: Descripción técnica
C50: Domos de estructura de acero Galvanizado. Tubos de 38mm. Para altas exigencias. Y Cobertura y/o Lona Anti desgarro Pesada, burlonería templada. Domo Área 43 m2 - Diámetro 7,4 ml. - Altura en el ápice 4,6 ml. - Volumen interior 133 m3 - Entradas: 1 Peso de la estructura 283 Kg. Conformada por tubos de 38 mm. de diámetro (1,5”) de acero galvanizado estructural con protección anticorrosiva de 30 micrones de zinc. Normas de fabricación de la estructura IRAM-IAS-U-500-2592 - ASTM A513 Peso de la cobertura 71 Kg. Peso por m2: 660 grs./m2 de PVC laminado en dos caras. Reforzada con trama poliéster anti desgarro. Color a elección. Impermeable. Incluye: Construcción, Armado, Instalación y puesta en funcionamiento.-
B51: Plazos y lugares de entrega
C52: El plazo de entrega no podrá ser superior a los veinte (20) días hábiles a partir de la fecha de recepción de la respectiva Orden de Compra, en el domicilio especial electrónico constituido, en virtud del método de contratación. La entrega de dichos bienes se realizará en el Dique El Jumeal sito en AV. Juan Pablo Segundo S/N. Se presentará remito que deberá cumplimentar lo dispuesto por la r.g. AFIP 1415/03, sin excepción.
B54: Calidad Minima esperada
B56: Mantenimiento: Treinta (30) Días hábiles.
B58: Garantia
C59: Garantía del fabricante minima de un (1) año.
B62: Especificidades Item N° 3:
B64: Descripción técnica
C65: Túnel Área 4 m2 - Altura 2,5 ml. - Perímetro 8ml Estructura de metálica de caño estructural redondo de 1 ½ (38,1mm) por 1,2mm. Unión cordón de soldadura. Laminada en dos caras. Reforzada con trama poliéster anti desgarro. Color a elección. Impermeable. Incluye: Construcción, Armado e Instalación.-
B66: Plazos y lugares de entrega
C67: El plazo de entrega no podrá ser superior a los veinte (20) días hábiles a partir de la fecha de recepción de la respectiva Orden de Compra, en el domicilio especial electrónico constituido, en virtud del método de contratación. La entrega de dichos bienes se realizará en el Dique El Jumeal sito en AV. Juan Pablo Segundo S/N. Se presentará remito que deberá cumplimentar lo dispuesto por la r.g. AFIP 1415/03, sin excepción.
B69: Calidad Minima esperada
B71: Mantenimiento: Treinta (30) Días hábiles.
B73: Garantia
C74: Garantía del fabricante minima de un (1) año.
B78: Especificidades Item N°4:
B80: Descripción técnica
C81: Piso de goma tipo homogéneo de 2 mm espesor para sectores de transito intenso, textura lisa, color a elegir. Dimensiones Largo x Ancho: 2000 cm x 200 cm. Presentación por rollo. Colocado con pegamento adhesivo de contacto sobre carpeta de nivelación. Incluye colocación.-
B82: Plazos y lugares de entrega
C83: El plazo de entrega no podrá ser superior a los veinte (20) días hábiles a partir de la fecha de recepción de la respectiva Orden de Compra, en el domicilio especial electrónico constituido, en virtud del método de contratación. La entrega de dichos bienes se realizará en el Dique El Jumeal sito en AV. Juan Pablo Segundo S/N. Se presentará remito que deberá cumplimentar lo dispuesto por la r.g. AFIP 1415/03, sin excepción.
B85: Calidad Minima esperada
B87: Mantenimiento: Treinta (30) Días hábiles.
B89: Garantia
C90: Garantía del fabricante minima de un (1) año.
B94: Especificidades Item N° 5:
B96: Descripción técnica
C97: Mesas, de madera semi circular, altura 80 cm. Estructura de soporte conformada con tubo estructural, unión cordón de soldadura. Tapa de melamina espesor 25mm, color a elegir. Diámetro externo 2.60m.
B98: Plazos y lugares de entrega
C99: El plazo de entrega no podrá ser superior a los veinte (20) días hábiles a partir de la fecha de recepción de la respectiva Orden de Compra, en el domicilio especial electrónico constituido, en virtud del método de contratación. La entrega de dichos bienes se realizará en el Dique El Jumeal sito en AV. Juan Pablo Segundo S/N Se presentará remito que deberá cumplimentar lo dispuesto por la r.g. AFIP 1415/03, sin excepción.
B101: Calidad Minima esperada
B103: Mantenimiento: Treinta (30) Días hábiles.
B105: Garantia
C106: Garantía del fabricante minima de un (1) año.
B111: Especificidades Item N° 6:
B113: Descripción técnica
C114: Tarima, semicircular compuesta por gradas en 3 niveles. Estructura metálica de soporte, conformada por tubo estructural 100x100 espesor 2mm con refuerzos de 50x50 espesor 2mm. Unión cordón de soldadura. Asientos corridos de madera tipo OSB, sin respaldo. Superficie 14m2, perímetro 16.60m. Incluye instalación.-
B115: Plazos y lugares de entrega
C116: El plazo de entrega no podrá ser superior a los veinte (20) días hábiles a partir de la fecha de recepción de la respectiva Orden de Compra, en el domicilio especial electrónico constituido, en virtud del método de contratación. La entrega de dichos bienes se realizará en el Dique El Jumeal sito en AV. Juan Pablo Segundo S/N Se presentará remito que deberá cumplimentar lo dispuesto por la r.g. AFIP 1415/03, sin excepción.
B118: Calidad Minima esperada
B120: Mantenimiento: Treinta (30) Días hábiles.
B122: Garantia
C123: Garantía del fabricante minima de un (1) año.
B128: Especificidades Item N° 7:
B130: Descripción técnica
B132: Plazos y lugares de entrega
C133: El plazo de entrega no podrá ser superior a los veinte (20) días hábiles a partir de la fecha de recepción de la respectiva Orden de Compra, en el domicilio especial electrónico constituido, en virtud del método de contratación. La entrega de dichos bienes se realizará en el Dique El Jumeal sito en AV. Juan Pablo Segundo S/N. Se presentará remito que deberá cumplimentar lo dispuesto por la r.g. AFIP 1415/03, sin excepción.
B135: Calidad Minima esperada
B137: Mantenimiento: Treinta (30) Días hábiles.
B139: Garantia
C140: Garantía del fabricante minima de un (1) año.
B144: Especificidades Item N° 8:
B146: Descripción técnica
C147: Provisión, colocación y puesta en funcionamiento Equipo de proyección sistema full dome: Incluye, espejo cóncavo en caja de transporte, Proyector DLP resolución WXGA nativa de 1280x800 y caja de operaciones con equipo de Sonido.
B148: Plazos y lugares de entrega
C149: El plazo de entrega no podrá ser superior a los veinte (20) días hábiles a partir de la fecha de recepción de la respectiva Orden de Compra, en el domicilio especial electrónico constituido, en virtud del método de contratación. La entrega de dichos bienes se realizará en el Dique El Jumeal sito en AV. Juan Pablo Segundo S/N. Se presentará remito que deberá cumplimentar lo dispuesto por la r.g. AFIP 1415/03, sin excepción.
B151: Calidad Minima esperada
B153: Mantenimiento: Treinta (30) Días hábiles.
B155: Garantia
C156: Garantía del fabricante minima de un (1) año.
B163: Especificidades Item N° 9:
B164: Descripción técnica
C165: kit acción y reacción: 40 fichas rectangulares- 1 péndulo- canaletas- 4 bolitas- 1 rueda- 1 blanco de tiro- 1 rollo de hilo- 1guia de ideas.
B166: Plazos y lugares de entrega
C167: El plazo de entrega no podrá ser superior a los veinte (20) días hábiles a partir de la fecha de recepción de la respectiva Orden de Compra, en el domicilio especial electrónico constituido, en virtud del método de contratación. La entrega de dichos bienes se realizará en el Dique El Jumeal sito en AV. Juan Pablo Segundo S/N. Se presentará remito que deberá cumplimentar lo dispuesto por la r.g. AFIP 1415/03, sin excepción.
B169: Calidad Minima esperada
...

Sheet  NotaPedido
A1: NOTA DE PEDIDO | J1: N° | K1: 018/2020
A3: JURISDICCIÓN: | D3: 70 - MINISTERIO DE CIENCIA E INNOVACION TECNOLOGICA
A4: SAF: | D4: 20 - MINISTERIO DE CIENCIA E INNOVACION TECNOLOGICA
A5: UNIDAD EJECUTORA: | D5: MINISTERIO DE CIENCIA E INNOVACION TECNOLOGICA
A6: DEPENDENCIA SOLICITANTE: | D6: DIRECCION PROVINCIAL DE GESTION ADMINISTRATIVA
A7: PERIODO UTILIZACIÓN: | D7: 4ª TRIMESTRE 2020
A8: OBJETO: | D8: ADQUISICIÓN DE EQUIPOS , MOBILIARIOS, INSUMOS Y SERVICIO PARA LA PUESTA DE DOMOS COMO ESPACIO RECREATIVO, TECNOLÒGICO Y EDUCATIVO A CONSTRUIRCE EN EL JUMEAL DE LA LOCALIDAD CAPITAL DE SAN FERNANDO DEL VALLE DE CATAMARCA- CATAMARCA.-
A10: Ítem | B10: Codigo Item | C10: DESCRIPCIÓN | H10: Adjunta Detalle Técnico | I10: Unidad Medida | J10: Precio Unitario Estimado | K10: Cantidad Solicitada
A12: 1 | B12: 4.3.9-491.107 | C12: CARPAS; TIPO: ESTRUCTURAL - DOMO, DIMENSION: SEGÚN PLIEGO, PESO:SEGÚN PLIEGO, CANTIDAD DE PERSONAS: SIN DEFINIR | H12: SI | I12: UNIDAD | J12: 308000 | K12: 1
A13: 2 | B13: 4.3.9-491.107 | C13: CARPAS; TIPO: ESTRUCTURAL - DOMO, DIMENSION: SEGÚN PLIEGO, PESO:SEGÚN PLIEGO, CANTIDAD DE PERSONAS: SIN DEFINIR | H13: SI | I13: UNIDAD | J13: 368109.53 | K13: 1
A14: 3 | B14: 4.3.9-491.106 | C14: CARPAS; TIPO: ESTRUCTURAL - TUNEL, DIMENSION: SEGÚN PLIEGO, PESO: SEGÚN PLIEGO, CANTIDAD DE PERSONAS: SIN DEFINIR | H14: SI | I14: UNIDAD | J14: 182000 | K14: 1
A15: 4 | B15: 2.4.3-742.39 | C15: PISOS EN ROLLO; MATERIAL: GOMA HOMOGENEO, TIPO: ALTO TRANSITO, ANCHO: 2M, LARGO: 20M | H15: SI | I15: UNIDAD | J15: 142800 | K15: 3
A16: 5 | B16: 4.3.7-1362.65 | C16: MESAS CURVAS; CURVA: SEMICIRCULAR, DIMENSION: SEGÚN PLIEGO, MATERIAL: MELAMINA, TERMINACION: SIN VALOR, COLOR: SIN VALOR, ANGULOS: SIN, ALTURA: SEGÚN PLIEGO, ESTANTE: SIN | H16: SI | I16: UNIDAD | J16: 42280 | K16: 2
A17: 6 | B17: 4.3.7-5851.21 | C17: TARIMAS; TIPO: SEMICIRCULAR, MATERIAL: METAL, DIMENSION: SIN VALOR | H17: SI | I17: UNIDAD | J17: 432460 | K17: 1
A18: 7 | B18: 4.3.7-45.486 | C18: SILLAS; MATERIAL ESTRUCTURA: METAL, TAPIZADO: TELA, ALTURA: 0,85 M, GIRATORIA: NO | H18: NO | I18: UNIDAD | J18: 16800 | K18: 4
A19: 8 | B19: 4.3.5-9472.2 | C19: PLANETARIO DIGITAL; TIPO: ALTA DEFINICION, RESOLUCION: SEGÚN PLIEGO | H19: SI | I19: UNIDAD | J19: 1330000 | K19: 1
A20: 9 | B20: 4.3.5-9163.90 | C20: EQUIPOS DIDACTICOS TECNICOS; NOMBRE: KIT EXPERIMENTAL , TIPO: SEGÚN PLIEGO | H20: SI | I20: UNIDAD | J20: 5600 | K20: 1
A21: 10 | B21: 4.3.5-9163.90 | C21: EQUIPOS DIDACTICOS TECNICOS; NOMBRE: KIT EXPERIMENTAL , TIPO: SEGÚN PLIEGO | H21: SI | I21: UNIDAD | J21: 5600 | K21: 1
A22: 11 | B22: 4.3.5-9163.90 | C22: EQUIPOS DIDACTICOS TECNICOS; NOMBRE: KIT EXPERIMENTAL , TIPO: SEGÚN PLIEGO | H22: SI | I22: UNIDAD | J22: 5600 | K22: 1
A23: 12 | B23: 4.3.5-9163.90 | C23: EQUIPOS DIDACTICOS TECNICOS; NOMBRE: KIT EXPERIMENTAL , TIPO: SEGÚN PLIEGO | H23: SI | I23: UNIDAD | J23: 5600 | K23: 1
... A32: 21 | B32: 3.3.1-2244.11 | C32: INSTALACIONES ELECTRICAS; DESCRIPCION: INSTALACIONES ELECTRICAS, CRITERIO SOCIAL: DECRETO 312/2010 | H32: SI | I32: SERVICIO | J32: 259000 | K32: 1
A33: Costo total estimado: PESOS CUATRO MILLONES CIENTO OCHENTA Y SIETE MIL SETECIENTOS VEINTINUEVE CON 53/100. | J33: 4187729.5

Sheet Autor Gastar
A1: EJERCICIO: | D1: ='Necesidades Trimestrales'!C6 -> 2020 | P1: AUTORIZACION PARA GASTAR
A4: JURISDICCIÓN: | G4: =' NotaPedido'!D3 -> 70 - MINISTERIO DE CIENCIA E INNOVACION TECNOLOGICA
A5: SAF: | G5: =' NotaPedido'!D4 -> 20 - MINISTERIO DE CIENCIA E INNOVACION TECNOLOGICA
A6: UNIDAD EJECUTORA: | G6: =' NotaPedido'!D5 -> MINISTERIO DE CIENCIA E INNOVACION TECNOLOGICA
A7: DEPENDENCIA SOLICITANTE: | G7: =' NotaPedido'!D6 -> DIRECCION PROVINCIAL DE GESTION ADMINISTRATIVA
A8: AUTORIZACIÓN:
A9: Señor Jefe de Servicio Administrativo Financiero:
A10: ="Autorizo la realización de los trámites correspondientes, a fin de proveer a este Organismo los bienes y/o servicios que se detallan en Nota de Pedido N° " & ' NotaPedido'!K1&", afectando la erogación resultante a los créditos presupuestarios aprobados a favor de esta Unidad Ejecutora, conforme al siguiente detalle:" -> Autorizo la realización de los trámites correspondientes, a fin de proveer a este Organismo los bienes y/o servicios que se detallan en Nota de Pedido N° 018/2020, afectando la erogación resultante a los créditos presupuestarios aprobados a favor de esta Unidad Ejecutora, conforme al siguiente detalle:
A12: IMPUTACIÓN PRESUPUESTARIA
A13: CÓDIGO | O13: DENOMINACIÓN DE LA PARTIDA PRESUPUESTARIA | Q13: IMPORTE
A14: PR | B14: SB | C14: PY | D14: AC | E14: OB | F14: UG | G14: FIN | H14: FUN | I14: I | J14: P | K14: P | L14: SubP | M14: M | N14: FF
A15: 15 | B15: 0 | C15: 0 | D15: 1 | E15: 0 | F15: 4901 | G15: 3 | H15: 4 | I15: 4 | J15: 3 | K15: 9 | L15: 0 | M15: 1 | N15: 11 | O15: Equipos Varios | Q15: 858109.53
A16: 15 | B16: 0 | C16: 0 | D16: 1 | E16: 0 | F16: 4901 | G16: 3 | H16: 4 | I16: 4 | J16: 3 | K16: 7 | L16: 0 | M16: 1 | N16: 11 | O16: Equipos de Oficina y Muebles | Q16: 1256220
A17: 15 | B17: 0 | C17: 0 | D17: 1 | E17: 0 | F17: 4901 | G17: 3 | H17: 4 | I17: 4 | J17: 3 | K17: 5 | L17: 0 | M17: 1 | N17: 11 | O17: Equipo Educacional y Recreativo | Q17: 1386000
A18: 15 | B18: 0 | C18: 0 | D18: 1 | E18: 0 | F18: 4901 | G18: 3 | H18: 4 | I18: 3 | J18: 3 | K18: 1 | L18: 0 | M18: 1 | N18: 11 | O18: Mantenimiento y Reparación de Edificios y Locales | Q18: 259000
A19: 15 | B19: 0 | C19: 0 | D19: 1 | E19: 0 | F19: 4901 | G19: 3 | H19: 4 | I19: 2 | J19: 4 | K19: 3 | L19: 0 | M19: 1 | N19: 11 | O19: Artículos de Caucho | Q19: 428400
A21: PESOS: PESOS CUATRO MILLONES CIENTO OCHENTA Y SIETE MIL SETECIENTOS VEINTINUEVE CON 53/100. | Q21: =SUM(Q15:Q20) -> 4187729.5
A23: JUSTIFICACIÓN:
A24: ADQUISICIÓN DE EQUIPOS , MOBILIARIOS, INSUMOS Y SERVICIO PARA LA PUESTA DE DOMOS COMO ESPACIO RECREATIVO, TECNOLÒGICO Y EDUCATIVO A CONSTRUIRCE EN EL JUMEAL DE LA LOCALIDAD CAPITAL DE SAN FERNANDO DEL VALLE DE CATAMARCA- CATAMARCA.-
