Workbook

Sheet Necesidades Trimestrales
B2: Pedido de Necesidades Trimestrales
A4: JURISDICCION: | C4: 040 - Ministerio de Salud
A5: SAF N°: | C5: 024 - Direccion de Administracion del Hospital Interzonal de Niños Eva Peron
A6: EJERCICIO: | C6: 2022
A7: TRIMESTRE: | C7: 2
A9: ID | B9: CODIGO ITEM | C9: RUBRO DE COMPRA | D9: I.P.P. | E9: DESCRIPCION | F9: UNIDAD DE MEDIDA | G9: CANTIDAD | H9: PRECIO UNITARIO ESTIMADO | I9: IMPORTE TOTAL ESTIMADO
A10: 1 | B10: 2.5.2-1821.235 | C10: PROD. MEDICO/FARMACEUTICOS/LAB | D10: 252 | E10: ANTIBIOTICOS P/PERSONAS; TIPO: MONODROGA, DROGA GENERICA: ACICLOVIR 500 MG, FORMA FARMACEUTICA: FRASCO AMPOLLA, PRESENTACION: 500 mGr | F10: AMPOLLA | G10: 300 | H10: 450 | I10: =+G10*H10 -> 135000
A11: 2 | B11: 2.5.2-1724.16 | C11: PROD. MEDICO/FARMACEUTICOS/LAB | D11: 252 | E11: ANALGESICOS ; TIPO: MONODROGA, DROGA GENERICA: ACIDO ACETILSALICILICO, PRESENTACION: 100 mGr, FORMA FARMACEUTICA: COMPRIMIDO | F11: COMPRIMIDO | G11: 200 | H11: 1.55 | I11: =+G11*H11 -> 310
A12: 3 | B12: 2.5.2-1864.6 | C12: PROD. MEDICO/FARMACEUTICOS/LAB | D12: 252 | E12: HIPOURICEMIANTES; TIPO: MONODROGA, DROGA GENERICA: ALOPURINOL 300 mGr, FORMA FARMACEUTICA: COMPRIMIDO, PRESENTACION: UNIDAD | F12: COMPRIMIDO | G12: 200 | H12: 12.15 | I12: =+G12*H12 -> 2430
A13: 4 | B13: 2.5.2-1821.1 | C13: PROD. MEDICO/FARMACEUTICOS/LAB | D13: 252 | E13: ANTIBIOTICOS P/PERSONAS; TIPO: MONODROGA, DROGA GENERICA: AMIKACINA, PRESENTACION: 500 mGr, FORMA FARMACEUTICA: AMPOLLA | F13: AMPOLLA | G13: 100 | H13: 87.95 | I13: =+G13*H13 -> 8795
A14: 5 | B14: 2.5.2-1821.524 | C14: PROD. MEDICO/FARMACEUTICOS/LAB | D14: 252 | E14: ANTIBIOTICOS P/PERSONAS; TIPO: ASOCIACION, DROGA GENERICA: AMOXICILINA + AC.CLAVULANICO 400 MG / 57 MG, FORMA FARMACEUTICA: SUSPENSION, PRESENTACION: ENVASE X 70 ML | F14: FRASCO | G14: 300 | H14: 374 | I14: =+G14*H14 -> 112200
A15: 6 | B15: 2.5.2-1821.440 | C15: PROD. MEDICO/FARMACEUTICOS/LAB | D15: 252 | E15: ANTIBIOTICOS P/PERSONAS; TIPO: ASOCIACION, DROGA GENERICA: AMOXICIL. 875 MG+CLAVUL.125 MG mGr, FORMA FARMACEUTICA: COMPRIMIDO, PRESENTACION: UNIDAD | F15: COMPRIMIDO | G15: 1000 | H15: 29.5 | I15: =+G15*H15 -> 29500
A16: 7 | B16: 2.5.2-1821.399 | C16: PROD. MEDICO/FARMACEUTICOS/LAB | D16: 252 | E16: ANTIBIOTICOS P/PERSONAS; TIPO: MONODROGA, DROGA GENERICA: AMOXICILINA 500 mGr, FORMA FARMACEUTICA: SUSPENSION, PRESENTACION: ENVASE X 90 mL | F16: FRASCO | G16: 300 | H16: 210 | I16: =+G16*H16 -> 63000
A17: 8 | B17: 2.5.2-1821.389 | C17: PROD. MEDICO/FARMACEUTICOS/LAB | D17: 252 | E17: ANTIBIOTICOS P/PERSONAS; TIPO: ASOCIACION, DROGA GENERICA: AMPICILINA + SULBACTAN, FORMA FARMACEUTICA: FRASCO AMPOLLA, PRESENTACION: ENVASE X 1,5 GR | F17: AMPOLLA | G17: 1000 | H17: 138 | I17: =+G17*H17 -> 138000
A18: 9 | B18: 2.5.2-1821.8 | C18: PROD. MEDICO/FARMACEUTICOS/LAB | D18: 252 | E18: ANTIBIOTICOS P/PERSONAS; TIPO: MONODROGA, DROGA GENERICA: AMPICILINA, FORMA FARMACEUTICA: AMPOLLA, PRESENTACION: 1 GR | F18: AMPOLLA | G18: 1000 | H18: 99 | I18: =+G18*H18 -> 99000
A19: 10 | B19: 2.5.2-1821.502 | C19: PROD. MEDICO/FARMACEUTICOS/LAB | D19: 252 | E19: ANTIBIOTICOS P/PERSONAS; TIPO: MONODROGA, DROGA GENERICA: AZITROMICINA 200 mGr, FORMA FARMACEUTICA: SUSPENSION, PRESENTACION: ENVASE X 15 Ml | F19: FRASCO | G19: 300 | H19: 310 | I19: =+G19*H19 -> 93000
A20: 11 | B20: 2.5.2-2199.16 | C20: PROD. MEDICO/FARMACEUTICOS/LAB | D20: 252 | E20: BLOQUEANTES NEUROMUSCULARES; DROGA GENERICA: ATRACURIO, FORMA FARMACEUTICA: AMPOLLA, PRESENTACION: 50 mGr, TIPO: MONODROGA | F20: AMPOLLA | G20: 300 | H20: 259 | I20: =+G20*H20 -> 77700
A21: 12 | B21: 2.5.2-1726.524 | C21: PROD. MEDICO/FARMACEUTICOS/LAB | D21: 252 | E21: SOLUCIONES P/MEDICINA; TIPO: SULFATO DE BARIO, PRESENTACION: ENVASE SUSPENSION PARA ENEMA X 500 ML | F21: FRASCO | G21: 5 | H21: 2810 | I21: =+G21*H21 -> 14050
... A79: 70 | B79: 2.5.2-2199.13 | C79: PROD. MEDICO/FARMACEUTICOS/LAB | D79: 252 | E79: BLOQUEANTES NEUROMUSCULARES; DROGA GENERICA: BROMURO DE VECURONIO, FORMA FARMACEUTICA: AMPOLLA X 10 mGr, PRESENTACION: UNIDAD, TIPO: MONODROGA | F79: AMPOLLA | G79: 2000 | H79: 864 | I79: =+G79*H79 -> 1728000
B81: Especificidades Item N° 12:
B82: Descripción técnica: | C82: TIPO GASTROPAQUE F
B84: Especificidades Item N° 14:
B85: Descripción técnica: | C85: BUPIVACAINA 0,5 % S/EPINEFRINA
B87: Especificidades Item N° 25:
B88: Descripción técnica: | C88: Tipo TRIYOSOM GI, TEMISTAC - Solucion Oral y Rectal
B90: Especificidades Item N° 35:
B91: Descripción técnica: | C91: TIPO GADOBUTROL , GADODIAMIDA , GADOPENTETATO
B93: Especificidades Item N° 61:
B94: Descripción técnica: | C94: Tipo OSTILAX
B96: Plazos y lugares de entrega
B97: Lugar de Entrega: SERVICIO DE FARMACIA -HOSPITAL INT. DE NIÑOS – AV. VIRGEN DEL VALLE N° 1050-CATAMARCA DE 8:00 A 12:00HS., DEBIENDO CORRER LOS GASTOS DE FLETES, ACARREO, CARGA, DESCARGA Y SEGURO A CARGO DEL ADJUDICATARIO.
B99: Plazo de entrega: Dentro de los diez (10) días habiles de notificada la Orden de Compra.
B100: Mantenimiento de Oferta: Cuarenta y Cinco (45) dias habiles.
B101: Forma de Pago: Dentro de los Treinta (30) dias habiles.

Sheet  NotaPedido
A1: NOTA DE PEDIDO | J1: N° | K1: 058/2022
A3: JURISDICCIÓN: | D3: ='Necesidades Trimestrales'!C4 -> 040 - Ministerio de Salud
A4: SAF: | D4: ='Necesidades Trimestrales'!C5 -> 024 - Direccion de Administracion del Hospital Interzonal de Niños Eva Peron
A5: UNIDAD EJECUTORA: | D5: 024 - Direccion de Administracion del Hospital Interzonal de Niños Eva Peron
A6: DEPENDENCIA SOLICITANTE: | D6: Servicio de Farmacia
A7: PERIODO UTILIZACIÓN: | D7: Semestral
A8: OBJETO: | D8: TERAPIA ANTIINFECCIOSA SISTEMICA/SUEROS INMUNES E INMUNOGLOBULINAS Y MEDIOS DE CONTRASTES /ANALGESICOS ANTINFLAMATORIOS /MIORRELAJANTES/ANESTESICOS/ANALGESICOS OPIACIOS
A10: Ítem | B10: Codigo Item | C10: DESCRIPCIÓN | H10: Adjunta Detalle Técnico | I10: Unidad Medida | J10: Precio Unitario Estimado | K10: Cantidad Solicitada
A12: 1 | B12: ='Necesidades Trimestrales'!B10 -> 2.5.2-1821.235 | C12: ='Necesidades Trimestrales'!E10 -> ANTIBIOTICOS P/PERSONAS; TIPO: MONODROGA, DROGA GENERICA: ACICLOVIR 500 MG, FORMA FARMACEUTICA: FRASCO AMPOLLA, PRESENTACION: 500 mGr | H12: NO | I12: ='Necesidades Trimestrales'!F10 -> AMPOLLA | J12: ='Necesidades Trimestrales'!H10 -> 450 | K12: ='Necesidades Trimestrales'!G10 -> 300
A13: 2 | B13: ='Necesidades Trimestrales'!B11 -> 2.5.2-1724.16 | C13: ='Necesidades Trimestrales'!E11 -> ANALGESICOS ; TIPO: MONODROGA, DROGA GENERICA: ACIDO ACETILSALICILICO, PRESENTACION: 100 mGr, FORMA FARMACEUTICA: COMPRIMIDO | H13: NO | I13: ='Necesidades Trimestrales'!F11 -> COMPRIMIDO | J13: ='Necesidades Trimestrales'!H11 -> 1.55 | K13: ='Necesidades Trimestrales'!G11 -> 200
A14: 3 | B14: ='Necesidades Trimestrales'!B12 -> 2.5.2-1864.6 | C14: ='Necesidades Trimestrales'!E12 -> HIPOURICEMIANTES; TIPO: MONODROGA, DROGA GENERICA: ALOPURINOL 300 mGr, FORMA FARMACEUTICA: COMPRIMIDO, PRESENTACION: UNIDAD | H14: NO | I14: ='Necesidades Trimestrales'!F12 -> COMPRIMIDO | J14: ='Necesidades Trimestrales'!H12 -> 12.15 | K14: ='Necesidades Trimestrales'!G12 -> 200
A15: 4 | B15: ='Necesidades Trimestrales'!B13 -> 2.5.2-1821.1 | C15: ='Necesidades Trimestrales'!E13 -> ANTIBIOTICOS P/PERSONAS; TIPO: MONODROGA, DROGA GENERICA: AMIKACINA, PRESENTACION: 500 mGr, FORMA FARMACEUTICA: AMPOLLA | H15: NO | I15: ='Necesidades Trimestrales'!F13 -> AMPOLLA | J15: ='Necesidades Trimestrales'!H13 -> 87.95 | K15: ='Necesidades Trimestrales'!G13 -> 100
A16: 5 | B16: ='Necesidades Trimestrales'!B14 -> 2.5.2-1821.524 | C16: ='Necesidades Trimestrales'!E14 -> ANTIBIOTICOS P/PERSONAS; TIPO: ASOCIACION, DROGA GENERICA: AMOXICILINA + AC.CLAVULANICO 400 MG / 57 MG, FORMA FARMACEUTICA: SUSPENSION, PRESENTACION: ENVASE X 70 ML | H16: NO | I16: ='Necesidades Trimestrales'!F14 -> FRASCO | J16: ='Necesidades Trimestrales'!H14 -> 374 | K16: ='Necesidades Trimestrales'!G14 -> 300
A17: 6 | B17: ='Necesidades Trimestrales'!B15 -> 2.5.2-1821.440 | C17: ='Necesidades Trimestrales'!E15 -> ANTIBIOTICOS P/PERSONAS; TIPO: ASOCIACION, DROGA GENERICA: AMOXICIL. 875 MG+CLAVUL.125 MG mGr, FORMA FARMACEUTICA: COMPRIMIDO, PRESENTACION: UNIDAD | H17: NO | I17: ='Necesidades Trimestrales'!F15 -> COMPRIMIDO | J17: ='Necesidades Trimestrales'!H15 -> 29.5 | K17: ='Necesidades Trimestrales'!G15 -> 1000
A18: 7 | B18: ='Necesidades Trimestrales'!B16 -> 2.5.2-1821.399 | C18: ='Necesidades Trimestrales'!E16 -> ANTIBIOTICOS P/PERSONAS; TIPO: MONODROGA, DROGA GENERICA: AMOXICILINA 500 mGr, FORMA FARMACEUTICA: SUSPENSION, PRESENTACION: ENVASE X 90 mL | H18: NO | I18: ='Necesidades Trimestrales'!F16 -> FRASCO | J18: ='Necesidades Trimestrales'!H16 -> 210 | K18: ='Necesidades Trimestrales'!G16 -> 300
A19: 8 | B19: ='Necesidades Trimestrales'!B17 -> 2.5.2-1821.389 | C19: ='Necesidades Trimestrales'!E17 -> ANTIBIOTICOS P/PERSONAS; TIPO: ASOCIACION, DROGA GENERICA: AMPICILINA + SULBACTAN, FORMA FARMACEUTICA: FRASCO AMPOLLA, PRESENTACION: ENVASE X 1,5 GR | H19: NO | I19: ='Necesidades Trimestrales'!F17 -> AMPOLLA | J19: ='Necesidades Trimestrales'!H17 -> 138 | K19: ='Necesidades Trimestrales'!G17 -> 1000
A20: 9 | B20: ='Necesidades Trimestrales'!B18 -> 2.5.2-1821.8 | C20: ='Necesidades Trimestrales'!E18 -> ANTIBIOTICOS P/PERSONAS; TIPO: MONODROGA, DROGA GENERICA: AMPICILINA, FORMA FARMACEUTICA: AMPOLLA, PRESENTACION: 1 GR | H20: NO | I20: ='Necesidades Trimestrales'!F18 -> AMPOLLA | J20: ='Necesidades Trimestrales'!H18 -> 99 | K20: ='Necesidades Trimestrales'!G18 -> 1000
A21: 10 | B21: ='Necesidades Trimestrales'!B19 -> 2.5.2-1821.502 | C21: ='Necesidades Trimestrales'!E19 -> ANTIBIOTICOS P/PERSONAS; TIPO: MONODROGA, DROGA GENERICA: AZITROMICINA 200 mGr, FORMA FARMACEUTICA: SUSPENSION, PRESENTACION: ENVASE X 15 Ml | H21: NO | I21: ='Necesidades Trimestrales'!F19 -> FRASCO | J21: ='Necesidades Trimestrales'!H19 -> 310 | K21: ='Necesidades Trimestrales'!G19 -> 300
A22: 11 | B22: ='Necesidades Trimestrales'!B20 -> 2.5.2-2199.16 | C22: ='Necesidades Trimestrales'!E20 -> BLOQUEANTES NEUROMUSCULARES; DROGA GENERICA: ATRACURIO, FORMA FARMACEUTICA: AMPOLLA, PRESENTACION: 50 mGr, TIPO: MONODROGA | H22: NO | I22: ='Necesidades Trimestrales'!F20 -> AMPOLLA | J22: ='Necesidades Trimestrales'!H20 -> 259 | K22: ='Necesidades Trimestrales'!G20 -> 300
A23: 12 | B23: ='Necesidades Trimestrales'!B21 -> 2.5.2-1726.524 | C23: ='Necesidades Trimestrales'!E21 -> SOLUCIONES P/MEDICINA; TIPO: SULFATO DE BARIO, PRESENTACION: ENVASE SUSPENSION PARA ENEMA X 500 ML | H23: SI | I23: ='Necesidades Trimestrales'!F21 -> FRASCO | J23: ='Necesidades Trimestrales'!H21 -> 2810 | K23: ='Necesidades Trimestrales'!G21 -> 5
... A81: 70 | B81: ='Necesidades Trimestrales'!B79 -> 2.5.2-2199.13 | C81: ='Necesidades Trimestrales'!E79 -> BLOQUEANTES NEUROMUSCULARES; DROGA GENERICA: BROMURO DE VECURONIO, FORMA FARMACEUTICA: AMPOLLA X 10 mGr, PRESENTACION: UNIDAD, TIPO: MONODROGA | H81: NO | I81: ='Necesidades Trimestrales'!F79 -> AMPOLLA | J81: ='Necesidades Trimestrales'!H79 -> 864 | K81: ='Necesidades Trimestrales'!G79 -> 2000
A82: Costo total estimado Pesos: Diecinueve Millones Doscientos Sesenta y Dos Mil Ochocientos Treinta y Seis Con 48/100. | J82: =SUMPRODUCT(J12:J81,K12:K81) -> 19262836

Sheet Autor Gastar
A1: EJERCICIO: | D1: ='Necesidades Trimestrales'!C6 -> 2022 | P1: AUTORIZACION PARA GASTAR
A4: JURISDICCIÓN: | G4: =' NotaPedido'!D3 -> 040 - Ministerio de Salud
A5: SAF: | G5: =' NotaPedido'!D4 -> 024 - Direccion de Administracion del Hospital Interzonal de Niños Eva Peron
A6: UNIDAD EJECUTORA: | G6: =' NotaPedido'!D5 -> 024 - Direccion de Administracion del Hospital Interzonal de Niños Eva Peron
A7: DEPENDENCIA SOLICITANTE: | G7: Servicio de Farmacia
A8: AUTORIZACIÓN:
A9: Señor Jefe de Servicio Administrativo Financiero:
A10: ="Autorizo la realización de los trámites correspondientes, a fin de proveer a este Organismo los bienes que se detallan en Nota de Pedido N° " & ' NotaPedido'!K1&", afectando la erogación resultante a los créditos presupuestarios aprobados a favor de esta Unidad Ejecutora, conforme al siguiente detalle:" -> Autorizo la realización de los trámites correspondientes, a fin de proveer a este Organismo los bienes que se detallan en Nota de Pedido N° 058/2022, afectando la erogación resultante a los créditos presupuestarios aprobados a favor de esta Unidad Ejecutora, conforme al siguiente detalle:
A12: IMPUTACIÓN PRESUPUESTARIA
A13: CÓDIGO | O13: DENOMINACIÓN DE LA PARTIDA PRESUPUESTARIA | Q13: IMPORTE
A14: PR | B14: SB | C14: PY | D14: AC | E14: OB | F14: UG | G14: FIN | H14: FUN | I14: I | J14: P | K14: P | L14: SubP | M14: M | N14: FF
A15: 36 | D15: 1 | F15: 4901 | G15: 3 | H15: 310 | I15: 2 | J15: 5 | K15: 2 | M15: 1 | N15: 1.1 | O15: PRODUCTOS FARMACEUTICOS Y MEDICINALES | Q15: 19262836
A21: TOTAL DE PESOS: DIECINUEVE MILLONES DOSCIENTOS SESENTA Y DOS MIL OCHOCIENTOS TREINTA Y SEIS CON 48/100. | Q21: =SUM(Q15:Q20) -> 19262836
A23: JUSTIFICACIÓN:
A24: Para la adquisición de insumos de TERAPIA ANTIINFECCIOSA SISTEMICA/ SUEROS INMUNES E INMUNOGLOBULINAS Y MEDIOS DE CONTRASTES/ ANALGESICOS ANTINFLAMATORIOS/ MIORRELAJANTES/ ANESTESICOS/ ANALGESICOS OPIACIOS destinados al Servicio de Farmacia del Hospital Interzonal de Niños Eva Peron, para el normal funcionamiento del organismo.
