Workbook

Sheet SAF 11
A1: 2022
B2: Pedido de Necesidades Trimestrales
A4: JURISDICCION: | C4: 040 - MINISTERIO DE SALUD
A5: SAF N°: | C5: 011 - DIRECCION PROVINCIAL DE ADMINISTRACION - MINISTERIO DE SALUD
A6: EJERCICIO: | C6: 2022
A7: TRIMESTRE: | C7: CUARTO
A9: ID | B9: CODIGO ITEM | C9: RUBRO DE COMPRA | D9: I.P.P. | E9: DESCRIPCION | F9: UNIDAD DE MEDIDA | G9: CANTIDAD TOTAL | H9: PRECIO UNITARIO ESTIMADO | I9: IMPORTE TOTAL ESTIMADO | J9: ESPECIFICACION TECNICA
A10: 1 | B10: 4.3.3-5080.1 | C10: EQUIPOS | D10: 4.3.3 | E10: ASPIRADORES DE SECRECION; ALIMENTACION: 12-220 V, TIPO: PORTATIL | F10: UNIDAD | G10: 20 | H10: 70156 | I10: =G10*H10 -> 1403120 | J10: Aspirador portátil de uso continuo libre de lubricantes. Debe Contar con una válvula reguladora de la aspiración desde un mínimo hasta un máximo. Debe poseer un frasco colector de 1000 cm3, con trampa antidesborde, para evitar el pasaje de líquido al cabezal aspirador. La unidad debe estar provista de un vacuómetro para proveer la indicación del vació generado por el aspirador. Características técnicas mínimas: - Tensión nominal: 220Vca. - Caudal de aspiración: 34 l/min - Vacío máximo: 58 cmHg - Presión de salida: 1,5 a 1,8 Kg/cm² - Presión sonora: 63,6 dB - Capacidad del recipiente: 1 litro Debe incluir: -Vaso de 1 litro con Trampa -Manual de uso
A11: 2 | B11: 4.3.3-6616.14 | C11: EQUIPOS | D11: 4.3.3 | E11: AUTOCLAVES ELECTRICOS; TIPO: AUTOMATICO, INDIC. TEMP: DIGITAL, CAPACIDAD: 20 L, ALIMENTACION: 220 V | F11: UNIDAD | G11: 1 | H11: 132500 | I11: =G11*H11 -> 132500 | J11: Estufa De Esterilización. De mesa. Uso: odontológico. Capacidad: hasta 20 litros. Voltaje: 220V. Potencia máxima: hasta 400 W. Medidas aproximadas: Altura: 31 cm, Largo: 34 cm, Ancho: 45 cm. Exterior pintado en blanco y el interior en acero inoxidable. Programas: por lo menos 4 reeestablecidos y 1 programa manual. Controles digitales comandados por un microprocesador. Bandejas: mínimo 4 (amplias y perforadas) de acero inoxidable que permitan acomodar gran cantidad de instrumental, no oxide a los mismos ni afecte puntas ni filos. Apertura: lateral. Terminación: hecha completamente en acero inoxidable.
A12: 3 | B12: 4.3.3-6616.14 | C12: EQUIPOS | D12: 4.3.3 | E12: AUTOCLAVES ELECTRICOS; TIPO: AUTOMATICO, INDIC. TEMP: DIGITAL, CAPACIDAD: 20 L, ALIMENTACION: 220 V | F12: UNIDAD | G12: 1 | H12: 525000 | I12: =G12*H12 -> 525000 | J12: Autoclave Digital Portatil Uso General 20 Litros: Debe contar con:- Sistema Inteligente de Control por Microprocesador que supervisa en tiempo Real los Parámetros de Ciclo (Temperatura/ Presión) dentro de la Cámara; - Sistema de Control LED Digital; - Alarma Sonora de Finalización de Proceso; - Sistema de Punto Seguridad (Cuando la Temperatura y la Presión llegan a su Punto de Seguridad, es cuando se podrá abrir la Tapa); - Sistema de Memoria (Programa Fijo de Ciclo: El Equipo dispone la Posibilidad de Programar y Setear un programa fijo de Ciclo de Esterilización); - Dispositivos de Seguridad: debe poseer dispositivos de Bloqueo contra Sobre temperatura y Sistema de Protección contra Sobre Presión y Sistema de Detección Automática de Fallas en el Proceso. -Cuerpo y Tapa construido en Acero Inoxidable Reforzado. - Rango de Timer 0-999 min. - Presion de Trabajo 0.142 Mpa. - Rango de Temperatura 50-126ºC. -Volumen de la Recamara Aprox. 20lt Volumen Util Aprox. 18lt. -Volumen de la cámara de esterilización Aprox. (diametro x altura) 280x260mm Cesta (diámetro x altura mm) Aprox. 260 x250mm. - Alimentación: 220V- 50Hz Consumo: 2 kW. INCLUYE UPS ACORDE AL EQUIPO
A13: 4 | B13: 4.3.3-8300.1 | C13: EQUIPOS | D13: 4.3.3 | E13: BICICLETAS P/ERGOMETRIA; VOLANTE DE INERCIA: 500 mm, ETAPA DE RESISTENCIA: 150 EN 150 Kgm, VOLANTE: DE INERCIA 500 mm | F13: UNIDAD | G13: 3 | H13: 396807 | I13: =G13*H13 -> 1190421 | J13: Bicicleta fija de caño reforzada y terminada en pintura epoxi, con piñón fijo y pedalera reforzada con transmisión a correa, debe ser totalmente silenciosa. Con asiento regulable en altura. Con manubrios antideslizantes y regulables en altura y posición. Con sistema de resistencia magnética que se modifique desde la consola y con 10 niveles de resistencia. Debe incluir computadora con múltiples funciones. Debe soportar hasta 150kg.
A14: 5 | B14: 4.3.3-5420.6 | C14: EQUIPOS | D14: 4.3.3 | E14: BOMBAS DE INFUSION; ALIMENTACION: 220 V, LECTURA: DISPLAY GRAFICO, VOLUMEN: 01-9999 ML, CONTRAPRESION: 40 KPA A 120 KPA | F14: UNIDAD | G14: 20 | H14: 316490 | I14: =G14*H14 -> 6329800 | J14: Bomba de infusión volumétrica totalmente microcontrolada para perfus genéricos siliconados. Debe contar con display TFT color LCD táctil de, al menos, 4”, el grado de protección al polvo y al agua debe ser IP24, construida con de material plástico de alta calidad, con baterías de alta duración (9 horas aproximadamente), el peso máximo no deberá superar los 1,6Kg., tensión de alimentación 220Vca con potencia aproximada de 50VA. Debe estar aprobada por ANMAT y tener 1 año de garantía mínima. Parámetros mínimos a cumplir: Precisión del sistema mayor a 1mL/h.Tasa de infusión con set de 60 gotas de 0,1 a 400mL/h. Tasa de bolus con set de 60 gotas de 0,1 a 400mL/h. Tasa de purga con set de 60 gotas de 400mL/h. Tasa de KVO de 0,01 a 5mL/h. Incremento de mínimo de caudal 0,01mL/h. Volumen total de infusión de 0,01 a 9999,99Ml. Intervalo de tiempo de 1minuto a 99horas. Rango de detección de oclusión aguas arriba de -75 a -600mmHg. Rango de detección de oclusión aguas abajo de 0 a 900mmHg. Rango de detección de aire (doble sensor) de 50 a 800uL. Debe indicar el nombre del medicamento que está infundiendo Modos de trabajo mínimos que debe incluir: Modo mL/h. Modo peso corporal. Modo goteo
A15: 6 | B15: 2.9.5-7987.9 | C15: PROD. MEDICO/FARMACEUTICOS/LAB | D15: 4.3.3 | E15: CAJAS DE INSTRUMENTAL; MATERIAL: ACERO INOXIDABLE, USO: CIRUGIA, CANTIDAD: 1 | F15: UNIDAD | G15: 20 | H15: 15200 | I15: =G15*H15 -> 304000 | J15: Caja acero inoxidable 18 x 8 x 3 cm lisa: incluye 1 Mango de Bisturi N3 + 10 Hojas de bisturí Nº10, 1 Pinza de disección 14.5 cm, 1 Pinza Kocher Recta 14 cm, 1 Pinza con diente de ratón 14.5cm 1x2dientes, 1 Pinza Halsted Recta 10 cm recta, 1 Pinza Halsted Curva 10 cm, 1 Pinza Adson 12 cm sin dientes, 1 Tijera curación recta 14 cm, 1 Tijera Mayo punta roma 14 cm, 1 Porta Agujas Mayo Hegar 14 cm, 1 Sonda acanalada 13cm.
A16: 7 | B16: 2.9.5-7987.9 | C16: PROD. MEDICO/FARMACEUTICOS/LAB | D16: 4.3.3 | E16: CAJAS DE INSTRUMENTAL; MATERIAL: ACERO INOXIDABLE, USO: CIRUGIA, CANTIDAD: 1 | F16: UNIDAD | G16: 20 | H16: 18000 | I16: =G16*H16 -> 360000 | J16: Caja 20 x 0,9x04cm A. Incluye: 1 Tijera mayo recta 14 CM. 1 Tijera iris curva 9 CM. Estilete. 1 Sonda acanalada 13cm. 1 Porta agujas mayo hegar 14 CM. 1 Pinza kocher recta 14 CM. 1 Pinza halstead curva 10 CM. 1 Pinza halstead recta 10 CM. 1 Pinza de disección 14,5 CM. 1 Pinza diente de ratón 14.5 1x2 dientes CM. 1 Mango para bisturí nro3. 1Separador farabeuf 15x1.5 CM (par)
A17: 8 | B17: 2.9.5-7987.1 | C17: PROD. MEDICO/FARMACEUTICOS/LAB | D17: 4.3.3 | E17: CAJAS DE INSTRUMENTAL; MATERIAL: ACERO INOXIDABLE, USO: EXAMEN GINECOLOG./INST.DE DIU, CANT.INSTRUMETAL: 10, CANTIDAD: 1 | F17: UNIDAD | G17: 7 | H17: 36100 | I17: =G17*H17 -> 252700 | J17: CAJA DE COLOCACION DE DIU: caja acero inoxidable. 30 x 15 x 8 cm aprox. Incluyre: - 2 pinza maier 20 cm recta, - 1 pinza bertola 18 cm recta, - 1 pinza bertola 18 cm curva, - 1 pinza allis 19 cm. 5 x 6 dientes, - 2 tijera metzenbaum 20 cm, - 2 pinza pozzi erina 25 cm, - 1 histerómetro sims 32 cm maleable
A18: 9 | B18: 4.3.3-1719.48 | C18: EQUIPOS | D18: 4.3.3 | E18: CAMILLAS; ANCHO: 60 Cm, LARGO: 200 Cm, ALTO: 70 Cm, ARNESES: SIN, TIPO: RODANTE | F18: UNIDAD | G18: 20 | H18: 62710 | I18: =G18*H18 -> 1254200 | J18: Camilla de transporte reforzada con estructura metálica acabada en pintura epoxi, con barandas rebatibles, porta suero, porta oxígeno, con cuatro ruedas de 125 mm de diámetro como mínimo, con frenos. De espuma de poliuretano de alta densidad tapizada en ecocuero de primera calidad de color negro
A19: 10 | B19: 4.3.3-1719.27 | C19: EQUIPOS | D19: 4.3.3 | E19: CAMILLAS; ANCHO: 75 Cm, LARGO: 185 Cm, ALTO: 75 Cm, ARNESES: SIN, TIPO: KINESICA | F19: UNIDAD | G19: 3 | H19: 66300 | I19: =G19*H19 -> 198900 | J19: Camilla fija para kinesiología con medidas aproximadas de: 75cm ancho, 185cm de largo y 75cm de alto, que soporte al menos 200kg de peso. Compuesta de caño estructural terminado en pintura epoxi. Con espuma de poliuretano de alta densidad tapizada en ecocuero de primera calidad de color negro.
A20: 11 | B20: 4.3.2-6331.12 | C20: TRANSPORTE Y DEPOSITO | D20: 4.3.3 | E20: CARROS P/TRANSP.; SUPERFICIE: 30 X 40 Cm, ALTURA: 120 Cm, MATERIAL: CHAPA METAL PLEGADA, ESTRUCTURA: METALICA, RUEDAS: 2 REFORZADAS- DIAM. 180 mm, ACCESORIO: 2 AGARRADERAS, MATERIAL ESTRUCTURA: METALICA | F20: UNIDAD | G20: 14 | H20: 16756 | I20: =G20*H20 -> 234584 | J20: Carro metálico protegido por pintura epoxi, para tubo de oxígeno de 6m3, con ruedas de goma de aproximadamente 175 a 180 mm y sistema de sujeción del tubo.
A21: 12 | B21: 4.3.3-5416.1 | C21: EQUIPOS | D21: 4.3.3 | E21: CARROS USO HOSPITALARIO; TERMINACION: ANTIOXIDANTE, ESTRUCTURA: REFORZADA DE CHAPA ACERO SAE, MEDIDAS: 0,70 X 0,50 X 0,90 M, PARACHOQUE: GOMA, PLANO SUPERIOR: ESTRATIFICADOS CON BARANDAS, CAJONES: CON, DIVISIONES: P/MATERIALES, MASTIL: CON, CONTENEDOR: P/RESIDUOS BIOLOGICOS, ALZADA SUPERIOR: PORTA CARDIODESFIBRILADOR, CANTIDAD DE CAJONES: CON, MATERIAL ESTRUCTURA: REFORZADA DE CHAPA ACERO SAE, DIMENSION: 0,70 X 0,50 X 0,90 M, TIPO: DE PARO | F21: UNIDAD | G21: 14 | H21: 408143 | I21: =G21*H21 -> 5714002 | J21: Carro de paro de 5 cajones. Construido en chapa SAE 1010. Cinco cajones con cerradura central, uno de ellos con división para medicamentos. Alzada para monitor Bandeja auxiliar lateral corrediza de acero inoxidable. Porta suero, porta tubo de oxígeno y parachoque perimetral. Manija de arrastre. Ruedas de aproximadamente 100mm, al menos dos de ellas con freno. Contenedor para residuos patógenos. Terminación pintura epoxi.
... A46: 37 | B46: 2.9.5-2020.1 | C46: PROD. MEDICO/FARMACEUTICOS/LAB | D46: 4.3.3 | E46: TAMBORES QUIRURGICOS; MATERIAL: ACERO INOXIDABLE, DIMENSION: 10 X 12 Cm | F46: UNIDAD | G46: 20 | H46: 11000 | I46: =G46*H46 -> 220000 | J46: Tambor Algodonero, tapa perforada
A47: TOTAL RUBRO | I47: =SUM(I10:I46) -> 50728263
C49: ESPECIFICIDADES Y DETALLE TECNICO:
C50: * ADJUNTAR FOLLETERIA, MANUALES Y/O CUALQUIER OTRA DOCUMENTACION QUE EL PROVEEDOR ESTIME NECESARIO PARA ACLARAR EL BIEN COTIZADO. EN CASO DE CORRESPONDER ADJUNTAR CERTIFICADO DE ANMAT.
C52: Plazos de entrega: | D52: veinte (20) dias habiles
C54: Lugar de Entrega: | D54: MINISTERIO DE SALUD - CHACABUCO N° 169 - en el horario de 8:00hs a 12:00hs de lunes a viernes
C56: Calidad Minima esperada:
C58: Garantia: | D58: garantia integral de doce (12) meses.
C60: Mantenimiento de oferta: | D60: cuarenta y cinco (45) días
C63: ESPECIFICIDADES ITEM 1
C64: =J10 -> Aspirador portátil de uso continuo libre de lubricantes. Debe Contar con una válvula reguladora de la aspiración desde un mínimo hasta un máximo. Debe poseer un frasco colector de 1000 cm3, con trampa antidesborde, para evitar el pasaje de líquido al cabezal aspirador. La unidad debe estar provista de un vacuómetro para proveer la indicación del vació generado por el aspirador. Características técnicas mínimas: - Tensión nominal: 220Vca. - Caudal de aspiración: 34 l/min - Vacío máximo: 58 cmHg - Presión de salida: 1,5 a 1,8 Kg/cm² - Presión sonora: 63,6 dB - Capacidad del recipiente: 1 litro Debe incluir: -Vaso de 1 litro con Trampa -Manual de uso
C66: ESPECIFICIDADES ITEM 2
C67: =J11 -> Estufa De Esterilización. De mesa. Uso: odontológico. Capacidad: hasta 20 litros. Voltaje: 220V. Potencia máxima: hasta 400 W. Medidas aproximadas: Altura: 31 cm, Largo: 34 cm, Ancho: 45 cm. Exterior pintado en blanco y el interior en acero inoxidable. Programas: por lo menos 4 reeestablecidos y 1 programa manual. Controles digitales comandados por un microprocesador. Bandejas: mínimo 4 (amplias y perforadas) de acero inoxidable que permitan acomodar gran cantidad de instrumental, no oxide a los mismos ni afecte puntas ni filos. Apertura: lateral. Terminación: hecha completamente en acero inoxidable.
C69: ESPECIFICIDADES ITEM 3
C70: =J12 -> Autoclave Digital Portatil Uso General 20 Litros: Debe contar con:- Sistema Inteligente de Control por Microprocesador que supervisa en tiempo Real los Parámetros de Ciclo (Temperatura/ Presión) dentro de la Cámara; - Sistema de Control LED Digital; - Alarma Sonora de Finalización de Proceso; - Sistema de Punto Seguridad (Cuando la Temperatura y la Presión llegan a su Punto de Seguridad, es cuando se podrá abrir la Tapa); - Sistema de Memoria (Programa Fijo de Ciclo: El Equipo dispone la Posibilidad de Programar y Setear un programa fijo de Ciclo de Esterilización); - Dispositivos de Seguridad: debe poseer dispositivos de Bloqueo contra Sobre temperatura y Sistema de Protección contra Sobre Presión y Sistema de Detección Automática de Fallas en el Proceso. -Cuerpo y Tapa construido en Acero Inoxidable Reforzado. - Rango de Timer 0-999 min. - Presion de Trabajo 0.142 Mpa. - Rango de Temperatura 50-126ºC. -Volumen de la Recamara Aprox. 20lt Volumen Util Aprox. 18lt. -Volumen de la cámara de esterilización Aprox. (diametro x altura) 280x260mm Cesta (diámetro x altura mm) Aprox. 260 x250mm. - Alimentación: 220V- 50Hz Consumo: 2 kW. INCLUYE UPS ACORDE AL EQUIPO
C72: ESPECIFICIDADES ITEM 4
C73: =J13 -> Bicicleta fija de caño reforzada y terminada en pintura epoxi, con piñón fijo y pedalera reforzada con transmisión a correa, debe ser totalmente silenciosa. Con asiento regulable en altura. Con manubrios antideslizantes y regulables en altura y posición. Con sistema de resistencia magnética que se modifique desde la consola y con 10 niveles de resistencia. Debe incluir computadora con múltiples funciones. Debe soportar hasta 150kg.
C75: ESPECIFICIDADES ITEM 5
C76: =J14 -> Bomba de infusión volumétrica totalmente microcontrolada para perfus genéricos siliconados. Debe contar con display TFT color LCD táctil de, al menos, 4”, el grado de protección al polvo y al agua debe ser IP24, construida con de material plástico de alta calidad, con baterías de alta duración (9 horas aproximadamente), el peso máximo no deberá superar los 1,6Kg., tensión de alimentación 220Vca con potencia aproximada de 50VA. Debe estar aprobada por ANMAT y tener 1 año de garantía mínima. Parámetros mínimos a cumplir: Precisión del sistema mayor a 1mL/h.Tasa de infusión con set de 60 gotas de 0,1 a 400mL/h. Tasa de bolus con set de 60 gotas de 0,1 a 400mL/h. Tasa de purga con set de 60 gotas de 400mL/h. Tasa de KVO de 0,01 a 5mL/h. Incremento de mínimo de caudal 0,01mL/h. Volumen total de infusión de 0,01 a 9999,99Ml. Intervalo de tiempo de 1minuto a 99horas. Rango de detección de oclusión aguas arriba de -75 a -600mmHg. Rango de detección de oclusión aguas abajo de 0 a 900mmHg. Rango de detección de aire (doble sensor) de 50 a 800uL. Debe indicar el nombre del medicamento que está infundiendo Modos de trabajo mínimos que debe incluir: Modo mL/h. Modo peso corporal. Modo goteo
C78: ESPECIFICIDADES ITEM 6
C79: =J15 -> Caja acero inoxidable 18 x 8 x 3 cm lisa: incluye 1 Mango de Bisturi N3 + 10 Hojas de bisturí Nº10, 1 Pinza de disección 14.5 cm, 1 Pinza Kocher Recta 14 cm, 1 Pinza con diente de ratón 14.5cm 1x2dientes, 1 Pinza Halsted Recta 10 cm recta, 1 Pinza Halsted Curva 10 cm, 1 Pinza Adson 12 cm sin dientes, 1 Tijera curación recta 14 cm, 1 Tijera Mayo punta roma 14 cm, 1 Porta Agujas Mayo Hegar 14 cm, 1 Sonda acanalada 13cm.
C81: ESPECIFICIDADES ITEM 7
C82: =J16 -> Caja 20 x 0,9x04cm A. Incluye: 1 Tijera mayo recta 14 CM. 1 Tijera iris curva 9 CM. Estilete. 1 Sonda acanalada 13cm. 1 Porta agujas mayo hegar 14 CM. 1 Pinza kocher recta 14 CM. 1 Pinza halstead curva 10 CM. 1 Pinza halstead recta 10 CM. 1 Pinza de disección 14,5 CM. 1 Pinza diente de ratón 14.5 1x2 dientes CM. 1 Mango para bisturí nro3. 1Separador farabeuf 15x1.5 CM (par)
C84: ESPECIFICIDADES ITEM 8
C85: =J17 -> CAJA DE COLOCACION DE DIU: caja acero inoxidable. 30 x 15 x 8 cm aprox. Incluyre: - 2 pinza maier 20 cm recta, - 1 pinza bertola 18 cm recta, - 1 pinza bertola 18 cm curva, - 1 pinza allis 19 cm. 5 x 6 dientes, - 2 tijera metzenbaum 20 cm, - 2 pinza pozzi erina 25 cm, - 1 histerómetro sims 32 cm maleable
C87: ESPECIFICIDADES ITEM 9
C88: =J18 -> Camilla de transporte reforzada con estructura metálica acabada en pintura epoxi, con barandas rebatibles, porta suero, porta oxígeno, con cuatro ruedas de 125 mm de diámetro como mínimo, con frenos. De espuma de poliuretano de alta densidad tapizada en ecocuero de primera calidad de color negro
C90: ESPECIFICIDADES ITEM 10
C91: =J19 -> Camilla fija para kinesiología con medidas aproximadas de: 75cm ancho, 185cm de largo y 75cm de alto, que soporte al menos 200kg de peso. Compuesta de caño estructural terminado en pintura epoxi. Con espuma de poliuretano de alta densidad tapizada en ecocuero de primera calidad de color negro.
C93: ESPECIFICIDADES ITEM 11
C94: =J20 -> Carro metálico protegido por pintura epoxi, para tubo de oxígeno de 6m3, con ruedas de goma de aproximadamente 175 a 180 mm y sistema de sujeción del tubo.
C96: ESPECIFICIDADES ITEM 12
C97: =J21 -> Carro de paro de 5 cajones. Construido en chapa SAE 1010. Cinco cajones con cerradura central, uno de ellos con división para medicamentos. Alzada para monitor Bandeja auxiliar lateral corrediza de acero inoxidable. Porta suero, porta tubo de oxígeno y parachoque perimetral. Manija de arrastre. Ruedas de aproximadamente 100mm, al menos dos de ellas con freno. Contenedor para residuos patógenos. Terminación pintura epoxi.
C99: ESPECIFICIDADES ITEM 13
C100: =J22 -> COAGULOMETRO: Principio de medición: FOTOMÉTRICO Y TURBODENSITOMÉTRICO, MÉTODOS COAGULOMÉTRICOS. CROMOGÉNICOS Y TURBIDIMÉTRICOS. BLOQUE DE MEDICIÓN: TEMPERATURA CONTROLADA A 37,4 +/- 0.4°C (CON SISTEMA PELTIER). 2 O 4 CANALES DE MEDICIÓN CON DOS LONGITUDES DE ONDA (405 NM Y 750NM) DISPONIBLES CADA UNO. 4 POSICIONES DE REACTIVOS, UNA DE ELLAS CON FUNCIÓN MEZCLADORA.18/16 POSICIONES DE INCUBACIÓN DE CUBETAS. INICIO AUTOMÁTICO CON EL AGREGADO DEL REACTIVO. VOLUMEN DEL TEST: MICROCUBETAS CON CAPACIDAD DE 150-300UL. PANTALLA: LCD. 2 LINES. 20 CARÁCTERES CADA UNA. PANEL DE CONTROL: TECLADO DE MEMBRANA. INTERFACE: RS232 (IMPRESORA/ LECTOR DE CÓDIGO DE BARRAS). USB (HOST). SD-CARD. IMPRESORA: IMPRESORA TÉRMICA INTEGRADA. DIMENSIONES/PESO:26X33X9 CM (LARGO/ANCHO/ALTO):3,9KG. DETERMINACIONES: TP-APTT-FIB-TT-FACTORES VÍA. INTRINSECA Y EXTRINSECA – ATII – PC-DRVVT-DD SOFWARE/HARDWARE: SISTEMA ABIERTO. PARÁMETROS DE TESTS EDITABLES Y COPIABLES. 15 TESTS PROGRAMABLES. CÁLCULO AUTOMÁTICO EN SEGUNDOS, RIN% G7L, MG/DL, RATIO, ME, UG/ML. CURVA DE CALIBRACIÓN: EDITABLE (DE HASTA 9 PUNTOS). COMUNICACIÓN HOST UNDIRECCIONAL. INTERFAZ DE USUARIO MULTILINGUE (DE, EN, ES,FR,PT,TU). FUENTE DE ALIMENTACION:100V-240V. 47-63HZ,260MA. SALIDA:24VDC/3.7A. OPCIONAL: CONEXIÓN A IMPRESORA TÉRMICA EXTERNA. CONEXIÓN A LECTOR DE CÓDIGO DE BARRAS. INCLUYE UPS ACORDE AL EQUIPO
C102: ESPECIFICIDADES ITEM 14
C103: =J23 -> Contador Hematológico Detección de WBC, detección de RBC y detección de PLT. -Principio de medición: impedancia eléctrica más colorimetría. - Diferencia la población leucocitaria en tres grupos: neutrófilos, linfocitos y células medias (monocitos, eosinófilos y basófilos). -Dos modos de conteo: sangre completa o prediluida. - 9ul de muestra para el modo sangre entera y modo sangre capilar. -Almacenamiento de hasta 200.000 resultados incluyendo histogramas. Impresora térmica incorporada. Opción para impresora externa. -Lector de código de barras para muestras (opcional). -Pantalla color táctil de 8,4 pulgadas. -Diseño compacto, de 30 cm de ancho -Seguro y simple de usar -Software y manuales de operación en su idioma. INCLUYE UPS ACORDE AL EQUIPO
C105: ESPECIFICIDADES ITEM 15
C106: =J24 -> Analizadores de hematología compactos totalmente automatizados con diferencial minimo de 4 partes. Especificaciones Principios y tecnologías: *Citometría de flujo fluorescente: WBC, DIFF, RET, IRF, diferencial de 2 partes para el análisis de fluidos corporales; *Método de impedancia con enfoque hidrodinámico: PLT-I, RBC, HCT; *Método SLS-hemoglobina libre de cianuro: HGB. Parámetros analizados: * Parámetros reportables en sangre entera y modo prediluido. (WBC, RBC, HGB, HCT, VCM, HCM, CHCM, PLT-I, RDW-SD, RDW-CV, MPV, NEUT #, LINFO #, MONO #, EO #, BASO #, NEUT%, LINFO%, MONO%, EO%, BASO%, IG #, IG%), * Parámetros de investigación en sangre entera y modo prediluido (PDW, P-LCR, PCT),* Parámetros reportables en el modo de fluidos corporales (WBC-BF, RBC-BF, MN_, PMN_, MN_, PMN%, TC-BF#), * Parámetros reportables en el canal de reticulocitos (RET#, RET%, IRF, RET-He), *Parámetros de investigación del canal de reticulocitos (LFR, MFR, HFR, PLT-O). Rendimiento: * Sangre entera: CBC: hasta 60 muestras por hora; CBC + DIFF: hasta 60 muestras por hora; CBC + DIFF + RET: hasta 35 muestras por hora. * Fluidos corporales: hasta 30 muestras por hora. Modo de aspiración: análisis de tubo cerrado Volumen de aspiración de muestra: * Sangre entera/modo Low WBC: 25 μl; * Modo prediluido: 70 μl; * Modo de fluidos corporales: 70 μl. Almacenamiento de datos: * Resultados: 100.000 muestras; * Información de pacientes: 10.000 registros; * Archivos de control de calidad: 99 archivos por analizador; * Gráficas de control de calidad: 300 datos por archivo; * Histórico de reemplazo de reactivos: 5.000 registros; * Histórico de mantenimiento: 5.000 registros. Control de calidad: * Tres niveles de material de control de calidad para todos los parámetros; * Dos niveles de material de control de calidad para fluidos corporales. Dimensiones y peso aproximado: Unidad principal: Ancho: 450 mm, Profundidad: 460 mm, Altura: 440 mm / Aprox.36 kg; Pantalla: táctil multicolor integrada con gráficas de usuario intuitiva interfaz para respaldar tareas de rutina. Conectividad extendida: * Puerto RS-232C y el puerto LAN para la conexión con el sistema de información (LIS) de cada laboratorio. * Cuatro puertos USB para lector de código de barras portátil, impresora y conexiones de dispositivos USB. INCLUYE UPS ACORDE AL EQUIPO
C108: ESPECIFICIDADES ITEM 16
C109: =J25 -> Cuna acrílica articulada con colchón debe permitir el movimiento para mecer o fijar en una posición deseada. La estructura del carro construida en perfiles de hierro pintado con pintura epoxi. Canasto de acrílico transparente moldeado en una sola pieza con tarjetero de identificación. Tren rodante compuesto por 4 ruedas giratorias duales de, al menos, 50 mm. 2 de ellas con freno. Debe Incluir colchón a medida que compense la curvatura de la cuna brindando una superficie plana. Medidas aproximadas: 75 x 35 x 80 cm (largo x ancho x alto).
C111: ESPECIFICIDADES ITEM 17
C112: =J26 -> Electrocardiógrafo digital de 3 canales con cabezal de impresión térmica para papel de 50mm. Cantidad de derivaciones: 12. Totalmente digital, con pantalla de LCD de alta resolución para visualizar la señal de ECG antes de la impresión. Con resolución de impresión mínima de 8 puntos/mm. Debe poseer al menos 2 filtros digitales para evitar señales ruidosas. Debe ser provisto con cable paciente con protección contra desfibrilación. Con alarma de desconexión de electrodos mostrando en pantalla la derivación suelta. Alimentación eléctrica de 220Vca, 50Hz, 35Va con batería con 3 horas de autonomía como mínimo. El peso máximo debe ser de 2,5Kg. La medición de ECG debe cumplir con las siguientes características mínimas: Circuito de entrada flotante, con protección de marcapasos y de desfibrilación, 12 derivaciones, Resolución del conversor A/D de 12 bits, Voltaje de calibración 1mV +/-3%, Sensibilidad: 2,5; 5; 10; 20 (mm/mV), Impedancia de entrada mayor a 10MOhms, Con autocentrado de línea de base, Modo de registro manual/automático, Seguridad anti shock eléctrico: Clase I – Tipo CF. Accesorios que debe incluir: Cable de alimentación, Cable paciente con protección contra desfibrilación, Juego de 4 electrodos de miembros tipo pinzas, Juego de electrodos precordiales tipo peritas, Rollo de papel térmico de 50mm, Portarollo de papel, Cable de tierra, Manual de instrucciones.
C114: ESPECIFICIDADES ITEM 18
C115: =J27 -> Monitor Multiparamétrico con pantalla táctil LCD color de 10” como mínimo, con resolución aproximada de 800x600, con botonera que permita realizar todas las funciones sin tocar la pantalla, con la posibilidad de seleccionar entre pacientes adultos, pediátricos y neonatales. Con múltiples puertos USB para conectar teclado, mouse y memorias extraíbles. Con los siguientes parámetros mínimos: ECG, Respiración, Temperatura, SpO2 y PNI. Con detección de marcapasos automática. Con batería con autonomía mínima de 4 horas. Debe cumplir con los siguientes requerimientos mínimos:  Memoria interna: para más de 120 horas de tablas y/o gráficos de tendencia. 1200 mediciones de PNI. 200 eventos de arritmias. 200 alarmas.  ECG: con cable de 5 derivaciones, velocidad de barrido de 25mm/seg. Rango de frecuencia de 15 a 350ppm con precisión del 1%.  Respiración: por impedancia entre RA-LL y RA-LA. Rango de medición de 0 a 150rpm con precisión de 2rpm.  Temperatura: Con sensor tipo YSI-10K, método por resistencia térmica, rango de medición de 0 a 50 ºC, con precisión de 0,3ºC.  SpO2: con sensor óptico, con rango de medición de 0 a 100% y precisión de 3%  PNI: por método oscilométrico, en modos manual/automático/continuo, rango de medición de 0 a 300mmHg con precisión de 1mmHg. Accesorios que se deben entregar:  1 Cable troncal de interconexión de ecg  1 Set de latiguillos de 5 derivaciones para ECG  1 Prolongador de interconexión para SpO2  1 Sensor de oximetría tipo dedal para adultos  1 Sensor de oximetría para pediatría/neonatología  1 Cuff tamaño pediátrico para PNI  1 Cuff tamaño adulto para PNI  1 Sensor de temperatura de piel  1 Batería  1 Cable de alimentación  Manuales y demás documentación. Debe estar inscripto en ANMAT y poseer 1 año de garantía.
C117: ESPECIFICIDADES ITEM 19
C118: =J28 -> Equipo de rayos rodante, con disparador digital. Características generales: Distancia Foco-Película: 200 mm; Diámetro de Diafragma de Plomo (filtro irremovible): 26 mm; Campo de Radiación (diam.): 60 mm; Corriente al Tubo: 9mA; Filtración Total: Equiv a 2.0 mm Al; Mancha Focal efectiva: 0.8 mm, Arrollamiento Inmerso en Aceite; Radiación Exterior ˂0,01 mGy/h a 100 cm de distancia; Peso aproximado: 35 kg Características eléctricas: Alimentación: 230/110 VAC . ±10% – 50/60 Hz; Corriente Primaria; 4 A max – 230 VAC, 920 VA; 8 A max – 110 VAC, 880 VA; Alta Tensión: 70 Kvp
C120: ESPECIFICIDADES ITEM 20
C121: =J29 -> Electroestimulador de ondas rusas de 8 canales. Totalmente microprocesado con 42 programas pre-establecidos como mínimo y la posibilidad de programar manualmente el tratamiento. Deberá contar con 3 modos de trabajo: Todos los canales, Extensión-Flexión, Secuencial. ONDAS RUSAS – 2500/5000 Hz. / INTERFERENCIAL / TENS. Ondas rusas: Con una frecuencia de 2.500 Hz. Aplicadas en ráfagas, con una frecuencia de 10 a 100 Hz. Las ondas deben presentar una rampa de subida que comience a intensidad cero y vaya aumentando progresivamente hasta llegar al máximo seleccionado, luego debe mantener la intensidad constante (pero siempre en ráfagas), y luego caer suavemente en algunos segundos. Los tiempos para las zonas de rampas, contracción y relajación se deben poder modificar de acuerdo a cada paciente y tratamiento. Características eléctricas mínimas: • Aparato Clase I • Alimentación: 220 VCA 50/60 Hz • Consumo promedio: 200 Vatios • Controlado por Microprocesador • Pantalla LCD Gráfica COLOR de 320 x 240 sensible al tacto, retro iluminada. Accesorios que debe incluir: • 12 bandas elásticas largas con abrojo. • 16 electrodos grandes de 100 mm. • 8 electrodos chicos de 50 mm. • 8 cables dobles con Plug a fichas bananas de 4 mm. • 1 cable de Alimentación.
C123: ESPECIFICIDADES ITEM 21
C124: =J30 -> Equipo generador de campo magnético totalmente digital. Con una pantalla LCD-LED. Debe incluir las siguientes patologías prefijadas: Artrosis, Osteoporosis, Tendinitis, Fractura, Desgarro, Lesiones Nerviosas, Heridas, Dermatosis, Bursitis, Epicondritis, Osteomielitis. También deberá contar con al menos 5 posiciones de memoria para que usuario configure sus programas. Y contar con un “modo” manual cuando no este seleccionada ni una patología ni una memoria de usuario. Debe poseer cuatro salidas como mínimo para conectar tanto aplicadores tipo túnel como así también aplicadores planos, pudiendo funcionar todos en forma simultánea. El equipo debe cumplir con las siguientes características técnicas mínimas: • Tensión de alimentación: 220 V - 50/60 Hz • Consumo: 50 watts • Potencia de Emisión: 500 gauss • Frecuencia de Emisión: 5 a 100 hz. (en pasos de 5hz) • Controles: panel táctil • Potencia: Variable Por Comando Digital • Interfaz: Pantalla LCD-LED retroiluminada. • Temporizador: Digital • Normas: IEC 60601.1 - Equipo Clase 1 - tipo BF • Grado de Protección contra penetración de líquidos: IPX0 • Medidas aprox: 33.5 x 11.5 x 27 cm. (ancho x alto x profundidad) Debe incluir: -1 Equipo de Magnetoterapia con 4 salidas - (11 Programas + 5 Memorias), 2 Aplicadores Planos (Solenoides), -1 kit de bandas elásticas de 60 milímetros y pasador para ajustar, -1 Aplicador Túnel con Aros de Alto Impacto de 27cm de diámetro (efectivos 24cm), - 1 Cable de Conexión, -1 Manual en español. -1 Imán para corroborar el funcionamiento del equipo.
C126: ESPECIFICIDADES ITEM 22
C127: =J31 -> SILLON DENTAL COLGANTE COMPLETO • Tapizado en cuerina anatómico y ergonómico sin costuras • Apoya cabeza multi-articulado • Foco LED circular, intensidad regulable • Con calentador de agua llena vaso • Control para asistente • Salivadera redonda de vidrio templado con llena vaso y lava bacha comandados • Sistema de agua presurizada • Platina regulable Colibrí o manguera colgante • Comandos electricos • Tres salidas neumática • Jeringa Triple • Negatoscopio LED • Eyector de alta y baja potencia • INCLUYE: * Banqueta con respaldo de contacto permanente, * Cavitador Neumático Kmd (3 Insertos), * Turbina Simple Spray Saca Fresa, * Contra Angulo 1:1 Coxo Externo a Gatillo, * Micromotor Neumático Rose 201am‐b2 Spray Externo 6m, * Compresor Gdk Jw032b 1.1hp 850w 38l Libre Aceite.
C129: ESPECIFICIDADES ITEM 23
C130: =J32 -> Programa de 5, 10, 15, 20 segundos. Continuo + Intermitente + función Rampa. Con protector U.V. Comando digital. Fibra óptica giratoria 360º y esterilizable. Emisión de luz de hasta 480 nm. Polimeriza 4 mm en 10 segundos. Su potencia es de 1200 mW/cm2.
C132: ESPECIFICIDADES ITEM 24
C133: =J33 -> Espectrofótometro: Analizador clínico semiautomático de última generación. Impresora incorporada. Sistema que permite trabajar con microcelda de flujo termostatizada o cubetas macro y semimicro. Almacena hasta 132 técnicas abiertas y 30 curvas de calibración Sistema óptico: -Monocromador con filtros interferenciales. -Rango de longitudes de onda: 340 - 1000 11111. -Selección de longitud de onda: rueda automática de filtros con 9 posiciones. -Filtros instalados: 340,405, 450, 505, 550, 620 y 750 nm + 2 posiciones libres. -Ancho de banda: 1O o 2 nm. -Rango fotométrico: -0,5 - 4,000 Abs. -Precisión: +/- 0,002 Abs. Fuente de luz: -Lámpara Halógena 6V - 1OW. Cero automático. -Stand by automático. Ajuste automático por Software. Sistema de cubetas DUAL: -Microcelda de flujo metálica con ventana de cuarzo. -10 mm de paso de luz, volumen: 18 µl. -Soporte standard de 10 nun x 10 nun para cubeta externa macro o semi-micro. -Celda de flujo termostatizada por efecto Peltier: 25°C, 30°C, 37°C. Sistema de aspiración: -Bomba peristá ltica con motor paso a paso. -Volúmen programable: 100 a 500 µl. -Arrastre: 2% para 400 µl. Interface con el operador: -Teclado de membrana con 25 teclas para funciones y entradas numéricas. -Impresora térmica incorporada: 27 caracteres/línea. -Display gráfico de cristal liquido con contraste. Programas: -132 test programables. -Control de Calidad: Estadísticas, Gráficos de Levey Jennings. -Hasta 1O controles programables. Menu de mantenimiento. Control de impresora. INCLUYE UPS ACORDE AL EQUIPO
C135: ESPECIFICIDADES ITEM 25
C136: =J34 -> Interior en acero inoxidable grado 304 18/8 Exterior de hierro con pintura horneada Aislamiento con lana de vidrio 2 puertas laterales con cierre a falleba giratoria Ajuste de puertas con cordón de silicona Aireador en la parte superior Termómetro a mercurio de control empotrado en el frente Temperatura mínima de trabajo 30ºC Temperatura máxima de trabajo 200ºC Termorregulador hidráulico a capilar Indicadores luminosos de funcionamiento Interruptor de corte de funcionamiento Exactitud: +- 1,5% del valor final de temperatura Uniformidad: +- 1,5% del valor final de temperatura Conexión a 220 Vac. 50-60Hz. Medida interna 60x40x 40 Volumen Lts. 96 Medida Externa 74 x 74 x 57 Accesorios: 2 estantes tipo rejilla regulables (5 posiciones)
C138: ESPECIFICIDADES ITEM 26
C139: =J35 -> - Diapason 128 Hz Hartmann – separador
C141: ESPECIFICIDADES ITEM 27
C142: =J36 -> Tabla larga plástica de inmovilización espinal y traslado para adultos obesos. Medidas aproximadas: 180 X 45 X 1,8 cm. Debe ser traslucida a RX, CT y MRI. Debe estar construida ergonómicamente en HDPE (polietileno de alta densidad, lavable antiestático de alta resistencia) sin costuras ni huecos, impermeable y atoxica. Debe presentar calados p/inmovilizador cervical, pectorales, abdomen y piernas independientes. Multifenestrada con amplios orificios para empuñaduras y orificios para tres cinturones de fijación de rápida liberación. Debe soportar una carga de 180 Kg como mínimo. Debe incluir 3 cinturones inmovilizadores.
C144: ESPECIFICIDADES ITEM 28
C145: =J37 -> Gabinete de Revelado de amplia capacidad interior para manipular las radiografías dentales. Accesibles a través de dos empuñaduras de tela que no permitan el ingreso de luz del exterior y evitar que se velen las placas. Equipos 100 % estancos para evitar el ingreso de luz exterior y deben disponer de una Tapa Acrílica roja con protección UV. Material del gabinete: Acero Inoxidable. Dimensiones aproximadas: Altura 240 mm, Largo 380 mm, Profundidad 255 mm. Peso aproximado 3 kg.
C147: ESPECIFICIDADES ITEM 29
C148: =J38 -> Medidor de glucosa ;Dispositivo de punción; 10 lancetas estériles; Manual del usuario; Guía de inicio; Estuche portátil.
C150: ESPECIFICIDADES ITEM 30
C151: =J39 -> Laringoscopio adulto tipo Mc Intosh fabricado en acero de primera calidad, con 3 ramas curvas (número: 3, 4 y 5). Con alimentación por pilas tipo C. Largo aproximado de 15cm. Con estuche de transporte.
C153: ESPECIFICIDADES ITEM 31
C154: =J40 -> Laringoscopio pediátrico tipo Mc Intosh fabricado en acero de primera calidad, con 3 ramas curvas (número: 0/55mm, 1/85mm y 2/135mm). Con alimentación por pilas tipo C. Largo aproximado de 15cm. Con estuche de transporte.
C156: ESPECIFICIDADES ITEM 32
C157: =J41 -> Lavador de Elisa Especificaciones Técnicas Protocolos de lavado: Hasta 100. Ciclos de lavado: De O a 9. Volumen de dispensado: De 50 hasta 3000 uL. Protección contra colisión de fondo Automático. Volumen residual por hilera <2 uL. Tiempo de inmersión: De O a 300 segundos. Tiempo de agitación: De O a 300 segundos. Opciones múltiples 1x8, 1x12. Medidas de las botellas: 2x2L (Detergente), 1x2L (Desechos), 1x2L (Agua destilada). Fuente de alimentación de CE 100-240V. Temperatura: De 5 a 35 ºC. Humedad: De 15 a 85 %. Dimensiones aproximadas 400 mm (Largo) x 330mm (ancho) x 145mm (Alto). INCLUYE UPS ACORDE AL EQUIPO
C159: ESPECIFICIDADES ITEM 33
C160: =J42 -> Lector de Elisa de Microplaca Pantalla LCD a color, sensible al tacto de 7.8". Cubierta opaca para evitar luz externa. Impresora térmica y opción a impresora externa. Capacidad para almacenar más de 20,000 resultados Múltiples opciones para ajuste de curva. Modos de agitación de velocidad y tiempo variables. Sistema óptico bi-cromático totalmente automático Amplio reporte con información del paciente. Lámpara de alta durabilidad. Software de gestión de datos (opcional). Especificaciones Técnicas: * Data Management Software. * Método de detección Absorbancia. * Microplacas aceptadas 96 y 48 pozos. *Sistema de Medición: Sistema óptico de 8 canales. * Fuente de Luz Lámpara de Halogeno-tunsteno. * Puertos de Conexión 1 x RS232, 2 x USB. * Agitación Modos de agitación de velocidad y tiempo variables. * Ingreso de Datos Mediante Pantalla Táctil. * Pantalla LCD a color. INCLUYE UPS ACORDE AL EQUIPO
C162: ESPECIFICIDADES ITEM 34
C163: =J43 -> Mesa auxiliar rodante de uso Odontologico, con 6 cajones y 1 gabinete con puerta lateral y 4 estantes, de melamina.
C165: ESPECIFICIDADES ITEM 35
C166: =J44 -> NEBULIZADOR: - Capacidad para 1.75mL. - Para Nebulizar aproximado 0.34 mililitros por minuto. - Con sistema monocámara. - Funcionamiento de forma silenciosa. - Niebla regulable - Apagar automaticamente - Aprobado por ANMAT. - Incluir accesorios.
C168: ESPECIFICIDADES ITEM 36
C169: =J45 -> Silla de Ruedas especialmente diseñada para usuarios con sobrepeso o de mayores dimensiones, con asiento extra ancho, barra doble cruzada inferior y estructura reforzada para soportar hasta 200 kg. Estructura plegable de acero inoxidable recubierto de alta resistencia. Apoyabrazos largos fijos, con superficie de apoyo acolchada blanda y apoya pies con plataforma metálica resistente y abatible para una mayor comodidad. Ruedas traseras macizas con la tecnología “anti pinchazo” con aro manual ergonómico y ruedas delanteras multi direccionales.
...

Sheet NP
A1: NOTA DE PEDIDO | J1: N°
A3: JURISDICCIÓN: | D3: 040 - MINISTERIO DE SALUD
A4: SAF: | D4: 011 - DIRECCION PROVINCIAL DE ADMINISTRACION DEL MINISTERIO DE SALUD
A5: UNIDAD EJECUTORA: | D5: 352 - MINISTERIO DE SALUD
A6: DEPENDENCIA SOLICITANTE: | D6: 352 - MINISTERIO DE SALUD
A7: PERIODO UTILIZACIÓN: | D7: DIEZ (10) AÑOS
A8: OBJETO: | D8: ADQUISICION DE UTILES MEDICOS Y EQUIPOS SANITARIOS Y DE LABORATORIO CON DESTINO A HOSPITALES DE LA PROVINCIA
A10: Ítem | B10: Codigo Item | C10: DESCRIPCIÓN | H10: Adjunta Detalle Técnico | I10: Unidad Medida | J10: Precio Unitario Estimado | K10: Cantidad Solicitada
A12: 1 | B12: ='SAF 11'!B10 -> 4.3.3-5080.1 | C12: ='SAF 11'!E10 -> ASPIRADORES DE SECRECION; ALIMENTACION: 12-220 V, TIPO: PORTATIL | H12: SI | I12: ='SAF 11'!F10 -> UNIDAD | J12: ='SAF 11'!H10 -> 70156 | K12: ='SAF 11'!G10 -> 20
A13: 2 | B13: ='SAF 11'!B11 -> 4.3.3-6616.14 | C13: ='SAF 11'!E11 -> AUTOCLAVES ELECTRICOS; TIPO: AUTOMATICO, INDIC. TEMP: DIGITAL, CAPACIDAD: 20 L, ALIMENTACION: 220 V | H13: SI | I13: ='SAF 11'!F11 -> UNIDAD | J13: ='SAF 11'!H11 -> 132500 | K13: ='SAF 11'!G11 -> 1
A14: 3 | B14: ='SAF 11'!B12 -> 4.3.3-6616.14 | C14: ='SAF 11'!E12 -> AUTOCLAVES ELECTRICOS; TIPO: AUTOMATICO, INDIC. TEMP: DIGITAL, CAPACIDAD: 20 L, ALIMENTACION: 220 V | H14: SI | I14: ='SAF 11'!F12 -> UNIDAD | J14: ='SAF 11'!H12 -> 525000 | K14: ='SAF 11'!G12 -> 1
A15: 4 | B15: ='SAF 11'!B13 -> 4.3.3-8300.1 | C15: ='SAF 11'!E13 -> BICICLETAS P/ERGOMETRIA; VOLANTE DE INERCIA: 500 mm, ETAPA DE RESISTENCIA: 150 EN 150 Kgm, VOLANTE: DE INERCIA 500 mm | H15: SI | I15: ='SAF 11'!F13 -> UNIDAD | J15: ='SAF 11'!H13 -> 396807 | K15: ='SAF 11'!G13 -> 3
A16: 5 | B16: ='SAF 11'!B14 -> 4.3.3-5420.6 | C16: ='SAF 11'!E14 -> BOMBAS DE INFUSION; ALIMENTACION: 220 V, LECTURA: DISPLAY GRAFICO, VOLUMEN: 01-9999 ML, CONTRAPRESION: 40 KPA A 120 KPA | H16: SI | I16: ='SAF 11'!F14 -> UNIDAD | J16: ='SAF 11'!H14 -> 316490 | K16: ='SAF 11'!G14 -> 20
A17: 6 | B17: ='SAF 11'!B15 -> 2.9.5-7987.9 | C17: ='SAF 11'!E15 -> CAJAS DE INSTRUMENTAL; MATERIAL: ACERO INOXIDABLE, USO: CIRUGIA, CANTIDAD: 1 | H17: SI | I17: ='SAF 11'!F15 -> UNIDAD | J17: ='SAF 11'!H15 -> 15200 | K17: ='SAF 11'!G15 -> 20
A18: 7 | B18: ='SAF 11'!B16 -> 2.9.5-7987.9 | C18: ='SAF 11'!E16 -> CAJAS DE INSTRUMENTAL; MATERIAL: ACERO INOXIDABLE, USO: CIRUGIA, CANTIDAD: 1 | H18: SI | I18: ='SAF 11'!F16 -> UNIDAD | J18: ='SAF 11'!H16 -> 18000 | K18: ='SAF 11'!G16 -> 20
A19: 8 | B19: ='SAF 11'!B17 -> 2.9.5-7987.1 | C19: ='SAF 11'!E17 -> CAJAS DE INSTRUMENTAL; MATERIAL: ACERO INOXIDABLE, USO: EXAMEN GINECOLOG./INST.DE DIU, CANT.INSTRUMETAL: 10, CANTIDAD: 1 | H19: SI | I19: ='SAF 11'!F17 -> UNIDAD | J19: ='SAF 11'!H17 -> 36100 | K19: ='SAF 11'!G17 -> 7
A20: 9 | B20: ='SAF 11'!B18 -> 4.3.3-1719.48 | C20: ='SAF 11'!E18 -> CAMILLAS; ANCHO: 60 Cm, LARGO: 200 Cm, ALTO: 70 Cm, ARNESES: SIN, TIPO: RODANTE | H20: SI | I20: ='SAF 11'!F18 -> UNIDAD | J20: ='SAF 11'!H18 -> 62710 | K20: ='SAF 11'!G18 -> 20
A21: 10 | B21: ='SAF 11'!B19 -> 4.3.3-1719.27 | C21: ='SAF 11'!E19 -> CAMILLAS; ANCHO: 75 Cm, LARGO: 185 Cm, ALTO: 75 Cm, ARNESES: SIN, TIPO: KINESICA | H21: SI | I21: ='SAF 11'!F19 -> UNIDAD | J21: ='SAF 11'!H19 -> 66300 | K21: ='SAF 11'!G19 -> 3
A22: 11 | B22: ='SAF 11'!B20 -> 4.3.2-6331.12 | C22: ='SAF 11'!E20 -> CARROS P/TRANSP.; SUPERFICIE: 30 X 40 Cm, ALTURA: 120 Cm, MATERIAL: CHAPA METAL PLEGADA, ESTRUCTURA: METALICA, RUEDAS: 2 REFORZADAS- DIAM. 180 mm, ACCESORIO: 2 AGARRADERAS, MATERIAL ESTRUCTURA: METALICA | H22: SI | I22: ='SAF 11'!F20 -> UNIDAD | J22: ='SAF 11'!H20 -> 16756 | K22: ='SAF 11'!G20 -> 14
A23: 12 | B23: ='SAF 11'!B21 -> 4.3.3-5416.1 | C23: ='SAF 11'!E21 -> CARROS USO HOSPITALARIO; TERMINACION: ANTIOXIDANTE, ESTRUCTURA: REFORZADA DE CHAPA ACERO SAE, MEDIDAS: 0,70 X 0,50 X 0,90 M, PARACHOQUE: GOMA, PLANO SUPERIOR: ESTRATIFICADOS CON BARANDAS, CAJONES: CON, DIVISIONES: P/MATERIALES, MASTIL: CON, CONTENEDOR: P/RESIDUOS BIOLOGICOS, ALZADA SUPERIOR: PORTA CARDIODESFIBRILADOR, CANTIDAD DE CAJONES: CON, MATERIAL ESTRUCTURA: REFORZADA DE CHAPA ACERO SAE, DIMENSION: 0,70 X 0,50 X 0,90 M, TIPO: DE PARO | H23: SI | I23: ='SAF 11'!F21 -> UNIDAD | J23: ='SAF 11'!H21 -> 408143 | K23: ='SAF 11'!G21 -> 14
... A48: 37 | B48: ='SAF 11'!B46 -> 2.9.5-2020.1 | C48: ='SAF 11'!E46 -> TAMBORES QUIRURGICOS; MATERIAL: ACERO INOXIDABLE, DIMENSION: 10 X 12 Cm | H48: SI | I48: ='SAF 11'!F46 -> UNIDAD | J48: ='SAF 11'!H46 -> 11000 | K48: ='SAF 11'!G46 -> 20
A50: Costo total estimado: PESOS CINCUENTA MILLONES SETECIENTOS VEINTIOCHO MIL DOSCIENTOS SESENTA Y TRES CON 00/100.- | J50: =SUMPRODUCT(J12:J48,K12:K48) -> 50728263

Sheet APG
A1: EJERCICIO: | D1: 2022 | P1: AUTORIZACION PARA GASTAR
A4: JURISDICCIÓN: | G4: =NP!D3 -> 040 - MINISTERIO DE SALUD
A5: SAF: | G5: =NP!D4 -> 011 - DIRECCION PROVINCIAL DE ADMINISTRACION DEL MINISTERIO DE SALUD
A6: UNIDAD EJECUTORA: | G6: =NP!D5 -> 352 - MINISTERIO DE SALUD
A7: DEPENDENCIA SOLICITANTE: | G7: =NP!D6 -> 352 - MINISTERIO DE SALUD
A8: AUTORIZACIÓN:
A9: Señor Director de Administración o Titular del Servicio Administrativo Financiero:
A10: Autorizo la realización de los trámites correspondientes, a fin de proveer a este Organismo los bienes, servicios o ejecución de obras públicas que se detallan en Nota de Pedido N° XX/2022 , afectando la erogación resultante a los créditos presupuestarios aprobados a favor de esta Unidad Ejecutora, conforme al siguiente detalle:
A12: IMPUTACIÓN PRESUPUESTARIA
A13: CÓDIGO | O13: DENOMINACIÓN DE LA PARTIDA PRESUPUESTARIA | Q13: IMPORTE
A14: PR | B14: SB | C14: PY | D14: AC | E14: OB | F14: UG | G14: FIN | H14: FUN | I14: I | J14: P | K14: P | L14: SubP | M14: M | N14: FF
A15: 1 | D15: 1 | F15: 4901 | G15: 3 | H15: 1 | I15: 4 | J15: 3 | K15: 3 | M15: 1 | N15: 1.1 | O15: EQUIPOS SANITARIOS Y DE LABORATORIO | Q15: =NP!J50 -> 50728263
A38: TOTAL DE PESOS: CINCUENTA MILLONES SETECIENTOS VEINTIOCHO MIL DOSCIENTOS SESENTA Y TRES CON 00/100.- | Q38: =SUM(Q15:Q37) -> 50728263
A40: JUSTIFICACIÓN:
A41: =NP!D8 -> ADQUISICION DE UTILES MEDICOS Y EQUIPOS SANITARIOS Y DE LABORATORIO CON DESTINO A HOSPITALES DE LA PROVINCIA
