Workbook

Sheet SAF 011
A1: 2022
B2: Pedido de Necesidades Trimestrales
A4: JURISDICCION: | C4: 040 - MINISTERIO DE SALUD
A5: SAF N°: | C5: 011 - DIRECCION PROVINCIAL DE ADMINISTRACION - MINISTERIO DE SALUD
A6: EJERCICIO: | C6: 2022
A7: TRIMESTRE: | C7: CUARTO
A9: ID | B9: CODIGO ITEM | C9: RUBRO DE COMPRA | D9: I.P.P. | E9: DESCRIPCION | F9: UNIDAD DE MEDIDA | G9: DIR. LAB. CENTRAL | H9: TOTAL DE LAB CENTRAL | I9: BCO DE SANGRE | J9: TOTAL BANCO DE SANGRE | K9: CANTIDAD TOTAL | L9: PRECIO UNITARIO ESTIMADO | M9: IMPORTE TOTAL ESTIMADO | N9: ESPECIFICACION TECNICA
A10: 1 | B10: 2.9.5-441.470 | C10: PROD. MEDICO/FARMACEUTICOS/LAB. | D10: 2.9.5 | E10: AGUJAS QUIRURGICAS; TIPO: TERUMO 21GX1", ESPECIFICACION: 25/8, UNIDAD VENTA: CAJA X 100, PRESENTACION: CAJA X 100 | F10: CAJA | G10: 500 | H10: =+G10*L10 -> 1502500 | K10: =+G10+I10 -> 500 | L10: 3005 | M10: =+K10*L10 -> 1502500
A11: 2 | B11: 2.9.5-441.471 | C11: PROD. MEDICO/FARMACEUTICOS/LAB. | D11: 2.9.5 | E11: AGUJAS QUIRURGICAS; TIPO: TERUMO 25GX5/8", ESPECIFICACION: 16/5, UNIDAD VENTA: CAJA X 100, PRESENTACION: CAJA X 100 | F11: CAJA | G11: 400 | H11: =+G11*L11 -> 1296800 | K11: =+G11+I11 -> 400 | L11: 3242 | M11: =+K11*L11 -> 1296800
A12: 3 | B12: 2.9.5-470.13 | C12: PROD. MEDICO/FARMACEUTICOS/LAB. | D12: 2.9.5 | E12: ALGODONES; TIPO: HIDROFILADO, CAPACIDAD: 500 GR, PRESENTACION: ENVASE X 500 GR | F12: PAQUETE | G12: 200 | H12: =+G12*L12 -> 172400 | I12: 40 | J12: =+I12*L12 -> 34480 | K12: =+G12+I12 -> 240 | L12: 862 | M12: =+K12*L12 -> 206880 | N12: ALGODONES PLISADO PRE-CORTADO - ENVASE X 500 GR
A13: 4 | B13: 2.9.5-5703.15 | C13: PROD. MEDICO/FARMACEUTICOS/LAB. | D13: 2.9.5 | E13: ANSA; PRESENTACION: UNIDAD, TIPO: PLASTICA DESCARTABLE | F13: BOLSA | G13: 100 | H13: =+G13*L13 -> 47500 | K13: =+G13+I13 -> 100 | L13: 475 | M13: =+K13*L13 -> 47500 | N13: ANSA DESCARTABLE DE PLASTICO CALIBRADA DE 10 ul ESTERIL X 20 UNIDADES Tipo DELTALAB
A14: 5 | B14: 2.9.5-427.131 | C14: PROD.MEDICO/FARMACEUTICOS/LAB | D14: 2.9.5 | E14: APOSITOS; TIPO: HIPOALARGENICO, TAMAÑO: 40 X 40 MM | F14: CAJA | I14: 50 | J14: =+I14*L14 -> 35100 | K14: =+G14+I14 -> 50 | L14: 702 | M14: =+K14*L14 -> 35100 | N14: CAJA X 250 UNID
A15: 6 | B15: 2.9.5-427.74 | C15: PROD. MEDICO/FARMACEUTICOS/LAB. | D15: 2.9.5 | E15: APOSITOS; TIPO: POST EXTRACCION SANGUINEA, TAMAÑO: 2 X 7,5 Cm | F15: CAJA | G15: 250 | H15: =+G15*L15 -> 244250 | K15: =+G15+I15 -> 250 | L15: 977 | M15: =+K15*L15 -> 244250 | N15: APOSITO POST EXTRACCION SANGUNEA 2X7,5 CM CAJA X 250 UNIDADES Tipo BANDERM
A16: 7 | B16: 2.9.5-2505.10 | C16: PROD. MEDICO/FARMACEUTICOS/LAB. | D16: 2.9.5 | E16: BOLSAS COLECTORAS; TIPO: DE ORINA, USO: PEDIATRICO, CAPACIDAD: 100 mL | F16: UNIDAD | G16: 10000 | H16: =+G16*L16 -> 2300000 | K16: =+G16+I16 -> 10000 | L16: 230 | M16: =+K16*L16 -> 2300000 | N16: RECOLECTORES DE ORINA PEDIATRICOS
A17: 8 | B17: 2.9.5-2694.22 | C17: PROD.MEDICO/FARMACEUTICOS/LAB | D17: 2.9.5 | E17: BOLSAS P/TRANSFUSIONES SANGRE; CAPACIDAD: 450 mL, SOLUCIONES: CFD CON ADENINA, TIPO: HEMOTERAPIA | F17: UNIDAD | I17: 1800 | J17: =+I17*L17 -> 2142000 | K17: =+G17+I17 -> 1800 | L17: 1190 | M17: =+K17*L17 -> 2142000 | N17: BOLSAS DE SANGRE TRIPLE KS TIPO GRIFOLS
A18: 9 | B18: 2.9.5-1908.28 | C18: PROD.MEDICO/FARMACEUTICOS/LAB | D18: 2.9.5 | E18: CEPILLOS P/LABORATORIO; TIPO: LIMPIEZA DE TUBOS, MATERIAL: CERDA, TAMAÑO: DIAM. 9 mm | F18: UNIDAD | I18: 10 | J18: =+I18*L18 -> 1250 | K18: =+G18+I18 -> 10 | L18: 125 | M18: =+K18*L18 -> 1250 | N18: CEPILLO LIMPIA PIPETA DE CERDA NATURAL
A19: 10 | B19: 2.9.5-4047.6 | C19: PROD. MEDICO/FARMACEUTICOS/LAB. | D19: 2.9.5 | E19: CRIOVIALES; MATERIAL: POLIPROPILENO, VOLUMEN: 5 mL | F19: UNIDAD | G19: 5000 | H19: =+G19*L19 -> 332000 | K19: =+G19+I19 -> 5000 | L19: 66.4 | M19: =+K19*L19 -> 332000 | N19: CRIOTUBO CON TAPA A ROSCA ESTERIL 5 ML
A20: 11 | B20: 2.9.5-5410.11 | C20: PROD. MEDICO/FARMACEUTICOS/LAB. | D20: 2.9.5 | E20: CUBETAS DE REACCION; MATERIAL: PLASTICO, CELDAS: 500 C/AGITADOR, USO: COAGULOMETRO | F20: CAJA | G20: 20 | H20: =+G20*L20 -> 357360 | K20: =+G20+I20 -> 20 | L20: 17868 | M20: =+K20*L20 -> 357360 | N20: CUBETAS SERIE X 500 UN PARA COAGULOMETRO COATRON Tipo TECO GMBH
A21: 12 | B21: 2.9.5-5410.11 | C21: PROD. MEDICO/FARMACEUTICOS/LAB. | D21: 2.9.5 | E21: CUBETAS DE REACCION; MATERIAL: PLASTICO, CELDAS: 500 C/AGITADOR, USO: COAGULOMETRO | F21: CAJA | G21: 20 | H21: =+G21*L21 -> 640360 | K21: =+G21+I21 -> 20 | L21: 32018 | M21: =+K21*L21 -> 640360 | N21: CUBETA PARA FIBRINTIMER x 500 UN. Tipo WIENER
A22: 13 | B22: 2.9.5-2557.32 | C22: PROD. MEDICO/FARMACEUTICOS/LAB. | D22: 2.9.5 | E22: CUBREOBJETOS; MATERIAL: VIDRIO, DIMENSION: 20 X 20 mm, PRESENTACION: ENVASE X 200 UN | F22: CAJA | G22: 400 | H22: =+G22*L22 -> 150000 | K22: =+G22+I22 -> 400 | L22: 375 | M22: =+K22*L22 -> 150000
A23: 14 | B23: 2.9.5-2160.1 | C23: PROD.MEDICO/FARMACEUTICOS/LAB | D23: 2.9.5 | E23: DESCARTADORES DE AGUJAS; BOCA: 1, CAPACIDAD: 500 AGUJAS, MODELO: 500, MODELO EQUIPO: 500, SISTEMA DE CIERRE: 500 | F23: UNIDAD | I23: 200 | J23: =+I23*L23 -> 39000 | K23: =+G23+I23 -> 200 | L23: 195 | M23: =+K23*L23 -> 39000
A24: 15 | B24: 2.9.2-675.161 | C24: LIBRERIA,PAP. Y UTILES OFICINA | D24: 2.3.4 | E24: ETIQUETAS AUTOADHESIVAS; MEDIDA: 80 X 25 mm, PRESENTACION: ROLLO X 380 GR, PAPEL BASE: AUTOADHESIVO | F24: PACK | G24: 10 | H24: =+G24*L24 -> 23080 | K24: =+G24+I24 -> 10 | L24: 2308 | M24: =+K24*L24 -> 23080 | N24: ETIQUETAS TERMICO PARA IMPRESORA ZEBRA 80X25 MM X 12 ROLLOS
A25: 16 | B25: 2.9.5-6877.16 | C25: PROD. MEDICO/FARMACEUTICOS/LAB. | D25: 2.9.5 | E25: FUENTES DE LUZ; USO: ILUMINADOR DE MICROSCOPIO, POTENCIA: 20 W, LAMPARA: LED | F25: UNIDAD | G25: 50 | H25: =+G25*L25 -> 110350 | K25: =+G25+I25 -> 50 | L25: 2207 | M25: =+K25*L25 -> 110350 | N25: LAMPARA PARA MICROSCOPIO 6V 20 W
A26: 17 | B26: 2.9.5-3017.27 | C26: PROD. MEDICO/FARMACEUTICOS/LAB. | D26: 2.9.5 | E26: GRADILLAS P/LABORATORIO; TAMAÑO TUBO: 15 X 2 Cm, CANTIDAD DE TUBOS: 36, MATERIAL: ALAMBRE REV.EN RESINA ANTIAD., MEDIDA TUBO: 15 X 2 Cm, CANT. DE ELEMENTOS: 36, MEDIDA: 15 X 2 Cm | F26: UNIDAD | G26: 40 | H26: =+G26*L26 -> 133440 | K26: =+G26+I26 -> 40 | L26: 3336 | M26: =+K26*L26 -> 133440 | N26: GRADILLA ALAMBRE PLASTIFICADO PARA 36 TUBOS FALCON de25 mm DIAMETRO Tipo ARGA
A27: 18 | B27: 2.9.5-3017.45 | C27: PROD. MEDICO/FARMACEUTICOS/LAB. | D27: 2.9.5 | E27: GRADILLAS P/LABORATORIO; TAMAÑO TUBO: 25 mm, CANTIDAD DE TUBOS: 24, MATERIAL: ALAMBRE PLASTIFICADO, MEDIDA TUBO: 25 mm, CANT. DE ELEMENTOS: 24, MEDIDA: 25 mm | F27: UNIDAD | G27: 40 | H27: =+G27*L27 -> 108160 | K27: =+G27+I27 -> 40 | L27: 2704 | M27: =+K27*L27 -> 108160 | N27: GRADILLA ALAMBRE PLASTIFICADO PARA 24 TUBOS FALCON de 25 mm DIAMETRO Tipo ARGA
A28: 19 | B28: 2.9.5-3017.36 | C28: PROD. MEDICO/FARMACEUTICOS/LAB. | D28: 2.9.5 | E28: GRADILLAS P/LABORATORIO; TAMAÑO TUBO: DIAM. EXT. 15 mm, CANTIDAD DE TUBOS: 48, MATERIAL: POLIPROPILENO, MEDIDA TUBO: DIAM. EXT. 15 mm, CANT. DE ELEMENTOS: 48, MEDIDA: DIAM. EXT. 15 mm | F28: UNIDAD | G28: 40 | H28: =+G28*L28 -> 169720 | K28: =+G28+I28 -> 40 | L28: 4243 | M28: =+K28*L28 -> 169720 | N28: GRADILLA ALAMBRE PLASTIFICADO PARA 48 TUBOS DE KAHN 1,6x1,6 cmTipo ARGA
A29: 20 | B29: 2.9.5-1909.77 | C29: PROD. MEDICO/FARMACEUTICOS/LAB. | D29: 2.9.5 | E29: GUANTES USO MEDICINAL; TIPO: DESCARTABLE, TAMAÑO: CHICO, MATERIAL: LATEX, PRESENTACION: ENVASE X 100 UN | F29: CAJA | G29: 800 | H29: =+G29*L29 -> 472000 | I29: 50 | J29: =+I29*L29 -> 29500 | K29: =+G29+I29 -> 850 | L29: 590 | M29: =+K29*L29 -> 501500 | N29: GUANTES DE LATEX TALLE "S" (CHICO) CAJA X 100 UNIDADES Tipo SRITRANG
A30: 21 | B30: 2.9.5-1909.81 | C30: PROD.MEDICO/FARMACEUTICOS/LAB | D30: 2.9.5 | E30: GUANTES USO MEDICINAL; TIPO: DESCARTABLE, TAMAÑO: GRANDE, MATERIAL: LATEX, PRESENTACION: ENVASE X 100 UNID. | F30: CAJA | I30: 50 | J30: =+I30*L30 -> 29500 | K30: =+G30+I30 -> 50 | L30: 590 | M30: =+K30*L30 -> 29500 | N30: GUANTES USO MEDICINAL; TIPO: EXAMINACION , TAMAÑO: GRANDE, MATERIAL: LATEX, PRESENTACION: ENVASE X 100 UN
A31: 22 | B31: 2.9.5-1909.87 | C31: PROD.MEDICO/FARMACEUTICOS/LAB | D31: 2.9.5 | E31: GUANTES USO MEDICINAL; TIPO: DESCARTABLE, TAMAÑO: MEDIANO, MATERIAL: LATEX, PRESENTACION: ENVASE X 100 UNID. | F31: CAJA | G31: 800 | H31: =+G31*L31 -> 472000 | I31: 50 | J31: =+I31*L31 -> 29500 | K31: =+G31+I31 -> 850 | L31: 590 | M31: =+K31*L31 -> 501500 | N31: GUANTES USO MEDICINAL; TIPO: EXAMINACION , TAMAÑO: MEDIANO, MATERIAL: LATEX, PRESENTACION: ENVASE X 100 UN
A32: 23 | B32: 2.9.5-1909.96 | C32: PROD. MEDICO/FARMACEUTICOS/LAB. | D32: 2.9.5 | E32: GUANTES USO MEDICINAL; TIPO: MANOPLA, TAMAÑO: MEDIANO, MATERIAL: POLIETILENO, PRESENTACION: ENVASE X 100 | F32: BOLSA | G32: 500 | H32: =+G32*L32 -> 1025000 | K32: =+G32+I32 -> 500 | L32: 2050 | M32: =+K32*L32 -> 1025000 | N32: MANOPLAS DE POLIETILENO x 100 U Tipo NP
A33: 24 | B33: 2.9.5-1909.84 | C33: PROD. MEDICO/FARMACEUTICOS/LAB. | D33: 2.9.5 | E33: GUANTES USO MEDICINAL; TIPO: P/QUIMICOS, TAMAÑO: CHICO, MATERIAL: NITRILO, PRESENTACION: ENVASE X 100 UN | F33: CAJA | G33: 400 | H33: =+G33*L33 -> 551200 | K33: =+G33+I33 -> 400 | L33: 1378 | M33: =+K33*L33 -> 551200 | N33: GUANTES DE NITRILO SIN POLVO TALLE "S" (CHICO) CAJAX100 UNIDADES Tipo TOP GLOVE
A34: 25 | B34: 2.9.5-1909.82 | C34: PROD. MEDICO/FARMACEUTICOS/LAB. | D34: 2.9.5 | E34: GUANTES USO MEDICINAL; TIPO: P/QUIMICOS, TAMAÑO: GRANDE, MATERIAL: NITRILO, PRESENTACION: ENVASE X 100 UN | F34: CAJA | G34: 50 | H34: =+G34*L34 -> 68900 | K34: =+G34+I34 -> 50 | L34: 1378 | M34: =+K34*L34 -> 68900 | N34: GUANTES DE NITRILO SIN POLVO TALLE "L" (GRANDE) CAJAX100 UNIDADES Tipo TOP GLOVE
A35: 26 | B35: 2.9.5-1909.83 | C35: PROD. MEDICO/FARMACEUTICOS/LAB. | D35: 2.9.5 | E35: GUANTES USO MEDICINAL; TIPO: P/QUIMICOS, TAMAÑO: MEDIANO, MATERIAL: NITRILO, PRESENTACION: ENVASE X 100 UN | F35: CAJA | G35: 500 | H35: =+G35*L35 -> 689000 | K35: =+G35+I35 -> 500 | L35: 1378 | M35: =+K35*L35 -> 689000 | N35: GUANTES DE NITRILO SIN POLVO TALLE "M" (MEDIANO) CAJAX100 UNIDADES Tipo TOP GLOVE
A36: 27 | B36: 2.9.5-2366.2 | C36: PROD. MEDICO/FARMACEUTICOS/LAB. | D36: 2.9.5 | E36: HISOPOS; MATERIAL DE EXTREMOS: ALGODON, PRESENTACION: CAJA X 100 | F36: BOLSA | G36: 400 | H36: =+G36*L36 -> 110400 | K36: =+G36+I36 -> 400 | L36: 276 | M36: =+K36*L36 -> 110400 | N36: HISOPO DE ALGODÓN BOLSAX 100 UNIDADES
A37: 28 | B37: 2.9.5-8799.12 | C37: PROD. MEDICO/FARMACEUTICOS/LAB. | D37: 2.9.5 | E37: JERINGA; MATERIAL: PLASTICO, CAPACIDAD: 10 CM3, ACCESORIOS: SIN, TIPO: ESTERIL, ACCESORIO: SIN | F37: CAJA | G37: 300 | H37: =+G37*L37 -> 608100 | K37: =+G37+I37 -> 300 | L37: 2027 | M37: =+K37*L37 -> 608100 | N37: JERINGAS 10 ML X 100 UNIDADES Tipo BREMEN
A38: 29 | B38: 2.9.5-8799.8 | C38: PROD. MEDICO/FARMACEUTICOS/LAB. | D38: 2.9.5 | E38: JERINGA; MATERIAL: PLASTICO, CAPACIDAD: 3 mL, ACCESORIOS: SIN, TIPO: NICHIRYO, ACCESORIO: SIN | F38: CAJA | G38: 500 | H38: =+G38*L38 -> 702500 | K38: =+G38+I38 -> 500 | L38: 1405 | M38: =+K38*L38 -> 702500 | N38: JERINGAS 3 ML X 100 UNIDADES Tipo BREMEN
A39: 30 | B39: 2.9.5-8799.11 | C39: PROD. MEDICO/FARMACEUTICOS/LAB. | D39: 2.9.5 | E39: JERINGA; MATERIAL: PLASTICO, CAPACIDAD: 5 CM3, ACCESORIOS: SIN, TIPO: ESTERIL, ACCESORIO: SIN | F39: CAJA | G39: 800 | H39: =+G39*L39 -> 1104000 | K39: =+G39+I39 -> 800 | L39: 1380 | M39: =+K39*L39 -> 1104000 | N39: JERINGAS 5 ML X 100 UNIDADES Tipo BREMEN
A40: 31 | B40: 2.9.5-7870.15 | C40: PROD. MEDICO/FARMACEUTICOS/LAB. | D40: 2.9.3 | E40: LAMPARAS P/AUTOANALIZADOR; TIPO: HALOGENA, TENSION: 6 V, POTENCIA: 10 W | F40: UNIDAD | G40: 15 | H40: =+G40*L40 -> 69000 | K40: =+G40+I40 -> 15 | L40: 4600 | M40: =+K40*L40 -> 69000 | N40: LAMPARA PARA ESPECTROFOTOMETRO MINDRAY BA 88A CON ZOCALO
A41: 32 | B41: 2.9.5-7870.15 | C41: PROD. MEDICO/FARMACEUTICOS/LAB. | D41: 2.9.3 | E41: LAMPARAS P/AUTOANALIZADOR; TIPO: HALOGENA, TENSION: 6 V, POTENCIA: 10 W | F41: UNIDAD | G41: 30 | H41: =+G41*L41 -> 77250 | K41: =+G41+I41 -> 30 | L41: 2575 | M41: =+K41*L41 -> 77250 | N41: LAMPARA PARA ESPECTROFOTOMETRO METROLAB 1600 SIN ZOCALO 6V 10 W
A42: 33 | B42: 2.9.5-7870.16 | C42: PROD. MEDICO/FARMACEUTICOS/LAB. | D42: 2.9.3 | E42: LAMPARAS P/AUTOANALIZADOR; TIPO: HALOGENA, TENSION: 6 V, POTENCIA: 20 W | F42: UNIDAD | G42: 5 | H42: =+G42*L42 -> 19000 | K42: =+G42+I42 -> 5 | L42: 3800 | M42: =+K42*L42 -> 19000 | N42: LAMPARA PARA ESPECTROFOTOMETRO MINDRAY BS-200 E CON ZOCALO
A43: 34 | B43: 2.9.5-2516.3 | C43: PROD. MEDICO/FARMACEUTICOS/LAB. | D43: 2.9.3 | E43: LAZOS P/EXTRACCION; MATERIAL: LATEX, DIAMETRO: PLANO 2 X 35 Cm | F43: CAJA | G43: 100 | H43: =+G43*L43 -> 42700 | K43: =+G43+I43 -> 100 | L43: 427 | M43: =+K43*L43 -> 42700 | N43: LAZO DE LATEX PARA EXTRACCION DE SANGRE CAJA X 10 U TIPO DELTALAB
... A47: 38 | B47: 2.9.5-6479.34 | C47: PROD. MEDICO/FARMACEUTICOS/LAB. | D47: 2.9.5 | E47: MICROPIPETAS AUTOMATICAS; TIPO: MONOCANAL, ESCALA: 100 A 10000 µL, VOLUMEN: 1000 µL, SENSIBILIDAD: 1 µL | F47: UNIDAD | G47: 20 | H47: =+G47*L47 -> 3034680 | K47: =+G47+I47 -> 20 | L47: 151734 | M47: =+K47*L47 -> 3034680 | N47: PIPETA AUTOMATICA VOLUMEN REGULABLE 100 A 1000 MICROLITROS Tipo SOCOREX
A48: 39 | B48: 2.9.5-2578.17 | C48: PROD.MEDICO/FARMACEUTICOS/LAB | D48: 2.9.5 | E48: MICROPIPETAS REGULABLES; CAPACIDAD: 100 - 1000 µL, DIVISIONES: CADA 5 µL, MATERIAL: PLASTICO | F48: CAJA | I48: 2 | J48: =+I48*L48 -> 100700 | K48: =+G48+I48 -> 2 | L48: 50350 | M48: =+K48*L48 -> 100700 | N48: CAJA X 100 UNIDADES
A49: 40 | B49: 2.9.5-2578.16 | C49: PROD.MEDICO/FARMACEUTICOS/LAB | D49: 2.9.5 | E49: MICROPIPETAS REGULABLES; CAPACIDAD: 10-100 µL, DIVISIONES: CADA 1 µL, MATERIAL: PLASTICO | F49: CAJA | I49: 2 | J49: =+I49*L49 -> 100700 | K49: =+G49+I49 -> 2 | L49: 50350 | M49: =+K49*L49 -> 100700 | N49: CAJA X 100 UNIDADES
A50: 41 | B50: 2.9.5-4633.11 | C50: PROD. MEDICO/FARMACEUTICOS/LAB. | D50: 2.9.5 | E50: MICROTUBOS P/LABORATORIO; MATERIAL: POLIPROPILENO, PRESENTACION: ENVASE X 1000 UN, MEDIDA: 1.5 mL, COLOR: TRANSPARENTE, TIPO: C/TAPA, LIBRE DNASAS/RNASAS | F50: BOLSA | G50: 80 | H50: =+G50*L50 -> 471200 | K50: =+G50+I50 -> 80 | L50: 5890 | M50: =+K50*L50 -> 471200 | N50: MICROTUBO EPPENDORF ESTERIL 1,5 ML (BOLSA X1000 UNIDADES) Tipo APTACA
A51: 42 | B51: 2.9.5-4633.47 | C51: PROD. MEDICO/FARMACEUTICOS/LAB. | D51: 2.9.5 | E51: MICROTUBOS P/LABORATORIO; MATERIAL: POLIPROPILENO, PRESENTACION: ENVASE X 1000 UN, MEDIDA: 2 mL, TIPO: EPPENDORF | F51: BOLSA | G51: 100 | H51: =+G51*L51 -> 630000 | K51: =+G51+I51 -> 100 | L51: 6300 | M51: =+K51*L51 -> 630000 | N51: MICROTUBO EPPENDORF ESTERIL 2 ML (BOLSA X1000 UNIDADES) Tipo APTACA
A52: 43 | B52: 2.9.5-2553.6 | C52: PROD. MEDICO/FARMACEUTICOS/LAB. | D52: 2.3.4 | E52: PAPEL P/ELECTROCARDIOGRAM.; MEDIDA: 50 MM X 30 M | F52: UNIDAD | G52: 300 | H52: =+G52*L52 -> 76200 | K52: =+G52+I52 -> 300 | L52: 254 | M52: =+K52*L52 -> 76200 | N52: PAPEL TERMOSENSIBLE PARA CONTADOR HEMATOLOGICO COUNTER W19 50 MM
A53: 44 | B53: 2.9.5-2553.6 | C53: PROD. MEDICO/FARMACEUTICOS/LAB. | D53: 2.3.4 | E53: PAPEL P/ELECTROCARDIOGRAM.; MEDIDA: 50 MM X 30 M | F53: UNIDAD | G53: 300 | H53: =+G53*L53 -> 106800 | K53: =+G53+I53 -> 300 | L53: 356 | M53: =+K53*L53 -> 106800 | N53: PAPEL TERMOSENSIBLE PARA METROLAB DR 1600 57 MM
A54: 45 | B54: 2.9.5-2553.6 | C54: PROD. MEDICO/FARMACEUTICOS/LAB. | D54: 2.3.4 | E54: PAPEL P/ELECTROCARDIOGRAM.; MEDIDA: 50 MM X 30 M | F54: UNIDAD | G54: 200 | H54: =+G54*L54 -> 82000 | K54: =+G54+I54 -> 200 | L54: 410 | M54: =+K54*L54 -> 82000 | N54: PAPEL TERMOSENSIBLE PARA SYSMEX XP 300 56 MM
A55: 46 | B55: 2.9.5-2553.6 | C55: PROD. MEDICO/FARMACEUTICOS/LAB. | D55: 2.3.4 | E55: PAPEL P/ELECTROCARDIOGRAM.; MEDIDA: 50 MM X 30 M | F55: UNIDAD | G55: 200 | H55: =+G55*L55 -> 102000 | K55: =+G55+I55 -> 200 | L55: 510 | M55: =+K55*L55 -> 102000 | N55: PAPEL TERMOSENSIBLE PARA CONTADOR MINDRAY 50 MM
A56: 47 | B56: 2.9.5-2592.2 | C56: PROD. MEDICO/FARMACEUTICOS/LAB. | D56: 2.9.5 | E56: PIPETAS GRADUADAS; MATERIAL: PLASTICO, CAPACIDAD: 3 mL, MEDIDA MINIMA: SIN VALOR, TIPO: PASTEUR DESCARTABLE | F56: CAJA | G56: 200 | H56: =+G56*L56 -> 896800 | K56: =+G56+I56 -> 200 | L56: 4484 | M56: =+K56*L56 -> 896800 | N56: PIPETA PLASTICA DESCARTABLE PASTEUR CAJA X 500 UNIDADES
A57: 48 | B57: 2.9.5-2782.1 | C57: PROD. MEDICO/FARMACEUTICOS/LAB. | D57: 2.9.5 | E57: PISETAS DE LABORATORIO; CAPACIDAD: 500 mL, MATERIAL: PLASTICO | F57: UNIDAD | G57: 50 | H57: =+G57*L57 -> 78750 | K57: =+G57+I57 -> 50 | L57: 1575 | M57: =+K57*L57 -> 78750
A58: 49 | B58: 2.9.5-6786.6 | C58: PROD. MEDICO/FARMACEUTICOS/LAB. | D58: 2.9.5 | E58: PLACAS DE TOQUE; MATERIAL: VIDRIO, LARGO: 8 Cm, ANCHO: 6 Cm, ESPESOR: 5 mm, USO: DETERMINACION VDRL | F58: UNIDAD | G58: 50 | H58: =+G58*L58 -> 225000 | K58: =+G58+I58 -> 50 | L58: 4500 | M58: =+K58*L58 -> 225000 | N58: PLACA DE VIDRIO VDRL 12 POCILLOS
A59: 50 | B59: 2.9.5-6786.6 | C59: PROD. MEDICO/FARMACEUTICOS/LAB. | D59: 2.9.5 | E59: PLACAS DE TOQUE; MATERIAL: VIDRIO, LARGO: 8 Cm, ANCHO: 6 Cm, ESPESOR: 5 mm, USO: DETERMINACION VDRL | F59: UNIDAD | G59: 50 | H59: =+G59*L59 -> 225000 | K59: =+G59+I59 -> 50 | L59: 4500 | M59: =+K59*L59 -> 225000 | N59: PLACA DE VIDRIO VDRL 6 POCILLOS
A60: 51 | B60: 2.9.5-6786.6 | C60: PROD.MEDICO/FARMACEUTICOS/LAB | D60: 2.9.5 | E60: PLACAS DE TOQUE; MATERIAL: VIDRIO, LARGO: 8 Cm, ANCHO: 6 Cm, ESPESOR: 5 mm, USO: DETERMINACION VDRL | F60: UNIDAD | I60: 5 | J60: =+I60*L60 -> 6100 | K60: =+G60+I60 -> 5 | L60: 1220 | M60: =+K60*L60 -> 6100 | N60: PLACA PARA VDRL CON POCILLO PROFUNDO 12 HOYOS
A61: 52 | B61: 2.9.5-2583.29 | C61: PROD. MEDICO/FARMACEUTICOS/LAB. | D61: 2.9.5 | E61: PLACAS POLICUBETA P/LAB.; DIVISIONES: 96; MATERIAL: PLACAS DE PLÁSTICO DESECHABLES Y PEINES DE PUNTA DE POLIPROPILENO KIN FISHER FLEX; MARCA: THERMOFISHER | F61: UNIDAD | G61: 1 | H61: =+G61*L61 -> 280000 | K61: =+G61+I61 -> 1 | L61: 280000 | M61: =+K61*L61 -> 280000 | N61: KingFisher 96 tip comb for deep-well magnets, 10x10 pcs/box (for Flex, Apex ande Presto)
A62: 53 | B62: 2.9.5-2583.31 | C62: PROD. MEDICO/FARMACEUTICOS/LAB. | D62: 2.9.5 | E62: PLACAS POLICUBETA P/LAB.; DIVISIONES: 96; MATERIAL: PLÁSTICO; ESTERILIZADA: NO; FONDO TIPO: TM PROFUNDO 200 UL KING FISHER FLEX; MARCA: THERMOFISHER | F62: UNIDAD | G62: 2 | H62: =+G62*L62 -> 165200 | K62: =+G62+I62 -> 2 | L62: 82600 | M62: =+K62*L62 -> 165200 | N62: KingFisher TM Plastic for standard and PCR format
A63: 54 | B63: 2.9.5-2583.30 | C63: PROD. MEDICO/FARMACEUTICOS/LAB. | D63: 2.9.5 | E63: PLACAS POLICUBETA P/LAB.; DIVISIONES: 96; MATERIAL: POLIPROPILENO; ESTERILIZADA: NO; FONDO: EN V; FONDO TIPO: PROFUNDO KING FISHER FLEX; MARCA: THERMOFISHER | F63: UNIDAD | G63: 7 | H63: =+G63*L63 -> 1015000 | K63: =+G63+I63 -> 7 | L63: 145000 | M63: =+K63*L63 -> 1015000 | N63: KingFisher Plastic Consumables for SARS-COV2 Testing
A64: 55 | B64: 2.9.5-5773.1 | C64: PROD. MEDICO/FARMACEUTICOS/LAB. | D64: 2.9.5 | E64: PORTAOBJETOS P/LABORATORIO; PRESENTACION: CAJA X 50 UN, MEDIDA: 2,5 X 7,5 Cm, USO: LABORATORIO, MATERIAL: VIDRIO | F64: CAJA | G64: 500 | H64: =+G64*L64 -> 132500 | K64: =+G64+I64 -> 500 | L64: 265 | M64: =+K64*L64 -> 132500 | N64: PORTAOBJETOS X 50 UNIDADES Tipo DELTALAB
A65: 56 | B65: 2.9.6-8875.293 | C65: REPUESTOS | D65: 2.9.5 | E65: REP. Y ACC P/ EQUIPO MEDICO; USO: PARA EQUIPO DE AFERESIS, MARCA DE EQUIPO: GRIFOLS, ELEMENTO: KITS PARA PLAQUETOFERESIS CON FILTRO CAJA X 8 UNID; EQUIPO: HAEMONETICS CS+ | F65: CAJA | I65: 48 | J65: =+I65*L65 -> 1968912 | K65: =+G65+I65 -> 48 | L65: 41019 | M65: =+K65*L65 -> 1968912 | N65: KITS PARA PLAQUETOFERESIS CON FILTRO
A66: 57 | B66: 2.9.6-8875.294 | C66: REPUESTOS | D66: 2.9.5 | E66: REP. Y ACC P/ EQUIPO MEDICO; USO: PARA EQUIPO DE AFERESIS, MARCA DE EQUIPO: GRIFOLS, ELEMENTO: KITS PARA PLASMAFERESIS CON FILTRO CAJA X 8UNID, EQUIPO: HAEMONETIC CS+ | F66: CAJA | I66: 24 | J66: =+I66*L66 -> 842160 | K66: =+G66+I66 -> 24 | L66: 35090 | M66: =+K66*L66 -> 842160 | N66: KIT PLASMAFERESIS
A67: 58 | B67: 2.9.6-8875.295 | C67: REPUESTOS | D67: 2.9.5 | E67: REP. Y ACC. P/ EQUIPO MEDICO, USO: BAÑO TERMOSTATIZADO PARA TARJETAS DE INMUNOHEMATOLOGIA, MARCA EQUIPO: GRIFOLS, ELEMENTO:TARJETA DE GEL ABO RH 2D, EQUIPO: CENTRIFUGA | F67: UNIDAD | I67: 1500 | J67: =+I67*L67 -> 885000 | K67: =+G67+I67 -> 1500 | L67: 590 | M67: =+K67*L67 -> 885000 | N67: TARJETA DE GEL ABO RH 2d
A68: 59 | B68: 2.9.6-8875.292 | C68: REPUESTOS | D68: 2.9.5 | E68: REP. Y ACC. P/ EQUIPO MEDICO; USO: FRACCIONADOR AUTOMATICO HEMODERIVADOS, MARCA EQUIPO: GRIFOLS, ELEMENTO: CONEXIÓN POR RADIO FRECUENCIA Y GR, MODELO DE EQUIPO: FRACTIOMATIC PLUS 2 | F68: UNIDAD | I68: 900 | J68: =+I68*L68 -> 3555000 | K68: =+G68+I68 -> 900 | L68: 3950 | M68: =+K68*L68 -> 3555000 | N68: CONEXIÓN POR RADIO Y FRECUENCIA Y GR PARA FRACCIONADOR AUTOMATICO DE HEMODERIVADOS. TIPO FRACTIOMATIC PLUS. 2 GRIFOLS
A69: 60 | B69: 2.9.6-6345.64 | C69: REPUESTOS | D69: 2.9.5 | E69: REP. Y ACC. P/AUTOANALIZADOR; REPUESTO: CUBETA DE REACCION, MARCA EQUIPO: METROLAB, MODELO EQUIPO: 2300 | F69: CAJA | G69: 50 | H69: =+G69*L69 -> 2031350 | K69: =+G69+I69 -> 50 | L69: 40627 | M69: =+K69*L69 -> 2031350 | N69: CUBETAS CURE CAJA X 1200 UNIDADES PARA AUTOANALIZADOR CM250 Tipo WIENER
A70: 61 | B70: 2.9.6-6345.64 | C70: REPUESTOS | D70: 2.9.5 | E70: REP. Y ACC. P/AUTOANALIZADOR; REPUESTO: CUBETA DE REACCION, MARCA EQUIPO: METROLAB, MODELO EQUIPO: 2300 | F70: UNIDAD | G70: 100 | H70: =+G70*L70 -> 400000 | K70: =+G70+I70 -> 100 | L70: 4000 | M70: =+K70*L70 -> 400000 | N70: CUBETAS DE REACCION PARA AUTOANALIZADOR DE QUIMICA INCCA
A71: 62 | B71: 2.9.6-8875.101 | C71: REPUESTOS | D71: 2.9.6 | E71: REP. Y ACC. P/EQUIPO MEDICO; USO: EXTRACCION DE SANGRE, MARCA EQUIPO: UNIVERSAL, ELEMENTO: APOYABRAZOS, MODELO EQUIPO: UNIVERSAL | F71: UNIDAD | G71: 10 | H71: =+G71*L71 -> 84190 | K71: =+G71+I71 -> 10 | L71: 8419 | M71: =+K71*L71 -> 84190 | N71: APOYA BRAZO PARA EXTRACCION DE SANGRE X UNIDAD
A72: 63 | B72: 2.9.5-931.3 | C72: PROD.MEDICO/FARMACEUTICOS/LAB | D72: 2.9.5 | E72: TELAS ADHESIVAS; ANCHO: 5.00 Cm, LONG.DE CUERPO: 9 M, TIPO: HIPOALERGENICA | F72: CAJA | I72: 5 | J72: =+I72*L72 -> 8305 | K72: =+G72+I72 -> 5 | L72: 1661 | M72: =+K72*L72 -> 8305 | N72: MICROSPORE - CAJA X 8 UNIDADES
A73: 64 | B73: 2.9.5-3492.42 | C73: PROD. MEDICO/FARMACEUTICOS/LAB. | D73: 2.9.5 | E73: TIP; TIPO: AMARILLO, PRESENTACION: BOLSA X 1000 UN, CAP. USO: 1 A 200 µL, CAPACIDAD: 1 A 200 µL | F73: BOLSA | G73: 400 | H73: =+G73*L73 -> 1033600 | K73: =+G73+I73 -> 400 | L73: 2584 | M73: =+K73*L73 -> 1033600 | N73: TIPS AMARILLOS SIN CORONA 5-200 ULBOLSA X 1000 UNIDADES
A74: 65 | B74: 2.9.5-3492.42 | C74: PROD. MEDICO/FARMACEUTICOS/LAB. | D74: 2.9.5 | E74: TIP; TIPO: AMARILLO, PRESENTACION: BOLSA X 1000 UN, CAP. USO: 1 A 200 µL, CAPACIDAD: 1 A 200 µL | F74: BOLSA | G74: 100 | H74: =+G74*L74 -> 216600 | K74: =+G74+I74 -> 100 | L74: 2166 | M74: =+K74*L74 -> 216600 | N74: TIPS AMARILLOS CON CORONA 5-200 UL BOLSA X 1000 UNIDADES
A75: 66 | B75: 2.9.5-3492.97 | C75: PROD. MEDICO/FARMACEUTICOS/LAB. | D75: 2.9.5 | E75: TIP; TIPO: P/PIPETA AUTOMATICA, PRESENTACION: BOLSA X 1000, CAP. USO: 100 A 1000 µL, CAPACIDAD: 100 A 1000 µL | F75: BOLSA | G75: 200 | H75: =+G75*L75 -> 737200 | K75: =+G75+I75 -> 200 | L75: 3686 | M75: =+K75*L75 -> 737200 | N75: TIPS AZULES CON CORONA 100-1000 UL BOLSA X 1000 UNIDADES
A76: 67 | B76: 2.9.5-3492.97 | C76: PROD. MEDICO/FARMACEUTICOS/LAB. | D76: 2.9.5 | E76: TIP; TIPO: P/PIPETA AUTOMATICA, PRESENTACION: BOLSA X 1000, CAP. USO: 100 A 1000 µL, CAPACIDAD: 100 A 1000 µL | F76: BOLSA | G76: 100 | H76: =+G76*L76 -> 554800 | K76: =+G76+I76 -> 100 | L76: 5548 | M76: =+K76*L76 -> 554800 | N76: TIPS AZULES SIN CORONA 100-1000 UL PP AUTOCLAVABLE BOLSA X 1000 UNIDADES
A77: 68 | B77: 2.9.5-3492.343 | C77: PROD.MEDICO/FARMACEUTICOS/LAB | D77: 2.9.5 | E77: TIP; TIPO: TIPS AMARILLO CON CORONA, PRESENTACION: X 1000 UNID., CAPACIDAD:0,2 ML | F77: BOLSA | I77: 2 | J77: =+I77*L77 -> 3080 | K77: =+G77+I77 -> 2 | L77: 1540 | M77: =+K77*L77 -> 3080
A78: 69 | B78: 2.9.5-3492.341 | C78: PROD.MEDICO/FARMACEUTICOS/LAB | D78: 2.9.5 | E78: TIP; TIPO: TIPS AMARILLO SIN CORONA,PRESENTACION: X 1000 UNID., CAPACIDAD:0,2 ML | F78: BOLSA | I78: 2 | J78: =+I78*L78 -> 3080 | K78: =+G78+I78 -> 2 | L78: 1540 | M78: =+K78*L78 -> 3080
A79: 70 | B79: 2.9.5-3492.342 | C79: PROD.MEDICO/FARMACEUTICOS/LAB | D79: 2.9.5 | E79: TIP; TIPO: TIPS AZUL AUTOCLAVABLE,PRESENTACION: X 1000 UNID., CAPACIDAD: 1000 MICROLITROS | F79: BOLSA | I79: 2 | J79: =+I79*L79 -> 4408 | K79: =+G79+I79 -> 2 | L79: 2204 | M79: =+K79*L79 -> 4408
A80: 71 | B80: 2.9.5-5003.8 | C80: PROD. MEDICO/FARMACEUTICOS/LAB. | D80: 2.9.5 | E80: TUBO DE KHAN; MATERIAL: VIDRIO, DIMENSION: 12 X 75 mm | F80: UNIDAD | G80: 5000 | H80: =+G80*L80 -> 145000 | K80: =+G80+I80 -> 5000 | L80: 29 | M80: =+K80*L80 -> 145000 | N80: TUBO DE KAHN DE VIDRIO 12X75X1 Tipo LUMEN
A81: 72 | B81: 2.9.5-4487.20 | C81: PROD. MEDICO/FARMACEUTICOS/LAB. | D81: 2.9.5 | E81: TUBOS A ROSCA; MEDIDA: 15 mm, TIPO: GRADUADO DE POLIPROPILENO, ACCESORIO: CON TAPA | F81: UNIDAD | G81: 50000 | H81: =+G81*L81 -> 2200000 | K81: =+G81+I81 -> 50000 | L81: 44 | M81: =+K81*L81 -> 2200000 | N81: TUBO CONICO PP GRADUADO ESTERIL CON TAPA 15 ML Tipo KINDER
A82: 73 | B82: 2.9.5-2576.56 | C82: PROD. MEDICO/FARMACEUTICOS/LAB. | D82: 2.9.5 | E82: TUBOS AL VACIO P/EXTRACCION; MATERIAL: PLASTICO, MEDIDA: 2 mL, ADITIVO: EDTA TRIPOTASICO, AGUJA: SIN | F82: UNIDAD | G82: 20000 | H82: =+G82*L82 -> 640000 | K82: =+G82+I82 -> 20000 | L82: 32 | M82: =+K82*L82 -> 640000 | N82: TUBO PARA HEMOGRAMA 2 ML TAPA LILA CON EDTA Tipo WEIGAO
A83: 74 | B83: 2.9.5-2582.2 | C83: PROD. MEDICO/FARMACEUTICOS/LAB. | D83: 2.9.5 | E83: TUBOS CAPILARES P/HEMATOCRITO; ADITIVO: CON HEPARINA, PRESENTACION: CAJA X 500 UN | F83: FRASCO | G83: 400 | H83: =+G83*L83 -> 596000 | K83: =+G83+I83 -> 400 | L83: 1490 | M83: =+K83*L83 -> 596000 | N83: CAPILARES MICROHEMATOCRITO CON HEPARINA X 500 UNIDADES Tipo BIOCAP
A84: 75 | B84: 2.9.5-2582.1 | C84: PROD. MEDICO/FARMACEUTICOS/LAB. | D84: 2.9.5 | E84: TUBOS CAPILARES P/HEMATOCRITO; PRESENTACION: CAJA X 500 UN, ADITIVO: SIN HEPARINA | F84: FRASCO | G84: 200 | H84: =+G84*L84 -> 229000 | K84: =+G84+I84 -> 200 | L84: 1145 | M84: =+K84*L84 -> 229000 | N84: CAPILARES MICROHEMATOCRITO SIN HEPARINA X 500 UNIDADES Tipo BIOCAP
A85: 76 | B85: 2.9.5-468.232 | C85: PROD.MEDICO/FARMACEUTICOS/LAB | D85: 2.9.5 | E85: TUBOS DE ENSAYO; TIPO: CONICO P/CENTRIFUGA, MATERIAL: POLIPROPILENO, DIMENSION: 0,5 A 15 mL, ACCESORIO: TAPA A ROSCA | F85: CAJA | I85: 2 | J85: =+I85*L85 -> 27400 | K85: =+G85+I85 -> 2 | L85: 13700 | M85: =+K85*L85 -> 27400 | N85: CAJA X 25 UNID. TIPO BIOLOGIX
A86: 77 | B86: 2.9.5-468.42 | C86: PROD.MEDICO/FARMACEUTICOS/LAB | D86: 2.9.5 | E86: TUBOS DE ENSAYO; TIPO: EPPENDORF, MATERIAL: PLASTICO, DIMENSION: 1.5 mL, ACCESORIOS: SIN, ACCESORIO: SIN | F86: BOLSA | I86: 10 | J86: =+I86*L86 -> 35580 | K86: =+G86+I86 -> 10 | L86: 3558 | M86: =+K86*L86 -> 35580 | N86: BOLSA X 1000 UNID.
A87: 78 | B87: 2.9.5-468.249 | C87: PROD.MEDICO/FARMACEUTICOS/LAB | D87: 2.9.5 | E87: TUBOS DE ENSAYO; TIPO: VACUTAINER P/ SUERO, MATERIAL: PLASTICO, DIMENSION: 4 ML, ACCESORIO: SIN | F87: CAJA | I87: 2 | J87: =+I87*L87 -> 27400 | K87: =+G87+I87 -> 2 | L87: 13700 | M87: =+K87*L87 -> 27400 | N87: TUBOS VACUTAINER P/SUERO DE 4ML, TAPA ROJA C/ETIQUETA - CAJA X 1000 UNID
A88: 79 | B88: 2.9.5-468.85 | C88: PROD.MEDICO/FARMACEUTICOS/LAB | D88: 2.9.5 | E88: TUBOS DE ENSAYO; TIPO: VACUTAINER, MATERIAL: VIDRIO BOROSILICATO, DIMENSION: 10 mL, ACCESORIOS: TAPA, ACCESORIO: TAPA | F88: CAJA | I88: 2 | J88: =+I88*L88 -> 26000 | K88: =+G88+I88 -> 2 | L88: 13000 | M88: =+K88*L88 -> 26000 | N88: CAJA X 1000 UNID.
A89: 80 | B89: 2.9.5-4522.1 | C89: PROD.MEDICO/FARMACEUTICOS/LAB | D89: 2.9.5 | E89: TUBOS DE HEMOLISIS; MATERIAL: VIDRIO, PRESENTACION: CAJA, DIMENSION: 100 X 13 DIAM. EXT., MEDIDAS: 100 X 13 DIAM. EXT., FORMA DE PRESENTACION: SOLIDO, ESTADO: SOLIDO | F89: CAJA | I89: 1 | J89: =+I89*L89 -> 72000 | K89: =+G89+I89 -> 1 | L89: 72000 | M89: =+K89*L89 -> 72000 | N89: CAJA X 1000 UNID.
A90: 81 | B90: 2.9.5-5409.13 | C90: PROD. MEDICO/FARMACEUTICOS/LAB. | D90: 2.9.5 | E90: TUBOS P/ANALISIS DE SANGRE; MATERIAL: PLASTICO, DIMENSION: 13 X 75 mm, TIPO: CONJUNTO ERITROSEDIMENTACION | F90: GRADILLA | G90: 30000 | H90: =+G90*L90 -> 2850000 | K90: =+G90+I90 -> 30000 | L90: 95 | M90: =+K90*L90 -> 2850000 | N90: ERITUBO CON CITRATO 3.8% + GRADILLA + PIPETA PARA ERITROSEDIMENTACION 1 ML Tipo DELTALAB
A91: 82 | B91: 2.9.5-5409.1 | C91: PROD. MEDICO/FARMACEUTICOS/LAB. | D91: 2.9.5 | E91: TUBOS P/ANALISIS DE SANGRE; MATERIAL: POLIMETILMETACRILATO, TIPO: C/ACELER. COAG. C/ GEL SEPARAD, DIMENSION: 13 X 75 mm | F91: UNIDAD | G91: 80000 | H91: =+G91*L91 -> 4160000 | K91: =+G91+I91 -> 80000 | L91: 52 | M91: =+K91*L91 -> 4160000 | N91: TUBO PARA SUERO CON GEL X 5 ML TAPA AMARILLA TIPO WEIGAO
A92: 83 | B92: 2.9.5-5380.6 | C92: PROD. MEDICO/FARMACEUTICOS/LAB. | D92: 2.9.5 | E92: TUBOS P/COAGULOGRAMA; DIMENSION: 12 X 86 mm, VOLUMEN: 2,5 mL, TIPO: ANTICOAGULANTE CITRATO | F92: UNIDAD | G92: 10000 | H92: =+G92*L92 -> 320000 | K92: =+G92+I92 -> 10000 | L92: 32 | M92: =+K92*L92 -> 320000 | N92: TUBO PARA COAGULOGRAMA 1 ML TAPA CELESTE CON CITRATO Tipo WEIGAO
A93: TOTAL RUBRO DESCARTABLE PARA LABORATORIO | H93: =SUM(H10:H92) -> 41869860 | J93: =SUM(J10:J92) -> 10006155 | M93: =SUM(M10:M92) -> 51876015
C96: DETALLE TECNICO Y ESPECIFICACIONES | D96: ANEXO 1-Para oferentes de la Provincia de Catamarca deberán presentar Habilitación Provincial para comercializar el producto que cotizan. 2-Para el resto de oferentes deberán presentar Certificado de Inscripción de ANMAT vigente al momento de la oferta, el mismo deberá ser correspondiente al objeto de la contratación y de encontrarse vencido adjuntar la solicitud de renovación. 3-No se aceptarán ofertas de productos no registrados y autorizada su venta por ANMAT. Se deberá especificar en cada ítem de la propuesta, marca y número de certificado otorgado por dicho ente regulador. 4-Los productos deberán tener un vencimiento posterior a doce (12) meses a partir de la fecha de su recepción.
C98: Plazos de entrega | D98: diez (10) dias habiles
C100: Lugar de Entrega: | D100: ITEMS 1, 2, 3 (200 unid), 4, 6, 7, 10 al 13, 15 al 19, 20 (800 unid), 21, 22 (800 unid), 23 al 38, 41 al 50, 52 al 55, 60 al 62, 64 al 67, 71 al 75, 81 al 83 - DIR. PROV. DE LABORATORIO - CHACABUCO N° 169 - en el horario de 8:00hs a 12:00hs de lunes a viernes. DEBIENDO CORRER LOS GASTOS DE FLETES, ACARREO, CARGA, DESCARGA Y SEGURO A CARGO DEL ADJUDICATARIO.
D101: ITEMS 3 (40 unid), 5, 8, 9, 14, 20 (50 unid), 21, 22 (50 unid), 39, 40, 51, 56 al 59, 63, 68 al 70, 76 al 80 - DIR. PROV. BANCO DE SANGRE - BOTO GARAY N° 500 - en el horario de 8:00hs a 12:00hs de lunes a viernes. DEBIENDO CORRER LOS GASTOS DE FLETES, ACARREO, CARGA, DESCARGA Y SEGURO A CARGO DEL ADJUDICATARIO.
C103: Calidad Minima esperada
C105: Mantenimiento | D105: cuarenta y cinco (45) días
C108: Especificidad item N° | D108: 3 | E108: ALGODONES PLISADO PRE-CORTADO - ENVASE X 500 GR
C109: Especificidad item N° | D109: 4 | E109: ANSA DESCARTABLE DE PLASTICO CALIBRADA DE 10 ul ESTERIL X 20 UNIDADES Tipo DELTALAB
C110: Especificidad item N° | D110: 5 | E110: CAJA X 250 UNID
C111: Especificidad item N° | D111: 6 | E111: APOSITO POST EXTRACCION SANGUNEA 2X7,5 CM CAJA X 250 UNIDADES Tipo BANDERM
C112: Especificidad item N° | D112: 7 | E112: RECOLECTORES DE ORINA PEDIATRICOS
C113: Especificidad item N° | D113: 8 | E113: BOLSAS DE SANGRE TRIPLE KS TIPO GRIFOLS
...

Sheet NP LABORATORIO
A1: NOTA DE PEDIDO | J1: N° | K1: XX/2022
A3: JURISDICCIÓN: | D3: ='SAF 011'!C4 -> 040 - MINISTERIO DE SALUD
A4: SAF: | D4: ='SAF 011'!C5 -> 011 - DIRECCION PROVINCIAL DE ADMINISTRACION - MINISTERIO DE SALUD
A5: UNIDAD EJECUTORA: | D5: 468 - DIRECCION PROVINCIAL DE LABORATORIO
A6: DEPENDENCIA SOLICITANTE: | D6: 468 - DIRECCION PROVINCIAL DE LABORATORIO
A7: PERIODO UTILIZACIÓN: | D7: TRES MESES
A8: OBJETO: | D8: ADQUISICION DEL RUBRO INSUMOS PARA LABORATORIO
A10: Ítem | B10: Codigo Item | C10: DESCRIPCIÓN | H10: Adjunta Detalle Técnico | I10: Unidad Medida | J10: Precio Unitario Estimado | K10: Cantidad Solicitada
A12: 1 | B12: ='SAF 011'!B10 -> 2.9.5-441.470 | C12: ='SAF 011'!E10 -> AGUJAS QUIRURGICAS; TIPO: TERUMO 21GX1", ESPECIFICACION: 25/8, UNIDAD VENTA: CAJA X 100, PRESENTACION: CAJA X 100 | H12: NO | I12: ='SAF 011'!F10 -> CAJA | J12: ='SAF 011'!L10 -> 3005 | K12: ='SAF 011'!G10 -> 500 | O12: =+J12*K12 -> 1502500
A13: 2 | B13: ='SAF 011'!B11 -> 2.9.5-441.471 | C13: ='SAF 011'!E11 -> AGUJAS QUIRURGICAS; TIPO: TERUMO 25GX5/8", ESPECIFICACION: 16/5, UNIDAD VENTA: CAJA X 100, PRESENTACION: CAJA X 100 | H13: NO | I13: ='SAF 011'!F11 -> CAJA | J13: ='SAF 011'!L11 -> 3242 | K13: ='SAF 011'!G11 -> 400 | O13: =+J13*K13 -> 1296800
A14: 3 | B14: ='SAF 011'!B12 -> 2.9.5-470.13 | C14: ='SAF 011'!E12 -> ALGODONES; TIPO: HIDROFILADO, CAPACIDAD: 500 GR, PRESENTACION: ENVASE X 500 GR | H14: SI | I14: ='SAF 011'!F12 -> PAQUETE | J14: ='SAF 011'!L12 -> 862 | K14: ='SAF 011'!G12 -> 200 | O14: =+J14*K14 -> 172400
A15: 4 | B15: ='SAF 011'!B13 -> 2.9.5-5703.15 | C15: ='SAF 011'!E13 -> ANSA; PRESENTACION: UNIDAD, TIPO: PLASTICA DESCARTABLE | H15: SI | I15: ='SAF 011'!F13 -> BOLSA | J15: ='SAF 011'!L13 -> 475 | K15: ='SAF 011'!G13 -> 100 | O15: =+J15*K15 -> 47500
A16: 5 | B16: ='SAF 011'!B15 -> 2.9.5-427.74 | C16: ='SAF 011'!E15 -> APOSITOS; TIPO: POST EXTRACCION SANGUINEA, TAMAÑO: 2 X 7,5 Cm | H16: SI | I16: ='SAF 011'!F15 -> CAJA | J16: ='SAF 011'!L15 -> 977 | K16: ='SAF 011'!G15 -> 250 | O16: =+J16*K16 -> 244250
A17: 6 | B17: ='SAF 011'!B16 -> 2.9.5-2505.10 | C17: ='SAF 011'!E16 -> BOLSAS COLECTORAS; TIPO: DE ORINA, USO: PEDIATRICO, CAPACIDAD: 100 mL | H17: SI | I17: ='SAF 011'!F16 -> UNIDAD | J17: ='SAF 011'!L16 -> 230 | K17: ='SAF 011'!G16 -> 10000 | O17: =+J17*K17 -> 2300000
A18: 7 | B18: ='SAF 011'!B19 -> 2.9.5-4047.6 | C18: ='SAF 011'!E19 -> CRIOVIALES; MATERIAL: POLIPROPILENO, VOLUMEN: 5 mL | H18: SI | I18: ='SAF 011'!F19 -> UNIDAD | J18: ='SAF 011'!L19 -> 66.4 | K18: ='SAF 011'!G19 -> 5000 | O18: =+J18*K18 -> 332000
A19: 8 | B19: ='SAF 011'!B20 -> 2.9.5-5410.11 | C19: ='SAF 011'!E20 -> CUBETAS DE REACCION; MATERIAL: PLASTICO, CELDAS: 500 C/AGITADOR, USO: COAGULOMETRO | H19: SI | I19: ='SAF 011'!F20 -> CAJA | J19: ='SAF 011'!L20 -> 17868 | K19: ='SAF 011'!G20 -> 20 | O19: =+J19*K19 -> 357360
A20: 9 | B20: ='SAF 011'!B21 -> 2.9.5-5410.11 | C20: ='SAF 011'!E21 -> CUBETAS DE REACCION; MATERIAL: PLASTICO, CELDAS: 500 C/AGITADOR, USO: COAGULOMETRO | H20: SI | I20: ='SAF 011'!F21 -> CAJA | J20: ='SAF 011'!L21 -> 32018 | K20: ='SAF 011'!G21 -> 20 | O20: =+J20*K20 -> 640360
A21: 10 | B21: ='SAF 011'!B22 -> 2.9.5-2557.32 | C21: ='SAF 011'!E22 -> CUBREOBJETOS; MATERIAL: VIDRIO, DIMENSION: 20 X 20 mm, PRESENTACION: ENVASE X 200 UN | H21: NO | I21: ='SAF 011'!F22 -> CAJA | J21: ='SAF 011'!L22 -> 375 | K21: ='SAF 011'!G22 -> 400 | O21: =+J21*K21 -> 150000
A22: 11 | B22: ='SAF 011'!B24 -> 2.9.2-675.161 | C22: ='SAF 011'!E24 -> ETIQUETAS AUTOADHESIVAS; MEDIDA: 80 X 25 mm, PRESENTACION: ROLLO X 380 GR, PAPEL BASE: AUTOADHESIVO | H22: SI | I22: ='SAF 011'!F24 -> PACK | J22: ='SAF 011'!L24 -> 2308 | K22: ='SAF 011'!G24 -> 10 | M22: =+J22*K22 -> 23080
A23: 12 | B23: ='SAF 011'!B25 -> 2.9.5-6877.16 | C23: ='SAF 011'!E25 -> FUENTES DE LUZ; USO: ILUMINADOR DE MICROSCOPIO, POTENCIA: 20 W, LAMPARA: LED | H23: SI | I23: ='SAF 011'!F25 -> UNIDAD | J23: ='SAF 011'!L25 -> 2207 | K23: ='SAF 011'!G25 -> 50 | O23: =+J23*K23 -> 110350
A24: 13 | B24: ='SAF 011'!B26 -> 2.9.5-3017.27 | C24: ='SAF 011'!E26 -> GRADILLAS P/LABORATORIO; TAMAÑO TUBO: 15 X 2 Cm, CANTIDAD DE TUBOS: 36, MATERIAL: ALAMBRE REV.EN RESINA ANTIAD., MEDIDA TUBO: 15 X 2 Cm, CANT. DE ELEMENTOS: 36, MEDIDA: 15 X 2 Cm | H24: SI | I24: ='SAF 011'!F26 -> UNIDAD | J24: ='SAF 011'!L26 -> 3336 | K24: ='SAF 011'!G26 -> 40 | O24: =+J24*K24 -> 133440
A25: 14 | B25: ='SAF 011'!B27 -> 2.9.5-3017.45 | C25: ='SAF 011'!E27 -> GRADILLAS P/LABORATORIO; TAMAÑO TUBO: 25 mm, CANTIDAD DE TUBOS: 24, MATERIAL: ALAMBRE PLASTIFICADO, MEDIDA TUBO: 25 mm, CANT. DE ELEMENTOS: 24, MEDIDA: 25 mm | H25: SI | I25: ='SAF 011'!F27 -> UNIDAD | J25: ='SAF 011'!L27 -> 2704 | K25: ='SAF 011'!G27 -> 40 | O25: =+J25*K25 -> 108160
A26: 15 | B26: ='SAF 011'!B28 -> 2.9.5-3017.36 | C26: ='SAF 011'!E28 -> GRADILLAS P/LABORATORIO; TAMAÑO TUBO: DIAM. EXT. 15 mm, CANTIDAD DE TUBOS: 48, MATERIAL: POLIPROPILENO, MEDIDA TUBO: DIAM. EXT. 15 mm, CANT. DE ELEMENTOS: 48, MEDIDA: DIAM. EXT. 15 mm | H26: SI | I26: ='SAF 011'!F28 -> UNIDAD | J26: ='SAF 011'!L28 -> 4243 | K26: ='SAF 011'!G28 -> 40 | O26: =+J26*K26 -> 169720
A27: 16 | B27: ='SAF 011'!B29 -> 2.9.5-1909.77 | C27: ='SAF 011'!E29 -> GUANTES USO MEDICINAL; TIPO: DESCARTABLE, TAMAÑO: CHICO, MATERIAL: LATEX, PRESENTACION: ENVASE X 100 UN | H27: SI | I27: ='SAF 011'!F29 -> CAJA | J27: ='SAF 011'!L29 -> 590 | K27: ='SAF 011'!G29 -> 800 | O27: =+J27*K27 -> 472000
A28: 17 | B28: ='SAF 011'!B31 -> 2.9.5-1909.87 | C28: ='SAF 011'!E31 -> GUANTES USO MEDICINAL; TIPO: DESCARTABLE, TAMAÑO: MEDIANO, MATERIAL: LATEX, PRESENTACION: ENVASE X 100 UNID. | H28: SI | I28: ='SAF 011'!F31 -> CAJA | J28: ='SAF 011'!L31 -> 590 | K28: ='SAF 011'!G31 -> 800 | O28: =+J28*K28 -> 472000
A29: 18 | B29: ='SAF 011'!B32 -> 2.9.5-1909.96 | C29: ='SAF 011'!E32 -> GUANTES USO MEDICINAL; TIPO: MANOPLA, TAMAÑO: MEDIANO, MATERIAL: POLIETILENO, PRESENTACION: ENVASE X 100 | H29: SI | I29: ='SAF 011'!F32 -> BOLSA | J29: ='SAF 011'!L32 -> 2050 | K29: ='SAF 011'!G32 -> 500 | O29: =+J29*K29 -> 1025000
A30: 19 | B30: ='SAF 011'!B33 -> 2.9.5-1909.84 | C30: ='SAF 011'!E33 -> GUANTES USO MEDICINAL; TIPO: P/QUIMICOS, TAMAÑO: CHICO, MATERIAL: NITRILO, PRESENTACION: ENVASE X 100 UN | H30: SI | I30: ='SAF 011'!F33 -> CAJA | J30: ='SAF 011'!L33 -> 1378 | K30: ='SAF 011'!G33 -> 400 | O30: =+J30*K30 -> 551200
A31: 20 | B31: ='SAF 011'!B34 -> 2.9.5-1909.82 | C31: ='SAF 011'!E34 -> GUANTES USO MEDICINAL; TIPO: P/QUIMICOS, TAMAÑO: GRANDE, MATERIAL: NITRILO, PRESENTACION: ENVASE X 100 UN | H31: SI | I31: ='SAF 011'!F34 -> CAJA | J31: ='SAF 011'!L34 -> 1378 | K31: ='SAF 011'!G34 -> 50 | O31: =+J31*K31 -> 68900
A32: 21 | B32: ='SAF 011'!B35 -> 2.9.5-1909.83 | C32: ='SAF 011'!E35 -> GUANTES USO MEDICINAL; TIPO: P/QUIMICOS, TAMAÑO: MEDIANO, MATERIAL: NITRILO, PRESENTACION: ENVASE X 100 UN | H32: SI | I32: ='SAF 011'!F35 -> CAJA | J32: ='SAF 011'!L35 -> 1378 | K32: ='SAF 011'!G35 -> 500 | O32: =+J32*K32 -> 689000
A33: 22 | B33: ='SAF 011'!B36 -> 2.9.5-2366.2 | C33: ='SAF 011'!E36 -> HISOPOS; MATERIAL DE EXTREMOS: ALGODON, PRESENTACION: CAJA X 100 | H33: SI | I33: ='SAF 011'!F36 -> BOLSA | J33: ='SAF 011'!L36 -> 276 | K33: ='SAF 011'!G36 -> 400 | O33: =+J33*K33 -> 110400
A34: 23 | B34: ='SAF 011'!B37 -> 2.9.5-8799.12 | C34: ='SAF 011'!E37 -> JERINGA; MATERIAL: PLASTICO, CAPACIDAD: 10 CM3, ACCESORIOS: SIN, TIPO: ESTERIL, ACCESORIO: SIN | H34: SI | I34: ='SAF 011'!F37 -> CAJA | J34: ='SAF 011'!L37 -> 2027 | K34: ='SAF 011'!G37 -> 300 | O34: =+J34*K34 -> 608100
A35: 24 | B35: ='SAF 011'!B38 -> 2.9.5-8799.8 | C35: ='SAF 011'!E38 -> JERINGA; MATERIAL: PLASTICO, CAPACIDAD: 3 mL, ACCESORIOS: SIN, TIPO: NICHIRYO, ACCESORIO: SIN | H35: SI | I35: ='SAF 011'!F38 -> CAJA | J35: ='SAF 011'!L38 -> 1405 | K35: ='SAF 011'!G38 -> 500 | O35: =+J35*K35 -> 702500
A36: 25 | B36: ='SAF 011'!B39 -> 2.9.5-8799.11 | C36: ='SAF 011'!E39 -> JERINGA; MATERIAL: PLASTICO, CAPACIDAD: 5 CM3, ACCESORIOS: SIN, TIPO: ESTERIL, ACCESORIO: SIN | H36: SI | I36: ='SAF 011'!F39 -> CAJA | J36: ='SAF 011'!L39 -> 1380 | K36: ='SAF 011'!G39 -> 800 | O36: =+J36*K36 -> 1104000
A37: 26 | B37: ='SAF 011'!B40 -> 2.9.5-7870.15 | C37: ='SAF 011'!E40 -> LAMPARAS P/AUTOANALIZADOR; TIPO: HALOGENA, TENSION: 6 V, POTENCIA: 10 W | H37: SI | I37: ='SAF 011'!F40 -> UNIDAD | J37: ='SAF 011'!L40 -> 4600 | K37: ='SAF 011'!G40 -> 15 | N37: =+K37*J37 -> 69000
A38: 27 | B38: ='SAF 011'!B41 -> 2.9.5-7870.15 | C38: ='SAF 011'!E41 -> LAMPARAS P/AUTOANALIZADOR; TIPO: HALOGENA, TENSION: 6 V, POTENCIA: 10 W | H38: SI | I38: ='SAF 011'!F41 -> UNIDAD | J38: ='SAF 011'!L41 -> 2575 | K38: ='SAF 011'!G41 -> 30 | N38: =+K38*J38 -> 77250
A39: 28 | B39: ='SAF 011'!B42 -> 2.9.5-7870.16 | C39: ='SAF 011'!E42 -> LAMPARAS P/AUTOANALIZADOR; TIPO: HALOGENA, TENSION: 6 V, POTENCIA: 20 W | H39: SI | I39: ='SAF 011'!F42 -> UNIDAD | J39: ='SAF 011'!L42 -> 3800 | K39: ='SAF 011'!G42 -> 5 | N39: =+K39*J39 -> 19000
A40: 29 | B40: ='SAF 011'!B43 -> 2.9.5-2516.3 | C40: ='SAF 011'!E43 -> LAZOS P/EXTRACCION; MATERIAL: LATEX, DIAMETRO: PLANO 2 X 35 Cm | H40: SI | I40: ='SAF 011'!F43 -> CAJA | J40: ='SAF 011'!L43 -> 427 | K40: ='SAF 011'!G43 -> 100 | O40: =+J40*K40 -> 42700
A41: 30 | B41: ='SAF 011'!B44 -> 2.9.5-6479.44 | C41: ='SAF 011'!E44 -> MICROPIPETAS AUTOMATICAS; TIPO: MONOCANAL, ESCALA: 1 µL, VOLUMEN: 2 A 20 µL, SENSIBILIDAD: 0,01 µL | H41: SI | I41: ='SAF 011'!F44 -> UNIDAD | J41: ='SAF 011'!L44 -> 151734 | K41: ='SAF 011'!G44 -> 10 | O41: =+J41*K41 -> 1517340
A42: 31 | B42: ='SAF 011'!B45 -> 2.9.5-6479.46 | C42: ='SAF 011'!E45 -> MICROPIPETAS AUTOMATICAS; TIPO: MONOCANAL, ESCALA: 1 µL, VOLUMEN: 20 A 200 µL, SENSIBILIDAD: 0,1 µL | H42: SI | I42: ='SAF 011'!F45 -> UNIDAD | J42: ='SAF 011'!L45 -> 151734 | K42: ='SAF 011'!G45 -> 10 | O42: =+J42*K42 -> 1517340
A43: 32 | B43: ='SAF 011'!B46 -> 2.9.5-6479.35 | C43: ='SAF 011'!E46 -> MICROPIPETAS AUTOMATICAS; TIPO: MONOCANAL, ESCALA: 1 A 10 µL, VOLUMEN: 10 µL, SENSIBILIDAD: 0,1 µL | H43: SI | I43: ='SAF 011'!F46 -> UNIDAD | J43: ='SAF 011'!L46 -> 151734 | K43: ='SAF 011'!G46 -> 10 | O43: =+J43*K43 -> 1517340
A44: 33 | B44: ='SAF 011'!B47 -> 2.9.5-6479.34 | C44: ='SAF 011'!E47 -> MICROPIPETAS AUTOMATICAS; TIPO: MONOCANAL, ESCALA: 100 A 10000 µL, VOLUMEN: 1000 µL, SENSIBILIDAD: 1 µL | H44: SI | I44: ='SAF 011'!F47 -> UNIDAD | J44: ='SAF 011'!L47 -> 151734 | K44: ='SAF 011'!G47 -> 20 | O44: =+J44*K44 -> 3034680
A45: 34 | B45: ='SAF 011'!B50 -> 2.9.5-4633.11 | C45: ='SAF 011'!E50 -> MICROTUBOS P/LABORATORIO; MATERIAL: POLIPROPILENO, PRESENTACION: ENVASE X 1000 UN, MEDIDA: 1.5 mL, COLOR: TRANSPARENTE, TIPO: C/TAPA, LIBRE DNASAS/RNASAS | H45: SI | I45: ='SAF 011'!F50 -> BOLSA | J45: ='SAF 011'!L50 -> 5890 | K45: ='SAF 011'!G50 -> 80 | O45: =+J45*K45 -> 471200
A46: 35 | B46: ='SAF 011'!B51 -> 2.9.5-4633.47 | C46: ='SAF 011'!E51 -> MICROTUBOS P/LABORATORIO; MATERIAL: POLIPROPILENO, PRESENTACION: ENVASE X 1000 UN, MEDIDA: 2 mL, TIPO: EPPENDORF | H46: SI | I46: ='SAF 011'!F51 -> BOLSA | J46: ='SAF 011'!L51 -> 6300 | K46: ='SAF 011'!G51 -> 100 | O46: =+J46*K46 -> 630000
A47: 36 | B47: ='SAF 011'!B52 -> 2.9.5-2553.6 | C47: ='SAF 011'!E52 -> PAPEL P/ELECTROCARDIOGRAM.; MEDIDA: 50 MM X 30 M | H47: SI | I47: ='SAF 011'!F52 -> UNIDAD | J47: ='SAF 011'!L52 -> 254 | K47: ='SAF 011'!G52 -> 300 | M47: =+J47*K47 -> 76200
A48: 37 | B48: ='SAF 011'!B53 -> 2.9.5-2553.6 | C48: ='SAF 011'!E53 -> PAPEL P/ELECTROCARDIOGRAM.; MEDIDA: 50 MM X 30 M | H48: SI | I48: ='SAF 011'!F53 -> UNIDAD | J48: ='SAF 011'!L53 -> 356 | K48: ='SAF 011'!G53 -> 300 | M48: =+J48*K48 -> 106800
A49: 38 | B49: ='SAF 011'!B54 -> 2.9.5-2553.6 | C49: ='SAF 011'!E54 -> PAPEL P/ELECTROCARDIOGRAM.; MEDIDA: 50 MM X 30 M | H49: SI | I49: ='SAF 011'!F54 -> UNIDAD | J49: ='SAF 011'!L54 -> 410 | K49: ='SAF 011'!G54 -> 200 | M49: =+J49*K49 -> 82000
A50: 39 | B50: ='SAF 011'!B55 -> 2.9.5-2553.6 | C50: ='SAF 011'!E55 -> PAPEL P/ELECTROCARDIOGRAM.; MEDIDA: 50 MM X 30 M | H50: SI | I50: ='SAF 011'!F55 -> UNIDAD | J50: ='SAF 011'!L55 -> 510 | K50: ='SAF 011'!G55 -> 200 | M50: =+J50*K50 -> 102000
A51: 40 | B51: ='SAF 011'!B56 -> 2.9.5-2592.2 | C51: ='SAF 011'!E56 -> PIPETAS GRADUADAS; MATERIAL: PLASTICO, CAPACIDAD: 3 mL, MEDIDA MINIMA: SIN VALOR, TIPO: PASTEUR DESCARTABLE | H51: SI | I51: ='SAF 011'!F56 -> CAJA | J51: ='SAF 011'!L56 -> 4484 | K51: ='SAF 011'!G56 -> 200 | O51: =+J51*K51 -> 896800
A52: 41 | B52: ='SAF 011'!B57 -> 2.9.5-2782.1 | C52: ='SAF 011'!E57 -> PISETAS DE LABORATORIO; CAPACIDAD: 500 mL, MATERIAL: PLASTICO | H52: NO | I52: ='SAF 011'!F57 -> UNIDAD | J52: ='SAF 011'!L57 -> 1575 | K52: ='SAF 011'!G57 -> 50 | O52: =+J52*K52 -> 78750
A53: 42 | B53: ='SAF 011'!B58 -> 2.9.5-6786.6 | C53: ='SAF 011'!E58 -> PLACAS DE TOQUE; MATERIAL: VIDRIO, LARGO: 8 Cm, ANCHO: 6 Cm, ESPESOR: 5 mm, USO: DETERMINACION VDRL | H53: SI | I53: ='SAF 011'!F58 -> UNIDAD | J53: ='SAF 011'!L58 -> 4500 | K53: ='SAF 011'!G58 -> 50 | O53: =+J53*K53 -> 225000
A54: 43 | B54: ='SAF 011'!B59 -> 2.9.5-6786.6 | C54: ='SAF 011'!E59 -> PLACAS DE TOQUE; MATERIAL: VIDRIO, LARGO: 8 Cm, ANCHO: 6 Cm, ESPESOR: 5 mm, USO: DETERMINACION VDRL | H54: SI | I54: ='SAF 011'!F59 -> UNIDAD | J54: ='SAF 011'!L59 -> 4500 | K54: ='SAF 011'!G59 -> 50 | O54: =+J54*K54 -> 225000
A55: 44 | B55: ='SAF 011'!B61 -> 2.9.5-2583.29 | C55: ='SAF 011'!E61 -> PLACAS POLICUBETA P/LAB.; DIVISIONES: 96; MATERIAL: PLACAS DE PLÁSTICO DESECHABLES Y PEINES DE PUNTA DE POLIPROPILENO KIN FISHER FLEX; MARCA: THERMOFISHER | H55: SI | I55: ='SAF 011'!F61 -> UNIDAD | J55: ='SAF 011'!L61 -> 280000 | K55: ='SAF 011'!G61 -> 1 | O55: =+J55*K55 -> 280000
A56: 45 | B56: ='SAF 011'!B62 -> 2.9.5-2583.31 | C56: ='SAF 011'!E62 -> PLACAS POLICUBETA P/LAB.; DIVISIONES: 96; MATERIAL: PLÁSTICO; ESTERILIZADA: NO; FONDO TIPO: TM PROFUNDO 200 UL KING FISHER FLEX; MARCA: THERMOFISHER | H56: SI | I56: ='SAF 011'!F62 -> UNIDAD | J56: ='SAF 011'!L62 -> 82600 | K56: ='SAF 011'!G62 -> 2 | O56: =+J56*K56 -> 165200
A57: 46 | B57: ='SAF 011'!B63 -> 2.9.5-2583.30 | C57: ='SAF 011'!E63 -> PLACAS POLICUBETA P/LAB.; DIVISIONES: 96; MATERIAL: POLIPROPILENO; ESTERILIZADA: NO; FONDO: EN V; FONDO TIPO: PROFUNDO KING FISHER FLEX; MARCA: THERMOFISHER | H57: SI | I57: ='SAF 011'!F63 -> UNIDAD | J57: ='SAF 011'!L63 -> 145000 | K57: ='SAF 011'!G63 -> 7 | O57: =+J57*K57 -> 1015000
A58: 47 | B58: ='SAF 011'!B64 -> 2.9.5-5773.1 | C58: ='SAF 011'!E64 -> PORTAOBJETOS P/LABORATORIO; PRESENTACION: CAJA X 50 UN, MEDIDA: 2,5 X 7,5 Cm, USO: LABORATORIO, MATERIAL: VIDRIO | H58: SI | I58: ='SAF 011'!F64 -> CAJA | J58: ='SAF 011'!L64 -> 265 | K58: ='SAF 011'!G64 -> 500 | O58: =+J58*K58 -> 132500
A59: 48 | B59: ='SAF 011'!B69 -> 2.9.6-6345.64 | C59: ='SAF 011'!E69 -> REP. Y ACC. P/AUTOANALIZADOR; REPUESTO: CUBETA DE REACCION, MARCA EQUIPO: METROLAB, MODELO EQUIPO: 2300 | H59: SI | I59: ='SAF 011'!F69 -> CAJA | J59: ='SAF 011'!L69 -> 40627 | K59: ='SAF 011'!G69 -> 50 | O59: =+J59*K59 -> 2031350
A60: 49 | B60: ='SAF 011'!B70 -> 2.9.6-6345.64 | C60: ='SAF 011'!E70 -> REP. Y ACC. P/AUTOANALIZADOR; REPUESTO: CUBETA DE REACCION, MARCA EQUIPO: METROLAB, MODELO EQUIPO: 2300 | H60: SI | I60: ='SAF 011'!F70 -> UNIDAD | J60: ='SAF 011'!L70 -> 4000 | K60: ='SAF 011'!G70 -> 100 | O60: =+J60*K60 -> 400000
A61: 50 | B61: ='SAF 011'!B71 -> 2.9.6-8875.101 | C61: ='SAF 011'!E71 -> REP. Y ACC. P/EQUIPO MEDICO; USO: EXTRACCION DE SANGRE, MARCA EQUIPO: UNIVERSAL, ELEMENTO: APOYABRAZOS, MODELO EQUIPO: UNIVERSAL | H61: SI | I61: ='SAF 011'!F71 -> UNIDAD | J61: ='SAF 011'!L71 -> 8419 | K61: ='SAF 011'!G71 -> 10 | P61: =+J61*K61 -> 84190
A62: 51 | B62: ='SAF 011'!B73 -> 2.9.5-3492.42 | C62: ='SAF 011'!E73 -> TIP; TIPO: AMARILLO, PRESENTACION: BOLSA X 1000 UN, CAP. USO: 1 A 200 µL, CAPACIDAD: 1 A 200 µL | H62: SI | I62: ='SAF 011'!F73 -> BOLSA | J62: ='SAF 011'!L73 -> 2584 | K62: ='SAF 011'!G73 -> 400 | O62: =+J62*K62 -> 1033600
A63: 52 | B63: ='SAF 011'!B74 -> 2.9.5-3492.42 | C63: ='SAF 011'!E74 -> TIP; TIPO: AMARILLO, PRESENTACION: BOLSA X 1000 UN, CAP. USO: 1 A 200 µL, CAPACIDAD: 1 A 200 µL | H63: SI | I63: ='SAF 011'!F74 -> BOLSA | J63: ='SAF 011'!L74 -> 2166 | K63: ='SAF 011'!G74 -> 100 | O63: =+J63*K63 -> 216600
A64: 53 | B64: ='SAF 011'!B75 -> 2.9.5-3492.97 | C64: ='SAF 011'!E75 -> TIP; TIPO: P/PIPETA AUTOMATICA, PRESENTACION: BOLSA X 1000, CAP. USO: 100 A 1000 µL, CAPACIDAD: 100 A 1000 µL | H64: SI | I64: ='SAF 011'!F75 -> BOLSA | J64: ='SAF 011'!L75 -> 3686 | K64: ='SAF 011'!G75 -> 200 | O64: =+J64*K64 -> 737200
A65: 54 | B65: ='SAF 011'!B76 -> 2.9.5-3492.97 | C65: ='SAF 011'!E76 -> TIP; TIPO: P/PIPETA AUTOMATICA, PRESENTACION: BOLSA X 1000, CAP. USO: 100 A 1000 µL, CAPACIDAD: 100 A 1000 µL | H65: SI | I65: ='SAF 011'!F76 -> BOLSA | J65: ='SAF 011'!L76 -> 5548 | K65: ='SAF 011'!G76 -> 100 | O65: =+J65*K65 -> 554800
A66: 55 | B66: ='SAF 011'!B80 -> 2.9.5-5003.8 | C66: ='SAF 011'!E80 -> TUBO DE KHAN; MATERIAL: VIDRIO, DIMENSION: 12 X 75 mm | H66: SI | I66: ='SAF 011'!F80 -> UNIDAD | J66: ='SAF 011'!L80 -> 29 | K66: ='SAF 011'!G80 -> 5000 | O66: =+J66*K66 -> 145000
A67: 56 | B67: ='SAF 011'!B81 -> 2.9.5-4487.20 | C67: ='SAF 011'!E81 -> TUBOS A ROSCA; MEDIDA: 15 mm, TIPO: GRADUADO DE POLIPROPILENO, ACCESORIO: CON TAPA | H67: SI | I67: ='SAF 011'!F81 -> UNIDAD | J67: ='SAF 011'!L81 -> 44 | K67: ='SAF 011'!G81 -> 50000 | O67: =+J67*K67 -> 2200000
A68: 57 | B68: ='SAF 011'!B82 -> 2.9.5-2576.56 | C68: ='SAF 011'!E82 -> TUBOS AL VACIO P/EXTRACCION; MATERIAL: PLASTICO, MEDIDA: 2 mL, ADITIVO: EDTA TRIPOTASICO, AGUJA: SIN | H68: SI | I68: ='SAF 011'!F82 -> UNIDAD | J68: ='SAF 011'!L82 -> 32 | K68: ='SAF 011'!G82 -> 20000 | O68: =+J68*K68 -> 640000
A69: 58 | B69: ='SAF 011'!B83 -> 2.9.5-2582.2 | C69: ='SAF 011'!E83 -> TUBOS CAPILARES P/HEMATOCRITO; ADITIVO: CON HEPARINA, PRESENTACION: CAJA X 500 UN | H69: SI | I69: ='SAF 011'!F83 -> FRASCO | J69: ='SAF 011'!L83 -> 1490 | K69: ='SAF 011'!G83 -> 400 | O69: =+J69*K69 -> 596000
A70: 59 | B70: ='SAF 011'!B84 -> 2.9.5-2582.1 | C70: ='SAF 011'!E84 -> TUBOS CAPILARES P/HEMATOCRITO; PRESENTACION: CAJA X 500 UN, ADITIVO: SIN HEPARINA | H70: SI | I70: ='SAF 011'!F84 -> FRASCO | J70: ='SAF 011'!L84 -> 1145 | K70: ='SAF 011'!G84 -> 200 | O70: =+J70*K70 -> 229000
A71: 60 | B71: ='SAF 011'!B90 -> 2.9.5-5409.13 | C71: ='SAF 011'!E90 -> TUBOS P/ANALISIS DE SANGRE; MATERIAL: PLASTICO, DIMENSION: 13 X 75 mm, TIPO: CONJUNTO ERITROSEDIMENTACION | H71: SI | I71: ='SAF 011'!F90 -> GRADILLA | J71: ='SAF 011'!L90 -> 95 | K71: ='SAF 011'!G90 -> 30000 | O71: =+J71*K71 -> 2850000
A72: 61 | B72: ='SAF 011'!B91 -> 2.9.5-5409.1 | C72: ='SAF 011'!E91 -> TUBOS P/ANALISIS DE SANGRE; MATERIAL: POLIMETILMETACRILATO, TIPO: C/ACELER. COAG. C/ GEL SEPARAD, DIMENSION: 13 X 75 mm | H72: SI | I72: ='SAF 011'!F91 -> UNIDAD | J72: ='SAF 011'!L91 -> 52 | K72: ='SAF 011'!G91 -> 80000 | O72: =+J72*K72 -> 4160000
A73: 62 | B73: ='SAF 011'!B92 -> 2.9.5-5380.6 | C73: ='SAF 011'!E92 -> TUBOS P/COAGULOGRAMA; DIMENSION: 12 X 86 mm, VOLUMEN: 2,5 mL, TIPO: ANTICOAGULANTE CITRATO | H73: SI | I73: ='SAF 011'!F92 -> UNIDAD | J73: ='SAF 011'!L92 -> 32 | K73: ='SAF 011'!G92 -> 10000 | O73: =+J73*K73 -> 320000
A74: Costo total estimado: PESOS CUARENTA Y UN MILLONES OCHOCIENTOS SESENTA Y NUEVE MIL OCHOCIENTOS SESENTA CON 00/100.- | J74: =SUMPRODUCT(J12:J73,K12:K73) -> 41869860 | M74: =SUM(M12:M73) -> 390080 | N74: =SUM(N12:N73) -> 165250 | O74: =SUM(O12:O73) -> 41230340 | P74: =SUM(P12:P73) -> 84190 | Q74: =SUM(M74:P74) -> 41869860
M76: 234 | N76: 293 | O76: 295 | P76: 296

Sheet APG LABORATORIO
A1: EJERCICIO: | D1: 2022 | P1: AUTORIZACION PARA GASTAR
A4: JURISDICCIÓN: | G4: ='NP LABORATORIO'!D3 -> 040 - MINISTERIO DE SALUD
A5: SAF: | G5: ='NP LABORATORIO'!D4 -> 011 - DIRECCION PROVINCIAL DE ADMINISTRACION - MINISTERIO DE SALUD
A6: UNIDAD EJECUTORA: | G6: ='NP LABORATORIO'!D5 -> 468 - DIRECCION PROVINCIAL DE LABORATORIO
A7: DEPENDENCIA SOLICITANTE: | G7: ='NP LABORATORIO'!D6 -> 468 - DIRECCION PROVINCIAL DE LABORATORIO
A8: AUTORIZACIÓN:
A9: Señor Director de Administración o Titular del Servicio Administrativo Financiero:
A10: Autorizo la realización de los trámites correspondientes, a fin de proveer a este Organismo los bienes que se detallan en Nota de Pedido N°....... , afectando la erogación resultante a los créditos presupuestarios aprobados a favor de esta Unidad Ejecutora, conforme al siguiente detalle:
A12: IMPUTACIÓN PRESUPUESTARIA
A13: CÓDIGO | O13: DENOMINACIÓN DE LA PARTIDA PRESUPUESTARIA | Q13: IMPORTE
A14: PR | B14: SB | C14: PY | D14: AC | E14: OB | F14: UG | G14: FIN | H14: FUN | I14: I | J14: P | K14: P | L14: SubP | M14: M | N14: FF
A15: 62 | D15: 1 | F15: 4901 | G15: 3 | H15: 1 | I15: 2 | J15: 3 | K15: 4 | M15: 1 | N15: 1.1 | O15: PRODUCTOS DE PAPEL Y CARTON | Q15: ='NP LABORATORIO'!M74 -> 390080
A16: 62 | D16: 1 | F16: 4901 | G16: 3 | H16: 1 | I16: 2 | J16: 9 | K16: 3 | M16: 1 | N16: 1.1 | O16: UTILES Y MATERIALES ELECTRICOS | Q16: ='NP LABORATORIO'!N74 -> 165250
A17: 62 | D17: 1 | F17: 4901 | G17: 3 | H17: 1 | I17: 2 | J17: 9 | K17: 5 | M17: 1 | N17: 1.1 | O17: UTILES MENORES MEDICOS, QUIRURGICOS Y DE LABORATORIO | Q17: ='NP LABORATORIO'!O74 -> 41230340
A18: 62 | D18: 1 | F18: 4901 | G18: 3 | H18: 1 | I18: 2 | J18: 9 | K18: 6 | M18: 1 | N18: 1.1 | O18: REPUESTOS Y ACCESORIOS | Q18: ='NP LABORATORIO'!P74 -> 84190
A38: TOTAL DE PESOS: CUARENTA Y UN MILLONES OCHOCIENTOS SESENTA Y NUEVE MIL OCHOCIENTOS SESENTA CON 00/100.- | Q38: =SUM(Q15:Q37) -> 41869860
A40: JUSTIFICACIÓN:
A41: ='NP LABORATORIO'!D8 -> ADQUISICION DEL RUBRO INSUMOS PARA LABORATORIO

Sheet NP BANCO DE SANGRE
A1: NOTA DE PEDIDO | J1: N° | K1: XX/2022
A3: JURISDICCIÓN: | D3: ='SAF 011'!C4 -> 040 - MINISTERIO DE SALUD
A4: SAF: | D4: ='SAF 011'!C5 -> 011 - DIRECCION PROVINCIAL DE ADMINISTRACION - MINISTERIO DE SALUD
A5: UNIDAD EJECUTORA: | D5: 747 - DIRECCION PROVINCIAL BANCO DE SANGRE
A6: DEPENDENCIA SOLICITANTE: | D6: 747 - DIRECCION PROVINCIAL BANCO DE SANGRE
A7: PERIODO UTILIZACIÓN: | D7: TRES MESES
A8: OBJETO: | D8: ADQUISICION DEL RUBRO INSUMOS PARA LABORATORIO
A10: Ítem | B10: Codigo Item | C10: DESCRIPCIÓN | H10: Adjunta Detalle Técnico | I10: Unidad Medida | J10: Precio Unitario Estimado | K10: Cantidad Solicitada
A12: 1 | B12: ='SAF 011'!B12 -> 2.9.5-470.13 | C12: ='SAF 011'!E12 -> ALGODONES; TIPO: HIDROFILADO, CAPACIDAD: 500 GR, PRESENTACION: ENVASE X 500 GR | H12: SI | I12: ='SAF 011'!F12 -> PAQUETE | J12: ='SAF 011'!L12 -> 862 | K12: ='SAF 011'!I12 -> 40
A13: 2 | B13: ='SAF 011'!B14 -> 2.9.5-427.131 | C13: ='SAF 011'!E14 -> APOSITOS; TIPO: HIPOALARGENICO, TAMAÑO: 40 X 40 MM | H13: SI | I13: ='SAF 011'!F14 -> CAJA | J13: ='SAF 011'!L14 -> 702 | K13: ='SAF 011'!I14 -> 50
A14: 3 | B14: ='SAF 011'!B17 -> 2.9.5-2694.22 | C14: ='SAF 011'!E17 -> BOLSAS P/TRANSFUSIONES SANGRE; CAPACIDAD: 450 mL, SOLUCIONES: CFD CON ADENINA, TIPO: HEMOTERAPIA | H14: SI | I14: ='SAF 011'!F17 -> UNIDAD | J14: ='SAF 011'!L17 -> 1190 | K14: ='SAF 011'!I17 -> 1800
A15: 4 | B15: ='SAF 011'!B18 -> 2.9.5-1908.28 | C15: ='SAF 011'!E18 -> CEPILLOS P/LABORATORIO; TIPO: LIMPIEZA DE TUBOS, MATERIAL: CERDA, TAMAÑO: DIAM. 9 mm | H15: SI | I15: ='SAF 011'!F18 -> UNIDAD | J15: ='SAF 011'!L18 -> 125 | K15: ='SAF 011'!I18 -> 10
A16: 5 | B16: ='SAF 011'!B23 -> 2.9.5-2160.1 | C16: ='SAF 011'!E23 -> DESCARTADORES DE AGUJAS; BOCA: 1, CAPACIDAD: 500 AGUJAS, MODELO: 500, MODELO EQUIPO: 500, SISTEMA DE CIERRE: 500 | H16: NO | I16: ='SAF 011'!F23 -> UNIDAD | J16: ='SAF 011'!L23 -> 195 | K16: ='SAF 011'!I23 -> 200
A17: 6 | B17: ='SAF 011'!B29 -> 2.9.5-1909.77 | C17: ='SAF 011'!E29 -> GUANTES USO MEDICINAL; TIPO: DESCARTABLE, TAMAÑO: CHICO, MATERIAL: LATEX, PRESENTACION: ENVASE X 100 UN | H17: SI | I17: ='SAF 011'!F29 -> CAJA | J17: ='SAF 011'!L29 -> 590 | K17: ='SAF 011'!I29 -> 50
A18: 7 | B18: ='SAF 011'!B30 -> 2.9.5-1909.81 | C18: ='SAF 011'!E30 -> GUANTES USO MEDICINAL; TIPO: DESCARTABLE, TAMAÑO: GRANDE, MATERIAL: LATEX, PRESENTACION: ENVASE X 100 UNID. | H18: SI | I18: ='SAF 011'!F30 -> CAJA | J18: ='SAF 011'!L30 -> 590 | K18: ='SAF 011'!I30 -> 50
A19: 8 | B19: ='SAF 011'!B31 -> 2.9.5-1909.87 | C19: ='SAF 011'!E31 -> GUANTES USO MEDICINAL; TIPO: DESCARTABLE, TAMAÑO: MEDIANO, MATERIAL: LATEX, PRESENTACION: ENVASE X 100 UNID. | H19: SI | I19: ='SAF 011'!F31 -> CAJA | J19: ='SAF 011'!L31 -> 590 | K19: ='SAF 011'!I31 -> 50
A20: 9 | B20: ='SAF 011'!B48 -> 2.9.5-2578.17 | C20: ='SAF 011'!E48 -> MICROPIPETAS REGULABLES; CAPACIDAD: 100 - 1000 µL, DIVISIONES: CADA 5 µL, MATERIAL: PLASTICO | H20: SI | I20: ='SAF 011'!F48 -> CAJA | J20: ='SAF 011'!L48 -> 50350 | K20: ='SAF 011'!I48 -> 2
A21: 10 | B21: ='SAF 011'!B49 -> 2.9.5-2578.16 | C21: ='SAF 011'!E49 -> MICROPIPETAS REGULABLES; CAPACIDAD: 10-100 µL, DIVISIONES: CADA 1 µL, MATERIAL: PLASTICO | H21: SI | I21: ='SAF 011'!F49 -> CAJA | J21: ='SAF 011'!L49 -> 50350 | K21: ='SAF 011'!I49 -> 2
A22: 11 | B22: ='SAF 011'!B60 -> 2.9.5-6786.6 | C22: ='SAF 011'!E60 -> PLACAS DE TOQUE; MATERIAL: VIDRIO, LARGO: 8 Cm, ANCHO: 6 Cm, ESPESOR: 5 mm, USO: DETERMINACION VDRL | H22: SI | I22: ='SAF 011'!F60 -> UNIDAD | J22: ='SAF 011'!L60 -> 1220 | K22: ='SAF 011'!I60 -> 5
A23: 12 | B23: ='SAF 011'!B65 -> 2.9.6-8875.293 | C23: ='SAF 011'!E65 -> REP. Y ACC P/ EQUIPO MEDICO; USO: PARA EQUIPO DE AFERESIS, MARCA DE EQUIPO: GRIFOLS, ELEMENTO: KITS PARA PLAQUETOFERESIS CON FILTRO CAJA X 8 UNID; EQUIPO: HAEMONETICS CS+ | H23: SI | I23: ='SAF 011'!F65 -> CAJA | J23: ='SAF 011'!L65 -> 41019 | K23: ='SAF 011'!I65 -> 48
A24: 13 | B24: ='SAF 011'!B66 -> 2.9.6-8875.294 | C24: ='SAF 011'!E66 -> REP. Y ACC P/ EQUIPO MEDICO; USO: PARA EQUIPO DE AFERESIS, MARCA DE EQUIPO: GRIFOLS, ELEMENTO: KITS PARA PLASMAFERESIS CON FILTRO CAJA X 8UNID, EQUIPO: HAEMONETIC CS+ | H24: SI | I24: ='SAF 011'!F66 -> CAJA | J24: ='SAF 011'!L66 -> 35090 | K24: ='SAF 011'!I66 -> 24
A25: 14 | B25: ='SAF 011'!B67 -> 2.9.6-8875.295 | C25: ='SAF 011'!E67 -> REP. Y ACC. P/ EQUIPO MEDICO, USO: BAÑO TERMOSTATIZADO PARA TARJETAS DE INMUNOHEMATOLOGIA, MARCA EQUIPO: GRIFOLS, ELEMENTO:TARJETA DE GEL ABO RH 2D, EQUIPO: CENTRIFUGA | H25: SI | I25: ='SAF 011'!F67 -> UNIDAD | J25: ='SAF 011'!L67 -> 590 | K25: ='SAF 011'!I67 -> 1500
A26: 15 | B26: ='SAF 011'!B68 -> 2.9.6-8875.292 | C26: ='SAF 011'!E68 -> REP. Y ACC. P/ EQUIPO MEDICO; USO: FRACCIONADOR AUTOMATICO HEMODERIVADOS, MARCA EQUIPO: GRIFOLS, ELEMENTO: CONEXIÓN POR RADIO FRECUENCIA Y GR, MODELO DE EQUIPO: FRACTIOMATIC PLUS 2 | H26: SI | I26: ='SAF 011'!F68 -> UNIDAD | J26: ='SAF 011'!L68 -> 3950 | K26: ='SAF 011'!I68 -> 900
A27: 16 | B27: ='SAF 011'!B72 -> 2.9.5-931.3 | C27: ='SAF 011'!E72 -> TELAS ADHESIVAS; ANCHO: 5.00 Cm, LONG.DE CUERPO: 9 M, TIPO: HIPOALERGENICA | H27: SI | I27: ='SAF 011'!F72 -> CAJA | J27: ='SAF 011'!L72 -> 1661 | K27: ='SAF 011'!I72 -> 5
A28: 17 | B28: ='SAF 011'!B77 -> 2.9.5-3492.343 | C28: ='SAF 011'!E77 -> TIP; TIPO: TIPS AMARILLO CON CORONA, PRESENTACION: X 1000 UNID., CAPACIDAD:0,2 ML | H28: NO | I28: ='SAF 011'!F77 -> BOLSA | J28: ='SAF 011'!L77 -> 1540 | K28: ='SAF 011'!I77 -> 2
A29: 18 | B29: ='SAF 011'!B78 -> 2.9.5-3492.341 | C29: ='SAF 011'!E78 -> TIP; TIPO: TIPS AMARILLO SIN CORONA,PRESENTACION: X 1000 UNID., CAPACIDAD:0,2 ML | H29: NO | I29: ='SAF 011'!F78 -> BOLSA | J29: ='SAF 011'!L78 -> 1540 | K29: ='SAF 011'!I78 -> 2
A30: 19 | B30: ='SAF 011'!B79 -> 2.9.5-3492.342 | C30: ='SAF 011'!E79 -> TIP; TIPO: TIPS AZUL AUTOCLAVABLE,PRESENTACION: X 1000 UNID., CAPACIDAD: 1000 MICROLITROS | H30: NO | I30: ='SAF 011'!F79 -> BOLSA | J30: ='SAF 011'!L79 -> 2204 | K30: ='SAF 011'!I79 -> 2
A31: 20 | B31: ='SAF 011'!B85 -> 2.9.5-468.232 | C31: ='SAF 011'!E85 -> TUBOS DE ENSAYO; TIPO: CONICO P/CENTRIFUGA, MATERIAL: POLIPROPILENO, DIMENSION: 0,5 A 15 mL, ACCESORIO: TAPA A ROSCA | H31: SI | I31: ='SAF 011'!F85 -> CAJA | J31: ='SAF 011'!L85 -> 13700 | K31: ='SAF 011'!I85 -> 2
A32: 21 | B32: ='SAF 011'!B86 -> 2.9.5-468.42 | C32: ='SAF 011'!E86 -> TUBOS DE ENSAYO; TIPO: EPPENDORF, MATERIAL: PLASTICO, DIMENSION: 1.5 mL, ACCESORIOS: SIN, ACCESORIO: SIN | H32: SI | I32: ='SAF 011'!F86 -> BOLSA | J32: ='SAF 011'!L86 -> 3558 | K32: ='SAF 011'!I86 -> 10
A33: 22 | B33: ='SAF 011'!B87 -> 2.9.5-468.249 | C33: ='SAF 011'!E87 -> TUBOS DE ENSAYO; TIPO: VACUTAINER P/ SUERO, MATERIAL: PLASTICO, DIMENSION: 4 ML, ACCESORIO: SIN | H33: SI | I33: ='SAF 011'!F87 -> CAJA | J33: ='SAF 011'!L87 -> 13700 | K33: ='SAF 011'!I87 -> 2
A34: 23 | B34: ='SAF 011'!B88 -> 2.9.5-468.85 | C34: ='SAF 011'!E88 -> TUBOS DE ENSAYO; TIPO: VACUTAINER, MATERIAL: VIDRIO BOROSILICATO, DIMENSION: 10 mL, ACCESORIOS: TAPA, ACCESORIO: TAPA | H34: SI | I34: ='SAF 011'!F88 -> CAJA | J34: ='SAF 011'!L88 -> 13000 | K34: ='SAF 011'!I88 -> 2
A35: 24 | B35: ='SAF 011'!B89 -> 2.9.5-4522.1 | C35: ='SAF 011'!E89 -> TUBOS DE HEMOLISIS; MATERIAL: VIDRIO, PRESENTACION: CAJA, DIMENSION: 100 X 13 DIAM. EXT., MEDIDAS: 100 X 13 DIAM. EXT., FORMA DE PRESENTACION: SOLIDO, ESTADO: SOLIDO | H35: SI | I35: ='SAF 011'!F89 -> CAJA | J35: ='SAF 011'!L89 -> 72000 | K35: ='SAF 011'!I89 -> 1
A36: Costo total estimado: PESOS DIEZ MILLONES SEIS MIL CIENTO CINCUENTA Y CINCO CON 00/100.- | J36: =SUMPRODUCT(J12:J35,K12:K35) -> 10006155 | Q36: =SUM(M36:P36) -> 0

Sheet APG BANCO DE SANGRE
A1: EJERCICIO: | D1: 2022 | P1: AUTORIZACION PARA GASTAR
A4: JURISDICCIÓN: | G4: ='NP BANCO DE SANGRE'!D3 -> 040 - MINISTERIO DE SALUD
A5: SAF: | G5: ='NP BANCO DE SANGRE'!D4 -> 011 - DIRECCION PROVINCIAL DE ADMINISTRACION - MINISTERIO DE SALUD
A6: UNIDAD EJECUTORA: | G6: ='NP BANCO DE SANGRE'!D5 -> 747 - DIRECCION PROVINCIAL BANCO DE SANGRE
A7: DEPENDENCIA SOLICITANTE: | G7: ='NP BANCO DE SANGRE'!D6 -> 747 - DIRECCION PROVINCIAL BANCO DE SANGRE
A8: AUTORIZACIÓN:
A9: Señor Director de Administración o Titular del Servicio Administrativo Financiero:
A10: Autorizo la realización de los trámites correspondientes, a fin de proveer a este Organismo los bienes que se detallan en Nota de Pedido N°....... , afectando la erogación resultante a los créditos presupuestarios aprobados a favor de esta Unidad Ejecutora, conforme al siguiente detalle:
A12: IMPUTACIÓN PRESUPUESTARIA
A13: CÓDIGO | O13: DENOMINACIÓN DE LA PARTIDA PRESUPUESTARIA | Q13: IMPORTE
A14: PR | B14: SB | C14: PY | D14: AC | E14: OB | F14: UG | G14: FIN | H14: FUN | I14: I | J14: P | K14: P | L14: SubP | M14: M | N14: FF
A15: 27 | D15: 1 | F15: 4901 | G15: 3 | H15: 1 | I15: 2 | J15: 9 | K15: 5 | M15: 1 | N15: 1.1 | O15: UTILES MENORES MEDICOS, QUIRURGICOS Y DE LABORATORIO | Q15: ='NP BANCO DE SANGRE'!J36 -> 10006155
A38: TOTAL DE PESOS: DIEZ MILLONES SEIS MIL CIENTO CINCUENTA Y CINCO CON 00/100.- | Q38: =SUM(Q15:Q37) -> 10006155
A40: JUSTIFICACIÓN:
A41: ='NP BANCO DE SANGRE'!D8 -> ADQUISICION DEL RUBRO INSUMOS PARA LABORATORIO
