Workbook

Sheet Necesidades Trimestrales
B2: Pedido de Necesidades Trimestrales
A4: JURISDICCION: | C4: 12 -Ministerio de Gobierno, Justicia y Derechos Humanos.
A5: SAF N°: | C5: 06 - Secretaria de Gestion Administrativa del Ministerio de Gobierno, Justicia y Derechos Humanos
A6: EJERCICIO: | C6: 2022
A7: TRIMESTRE: | C7: 2do. TRIMESTRE
A9: ID | B9: CODIGO ITEM | C9: RUBRO DE COMPRA | D9: I.P.P. | E9: DESCRIPCION | F9: UNIDAD DE MEDIDA | G9: CANTIDAD | H9: PRECIO UNITARIO ESTIMADO | I9: IMPORTE TOTAL ESTIMADO
A10: 1 | B10: 2.1.1-541.122 | C10: ALIMENTOS | D10: 2.1.1. | E10: CARNES; CORTE: CHORIZO CONGELADO, TIPO: VACUNA, ESPECIE: VACUNA | F10: KG | G10: 30 | H10: 600 | I10: =G10*H10 -> 18000
A11: 2 | B11: 2.1.1-541.45 | C11: ALIMENTOS | D11: 2.1.1. | E11: CARNES; CORTE: HIGADO, ESPECIE: VACUNA, TIPO: VACUNA | F11: KG | G11: 60 | H11: 300 | I11: =G11*H11 -> 18000
A12: 3 | B12: 2.1.1-541.49 | C12: ALIMENTOS | D12: 2.1.1. | E12: CARNES; ESPECIE: VACUNA, CORTE: NALGA, TIPO: VACUNA | F12: KG | G12: 90 | H12: 1200 | I12: =G12*H12 -> 108000
A13: 4 | B13: 2.1.1-541.34 | C13: ALIMENTOS | D13: 2.1.1. | E13: CARNES; CORTE: OSOBUCO, TIPO: VACUNA, ESPECIE: VACUNA | F13: KG | G13: 90 | H13: 500 | I13: =G13*H13 -> 45000
A14: 5 | B14: 2.1.1-541.70 | C14: ALIMENTOS | D14: 2.1.1. | E14: CARNES; CORTE: CARRE CON LOMO, TIPO: PORCINA, ESPECIE: PORCINA | F14: KG | G14: 90 | H14: 900 | I14: =G14*H14 -> 81000
A15: 6 | B15: 2.1.1-621.13 | C15: ALIMENTOS | D15: 2.1.1. | E15: AVES; ESPECIE: POLLO, PRESENTACION: CAJON X 8 UN, EVISCERADO: SIN VALOR, TIPO: POLLO | F15: CAJON | G15: 6 | H15: 4500 | I15: =G15*H15 -> 27000
A16: 7 | B16: 2.1.1-2116.2 | C16: ALIMENTOS | D16: 2.1.1. | E16: LEVADURAS; TIPO: DE CERVEZA, PRESENTACION: PAQUETE, PESO: 1 Kg | F16: UNIDAD | G16: 8 | H16: 300 | I16: =G16*H16 -> 2400
A17: 8 | B17: 2.1.1-969.82 | C17: ALIMENTOS | D17: 2.1.1. | E17: FIAMBRES; TIPO: JAMON COCIDO, PRESENTACION: AL PESO | F17: KG | G17: 15 | H17: 760 | I17: =G17*H17 -> 11400
A18: 9 | B18: 2.1.1-542.236 | C18: ALIMENTOS | D18: 2.1.1. | E18: QUESOS; TIPO: CREMOSO, PRESENTACION: AL PESO, ELEM. TRANSPORTE: SIN, MATERIAL ELEM. TRANSPORTE: SIN, MATERIAL ENVASE: SIN, CERTIFICADO FORESTAL (GFS): SIN, LIBRE DE GLUTEN: A DEFINIR | F18: KG | G18: 12 | H18: 700 | I18: =G18*H18 -> 8400
A19: 10 | B19: 2.1.1-542.197 | C19: ALIMENTOS | D19: 2.1.1. | E19: QUESOS; TIPO: TYBO, PRESENTACION: HORMA, ELEM. TRANSPORTE: SIN, MATERIAL ELEM. TRANSPORTE: SIN, MATERIAL ENVASE: PLASTICO, CERTIFICADO FORESTAL (GFS): SIN, LIBRE DE GLUTEN: NO | F19: KG | G19: 18 | H19: 3800 | I19: =G19*H19 -> 68400
A20: 11 | B20: 2.1.1-6539.30 | C20: ALIMENTOS | D20: 2.1.1. | E20: FRUTAS; VARIEDAD: BANANA, PRESENTACION: CAJON, ESTADO: NATURAL, PESO: SIN VALOR | F20: KG | G20: 70 | H20: 270 | I20: =G20*H20 -> 18900
A21: 12 | B21: 2.1.1-6539.20 | C21: ALIMENTOS | D21: 2.1.1. | E21: FRUTAS; ESTADO: NATURAL, VARIEDAD: MANZANA RED DELICIOSA, PRESENTACION: CAJON, PESO: SIN VALOR | F21: KG | G21: 50 | H21: 290 | I21: =G21*H21 -> 14500
... A42: 33 | B42: 2.1.1-707.38 | C42: ALIMENTOS | D42: 2.1.1. | E42: PASTAS FRESCAS; VARIEDAD: RAVIOL, RELLENO: VERDURA Y POLLO, PRESENTACION: ENVASE X 500 GR | F42: UNIDAD | G42: 21 | H42: 300 | I42: =G42*H42 -> 6300
B45: Especificidades de los Items:
B46: ÍTEM N° 6: CAJON DE 22 Kg.
B47: ITEM N° 16: 30 UNIDADES = 1 CARTON.
B48: ITEM N° 17: ATADO DE 400 Gr.
B49: ÍTEM N° 18: TAMAÑO GRANDE.
B51: Plazos y lugares de entrega:
B52: a) LUGAR DE ENTREGA: Hogar de Protección Integral de Victimas de Violencia de Género "WARMI"- Pasaje Dr Gallo S/N frente a la Guardia de Maternidad Provincial - Capital - De 08 a 12 horas. b)FORMA DE ENTREGA: Las entregas se realizarán a requerimiento de acuerdo, a las Solicitudes de Provisión que se realicen, libre de flete, acarreo y embalaje, como así también, de todo riesgo de pérdida o destrucción total o parcial, por causas ajenas a la Institución. Se estima emitir una cantidad aproximada de 3 (Tres) Solicitudes de Provisión de 1/3 aprox. de la cantidad solicitada, en un plazo de 3 (Tres) meses: 1° Solic.de Provisión: aprox.a los 3 (Tres) dias hábiles de la firma del instrumento contractual. 2° Solic.de Provisión: al mes de la firma del instrumento contractual. Y 3° Solic.de Provisión: a los 2 (Dos) meses de la firma del instrumento contractual. Plazo de cumplimiento de cada Solicitud de Provisión: a los 2 días hábiles de notificada la misma, según necesidades del Organismo solicitante.
B53: Calidad Minima esperada:
B54: Que cumpla con lo solicitado y condiciones de calidad adjuntas, productos de muy buena calidad.-
B55: Mantenimiento:
B56: 30 (treinta) días habiles
B57: Forma de Pago:
B58: Se solicita Pagos parciales por cada Solicitud de Provision emitida, una vez finalizada la entrega de las cantidades contenidas en la misma.

Sheet  NotaPedido
A1: NOTA DE PEDIDO
F2: N° | G2: 23/2022
A4: JURISDICCIÓN: | C4: ='Necesidades Trimestrales'!C4 -> 12 -Ministerio de Gobierno, Justicia y Derechos Humanos.
A5: SAF: | C5: ='Necesidades Trimestrales'!C5 -> 06 - Secretaria de Gestion Administrativa del Ministerio de Gobierno, Justicia y Derechos Humanos
A6: UNIDAD EJECUTORA: | C6: Ministerio de Gobierno, Justicia y Derechos Humanos.
A7: DEPENDENCIA SOLICITANTE: | C7: Atención Integral de Víctimas de violencia de Género (HOGAR WARMI).
A8: PERIODO UTILIZACIÓN: | C8: 2022 - 2do Trimestre
A9: OBJETO: | C9: ADQ. DE ALIMENTOS PERECEDEROS PARA EL HOGAR DE PROTECCION INTEGRAL DE VICTIMAS DE VIOLENCIA DE GENERO (HOGAR WARMI).
A11: Ítem | B11: Codigo Item | C11: DESCRIPCIÓN | D11: Adjunta Detalle Técnico | E11: Unidad Medida | F11: Precio Unitario Estimado | G11: Cantidad Solicitada
A13: ='Necesidades Trimestrales'!A10 -> 1 | B13: ='Necesidades Trimestrales'!B10 -> 2.1.1-541.122 | C13: ='Necesidades Trimestrales'!E10 -> CARNES; CORTE: CHORIZO CONGELADO, TIPO: VACUNA, ESPECIE: VACUNA | D13: NO | E13: ='Necesidades Trimestrales'!F10 -> KG | F13: ='Necesidades Trimestrales'!H10 -> 600 | G13: ='Necesidades Trimestrales'!G10 -> 30
A14: ='Necesidades Trimestrales'!A11 -> 2 | B14: ='Necesidades Trimestrales'!B11 -> 2.1.1-541.45 | C14: ='Necesidades Trimestrales'!E11 -> CARNES; CORTE: HIGADO, ESPECIE: VACUNA, TIPO: VACUNA | D14: NO | E14: ='Necesidades Trimestrales'!F11 -> KG | F14: ='Necesidades Trimestrales'!H11 -> 300 | G14: ='Necesidades Trimestrales'!G11 -> 60
A15: ='Necesidades Trimestrales'!A12 -> 3 | B15: ='Necesidades Trimestrales'!B12 -> 2.1.1-541.49 | C15: ='Necesidades Trimestrales'!E12 -> CARNES; ESPECIE: VACUNA, CORTE: NALGA, TIPO: VACUNA | D15: NO | E15: ='Necesidades Trimestrales'!F12 -> KG | F15: ='Necesidades Trimestrales'!H12 -> 1200 | G15: ='Necesidades Trimestrales'!G12 -> 90
A16: ='Necesidades Trimestrales'!A13 -> 4 | B16: ='Necesidades Trimestrales'!B13 -> 2.1.1-541.34 | C16: ='Necesidades Trimestrales'!E13 -> CARNES; CORTE: OSOBUCO, TIPO: VACUNA, ESPECIE: VACUNA | D16: NO | E16: ='Necesidades Trimestrales'!F13 -> KG | F16: ='Necesidades Trimestrales'!H13 -> 500 | G16: ='Necesidades Trimestrales'!G13 -> 90
A17: ='Necesidades Trimestrales'!A14 -> 5 | B17: ='Necesidades Trimestrales'!B14 -> 2.1.1-541.70 | C17: ='Necesidades Trimestrales'!E14 -> CARNES; CORTE: CARRE CON LOMO, TIPO: PORCINA, ESPECIE: PORCINA | D17: NO | E17: ='Necesidades Trimestrales'!F14 -> KG | F17: ='Necesidades Trimestrales'!H14 -> 900 | G17: ='Necesidades Trimestrales'!G14 -> 90
A18: ='Necesidades Trimestrales'!A15 -> 6 | B18: ='Necesidades Trimestrales'!B15 -> 2.1.1-621.13 | C18: ='Necesidades Trimestrales'!E15 -> AVES; ESPECIE: POLLO, PRESENTACION: CAJON X 8 UN, EVISCERADO: SIN VALOR, TIPO: POLLO | D18: NO | E18: ='Necesidades Trimestrales'!F15 -> CAJON | F18: ='Necesidades Trimestrales'!H15 -> 4500 | G18: ='Necesidades Trimestrales'!G15 -> 6
A19: ='Necesidades Trimestrales'!A16 -> 7 | B19: ='Necesidades Trimestrales'!B16 -> 2.1.1-2116.2 | C19: ='Necesidades Trimestrales'!E16 -> LEVADURAS; TIPO: DE CERVEZA, PRESENTACION: PAQUETE, PESO: 1 Kg | D19: NO | E19: ='Necesidades Trimestrales'!F16 -> UNIDAD | F19: ='Necesidades Trimestrales'!H16 -> 300 | G19: ='Necesidades Trimestrales'!G16 -> 8
A20: ='Necesidades Trimestrales'!A17 -> 8 | B20: ='Necesidades Trimestrales'!B17 -> 2.1.1-969.82 | C20: ='Necesidades Trimestrales'!E17 -> FIAMBRES; TIPO: JAMON COCIDO, PRESENTACION: AL PESO | D20: NO | E20: ='Necesidades Trimestrales'!F17 -> KG | F20: ='Necesidades Trimestrales'!H17 -> 760 | G20: ='Necesidades Trimestrales'!G17 -> 15
A21: ='Necesidades Trimestrales'!A18 -> 9 | B21: ='Necesidades Trimestrales'!B18 -> 2.1.1-542.236 | C21: ='Necesidades Trimestrales'!E18 -> QUESOS; TIPO: CREMOSO, PRESENTACION: AL PESO, ELEM. TRANSPORTE: SIN, MATERIAL ELEM. TRANSPORTE: SIN, MATERIAL ENVASE: SIN, CERTIFICADO FORESTAL (GFS): SIN, LIBRE DE GLUTEN: A DEFINIR | D21: NO | E21: ='Necesidades Trimestrales'!F18 -> KG | F21: ='Necesidades Trimestrales'!H18 -> 700 | G21: ='Necesidades Trimestrales'!G18 -> 12
A22: ='Necesidades Trimestrales'!A19 -> 10 | B22: ='Necesidades Trimestrales'!B19 -> 2.1.1-542.197 | C22: ='Necesidades Trimestrales'!E19 -> QUESOS; TIPO: TYBO, PRESENTACION: HORMA, ELEM. TRANSPORTE: SIN, MATERIAL ELEM. TRANSPORTE: SIN, MATERIAL ENVASE: PLASTICO, CERTIFICADO FORESTAL (GFS): SIN, LIBRE DE GLUTEN: NO | D22: NO | E22: ='Necesidades Trimestrales'!F19 -> KG | F22: ='Necesidades Trimestrales'!H19 -> 3800 | G22: ='Necesidades Trimestrales'!G19 -> 18
A23: ='Necesidades Trimestrales'!A20 -> 11 | B23: ='Necesidades Trimestrales'!B20 -> 2.1.1-6539.30 | C23: ='Necesidades Trimestrales'!E20 -> FRUTAS; VARIEDAD: BANANA, PRESENTACION: CAJON, ESTADO: NATURAL, PESO: SIN VALOR | D23: NO | E23: ='Necesidades Trimestrales'!F20 -> KG | F23: ='Necesidades Trimestrales'!H20 -> 270 | G23: ='Necesidades Trimestrales'!G20 -> 70
A24: ='Necesidades Trimestrales'!A21 -> 12 | B24: ='Necesidades Trimestrales'!B21 -> 2.1.1-6539.20 | C24: ='Necesidades Trimestrales'!E21 -> FRUTAS; ESTADO: NATURAL, VARIEDAD: MANZANA RED DELICIOSA, PRESENTACION: CAJON, PESO: SIN VALOR | D24: NO | E24: ='Necesidades Trimestrales'!F21 -> KG | F24: ='Necesidades Trimestrales'!H21 -> 290 | G24: ='Necesidades Trimestrales'!G21 -> 50
... A45: ='Necesidades Trimestrales'!A42 -> 33 | B45: ='Necesidades Trimestrales'!B42 -> 2.1.1-707.38 | C45: ='Necesidades Trimestrales'!E42 -> PASTAS FRESCAS; VARIEDAD: RAVIOL, RELLENO: VERDURA Y POLLO, PRESENTACION: ENVASE X 500 GR | D45: NO | E45: ='Necesidades Trimestrales'!F42 -> UNIDAD | F45: ='Necesidades Trimestrales'!H42 -> 300 | G45: ='Necesidades Trimestrales'!G42 -> 21
A46: Costo total estimado: Pesos Seiscientos noventa y un mil, Trescientos diez con 00/100.- | F46: =SUMPRODUCT(F13:F45*G13:G45) -> 691310

Sheet APG
A1: EJERCICIO: | D1: ='Necesidades Trimestrales'!C6 -> 2022 | P1: AUTORIZACION PARA GASTAR
A4: JURISDICCIÓN: | G4: =' NotaPedido'!C4 -> 12 -Ministerio de Gobierno, Justicia y Derechos Humanos.
A5: SAF: | G5: =' NotaPedido'!C5 -> 06 - Secretaria de Gestion Administrativa del Ministerio de Gobierno, Justicia y Derechos Humanos
A6: UNIDAD EJECUTORA: | G6: =' NotaPedido'!C6 -> Ministerio de Gobierno, Justicia y Derechos Humanos.
A7: DEPENDENCIA SOLICITANTE: | G7: =' NotaPedido'!C7 -> Atención Integral de Víctimas de violencia de Género (HOGAR WARMI).
A8: AUTORIZACIÓN:
A9: Señor Jefe de Servicio Administrativo Financiero:
A10: ="Autorizo la realización de los trámites correspondientes, a fin de proveer a este Organismo los bienes y/o servicios que se detallan en Nota de Pedido N° " & ' NotaPedido'!G2&", afectando la erogación resultante a los créditos presupuestarios aprobados a favor de esta Unidad Ejecutora, conforme al siguiente detalle:" -> Autorizo la realización de los trámites correspondientes, a fin de proveer a este Organismo los bienes y/o servicios que se detallan en Nota de Pedido N° 23/2022, afectando la erogación resultante a los créditos presupuestarios aprobados a favor de esta Unidad Ejecutora, conforme al siguiente detalle:
A12: IMPUTACIÓN PRESUPUESTARIA
A13: CÓDIGO | O13: DENOMINACIÓN DE LA PARTIDA PRESUPUESTARIA | Q13: IMPORTE
A14: PR | B14: SB | C14: PY | D14: AC | E14: OB | F14: UG | G14: FIN | H14: FUN | I14: I | J14: P | K14: P | L14: SubP | M14: M | N14: FF
A15: 9 | B15: 0 | C15: 0 | D15: 1 | E15: 0 | F15: 4901 | G15: 3 | H15: 2 | I15: 2 | J15: 1 | K15: 1 | L15: 0 | M15: 1 | N15: 1.1 | O15: Alimentos para personas | Q15: =' NotaPedido'!F46 -> 691310
A20: TOTAL DE PESOS: Seiscientos noventa y un mil, Trescientos diez con 00/100.- | Q20: =SUM(Q15:Q19) -> 691310
A22: JUSTIFICACIÓN:
A23: =' NotaPedido'!C9 -> ADQ. DE ALIMENTOS PERECEDEROS PARA EL HOGAR DE PROTECCION INTEGRAL DE VICTIMAS DE VIOLENCIA DE GENERO (HOGAR WARMI).
A25: OBSERVACIONES:
