Workbook

Sheet Necesidades Trimestrales
B2: Pedido de Necesidades Trimestrales
A4: JURISDICCION: | C4: 040 - Ministerio de Salud
A5: SAF N°: | C5: 024 - Hospital Interzonal de Niños
A6: EJERCICIO: | C6: 2022
A7: TRIMESTRE: | C7: 2
A9: ITEM | B9: CODIGO ITEM | C9: RUBRO DE COMPRA | D9: I.P.P. | E9: DESCRIPCION | F9: UNIDAD DE MEDIDA | G9: CANTIDAD | H9: PRECIO UNITARIO ESTIMADO | I9: IMPORTE TOTAL ESTIMADO
A10: 1 | C10: PROD. MEDICO/ FARMACEUTICOS/LAB | D10: 251 | E10: ACIDOS; COMPUESTO QUIMICO: AC. CITRICO, ESTADO: SOLIDO, CALIDAD: BIOLOGIA MOLECULAR, CONCENTRACION/PUREZA: 99,99 %, PRESENTACION: ENVASE X 1 Kg | F10: unidad | G10: 1 | H10: 6300 | I10: =+G10*H10 -> 6300
A11: 2 | C11: PROD. MEDICO/ FARMACEUTICOS/LAB | D11: 295 | E11: BANDEJA PARA HEMOFILTRACION PEDIATRICA – HEMOFILTRO D150 | F11: unidad | G11: 10 | H11: 34000 | I11: =+G11*H11 -> 340000
A12: 3 | C12: PROD. MEDICO/ FARMACEUTICOS/LAB | D12: 295 | E12: Bobina Baja Densidad 30 X 40 rollo x 200 un. Tipo Mapsa | F12: unidad | G12: 5 | H12: 800 | I12: =+G12*H12 -> 4000
A13: 4 | C13: PROD. MEDICO/ FARMACEUTICOS/LAB | D13: 295 | E13: CATETER DOBLE J 4.7 FR x 26 CM TIPO COOK | F13: unidad | G13: 1 | H13: 12500 | I13: =+G13*H13 -> 12500
A14: 5 | C14: PROD. MEDICO/ FARMACEUTICOS/LAB | D14: 295 | E14: CATETER DOBLE J 7 FRENCH X 26 CM TIPO COOK | F14: unidad | G14: 1 | H14: 12500 | I14: =+G14*H14 -> 12500
A15: 6 | C15: PROD. MEDICO/ FARMACEUTICOS/LAB | D15: 295 | E15: CATETERES/SONDAS; NUMERO: SIN, TIPO: TUBO DE LUKEN PARA TOMA DE MUESTRAS | F15: unidad | G15: 5 | H15: 980 | I15: =+G15*H15 -> 4900
A16: 7 | C16: PROD. MEDICO/ FARMACEUTICOS/LAB | D16: 295 | E16: LUPAS; POTENCIA: 75 Diop, DIAMETRO: 65 mm, MATERIAL LENTE: VIDRIO, ACCESORIO: C/LUZ, ARMAZON: PLASTICO, ESTRUCTURA: PLASTICO | F16: unidad | G16: 1 | H16: 6500 | I16: =+G16*H16 -> 6500
A17: 8 | C17: PROD. MEDICO/ FARMACEUTICOS/LAB | D17: 295 | E17: MALLA ABSORBIBLE POLIGLICOLICO 30 X 30 TIPO VICRYL | F17: unidad | G17: 5 | H17: 36970 | I17: =+G17*H17 -> 184850
A18: 9 | C18: PROD. MEDICO/ FARMACEUTICOS/LAB | D18: 234 | E18: PAPEL PARA ELECTROCARDIOGRAFO PAGE WRITER TRIM RESMA TIPO PHILIPS 210 MM X 300 MM X 100 HOJAS | F18: resma | G18: 5 | H18: 1580 | I18: =+G18*H18 -> 7900
A19: 10 | C19: PROD. MEDICO/ FARMACEUTICOS/LAB | D19: 252 | E19: PASTA CONDUCTORA PARA ELECTRODOS X 226 GRS | F19: unidad | G19: 40 | H19: 6300 | I19: =+G19*H19 -> 252000
A20: 11 | C20: PROD. MEDICO/ FARMACEUTICOS/LAB | D20: 252 | E20: PASTA CONDUCTORA PARA ELECTRODOS X 400 GRS | F20: unidad | G20: 20 | H20: 12000 | I20: =+G20*H20 -> 240000
A21: 12 | C21: PROD. MEDICO/ FARMACEUTICOS/LAB | D21: 259 | E21: ROLLO EN PAPEL TERMICO ORIGINALES 57 mm. X 20 mts | F21: rollo | G21: 24 | H21: 90 | I21: =+G21*H21 -> 2160
... A26: 17 | C26: PROD. MEDICO/ FARMACEUTICOS/LAB | D26: 295 | E26: TROCAR D/PUNCION ASP.D/MEDULA OSEA PEDIATRICO T/GA X 10 UNIDADES | F26: caja | G26: 1 | H26: 27000 | I26: =+G26*H26 -> 27000
B29: Plazos y lugares de entrega
B30: Lugar de Entrega: SERVICIO DE FARMACIA -HOSPITAL INT. DE NIÑOS – AV. VIRGEN DEL VALLE N° 1050-CATAMARCA DE 8:00 A 12:00HS., DEBIENDO CORRER LOS GASTOS DE FLETES, ACARREO, CARGA, DESCARGA Y SEGURO A CARGO DEL ADJUDICATARIO.
B32: Plazo de entrega: Dentro de los diez (10) días habiles de notificada la Orden de Compra
B33: Mantenimiento de Oferta: Cuarenta y Cinco (45) dias habiles.
B34: Forma de Pago: Treinta (30) dias habiles.

Sheet  NotaPedido
A1: NOTA DE PEDIDO | J1: N° | K1: 052/2022
A3: JURISDICCIÓN: | D3: ='Necesidades Trimestrales'!C4 -> 040 - Ministerio de Salud
A4: SAF: | D4: ='Necesidades Trimestrales'!C5 -> 024 - Hospital Interzonal de Niños
A5: UNIDAD EJECUTORA: | D5: 024 - Hospital Interzonal de Niños
A6: DEPENDENCIA SOLICITANTE: | D6: Farmacia
A7: PERIODO UTILIZACIÓN: | D7: 2 TRIMESTRE
A8: OBJETO: | D8: Adquisición de Descartables
A10: Ítem | B10: Codigo Item | C10: DESCRIPCIÓN | H10: Adjunta Detalle Técnico | I10: Unidad Medida | J10: Precio Unitario Estimado | K10: Cantidad Solicitada
A12: 1 | C12: =+'Necesidades Trimestrales'!E10 -> ACIDOS; COMPUESTO QUIMICO: AC. CITRICO, ESTADO: SOLIDO, CALIDAD: BIOLOGIA MOLECULAR, CONCENTRACION/PUREZA: 99,99 %, PRESENTACION: ENVASE X 1 Kg | H12: NO | I12: =+'Necesidades Trimestrales'!F10 -> unidad | J12: =+'Necesidades Trimestrales'!H10 -> 6300 | K12: ='Necesidades Trimestrales'!G10 -> 1
A13: 2 | C13: =+'Necesidades Trimestrales'!E11 -> BANDEJA PARA HEMOFILTRACION PEDIATRICA – HEMOFILTRO D150 | H13: NO | I13: =+'Necesidades Trimestrales'!F11 -> unidad | J13: =+'Necesidades Trimestrales'!H11 -> 34000 | K13: ='Necesidades Trimestrales'!G11 -> 10
A14: 3 | C14: =+'Necesidades Trimestrales'!E12 -> Bobina Baja Densidad 30 X 40 rollo x 200 un. Tipo Mapsa | H14: NO | I14: =+'Necesidades Trimestrales'!F12 -> unidad | J14: =+'Necesidades Trimestrales'!H12 -> 800 | K14: ='Necesidades Trimestrales'!G12 -> 5
A15: 4 | C15: =+'Necesidades Trimestrales'!E13 -> CATETER DOBLE J 4.7 FR x 26 CM TIPO COOK | H15: NO | I15: =+'Necesidades Trimestrales'!F13 -> unidad | J15: =+'Necesidades Trimestrales'!H13 -> 12500 | K15: ='Necesidades Trimestrales'!G13 -> 1
A16: 5 | C16: =+'Necesidades Trimestrales'!E14 -> CATETER DOBLE J 7 FRENCH X 26 CM TIPO COOK | H16: NO | I16: =+'Necesidades Trimestrales'!F14 -> unidad | J16: =+'Necesidades Trimestrales'!H14 -> 12500 | K16: ='Necesidades Trimestrales'!G14 -> 1
A17: 6 | C17: =+'Necesidades Trimestrales'!E15 -> CATETERES/SONDAS; NUMERO: SIN, TIPO: TUBO DE LUKEN PARA TOMA DE MUESTRAS | H17: NO | I17: =+'Necesidades Trimestrales'!F15 -> unidad | J17: =+'Necesidades Trimestrales'!H15 -> 980 | K17: ='Necesidades Trimestrales'!G15 -> 5
A18: 7 | C18: =+'Necesidades Trimestrales'!E16 -> LUPAS; POTENCIA: 75 Diop, DIAMETRO: 65 mm, MATERIAL LENTE: VIDRIO, ACCESORIO: C/LUZ, ARMAZON: PLASTICO, ESTRUCTURA: PLASTICO | H18: NO | I18: =+'Necesidades Trimestrales'!F16 -> unidad | J18: =+'Necesidades Trimestrales'!H16 -> 6500 | K18: ='Necesidades Trimestrales'!G16 -> 1
A19: 8 | C19: =+'Necesidades Trimestrales'!E17 -> MALLA ABSORBIBLE POLIGLICOLICO 30 X 30 TIPO VICRYL | H19: NO | I19: =+'Necesidades Trimestrales'!F17 -> unidad | J19: =+'Necesidades Trimestrales'!H17 -> 36970 | K19: ='Necesidades Trimestrales'!G17 -> 5
A20: 9 | C20: =+'Necesidades Trimestrales'!E18 -> PAPEL PARA ELECTROCARDIOGRAFO PAGE WRITER TRIM RESMA TIPO PHILIPS 210 MM X 300 MM X 100 HOJAS | H20: NO | I20: =+'Necesidades Trimestrales'!F18 -> resma | J20: =+'Necesidades Trimestrales'!H18 -> 1580 | K20: ='Necesidades Trimestrales'!G18 -> 5
A21: 10 | C21: =+'Necesidades Trimestrales'!E19 -> PASTA CONDUCTORA PARA ELECTRODOS X 226 GRS | H21: NO | I21: =+'Necesidades Trimestrales'!F19 -> unidad | J21: =+'Necesidades Trimestrales'!H19 -> 6300 | K21: ='Necesidades Trimestrales'!G19 -> 40
A22: 11 | C22: =+'Necesidades Trimestrales'!E20 -> PASTA CONDUCTORA PARA ELECTRODOS X 400 GRS | H22: NO | I22: =+'Necesidades Trimestrales'!F20 -> unidad | J22: =+'Necesidades Trimestrales'!H20 -> 12000 | K22: ='Necesidades Trimestrales'!G20 -> 20
A23: 12 | C23: =+'Necesidades Trimestrales'!E21 -> ROLLO EN PAPEL TERMICO ORIGINALES 57 mm. X 20 mts | H23: NO | I23: =+'Necesidades Trimestrales'!F21 -> rollo | J23: =+'Necesidades Trimestrales'!H21 -> 90 | K23: ='Necesidades Trimestrales'!G21 -> 24
... A28: 17 | C28: =+'Necesidades Trimestrales'!E26 -> TROCAR D/PUNCION ASP.D/MEDULA OSEA PEDIATRICO T/GA X 10 UNIDADES | H28: NO | I28: =+'Necesidades Trimestrales'!F26 -> caja | J28: =+'Necesidades Trimestrales'!H26 -> 27000 | K28: ='Necesidades Trimestrales'!G26 -> 1
A29: Costo total estimado: Un Millon Doscientos Diecisiete Mil Novecientos Diez con 00/100. | J29: =SUMPRODUCT(J12:J28,K12:K28) -> 1217910

Sheet Autor Gastar
A1: EJERCICIO: | D1: ='Necesidades Trimestrales'!C6 -> 2022 | P1: AUTORIZACION PARA GASTAR
A4: JURISDICCIÓN: | G4: =' NotaPedido'!D3 -> 040 - Ministerio de Salud
A5: SAF: | G5: =' NotaPedido'!D4 -> 024 - Hospital Interzonal de Niños
A6: UNIDAD EJECUTORA: | G6: =' NotaPedido'!D5 -> 024 - Hospital Interzonal de Niños
A7: DEPENDENCIA SOLICITANTE: | G7: =' NotaPedido'!D6 -> Farmacia
A8: AUTORIZACIÓN:
A9: Señor Jefe de Servicio Administrativo Financiero:
A10: ="Autorizo la realización de los trámites correspondientes, a fin de proveer a este Organismo los bienes y/o servicios que se detallan en Nota de Pedido N° " & ' NotaPedido'!K1&", afectando la erogación resultante a los créditos presupuestarios aprobados a favor de esta Unidad Ejecutora, conforme al siguiente detalle:" -> Autorizo la realización de los trámites correspondientes, a fin de proveer a este Organismo los bienes y/o servicios que se detallan en Nota de Pedido N° 052/2022, afectando la erogación resultante a los créditos presupuestarios aprobados a favor de esta Unidad Ejecutora, conforme al siguiente detalle:
A12: IMPUTACIÓN PRESUPUESTARIA
A13: CÓDIGO | O13: DENOMINACIÓN DE LA PARTIDA PRESUPUESTARIA | Q13: IMPORTE
A14: PR | B14: SB | C14: PY | D14: AC | E14: OB | F14: UG | G14: FIN | H14: FUN | I14: I | J14: P | K14: P | L14: SubP | M14: M | N14: FF
A15: 36 | D15: 1 | F15: 4901 | G15: 3 | H15: 310 | I15: 2 | J15: 3 | K15: 4 | M15: 1 | N15: 1.1 | O15: Productos de Papel y Carton | Q15: 7900
A16: 36 | D16: 1 | F16: 4901 | G16: 3 | H16: 310 | I16: 2 | J16: 5 | K16: 1 | M16: 1 | N16: 1.1 | O16: Compuestos Quimicos | Q16: 6300
A17: 36 | D17: 1 | F17: 4901 | G17: 3 | H17: 310 | I17: 2 | J17: 5 | K17: 2 | M17: 1 | N17: 1.1 | O17: Productos Farmaceuticos y Medicinales | Q17: 492000
A18: 36 | D18: 1 | F18: 4901 | G18: 3 | H18: 310 | I18: 2 | J18: 5 | K18: 9 | M18: 1 | N18: 1.1 | O18: Otros No Especificados Precedentemente | Q18: 2160
A19: 36 | D19: 1 | F19: 4901 | G19: 3 | H19: 310 | I19: 2 | J19: 9 | K19: 5 | M19: 1 | N19: 1.1 | O19: Utiles Menores Medico, Quirurgico y de Laboratorio | Q19: 709550
A22: TOTAL DE PESOS: UN MILLON DOSCIENTOS DIECISIETE MIL NOVECIENTOS DIEZ CON 00/100. | Q22: =SUM(Q15:Q21) -> 1217910
A24: JUSTIFICACIÓN:
A25: Para la adquisición de items desiertos y fracasados de descartables del 1º trimestre 2022, destinados al servico de Farmacia del Hospital Interzonal de Niños.
