Workbook

Sheet Necesidades Trimestrales
B2: Pedido de Necesidades Trimestrales
A4: JURISDICCION: | C4: 90 - Ministerio de Seguridad
A5: SAF N°: | C5: 7 - Direccion Provincial de Administracion de la Policia de Catamarca
A6: EJERCICIO: | C6: 2020
A7: TRIMESTRE: | C7: 4
A9: ID | B9: CODIGO ITEM | C9: RUBRO DE COMPRA | D9: I.P.P. | E9: DESCRIPCION | F9: UNIDAD DE MEDIDA | G9: CANTIDAD | H9: PRECIO UNITARIO ESTIMADO | I9: IMPORTE TOTAL ESTIMADO
A10: 1 | B10: 3.5.4-2065.1 | C10: BANCOS Y SEGUROS | D10: =LEFT(B10,5) -> 3.5.4 | E10: SEGURO DE RESPONSABILIDAD; DESCRIPCION: SEGURO DE RESPONSABILIDAD | F10: UNIDAD | G10: =70+141 -> 211 | I10: =SUM(1567676+178060) -> 1745736
B13: Especificidades Item N° 1:
B15: Descripción técnica
C16: CARACTERÍSTICAS: “Seguro Obligatorio de Responsabilidad Civil del Automotor conforme Res. SSN N° 35.863, 36.100 y modificatorias. Responsabilidad Civil con límites, en la República Argentina y países limítrofes: por lesiones y/o muerte y daños a cosas de terceros no transportados por acontecimientos hasta la suma de pesos 6.000.000,00. Extensión a países limítrofes sin cargo” de 212 vehiculos que integran el Parque Automotor Policial, cuyos datos se detallan en Anexo. VIGENCIA: desde el 30/12/2020 al 30/12/2021.
B17: Plazos y lugares de entrega
C18: a) LUGAR DE ENTREGA: SECCION CONTROL PATRIMONIAL (Dpto Logística), sito en Chacabuco N° 809 - Capital - De 08 a 12 horas. b) FORMA DE LA ENTREGA: Las Pólizas deben entregarse detallando el vehículo que está cubriendo el seguro contratado. c) PLAZO DE ENTREGA: El Oferente deberá establecer plazo de entrega de los elementos cotizados, debiendo ser expresado en días hábiles; que no podrá ser superior a cinco (5) días hábiles, contados a partir de la recepción de la comunicación prevista en el Artículo 80° de del Reglamento Parcial N° 2 de la ley 4938.
B20: Calidad Minima esperada
C21: Que cumpla íntegramente con lo solicitado y se extienda a todo y cada uno de los vehiculos desagregados en la planilla anexa a la presente.
B22: Mantenimiento
C23: 30 (treinta) días
B24: Garantia

Sheet  NotaPedido
A1: NOTA DE PEDIDO | J1: N° | K1: 90/2020
A3: JURISDICCIÓN: | D3: ='Necesidades Trimestrales'!C4 -> 90 - Ministerio de Seguridad
A4: SAF: | D4: ='Necesidades Trimestrales'!C5 -> 7 - Direccion Provincial de Administracion de la Policia de Catamarca
A5: UNIDAD EJECUTORA: | D5: Jefatura de Policía de la Provincia de Catamarca
A6: DEPENDENCIA SOLICITANTE: | D6: Sección Control Patrimonial - Dpto. Logistica (D-4)
A7: PERIODO UTILIZACIÓN: | D7: ='Necesidades Trimestrales'!C7 & "° Trimestre - Año " & 'Necesidades Trimestrales'!C6 -> 4° Trimestre - Año 2020
A8: OBJETO:
A10: Ítem | B10: Codigo Item | C10: DESCRIPCIÓN | H10: Adjunta Detalle Técnico | I10: Unidad Medida | J10: Precio Unitario Estimado | K10: Cantidad Solicitada
A12: 1 | B12: ='Necesidades Trimestrales'!B10 -> 3.5.4-2065.1 | C12: ='Necesidades Trimestrales'!E10 -> SEGURO DE RESPONSABILIDAD; DESCRIPCION: SEGURO DE RESPONSABILIDAD | H12: SI | I12: ='Necesidades Trimestrales'!F10 -> UNIDAD | J12: ='Necesidades Trimestrales'!H10 -> 0 | K12: ='Necesidades Trimestrales'!G10 -> 211
A13: 2
A14: 3
A15: 4
A16: 5
A17: Costo total estimado: Un Millon Setecientos Cuarenta y Cinco Mil Setecientos Treinta y Seis con 00/100 | J17: ='Necesidades Trimestrales'!I10 -> 1745736

Sheet Autor Gastar
A1: EJERCICIO: | D1: ='Necesidades Trimestrales'!C6 -> 2020 | P1: AUTORIZACION PARA GASTAR
A4: JURISDICCIÓN: | G4: =' NotaPedido'!D3 -> 90 - Ministerio de Seguridad
A5: SAF: | G5: =' NotaPedido'!D4 -> 7 - Direccion Provincial de Administracion de la Policia de Catamarca
A6: UNIDAD EJECUTORA: | G6: =' NotaPedido'!D5 -> Jefatura de Policía de la Provincia de Catamarca
A7: DEPENDENCIA SOLICITANTE: | G7: =' NotaPedido'!D6 -> Sección Control Patrimonial - Dpto. Logistica (D-4)
A8: AUTORIZACIÓN:
A9: Señor Jefe de Servicio Administrativo Financiero:
A10: ="Autorizo la realización de los trámites correspondientes, a fin de proveer a este Organismo los bienes y/o servicios que se detallan en Nota de Pedido N° " & ' NotaPedido'!K1&", afectando la erogación resultante a los créditos presupuestarios aprobados a favor de esta Unidad Ejecutora, conforme al siguiente detalle:" -> Autorizo la realización de los trámites correspondientes, a fin de proveer a este Organismo los bienes y/o servicios que se detallan en Nota de Pedido N° 90/2020, afectando la erogación resultante a los créditos presupuestarios aprobados a favor de esta Unidad Ejecutora, conforme al siguiente detalle:
A12: IMPUTACIÓN PRESUPUESTARIA
A13: CÓDIGO | O13: DENOMINACIÓN DE LA PARTIDA PRESUPUESTARIA | Q13: IMPORTE
A14: PR | B14: SB | C14: PY | D14: AC | E14: OB | F14: UG | G14: FIN | H14: FUN | I14: I | J14: P | K14: P | L14: SubP | M14: M | N14: FF
A15: 16 | B15: 0 | C15: 0 | D15: 1 | E15: 0 | F15: 10 | G15: 2 | H15: 210 | I15: =LEFT('Necesidades Trimestrales'!D10,1) -> 3 | J15: =MID('Necesidades Trimestrales'!D10,3,1) -> 5 | K15: =RIGHT('Necesidades Trimestrales'!D10,1) -> 4 | L15: 0 | M15: 1 | N15: 1.1 | O15: PRIMAS Y GASTOS DE SEGUROS | Q15: ='Necesidades Trimestrales'!I10 -> 1745736
A23: TOTAL DE PESOS: Un Millon Setecientos Cuarenta y Cinco Mil Setecientos Treinta y Seis con 00/100 | Q23: =SUM(Q15:Q22) -> 1745736
A25: JUSTIFICACIÓN:
A26: Para la adquisición de Seguro Obligatorio de Responsabilidad Civil del Automotor para los vehiculos pertenecientes a la Institucion Policial.-

Sheet Planilla Tecnica
A1: AUTOMOVILES
A2: Nº | B2: TIPO | C2: DOMINIO | D2: MARCA | E2: MOD. | F2: MOTOR | G2: CHASIS
A3: 1 | B3: AUTO | C3: OSL-109 | D3: TOYOTA ETIOS X 1,5 M/T 5P | E3: 2015 | F3: 2NRV274614 | G3: 9BRK29BT3F0055994
A4: 2 | B4: AUTO | C4: EUE-056 | D4: VW POLO | E4: 2005 | F4: 1Y958444 | G4: 8AWZZZ9EZ5A688395
A5: 3 | B5: AUTO | C5: HKX-868 | D5: VW POLO | E5: 2008 | F5: UVC038611 | G5: 8AWZZZ9EZ9A002754
A6: 4 | B6: AUTO | C6: HKX-869 | D6: VW POLO | E6: 2008 | F6: UVC038558 | G6: 8AWZZZ9EZ9A002872
A7: 5 | B7: AUTO | C7: KSV-199 | D7: FIAT SIENA | E7: 2011 | F7: 178F4055 2176328 | G7: 8AP17269HC 2241027
A8: 6 | B8: AUTO | C8: LYY-007 | D8: CHEVROLET CORSA -SPIRIT LT 1.4 | E8: 2012 | F8: T85148700 | G8: 8AGSE1950DR180215
A9: 7 | B9: AUTO | C9: LYY-053 | D9: CHEVROLET PRISMA 1,4LS | E9: 2013 | F9: T70034459 | G9: 9BGRG6950CG401440
A10: 8 | B10: AUTO | C10: HKX-841 | D10: CHEVR. CORSA | E10: 2008 | F10: 7H5145376 | G10: 8AGSB19N09R102420
A11: 9 | B11: AUTO | C11: NHS 501 | D11: TOYOTA COROLLA | E11: 2013 | F11: 2ZRM175001 | G11: 9BRBU48E4778689
A12: 10 | B12: AUTO | C12: PHO-195 | D12: FIAT PALIO ATTRACTIVE 1,4 | E12: 2015 | F12: 327A0552366431 | G12: 8AP196475F4124427
A13: 11 | B13: AUTO | C13: PHO-196 | D13: FIAT PALIO ATTRACTIVE 1,4 | E13: 2015 | F13: 327A0552346624 | G13: 8AP196475F4123099
A14: 12 | B14: AUTO | C14: AB 322 SC | D14: TOYOTA ETIOS X 1,5 M/T 5P | E14: 2017 | F14: 2NR4073730 | G14: 9BRK29BT9H0111908
A15: 13 | B15: AUTO | C15: MXR-597 | D15: CHEVROLET CORSA -SPIRIT LT 1.4 | E15: 2013 | F15: T85170468 | G15: 8AGSC1950ER113641
A16: CAMIONETAS
A17: Nº | B17: TIPO | C17: DOMINIO | D17: MARCA | E17: MOD. | F17: MOTOR | G17: CHASIS
A18: 14 | B18: CAMIONETA | C18: LZR-302 | D18: TOYOTA HILUX 4X2 SR 3.0 TDI | E18: 2012 | F18: 1KD-5931120 | G18: 8AJEZ32G4D1012111
A19: 15 | B19: CAMIONETA | C19: NQS-933 | D19: TOYOTA HILUX 4X2 D/C PACK DX 2,5 TDI | E19: 2013 | F19: 2KD-A106134 | G19: 8AJFR22G9D4566063
A20: 16 | B20: CAMIONETA | C20: OYW-526 | D20: TOYOTA HILUX 4X2 D/C PACK DX 2,5 TDI | E20: 2015 | F20: 2KD-A789175 | G20: 8AJER32G3F4057901
A21: 17 | B21: CAMIONETA | C21: OYW-527 | D21: TOYOTA HILUX 4X2 D/C PACK DX 2,5 TDI | E21: 2015 | F21: 2KD-A786575 | G21: 8AJER32G0F4057855
A22: 18 | B22: CAMIONETA | C22: OYW-528 | D22: TOYOTA HILUX 4X2 D/C PACK DX 2,5 TDI | E22: 2015 | F22: 2KD-A786461 | G22: 8AJER32G0F4057855
A23: 19 | B23: CAMIONETA | C23: OYW-530 | D23: TOYOTA HILUX 4X2 D/C PACK DX 2,5 TDI | E23: 2015 | F23: 2KD-A790442 | G23: 8AJER32G8F4057909
A24: 20 | B24: CAMIONETA | C24: OYW-531 | D24: TOYOTA HILUX 4X2 D/C PACK DX 2,5 TDI | E24: 2015 | F24: 2KD-A791057 | G24: 8AJER32G5F4057804
A25: 21 | B25: CAMIONETA | C25: FGD-109 | D25: CHEVROLET S-10 STD 4X2 | E25: 2005 | F25: 40704214298 | G25: 9BG138AC05C425603
A26: 22 | B26: CAMIONETA | C26: FGJ-769 | D26: CHEVROLET S-10 STD 4X2 | E26: 2005 | F26: 40704214142 | G26: 9BG138AC05C425904
A27: 23 | B27: CAMIONETA | C27: LJT-997 | D27: TOYOTA HILUX 4X2 D/C PACK DX 2,5 TDI | E27: 2012 | F27: 2KD-5647509 | G27: 8AJER32G1C4041563
A28: 24 | B28: CAMIONETA | C28: FHM-882 | D28: CHEVROLET S-10 STD 4X2 | E28: 2005 | F28: M1T239064 | G28: 9BG138BC06C406383
A29: 25 | B29: CAMIONETA | C29: FGD-110 | D29: CHEVROLET S-10 STD 4X2 | E29: 2005 | F29: 40704214140 | G29: 9BG138AC05C425771
A30: CAMIONETAS
A31: Nº | B31: TIPO | C31: DOMINIO | D31: MARCA | E31: MOD. | F31: MOTOR | G31: CHASIS
A32: 26 | B32: CAMIONETA | C32: OZB-152 | D32: TOYOTA HILUX 4X4 SR 3.0 TDI | E32: 2015 | F32: 2KD-A797676 | G32: 8AJFR22G7F4580238
A33: 27 | B33: CAMIONETA | C33: OZB-153 | D33: TOYOTA HILUX 4X4 SR 3.0 TDI | E33: 2015 | F33: 2KD-A799562 | G33: 8AJFR22G7F4580272
A34: 28 | B34: CAMIONETA | C34: OUL-117 | D34: TOYOTA HILUX 4X2 D/C PACK DX 2,5 TDI | E34: 2015 | F34: 1KD-A7366258 | G34: 8AJEZ32G9F1017162
A35: 29 | B35: CAMIONETA | C35: PCN-063 | D35: TOYOTA HILUX 4X2 D/C PACK DX 2,5 TDI | E35: 2015 | F35: 2KD-A824596 | G35: 8AJER32G2F4059204
A36: 30 | B36: CAMIONETA | C36: PCN-064 | D36: TOYOTA HILUX 4X2 D/C PACK DX 2,5 TDI | E36: 2015 | F36: 2KD-A824348 | G36: 8AJER32G9F4059183
A37: 31 | B37: CAMIONETA | C37: PCN-065 | D37: TOYOTA HILUX 4X2 D/C PACK DX 2,5 TDI | E37: 2015 | F37: 2KD-A823692 | G37: 8AJER32G9F4059149
A38: 32 | B38: CAMIONETA | C38: PCN-066 | D38: TOYOTA HILUX 4X2 D/C PACK DX 2,5 TDI | E38: 2015 | F38: 2KD-A824560 | G38: 8AJER32G6F4059187
A39: 33 | B39: CAMIONETA | C39: PEB-293 | D39: TOYOTA HILUX 4X2 D/C PACK DX 2,5 TDI | E39: 2015 | F39: 2KD-A835061 | G39: 8AJER32G5F4059567
A40: 34 | B40: CAMIONETA | C40: PEG-687 | D40: TOYOTA HILUX 4X2 D/C PACK DX 2,5 TDI | E40: 2015 | F40: 2KD-A839103 | G40: 8AJER32G0F4059587
A41: 35 | B41: CAMIONETA | C41: PIO-390 | D41: VOLKSWAGEN AMAROK 4X2 STARTLINE 2,0 | E41: 2015 | F41: CNF059596 | G41: 8AWDD42H3GA002810
A42: 36 | B42: CAMIONETA | C42: PIO-392 | D42: VOLKSWAGEN AMAROK 4X2 STARTLINE 2,0 | E42: 2015 | F42: CNF059822 | G42: 8AWDD42H7GA003328
A43: 37 | B43: CAMIONETA | C43: PIO-394 | D43: VOLKSWAGEN AMAROK 4X2 STARTLINE 2,0 | E43: 2015 | F43: CNF060763 | G43: 8AWDD42H1GA007889
A44: 38 | B44: CAMIONETA | C44: PIO-395 | D44: VOLKSWAGEN AMAROK 4X2 STARTLINE 2,0 | E44: 2015 | F44: CNF059474 | G44: 8AWDD42H1GA003230
A45: 39 | B45: CAMIONETA | C45: PIO-396 | D45: VOLKSWAGEN AMAROK 4X2 STARTLINE 2,0 | E45: 2015 | F45: CNF057857 | G45: 8AWDD42H5GA0033361
A46: 40 | B46: CAMIONETA | C46: PIO-397 | D46: VOLKSWAGEN AMAROK 4X2 STARTLINE 2,0 | E46: 2015 | F46: CNF060775 | G46: 8AWDD42H2GA007058
A47: 41 | B47: CAMIONETA | C47: PIO-398 | D47: VOLKSWAGEN AMAROK 4X2 STARTLINE 2,0 | E47: 2015 | F47: CNF057854 | G47: 8AWDD42HXGA003369
A48: 42 | B48: CAMIONETA | C48: PIO-399 | D48: VOLKSWAGEN AMAROK 4X2 STARTLINE 2,0 | E48: 2015 | F48: CNF059685 | G48: 8AWDD42H8GA003323
A49: 43 | B49: CAMIONETA | C49: PIO-400 | D49: VOLKSWAGEN AMAROK 4X2 STARTLINE 2,0 | E49: 2015 | F49: CNF59918 | G49: 8AWDD42H3GA009160
A50: 44 | B50: CAMIONETA | C50: PIO-401 | D50: VOLKSWAGEN AMAROK 4X2 STARTLINE 2,0 | E50: 2015 | F50: CNF060074 | G50: 8AWDD42H4GA009085
A51: 45 | B51: CAMIONETA | C51: PIO-402 | D51: VOLKSWAGEN AMAROK 4X2 STARTLINE 2,0 | E51: 2015 | F51: CNF059698 | G51: 8AWDD42H7GA003314
A52: 46 | B52: CAMIONETA | C52: PIO-403 | D52: VOLKSWAGEN AMAROK 4X2 STARTLINE 2,0 | E52: 2015 | F52: CNF059606 | G52: 8AWDD42H7GA003524
A53: 47 | B53: CAMIONETA | C53: PIO-404 | D53: VOLKSWAGEN AMAROK 4X2 STARTLINE 2,0 | E53: 2015 | F53: CNF057850 | G53: 8AWDD42H6GA003367
A54: 48 | B54: CAMIONETA | C54: PIO-405 | D54: VOLKSWAGEN AMAROK 4X2 STARTLINE 2,0 | E54: 2015 | F54: CNF058298 | G54: 8AWDD42H7GA003149
A55: 49 | B55: CAMIONETA | C55: PIO-406 | D55: VOLKSWAGEN AMAROK 4X2 STARTLINE 2,0 | E55: 2015 | F55: CNF059329 | G55: 8AWDD42H0GA003509
A56: 50 | B56: CAMIONETA | C56: PIO-407 | D56: VOLKSWAGEN AMAROK 4X2 STARTLINE 2,0 | E56: 2015 | F56: CNF059334 | G56: 8AWDD42HXGA003484
... A59: 53 | B59: CAMIONETA | C59: PIO-417 | D59: VOLKSWAGEN AMAROK 4X2 STARTLINE 2,0 | E59: 2015 | F59: CNF060226 | G59: 8AWDD42H9GA003265
A60: CAMIONETAS
A61: Nº | B61: TIPO | C61: DOMINIO | D61: MARCA | E61: MOD. | F61: MOTOR | G61: CHASIS
A62: 54 | B62: CAMIONETA | C62: PIO-418 | D62: VOLKSWAGEN AMAROK 4X2 STARTLINE 2,0 | E62: 2015 | F62: CNF059606 | G62: 8AWDD42H9GA003217
A63: 55 | B63: CAMIONETA | C63: PIO-419 | D63: VOLKSWAGEN AMAROK 4X2 STARTLINE 2,0 | E63: 2015 | F63: CNF060978 | G63: 8AWDD42H7GA007069
A64: 56 | B64: CAMIONETA | C64: PIQ-540 | D64: VOLKSWAGEN AMAROK 4X2 STARTLINE 2,0 | E64: 2015 | F64: CNF060489 | G64: 8AWDD42H6GA006642
A65: 57 | B65: CAMIONETA | C65: PIQ-541 | D65: VOLKSWAGEN AMAROK 4X2 STARTLINE 2,0 | E65: 2015 | F65: CNF059421 | G65: 8AWDD42H2GA008775
A66: 58 | B66: CAMIONETA | C66: PIQ-542 | D66: VOLKSWAGEN AMAROK 4X2 STARTLINE 2,0 | E66: 2015 | F66: CNF060183 | G66: 8AWDD42H5GA007880
A67: 59 | B67: CAMIONETA | C67: PIQ-543 | D67: VOLKSWAGEN AMAROK 4X2 STARTLINE 2,0 | E67: 2015 | F67: CNF059829 | G67: 8AWDD42H2GA003334
A68: 60 | B68: CAMIONETA | C68: PIQ-545 | D68: VOLKSWAGEN AMAROK 4X2 STARTLINE 2,0 | E68: 2015 | F68: CNF057846 | G68: 8AWDD42H1GA003387
A69: 61 | B69: CAMIONETA | C69: PIQ-546 | D69: VOLKSWAGEN AMAROK 4X2 STARTLINE 2,0 | E69: 2015 | F69: CNF059510 | G69: 8AWDD42H5GA002825
A70: 62 | B70: CAMIONETA | C70: PIQ-547 | D70: VOLKSWAGEN AMAROK 4X2 STARTLINE 2,0 | E70: 2015 | F70: CNF059663 | G70: 8AWDD42HXGA003288
A71: 63 | B71: CAMIONETA | C71: PIQ-548 | D71: VOLKSWAGEN AMAROK 4X2 STARTLINE 2,0 | E71: 2015 | F71: CNF061376 | G71: 8AWDD42H4GA008812
A72: 64 | B72: CAMIONETA | C72: PIQ-549 | D72: VOLKSWAGEN AMAROK 4X2 STARTLINE 2,0 | E72: 2015 | F72: CNF058381 | G72: 8AWDD42H8GA007050
A73: 65 | B73: CAMIONETA | C73: PIQ-550 | D73: VOLKSWAGEN AMAROK 4X2 STARTLINE 2,0 | E73: 2015 | F73: CNF060051 | G73: 8AWDD42H8GA009090
... A86: 78 | B86: CAMIONETA | C86: PIQ-568 | D86: VOLKSWAGEN AMAROK 4X2 STARTLINE 2,0 | E86: 2015 | F86: CNF059920 | G86: 8AWDD42H1GA008685
A87: 79 | B87: CAMIONETA | C87: PIQ-570 | D87: VOLKSWAGEN AMAROK 4X2 STARTLINE 2,0 | E87: 2015 | F87: CNF059715 | G87: 8AWDD42H2GA003317
A88: 80 | B88: CAMIONETA | C88: PIQ-571 | D88: VOLKSWAGEN AMAROK 4X2 STARTLINE 2,0 | E88: 2015 | F88: CNF059664 | G88: 8AWDD42H2GA003303
A89: 81 | B89: CAMIONETA | C89: PIQ-573 | D89: VOLKSWAGEN AMAROK 4X2 STARTLINE 2,0 | E89: 2015 | F89: CNF059340 | G89: 8AWDD42H8GA002883
A90: CAMIONETAS
A91: Nº | B91: TIPO | C91: DOMINIO | D91: MARCA | E91: MOD. | F91: MOTOR | G91: CHASIS
A92: 82 | B92: CAMIONETA | C92: PIQ-574 | D92: VOLKSWAGEN AMAROK 4X2 STARTLINE 2,0 | E92: 2015 | F92: CNF057855 | G92: 8AWDD42H0GA003364
A93: 83 | B93: CAMIONETA | C93: PIQ-575 | D93: VOLKSWAGEN AMAROK 4X2 STARTLINE 2,0 | E93: 2015 | F93: CNF060279 | G93: 8AWDD42H8GA007176
A94: 84 | B94: CAMIONETA | C94: PIQ-576 | D94: VOLKSWAGEN AMAROK 4X2 STARTLINE 2,0 | E94: 2015 | F94: CNF060696 | G94: 8AWDD42H8GA007128
A95: 85 | B95: CAMIONETA | C95: PHV-803 | D95: TOYOTA HILUX 4X2 D/C PACK DX 2,5 TDI | E95: 2015 | F95: 2KD-A865632 | G95: 8AJER32G4F4061858
A96: 86 | B96: CAMIONETA | C96: AD 922 FA | D96: CHEVROLET S-10 TD 4X2 LS | E96: 2019 | F96: LWNF190981136 | G96: 9BG148CK0LC401712
A97: 87 | B97: CAMIONETA | C97: AD 922 FB | D97: CHEVROLET S-10 TD 4X2 LS | E97: 2019 | F97: LWNF190991037 | G97: 9BG148CK0LC401707
A98: 88 | B98: CAMIONETA | C98: AD 922 FC | D98: CHEVROLET S-10 TD 4X2 LS | E98: 2019 | F98: LWNF190981126 | G98: 9BG148CK0LC401677
A99: 89 | B99: CAMIONETA | C99: AD 922 FD | D99: CHEVROLET S-10 TD 4X2 LS | E99: 2019 | F99: LWNF190851068 | G99: 9BG148CK0LC400227
A100: 90 | B100: CAMIONETA | C100: AD 922 FE | D100: CHEVROLET S-10 TD 4X2 LS | E100: 2019 | F100: LWNF190981178 | G100: 9BG148CK0LC401661
A101: 91 | B101: CAMIONETA | C101: AD 922 FF | D101: CHEVROLET S-10 TD 4X2 LS | E101: 2019 | F101: LWNF190991016 | G101: 9BG148CK0LC401741
A102: 92 | B102: CAMIONETA | C102: AD 922 FG | D102: CHEVROLET S-10 TD 4X2 LS | E102: 2019 | F102: LWNF190981077 | G102: 9BG148CK0LC401672
A103: 93 | B103: CAMIONETA | C103: AD 922 FH | D103: CHEVROLET S-10 TD 4X2 LS | E103: 2019 | F103: LWNF190861066 | G103: 9BG148CK0LC400210
... A109: 99 | B109: CAMIONETA | C109: AD 897 EZ | D109: CHEVROLET S-10 TD 4X2 LS | E109: 2019 | F109: LWNF190981139 | G109: 9BG148CK0LC401739
A110: 100 | B110: CAMIONETA | C110: AE 290 OT | D110: TOYOTA HILUX 4X4 D/C DX 2,4 TDI 6 M/T | E110: 2020 | F110: 2GD-G156129 | G110: 8AJDB3CD2L1302799
A111: 101 | B111: CAMIONETA | C111: AE 290 OU | D111: TOYOTA HILUX 4X4 D/C DX 2,4 TDI 6 M/T | E111: 2020 | F111: 2GD-0743967 | G111: 8AJDB3CD9L1301813
A112: 102 | B112: CAMIONETA | C112: AE 290 OV | D112: TOYOTA HILUX 4X4 D/C DX 2,4 TDI 6 M/T | E112: 2020 | F112: 2GD-0753555 | G112: 8AJDB3CDXL1302145
A113: 103 | B113: CAMIONETA | C113: AE 290 OW | D113: TOYOTA HILUX 4X4 D/C DX 2,4 TDI 6 M/T | E113: 2020 | F113: 2GD-G164416 | G113: 8AJDB3CD9L1303092
A114: 104 | B114: CAMIONETA | C114: AE 290 OX | D114: TOYOTA HILUX 4X4 D/C DX 2,4 TDI 6 M/T | E114: 2020 | F114: 2GD-G156166 | G114: 8AJDB3CD5L1302800
A115: 105 | B115: CAMIONETA | C115: AE 290 OY | D115: TOYOTA HILUX 4X4 D/C DX 2,4 TDI 6 M/T | E115: 2020 | F115: 2GD-G164667 | G115: 8AJDB3CD7L1303110
A116: 106 | B116: CAMIONETA | C116: AE 290 OZ | D116: TOYOTA HILUX 4X4 D/C DX 2,4 TDI 6 M/T | E116: 2020 | F116: 2GD-G163823 | G116: 8AJDB3CD3L1303055
A117: 107 | B117: CAMIONETA | C117: AE 317 XA | D117: TOYOTA HILUX 4X4 D/C DX 2,4 TDI 6 M/T | E117: 2020 | F117: 2GD-G163509 | G117: 8AJDB3CD8L1303035
A118: 108 | B118: CAMIONETA | C118: AE 317 XC | D118: TOYOTA HILUX 4X4 D/C DX 2,4 TDI 6 M/T | E118: 2020 | F118: 2GD-G163505 | G118: 8AJDB3CD6L1303034
A119: 109 | B119: CAMIONETA | C119: AE 317 XD | D119: TOYOTA HILUX 4X4 D/C DX 2,4 TDI 6 M/T | E119: 2020 | F119: 2GD-G164085 | G119: 8AJDB3CD3L1303072
...
