Workbook

Sheet SAF 011
A1: 2022
B2: Pedido de Necesidades Trimestrales
A4: JURISDICCION: | C4: 040 - MINISTERIO DE SALUD
A5: SAF N°: | C5: 011 - DIRECCION PROVINCIAL DE ADMINISTRACION - MINISTERIO DE SALUD
A6: EJERCICIO: | C6: 2022
A7: TRIMESTRE: | C7: PRIMERO
A9: ID | B9: CODIGO ITEM | C9: RUBRO DE COMPRA | D9: I.P.P. | E9: DESCRIPCION | F9: UNIDAD DE MEDIDA | G9: CANTIDAD TOTAL | H9: PRECIO UNITARIO ESTIMADO | I9: IMPORTE TOTAL ESTIMADO | J9: ESPECIFICACION TECNICA
A10: 1 | B10: 2.1.1-2456.8 | C10: ALIMENTOS | D10: 2.1.1 | E10: RACIONAMIENTO; DESCRIPCION: ALMUERZO | F10: RACION | G10: 3060 | H10: 550 | I10: 1683000 | J10: ALMUERZOS: una ración de carne con guarnición y postre: CARNES: carne vacuna, carne de cerdo, pescado y carne de pollo. Deberá proveerse en la semana dos raciones de carne vacuna, dos raciones de carne de cerdo, dos raciones de carne de pescado y una ración de carne de pollo. GUARNICION: ensaladas de verduras variadas alternadas que contengan: tomate, lechuga, repollo, rucula, zapallitos tiernos hervidos, remolacha, huevo duro, zanahoria rallada, entre otros. Además, Puré de papas, papas fritas o papas al horno. POSTRE: una fruta por persona por día: una pera, manzana o banana (mediana). El peso de la ración debe ser no menor a 400 gr. Deben ser entregadas en bandejas plásticas de 18x25x5 cm. Recubiertas de papel film.
A11: 2 | B11: 2.1.1-2456.10 | C11: ALIMENTOS | D11: 2.1.1 | E11: RACIONAMIENTO; DESCRIPCION: CENA | F11: RACION | G11: 3060 | H11: 550 | I11: 1683000 | J11: CENAS: una ración de Pastas: ravioles, ñoquis, fideos tirabuzón, fideos espagueti o sorrentinos, con salsa bolognesa con carne vacuna o pollo, 4 quesos o salsa blanca. Una pasta distinta por día, alternando a su vez las salsas y repitiéndose los sorrentinos o ravioles para completar la semana. POSTRE: una fruta por persona por día: una pera, manzana o banana (mediana). El peso de la ración debe ser no menor a 400 gr. Deben ser entregadas en bandejas plásticas de 18x25x5 cm. Recubiertas de papel film
E12: TOTAL RUBRO ALIMENTOS | I12: 3366000
C15: Especificidades ITEM 1 Y 2 | D15: VER ANEXO I
C17: Cantidad: | D17: UN MIL VEINTE (1020) RACIONES DE ALMUERZOS Y UN MIL VEINTE (1020) RACIONES CENAS CADA TREINTA (30) DIAS.
C19: Duracion del Contrato: | D19: DURANTE 90 (noventa) DIAS CORRIDOS, CON OPCION A PRORROGA POR IGUAL PERIODO.
C21: Plazos de entrega | D21: DENTRO DE LOS 5 (CINCO) DIAS DE LA RECEPCION DEL INSTRUMENTO RESPECTIVO.
C23: Lugar de Entrega: | D23: S.A.M.E. - Caseros N° 864 en la forma y horarios establecidos en ANEXO I.
C25: Forma de Pago: | D25: El pago se realizará en forma mensual dentro de losTREINTA (30) días corridos de la recepciones definitivas.
C27: Calidad Minima esperada | D27: que cumpla con todo lo solicitado en ANEXO I.
C29: Mantenimiento de Oferta | D29: cuarenta y cinco (45) días

Sheet ANEXO I
A1: ANEXO I
A3: ESPECIFICACIONES: ALIMENTOS PARA PERSONAS
A5: Se deberá entregar treinta y cuatro (34) raciones de ALMUERZOS por día y treinta y cuatro (34) raciones de CENAS por día, durante un plazo de 90 (noventa) días corridos en forma continua e ininterrumpida en virtud del Servicio de Atención de Emergencias que presta dicho Organismo (SAME).
A7: Totalizando un mil veinte (1020) raciones por mes de ALMUERZOS y un mil veinte (1020) raciones por mes de CENAS, durante el plazo antes mencionado
A9: ALMUERZOS: una ración de carne con guarnición y postre:
A10: CARNES: carne vacuna, carne de cerdo, pescado y carne de pollo. Deberá proveerse en la semana dos raciones de carne vacuna, dos raciones de carne de cerdo, dos raciones de carne de pescado y una ración de carne de pollo. GUARNICION: ensaladas de verduras variadas alternadas que contengan: tomate, lechuga, repollo, rucula, zapallitos tiernos hervidos, remolacha, huevo duro, zanahoria rallada, entre otros. Además, Puré de papas, papas fritas o papas al horno. POSTRE: una fruta por persona por día: una pera, manzana o banana (mediana). El peso de la ración debe ser no menor a 400 gr. Deben ser entregadas en bandejas plásticas de 18x25x5 cm. Recubiertas de papel film.
A11: ALMUERZOS: HORARIO DE ENTREGA 12:00 HS.
A13: CENAS: una ración de Pastas con salsa y postre:
A14: PASTAS: ravioles, ñoquis, fideos tirabuzón, fideos espagueti o sorrentinos, con salsa bolognesa con carne vacuna o pollo, 4 quesos o salsa blanca. Una pasta distinta por día, alternando a su vez las salsas y repitiéndose los sorrentinos o ravioles para completar la semana. POSTRE: una fruta por persona por día: una pera, manzana o banana (mediana).
A15: CENAS: HORARIO DE ENTREGA 20:00 HS.
A17: El peso de la ración debe ser no menor a 400 gr. Deben ser entregadas en bandejas plásticas de 18x25x5 cm. Recubiertas de papel film, corriendo los gastos de flete, acarreo, carga, descarga y seguro (de corresponder) por cuenta del adjudicatario. Las personas designadas para la recepción de dichas bandejas de alimento son: • Lencina Eugenia - DNI 23854289 • Sánchez Gisella - DNI 26815200 • Toledo María Alejandra - DNI 24843448

Sheet NP
A1: NOTA DE PEDIDO | J1: N° | K1: XX/2022
A3: JURISDICCIÓN: | D3: ='SAF 011'!C4 -> 040 - MINISTERIO DE SALUD
A4: SAF: | D4: ='SAF 011'!C5 -> 011 - DIRECCION PROVINCIAL DE ADMINISTRACION - MINISTERIO DE SALUD
A5: UNIDAD EJECUTORA: | D5: 748 - DIRECCION PROVINCIAL SISTEMA DE ATENCION MEDICA DE EMERGENCIA
A6: DEPENDENCIA SOLICITANTE: | D6: 748 - DIRECCION PROVINCIAL SISTEMA DE ATENCION MEDICA DE EMERGENCIA
A7: PERIODO UTILIZACIÓN: | D7: 3° TRIMESTRE 2022
A8: OBJETO: | D8: ADQUISICION DEL RUBRO ALIMENTOS PARA PERSONAS (RACIONES DE ALMUERZO Y CENA)
A10: Ítem | B10: Codigo Item | C10: DESCRIPCIÓN | H10: Adjunta Detalle Técnico | I10: Unidad Medida | J10: Precio Unitario Estimado | K10: Cantidad Solicitada
A12: 1 | B12: ='SAF 011'!B10 -> 2.1.1-2456.8 | C12: ='SAF 011'!E10 -> RACIONAMIENTO; DESCRIPCION: ALMUERZO | H12: SI | I12: ='SAF 011'!F10 -> RACION | J12: ='SAF 011'!H10 -> 550 | K12: 3060 | M12: =+J12*K12 -> 1683000
A13: 2 | B13: ='SAF 011'!B11 -> 2.1.1-2456.10 | C13: ='SAF 011'!E11 -> RACIONAMIENTO; DESCRIPCION: CENA | H13: SI | I13: ='SAF 011'!F11 -> RACION | J13: ='SAF 011'!H11 -> 550 | K13: 3060 | M13: =+J13*K13 -> 1683000
A15: Costo total estimado: PESOS TRES MILLONES TRESCIENTOS SESENTA Y SEIS MIL CON 00/100.- | J15: =+M15 -> 3366000 | M15: =SUM(M12:M14) -> 3366000

Sheet APG
A1: EJERCICIO: | D1: 2022 | P1: AUTORIZACION PARA GASTAR
A4: JURISDICCIÓN: | G4: =NP!D3 -> 040 - MINISTERIO DE SALUD
A5: SAF: | G5: =NP!D4 -> 011 - DIRECCION PROVINCIAL DE ADMINISTRACION - MINISTERIO DE SALUD
A6: UNIDAD EJECUTORA: | G6: =NP!D5 -> 748 - DIRECCION PROVINCIAL SISTEMA DE ATENCION MEDICA DE EMERGENCIA
A7: DEPENDENCIA SOLICITANTE: | G7: =NP!D6 -> 748 - DIRECCION PROVINCIAL SISTEMA DE ATENCION MEDICA DE EMERGENCIA
A8: AUTORIZACIÓN:
A9: Señor Director de Administración o Titular del Servicio Administrativo Financiero:
A10: Autorizo la realización de los trámites correspondientes, a fin de proveer a este Organismo los bienes/servicios que se detallan en Nota de Pedido N° XX/2022 afectando la erogación resultante a los créditos presupuestarios aprobados a favor de esta Unidad Ejecutora, conforme al siguiente detalle:
A12: IMPUTACIÓN PRESUPUESTARIA
A13: CÓDIGO | O13: DENOMINACIÓN DE LA PARTIDA PRESUPUESTARIA | Q13: IMPORTE
A14: PR | B14: SB | C14: PY | D14: AC | E14: OB | F14: UG | G14: FIN | H14: FUN | I14: I | J14: P | K14: P | L14: SubP | M14: M | N14: FF
A15: 31 | D15: 1 | F15: 4901 | G15: 3 | H15: 1 | I15: 2 | J15: 1 | K15: 1 | M15: 1 | N15: 1.1 | O15: ALIMENTOS PARA PERSONAS | Q15: =NP!M15 -> 3366000
A38: TOTAL DE PESOS: TRES MILLONES TRESCIENTOS SESENTA Y SEIS MIL CON 00/100.- | Q38: =SUM(Q15:Q37) -> 3366000
A40: JUSTIFICACIÓN:
A41: =NP!D8 -> ADQUISICION DEL RUBRO ALIMENTOS PARA PERSONAS (RACIONES DE ALMUERZO Y CENA)
