Workbook

Sheet SAF 011
A1: 2022
B2: Pedido de Necesidades Trimestrales
A4: JURISDICCION: | C4: 040 - MINISTERIO DE SALUD
A5: SAF N°: | C5: 011 - DIRECCION PROVINCIAL DE ADMINISTRACION - MINISTERIO DE SALUD
A6: EJERCICIO: | C6: 2022
A7: TRIMESTRE: | C7: CUARTO
A9: ID | B9: CODIGO ITEM | C9: RUBRO DE COMPRA | D9: I.P.P. | E9: DESCRIPCION | F9: UNIDAD DE MEDIDA | G9: CANTIDAD TOTAL | H9: PRECIO UNITARIO ESTIMADO | I9: IMPORTE TOTAL ESTIMADO | J9: ESPECIFICACION TECNICA
A10: 1 | B10: 2.5.1-9043.2 | C10: QUIMICOS | D10: 2.5.1. | E10: ACEITES Y GRASAS; COMPUESTO QUIMICO: ACEITE DE INMERSION, ESTADO: LIQUIDO, CALIDAD: PRO ANALISIS, CONCENTRACION/PUREZA: 99,9 %, PRESENTACION: ENVASE X 100 mL | F10: FRASCO | G10: 40 | H10: 5017 | I10: 200680 | J10: ACEITE DE INMERSION 100 ML Tipo CICARELLI
A11: 2 | B11: 2.5.1-9017.381 | C11: QUIMICOS | D11: 2.5.1. | E11: ANTICUERPOS P/LABORATORIO; NOMBRE: ANTI-A, ESTADO: LIQUIDO, MARCADO CON: SIN MARCAR, ORIGEN: HUMANO, PRESENTACION: ENVASE X 10 mL, TIPO: MONOCLONAL | F11: FRASCO | G11: 100 | H11: 876 | I11: 87600
A12: 3 | B12: 2.5.1-9017.136 | C12: QUIMICOS | D12: 2.5.1. | E12: ANTICUERPOS P/LABORATORIO; NOMBRE: ANTI-B, ESTADO: SOLUCION, MARCADO CON: SIN MARCAR, ORIGEN: HUMANO, PRESENTACION: ENVASE X 10 mL, TIPO: MONOCLONAL | F12: FRASCO | G12: 100 | H12: 876 | I12: 87600
A13: 4 | B13: 2.5.1-9017.137 | C13: QUIMICOS | D13: 2.5.1. | E13: ANTICUERPOS P/LABORATORIO; NOMBRE: ANTI-D, ESTADO: SOLUCION, MARCADO CON: SIN MARCAR, ORIGEN: HUMANO, PRESENTACION: ENVASE X 10 mL, TIPO: MONOCLONAL | F13: UNIDAD | G13: 100 | H13: 1657 | I13: 165700 | J13: ANTI-D (RHO) MONOCLONAL-FRASCOS 10 ML
A14: 5 | B14: 2.5.1-9007.169 | C14: QUIMICOS | D14: 2.5.1. | E14: COMP. HIDROXILADOS Y ALCOHOLES; COMPUESTO QUIMICO: METANOL, ESTADO: LIQUIDO, CALIDAD: PRO ANALISIS, CONCENTRACION/PUREZA: 98 %, PRESENTACION: ENVASE X 1 L | F14: BOTELLA | G14: 50 | H14: 3980 | I14: 199000 | J14: ALCOHOL METILICO X LITRO Tipo CICARELLI
A15: 6 | B15: 2.5.1-9019.119 | C15: QUIMICOS | D15: 2.5.1. | E15: HIDRATOS DE CARBONO; COMPUESTO QUIMICO: GLUCOCURVE 75 GR, ESTADO: SOLIDO, CALIDAD: PRO ANALISIS, CONCENTRACION/PUREZA: SIN VALOR, PRESENTACION: ENVASE X 10 SOBRES | F15: CAJA | G15: 100 | H15: 1781 | I15: 178100 | J15: GLUCOCURVE SDA 75 GR X 10 SOBRES Tipo GLUCOCURVE
A16: 7 | B16: 2.9.9-3646.23 | C16: PROD. MEDICO/FARMACEUTICOS/LAB | D16: 2.5.1. | E16: INSUMOS P/CONTADOR HEMATOL; TIPO: DETERGENTE, USO: CONTADOR HEMATOLOGICO MINDRAY | F16: BIDON | G16: 15 | H16: 10600 | I16: 159000 | J16: RINSE DETERGENTE X 20 LT Tipo MINDRAY
A17: 8 | B17: 2.9.9-3646.22 | C17: PROD. MEDICO/FARMACEUTICOS/LAB | D17: 2.5.1. | E17: INSUMOS P/CONTADOR HEMATOL; TIPO: DILUYENTE, USO: CONTADOR HEMATOLOGICO MINDRAY | F17: BIDON | G17: 60 | H17: 11200 | I17: 672000 | J17: DILUYENTE 20 LITROS Tipo MINDRAY
A18: 9 | B18: 2.9.9-3646.21 | C18: PROD. MEDICO/FARMACEUTICOS/LAB | D18: 2.5.1. | E18: INSUMOS P/CONTADOR HEMATOL; TIPO: LISANTE, USO: CONTADOR HEMATOLOGICO MINDRAY | F18: BOTELLA | G18: 40 | H18: 17700 | I18: 708000 | J18: LISANTE Tipo MINDRAY X 500 ML
A19: 10 | B19: 2.5.1-9016.223 | C19: QUIMICOS | D19: 2.5.1. | E19: MEDIOS DE CULTIVO Y SUPLEMENTO; NOMBRE DEL PRODUCTO: AGAR DIFERENCIAL ACETATO, ESTADO: SOLIDO, PRESENTACION: ENVASE X 500 GR | F19: FRASCO | G19: 2 | H19: 18017 | I19: 36034 | J19: MEDIO ACETATO DIFERENCIAL AGAR X 500 GR
A20: 11 | B20: 2.5.1-9016.547 | C20: QUIMICOS | D20: 2.5.1. | E20: MEDIOS DE CULTIVO Y SUPLEMENTO; NOMBRE DEL PRODUCTO: AGAR SANGRE C/POLINUTRIENTES, ESTADO: SOLIDO EN PLACA, PRESENTACION: ENVASE X 10 UN | F20: CAJA | G20: 20 | H20: 12000 | I20: 240000 | J20: MEDIO AGAR SANGRE PLACA X 10 UNIDADES Tipo BIOMERIEUX
A21: 12 | B21: 2.5.1-9016.1014 | C21: QUIMICOS | D21: 2.5.1. | E21: MEDIOS DE CULTIVO Y SUPLEMENTO; NOMBRE DEL PRODUCTO: CALDO TODD HEWITT, ESTADO: LIQUIDO, PRESENTACION: 10 FRASCOS X 10 ML | F21: CAJA | G21: 10 | H21: 38000 | I21: 380000 | J21: CALDO TODD HEWITT 10 FRASCOS X 10 ML Tipo BRITANIA
A22: 13 | B22: 2.5.1-9016.1014 | C22: QUIMICOS | D22: 2.5.1. | E22: MEDIOS DE CULTIVO Y SUPLEMENTO; NOMBRE DEL PRODUCTO: CALDO TODD HEWITT, ESTADO: LIQUIDO, PRESENTACION: 10 FRASCOS X 10 ML | F22: CAJA | G22: 30 | H22: 42900 | I22: 1287000 | J22: MEDIO TODD HEWITT CALDO 10X10 ML Tipo BRITANIA
A23: 14 | B23: 2.5.1-9016.89 | C23: QUIMICOS | D23: 2.5.1. | E23: MEDIOS DE CULTIVO Y SUPLEMENTO; NOMBRE DEL PRODUCTO: CALDO TRIPTEINA SOJA, ESTADO: SOLIDO, PRESENTACION: ENVASE X 500 GR | F23: FRASCO | G23: 2 | H23: 11000 | I23: 22000 | J23: MEDIO TRIPTEINA SOYA AGAR 500 GR
A24: 15 | B24: 2.5.1-9016.429 | C24: QUIMICOS | D24: 2.5.1. | E24: MEDIOS DE CULTIVO Y SUPLEMENTO; NOMBRE DEL PRODUCTO: CROMAGAR ESTREPTO B, ESTADO: SOLIDO EN PLACA, PRESENTACION: ENVASE X 20 UN | F24: CAJA | G24: 30 | H24: 15000 | I24: 450000 | J24: MEDIO CHROM ID STREPTO B X 20 PLACAS Tipo BIOMERIEUX
... A37: 28 | B37: 2.5.1-8937.921 | C37: QUIMICOS | D37: 2.5.1. | E37: PATRÓN/ESTANDAR P/CALIBRACIÓN; EQUIPO: CONTADOR HEMATOLÓGICO; MARCA EQUIPO: SYSMEX ROCHE; NOMBRE DEL PRODUCTO: CONTROL P/HEMATOLOGÍA; PRESENTACIÓN: 4 X 2 X 3 ML | F37: UNIDAD | G37: 4 | H37: 116900 | I37: 467600 | J37: CONTROL HEMATOLOGIA XP 300 EIGTCHEK 3WPX-TRA 3X4X2ML Tipo SYSMEX
A38: 29 | B38: 2.5.1-9037.72 | C38: QUIMICOS | D38: 2.5.1. | E38: PROTEINAS; COMPUESTO QUIMICO: ALBUMINA BOVINA, ESTADO: LIQUIDO, CALIDAD: TECNICA MANUAL, CONCENTRACION/PUREZA: 30%, PRESENTACION: ENVASE X 10 ML | F38: UNIDAD | G38: 12 | H38: 1251 | I38: 15012
A39: 30 | B39: 2.5.1-9038.83 | C39: QUIMICOS | D39: 2.5.1. | E39: REACTIVO INDICADOR-COLORANTE; COMPUESTO QUIMICO: COLORACION DE GRAM, ESTADO: SOLUCION, CALIDAD: PRO ANALISIS, PRESENTACION: ENVASE X 100 mL | F39: CAJA | G39: 20 | H39: 3510 | I39: 70200 | J39: COLORACION DE GRAM X 100 ML Tipo BRITANIA
A40: 31 | B40: 2.5.1-9038.342 | C40: QUIMICOS | D40: 2.5.1. | E40: REACTIVO INDICADOR-COLORANTE; COMPUESTO QUIMICO: DECOLORANTE GRAM, ESTADO: SOLUCION, CALIDAD: PRO ANALISIS, PRESENTACION: ENVASE X 500 mL | F40: BOTELLA | G40: 20 | H40: 8600 | I40: 172000 | J40: SOLUCION DECOLORANTE PARA GRAM X 500 MLTipo BRITANIA
A41: 32 | B41: 2.5.1-9038.117 | C41: QUIMICOS | D41: 2.5.1. | E41: REACTIVO INDICADOR-COLORANTE; COMPUESTO QUIMICO: GIEMSA, ESTADO: LIQUIDO, CALIDAD: PRO ANALISIS, PRESENTACION: ENVASE X 1 L | F41: BOTELLA | G41: 60 | H41: 7052 | I41: 423120 | J41: COLORANTE GIEMSA X LITRO Tipo BIOPUR
A42: 33 | B42: 2.5.1-9038.46 | C42: QUIMICOS | D42: 2.5.1. | E42: REACTIVO INDICADOR-COLORANTE; COMPUESTO QUIMICO: MAY GRUNWALD, ESTADO: SOLUCION, CALIDAD: PRO ANALISIS, PRESENTACION: ENVASE X 1 L | F42: BOTELLA | G42: 20 | H42: 6970 | I42: 139400 | J42: COLORANTE MAY GRUNGUAL X 1 LT Tipo CICARELLI
A43: 34 | B43: 2.5.1-9038.228 | C43: QUIMICOS | D43: 2.5.1. | E43: REACTIVO INDICADOR-COLORANTE; COMPUESTO QUIMICO: ZIEL-NIELSEN, ESTADO: SOLUCION, CALIDAD: PRO ANALISIS, PRESENTACION: ENVASE X 100 mL | F43: CAJA | G43: 20 | H43: 3634 | I43: 72680 | J43: COLORACION DE ZIEHL NEELSEN X 100 ML Tipo BRITANIA
A44: 35 | B44: 2.5.1-8988.2507 | C44: QUIMICOS | D44: 2.5.1. | E44: REACTIVOS P/EQUIPO; EQUIPO: AFERESIS, MARCA EQUIPO: HAEMONETICS MCS PLUS, NOMBRE DEL PRODUCTO: SOLUCION ACD FORMULA A ANTI COAGULANTE TIPO RIVERO FENVAL SOLUFLEX 679-S, PRESENTACION: 600ML | F44: UNIDAD | G44: 81 | H44: 4350 | I44: 352350
A45: 36 | B45: 2.5.1-8988.372 | C45: QUIMICOS | D45: 2.5.1. | E45: REACTIVOS P/EQUIPO; EQUIPO: ANALIZ. X ENZIMO-INMUNO-ENSAYO, MARCA EQUIPO: ABBOTT, NOMBRE DEL PRODUCTO: DET. ANTIG. CORE/ANTIC ANTIHCV, PRESENTACION: ENVASE X 96 DETERM. | F45: CAJA | G45: 3 | H45: 50545 | I45: 151635
A46: 37 | B46: 2.5.1-8988.521 | C46: QUIMICOS | D46: 2.5.1. | E46: REACTIVOS P/EQUIPO; EQUIPO: ANALIZADOR DE CREATININA, MARCA EQUIPO: WIENER LAB, NOMBRE DEL PRODUCTO: CREATININA DIRECTA, PRESENTACION: ENVASE X 120 DETERM. | F46: CAJA | G46: 30 | H46: 4693 | I46: 140790 | J46: CREATININA DIRECTA 120 Det TIPO WIENER
A47: 38 | B47: 2.5.1-8988.1224 | C47: QUIMICOS | D47: 2.5.1. | E47: REACTIVOS P/EQUIPO; EQUIPO: ANALIZADOR DE GASES EN SANGRE, MARCA EQUIPO: OPTIMEDICAL, NOMBRE DEL PRODUCTO: MEDICION DE PH PO2 PCO2, PRESENTACION: UNIDAD | F47: CAJA | G47: 24 | H47: 100000 | I47: 2400000 | J47: CASSETTE MEDICION DE PH PO2 PCO2 X25 DET. "E-CL" OSMETECH OPTI CCA, Tipo OPTIMEDICAL
A48: 39 | B48: 2.5.1-8988.197 | C48: QUIMICOS | D48: 2.5.1. | E48: REACTIVOS P/EQUIPO; EQUIPO: ANALIZADOR DE INMUNOENSAYO, MARCA EQUIPO: ABBOTT, NOMBRE DEL PRODUCTO: HIV 1-2, PRESENTACION: ENVASE X 96 DETERM. | F48: CAJA | G48: 48 | H48: 23147 | I48: 1111056 | J48: HIV ELISA AG/AC 4° GENERACION -96 DET-
A49: 40 | B49: 2.5.1-8988.630 | C49: QUIMICOS | D49: 2.5.1. | E49: REACTIVOS P/EQUIPO; EQUIPO: ANALIZADOR DE IONES, MARCA EQUIPO: DIESTRO, NOMBRE DEL PRODUCTO: SOLUCIONES NA, KCL, CAL, PRESENTACION: PACK DE SOLUCIONES | F49: PACK | G49: 40 | H49: 28900 | I49: 1156000 | J49: PACK DIESTRO
A50: 41 | B50: 2.5.1-8988.482 | C50: QUIMICOS | D50: 2.5.1. | E50: REACTIVOS P/EQUIPO; EQUIPO: ANALIZADOR DE QUIMICA CLINICA, MARCA EQUIPO: METROLAB, NOMBRE DEL PRODUCTO: SOLUCION DE LIMPIEZA, PRESENTACION: 2 X ENVASE X 500 mL | F50: CAJA | G50: 20 | H50: 6900 | I50: 138000 | J50: SOLUCION DE LIMPIEZA SE ML Tipo WIENER
A51: 42 | B51: 2.5.1-8988.2426 | C51: QUIMICOS | D51: 2.5.1. | E51: REACTIVOS P/EQUIPO; EQUIPO: ANALIZADOR HEMATOLOGICO, MARCA EQUIPO: MINDRAY, NOMBRE DEL PRODUCTO: E-Z CLEANSER, PRESENTACION: FRASCO 100 ML | F51: UNIDAD | G51: 20 | H51: 15520 | I51: 310400 | J51: EZ CLEANSER COUNTER 19 SOLUCION DE LIMPIEZA Tipo WIENER X 100 ML
A52: 43 | B52: 2.5.1-8988.2426 | C52: QUIMICOS | D52: 2.5.1. | E52: REACTIVOS P/EQUIPO; EQUIPO: ANALIZADOR HEMATOLOGICO, MARCA EQUIPO: MINDRAY, NOMBRE DEL PRODUCTO: E-Z CLEANSER, PRESENTACION: FRASCO 100 ML | F52: UNIDAD | G52: 30 | H52: 2100 | I52: 63000 | J52: EZ CLEANSER SOLUCION DE LIMPIEZA TIPO MINDRAY 100 ML
A53: 44 | B53: 2.5.1-8988.2424 | C53: QUIMICOS | D53: 2.5.1. | E53: REACTIVOS P/EQUIPO; EQUIPO: ANALIZADOR QUIMICA CLINICA, MARCA EQUIPO: WIENER, NOMBRE DEL PRODUCTO: DETERGENTE NO IONICO, PRESENTACION: 2 X 500 ML | F53: CAJA | G53: 40 | H53: 17800 | I53: 712000 | J53: DETERGENTE NO IONICO TIPO WIENER
A54: 45 | B54: 2.5.1-8988.2423 | C54: QUIMICOS | D54: 2.5.1. | E54: REACTIVOS P/EQUIPO; EQUIPO: ANALIZADOR, MARCA EQUIPO: MINDRAY, NOMBRE DEL PRODUCTO: DETERGENTE CD80, PRESENTACION: 1 LITRO | F54: BOTELLA | G54: 40 | H54: 17800 | I54: 712000 | J54: DETERGENTE CONCENTRADO CD 80 TIPO MINDRAY
A55: 46 | B55: 2.5.1-8988.2428 | C55: QUIMICOS | D55: 2.5.1. | E55: REACTIVOS P/EQUIPO; EQUIPO: ANALIZADOR, MARCA EQUIPO: WIENER, NOMBRE DEL PRODUCTO: FOSFATASA ALCALINA OPTIMIZADA, PRESENTACION: CAJA X 200 DETERMINACIONES | F55: CAJA | G55: 30 | H55: 10113 | I55: 303390 | J55: FOSFATASA ALCALINA Optimizada 200 DET. Tipo WIENER
A56: 47 | B56: 2.5.1-8988.2420 | C56: QUIMICOS | D56: 2.5.1. | E56: REACTIVOS P/EQUIPO; EQUIPO: ANALIZADOR, MARCA EQUIPO: WIENER, NOMBRE DEL PRODUCTO: PROTI 2 C/TESTIGO , PRESENTACION: 140 DETERMINACIONES | F56: CAJA | G56: 10 | H56: 12000 | I56: 120000 | J56: PROTI 2 (140 DET) Tipo WIENER
A57: 48 | B57: 2.5.1-8988.2421 | C57: QUIMICOS | D57: 2.5.1. | E57: REACTIVOS P/EQUIPO; EQUIPO: ANALIZADOR, MARCA EQUIPO: WIENER, NOMBRE DEL PRODUCTO: PROTI U/LCR , PRESENTACION: ENVASE X 100 ML | F57: BOTELLA | G57: 10 | H57: 6277 | I57: 62770 | J57: PROTI U/LCR 100 ML Tipo WIENER
... A123: 114 | B123: 2.5.1-8988.2468 | C123: QUIMICOS | D123: 2.5.1. | E123: REACTIVOS P/EQUIPO; EQUIPO: CONTADOR HEMATOLÓGICO; MARCA EQUIPO: SYSMEX ROCHE; NOMBRE DEL PRODUCTO: STROMATOLYSER WH XP300; PRESENTACIÓN: 3 X 500 ML | F123: CAJA | G123: 15 | H123: 24500 | I123: 367500 | J123: LISANTE SROMATOLYSER WH 3X500 ML Tipo SYSMEX XP300
A124: 115 | B124: 2.5.1-8988.2404 | C124: QUIMICOS | D124: 2.5.1. | E124: REACTIVOS P/EQUIPO; EQUIPO: ELECTROLUMINISCENCIA, MARCA EQUIPO: COBAS ROCHE, NOMBRE DEL PRODUCTO: ATG SUPERFICIE HEPATITIS B, PRESENTACION: ENVASE X 100 DETERM. | F124: CAJA | G124: 6 | H124: 27546 | I124: 165276
A125: 116 | B125: 2.5.1-8988.2406 | C125: QUIMICOS | D125: 2.5.1. | E125: REACTIVOS P/EQUIPO; EQUIPO: ELECTROLUMINISCENCIA, MARCA EQUIPO: COBAS ROCHE, NOMBRE DEL PRODUCTO: REACTIVO CHAGAS, PRESENTACION: ENVASE X 100 DETERM. | F125: CAJA | G125: 6 | H125: 51404 | I125: 308424
A126: 117 | B126: 2.5.1-8988.2405 | C126: QUIMICOS | D126: 2.5.1. | E126: REACTIVOS P/EQUIPO; EQUIPO: ELECTROLUMINISCENCIA, MARCA EQUIPO: COBAS ROCHE, NOMBRE DEL PRODUCTO: REACTIVO HTLV, PRESENTACION: ENVASE X 100 DETERM. | F126: CAJA | G126: 6 | H126: 61263 | I126: 367578
A127: 118 | B127: 2.5.1-8988.2407 | C127: QUIMICOS | D127: 2.5.1. | E127: REACTIVOS P/EQUIPO; EQUIPO: ELECTROLUMINISCENCIA, MARCA EQUIPO: COBAS ROCHE, NOMBRE DEL PRODUCTO: REACTIVO SYPHILIS, PRESENTACION: ENVASE X 100 DETERM. | F127: CAJA | G127: 6 | H127: 63289 | I127: 379734
A128: 119 | B128: 2.5.1-8988.1756 | C128: QUIMICOS | D128: 2.5.1. | E128: REACTIVOS P/EQUIPO; EQUIPO: INMUNOANALIZADOR, MARCA EQUIPO: VIDAS, NOMBRE DEL PRODUCTO: CMV IGG AVIDEZ, PRESENTACION: ENVASE X 30 DETERM. | F128: CAJA | G128: 2 | H128: 62000 | I128: 124000 | J128: CMV AVIDEZ X 30dets. MINIVIDAS Tipo BIOMERIEUX
A129: 120 | B129: 2.5.1-8988.865 | C129: QUIMICOS | D129: 2.5.1. | E129: REACTIVOS P/EQUIPO; EQUIPO: INMUNOANALIZADOR, MARCA EQUIPO: VIDAS, NOMBRE DEL PRODUCTO: TOXO IGG II, PRESENTACION: ENVASE X 60 DETERM. | F129: CAJA | G129: 5 | H129: 62300 | I129: 311500 | J129: TXG x 60 dets. (lgG toxo) MINIVIDAS Tipo BIOMERIEUX
A130: 121 | B130: 2.5.1-8988.864 | C130: QUIMICOS | D130: 2.5.1. | E130: REACTIVOS P/EQUIPO; EQUIPO: INMUNOANALIZADOR, MARCA EQUIPO: VIDAS, NOMBRE DEL PRODUCTO: TOXO IGM, PRESENTACION: ENVASE X 60 DETERM. | F130: CAJA | G130: 6 | H130: 64500 | I130: 387000 | J130: TXM x 60 dets. (lgM toxo) MINIVIDAS Tipo BIOMERIEUX
A131: 122 | B131: 2.5.1-8988.1446 | C131: QUIMICOS | D131: 2.5.1. | E131: REACTIVOS P/EQUIPO; EQUIPO: MICROTUBOS C/GEL, MARCA EQUIPO: GRIFOLS, NOMBRE DEL PRODUCTO: TARJETAS LISS COOMBS, PRESENTACION: ENVASE X 48 UN | F131: UNIDAD | G131: 900 | H131: 725 | I131: 652500 | J131: TARJETA DE GEL COOMBS
A132: 123 | B132: 2.5.1-8988.2419 | C132: QUIMICOS | D132: 2.5.1. | E132: REACTIVOS P/EQUIPO; EQUIPO: MINDRAY, MARCA EQUIPO: MINDRAY, NOMBRE DEL PRODUCTO: PROBE CLEANSER, PRESENTACION: 50 ML | F132: FRASCO | G132: 10 | H132: 11000 | I132: 110000 | J132: PORBE CLEANSER SOLUCION DE LIMPIEZA MINDRAY 50 ML
A133: 124 | B133: 2.5.1-8988.2408 | C133: QUIMICOS | D133: 2.5.1. | E133: REACTIVOS P/EQUIPO; EQUIPO: OPTI CCA-TS, MARCA EQUIPO: OPTI MEDICAL, NOMBRE DEL PRODUCTO: CASSETTE CALIBRADOR-HB , PRESENTACION: CASSETTE | F133: UNIDAD | G133: 10 | H133: 100000 | I133: 1000000 | J133: CASSETTE CALIBRADOR HEMOCLOBINA OSMETECH OPTI CCA, Tipo OPTI MEDICAL
A134: 125 | B134: 2.5.1-8988.2409 | C134: QUIMICOS | D134: 2.5.1. | E134: REACTIVOS P/EQUIPO; EQUIPO: OPTI CCA-TS, MARCA EQUIPO: OPTI MEDICAL, NOMBRE DEL PRODUCTO: CASSETTE SCR N1 , PRESENTACION: CASSETTE | F134: UNIDAD | G134: 10 | H134: 100000 | I134: 1000000 | J134: CASSETTE DE REFERENCIA ESTANDAR SRC NIVEL 1 OSMETECH OPTI CCA, Tipo OPTI MEDICAL
A135: 126 | B135: 2.5.1-8988.2410 | C135: QUIMICOS | D135: 2.5.1. | E135: REACTIVOS P/EQUIPO; EQUIPO: OPTI CCA-TS, MARCA EQUIPO: OPTI MEDICAL, NOMBRE DEL PRODUCTO: CASSETTE SCR N3 , PRESENTACION: CASSETTE | F135: UNIDAD | G135: 10 | H135: 100000 | I135: 1000000 | J135: CASSETTE DE REFERENCIA ESTANDAR SRC NIVEL 3 OSMETECH OPTI CCA, Tipo OPTI MEDICAL
A136: 127 | B136: 2.5.1-9052.62 | C136: QUIMICOS | D136: 2.5.1. | E136: REACTIVOS P/LAB. TEC. MANUAL ; NOMBRE: ANTI A SUERO, USO: HEMOCLASIFICADOR, PRESENTACION: ENVASE X 10 mL | F136: FRASCO | G136: 40 | H136: 1987 | I136: 79480 | J136: ANTI A MONOCLONAL FRASCO X 10 ML Tipo WIENER
A137: 128 | B137: 2.5.1-9052.637 | C137: QUIMICOS | D137: 2.5.1. | E137: REACTIVOS P/LAB. TEC. MANUAL ; NOMBRE: ANTI B SUERO, USO: HEMOCLASIFICADOR, PRESENTACION: ENVASE X 10 mL | F137: FRASCO | G137: 40 | H137: 1987 | I137: 79480 | J137: ANTI B MONOCLONAL FRASCO X 10 ML Tipo WIENER
A138: 129 | B138: 2.5.1-9052.2154 | C138: QUIMICOS | D138: 2.5.1. | E138: REACTIVOS P/LAB. TEC. MANUAL ; NOMBRE: ANTICOAGULANTE TP (CITRATO), USO: LABORATORIO, PRESENTACION: 6 X 50 ML | F138: CAJA | G138: 20 | H138: 15000 | I138: 300000 | J138: ANTICOAGULANTE TP (CITRATO) 6X50 ML Tipo WIENER
A139: 130 | B139: 2.5.1-9052.1143 | C139: QUIMICOS | D139: 2.5.1. | E139: REACTIVOS P/LAB. TEC. MANUAL ; NOMBRE: ANTICOAGULANTE W, USO: LABORATORIO, PRESENTACION: 6 X ENVAS X 50 mL | F139: CAJA | G139: 20 | H139: 15000 | I139: 300000 | J139: ANTICOAGULANTE W (EDTA) 6X50 ML Tipo WIENER
... A144: 135 | B144: 2.5.1-9052.342 | C144: QUIMICOS | D144: 2.5.1. | E144: REACTIVOS P/LAB. TEC. MANUAL ; NOMBRE: CA COLOR ARSENAZO III, USO: METODO COLORIMETRICO, PRESENTACION: 4 X ENVASE X 50 mL | F144: CAJA | G144: 15 | H144: 5193 | I144: 77895 | J144: CALCIO COLOR ARSENAZO III AA Tipo WIENER 4X50 ML
A145: 136 | B145: 2.5.1-9052.2126 | C145: QUIMICOS | D145: 2.5.1. | E145: REACTIVOS P/LAB. TEC. MANUAL ; NOMBRE: CELDAS DE REACCION TEMPERATURA AMBIENTE-SISTEMA DE INMUNO ENSAYO. TIPO ABBOT, USO:INMUNOSEROLOGIA ; PRESENTACION: 4000 DETERMINACIONES. | F145: CAJA | G145: 6 | H145: 373520 | I145: 2241120
A146: 137 | B146: 2.5.1-9052.343 | C146: QUIMICOS | D146: 2.5.1. | E146: REACTIVOS P/LAB. TEC. MANUAL ; NOMBRE: CK-NAC MET, USO: DETERMINACION DE ISOENZIMAS, PRESENTACION: 20 X ENVASE X 2,5 mL | F146: CAJA | G146: 15 | H146: 12864 | I146: 192960 | J146: CK-NAC UV UNITEST 20X2,5 ML Tipo WIENER
A147: 138 | B147: 2.5.1-9052.2129 | C147: QUIMICOS | D147: 2.5.1. | E147: REACTIVOS P/LAB. TEC. MANUAL ; NOMBRE: COVIDAR IGG(SEROKIT MAS ELISA IGG), USO: DIAGNOSTICO SARS-COV-2, PRESENTACION: ENVASE X 192 DETERM. | F147: CAJA | G147: 15 | H147: 64700 | I147: 970500
A148: 139 | B148: 2.5.1-9052.2129 | C148: QUIMICOS | D148: 2.5.1. | E148: REACTIVOS P/LAB. TEC. MANUAL ; NOMBRE: COVIDAR IGG(SEROKIT MAS ELISA IGG), USO: DIAGNOSTICO SARS-COV-2, PRESENTACION: ENVASE X 192 DETERM. | F148: CAJA | G148: 12 | H148: 19744 | I148: 236928 | J148: Equipos Covidar IGG x 192 determinaciones tipo Lemos
A149: 140 | B149: 2.5.1-9052.365 | C149: QUIMICOS | D149: 2.5.1. | E149: REACTIVOS P/LAB. TEC. MANUAL ; NOMBRE: DET. G GLUTAMIL TRANSFERASA, USO: QUIMICA CLINICA, PRESENTACION: 3 X ENVASE X 200 mL | F149: CAJA | G149: 10 | H149: 5868 | I149: 58680 | J149: GAMMA G-test CINETICA AA 20X3 ML Tipo WIENER
A150: 141 | B150: 2.5.1-9052.1513 | C150: QUIMICOS | D150: 2.5.1. | E150: REACTIVOS P/LAB. TEC. MANUAL ; NOMBRE: DET. SANGRE EN MAT FECAL, USO: DIAGNOSTICO, PRESENTACION: ENVASE X 25 DETERM. | F150: CAJA | G150: 20 | H150: 6500 | I150: 130000 | J150: SANGRE OCULTA EN MATERIA FECAL X 25 DETERMINACIONES
A151: 142 | B151: 2.5.1-9052.1488 | C151: QUIMICOS | D151: 2.5.1. | E151: REACTIVOS P/LAB. TEC. MANUAL ; NOMBRE: ELISA ANTI HCV, USO: DETERMINACION DE ANTICUERPOS, PRESENTACION: ENVASE X 96 DETERM. | F151: CAJA | G151: 12 | H151: 39806 | I151: 477672 | J151: HEPATITIS C HCV ELISA 3º GEN. 96 DET.
A152: 143 | B152: 2.5.1-9052.740 | C152: QUIMICOS | D152: 2.5.1. | E152: REACTIVOS P/LAB. TEC. MANUAL ; NOMBRE: ELISA P/DET. ANTIC ANTI-HBSAG, USO: DETERMINACION HEPATITIS B, PRESENTACION: ENVASE X 96 DETERM. | F152: CAJA | G152: 12 | H152: 14586 | I152: 175032 | J152: HEPATITIS B ELISA HBSAG-96DET.
A153: 144 | B153: 2.5.1-9052.862 | C153: QUIMICOS | D153: 2.5.1. | E153: REACTIVOS P/LAB. TEC. MANUAL ; NOMBRE: ELISA PARA HTLV, USO: SEROLOGIA, PRESENTACION: ENVASE X 96 DETERM. | F153: CAJA | G153: 12 | H153: 25747 | I153: 308964 | J153: HTLV 1 Y 2 ELISA-96DET.
A154: 145 | B154: 2.5.1-9052.355 | C154: QUIMICOS | D154: 2.5.1. | E154: REACTIVOS P/LAB. TEC. MANUAL ; NOMBRE: HBSAG ELISA, USO: DIAGNOSTICO, PRESENTACION: ENVASE X 96 DETERM. | F154: CAJA | G154: 50 | H154: 33081 | I154: 1654050 | J154: HEPATITIS B AG SUPERFICIE HBsAG ELISA X 96 DETERMINACIONES Tipo WIENER
A155: 146 | B155: 2.5.1-9052.648 | C155: QUIMICOS | D155: 2.5.1. | E155: REACTIVOS P/LAB. TEC. MANUAL ; NOMBRE: HEMAGLUTINACION P/CHAGAS, USO: DETERMINACION, PRESENTACION: ENVASE X 96 DETERM. | F155: CAJA | G155: 50 | H155: 24600 | I155: 1230000 | J155: CHAGAS HAI X 96 DETERMINACIONES Tipo WIENER
A156: 147 | B156: 2.5.1-9052.762 | C156: QUIMICOS | D156: 2.5.1. | E156: REACTIVOS P/LAB. TEC. MANUAL ; NOMBRE: LDL COLESTEROL REACTIVO PRECIP, USO: LABORATORIO, PRESENTACION: ENVASE X 100 DETERM. | F156: CAJA | G156: 20 | H156: 5432 | I156: 108640 | J156: LDL COLESTEROL REACTIVO PRECIPITANTE X 100 DETERMINACIONES Tipo WIENER
A157: 148 | B157: 2.5.1-9052.421 | C157: QUIMICOS | D157: 2.5.1. | E157: REACTIVOS P/LAB. TEC. MANUAL ; NOMBRE: PROTEINA C REACTIVA, USO: INMUNOSEROLOGIA, PRESENTACION: ENVASE X 50 DETERM. | F157: CAJA | G157: 80 | H157: 6811 | I157: 544880 | J157: PCR -latex directo 50 DET. Tipo WIENER
A158: 149 | B158: 2.5.1-9052.2132 | C158: QUIMICOS | D158: 2.5.1. | E158: REACTIVOS P/LAB. TEC. MANUAL ; NOMBRE: REACTIVO ANTI HBC TEC. ELECTROLIMINISCENCIA TIPO ROCHE COBAS E411 CRACK, USO: INMUNOSEROLOGIA; PRESENTACION: X 100 DETERMINACIONES. | F158: CAJA | G158: 6 | H158: 41413 | I158: 248478
A159: 150 | B159: 2.5.1-9052.2134 | C159: QUIMICOS | D159: 2.5.1. | E159: REACTIVOS P/LAB. TEC. MANUAL ; NOMBRE: REACTIVO ANTI HCV TEC. ELECTROLUMINISCENCIA TIPO ROCHE COBAS E411 CRACK; USO: INMUNOSEROLOGIA ; PRESENTACION: X 100 DETERMINACIONES. | F159: CAJA | G159: 6 | H159: 93380 | I159: 560280
A160: 151 | B160: 2.5.1-9052.2133 | C160: QUIMICOS | D160: 2.5.1. | E160: REACTIVOS P/LAB. TEC. MANUAL ; NOMBRE: REACTIVO HC1V TEC. ELECTROLUNINISCENCIA TIPO ROCHE COBAS E411 CRACK, USO: INMUNOSEROLOGIA ; PRESENTACION: X 100 DETERMINACIONES. | F160: CAJA | G160: 6 | H160: 27563 | I160: 165378
A161: 152 | B161: 2.5.1-9052.294 | C161: QUIMICOS | D161: 2.5.1. | E161: REACTIVOS P/LAB. TEC. MANUAL ; NOMBRE: REACTIVO HUDDLESON, USO: DIAGNOSTICO DE BRUCELOSIS, PRESENTACION: ENVASE X 5 mL | F161: UNIDAD | G161: 12 | H161: 1184 | I161: 14208 | J161: ANTIGENO FEBRIL BRUCELLA (HUDDLESON 1 X 5 ML.
A162: 153 | B162: 2.5.1-9052.763 | C162: QUIMICOS | D162: 2.5.1. | E162: REACTIVOS P/LAB. TEC. MANUAL ; NOMBRE: SOLUPLASTIN, USO: LABORATORIO, PRESENTACION: 10 X ENVASE X 2 mL | F162: CAJA | G162: 60 | H162: 8658 | I162: 519480 | J162: SOLUPLASTIN 10 X2 ML 100 DET. Tipo WIENER
A163: 154 | B163: 2.5.1-9052.288 | C163: QUIMICOS | D163: 2.5.1. | E163: REACTIVOS P/LAB. TEC. MANUAL ; NOMBRE: SUERO COOMBS MONOES. ANTI-IGA, USO: HEMOTERAPIA, PRESENTACION: ENVASE X 5 mL | F163: UNIDAD | G163: 12 | H163: 1325 | I163: 15900 | J163: SUERO ANTI HUMANO COOMBS
A164: 155 | B164: 2.5.1-9052.1590 | C164: QUIMICOS | D164: 2.5.1. | E164: REACTIVOS P/LAB. TEC. MANUAL ; NOMBRE: SUERO DE COOMBS POLIESPECIFICO, USO: HEMOTERAPIA, PRESENTACION: ENVASE X 10 mL | F164: FRASCO | G164: 5 | H164: 8700 | I164: 43500 | J164: SUERO DE COOMBS ANTIHUMANO POLIESPECIFICO X 10 ML Tipo WIENER
A165: 156 | B165: 2.5.1-9052.1864 | C165: QUIMICOS | D165: 2.5.1. | E165: REACTIVOS P/LAB. TEC. MANUAL ; NOMBRE: SUERO HEMOTIFIC ANTI D IGM, USO: HEMOTERAPIA, PRESENTACION: ENVASE X 10 mL | F165: FRASCO | G165: 50 | H165: 3759 | I165: 187950 | J165: ANTI D(RHO) MONOCLONAL FRASCO X 10 ML Tipo WIENER
A166: 157 | B166: 2.5.1-9052.247 | C166: QUIMICOS | D166: 2.5.1. | E166: REACTIVOS P/LAB. TEC. MANUAL ; NOMBRE: SUERO HEMOTIPIFICADOR ANTI-AB, USO: HEMOTERAPIA, PRESENTACION: ENVASE X 10 mL | F166: CAJA | G166: 100 | H166: 888 | I166: 88800 | J166: ANTI-AB MONOCLONAL- FRASCO 10 ML
A167: 158 | B167: 2.5.1-9052.308 | C167: QUIMICOS | D167: 2.5.1. | E167: REACTIVOS P/LAB. TEC. MANUAL ; NOMBRE: TEST EMBARAZO, USO: DIAGNOSTICO, PRESENTACION: ENVASE X 25 UN | F167: CAJA | G167: 100 | H167: 3654 | I167: 365400 | J167: FECUNTEST STRIP X 25 DETERMINACIONES Tipo WIENER
A168: 159 | B168: 2.5.1-9052.500 | C168: QUIMICOS | D168: 2.5.1. | E168: REACTIVOS P/LAB. TEC. MANUAL ; NOMBRE: TEST EMBARAZO, USO: DIAGNOSTICO, PRESENTACION: ENVASE X 50 DETERM. | F168: CAJA | G168: 10 | H168: 13292 | I168: 132920 | J168: FECUNTEST DIRECTO X 50 DETERMINACIONES Tipo WIENER
A169: 160 | B169: 2.5.1-9052.652 | C169: QUIMICOS | D169: 2.5.1. | E169: REACTIVOS P/LAB. TEC. MANUAL ; NOMBRE: TIRAS REACTIVAS ANALISIS ORINA, USO: LABORATORIO, PRESENTACION: ENVASE X 100 DETERM. | F169: CAJA | G169: 200 | H169: 6800 | I169: 1360000 | J169: TIRAS DE ORINA X100 UNIDADES Tipo WIENER
A170: 161 | B170: 2.5.1-9052.354 | C170: QUIMICOS | D170: 2.5.1. | E170: REACTIVOS P/LAB. TEC. MANUAL ; NOMBRE: TOXOTEST HAI, USO: INMUNOLOGIA, PRESENTACION: ENVASE X 96 DETERM. | F170: CAJA | G170: 12 | H170: 16645 | I170: 199740
A171: 162 | B171: 2.5.1-9052.981 | C171: QUIMICOS | D171: 2.5.1. | E171: REACTIVOS P/LAB. TEC. MANUAL ; NOMBRE: UREA COLORIMETRICA MANUAL, USO: LABORATORIO, PRESENTACION: ENVASE X 500 DETERM. | F171: CAJA | G171: 40 | H171: 11600 | I171: 464000 | J171: UREA COLOR 2R 500 DET. Tipo WIENER
A172: 163 | B172: 2.5.1-9052.645 | C172: QUIMICOS | D172: 2.5.1. | E172: REACTIVOS P/LAB. TEC. MANUAL ; NOMBRE: VDRL, USO: DIAGNOSTICO, PRESENTACION: ENVASE X 250 DETERM. | F172: CAJA | G172: 112 | H172: 3800 | I172: 425600 | J172: V.D.R.L. test 250 DET. Tipo WIENER
A173: 164 | B173: 2.5.1-9052.2123 | C173: QUIMICOS | D173: 2.5.1. | E173: REACTIVOS P/LAB. TEC. MANUAL ; NOMBRE:SARS- COV-2 IGM CONTROL, USO: IDENTIFICACION DE ANTICUERPOS, PRESENTACION: 2 X ENVASE X 10 ML | F173: CAJA | G173: 2 | H173: 17788 | I173: 35576 | J173: SARS- COV-2 Igm Control
A174: 165 | B174: 2.5.1-9052.2155 | C174: QUIMICOS | D174: 2.5.1. | E174: REACTIVOS P/LAB. TEC. MANUAL, NOMBRE:CMV CITOMEGALOVIRUS IGM , USO: METODO ELISA TIPO WIENER, PRESENTACION: 96 DETERMINACIONES | F174: CAJA | G174: 12 | H174: 19749 | I174: 236988
A175: 166 | B175: 2.5.1-9052.2138 | C175: QUIMICOS | D175: 2.5.1. | E175: REACTIVOS P/LAB. TEC. MANUAL; MARCA EQUIPO: ABBOTT; NOMBRE DEL PRODUCTO: ANTÍGENO SARS-COV-2; PRESENTACIÓN: 25 TEST | F175: CAJA | G175: 400 | H175: 21000 | I175: 8400000 | J175: PRUEBA RAPIDA PARA LA DETECCION CUALITATIVA DE ANTIGENOS DEL NUEVO CORONAVIRUS, VIRUS DE INFLUENZA A&B EN MUESTRAS DE HISOPADO NASOFARINGEO (CAJA X 25 TEST) Tipo ABBOTT
A176: 167 | B176: 2.5.1-9052.2142 | C176: QUIMICOS | D176: 2.5.1. | E176: REACTIVOS P/LAB. TEC. MANUAL; NOMBRE DEL PRODUCTO: HCV ELISA 3RA GENERACION, USO: DETERMINACION HEPATITIS C, PRESENTACION: ENVASE X 96 DETERM. | F176: CAJA | G176: 5 | H176: 59902 | I176: 299510 | J176: HVC ELISA HEPATITIS C 3RA GENERACION X96 DETERMINACIONES Tipo WIENER
A177: 168 | B177: 2.5.1-9052.2136 | C177: QUIMICOS | D177: 2.5.1. | E177: REACTIVOS P/LAB. TEC. MANUAL; NOMBRE: AD PARA TOXOPLASMOSIS; MARCA: POLYCHACO; USO: SEROLOGÍA; PRESENTACIÓN: ENVASE X 96 DETERMINACIONES | F177: CAJA | G177: 50 | H177: 64575 | I177: 3228750 | J177: TOXOPLASMOSIS AD X96 DET Tipo POLICHACO
A178: 169 | B178: 2.5.1-9052.2127 | C178: QUIMICOS | D178: 2.5.1. | E178: REACTIVOS P/LAB. TEC. MANUAL; NOMBRE: REACTIVO PARA HEPATITIS C, USO: DETECCION DE ANTIGENO- ANTICUERPO TIPO BIORAD ; PRESENTACION: X 96 DETERMINACIONES. | F178: CAJA | G178: 16 | H178: 130000 | I178: 2080000 | J178: Equipos por metodo de Elisa para la deteccion simultanea anticuerpos y antigenos de virus de Hepatitis C por Elisa en microplaca recubierta con anticuerpos monoclonales anti caspide de HCV con antigenos reconvinantes de la region NS3 genotipos 1 y 3º y de la region no estructural NS4 y un peptido mutado de la region de la caspide del Virus HCV. En equipos de 96 det. Por metodologia EIA en microplacas con provision de 1 de lavado, y todo insumo necesario para suprocesamiento Monolisa
A179: 170 | B179: 2.5.1-9052.2128 | C179: QUIMICOS | D179: 2.5.1. | E179: REACTIVOS P/LAB. TEC: MANUAL; NOMBRE: DETECCION DE ANTI HB CORE POR METODO DE ELISA EN MICROPLACAS, USO: INMUNOSEROLOGIA TIPO BIORAD; PRESENTACION: X 96 DETERMINACIONES | F179: CAJA | G179: 16 | H179: 20160 | I179: 322560 | J179: Equipo para la deteccion de Anti Hb Core, por metodo de Elisa en microplacas en equipos de 96 det. Monolisa HBc Plus
A180: 171 | B180: 2.5.1-9052.2162 | C180: QUIMICOS | D180: 2.5.1. | E180: REACTIVOS PARA LABORATORIO TEC. MANUAL, NOMBRE: CHAGATEST ELISA LISADO TIPO WIENER , USO: DIAGNOSTICO, PRESENTACION: CAJA X 96 DETERMINACIONES | F180: CAJA | G180: 12 | H180: 10206 | I180: 122472
A181: 172 | B181: 2.5.1-9052.2161 | C181: QUIMICOS | D181: 2.5.1. | E181: REACTIVOS PARA LABORATORIO TEC. MANUAL, NOMBRE: CHAGATEST ELISA RECOMBINANTE (V4,0) TIPO WIENER , USO: DIAGNOSTICO , PRESENTACION: CAJA X 96 DETERMINACIONES | F181: CAJA | G181: 12 | H181: 11295 | I181: 135540
A182: 173 | B182: 2.5.1-9052.2156 | C182: QUIMICOS | D182: 2.5.1. | E182: REACTIVOS PARA LABORATORIO TEC. MANUAL, NOMBRE: IDENTIERA DIANA, USO: DIAGNOSTICO, PRESENTACION: CAJA DE 11 FRASCOS DE 5ML | F182: CAJA | G182: 9 | H182: 29160 | I182: 262440
A183: 174 | B183: 2.5.1-9052.2157 | C183: QUIMICOS | D183: 2.5.1. | E183: REACTIVOS PARA LABORATORIO TEC. MANUAL, NOMBRE: PANEL SARASCAN DIANA 2, USO: DIAGNOSTICO, PRESENTACION: CAJA X 2 FRASCO DE 10ML | F183: CAJA | G183: 9 | H183: 22500 | I183: 202500
...

Sheet NP LABORATORIO
B1: Nota de Pedido
A2: Jurisdicción: | C2: 040 - MINISTERIO DE SALUD
A3: SAF: | C3: 011 - DIRECCION PROVINCIAL DE ADMINISTRACION - MINISTERIO DE SALUD
A4: Unidad Ejecutora: | C4: 468 - DIRECCION PROVINCIAL DE LABORATORIO
A5: Dependencia Solicitante: | C5: 468 - DIRECCION PROVINCIAL DE LABORATORIO
A6: Objeto: | C6: ADQUISICION DEL RUBRO REACTIVOS PARA LABORATORIO
A7: Periodo de Utilización: | C7: 3 (TRES) MESES
A9: Orden | B9: Código | C9: Descripción | D9: Detalle Técnico | E9: Unidad de Medida | F9: Precio Unitario Estimado | G9: Cantidad Solicitada
A10: 1 | B10: ='SAF 011'!B10 -> 2.5.1-9043.2 | C10: ='SAF 011'!E10 -> ACEITES Y GRASAS; COMPUESTO QUIMICO: ACEITE DE INMERSION, ESTADO: LIQUIDO, CALIDAD: PRO ANALISIS, CONCENTRACION/PUREZA: 99,9 %, PRESENTACION: ENVASE X 100 mL | D10: SI | E10: ='SAF 011'!F10 -> FRASCO | F10: ='SAF 011'!H10 -> 5017 | G10: ='SAF 011'!#REF! -> #REF!
A11: 2 | B11: ='SAF 011'!B14 -> 2.5.1-9007.169 | C11: ='SAF 011'!E14 -> COMP. HIDROXILADOS Y ALCOHOLES; COMPUESTO QUIMICO: METANOL, ESTADO: LIQUIDO, CALIDAD: PRO ANALISIS, CONCENTRACION/PUREZA: 98 %, PRESENTACION: ENVASE X 1 L | D11: SI | E11: ='SAF 011'!F14 -> BOTELLA | F11: ='SAF 011'!H14 -> 3980 | G11: ='SAF 011'!#REF! -> #REF!
A12: 3 | B12: ='SAF 011'!B15 -> 2.5.1-9019.119 | C12: ='SAF 011'!E15 -> HIDRATOS DE CARBONO; COMPUESTO QUIMICO: GLUCOCURVE 75 GR, ESTADO: SOLIDO, CALIDAD: PRO ANALISIS, CONCENTRACION/PUREZA: SIN VALOR, PRESENTACION: ENVASE X 10 SOBRES | D12: SI | E12: ='SAF 011'!F15 -> CAJA | F12: ='SAF 011'!H15 -> 1781 | G12: ='SAF 011'!#REF! -> #REF!
A13: 4 | B13: ='SAF 011'!B16 -> 2.9.9-3646.23 | C13: ='SAF 011'!E16 -> INSUMOS P/CONTADOR HEMATOL; TIPO: DETERGENTE, USO: CONTADOR HEMATOLOGICO MINDRAY | D13: SI | E13: ='SAF 011'!F16 -> BIDON | F13: ='SAF 011'!H16 -> 10600 | G13: ='SAF 011'!#REF! -> #REF!
A14: 5 | B14: ='SAF 011'!B17 -> 2.9.9-3646.22 | C14: ='SAF 011'!E17 -> INSUMOS P/CONTADOR HEMATOL; TIPO: DILUYENTE, USO: CONTADOR HEMATOLOGICO MINDRAY | D14: SI | E14: ='SAF 011'!F17 -> BIDON | F14: ='SAF 011'!H17 -> 11200 | G14: ='SAF 011'!#REF! -> #REF!
A15: 6 | B15: ='SAF 011'!B18 -> 2.9.9-3646.21 | C15: ='SAF 011'!E18 -> INSUMOS P/CONTADOR HEMATOL; TIPO: LISANTE, USO: CONTADOR HEMATOLOGICO MINDRAY | D15: SI | E15: ='SAF 011'!F18 -> BOTELLA | F15: ='SAF 011'!H18 -> 17700 | G15: ='SAF 011'!#REF! -> #REF!
A16: 7 | B16: ='SAF 011'!B19 -> 2.5.1-9016.223 | C16: ='SAF 011'!E19 -> MEDIOS DE CULTIVO Y SUPLEMENTO; NOMBRE DEL PRODUCTO: AGAR DIFERENCIAL ACETATO, ESTADO: SOLIDO, PRESENTACION: ENVASE X 500 GR | D16: SI | E16: ='SAF 011'!F19 -> FRASCO | F16: ='SAF 011'!H19 -> 18017 | G16: ='SAF 011'!#REF! -> #REF!
A17: 8 | B17: ='SAF 011'!B20 -> 2.5.1-9016.547 | C17: ='SAF 011'!E20 -> MEDIOS DE CULTIVO Y SUPLEMENTO; NOMBRE DEL PRODUCTO: AGAR SANGRE C/POLINUTRIENTES, ESTADO: SOLIDO EN PLACA, PRESENTACION: ENVASE X 10 UN | D17: SI | E17: ='SAF 011'!F20 -> CAJA | F17: ='SAF 011'!H20 -> 12000 | G17: ='SAF 011'!#REF! -> #REF!
A18: 9 | B18: ='SAF 011'!B21 -> 2.5.1-9016.1014 | C18: ='SAF 011'!E21 -> MEDIOS DE CULTIVO Y SUPLEMENTO; NOMBRE DEL PRODUCTO: CALDO TODD HEWITT, ESTADO: LIQUIDO, PRESENTACION: 10 FRASCOS X 10 ML | D18: SI | E18: ='SAF 011'!F21 -> CAJA | F18: ='SAF 011'!H21 -> 38000 | G18: ='SAF 011'!#REF! -> #REF!
A19: 10 | B19: ='SAF 011'!B22 -> 2.5.1-9016.1014 | C19: ='SAF 011'!E22 -> MEDIOS DE CULTIVO Y SUPLEMENTO; NOMBRE DEL PRODUCTO: CALDO TODD HEWITT, ESTADO: LIQUIDO, PRESENTACION: 10 FRASCOS X 10 ML | D19: SI | E19: ='SAF 011'!F22 -> CAJA | F19: ='SAF 011'!H22 -> 42900 | G19: ='SAF 011'!#REF! -> #REF!
A20: 11 | B20: ='SAF 011'!B23 -> 2.5.1-9016.89 | C20: ='SAF 011'!E23 -> MEDIOS DE CULTIVO Y SUPLEMENTO; NOMBRE DEL PRODUCTO: CALDO TRIPTEINA SOJA, ESTADO: SOLIDO, PRESENTACION: ENVASE X 500 GR | D20: SI | E20: ='SAF 011'!F23 -> FRASCO | F20: ='SAF 011'!H23 -> 11000 | G20: ='SAF 011'!#REF! -> #REF!
A21: 12 | B21: ='SAF 011'!B24 -> 2.5.1-9016.429 | C21: ='SAF 011'!E24 -> MEDIOS DE CULTIVO Y SUPLEMENTO; NOMBRE DEL PRODUCTO: CROMAGAR ESTREPTO B, ESTADO: SOLIDO EN PLACA, PRESENTACION: ENVASE X 20 UN | D21: SI | E21: ='SAF 011'!F24 -> CAJA | F21: ='SAF 011'!H24 -> 15000 | G21: ='SAF 011'!#REF! -> #REF!
A22: 13 | B22: ='SAF 011'!B25 -> 2.5.1-9016.1011 | C22: ='SAF 011'!E25 -> MEDIOS DE CULTIVO Y SUPLEMENTO; NOMBRE DEL PRODUCTO: MEDIO DE TRANSPORTE CARY BLAIR, ESTADO: SOLIDO, PRESENTACION: HISOPOS X 100 UNIDADES | D22: SI | E22: ='SAF 011'!F25 -> CAJA | F22: ='SAF 011'!H25 -> 18800 | G22: ='SAF 011'!#REF! -> #REF!
... A34: 25 | B34: ='SAF 011'!B37 -> 2.5.1-8937.921 | C34: ='SAF 011'!E37 -> PATRÓN/ESTANDAR P/CALIBRACIÓN; EQUIPO: CONTADOR HEMATOLÓGICO; MARCA EQUIPO: SYSMEX ROCHE; NOMBRE DEL PRODUCTO: CONTROL P/HEMATOLOGÍA; PRESENTACIÓN: 4 X 2 X 3 ML | D34: SI | E34: ='SAF 011'!F37 -> UNIDAD | F34: ='SAF 011'!H37 -> 116900 | G34: ='SAF 011'!#REF! -> #REF!
A35: 26 | B35: ='SAF 011'!B39 -> 2.5.1-9038.83 | C35: ='SAF 011'!E39 -> REACTIVO INDICADOR-COLORANTE; COMPUESTO QUIMICO: COLORACION DE GRAM, ESTADO: SOLUCION, CALIDAD: PRO ANALISIS, PRESENTACION: ENVASE X 100 mL | D35: SI | E35: ='SAF 011'!F39 -> CAJA | F35: ='SAF 011'!H39 -> 3510 | G35: ='SAF 011'!#REF! -> #REF!
A36: 27 | B36: ='SAF 011'!B40 -> 2.5.1-9038.342 | C36: ='SAF 011'!E40 -> REACTIVO INDICADOR-COLORANTE; COMPUESTO QUIMICO: DECOLORANTE GRAM, ESTADO: SOLUCION, CALIDAD: PRO ANALISIS, PRESENTACION: ENVASE X 500 mL | D36: SI | E36: ='SAF 011'!F40 -> BOTELLA | F36: ='SAF 011'!H40 -> 8600 | G36: ='SAF 011'!#REF! -> #REF!
A37: 28 | B37: ='SAF 011'!B41 -> 2.5.1-9038.117 | C37: ='SAF 011'!E41 -> REACTIVO INDICADOR-COLORANTE; COMPUESTO QUIMICO: GIEMSA, ESTADO: LIQUIDO, CALIDAD: PRO ANALISIS, PRESENTACION: ENVASE X 1 L | D37: SI | E37: ='SAF 011'!F41 -> BOTELLA | F37: ='SAF 011'!H41 -> 7052 | G37: ='SAF 011'!#REF! -> #REF!
A38: 29 | B38: ='SAF 011'!B42 -> 2.5.1-9038.46 | C38: ='SAF 011'!E42 -> REACTIVO INDICADOR-COLORANTE; COMPUESTO QUIMICO: MAY GRUNWALD, ESTADO: SOLUCION, CALIDAD: PRO ANALISIS, PRESENTACION: ENVASE X 1 L | D38: SI | E38: ='SAF 011'!F42 -> BOTELLA | F38: ='SAF 011'!H42 -> 6970 | G38: ='SAF 011'!#REF! -> #REF!
A39: 30 | B39: ='SAF 011'!B43 -> 2.5.1-9038.228 | C39: ='SAF 011'!E43 -> REACTIVO INDICADOR-COLORANTE; COMPUESTO QUIMICO: ZIEL-NIELSEN, ESTADO: SOLUCION, CALIDAD: PRO ANALISIS, PRESENTACION: ENVASE X 100 mL | D39: SI | E39: ='SAF 011'!F43 -> CAJA | F39: ='SAF 011'!H43 -> 3634 | G39: ='SAF 011'!#REF! -> #REF!
A40: 31 | B40: ='SAF 011'!B46 -> 2.5.1-8988.521 | C40: ='SAF 011'!E46 -> REACTIVOS P/EQUIPO; EQUIPO: ANALIZADOR DE CREATININA, MARCA EQUIPO: WIENER LAB, NOMBRE DEL PRODUCTO: CREATININA DIRECTA, PRESENTACION: ENVASE X 120 DETERM. | D40: SI | E40: ='SAF 011'!F46 -> CAJA | F40: ='SAF 011'!H46 -> 4693 | G40: ='SAF 011'!#REF! -> #REF!
A41: 32 | B41: ='SAF 011'!B47 -> 2.5.1-8988.1224 | C41: ='SAF 011'!E47 -> REACTIVOS P/EQUIPO; EQUIPO: ANALIZADOR DE GASES EN SANGRE, MARCA EQUIPO: OPTIMEDICAL, NOMBRE DEL PRODUCTO: MEDICION DE PH PO2 PCO2, PRESENTACION: UNIDAD | D41: SI | E41: ='SAF 011'!F47 -> CAJA | F41: ='SAF 011'!H47 -> 100000 | G41: ='SAF 011'!#REF! -> #REF!
A42: 33 | B42: ='SAF 011'!B49 -> 2.5.1-8988.630 | C42: ='SAF 011'!E49 -> REACTIVOS P/EQUIPO; EQUIPO: ANALIZADOR DE IONES, MARCA EQUIPO: DIESTRO, NOMBRE DEL PRODUCTO: SOLUCIONES NA, KCL, CAL, PRESENTACION: PACK DE SOLUCIONES | D42: SI | E42: ='SAF 011'!F49 -> PACK | F42: ='SAF 011'!H49 -> 28900 | G42: ='SAF 011'!#REF! -> #REF!
A43: 34 | B43: ='SAF 011'!B50 -> 2.5.1-8988.482 | C43: ='SAF 011'!E50 -> REACTIVOS P/EQUIPO; EQUIPO: ANALIZADOR DE QUIMICA CLINICA, MARCA EQUIPO: METROLAB, NOMBRE DEL PRODUCTO: SOLUCION DE LIMPIEZA, PRESENTACION: 2 X ENVASE X 500 mL | D43: SI | E43: ='SAF 011'!F50 -> CAJA | F43: ='SAF 011'!H50 -> 6900 | G43: ='SAF 011'!#REF! -> #REF!
A44: 35 | B44: ='SAF 011'!B51 -> 2.5.1-8988.2426 | C44: ='SAF 011'!E51 -> REACTIVOS P/EQUIPO; EQUIPO: ANALIZADOR HEMATOLOGICO, MARCA EQUIPO: MINDRAY, NOMBRE DEL PRODUCTO: E-Z CLEANSER, PRESENTACION: FRASCO 100 ML | D44: SI | E44: ='SAF 011'!F51 -> UNIDAD | F44: ='SAF 011'!H51 -> 15520 | G44: ='SAF 011'!#REF! -> #REF!
A45: 36 | B45: ='SAF 011'!B52 -> 2.5.1-8988.2426 | C45: ='SAF 011'!E52 -> REACTIVOS P/EQUIPO; EQUIPO: ANALIZADOR HEMATOLOGICO, MARCA EQUIPO: MINDRAY, NOMBRE DEL PRODUCTO: E-Z CLEANSER, PRESENTACION: FRASCO 100 ML | D45: SI | E45: ='SAF 011'!F52 -> UNIDAD | F45: ='SAF 011'!H52 -> 2100 | G45: ='SAF 011'!#REF! -> #REF!
A46: 37 | B46: ='SAF 011'!B53 -> 2.5.1-8988.2424 | C46: ='SAF 011'!E53 -> REACTIVOS P/EQUIPO; EQUIPO: ANALIZADOR QUIMICA CLINICA, MARCA EQUIPO: WIENER, NOMBRE DEL PRODUCTO: DETERGENTE NO IONICO, PRESENTACION: 2 X 500 ML | D46: SI | E46: ='SAF 011'!F53 -> CAJA | F46: ='SAF 011'!H53 -> 17800 | G46: ='SAF 011'!#REF! -> #REF!
A47: 38 | B47: ='SAF 011'!B54 -> 2.5.1-8988.2423 | C47: ='SAF 011'!E54 -> REACTIVOS P/EQUIPO; EQUIPO: ANALIZADOR, MARCA EQUIPO: MINDRAY, NOMBRE DEL PRODUCTO: DETERGENTE CD80, PRESENTACION: 1 LITRO | D47: SI | E47: ='SAF 011'!F54 -> BOTELLA | F47: ='SAF 011'!H54 -> 17800 | G47: ='SAF 011'!#REF! -> #REF!
A48: 39 | B48: ='SAF 011'!B55 -> 2.5.1-8988.2428 | C48: ='SAF 011'!E55 -> REACTIVOS P/EQUIPO; EQUIPO: ANALIZADOR, MARCA EQUIPO: WIENER, NOMBRE DEL PRODUCTO: FOSFATASA ALCALINA OPTIMIZADA, PRESENTACION: CAJA X 200 DETERMINACIONES | D48: SI | E48: ='SAF 011'!F55 -> CAJA | F48: ='SAF 011'!H55 -> 10113 | G48: ='SAF 011'!#REF! -> #REF!
A49: 40 | B49: ='SAF 011'!B56 -> 2.5.1-8988.2420 | C49: ='SAF 011'!E56 -> REACTIVOS P/EQUIPO; EQUIPO: ANALIZADOR, MARCA EQUIPO: WIENER, NOMBRE DEL PRODUCTO: PROTI 2 C/TESTIGO , PRESENTACION: 140 DETERMINACIONES | D49: SI | E49: ='SAF 011'!F56 -> CAJA | F49: ='SAF 011'!H56 -> 12000 | G49: ='SAF 011'!#REF! -> #REF!
A50: 41 | B50: ='SAF 011'!B57 -> 2.5.1-8988.2421 | C50: ='SAF 011'!E57 -> REACTIVOS P/EQUIPO; EQUIPO: ANALIZADOR, MARCA EQUIPO: WIENER, NOMBRE DEL PRODUCTO: PROTI U/LCR , PRESENTACION: ENVASE X 100 ML | D50: SI | E50: ='SAF 011'!F57 -> BOTELLA | F50: ='SAF 011'!H57 -> 6277 | G50: ='SAF 011'!#REF! -> #REF!
A51: 42 | B51: ='SAF 011'!B58 -> 2.5.1-8988.1088 | C51: ='SAF 011'!E58 -> REACTIVOS P/EQUIPO; EQUIPO: AUTOANA. QUIMICA CLINICA, MARCA EQUIPO: WIENER, NOMBRE DEL PRODUCTO: CALIBRADOR A PLUS, PRESENTACION: 2 X ENVASE X 3 mL | D51: SI | E51: ='SAF 011'!F58 -> CAJA | F51: ='SAF 011'!H58 -> 7900 | G51: ='SAF 011'!#REF! -> #REF!
A52: 43 | B52: ='SAF 011'!B59 -> 2.5.1-8988.1085 | C52: ='SAF 011'!E59 -> REACTIVOS P/EQUIPO; EQUIPO: AUTOANA. QUIMICA CLINICA, MARCA EQUIPO: WIENER, NOMBRE DEL PRODUCTO: COLESTEROL ENZIMATICO AA, PRESENTACION: 4 X ENVASE X 100 mL | D52: SI | E52: ='SAF 011'!F59 -> CAJA | F52: ='SAF 011'!H59 -> 8000 | G52: ='SAF 011'!#REF! -> #REF!
A53: 44 | B53: ='SAF 011'!B60 -> 2.5.1-8988.2484 | C53: ='SAF 011'!E60 -> REACTIVOS P/EQUIPO; EQUIPO: AUTOANA. QUIMICA CLINICA, MARCA EQUIPO: WIENER, NOMBRE DEL PRODUCTO: COLESTEROL HDL MONOFASE AA PLUS, PRESENTACION: ENVASE X 80 ML | D53: SI | E53: ='SAF 011'!F60 -> UNIDAD | F53: ='SAF 011'!H60 -> 22000 | G53: ='SAF 011'!#REF! -> #REF!
... A87: 78 | B87: ='SAF 011'!B94 -> 2.5.1-8988.2415 | C87: ='SAF 011'!E94 -> REACTIVOS P/EQUIPO; EQUIPO: AUTOANALIZADOR; MARCA EQUIPO: WIENER; NOMBRE DEL PRODUCTO: TG GPO/ PAP AA; PRESENTACIÓN: 4 X ENVASE X 100 ML | D87: SI | E87: ='SAF 011'!F94 -> CAJA | F87: ='SAF 011'!H94 -> 18100 | G87: ='SAF 011'!#REF! -> #REF!
A88: 79 | B88: ='SAF 011'!B96 -> 2.5.1-8988.2467 | C88: ='SAF 011'!E96 -> REACTIVOS P/EQUIPO; EQUIPO: AUTOMATIZADO; MARCA EQUIPO: KINGFISHER FLEX; NOMBRE DEL PRODUCTO: MAGMAX TM VIRAL / PATHOGEN II (MPV) NUCLAIC ACID ISOLATION; PRESENTACIÓN: S/PLIEGO | D88: SI | E88: ='SAF 011'!F96 -> KIT | F88: ='SAF 011'!H96 -> 1200000 | G88: ='SAF 011'!#REF! -> #REF!
A89: 80 | B89: ='SAF 011'!B97 -> 2.5.1-8988.2414 | C89: ='SAF 011'!E97 -> REACTIVOS P/EQUIPO; EQUIPO: AUTOMATIZADO; MARCA EQUIPO: TOSOH; NOMBRE DEL PRODUCTO: T4 LIBRE; PRESENTACIÓN: 100 DETERMINACIONES | D89: SI | E89: ='SAF 011'!F97 -> CAJA | F89: ='SAF 011'!H97 -> 43296 | G89: ='SAF 011'!#REF! -> #REF!
A90: 81 | B90: ='SAF 011'!B98 -> 2.5.1-8988.2043 | C90: ='SAF 011'!E98 -> REACTIVOS P/EQUIPO; EQUIPO: AUTOMATIZADO; MARCA EQUIPO: VIDAS; NOMBRE DEL PRODUCTO: CMV IGG; PRESENTACIÓN: DETERMINACIÓN S/PLIEGO | D90: SI | E90: ='SAF 011'!F98 -> CAJA | F90: ='SAF 011'!H98 -> 51200 | G90: ='SAF 011'!#REF! -> #REF!
A91: 82 | B91: ='SAF 011'!B99 -> 2.5.1-8988.2042 | C91: ='SAF 011'!E99 -> REACTIVOS P/EQUIPO; EQUIPO: AUTOMATIZADO; MARCA EQUIPO: VIDAS; NOMBRE DEL PRODUCTO: CMV IGM; PRESENTACIÓN: DETERMINACIÓN S/PLIEGO | D91: SI | E91: ='SAF 011'!F99 -> CAJA | F91: ='SAF 011'!H99 -> 52100 | G91: ='SAF 011'!#REF! -> #REF!
A92: 83 | B92: ='SAF 011'!B100 -> 2.5.1-8988.2445 | C92: ='SAF 011'!E100 -> REACTIVOS P/EQUIPO; EQUIPO: AUTOMATIZADO; MARCA EQUIPO: VIDAS; NOMBRE DEL PRODUCTO: DENGUE IGG; PRESENTACIÓN: X 60 DETERMINACIONES | D92: SI | E92: ='SAF 011'!F100 -> CAJA | F92: ='SAF 011'!H100 -> 110000 | G92: ='SAF 011'!#REF! -> #REF!
A93: 84 | B93: ='SAF 011'!B101 -> 2.5.1-8988.2442 | C93: ='SAF 011'!E101 -> REACTIVOS P/EQUIPO; EQUIPO: AUTOMATIZADO; MARCA EQUIPO: VIDAS; NOMBRE DEL PRODUCTO: DENGUE IGM; PRESENTACION: X 60 DETERMINACIONES | D93: SI | E93: ='SAF 011'!F101 -> CAJA | F93: ='SAF 011'!H101 -> 110000 | G93: ='SAF 011'!#REF! -> #REF!
A94: 85 | B94: ='SAF 011'!B102 -> 2.5.1-8988.2440 | C94: ='SAF 011'!E102 -> REACTIVOS P/EQUIPO; EQUIPO: AUTOMATIZADO; MARCA EQUIPO: VIDAS; NOMBRE DEL PRODUCTO: DENGUE NS1; PRESENTACIÓN: X 60 DETERMINACIONES | D94: SI | E94: ='SAF 011'!F102 -> CAJA | F94: ='SAF 011'!H102 -> 110000 | G94: ='SAF 011'!#REF! -> #REF!
A95: 86 | B95: ='SAF 011'!B103 -> 2.5.1-8988.2465 | C95: ='SAF 011'!E103 -> REACTIVOS P/EQUIPO; EQUIPO: AUTOMATIZADO; MARCA EQUIPO: VIDAS; NOMBRE DEL PRODUCTO: EPSTEIN BAR IGG; PRESENTACIÓN: X 30 DETERMINACIONES | D95: SI | E95: ='SAF 011'!F103 -> CAJA | F95: ='SAF 011'!H103 -> 42000 | G95: ='SAF 011'!#REF! -> #REF!
A96: 87 | B96: ='SAF 011'!B104 -> 2.5.1-8988.2466 | C96: ='SAF 011'!E104 -> REACTIVOS P/EQUIPO; EQUIPO: AUTOMATIZADO; MARCA EQUIPO: VIDAS; NOMBRE DEL PRODUCTO: EPSTEIN BAR IGM; PRESENTACIÓN: X 30 DETERMINACIONES | D96: SI | E96: ='SAF 011'!F104 -> CAJA | F96: ='SAF 011'!H104 -> 39160 | G96: ='SAF 011'!#REF! -> #REF!
A97: 88 | B97: ='SAF 011'!B105 -> 2.5.1-8988.2460 | C97: ='SAF 011'!E105 -> REACTIVOS P/EQUIPO; EQUIPO: AUTOMATIZADO; MARCA EQUIPO: VIDAS; NOMBRE DEL PRODUCTO: RUBEOLA IGG; PRESENTACIÓN: X 60 DETERMINACIONES | D97: SI | E97: ='SAF 011'!F105 -> CAJA | F97: ='SAF 011'!H105 -> 51300 | G97: ='SAF 011'!#REF! -> #REF!
A98: 89 | B98: ='SAF 011'!B106 -> 2.5.1-8988.2456 | C98: ='SAF 011'!E106 -> REACTIVOS P/EQUIPO; EQUIPO: AUTOMATIZADO; MARCA EQUIPO: VIDAS; NOMBRE DEL PRODUCTO: RUBEOLA IGM; PRESENTACIÓN: X 60 DETERMINACIONES | D98: SI | E98: ='SAF 011'!F106 -> CAJA | F98: ='SAF 011'!H106 -> 52100 | G98: ='SAF 011'!#REF! -> #REF!
A99: 90 | B99: ='SAF 011'!B107 -> 2.5.1-8988.2464 | C99: ='SAF 011'!E107 -> REACTIVOS P/EQUIPO; EQUIPO: AUTOMATIZADO; MARCA EQUIPO: VIDAS; NOMBRE DEL PRODUCTO: VARICELA IGG; PRESENTACION: X 60 DETERMINACIONES | D99: SI | E99: ='SAF 011'!F107 -> CAJA | F99: ='SAF 011'!H107 -> 62000 | G99: ='SAF 011'!#REF! -> #REF!
... A115: 106 | B115: ='SAF 011'!B123 -> 2.5.1-8988.2468 | C115: ='SAF 011'!E123 -> REACTIVOS P/EQUIPO; EQUIPO: CONTADOR HEMATOLÓGICO; MARCA EQUIPO: SYSMEX ROCHE; NOMBRE DEL PRODUCTO: STROMATOLYSER WH XP300; PRESENTACIÓN: 3 X 500 ML | D115: SI | E115: ='SAF 011'!F123 -> CAJA | F115: ='SAF 011'!H123 -> 24500 | G115: ='SAF 011'!#REF! -> #REF!
A116: 107 | B116: ='SAF 011'!B128 -> 2.5.1-8988.1756 | C116: ='SAF 011'!E128 -> REACTIVOS P/EQUIPO; EQUIPO: INMUNOANALIZADOR, MARCA EQUIPO: VIDAS, NOMBRE DEL PRODUCTO: CMV IGG AVIDEZ, PRESENTACION: ENVASE X 30 DETERM. | D116: SI | E116: ='SAF 011'!F128 -> CAJA | F116: ='SAF 011'!H128 -> 62000 | G116: ='SAF 011'!#REF! -> #REF!
A117: 108 | B117: ='SAF 011'!B129 -> 2.5.1-8988.865 | C117: ='SAF 011'!E129 -> REACTIVOS P/EQUIPO; EQUIPO: INMUNOANALIZADOR, MARCA EQUIPO: VIDAS, NOMBRE DEL PRODUCTO: TOXO IGG II, PRESENTACION: ENVASE X 60 DETERM. | D117: SI | E117: ='SAF 011'!F129 -> CAJA | F117: ='SAF 011'!H129 -> 62300 | G117: ='SAF 011'!#REF! -> #REF!
A118: 109 | B118: ='SAF 011'!B130 -> 2.5.1-8988.864 | C118: ='SAF 011'!E130 -> REACTIVOS P/EQUIPO; EQUIPO: INMUNOANALIZADOR, MARCA EQUIPO: VIDAS, NOMBRE DEL PRODUCTO: TOXO IGM, PRESENTACION: ENVASE X 60 DETERM. | D118: SI | E118: ='SAF 011'!F130 -> CAJA | F118: ='SAF 011'!H130 -> 64500 | G118: ='SAF 011'!#REF! -> #REF!
A119: 110 | B119: ='SAF 011'!B132 -> 2.5.1-8988.2419 | C119: ='SAF 011'!E132 -> REACTIVOS P/EQUIPO; EQUIPO: MINDRAY, MARCA EQUIPO: MINDRAY, NOMBRE DEL PRODUCTO: PROBE CLEANSER, PRESENTACION: 50 ML | D119: SI | E119: ='SAF 011'!F132 -> FRASCO | F119: ='SAF 011'!H132 -> 11000 | G119: ='SAF 011'!#REF! -> #REF!
A120: 111 | B120: ='SAF 011'!B133 -> 2.5.1-8988.2408 | C120: ='SAF 011'!E133 -> REACTIVOS P/EQUIPO; EQUIPO: OPTI CCA-TS, MARCA EQUIPO: OPTI MEDICAL, NOMBRE DEL PRODUCTO: CASSETTE CALIBRADOR-HB , PRESENTACION: CASSETTE | D120: SI | E120: ='SAF 011'!F133 -> UNIDAD | F120: ='SAF 011'!H133 -> 100000 | G120: ='SAF 011'!#REF! -> #REF!
A121: 112 | B121: ='SAF 011'!B134 -> 2.5.1-8988.2409 | C121: ='SAF 011'!E134 -> REACTIVOS P/EQUIPO; EQUIPO: OPTI CCA-TS, MARCA EQUIPO: OPTI MEDICAL, NOMBRE DEL PRODUCTO: CASSETTE SCR N1 , PRESENTACION: CASSETTE | D121: SI | E121: ='SAF 011'!F134 -> UNIDAD | F121: ='SAF 011'!H134 -> 100000 | G121: ='SAF 011'!#REF! -> #REF!
A122: 113 | B122: ='SAF 011'!B135 -> 2.5.1-8988.2410 | C122: ='SAF 011'!E135 -> REACTIVOS P/EQUIPO; EQUIPO: OPTI CCA-TS, MARCA EQUIPO: OPTI MEDICAL, NOMBRE DEL PRODUCTO: CASSETTE SCR N3 , PRESENTACION: CASSETTE | D122: SI | E122: ='SAF 011'!F135 -> UNIDAD | F122: ='SAF 011'!H135 -> 100000 | G122: ='SAF 011'!#REF! -> #REF!
A123: 114 | B123: ='SAF 011'!B136 -> 2.5.1-9052.62 | C123: ='SAF 011'!E136 -> REACTIVOS P/LAB. TEC. MANUAL ; NOMBRE: ANTI A SUERO, USO: HEMOCLASIFICADOR, PRESENTACION: ENVASE X 10 mL | D123: SI | E123: ='SAF 011'!F136 -> FRASCO | F123: ='SAF 011'!H136 -> 1987 | G123: ='SAF 011'!#REF! -> #REF!
A124: 115 | B124: ='SAF 011'!B137 -> 2.5.1-9052.637 | C124: ='SAF 011'!E137 -> REACTIVOS P/LAB. TEC. MANUAL ; NOMBRE: ANTI B SUERO, USO: HEMOCLASIFICADOR, PRESENTACION: ENVASE X 10 mL | D124: SI | E124: ='SAF 011'!F137 -> FRASCO | F124: ='SAF 011'!H137 -> 1987 | G124: ='SAF 011'!#REF! -> #REF!
A125: 116 | B125: ='SAF 011'!B138 -> 2.5.1-9052.2154 | C125: ='SAF 011'!E138 -> REACTIVOS P/LAB. TEC. MANUAL ; NOMBRE: ANTICOAGULANTE TP (CITRATO), USO: LABORATORIO, PRESENTACION: 6 X 50 ML | D125: SI | E125: ='SAF 011'!F138 -> CAJA | F125: ='SAF 011'!H138 -> 15000 | G125: ='SAF 011'!#REF! -> #REF!
A126: 117 | B126: ='SAF 011'!B139 -> 2.5.1-9052.1143 | C126: ='SAF 011'!E139 -> REACTIVOS P/LAB. TEC. MANUAL ; NOMBRE: ANTICOAGULANTE W, USO: LABORATORIO, PRESENTACION: 6 X ENVAS X 50 mL | D126: SI | E126: ='SAF 011'!F139 -> CAJA | F126: ='SAF 011'!H139 -> 15000 | G126: ='SAF 011'!#REF! -> #REF!
A127: 118 | B127: ='SAF 011'!B140 -> 2.5.1-9052.388 | C127: ='SAF 011'!E140 -> REACTIVOS P/LAB. TEC. MANUAL ; NOMBRE: APTT, USO: HEMOSTASIA, PRESENTACION: ENVASE X 150 DETERM. | D127: SI | E127: ='SAF 011'!F140 -> CAJA | F127: ='SAF 011'!H140 -> 11955 | G127: ='SAF 011'!#REF! -> #REF!
A128: 119 | B128: ='SAF 011'!B141 -> 2.5.1-9052.358 | C128: ='SAF 011'!E141 -> REACTIVOS P/LAB. TEC. MANUAL ; NOMBRE: ARTRITEST, USO: INMUNOANALISIS, PRESENTACION: ENVASE X 50 DETERM. | D128: SI | E128: ='SAF 011'!F141 -> UNIDAD | F128: ='SAF 011'!H141 -> 3995 | G128: ='SAF 011'!#REF! -> #REF!
A129: 120 | B129: ='SAF 011'!B144 -> 2.5.1-9052.342 | C129: ='SAF 011'!E144 -> REACTIVOS P/LAB. TEC. MANUAL ; NOMBRE: CA COLOR ARSENAZO III, USO: METODO COLORIMETRICO, PRESENTACION: 4 X ENVASE X 50 mL | D129: SI | E129: ='SAF 011'!F144 -> CAJA | F129: ='SAF 011'!H144 -> 5193 | G129: ='SAF 011'!#REF! -> #REF!
A130: 121 | B130: ='SAF 011'!B146 -> 2.5.1-9052.343 | C130: ='SAF 011'!E146 -> REACTIVOS P/LAB. TEC. MANUAL ; NOMBRE: CK-NAC MET, USO: DETERMINACION DE ISOENZIMAS, PRESENTACION: 20 X ENVASE X 2,5 mL | D130: SI | E130: ='SAF 011'!F146 -> CAJA | F130: ='SAF 011'!H146 -> 12864 | G130: ='SAF 011'!#REF! -> #REF!
A131: 122 | B131: ='SAF 011'!B149 -> 2.5.1-9052.365 | C131: ='SAF 011'!E149 -> REACTIVOS P/LAB. TEC. MANUAL ; NOMBRE: DET. G GLUTAMIL TRANSFERASA, USO: QUIMICA CLINICA, PRESENTACION: 3 X ENVASE X 200 mL | D131: SI | E131: ='SAF 011'!F149 -> CAJA | F131: ='SAF 011'!H149 -> 5868 | G131: ='SAF 011'!#REF! -> #REF!
A132: 123 | B132: ='SAF 011'!B150 -> 2.5.1-9052.1513 | C132: ='SAF 011'!E150 -> REACTIVOS P/LAB. TEC. MANUAL ; NOMBRE: DET. SANGRE EN MAT FECAL, USO: DIAGNOSTICO, PRESENTACION: ENVASE X 25 DETERM. | D132: SI | E132: ='SAF 011'!F150 -> CAJA | F132: ='SAF 011'!H150 -> 6500 | G132: ='SAF 011'!#REF! -> #REF!
A133: 124 | B133: ='SAF 011'!B154 -> 2.5.1-9052.355 | C133: ='SAF 011'!E154 -> REACTIVOS P/LAB. TEC. MANUAL ; NOMBRE: HBSAG ELISA, USO: DIAGNOSTICO, PRESENTACION: ENVASE X 96 DETERM. | D133: SI | E133: ='SAF 011'!F154 -> CAJA | F133: ='SAF 011'!H154 -> 33081 | G133: ='SAF 011'!#REF! -> #REF!
A134: 125 | B134: ='SAF 011'!B155 -> 2.5.1-9052.648 | C134: ='SAF 011'!E155 -> REACTIVOS P/LAB. TEC. MANUAL ; NOMBRE: HEMAGLUTINACION P/CHAGAS, USO: DETERMINACION, PRESENTACION: ENVASE X 96 DETERM. | D134: SI | E134: ='SAF 011'!F155 -> CAJA | F134: ='SAF 011'!H155 -> 24600 | G134: ='SAF 011'!#REF! -> #REF!
A135: 126 | B135: ='SAF 011'!B156 -> 2.5.1-9052.762 | C135: ='SAF 011'!E156 -> REACTIVOS P/LAB. TEC. MANUAL ; NOMBRE: LDL COLESTEROL REACTIVO PRECIP, USO: LABORATORIO, PRESENTACION: ENVASE X 100 DETERM. | D135: SI | E135: ='SAF 011'!F156 -> CAJA | F135: ='SAF 011'!H156 -> 5432 | G135: ='SAF 011'!#REF! -> #REF!
A136: 127 | B136: ='SAF 011'!B157 -> 2.5.1-9052.421 | C136: ='SAF 011'!E157 -> REACTIVOS P/LAB. TEC. MANUAL ; NOMBRE: PROTEINA C REACTIVA, USO: INMUNOSEROLOGIA, PRESENTACION: ENVASE X 50 DETERM. | D136: SI | E136: ='SAF 011'!F157 -> CAJA | F136: ='SAF 011'!H157 -> 6811 | G136: ='SAF 011'!#REF! -> #REF!
A137: 128 | B137: ='SAF 011'!B162 -> 2.5.1-9052.763 | C137: ='SAF 011'!E162 -> REACTIVOS P/LAB. TEC. MANUAL ; NOMBRE: SOLUPLASTIN, USO: LABORATORIO, PRESENTACION: 10 X ENVASE X 2 mL | D137: SI | E137: ='SAF 011'!F162 -> CAJA | F137: ='SAF 011'!H162 -> 8658 | G137: ='SAF 011'!#REF! -> #REF!
A138: 129 | B138: ='SAF 011'!B164 -> 2.5.1-9052.1590 | C138: ='SAF 011'!E164 -> REACTIVOS P/LAB. TEC. MANUAL ; NOMBRE: SUERO DE COOMBS POLIESPECIFICO, USO: HEMOTERAPIA, PRESENTACION: ENVASE X 10 mL | D138: SI | E138: ='SAF 011'!F164 -> FRASCO | F138: ='SAF 011'!H164 -> 8700 | G138: ='SAF 011'!#REF! -> #REF!
A139: 130 | B139: ='SAF 011'!B165 -> 2.5.1-9052.1864 | C139: ='SAF 011'!E165 -> REACTIVOS P/LAB. TEC. MANUAL ; NOMBRE: SUERO HEMOTIFIC ANTI D IGM, USO: HEMOTERAPIA, PRESENTACION: ENVASE X 10 mL | D139: SI | E139: ='SAF 011'!F165 -> FRASCO | F139: ='SAF 011'!H165 -> 3759 | G139: ='SAF 011'!#REF! -> #REF!
A140: 131 | B140: ='SAF 011'!B167 -> 2.5.1-9052.308 | C140: ='SAF 011'!E167 -> REACTIVOS P/LAB. TEC. MANUAL ; NOMBRE: TEST EMBARAZO, USO: DIAGNOSTICO, PRESENTACION: ENVASE X 25 UN | D140: SI | E140: ='SAF 011'!F167 -> CAJA | F140: ='SAF 011'!H167 -> 3654 | G140: ='SAF 011'!#REF! -> #REF!
A141: 132 | B141: ='SAF 011'!B168 -> 2.5.1-9052.500 | C141: ='SAF 011'!E168 -> REACTIVOS P/LAB. TEC. MANUAL ; NOMBRE: TEST EMBARAZO, USO: DIAGNOSTICO, PRESENTACION: ENVASE X 50 DETERM. | D141: SI | E141: ='SAF 011'!F168 -> CAJA | F141: ='SAF 011'!H168 -> 13292 | G141: ='SAF 011'!#REF! -> #REF!
A142: 133 | B142: ='SAF 011'!B169 -> 2.5.1-9052.652 | C142: ='SAF 011'!E169 -> REACTIVOS P/LAB. TEC. MANUAL ; NOMBRE: TIRAS REACTIVAS ANALISIS ORINA, USO: LABORATORIO, PRESENTACION: ENVASE X 100 DETERM. | D142: SI | E142: ='SAF 011'!F169 -> CAJA | F142: ='SAF 011'!H169 -> 6800 | G142: ='SAF 011'!#REF! -> #REF!
A143: 134 | B143: ='SAF 011'!B171 -> 2.5.1-9052.981 | C143: ='SAF 011'!E171 -> REACTIVOS P/LAB. TEC. MANUAL ; NOMBRE: UREA COLORIMETRICA MANUAL, USO: LABORATORIO, PRESENTACION: ENVASE X 500 DETERM. | D143: SI | E143: ='SAF 011'!F171 -> CAJA | F143: ='SAF 011'!H171 -> 11600 | G143: ='SAF 011'!#REF! -> #REF!
A144: 135 | B144: ='SAF 011'!B172 -> 2.5.1-9052.645 | C144: ='SAF 011'!E172 -> REACTIVOS P/LAB. TEC. MANUAL ; NOMBRE: VDRL, USO: DIAGNOSTICO, PRESENTACION: ENVASE X 250 DETERM. | D144: SI | E144: ='SAF 011'!F172 -> CAJA | F144: ='SAF 011'!H172 -> 3800 | G144: ='SAF 011'!#REF! -> #REF!
A145: 136 | B145: ='SAF 011'!B175 -> 2.5.1-9052.2138 | C145: ='SAF 011'!E175 -> REACTIVOS P/LAB. TEC. MANUAL; MARCA EQUIPO: ABBOTT; NOMBRE DEL PRODUCTO: ANTÍGENO SARS-COV-2; PRESENTACIÓN: 25 TEST | D145: SI | E145: ='SAF 011'!F175 -> CAJA | F145: ='SAF 011'!H175 -> 21000 | G145: ='SAF 011'!#REF! -> #REF!
A146: 137 | B146: ='SAF 011'!B176 -> 2.5.1-9052.2142 | C146: ='SAF 011'!E176 -> REACTIVOS P/LAB. TEC. MANUAL; NOMBRE DEL PRODUCTO: HCV ELISA 3RA GENERACION, USO: DETERMINACION HEPATITIS C, PRESENTACION: ENVASE X 96 DETERM. | D146: SI | E146: ='SAF 011'!F176 -> CAJA | F146: ='SAF 011'!H176 -> 59902 | G146: ='SAF 011'!#REF! -> #REF!
A147: 138 | B147: ='SAF 011'!B177 -> 2.5.1-9052.2136 | C147: ='SAF 011'!E177 -> REACTIVOS P/LAB. TEC. MANUAL; NOMBRE: AD PARA TOXOPLASMOSIS; MARCA: POLYCHACO; USO: SEROLOGÍA; PRESENTACIÓN: ENVASE X 96 DETERMINACIONES | D147: SI | E147: ='SAF 011'!F177 -> CAJA | F147: ='SAF 011'!H177 -> 64575 | G147: ='SAF 011'!#REF! -> #REF!
A148: Costo total estimado: PESOS SESENTA Y OCHO MILLONES TRESCIENTOS NOVENTA Y SIETE MIL CIENTO SESENTA Y NUEVE CON 00/100 | F148: =SUMPRODUCT(F10:F147,G10:G147) -> #REF!

Sheet APG LABORATORIO
A1: EJERCICIO: | D1: 2022 | P1: AUTORIZACION PARA GASTAR
A4: JURISDICCIÓN: | G4: ='NP LABORATORIO'!C2 -> 040 - MINISTERIO DE SALUD
A5: SAF: | G5: ='NP LABORATORIO'!C3 -> 011 - DIRECCION PROVINCIAL DE ADMINISTRACION - MINISTERIO DE SALUD
A6: UNIDAD EJECUTORA: | G6: ='NP LABORATORIO'!C4 -> 468 - DIRECCION PROVINCIAL DE LABORATORIO
A7: DEPENDENCIA SOLICITANTE: | G7: ='NP LABORATORIO'!C5 -> 468 - DIRECCION PROVINCIAL DE LABORATORIO
A8: AUTORIZACIÓN:
A9: Señor Director de Administración o Titular del Servicio Administrativo Financiero:
A10: Autorizo la realización de los trámites correspondientes, a fin de proveer a este Organismo los bienes que se detallan en Nota de Pedido N°....... , afectando la erogación resultante a los créditos presupuestarios aprobados a favor de esta Unidad Ejecutora, conforme al siguiente detalle:
A12: IMPUTACIÓN PRESUPUESTARIA
A13: CÓDIGO | O13: DENOMINACIÓN DE LA PARTIDA PRESUPUESTARIA | Q13: IMPORTE
A14: PR | B14: SB | C14: PY | D14: AC | E14: OB | F14: UG | G14: FIN | H14: FUN | I14: I | J14: P | K14: P | L14: SubP | M14: M | N14: FF
A15: 62 | D15: 1 | F15: 4901 | G15: 3 | H15: 1 | I15: 2 | J15: 5 | K15: 1 | M15: 1 | N15: 1.1 | O15: COMPUESTOS QUIMICOS | Q15: ='NP LABORATORIO'!F148 -> #REF!
A38: TOTAL DE PESOS: SESENTA Y OCHO MILLONES TRESCIENTOS NOVENTA Y SIETE MIL CIENTO SESENTA Y NUEVE CON 00/100 | Q38: =SUM(Q15:Q37) -> #REF!
A40: JUSTIFICACIÓN:
A41: ='NP LABORATORIO'!C6 -> ADQUISICION DEL RUBRO REACTIVOS PARA LABORATORIO

Sheet NP BCO DE SANGRE
B1: Nota de Pedido
A2: Jurisdicción: | C2: 040 - MINISTERIO DE SALUD
A3: SAF: | C3: 011 - DIRECCION PROVINCIAL DE ADMINISTRACION - MINISTERIO DE SALUD
A4: Unidad Ejecutora: | C4: 747 - DIRECCION PROVINCIAL BANCO DE SANGRE
A5: Dependencia Solicitante: | C5: 747 - DIRECCION PROVINCIAL BANCO DE SANGRE
A6: Objeto: | C6: ADQUISICION DEL RUBRO REACTIVOS PARA LABORATORIO
A7: Periodo de Utilización: | C7: 3 (TRES) MESES
A9: Orden | B9: Código | C9: Descripción | D9: Detalle Técnico | E9: Unidad de Medida | F9: Precio Unitario Estimado | G9: Cantidad Solicitada
A10: 1 | B10: ='SAF 011'!B11 -> 2.5.1-9017.381 | C10: ='SAF 011'!E11 -> ANTICUERPOS P/LABORATORIO; NOMBRE: ANTI-A, ESTADO: LIQUIDO, MARCADO CON: SIN MARCAR, ORIGEN: HUMANO, PRESENTACION: ENVASE X 10 mL, TIPO: MONOCLONAL | D10: NO | E10: ='SAF 011'!F11 -> FRASCO | F10: ='SAF 011'!H11 -> 876 | G10: ='SAF 011'!#REF! -> #REF!
A11: 2 | B11: ='SAF 011'!B12 -> 2.5.1-9017.136 | C11: ='SAF 011'!E12 -> ANTICUERPOS P/LABORATORIO; NOMBRE: ANTI-B, ESTADO: SOLUCION, MARCADO CON: SIN MARCAR, ORIGEN: HUMANO, PRESENTACION: ENVASE X 10 mL, TIPO: MONOCLONAL | D11: NO | E11: ='SAF 011'!F12 -> FRASCO | F11: ='SAF 011'!H12 -> 876 | G11: ='SAF 011'!#REF! -> #REF!
A12: 3 | B12: ='SAF 011'!B13 -> 2.5.1-9017.137 | C12: ='SAF 011'!E13 -> ANTICUERPOS P/LABORATORIO; NOMBRE: ANTI-D, ESTADO: SOLUCION, MARCADO CON: SIN MARCAR, ORIGEN: HUMANO, PRESENTACION: ENVASE X 10 mL, TIPO: MONOCLONAL | D12: SI | E12: ='SAF 011'!F13 -> UNIDAD | F12: ='SAF 011'!H13 -> 1657 | G12: ='SAF 011'!#REF! -> #REF!
A13: 4 | B13: ='SAF 011'!B38 -> 2.5.1-9037.72 | C13: ='SAF 011'!E38 -> PROTEINAS; COMPUESTO QUIMICO: ALBUMINA BOVINA, ESTADO: LIQUIDO, CALIDAD: TECNICA MANUAL, CONCENTRACION/PUREZA: 30%, PRESENTACION: ENVASE X 10 ML | D13: NO | E13: ='SAF 011'!F38 -> UNIDAD | F13: ='SAF 011'!H38 -> 1251 | G13: ='SAF 011'!#REF! -> #REF!
A14: 5 | B14: ='SAF 011'!B44 -> 2.5.1-8988.2507 | C14: ='SAF 011'!E44 -> REACTIVOS P/EQUIPO; EQUIPO: AFERESIS, MARCA EQUIPO: HAEMONETICS MCS PLUS, NOMBRE DEL PRODUCTO: SOLUCION ACD FORMULA A ANTI COAGULANTE TIPO RIVERO FENVAL SOLUFLEX 679-S, PRESENTACION: 600ML | D14: NO | E14: ='SAF 011'!F44 -> UNIDAD | F14: ='SAF 011'!H44 -> 4350 | G14: ='SAF 011'!#REF! -> #REF!
A15: 6 | B15: ='SAF 011'!B45 -> 2.5.1-8988.372 | C15: ='SAF 011'!E45 -> REACTIVOS P/EQUIPO; EQUIPO: ANALIZ. X ENZIMO-INMUNO-ENSAYO, MARCA EQUIPO: ABBOTT, NOMBRE DEL PRODUCTO: DET. ANTIG. CORE/ANTIC ANTIHCV, PRESENTACION: ENVASE X 96 DETERM. | D15: NO | E15: ='SAF 011'!F45 -> CAJA | F15: ='SAF 011'!H45 -> 50545 | G15: ='SAF 011'!#REF! -> #REF!
A16: 7 | B16: ='SAF 011'!B48 -> 2.5.1-8988.197 | C16: ='SAF 011'!E48 -> REACTIVOS P/EQUIPO; EQUIPO: ANALIZADOR DE INMUNOENSAYO, MARCA EQUIPO: ABBOTT, NOMBRE DEL PRODUCTO: HIV 1-2, PRESENTACION: ENVASE X 96 DETERM. | D16: SI | E16: ='SAF 011'!F48 -> CAJA | F16: ='SAF 011'!H48 -> 23147 | G16: ='SAF 011'!#REF! -> #REF!
A17: 8 | B17: ='SAF 011'!B95 -> 2.5.1-8988.2287 | C17: ='SAF 011'!E95 -> REACTIVOS P/EQUIPO; EQUIPO: AUTOMATIZADO, MARCA EQUIPO: A DEFINIR, NOMBRE DEL PRODUCTO: RH/PHENO/KELL DONANTES, PRESENTACION: ENVASE X 48 DETERM. | D17: SI | E17: ='SAF 011'!F95 -> UNIDAD | F17: ='SAF 011'!H95 -> 795 | G17: ='SAF 011'!#REF! -> #REF!
A18: 9 | B18: ='SAF 011'!B124 -> 2.5.1-8988.2404 | C18: ='SAF 011'!E124 -> REACTIVOS P/EQUIPO; EQUIPO: ELECTROLUMINISCENCIA, MARCA EQUIPO: COBAS ROCHE, NOMBRE DEL PRODUCTO: ATG SUPERFICIE HEPATITIS B, PRESENTACION: ENVASE X 100 DETERM. | D18: NO | E18: ='SAF 011'!F124 -> CAJA | F18: ='SAF 011'!H124 -> 27546 | G18: ='SAF 011'!#REF! -> #REF!
A19: 10 | B19: ='SAF 011'!B125 -> 2.5.1-8988.2406 | C19: ='SAF 011'!E125 -> REACTIVOS P/EQUIPO; EQUIPO: ELECTROLUMINISCENCIA, MARCA EQUIPO: COBAS ROCHE, NOMBRE DEL PRODUCTO: REACTIVO CHAGAS, PRESENTACION: ENVASE X 100 DETERM. | D19: NO | E19: ='SAF 011'!F125 -> CAJA | F19: ='SAF 011'!H125 -> 51404 | G19: ='SAF 011'!#REF! -> #REF!
A20: 11 | B20: ='SAF 011'!B126 -> 2.5.1-8988.2405 | C20: ='SAF 011'!E126 -> REACTIVOS P/EQUIPO; EQUIPO: ELECTROLUMINISCENCIA, MARCA EQUIPO: COBAS ROCHE, NOMBRE DEL PRODUCTO: REACTIVO HTLV, PRESENTACION: ENVASE X 100 DETERM. | D20: NO | E20: ='SAF 011'!F126 -> CAJA | F20: ='SAF 011'!H126 -> 61263 | G20: ='SAF 011'!#REF! -> #REF!
A21: 12 | B21: ='SAF 011'!B127 -> 2.5.1-8988.2407 | C21: ='SAF 011'!E127 -> REACTIVOS P/EQUIPO; EQUIPO: ELECTROLUMINISCENCIA, MARCA EQUIPO: COBAS ROCHE, NOMBRE DEL PRODUCTO: REACTIVO SYPHILIS, PRESENTACION: ENVASE X 100 DETERM. | D21: NO | E21: ='SAF 011'!F127 -> CAJA | F21: ='SAF 011'!H127 -> 63289 | G21: ='SAF 011'!#REF! -> #REF!
A22: 13 | B22: ='SAF 011'!B131 -> 2.5.1-8988.1446 | C22: ='SAF 011'!E131 -> REACTIVOS P/EQUIPO; EQUIPO: MICROTUBOS C/GEL, MARCA EQUIPO: GRIFOLS, NOMBRE DEL PRODUCTO: TARJETAS LISS COOMBS, PRESENTACION: ENVASE X 48 UN | D22: SI | E22: ='SAF 011'!F131 -> UNIDAD | F22: ='SAF 011'!H131 -> 725 | G22: ='SAF 011'!#REF! -> #REF!
A23: 14 | B23: ='SAF 011'!B142 -> 2.5.1-9052.2130 | C23: ='SAF 011'!E142 -> REACTIVOS P/LAB. TEC. MANUAL ; NOMBRE: BIOZIMA CHAGAS, USO: DETECCION ANTICUERPOS ANTI-TRIPANOSOMA CRUZI, PRESENTACION: ENVASE X 192 DETERM. | D23: SI | E23: ='SAF 011'!F142 -> CAJA | F23: ='SAF 011'!H142 -> 10578 | G23: ='SAF 011'!#REF! -> #REF!
A24: 15 | B24: ='SAF 011'!B143 -> 2.5.1-9052.2131 | C24: ='SAF 011'!E143 -> REACTIVOS P/LAB. TEC. MANUAL ; NOMBRE: BIOZIMA RECONVINANTE CHAGAS, USO: DETECCION ANTICUERPOS ANTI-TRIPANOSOMA CRUZI, PRESENTACION: ENVASE X 192 DETERM. | D24: SI | E24: ='SAF 011'!F143 -> CAJA | F24: ='SAF 011'!H143 -> 11503 | G24: ='SAF 011'!#REF! -> #REF!
A25: 16 | B25: ='SAF 011'!B145 -> 2.5.1-9052.2126 | C25: ='SAF 011'!E145 -> REACTIVOS P/LAB. TEC. MANUAL ; NOMBRE: CELDAS DE REACCION TEMPERATURA AMBIENTE-SISTEMA DE INMUNO ENSAYO. TIPO ABBOT, USO:INMUNOSEROLOGIA ; PRESENTACION: 4000 DETERMINACIONES. | D25: NO | E25: ='SAF 011'!F145 -> CAJA | F25: ='SAF 011'!H145 -> 373520 | G25: ='SAF 011'!#REF! -> #REF!
A26: 17 | B26: ='SAF 011'!B147 -> 2.5.1-9052.2129 | C26: ='SAF 011'!E147 -> REACTIVOS P/LAB. TEC. MANUAL ; NOMBRE: COVIDAR IGG(SEROKIT MAS ELISA IGG), USO: DIAGNOSTICO SARS-COV-2, PRESENTACION: ENVASE X 192 DETERM. | D26: NO | E26: ='SAF 011'!F147 -> CAJA | F26: ='SAF 011'!H147 -> 64700 | G26: ='SAF 011'!#REF! -> #REF!
A27: 18 | B27: ='SAF 011'!B148 -> 2.5.1-9052.2129 | C27: ='SAF 011'!E148 -> REACTIVOS P/LAB. TEC. MANUAL ; NOMBRE: COVIDAR IGG(SEROKIT MAS ELISA IGG), USO: DIAGNOSTICO SARS-COV-2, PRESENTACION: ENVASE X 192 DETERM. | D27: SI | E27: ='SAF 011'!F148 -> CAJA | F27: ='SAF 011'!H148 -> 19744 | G27: ='SAF 011'!#REF! -> #REF!
A28: 19 | B28: ='SAF 011'!B151 -> 2.5.1-9052.1488 | C28: ='SAF 011'!E151 -> REACTIVOS P/LAB. TEC. MANUAL ; NOMBRE: ELISA ANTI HCV, USO: DETERMINACION DE ANTICUERPOS, PRESENTACION: ENVASE X 96 DETERM. | D28: SI | E28: ='SAF 011'!F151 -> CAJA | F28: ='SAF 011'!H151 -> 39806 | G28: ='SAF 011'!#REF! -> #REF!
A29: 20 | B29: ='SAF 011'!B152 -> 2.5.1-9052.740 | C29: ='SAF 011'!E152 -> REACTIVOS P/LAB. TEC. MANUAL ; NOMBRE: ELISA P/DET. ANTIC ANTI-HBSAG, USO: DETERMINACION HEPATITIS B, PRESENTACION: ENVASE X 96 DETERM. | D29: SI | E29: ='SAF 011'!F152 -> CAJA | F29: ='SAF 011'!H152 -> 14586 | G29: ='SAF 011'!#REF! -> #REF!
A30: 21 | B30: ='SAF 011'!B153 -> 2.5.1-9052.862 | C30: ='SAF 011'!E153 -> REACTIVOS P/LAB. TEC. MANUAL ; NOMBRE: ELISA PARA HTLV, USO: SEROLOGIA, PRESENTACION: ENVASE X 96 DETERM. | D30: SI | E30: ='SAF 011'!F153 -> CAJA | F30: ='SAF 011'!H153 -> 25747 | G30: ='SAF 011'!#REF! -> #REF!
A31: 22 | B31: ='SAF 011'!B158 -> 2.5.1-9052.2132 | C31: ='SAF 011'!E158 -> REACTIVOS P/LAB. TEC. MANUAL ; NOMBRE: REACTIVO ANTI HBC TEC. ELECTROLIMINISCENCIA TIPO ROCHE COBAS E411 CRACK, USO: INMUNOSEROLOGIA; PRESENTACION: X 100 DETERMINACIONES. | D31: NO | E31: ='SAF 011'!F158 -> CAJA | F31: ='SAF 011'!H158 -> 41413 | G31: ='SAF 011'!#REF! -> #REF!
A32: 23 | B32: ='SAF 011'!B159 -> 2.5.1-9052.2134 | C32: ='SAF 011'!E159 -> REACTIVOS P/LAB. TEC. MANUAL ; NOMBRE: REACTIVO ANTI HCV TEC. ELECTROLUMINISCENCIA TIPO ROCHE COBAS E411 CRACK; USO: INMUNOSEROLOGIA ; PRESENTACION: X 100 DETERMINACIONES. | D32: NO | E32: ='SAF 011'!F159 -> CAJA | F32: ='SAF 011'!H159 -> 93380 | G32: ='SAF 011'!#REF! -> #REF!
A33: 24 | B33: ='SAF 011'!B160 -> 2.5.1-9052.2133 | C33: ='SAF 011'!E160 -> REACTIVOS P/LAB. TEC. MANUAL ; NOMBRE: REACTIVO HC1V TEC. ELECTROLUNINISCENCIA TIPO ROCHE COBAS E411 CRACK, USO: INMUNOSEROLOGIA ; PRESENTACION: X 100 DETERMINACIONES. | D33: NO | E33: ='SAF 011'!F160 -> CAJA | F33: ='SAF 011'!H160 -> 27563 | G33: ='SAF 011'!#REF! -> #REF!
A34: 25 | B34: ='SAF 011'!B161 -> 2.5.1-9052.294 | C34: ='SAF 011'!E161 -> REACTIVOS P/LAB. TEC. MANUAL ; NOMBRE: REACTIVO HUDDLESON, USO: DIAGNOSTICO DE BRUCELOSIS, PRESENTACION: ENVASE X 5 mL | D34: SI | E34: ='SAF 011'!F161 -> UNIDAD | F34: ='SAF 011'!H161 -> 1184 | G34: ='SAF 011'!#REF! -> #REF!
A35: 26 | B35: ='SAF 011'!B163 -> 2.5.1-9052.288 | C35: ='SAF 011'!E163 -> REACTIVOS P/LAB. TEC. MANUAL ; NOMBRE: SUERO COOMBS MONOES. ANTI-IGA, USO: HEMOTERAPIA, PRESENTACION: ENVASE X 5 mL | D35: SI | E35: ='SAF 011'!F163 -> UNIDAD | F35: ='SAF 011'!H163 -> 1325 | G35: ='SAF 011'!#REF! -> #REF!
A36: 27 | B36: ='SAF 011'!B166 -> 2.5.1-9052.247 | C36: ='SAF 011'!E166 -> REACTIVOS P/LAB. TEC. MANUAL ; NOMBRE: SUERO HEMOTIPIFICADOR ANTI-AB, USO: HEMOTERAPIA, PRESENTACION: ENVASE X 10 mL | D36: SI | E36: ='SAF 011'!F166 -> CAJA | F36: ='SAF 011'!H166 -> 888 | G36: ='SAF 011'!#REF! -> #REF!
A37: 28 | B37: ='SAF 011'!B170 -> 2.5.1-9052.354 | C37: ='SAF 011'!E170 -> REACTIVOS P/LAB. TEC. MANUAL ; NOMBRE: TOXOTEST HAI, USO: INMUNOLOGIA, PRESENTACION: ENVASE X 96 DETERM. | D37: NO | E37: ='SAF 011'!F170 -> CAJA | F37: ='SAF 011'!H170 -> 16645 | G37: ='SAF 011'!#REF! -> #REF!
A38: 29 | B38: ='SAF 011'!B172 -> 2.5.1-9052.645 | C38: ='SAF 011'!E172 -> REACTIVOS P/LAB. TEC. MANUAL ; NOMBRE: VDRL, USO: DIAGNOSTICO, PRESENTACION: ENVASE X 250 DETERM. | D38: SI | E38: ='SAF 011'!F172 -> CAJA | F38: ='SAF 011'!H172 -> 3800 | G38: ='SAF 011'!#REF! -> #REF!
A39: 30 | B39: ='SAF 011'!B173 -> 2.5.1-9052.2123 | C39: ='SAF 011'!E173 -> REACTIVOS P/LAB. TEC. MANUAL ; NOMBRE:SARS- COV-2 IGM CONTROL, USO: IDENTIFICACION DE ANTICUERPOS, PRESENTACION: 2 X ENVASE X 10 ML | D39: SI | E39: ='SAF 011'!F173 -> CAJA | F39: ='SAF 011'!H173 -> 17788 | G39: ='SAF 011'!#REF! -> #REF!
A40: 31 | B40: ='SAF 011'!B174 -> 2.5.1-9052.2155 | C40: ='SAF 011'!E174 -> REACTIVOS P/LAB. TEC. MANUAL, NOMBRE:CMV CITOMEGALOVIRUS IGM , USO: METODO ELISA TIPO WIENER, PRESENTACION: 96 DETERMINACIONES | D40: NO | E40: ='SAF 011'!F174 -> CAJA | F40: ='SAF 011'!H174 -> 19749 | G40: ='SAF 011'!#REF! -> #REF!
A41: 32 | B41: ='SAF 011'!B178 -> 2.5.1-9052.2127 | C41: ='SAF 011'!E178 -> REACTIVOS P/LAB. TEC. MANUAL; NOMBRE: REACTIVO PARA HEPATITIS C, USO: DETECCION DE ANTIGENO- ANTICUERPO TIPO BIORAD ; PRESENTACION: X 96 DETERMINACIONES. | D41: SI | E41: ='SAF 011'!F178 -> CAJA | F41: ='SAF 011'!H178 -> 130000 | G41: ='SAF 011'!#REF! -> #REF!
A42: 33 | B42: ='SAF 011'!B179 -> 2.5.1-9052.2128 | C42: ='SAF 011'!E179 -> REACTIVOS P/LAB. TEC: MANUAL; NOMBRE: DETECCION DE ANTI HB CORE POR METODO DE ELISA EN MICROPLACAS, USO: INMUNOSEROLOGIA TIPO BIORAD; PRESENTACION: X 96 DETERMINACIONES | D42: SI | E42: ='SAF 011'!F179 -> CAJA | F42: ='SAF 011'!H179 -> 20160 | G42: ='SAF 011'!#REF! -> #REF!
A43: 34 | B43: ='SAF 011'!B180 -> 2.5.1-9052.2162 | C43: ='SAF 011'!E180 -> REACTIVOS PARA LABORATORIO TEC. MANUAL, NOMBRE: CHAGATEST ELISA LISADO TIPO WIENER , USO: DIAGNOSTICO, PRESENTACION: CAJA X 96 DETERMINACIONES | D43: NO | E43: ='SAF 011'!F180 -> CAJA | F43: ='SAF 011'!H180 -> 10206 | G43: ='SAF 011'!#REF! -> #REF!
A44: 35 | B44: ='SAF 011'!B181 -> 2.5.1-9052.2161 | C44: ='SAF 011'!E181 -> REACTIVOS PARA LABORATORIO TEC. MANUAL, NOMBRE: CHAGATEST ELISA RECOMBINANTE (V4,0) TIPO WIENER , USO: DIAGNOSTICO , PRESENTACION: CAJA X 96 DETERMINACIONES | D44: NO | E44: ='SAF 011'!F181 -> CAJA | F44: ='SAF 011'!H181 -> 11295 | G44: ='SAF 011'!#REF! -> #REF!
A45: 36 | B45: ='SAF 011'!B182 -> 2.5.1-9052.2156 | C45: ='SAF 011'!E182 -> REACTIVOS PARA LABORATORIO TEC. MANUAL, NOMBRE: IDENTIERA DIANA, USO: DIAGNOSTICO, PRESENTACION: CAJA DE 11 FRASCOS DE 5ML | D45: NO | E45: ='SAF 011'!F182 -> CAJA | F45: ='SAF 011'!H182 -> 29160 | G45: ='SAF 011'!#REF! -> #REF!
A46: 37 | B46: ='SAF 011'!B183 -> 2.5.1-9052.2157 | C46: ='SAF 011'!E183 -> REACTIVOS PARA LABORATORIO TEC. MANUAL, NOMBRE: PANEL SARASCAN DIANA 2, USO: DIAGNOSTICO, PRESENTACION: CAJA X 2 FRASCO DE 10ML | D46: NO | E46: ='SAF 011'!F183 -> CAJA | F46: ='SAF 011'!H183 -> 22500 | G46: ='SAF 011'!#REF! -> #REF!
A47: 38 | B47: ='SAF 011'!B184 -> 2.5.1-9052.2159 | C47: ='SAF 011'!E184 -> REACTIVOS PARA LABORATORIO TEC. MANUAL, NOMBRE: PANEL SERIGROUP DIANA A1/B, USO: DIAGNOSTICO, PRESENTACION: CAJA 1 X 10ML | D47: SI | E47: ='SAF 011'!F184 -> CAJA | F47: ='SAF 011'!H184 -> 12900 | G47: ='SAF 011'!#REF! -> #REF!
A48: 39 | B48: ='SAF 011'!B185 -> 2.5.1-9052.2158 | C48: ='SAF 011'!E185 -> REACTIVOS PARA LABORATORIO TEC. MANUAL, NOMBRE: PANEL SERO CYTE, USO: DIAGNOSTICO, PRESENTACION: CAJA X 3 UNID. DE 10ML | D48: SI | E48: ='SAF 011'!F185 -> CAJA | F48: ='SAF 011'!H185 -> 18500 | G48: ='SAF 011'!#REF! -> #REF!
A49: 40 | B49: ='SAF 011'!B186 -> 2.5.1-9052.2160 | C49: ='SAF 011'!E186 -> REACTIVOS PARA LABORATORIO TEC. MANUAL; NOMBRE: SOLUCION DG SOL, USO: DIAGNOSTICO, PRESENTACION: CAJA X 2 UNID 100ML | D49: NO | E49: ='SAF 011'!F186 -> CAJA | F49: ='SAF 011'!H186 -> 4980 | G49: ='SAF 011'!#REF! -> #REF!
A50: Costo total estimado: PESOS CATORCE MILLONES QUINIENTOS TRES MIL DOSCIENTOS TRECE CON 00/100 | F50: =SUMPRODUCT(F10:F49,G10:G49) -> #REF!

Sheet APG BCO DE SANGRE
A1: EJERCICIO: | D1: 2022 | P1: AUTORIZACION PARA GASTAR
A4: JURISDICCIÓN: | G4: ='NP BCO DE SANGRE'!C2 -> 040 - MINISTERIO DE SALUD
A5: SAF: | G5: ='NP BCO DE SANGRE'!C3 -> 011 - DIRECCION PROVINCIAL DE ADMINISTRACION - MINISTERIO DE SALUD
A6: UNIDAD EJECUTORA: | G6: ='NP BCO DE SANGRE'!C4 -> 747 - DIRECCION PROVINCIAL BANCO DE SANGRE
A7: DEPENDENCIA SOLICITANTE: | G7: ='NP BCO DE SANGRE'!C5 -> 747 - DIRECCION PROVINCIAL BANCO DE SANGRE
A8: AUTORIZACIÓN:
A9: Señor Director de Administración o Titular del Servicio Administrativo Financiero:
A10: Autorizo la realización de los trámites correspondientes, a fin de proveer a este Organismo los bienes que se detallan en Nota de Pedido N°....... , afectando la erogación resultante a los créditos presupuestarios aprobados a favor de esta Unidad Ejecutora, conforme al siguiente detalle:
A12: IMPUTACIÓN PRESUPUESTARIA
A13: CÓDIGO | O13: DENOMINACIÓN DE LA PARTIDA PRESUPUESTARIA | Q13: IMPORTE
A14: PR | B14: SB | C14: PY | D14: AC | E14: OB | F14: UG | G14: FIN | H14: FUN | I14: I | J14: P | K14: P | L14: SubP | M14: M | N14: FF
A15: 27 | D15: 1 | F15: 4901 | G15: 3 | H15: 1 | I15: 2 | J15: 5 | K15: 1 | M15: 1 | N15: 1.1 | O15: COMPUESTOS QUIMICOS | Q15: ='NP BCO DE SANGRE'!F50 -> #REF!
A38: TOTAL DE PESOS: CATORCE MILLONES QUINIENTOS TRES MIL DOSCIENTOS TRECE CON 00/100.- | Q38: =SUM(Q15:Q37) -> #REF!
A40: JUSTIFICACIÓN:
A41: ='NP BCO DE SANGRE'!C6 -> ADQUISICION DEL RUBRO REACTIVOS PARA LABORATORIO
