Workbook

Sheet SAF 011
A1: 2022
B2: Pedido de Necesidades Trimestrales
A4: JURISDICCION: | C4: 040 - MINISTERIO DE SALUD
A5: SAF N°: | C5: 011 - DIRECCION PROVINCIAL DE ADMINISTRACION - MINISTERIO DE SALUD
A6: EJERCICIO: | C6: 2022
A7: TRIMESTRE: | C7: PRIMERO
A9: ID | B9: CODIGO ITEM | C9: RUBRO DE COMPRA | D9: I.P.P. | E9: DESCRIPCION | F9: UNIDAD DE MEDIDA | G9: CANTIDAD TOTAL | H9: PRECIO UNITARIO ESTIMADO | I9: IMPORTE TOTAL ESTIMADO | J9: ESPECIFICACION TECNICA | L9: ESPECIFICACION TECNICA PROGRAMACION | M9: DESCRIPCION | O9: IPP | Q9: UNIDAD DE MEDIDA | S9: PRECIO UNITARIO ESTIMADO
A10: 1 | B10: 2.5.2-710.4 | C10: PROD. MEDICO/FARMACEUTICOS/LAB | D10: 252 | E10: AGUA OXIGENADA; CAPACIDAD: 1000 CM3, VOLUMEN: 10, PRESENTACION: ENVASE X 1000 CM3 | F10: BOTELLA | G10: 1030 | H10: 128.59 | I10: =+G10*H10 -> 132447.7 | M10: AGUA OXIGENADA; CAPACIDAD: 1000 CM3, VOLUMEN: 10, PRESENTACION: ENVASE X 1000 CM3 | N10: =E10=M10 -> TRUE | O10: =+VLOOKUP(E10,'[1]Necesidades Trimestrales'!$H$10:$I$43,2,0) -> 252 | P10: =O10=D10 -> TRUE | Q10: =+VLOOKUP(E10,'[1]Necesidades Trimestrales'!$H$10:$K$43,4,0) -> BOTELLA | R10: =Q10=F10 -> TRUE | S10: =+VLOOKUP(E10,'[1]Necesidades Trimestrales'!$H$10:$M$43,6,0) -> 128.59 | T10: =S10=H10 -> TRUE | U10: =+G10*H10-I10 -> 0
A11: 2 | B11: 2.5.2-711.41 | C11: PROD. MEDICO/FARMACEUTICOS/LAB | D11: 252 | E11: ALCOHOL USO MEDICINAL; PUREZA: 70 %, PRESENTACION: GEL ENVASE X 250 CM3 | F11: UNIDAD | G11: 120 | H11: 158 | I11: =+G11*H11 -> 18960 | M11: ALCOHOL USO MEDICINAL; PUREZA: 70 %, PRESENTACION: GEL ENVASE X 250 CM3 | N11: =E11=M11 -> TRUE | O11: =+VLOOKUP(E11,'[1]Necesidades Trimestrales'!$H$10:$I$43,2,0) -> 252 | P11: =O11=D11 -> TRUE | Q11: =+VLOOKUP(E11,'[1]Necesidades Trimestrales'!$H$10:$K$43,4,0) -> UNIDAD | R11: =Q11=F11 -> TRUE | S11: =+VLOOKUP(E11,'[1]Necesidades Trimestrales'!$H$10:$M$43,6,0) -> 158 | T11: =S11=H11 -> TRUE | U11: =+G11*H11-I11 -> 0
A12: 3 | B12: 2.5.2-711.32 | C12: PROD. MEDICO/FARMACEUTICOS/LAB | D12: 252 | E12: ALCOHOL USO MEDICINAL; PUREZA: 96 %, PRESENTACION: ENVASE X 1000 CM3 | F12: BOTELLA | G12: 400 | H12: 201 | I12: =+G12*H12 -> 80400 | M12: ALCOHOL USO MEDICINAL; PUREZA: 96 %, PRESENTACION: ENVASE X 1000 CM3 | N12: =E12=M12 -> TRUE | O12: =+VLOOKUP(E12,'[1]Necesidades Trimestrales'!$H$10:$I$43,2,0) -> 252 | P12: =O12=D12 -> TRUE | Q12: =+VLOOKUP(E12,'[1]Necesidades Trimestrales'!$H$10:$K$43,4,0) -> BOTELLA | R12: =Q12=F12 -> TRUE | S12: =+VLOOKUP(E12,'[1]Necesidades Trimestrales'!$H$10:$M$43,6,0) -> 201 | T12: =S12=H12 -> TRUE | U12: =+G12*H12-I12 -> 0
A13: 4 | B13: 2.5.2-711.1 | C13: PROD. MEDICO/FARMACEUTICOS/LAB | D13: 252 | E13: ALCOHOL USO MEDICINAL; PUREZA: 96 %, PRESENTACION: ENVASE X 500 CM3, CAPACIDAD: 500 CM3 | F13: BOTELLA | G13: 300 | H13: 108 | I13: =+G13*H13 -> 32400 | M13: ALCOHOL USO MEDICINAL; PUREZA: 96 %, PRESENTACION: ENVASE X 500 CM3, CAPACIDAD: 500 CM3 | N13: =E13=M13 -> TRUE | O13: =+VLOOKUP(E13,'[1]Necesidades Trimestrales'!$H$10:$I$43,2,0) -> 252 | P13: =O13=D13 -> TRUE | Q13: =+VLOOKUP(E13,'[1]Necesidades Trimestrales'!$H$10:$K$43,4,0) -> BOTELLA | R13: =Q13=F13 -> TRUE | S13: =+VLOOKUP(E13,'[1]Necesidades Trimestrales'!$H$10:$M$43,6,0) -> 108 | T13: =S13=H13 -> TRUE | U13: =+G13*H13-I13 -> 0
A14: 5 | B14: 2.5.2-1723.50 | C14: PROD. MEDICO/FARMACEUTICOS/LAB | D14: 252 | E14: ANTISEPTICOS LOCALES P/PERSONA; DROGA GENERICA: IODOPOVIDONA 10%, FORMA FARMACEUTICA: SOLUCION, PRESENTACION: ENVASE X 1 L, TIPO: MONODROGA | F14: BOTELLA | G14: 365 | H14: 573 | I14: =+G14*H14 -> 209145 | J14: con valvula atomizadora | L14: =+VLOOKUP(E14,'[1]Necesidades Trimestrales'!$H$10:$J$43,3,0) -> con valvula atomizadora | M14: ANTISEPTICOS LOCALES P/PERSONA; DROGA GENERICA: IODOPOVIDONA 10%, FORMA FARMACEUTICA: SOLUCION, PRESENTACION: ENVASE X 1 L, TIPO: MONODROGA | N14: =E14=M14 -> TRUE | O14: =+VLOOKUP(E14,'[1]Necesidades Trimestrales'!$H$10:$I$43,2,0) -> 252 | P14: =O14=D14 -> TRUE | Q14: =+VLOOKUP(E14,'[1]Necesidades Trimestrales'!$H$10:$K$43,4,0) -> BOTELLA | R14: =Q14=F14 -> TRUE | S14: =+VLOOKUP(E14,'[1]Necesidades Trimestrales'!$H$10:$M$43,6,0) -> 573 | T14: =S14=H14 -> TRUE | U14: =+G14*H14-I14 -> 0
A15: 6 | B15: 2.5.2-1723.173 | C15: PROD. MEDICO/FARMACEUTICOS/LAB | D15: 295 | E15: ANTISEPTICOS LOCALES P/PERSONA; TIPO: MONODROGA, DROGA GENERICA: IODOFORMADA AL 10% , FORMA FARMACEUTICA: GASA, PRESENTACION: DE 10X10, 15 UNIDADES POR PACK | F15: CAJA | G15: 50 | H15: 950 | I15: =+G15*H15 -> 47500 | M15: ANTISEPTICOS LOCALES P/PERSONA; TIPO: MONODROGA, DROGA GENERICA: IODOFORMADA AL 10% , FORMA FARMACEUTICA: GASA, PRESENTACION: DE 10X10, 15 UNIDADES POR PACK | N15: =E15=M15 -> TRUE | O15: =+VLOOKUP(E15,'[1]Necesidades Trimestrales'!$H$10:$I$43,2,0) -> 295 | P15: =O15=D15 -> TRUE | Q15: =+VLOOKUP(E15,'[1]Necesidades Trimestrales'!$H$10:$K$43,4,0) -> CAJA | R15: =Q15=F15 -> TRUE | S15: =+VLOOKUP(E15,'[1]Necesidades Trimestrales'!$H$10:$M$43,6,0) -> 950 | T15: =S15=H15 -> TRUE | U15: =+G15*H15-I15 -> 0
A16: 7 | B16: 2.5.2-1723.30 | C16: PROD. MEDICO/FARMACEUTICOS/LAB | D16: 252 | E16: ANTISEPTICOS LOCALES P/PERSONA; TIPO: MONODROGA, DROGA GENERICA: IODOPOVIDONA, FORMA FARMACEUTICA: SOLUCION, PRESENTACION: BIDON X 5 L | F16: BIDON | G16: 50 | H16: 2250 | I16: =+G16*H16 -> 112500 | M16: ANTISEPTICOS LOCALES P/PERSONA; TIPO: MONODROGA, DROGA GENERICA: IODOPOVIDONA, FORMA FARMACEUTICA: SOLUCION, PRESENTACION: BIDON X 5 L | N16: =E16=M16 -> TRUE | O16: =+VLOOKUP(E16,'[1]Necesidades Trimestrales'!$H$10:$I$43,2,0) -> 252 | P16: =O16=D16 -> TRUE | Q16: =+VLOOKUP(E16,'[1]Necesidades Trimestrales'!$H$10:$K$43,4,0) -> BIDON | R16: =Q16=F16 -> TRUE | S16: =+VLOOKUP(E16,'[1]Necesidades Trimestrales'!$H$10:$M$43,6,0) -> 2250 | T16: =S16=H16 -> TRUE | U16: =+G16*H16-I16 -> 0
A17: 8 | B17: 2.5.2-1723.35 | C17: PROD. MEDICO/FARMACEUTICOS/LAB | D17: 252 | E17: ANTISEPTICOS LOCALES P/PERSONA; TIPO: MONODROGA, DROGA GENERICA: NITROFURAZONA, FORMA FARMACEUTICA: SOLUCION, PRESENTACION: FRASCO X 1 L | F17: BOTELLA | G17: 40 | H17: 859 | I17: =+G17*H17 -> 34360 | M17: ANTISEPTICOS LOCALES P/PERSONA; TIPO: MONODROGA, DROGA GENERICA: NITROFURAZONA, FORMA FARMACEUTICA: SOLUCION, PRESENTACION: FRASCO X 1 L | N17: =E17=M17 -> TRUE | O17: =+VLOOKUP(E17,'[1]Necesidades Trimestrales'!$H$10:$I$43,2,0) -> 252 | P17: =O17=D17 -> TRUE | Q17: =+VLOOKUP(E17,'[1]Necesidades Trimestrales'!$H$10:$K$43,4,0) -> BOTELLA | R17: =Q17=F17 -> TRUE | S17: =+VLOOKUP(E17,'[1]Necesidades Trimestrales'!$H$10:$M$43,6,0) -> 859 | T17: =S17=H17 -> TRUE | U17: =+G17*H17-I17 -> 0
A18: 9 | B18: 2.9.1-6956.122 | C18: ELEMENTOS DE LIMPIEZA | D18: 252 | E18: ARTICULOS DE TOCADOR; TIPO: JABON LIQUIDO HIPOALERGENICO, PRESENTACION: ENVASE X 800 ML BAG IN BOX | F18: BAG IN BOX | G18: 100 | H18: 1150 | I18: =+G18*H18 -> 115000 | J18: Jabón Líquido hipoalergenico. Ph Dérmico. No contiene cloruro de sodio, ni parabenos. Envase BAG IN BOX por 800 ml.Tipo JL4 ADOX. | L18: =+VLOOKUP(E18,'[1]Necesidades Trimestrales'!$H$10:$J$43,3,0) -> Jabón Líquido hipoalergenico. Ph Dérmico. No contiene cloruro de sodio, ni parabenos. Envase BAG IN BOX por 800 ml.Tipo JL4 ADOX. | M18: ARTICULOS DE TOCADOR; TIPO: JABON LIQUIDO HIPOALERGENICO, PRESENTACION: ENVASE X 800 ML BAG IN BOX | N18: =E18=M18 -> TRUE | O18: =+VLOOKUP(E18,'[1]Necesidades Trimestrales'!$H$10:$I$43,2,0) -> 252 | P18: =O18=D18 -> TRUE | Q18: =+VLOOKUP(E18,'[1]Necesidades Trimestrales'!$H$10:$K$43,4,0) -> BAG IN BOX | R18: =Q18=F18 -> TRUE | S18: =+VLOOKUP(E18,'[1]Necesidades Trimestrales'!$H$10:$M$43,6,0) -> 1150 | T18: =S18=H18 -> TRUE | U18: =+G18*H18-I18 -> 0
A19: 10 | B19: 2.5.1-9065.27 | C19: QUIMICOS | D19: 251 | E19: DESINFECTANTES Y DETERGENTES; PRINCIPIO ACTIVO: AMONIO CUATERNARIO, CALIDAD: COMERCIAL, CONCENTRACION/PUREZA: 99 %, PRESENTACION: ENVASE X 5 L | F19: BIDON | G19: 50 | H19: 9229.2 | I19: =+G19*H19 -> 461460 | J19: USO HOSPITALARIO. Limpiador para areas criticas en base a amonios cuaternarios de 4TA Generacion.Dilucion 2,5 ml/ litro .Aprobacion ANMAT | L19: =+VLOOKUP(E19,'[1]Necesidades Trimestrales'!$H$10:$J$43,3,0) -> USO HOSPITALARIO. Limpiador para areas criticas en base a amonios cuaternarios de 4TA Generacion.Dilucion 2,5 ml/ litro .Aprobacion ANMAT | M19: DESINFECTANTES Y DETERGENTES; PRINCIPIO ACTIVO: AMONIO CUATERNARIO, CALIDAD: COMERCIAL, CONCENTRACION/PUREZA: 99 %, PRESENTACION: ENVASE X 5 L | N19: =E19=M19 -> TRUE | O19: =+VLOOKUP(E19,'[1]Necesidades Trimestrales'!$H$10:$I$43,2,0) -> 251 | P19: =O19=D19 -> TRUE | Q19: =+VLOOKUP(E19,'[1]Necesidades Trimestrales'!$H$10:$K$43,4,0) -> BIDON | R19: =Q19=F19 -> TRUE | S19: =+VLOOKUP(E19,'[1]Necesidades Trimestrales'!$H$10:$M$43,6,0) -> 9229.2 | T19: =S19=H19 -> TRUE | U19: =+G19*H19-I19 -> 0
A20: 11 | B20: 2.5.1-9065.53 | C20: QUIMICOS | D20: 251 | E20: DESINFECTANTES Y DETERGENTES; PRINCIPIO ACTIVO: GLUTARALDEHIDO CON SULFACTANTE, CALIDAD: BIOLOGIA MOLECULAR, CONCENTRACION/PUREZA: 2 %, PRESENTACION: ENVASE X 4 L | F20: BIDON | G20: 50 | H20: 1680 | I20: =+G20*H20 -> 84000 | M20: DESINFECTANTES Y DETERGENTES; PRINCIPIO ACTIVO: GLUTARALDEHIDO CON SULFACTANTE, CALIDAD: BIOLOGIA MOLECULAR, CONCENTRACION/PUREZA: 2 %, PRESENTACION: ENVASE X 4 L | N20: =E20=M20 -> TRUE | O20: =+VLOOKUP(E20,'[1]Necesidades Trimestrales'!$H$10:$I$43,2,0) -> 251 | P20: =O20=D20 -> TRUE | Q20: =+VLOOKUP(E20,'[1]Necesidades Trimestrales'!$H$10:$K$43,4,0) -> BIDON | R20: =Q20=F20 -> TRUE | S20: =+VLOOKUP(E20,'[1]Necesidades Trimestrales'!$H$10:$M$43,6,0) -> 1680 | T20: =S20=H20 -> TRUE | U20: =+G20*H20-I20 -> 0
A21: 12 | B21: 2.5.2-1726.492 | C21: PROD. MEDICO/FARMACEUTICOS/LAB | D21: 251 | E21: SOLUCIONES P/MEDICINA; TIPO: FORMOL AL 40 %, PRESENTACION: ENVASE X 1 L | F21: BOTELLA | G21: 10 | H21: 661 | I21: =+G21*H21 -> 6610 | M21: SOLUCIONES P/MEDICINA; TIPO: FORMOL AL 40 %, PRESENTACION: ENVASE X 1 L | N21: =E21=M21 -> TRUE | O21: =+VLOOKUP(E21,'[1]Necesidades Trimestrales'!$H$10:$I$43,2,0) -> 251 | P21: =O21=D21 -> TRUE | Q21: =+VLOOKUP(E21,'[1]Necesidades Trimestrales'!$H$10:$K$43,4,0) -> BOTELLA | R21: =Q21=F21 -> TRUE | S21: =+VLOOKUP(E21,'[1]Necesidades Trimestrales'!$H$10:$M$43,6,0) -> 661 | T21: =S21=H21 -> TRUE | U21: =+G21*H21-I21 -> 0
E22: TOTAL RUBRO ANTISEPTICOS Y DESINFECTANTES | I22: =SUM(I10:I21) -> 1334782.7
C24: DETALLE TECNICO Y ESPECIFICACIONES ITEMS 1 AL 12 | D24: ANEXO 1-Para oferentes de la Provincia de Catamarca deberán presentar Habilitación Provincial para comercializar el producto que cotizan. 2-Para el resto de oferentes deberán presentar Certificado de Inscripción de ANMAT vigente al momento de la oferta, el mismo deberá ser correspondiente al objeto de la contratación y de encontrarse vencido adjuntar la solicitud de renovación. 3-No se aceptarán ofertas de productos no registrados y autorizada su venta por ANMAT. Se deberá especificar en cada ítem de la propuesta, marca y número de certificado otorgado por dicho ente regulador. 4-Los productos deberán tener un vencimiento posterior a doce (12) meses a partir de la fecha de su recepción.
C26: Plazos de entrega | D26: veinte (20) dias habiles
C28: Lugar de Entrega: | D28: DIR. PROV. DE FARMACIA E INSUMOS - CHACABUCO N° 169 - en el horario de 8:00hs a 12:00hs de lunes a viernes
C30: Calidad Minima esperada
C32: Mantenimiento | D32: cuarenta y cinco (45) días
C33: Especificidades Item N° 5:
C34: Descripción técnica: con valvula atomizadora
C36: Especificidades Item N° 9:
C37: Descripción técnica: Jabón Líquido hipoalergenico. Ph Dérmico. No contiene cloruro de sodio, ni parabenos. Envase BAG IN BOX por 800 ml.Tipo JL4 ADOX.
C39: Especificidades Item N° 10:
C40: Descripción técnica: USO HOSPITALARIO. Limpiador para areas criticas en base a amonios cuaternarios de 4TA Generacion.Dilucion 2,5 ml/ litro .Aprobacion ANMAT

Sheet NP FARMACIA
A1: NOTA DE PEDIDO | J1: N° | K1: 12/2022
A3: JURISDICCIÓN: | D3: ='SAF 011'!C4 -> 040 - MINISTERIO DE SALUD
A4: SAF: | D4: ='SAF 011'!C5 -> 011 - DIRECCION PROVINCIAL DE ADMINISTRACION - MINISTERIO DE SALUD
A5: UNIDAD EJECUTORA: | D5: DIRECCION PROVINCIAL DE FARMACIA E INSUMOS
A6: DEPENDENCIA SOLICITANTE: | D6: DIRECCION PROVINCIAL DE FARMACIA E INSUMOS
A7: PERIODO UTILIZACIÓN: | D7: SEMESTRAL
A8: OBJETO: | D8: ADQUISICION DEL RUBRO ANTISEPTICOS Y DESINFECTANTES
A10: Ítem | B10: Codigo Item | C10: DESCRIPCIÓN | H10: Adjunta Detalle Técnico | I10: Unidad Medida | J10: Precio Unitario Estimado | K10: Cantidad Solicitada
A12: 1 | B12: ='SAF 011'!B10 -> 2.5.2-710.4 | C12: ='SAF 011'!E10 -> AGUA OXIGENADA; CAPACIDAD: 1000 CM3, VOLUMEN: 10, PRESENTACION: ENVASE X 1000 CM3 | H12: SI | I12: ='SAF 011'!F10 -> BOTELLA | J12: ='SAF 011'!H10 -> 128.59 | K12: ='SAF 011'!#REF! -> #REF! | L12: 252 | M12: =B12='SAF 011'!B10 -> TRUE | N12: =+J12*K12 -> #REF! | O12: =C12='SAF 011'!E10 -> TRUE
A13: 2 | B13: ='SAF 011'!B14 -> 2.5.2-1723.50 | C13: ='SAF 011'!E14 -> ANTISEPTICOS LOCALES P/PERSONA; DROGA GENERICA: IODOPOVIDONA 10%, FORMA FARMACEUTICA: SOLUCION, PRESENTACION: ENVASE X 1 L, TIPO: MONODROGA | H13: SI | I13: ='SAF 011'!F14 -> BOTELLA | J13: ='SAF 011'!H14 -> 573 | K13: ='SAF 011'!#REF! -> #REF! | L13: 252 | M13: =B13='SAF 011'!B14 -> TRUE | N13: =+J13*K13 -> #REF! | O13: =C13='SAF 011'!E14 -> TRUE
A14: 3 | B14: ='SAF 011'!B16 -> 2.5.2-1723.30 | C14: ='SAF 011'!E16 -> ANTISEPTICOS LOCALES P/PERSONA; TIPO: MONODROGA, DROGA GENERICA: IODOPOVIDONA, FORMA FARMACEUTICA: SOLUCION, PRESENTACION: BIDON X 5 L | H14: SI | I14: ='SAF 011'!F16 -> BIDON | J14: ='SAF 011'!H16 -> 2250 | K14: ='SAF 011'!#REF! -> #REF! | L14: 252 | M14: =B14='SAF 011'!B16 -> TRUE | N14: =+J14*K14 -> #REF! | O14: =C14='SAF 011'!E16 -> TRUE
A15: 4 | B15: ='SAF 011'!B17 -> 2.5.2-1723.35 | C15: ='SAF 011'!E17 -> ANTISEPTICOS LOCALES P/PERSONA; TIPO: MONODROGA, DROGA GENERICA: NITROFURAZONA, FORMA FARMACEUTICA: SOLUCION, PRESENTACION: FRASCO X 1 L | H15: SI | I15: ='SAF 011'!F17 -> BOTELLA | J15: ='SAF 011'!H17 -> 859 | K15: ='SAF 011'!#REF! -> #REF! | L15: 252 | M15: =B15='SAF 011'!B17 -> TRUE | N15: =+J15*K15 -> #REF! | O15: =C15='SAF 011'!E17 -> TRUE
A16: 5 | B16: ='SAF 011'!B18 -> 2.9.1-6956.122 | C16: ='SAF 011'!E18 -> ARTICULOS DE TOCADOR; TIPO: JABON LIQUIDO HIPOALERGENICO, PRESENTACION: ENVASE X 800 ML BAG IN BOX | H16: SI | I16: ='SAF 011'!F18 -> BAG IN BOX | J16: ='SAF 011'!H18 -> 1150 | K16: ='SAF 011'!#REF! -> #REF! | L16: 252 | M16: =B16='SAF 011'!B18 -> TRUE | N16: =+J16*K16 -> #REF! | O16: =C16='SAF 011'!E18 -> TRUE
A17: 6 | B17: ='SAF 011'!B20 -> 2.5.1-9065.53 | C17: ='SAF 011'!E20 -> DESINFECTANTES Y DETERGENTES; PRINCIPIO ACTIVO: GLUTARALDEHIDO CON SULFACTANTE, CALIDAD: BIOLOGIA MOLECULAR, CONCENTRACION/PUREZA: 2 %, PRESENTACION: ENVASE X 4 L | H17: SI | I17: ='SAF 011'!F20 -> BIDON | J17: ='SAF 011'!H20 -> 1680 | K17: ='SAF 011'!#REF! -> #REF! | L17: 251 | M17: =B17='SAF 011'!B20 -> TRUE | N17: =+J17*K17 -> #REF! | O17: =C17='SAF 011'!E20 -> TRUE
A18: 7 | B18: ='SAF 011'!B21 -> 2.5.2-1726.492 | C18: ='SAF 011'!E21 -> SOLUCIONES P/MEDICINA; TIPO: FORMOL AL 40 %, PRESENTACION: ENVASE X 1 L | H18: SI | I18: ='SAF 011'!F21 -> BOTELLA | J18: ='SAF 011'!H21 -> 661 | K18: ='SAF 011'!#REF! -> #REF! | L18: 251 | M18: =B18='SAF 011'!B21 -> TRUE | N18: =+J18*K18 -> #REF! | O18: =C18='SAF 011'!E21 -> TRUE
A20: Costo total estimado: SEISCIENTOS OCHENTA Y UN MIL SEISCIENTOS DIEZ CON 00/100.- | J20: =+N20 -> #REF! | N20: =SUM(N12:N19) -> #REF!
K22: 252 | L22: =+J12*K12+J13*K13+J14*K14+J15*K15+J16*K16 -> #REF! | M22: =+L22+80400+51360 -> #REF! | N22: =+N20-N16-N17 -> #REF!
K23: 251 | L23: =+J17*K17+J18*K18 -> #REF! | M23: =+L23 -> #REF!
M24: =+M22+M23 -> #REF!
M25: =+M24-681610-80400-51360 -> #REF!

Sheet NP LABORATORIO
A1: NOTA DE PEDIDO | J1: N° | K1: 02/2022
A3: JURISDICCIÓN: | D3: ='SAF 011'!C4 -> 040 - MINISTERIO DE SALUD
A4: SAF: | D4: ='SAF 011'!C5 -> 011 - DIRECCION PROVINCIAL DE ADMINISTRACION - MINISTERIO DE SALUD
A5: UNIDAD EJECUTORA: | D5: DIRECCION PROVINCIAL DE LABORATORIO
A6: DEPENDENCIA SOLICITANTE: | D6: DIRECCION PROVINCIAL DE LABORATORIO
A7: PERIODO UTILIZACIÓN: | D7: SEMESTRAL
A8: OBJETO: | D8: ADQUISICION DEL RUBRO ANTISEPTICOS Y DESINFECTANTES
A10: Ítem | B10: Codigo Item | C10: DESCRIPCIÓN | H10: Adjunta Detalle Técnico | I10: Unidad Medida | J10: Precio Unitario Estimado | K10: Cantidad Solicitada
A12: 1 | B12: ='SAF 011'!B12 -> 2.5.2-711.32 | C12: ='SAF 011'!E12 -> ALCOHOL USO MEDICINAL; PUREZA: 96 %, PRESENTACION: ENVASE X 1000 CM3 | H12: SI | I12: ='SAF 011'!F12 -> BOTELLA | J12: ='SAF 011'!H12 -> 201 | K12: ='SAF 011'!#REF! -> #REF! | L12: 252 | M12: =B12='SAF 011'!B12 -> TRUE | N12: =+J12*K12 -> #REF! | O12: =C12='SAF 011'!E12 -> TRUE
A14: Costo total estimado: OCHENTA MIL CUATROCIENTOS CON 00/100.- | J14: =+N14 -> #REF! | N14: =SUM(N12:N13) -> #REF!
K16: =+J12*K12 -> #REF!

Sheet NP BANCO DE SANGRE
A1: NOTA DE PEDIDO | J1: N° | K1: 03/2022
A3: JURISDICCIÓN: | D3: ='SAF 011'!C4 -> 040 - MINISTERIO DE SALUD
A4: SAF: | D4: ='SAF 011'!C5 -> 011 - DIRECCION PROVINCIAL DE ADMINISTRACION - MINISTERIO DE SALUD
A5: UNIDAD EJECUTORA: | D5: DIRECCION PROVINCIAL BANCO DE SANGRE
A6: DEPENDENCIA SOLICITANTE: | D6: DIRECCION PROVINCIAL BANCO DE SANGRE
A7: PERIODO UTILIZACIÓN: | D7: SEMESTRAL
A8: OBJETO: | D8: ADQUISICION DEL RUBRO ANTISEPTICOS Y DESINFECTANTES
A10: Ítem | B10: Codigo Item | C10: DESCRIPCIÓN | H10: Adjunta Detalle Técnico | I10: Unidad Medida | J10: Precio Unitario Estimado | K10: Cantidad Solicitada
A12: 1 | B12: ='SAF 011'!B11 -> 2.5.2-711.41 | C12: ='SAF 011'!E11 -> ALCOHOL USO MEDICINAL; PUREZA: 70 %, PRESENTACION: GEL ENVASE X 250 CM3 | H12: SI | I12: ='SAF 011'!F11 -> UNIDAD | J12: ='SAF 011'!H11 -> 158 | K12: ='SAF 011'!#REF! -> #REF! | L12: 252 | M12: ='SAF 011'!B11=B12 -> TRUE | N12: =+J12*K12 -> #REF! | O12: =C12='SAF 011'!E11 -> TRUE
A13: 2 | B13: ='SAF 011'!B13 -> 2.5.2-711.1 | C13: ='SAF 011'!E13 -> ALCOHOL USO MEDICINAL; PUREZA: 96 %, PRESENTACION: ENVASE X 500 CM3, CAPACIDAD: 500 CM3 | H13: SI | I13: ='SAF 011'!F13 -> BOTELLA | J13: ='SAF 011'!H13 -> 108 | K13: ='SAF 011'!#REF! -> #REF! | L13: 252 | M13: =B13='SAF 011'!B13 -> TRUE | N13: =+J13*K13 -> #REF! | O13: ='SAF 011'!E13=C13 -> TRUE
A15: Costo total estimado: CINCUENTA Y UN MIL TRESCIENTOS SESENTA CON 00/100.- | J15: =+N15 -> #REF! | N15: =SUM(N12:N14) -> #REF!
J17: =+J12*K12+J13*K13 -> #REF!

Sheet APG FARMACIA
A1: EJERCICIO: | D1: 2022 | P1: AUTORIZACION PARA GASTAR
A4: JURISDICCIÓN: | G4: ='NP FARMACIA'!D3 -> 040 - MINISTERIO DE SALUD
A5: SAF: | G5: ='NP FARMACIA'!D4 -> 011 - DIRECCION PROVINCIAL DE ADMINISTRACION - MINISTERIO DE SALUD
A6: UNIDAD EJECUTORA: | G6: ='NP FARMACIA'!D5 -> DIRECCION PROVINCIAL DE FARMACIA E INSUMOS
A7: DEPENDENCIA SOLICITANTE: | G7: ='NP FARMACIA'!D6 -> DIRECCION PROVINCIAL DE FARMACIA E INSUMOS
A8: AUTORIZACIÓN:
A9: Señor Director de Administración o Titular del Servicio Administrativo Financiero:
A10: Autorizo la realización de los trámites correspondientes, a fin de proveer a este Organismo los bienes que se detallan en Nota de Pedido N° D.P.F.e I. 12/2022 - D.P.L. 02/2022 - D.P.B.S. 03/2022 afectando la erogación resultante a los créditos presupuestarios aprobados a favor de esta Unidad Ejecutora, conforme al siguiente detalle:
A12: IMPUTACIÓN PRESUPUESTARIA
A13: CÓDIGO | O13: DENOMINACIÓN DE LA PARTIDA PRESUPUESTARIA | Q13: IMPORTE
A14: PR | B14: SB | C14: PY | D14: AC | E14: OB | F14: UG | G14: FIN | H14: FUN | I14: I | J14: P | K14: P | L14: SubP | M14: M | N14: FF
A15: 30 | D15: 1 | F15: 4901 | G15: 3 | H15: 1 | I15: 2 | J15: 5 | K15: 1 | M15: 1 | N15: 1.1 | O15: COMPUESTOS QUIMICOS | Q15: =+'NP FARMACIA'!L23 -> #REF!
A16: 30 | D16: 1 | F16: 4901 | G16: 3 | H16: 1 | I16: 2 | J16: 5 | K16: 2 | M16: 1 | N16: 1.1 | O16: PRODUCTOS FARMACEUTICOS Y MEDICINALES | Q16: =+'NP FARMACIA'!L22+'NP LABORATORIO'!K16+'NP BANCO DE SANGRE'!J17 -> #REF!
A38: TOTAL DE PESOS: OCHOCIENTOS TRECE MIL TRESCIENTOS SETENTA CON 00/100.- | Q38: =SUM(Q15:Q37) -> #REF!
A40: JUSTIFICACIÓN:
A41: ='NP FARMACIA'!D8 -> ADQUISICION DEL RUBRO ANTISEPTICOS Y DESINFECTANTES

Sheet NP ODONTOLOGIA
A1: NOTA DE PEDIDO | J1: N° | K1: 02/2022
A3: JURISDICCIÓN: | D3: ='SAF 011'!C4 -> 040 - MINISTERIO DE SALUD
A4: SAF: | D4: ='SAF 011'!C5 -> 011 - DIRECCION PROVINCIAL DE ADMINISTRACION - MINISTERIO DE SALUD
A5: UNIDAD EJECUTORA: | D5: DIRECCION PROVINCIAL DE ODONTOLOGIA
A6: DEPENDENCIA SOLICITANTE: | D6: DIRECCION PROVINCIAL DE ODONTOLOGIA
A7: PERIODO UTILIZACIÓN: | D7: SEMESTRAL
A8: OBJETO: | D8: ADQUISICION DEL RUBRO ANTISEPTICOS Y DESINFECTANTES
A10: Ítem | B10: Codigo Item | C10: DESCRIPCIÓN | H10: Adjunta Detalle Técnico | I10: Unidad Medida | J10: Precio Unitario Estimado | K10: Cantidad Solicitada
A12: 1 | B12: ='SAF 011'!B15 -> 2.5.2-1723.173 | C12: ='SAF 011'!E15 -> ANTISEPTICOS LOCALES P/PERSONA; TIPO: MONODROGA, DROGA GENERICA: IODOFORMADA AL 10% , FORMA FARMACEUTICA: GASA, PRESENTACION: DE 10X10, 15 UNIDADES POR PACK | H12: SI | I12: ='SAF 011'!F15 -> CAJA | J12: ='SAF 011'!H15 -> 950 | K12: ='SAF 011'!#REF! -> #REF! | L12: 295 | M12: =B12='SAF 011'!B15 -> TRUE | N12: =+J12*K12 -> #REF! | O12: ='SAF 011'!E15=C12 -> TRUE
A13: 2 | B13: ='SAF 011'!B19 -> 2.5.1-9065.27 | C13: ='SAF 011'!E19 -> DESINFECTANTES Y DETERGENTES; PRINCIPIO ACTIVO: AMONIO CUATERNARIO, CALIDAD: COMERCIAL, CONCENTRACION/PUREZA: 99 %, PRESENTACION: ENVASE X 5 L | H13: SI | I13: ='SAF 011'!F19 -> BIDON | J13: ='SAF 011'!H19 -> 9229.2 | K13: ='SAF 011'!#REF! -> #REF! | L13: 251 | M13: ='SAF 011'!B19=B13 -> TRUE | N13: =+J13*K13 -> #REF! | O13: =C13='SAF 011'!E19 -> TRUE
A15: Costo total estimado: QUINIENTOS OCHO MIL NOVECIENTOS SESENTA CON 00/100.- | J15: =+N15 -> #REF! | N15: =SUM(N12:N14) -> #REF!
K18: =+K12*J12 -> #REF!
K19: =+J13*K13 -> #REF!

Sheet APG ODONTOLOGIA
A1: EJERCICIO: | D1: 2022 | P1: AUTORIZACION PARA GASTAR
A4: JURISDICCIÓN: | G4: ='NP ODONTOLOGIA'!D3 -> 040 - MINISTERIO DE SALUD
A5: SAF: | G5: ='NP ODONTOLOGIA'!D4 -> 011 - DIRECCION PROVINCIAL DE ADMINISTRACION - MINISTERIO DE SALUD
A6: UNIDAD EJECUTORA: | G6: ='NP ODONTOLOGIA'!D5 -> DIRECCION PROVINCIAL DE ODONTOLOGIA
A7: DEPENDENCIA SOLICITANTE: | G7: ='NP ODONTOLOGIA'!D6 -> DIRECCION PROVINCIAL DE ODONTOLOGIA
A8: AUTORIZACIÓN:
A9: Señor Director de Administración o Titular del Servicio Administrativo Financiero:
A10: Autorizo la realización de los trámites correspondientes, a fin de proveer a este Organismo los bienes que se detallan en Nota de Pedido N° 02/2022 afectando la erogación resultante a los créditos presupuestarios aprobados a favor de esta Unidad Ejecutora, conforme al siguiente detalle:
A12: IMPUTACIÓN PRESUPUESTARIA
A13: CÓDIGO | O13: DENOMINACIÓN DE LA PARTIDA PRESUPUESTARIA | Q13: IMPORTE
A14: PR | B14: SB | C14: PY | D14: AC | E14: OB | F14: UG | G14: FIN | H14: FUN | I14: I | J14: P | K14: P | L14: SubP | M14: M | N14: FF
A15: 29 | D15: 1 | F15: 4901 | G15: 3 | H15: 1 | I15: 2 | J15: 5 | K15: 1 | M15: 1 | N15: 1.1 | O15: COMPUESTOS QUIMICOS | Q15: ='NP ODONTOLOGIA'!N13 -> #REF!
A16: 29 | D16: 1 | F16: 4901 | G16: 3 | H16: 1 | I16: 2 | J16: 9 | K16: 5 | M16: 1 | N16: 1.1 | O16: UTILES MENORES MEDICOS, QUIRURGICOS Y DE LABORATORIO | Q16: ='NP ODONTOLOGIA'!N12 -> #REF!
A38: TOTAL DE PESOS: QUINIENTOS OCHO MIL NOVECIENTOS SESENTA CON 00/100.- | Q38: =SUM(Q15:Q37) -> #REF!
A40: JUSTIFICACIÓN:
A41: ='NP ODONTOLOGIA'!D8 -> ADQUISICION DEL RUBRO ANTISEPTICOS Y DESINFECTANTES

Sheet NP SAME
A1: NOTA DE PEDIDO | J1: N° | K1: 03/2022
A3: JURISDICCIÓN: | D3: ='SAF 011'!C4 -> 040 - MINISTERIO DE SALUD
A4: SAF: | D4: ='SAF 011'!C5 -> 011 - DIRECCION PROVINCIAL DE ADMINISTRACION - MINISTERIO DE SALUD
A5: UNIDAD EJECUTORA: | D5: DIRECCION PROVINCIAL SISTEMA DE ATENCION MEDICA DE EMERGENCIA
A6: DEPENDENCIA SOLICITANTE: | D6: DIRECCION PROVINCIAL SISTEMA DE ATENCION MEDICA DE EMERGENCIA
A7: PERIODO UTILIZACIÓN: | D7: SEMESTRAL
A8: OBJETO: | D8: ADQUISICION DEL RUBRO ANTISEPTICOS Y DESINFECTANTES
A10: Ítem | B10: Codigo Item | C10: DESCRIPCIÓN | H10: Adjunta Detalle Técnico | I10: Unidad Medida | J10: Precio Unitario Estimado | K10: Cantidad Solicitada
A12: 1 | B12: ='SAF 011'!B10 -> 2.5.2-710.4 | C12: ='SAF 011'!E10 -> AGUA OXIGENADA; CAPACIDAD: 1000 CM3, VOLUMEN: 10, PRESENTACION: ENVASE X 1000 CM3 | H12: SI | I12: ='SAF 011'!F10 -> BOTELLA | J12: ='SAF 011'!H10 -> 128.59 | K12: ='SAF 011'!#REF! -> #REF! | L12: 252 | M12: =+J12*K12 -> #REF!
A13: 2 | B13: ='SAF 011'!B14 -> 2.5.2-1723.50 | C13: ='SAF 011'!E14 -> ANTISEPTICOS LOCALES P/PERSONA; DROGA GENERICA: IODOPOVIDONA 10%, FORMA FARMACEUTICA: SOLUCION, PRESENTACION: ENVASE X 1 L, TIPO: MONODROGA | H13: SI | I13: ='SAF 011'!F14 -> BOTELLA | J13: ='SAF 011'!H14 -> 573 | K13: ='SAF 011'!#REF! -> #REF! | L13: 252 | M13: =+J13*K13 -> #REF!
A15: Costo total estimado: DOCE MIL CUATROCIENTOS CINCUENTA Y DOS CON 70/100.- | J15: =+M15 -> #REF! | M15: =SUM(M12:M14) -> #REF!

Sheet APG SAME
A1: EJERCICIO: | D1: 2022 | P1: AUTORIZACION PARA GASTAR
A4: JURISDICCIÓN: | G4: ='NP SAME'!D3 -> 040 - MINISTERIO DE SALUD
A5: SAF: | G5: ='NP SAME'!D4 -> 011 - DIRECCION PROVINCIAL DE ADMINISTRACION - MINISTERIO DE SALUD
A6: UNIDAD EJECUTORA: | G6: ='NP SAME'!D5 -> DIRECCION PROVINCIAL SISTEMA DE ATENCION MEDICA DE EMERGENCIA
A7: DEPENDENCIA SOLICITANTE: | G7: ='NP SAME'!D6 -> DIRECCION PROVINCIAL SISTEMA DE ATENCION MEDICA DE EMERGENCIA
A8: AUTORIZACIÓN:
A9: Señor Director de Administración o Titular del Servicio Administrativo Financiero:
A10: Autorizo la realización de los trámites correspondientes, a fin de proveer a este Organismo los bienes que se detallan en Nota de Pedido N° 03/2022 afectando la erogación resultante a los créditos presupuestarios aprobados a favor de esta Unidad Ejecutora, conforme al siguiente detalle:
A12: IMPUTACIÓN PRESUPUESTARIA
A13: CÓDIGO | O13: DENOMINACIÓN DE LA PARTIDA PRESUPUESTARIA | Q13: IMPORTE
A14: PR | B14: SB | C14: PY | D14: AC | E14: OB | F14: UG | G14: FIN | H14: FUN | I14: I | J14: P | K14: P | L14: SubP | M14: M | N14: FF
A15: 31 | D15: 1 | F15: 4901 | G15: 3 | H15: 1 | I15: 2 | J15: 5 | K15: 2 | M15: 1 | N15: 1.1 | O15: PRODUCTOS FARMACEUTICOS Y MEDICINALES | Q15: ='NP SAME'!M15 -> #REF!
A37: TOTAL DE PESOS: DOCE MIL CUATROCIENTOS CINCUENTA Y DOS CON 70/100.- | Q37: =SUM(Q15:Q36) -> #REF!
A39: JUSTIFICACIÓN:
A40: ='NP SAME'!D8 -> ADQUISICION DEL RUBRO ANTISEPTICOS Y DESINFECTANTES
