Workbook

Sheet Necesidades Trimestrales
A1: 2022
B2: Pedido de Necesidades Trimestrales
A4: JURISDICCION: | C4: 040 - Ministerio de Salud
A5: SAF N°: | C5: 011 - Direccion Provincial de Administracion - MS
A6: EJERCICIO: | C6: 2022
A7: TRIMESTRE: | C7: 2
A9: ID | B9: CODIGO ITEM | C9: RUBRO DE COMPRA | D9: I.P.P. | E9: DESCRIPCION | F9: UNIDAD DE MEDIDA | G9: CANTIDAD | H9: PRECIO UNITARIO ESTIMADO | I9: IMPORTE TOTAL ESTIMADO
A10: 1 | B10: 2.5.2-1829.35 | C10: PROD. MEDICO/FARMACEUTICOS/LAB | D10: 252 | E10: ANTIVIRALES; TIPO: MONODROGA, DROGA GENERICA: ACICLOVIR, FORMA FARMACEUTICA: COMPRIMIDO, PRESENTACION: 400 mGr | F10: COMPRIMIDO | G10: 1000 | H10: 70.1 | I10: =+G10*H10 -> 70100
A11: 2 | B11: 2.5.2-1724.16 | C11: PROD. MEDICO/FARMACEUTICOS/LAB | D11: 252 | E11: ANALGESICOS ; TIPO: MONODROGA, DROGA GENERICA: ACIDO ACETILSALICILICO, PRESENTACION: 100 mGr, FORMA FARMACEUTICA: COMPRIMIDO | F11: COMPRIMIDO | G11: 12050 | H11: 1.55 | I11: =+G11*H11 -> 18677.5
A12: 3 | B12: 2.5.2-1821.524 | C12: PROD. MEDICO/FARMACEUTICOS/LAB | D12: 252 | E12: ANTIBIOTICOS P/PERSONAS; TIPO: ASOCIACION, DROGA GENERICA: AMOXICILINA + AC.CLAVULANICO 400 MG / 57 MG, FORMA FARMACEUTICA: SUSPENSION, PRESENTACION: ENVASE X 70 ML | F12: FRASCO | G12: 10000 | H12: 374 | I12: =+G12*H12 -> 3740000
A13: 4 | B13: 2.5.2-1821.440 | C13: PROD. MEDICO/FARMACEUTICOS/LAB | D13: 252 | E13: ANTIBIOTICOS P/PERSONAS; TIPO: ASOCIACION, DROGA GENERICA: AMOXICIL. 875 MG+CLAVUL.125 MG mGr, FORMA FARMACEUTICA: COMPRIMIDO, PRESENTACION: UNIDAD | F13: COMPRIMIDO | G13: 120000 | H13: 29.5 | I13: =+G13*H13 -> 3540000
A14: 5 | B14: 2.5.2-1821.9 | C14: PROD. MEDICO/FARMACEUTICOS/LAB | D14: 252 | E14: ANTIBIOTICOS P/PERSONAS; TIPO: MONODROGA, DROGA GENERICA: AMOXICILINA, PRESENTACION: 500 mGr, FORMA FARMACEUTICA: COMPRIMIDOS | F14: COMPRIMIDO | G14: 50000 | H14: 7.85 | I14: =+G14*H14 -> 392500
A15: 6 | B15: 2.5.2-1821.399 | C15: PROD. MEDICO/FARMACEUTICOS/LAB | D15: 252 | E15: ANTIBIOTICOS P/PERSONAS; TIPO: MONODROGA, DROGA GENERICA: AMOXICILINA 500 mGr, FORMA FARMACEUTICA: SUSPENSION, PRESENTACION: ENVASE X 90 mL | F15: FRASCO | G15: 4000 | H15: 210 | I15: =+G15*H15 -> 840000
A16: 7 | B16: 2.5.2-1821.8 | C16: PROD. MEDICO/FARMACEUTICOS/LAB | D16: 252 | E16: ANTIBIOTICOS P/PERSONAS; TIPO: MONODROGA, DROGA GENERICA: AMPICILINA, FORMA FARMACEUTICA: AMPOLLA, PRESENTACION: 1 GR | F16: AMPOLLA | G16: 14000 | H16: 99 | I16: =+G16*H16 -> 1386000
A17: 8 | B17: 2.5.2-1821.502 | C17: PROD. MEDICO/FARMACEUTICOS/LAB | D17: 252 | E17: ANTIBIOTICOS P/PERSONAS; TIPO: MONODROGA, DROGA GENERICA: AZITROMICINA 200 mGr, FORMA FARMACEUTICA: SUSPENSION, PRESENTACION: ENVASE X 15 Ml | F17: FRASCO | G17: 3000 | H17: 310 | I17: =+G17*H17 -> 930000
A18: 9 | B18: 2.5.2-1821.94 | C18: PROD. MEDICO/FARMACEUTICOS/LAB | D18: 252 | E18: ANTIBIOTICOS P/PERSONAS; TIPO: MONODROGA, DROGA GENERICA: AZITROMICINA, FORMA FARMACEUTICA: COMPRIMIDO, PRESENTACION: 500 mGr | F18: COMPRIMIDO | G18: 25000 | H18: 36 | I18: =+G18*H18 -> 900000
A19: 10 | B19: 2.5.2-1883.188 | C19: PROD. MEDICO/FARMACEUTICOS/LAB | D19: 252 | E19: ANESTESICOS LOCALES; TIPO: MONODROGA, DROGA GENERICA: BUPIVACAINA 0,5% HIPERBARICA, FORMA FARMACEUTICA: AMPOLLA, PRESENTACION: 4 ML CON AGUJA 27 G X 3 1/2 CON INTRODUCTOR | F19: AMPOLLA | G19: 500 | H19: 1420 | I19: =+G19*H19 -> 710000
A20: 11 | B20: 2.5.2-1821.321 | C20: PROD. MEDICO/FARMACEUTICOS/LAB | D20: 252 | E20: ANTIBIOTICOS P/PERSONAS; TIPO: MONODROGA, DROGA GENERICA: CEFALEXINA 500 mGr, FORMA FARMACEUTICA: COMPRIMIDO, PRESENTACION: 1 UN | F20: COMPRIMIDO | G20: 100000 | H20: 13.9 | I20: =+G20*H20 -> 1390000
A21: 12 | B21: 2.5.2-1821.337 | C21: PROD. MEDICO/FARMACEUTICOS/LAB | D21: 252 | E21: ANTIBIOTICOS P/PERSONAS; TIPO: MONODROGA, DROGA GENERICA: CEFALEXINA 500MG, FORMA FARMACEUTICA: SUSPENSION, PRESENTACION: ENVASE X 90 mL | F21: FRASCO | G21: 1000 | H21: 350 | I21: =+G21*H21 -> 350000
... A60: 51 | B60: 2.5.2-2455.31 | C60: PROD. MEDICO/FARMACEUTICOS/LAB | D60: 252 | E60: ANESTESICOS GENERALES; DROGA GENERICA: SEVOFLUORANO, FORMA FARMACEUTICA: SOLUCION, PRESENTACION: ENVASE X 250 mL, TIPO: MONODROGA | F60: FRASCO | G60: 10 | H60: 13840 | I60: =+G60*H60 -> 138400
A61: TOTAL RUBRO | I61: =SUM(I10:I60) -> 47689980
C63: DETALLE TECNICO Y ESPECIFICACIONES | D63: ANEXO 1-Para oferentes de la Provincia de Catamarca deberán presentar Habilitación Provincial para comercializar el producto que cotizan. 2-Para el resto de oferentes deberán presentar Certificado de Inscripción de ANMAT vigente al momento de la oferta, el mismo deberá ser correspondiente al objeto de la contratación y de encontrarse vencido adjuntar la solicitud de renovación. 3-No se aceptarán ofertas de productos no registrados y autorizada su venta por ANMAT. Se deberá especificar en cada ítem de la propuesta, marca y número de certificado otorgado por dicho ente regulador. 4-Los productos deberán tener un vencimiento posterior a doce (12) meses a partir de la fecha de su recepción.
C65: Plazos de entrega | D65: veinte (20) dias habiles
C67: Lugar de Entrega: | D67: ITEM 1, 2 (12.000 un.), 3, 4, 5, 6, 7, 8, 9, 10, 11, 12, 13, 14, 15, 16, 17, 18, 19, 20 (150.000 un.), 21 (100.000 un.), 22 (100.000 un.), 23, 24, 25, 26, 27, 28 (15.000 u.), 29, 32 (10.000 un.), 33, 35, 36, 37, 38, 39, 41, 42, 43 (20.000 un.), 44, 45, 46, 47, 48, 49, 50, 51 - DIR. PROV. DE FARMACIA E INSUMOS - CHACABUCO N° 169 - en el horario de 8:00hs a 12:00hs de lunes a viernes
D68: ITEM 2 (50 un.), 20 (150 un.), 21 (250 un.), 22 (500 un.), 28 (50 un.), 30, 31, 32 (100 un.), 34, 40, 43 (500 un.) - DIR. PROV. SAME - CASEROS N° 864 - en el horario de 8:00hs a 12:00hs de lunes a viernes
C70: Calidad Minima esperada
C72: Mantenimiento | D72: cuarenta y cinco (45) días
B75: Especificidades: ITEMS 24 Tipo INTRALIPIP
B76: Lugar de Entrega: D.P. DE FARMACIA E INSUMOS - CHACABUCO N° 169 - DE 08:00 A 12:00HS., DEBIENDO CORRER LOS GASTOS DE FLETES, ACARREO, CARGA, DESCARGA Y SEGURO A CARGO DEL ADJUDICATARIO.
B78: Plazo de entrega: VEINTE (20) DIAS HABILES
B80: Calidad Minima esperada:
B81: Mantenimiento: 45 dias habiles

Sheet  NotaPedido DPFARMACIA
A1: NOTA DE PEDIDO | J1: N° | K1: 16/2022
A3: JURISDICCIÓN: | D3: ='Necesidades Trimestrales'!C4 -> 040 - Ministerio de Salud
A4: SAF: | D4: ='Necesidades Trimestrales'!C5 -> 011 - Direccion Provincial de Administracion - MS
A5: UNIDAD EJECUTORA: | D5: 469 - Direccion Provincial de Farmacia e Insumos
A6: DEPENDENCIA SOLICITANTE: | D6: 469 - Direccion Provincial de Farmacia e Insumos
A7: PERIODO UTILIZACIÓN: | D7: Semestral
A8: OBJETO: | D8: Adquisición de TERAPIA ANTIINFECCIOSA SISTEMICA/SUEROS INMUNES E INMUNOGLOBULINAS Y MEDIOS DE CONTRASTES /ANALGESICOS ANTINFLAMATORIOS /MIORRELAJANTES/ANESTESICOS/ANALGESICOS OPIACIOS
A10: Ítem | B10: Codigo Item | C10: DESCRIPCIÓN | H10: Adjunta Detalle Técnico | I10: Unidad Medida | J10: Precio Unitario Estimado | K10: Cantidad Solicitada
A12: 1 | B12: ='Necesidades Trimestrales'!B10 -> 2.5.2-1829.35 | C12: ='Necesidades Trimestrales'!E10 -> ANTIVIRALES; TIPO: MONODROGA, DROGA GENERICA: ACICLOVIR, FORMA FARMACEUTICA: COMPRIMIDO, PRESENTACION: 400 mGr | H12: NO | I12: ='Necesidades Trimestrales'!F10 -> COMPRIMIDO | J12: ='Necesidades Trimestrales'!H10 -> 70.1 | K12: ='Necesidades Trimestrales'!#REF! -> #REF!
A13: 2 | B13: ='Necesidades Trimestrales'!B11 -> 2.5.2-1724.16 | C13: ='Necesidades Trimestrales'!E11 -> ANALGESICOS ; TIPO: MONODROGA, DROGA GENERICA: ACIDO ACETILSALICILICO, PRESENTACION: 100 mGr, FORMA FARMACEUTICA: COMPRIMIDO | H13: NO | I13: ='Necesidades Trimestrales'!F11 -> COMPRIMIDO | J13: ='Necesidades Trimestrales'!H11 -> 1.55 | K13: ='Necesidades Trimestrales'!#REF! -> #REF!
A14: 3 | B14: ='Necesidades Trimestrales'!B12 -> 2.5.2-1821.524 | C14: ='Necesidades Trimestrales'!E12 -> ANTIBIOTICOS P/PERSONAS; TIPO: ASOCIACION, DROGA GENERICA: AMOXICILINA + AC.CLAVULANICO 400 MG / 57 MG, FORMA FARMACEUTICA: SUSPENSION, PRESENTACION: ENVASE X 70 ML | H14: NO | I14: ='Necesidades Trimestrales'!F12 -> FRASCO | J14: ='Necesidades Trimestrales'!H12 -> 374 | K14: ='Necesidades Trimestrales'!#REF! -> #REF!
A15: 4 | B15: ='Necesidades Trimestrales'!B13 -> 2.5.2-1821.440 | C15: ='Necesidades Trimestrales'!E13 -> ANTIBIOTICOS P/PERSONAS; TIPO: ASOCIACION, DROGA GENERICA: AMOXICIL. 875 MG+CLAVUL.125 MG mGr, FORMA FARMACEUTICA: COMPRIMIDO, PRESENTACION: UNIDAD | H15: NO | I15: ='Necesidades Trimestrales'!F13 -> COMPRIMIDO | J15: ='Necesidades Trimestrales'!H13 -> 29.5 | K15: ='Necesidades Trimestrales'!#REF! -> #REF!
A16: 5 | B16: ='Necesidades Trimestrales'!B14 -> 2.5.2-1821.9 | C16: ='Necesidades Trimestrales'!E14 -> ANTIBIOTICOS P/PERSONAS; TIPO: MONODROGA, DROGA GENERICA: AMOXICILINA, PRESENTACION: 500 mGr, FORMA FARMACEUTICA: COMPRIMIDOS | H16: NO | I16: ='Necesidades Trimestrales'!F14 -> COMPRIMIDO | J16: ='Necesidades Trimestrales'!H14 -> 7.85 | K16: ='Necesidades Trimestrales'!#REF! -> #REF!
A17: 6 | B17: ='Necesidades Trimestrales'!B15 -> 2.5.2-1821.399 | C17: ='Necesidades Trimestrales'!E15 -> ANTIBIOTICOS P/PERSONAS; TIPO: MONODROGA, DROGA GENERICA: AMOXICILINA 500 mGr, FORMA FARMACEUTICA: SUSPENSION, PRESENTACION: ENVASE X 90 mL | H17: NO | I17: ='Necesidades Trimestrales'!F15 -> FRASCO | J17: ='Necesidades Trimestrales'!H15 -> 210 | K17: ='Necesidades Trimestrales'!#REF! -> #REF!
A18: 7 | B18: ='Necesidades Trimestrales'!B16 -> 2.5.2-1821.8 | C18: ='Necesidades Trimestrales'!E16 -> ANTIBIOTICOS P/PERSONAS; TIPO: MONODROGA, DROGA GENERICA: AMPICILINA, FORMA FARMACEUTICA: AMPOLLA, PRESENTACION: 1 GR | H18: NO | I18: ='Necesidades Trimestrales'!F16 -> AMPOLLA | J18: ='Necesidades Trimestrales'!H16 -> 99 | K18: ='Necesidades Trimestrales'!#REF! -> #REF!
A19: 8 | B19: ='Necesidades Trimestrales'!B17 -> 2.5.2-1821.502 | C19: ='Necesidades Trimestrales'!E17 -> ANTIBIOTICOS P/PERSONAS; TIPO: MONODROGA, DROGA GENERICA: AZITROMICINA 200 mGr, FORMA FARMACEUTICA: SUSPENSION, PRESENTACION: ENVASE X 15 Ml | H19: NO | I19: ='Necesidades Trimestrales'!F17 -> FRASCO | J19: ='Necesidades Trimestrales'!H17 -> 310 | K19: ='Necesidades Trimestrales'!#REF! -> #REF!
A20: 9 | B20: ='Necesidades Trimestrales'!B18 -> 2.5.2-1821.94 | C20: ='Necesidades Trimestrales'!E18 -> ANTIBIOTICOS P/PERSONAS; TIPO: MONODROGA, DROGA GENERICA: AZITROMICINA, FORMA FARMACEUTICA: COMPRIMIDO, PRESENTACION: 500 mGr | H20: NO | I20: ='Necesidades Trimestrales'!F18 -> COMPRIMIDO | J20: ='Necesidades Trimestrales'!H18 -> 36 | K20: ='Necesidades Trimestrales'!#REF! -> #REF!
A21: 10 | B21: ='Necesidades Trimestrales'!B19 -> 2.5.2-1883.188 | C21: ='Necesidades Trimestrales'!E19 -> ANESTESICOS LOCALES; TIPO: MONODROGA, DROGA GENERICA: BUPIVACAINA 0,5% HIPERBARICA, FORMA FARMACEUTICA: AMPOLLA, PRESENTACION: 4 ML CON AGUJA 27 G X 3 1/2 CON INTRODUCTOR | H21: NO | I21: ='Necesidades Trimestrales'!F19 -> AMPOLLA | J21: ='Necesidades Trimestrales'!H19 -> 1420 | K21: ='Necesidades Trimestrales'!#REF! -> #REF!
A22: 11 | B22: ='Necesidades Trimestrales'!B20 -> 2.5.2-1821.321 | C22: ='Necesidades Trimestrales'!E20 -> ANTIBIOTICOS P/PERSONAS; TIPO: MONODROGA, DROGA GENERICA: CEFALEXINA 500 mGr, FORMA FARMACEUTICA: COMPRIMIDO, PRESENTACION: 1 UN | H22: NO | I22: ='Necesidades Trimestrales'!F20 -> COMPRIMIDO | J22: ='Necesidades Trimestrales'!H20 -> 13.9 | K22: ='Necesidades Trimestrales'!#REF! -> #REF!
A23: 12 | B23: ='Necesidades Trimestrales'!B21 -> 2.5.2-1821.337 | C23: ='Necesidades Trimestrales'!E21 -> ANTIBIOTICOS P/PERSONAS; TIPO: MONODROGA, DROGA GENERICA: CEFALEXINA 500MG, FORMA FARMACEUTICA: SUSPENSION, PRESENTACION: ENVASE X 90 mL | H23: NO | I23: ='Necesidades Trimestrales'!F21 -> FRASCO | J23: ='Necesidades Trimestrales'!H21 -> 350 | K23: ='Necesidades Trimestrales'!#REF! -> #REF!
... A40: 29 | B40: ='Necesidades Trimestrales'!B38 -> 2.5.2-1724.4 | C40: ='Necesidades Trimestrales'!E38 -> ANALGESICOS ; TIPO: MONODROGA, DROGA GENERICA: IBUPROFENO, PRESENTACION: 400 mGr, FORMA FARMACEUTICA: COMPRIMIDO | H40: NO | I40: ='Necesidades Trimestrales'!F38 -> AMPOLLA | J40: ='Necesidades Trimestrales'!H38 -> 45 | K40: ='Necesidades Trimestrales'!#REF! -> #REF!
A41: 30 | B41: ='Necesidades Trimestrales'!B41 -> 2.5.2-1724.23 | C41: ='Necesidades Trimestrales'!E41 -> ANALGESICOS ; TIPO: MONODROGA, DROGA GENERICA: KETOROLAC, FORMA FARMACEUTICA: AMPOLLA, PRESENTACION: 30 mGr | H41: NO | I41: ='Necesidades Trimestrales'!F41 -> AMPOLLA | J41: ='Necesidades Trimestrales'!H41 -> 56 | K41: ='Necesidades Trimestrales'!#REF! -> #REF!
A42: 31 | B42: ='Necesidades Trimestrales'!B42 -> 2.5.2-1883.186 | C42: ='Necesidades Trimestrales'!E42 -> ANESTESICOS LOCALES; TIPO: MONODROGA, DROGA GENERICA: LIDOCAINA 2%S/EPINEFRINA, FORMA FARMACEUTICA: AMPOLLA, PRESENTACION: 5 mL | H42: NO | I42: ='Necesidades Trimestrales'!F42 -> AMPOLLA | J42: ='Necesidades Trimestrales'!H42 -> 35 | K42: ='Necesidades Trimestrales'!#REF! -> #REF!
A43: 32 | B43: ='Necesidades Trimestrales'!B44 -> 2.5.2-1883.111 | C43: ='Necesidades Trimestrales'!E44 -> ANESTESICOS LOCALES; TIPO: ASOCIACION, DROGA GENERICA: LIDOCAINA 2% C/EPINEFRINA, FORMA FARMACEUTICA: FRASCO AMPOLLA, PRESENTACION: 20 mL | H43: NO | I43: ='Necesidades Trimestrales'!F44 -> AMPOLLA | J43: ='Necesidades Trimestrales'!H44 -> 493 | K43: ='Necesidades Trimestrales'!#REF! -> #REF!
A44: 33 | B44: ='Necesidades Trimestrales'!B45 -> 2.5.2-1883.28 | C44: ='Necesidades Trimestrales'!E45 -> ANESTESICOS LOCALES; TIPO: MONODROGA, DROGA GENERICA: LIDOCAINA, FORMA FARMACEUTICA: AEROSOL, PRESENTACION: 100 mL | H44: NO | I44: ='Necesidades Trimestrales'!F45 -> ENVASE | J44: ='Necesidades Trimestrales'!H45 -> 640 | K44: ='Necesidades Trimestrales'!#REF! -> #REF!
A45: 34 | B45: ='Necesidades Trimestrales'!B46 -> 2.5.2-1883.19 | C45: ='Necesidades Trimestrales'!E46 -> ANESTESICOS LOCALES; TIPO: MONODROGA, DROGA GENERICA: LIDOCAINA VISCOSA, FORMA FARMACEUTICA: ENVASE, PRESENTACION: 50 mL | H45: NO | I45: ='Necesidades Trimestrales'!F46 -> ENVASE | J45: ='Necesidades Trimestrales'!H46 -> 390 | K45: ='Necesidades Trimestrales'!#REF! -> #REF!
A46: 35 | B46: ='Necesidades Trimestrales'!B47 -> 2.5.2-1821.76 | C46: ='Necesidades Trimestrales'!E47 -> ANTIBIOTICOS P/PERSONAS; TIPO: MONODROGA, FORMA FARMACEUTICA: COMPRIMIDO, PRESENTACION: 500 mGr, DROGA GENERICA: METRONIDAZOL | H46: NO | I46: ='Necesidades Trimestrales'!F47 -> COMPRIMIDO | J46: ='Necesidades Trimestrales'!H47 -> 7.3 | K46: ='Necesidades Trimestrales'!#REF! -> #REF!
A47: 36 | B47: ='Necesidades Trimestrales'!B48 -> 2.5.2-1821.400 | C47: ='Necesidades Trimestrales'!E48 -> ANTIBIOTICOS P/PERSONAS; TIPO: MONODROGA, DROGA GENERICA: METRONIDAZOL 500 mGr, FORMA FARMACEUTICA: SACHET X 100 mL, PRESENTACION: UNIDAD | H47: NO | I47: ='Necesidades Trimestrales'!F48 -> ENVASE | J47: ='Necesidades Trimestrales'!H48 -> 118 | K47: ='Necesidades Trimestrales'!#REF! -> #REF!
A48: 37 | B48: ='Necesidades Trimestrales'!B50 -> 2.5.2-1724.206 | C48: ='Necesidades Trimestrales'!E50 -> ANALGESICOS ; TIPO: MONODROGA, DROGA GENERICA: NALBUFINA 10 mGr, FORMA FARMACEUTICA: AMPOLLA, PRESENTACION: ENVASE X 1 mL | H48: NO | I48: ='Necesidades Trimestrales'!F50 -> AMPOLLA | J48: ='Necesidades Trimestrales'!H50 -> 120 | K48: ='Necesidades Trimestrales'!#REF! -> #REF!
A49: 38 | B49: ='Necesidades Trimestrales'!B51 -> 2.5.2-1725.35 | C49: ='Necesidades Trimestrales'!E51 -> ANTIINFLAMATORIOS NO ESTEROIDE; TIPO: MONODROGA, DROGA GENERICA: NAPROXENO, FORMA FARMACEUTICA: COMPRIMIDO, PRESENTACION: 500 mGr | H49: NO | I49: ='Necesidades Trimestrales'!F51 -> COMPRIMIDO | J49: ='Necesidades Trimestrales'!H51 -> 16.8 | K49: ='Necesidades Trimestrales'!#REF! -> #REF!
A50: 39 | B50: ='Necesidades Trimestrales'!B52 -> 2.5.2-1724.243 | C50: ='Necesidades Trimestrales'!E52 -> ANALGESICOS ; TIPO: MONODROGA, DROGA GENERICA: PARACETAMOL 1 GR, FORMA FARMACEUTICA: COMPRIMIDO, PRESENTACION: UNIDAD | H50: NO | I50: ='Necesidades Trimestrales'!F52 -> COMPRIMIDO | J50: ='Necesidades Trimestrales'!H52 -> 9.8 | K50: ='Necesidades Trimestrales'!#REF! -> #REF!
A51: 40 | B51: ='Necesidades Trimestrales'!B53 -> 2.5.2-1724.244 | C51: ='Necesidades Trimestrales'!E53 -> ANALGESICOS ; TIPO: MONODROGA, DROGA GENERICA: PARACETAMOL 2%, 100MG/5ML, FORMA FARMACEÚTICA: JARABE, PRESENTACION: 120 ML | H51: NO | I51: ='Necesidades Trimestrales'!F53 -> FRASCO | J51: ='Necesidades Trimestrales'!H53 -> 165 | K51: ='Necesidades Trimestrales'!#REF! -> #REF!
A52: 41 | B52: ='Necesidades Trimestrales'!B54 -> 2.5.2-1724.245 | C52: ='Necesidades Trimestrales'!E54 -> ANALGÉSICOS ; TIPO: MONODROGA, DROGA GENÉRICA: PARACETAMOL 500 MGR, FORMA FARMACEÚTICA: COMPRIMIDO, PRESENTACIÓN: X UNIDAD | H52: NO | I52: ='Necesidades Trimestrales'!F54 -> COMPRIMIDO | J52: ='Necesidades Trimestrales'!H54 -> 5.3 | K52: ='Necesidades Trimestrales'!#REF! -> #REF!
A53: 42 | B53: ='Necesidades Trimestrales'!B55 -> 2.5.2-1821.54 | C53: ='Necesidades Trimestrales'!E55 -> ANTIBIOTICOS P/PERSONAS; TIPO: MONODROGA, DROGA GENERICA: PENICILINA G. BENZATINICA, FORMA FARMACEUTICA: AMPOLLA, PRESENTACION: 1.200.000 UI | H53: NO | I53: ='Necesidades Trimestrales'!F55 -> AMPOLLA | J53: ='Necesidades Trimestrales'!H55 -> 189 | K53: ='Necesidades Trimestrales'!#REF! -> #REF!
A54: 43 | B54: ='Necesidades Trimestrales'!B56 -> 2.5.2-1821.220 | C54: ='Necesidades Trimestrales'!E56 -> ANTIBIOTICOS P/PERSONAS; TIPO: MONODROGA, DROGA GENERICA: PENICILINA G. BENZATINICA, FORMA FARMACEUTICA: FRASCO AMPOLLA, PRESENTACION: 2.400.000 UI | H54: NO | I54: ='Necesidades Trimestrales'!F56 -> AMPOLLA | J54: ='Necesidades Trimestrales'!H56 -> 256 | K54: ='Necesidades Trimestrales'!#REF! -> #REF!
A55: 44 | B55: ='Necesidades Trimestrales'!B57 -> 2.5.2-3097.9 | C55: ='Necesidades Trimestrales'!E57 -> PEDICULICIDAS; DROGA GENERICA: PERMETRINA, FORMA FARMACEUTICA: EMULSION, PRESENTACION: 100 mL | H55: NO | I55: ='Necesidades Trimestrales'!F57 -> ENVASE | J55: ='Necesidades Trimestrales'!H57 -> 958 | K55: ='Necesidades Trimestrales'!#REF! -> #REF!
A56: 45 | B56: ='Necesidades Trimestrales'!B58 -> 2.5.2-1821.201 | C56: ='Necesidades Trimestrales'!E58 -> ANTIBIOTICOS P/PERSONAS; TIPO: ANTITUBERCULOSTATICO, DROGA GENERICA: RIFAMPICINA X 2 GR, FORMA FARMACEUTICA: EN SUSPENSION CADA 100 mL, PRESENTACION: FRASCO X 50 Ml | H56: NO | I56: ='Necesidades Trimestrales'!F58 -> FRASCO | J56: ='Necesidades Trimestrales'!H58 -> 1602 | K56: ='Necesidades Trimestrales'!#REF! -> #REF!
A57: 46 | B57: ='Necesidades Trimestrales'!B59 -> 2.5.2-1822.6 | C57: ='Necesidades Trimestrales'!E59 -> ANTIMICOBACTERIAS; TIPO: MONODROGA, DROGA GENERICA: RIFAMPICINA, PRESENTACION: 300 mGr, FORMA FARMACEUTICA: CAPSULA | H57: NO | I57: ='Necesidades Trimestrales'!F59 -> CAPSULAS | J57: ='Necesidades Trimestrales'!H59 -> 45 | K57: ='Necesidades Trimestrales'!#REF! -> #REF!
A58: 47 | B58: ='Necesidades Trimestrales'!B60 -> 2.5.2-2455.31 | C58: ='Necesidades Trimestrales'!E60 -> ANESTESICOS GENERALES; DROGA GENERICA: SEVOFLUORANO, FORMA FARMACEUTICA: SOLUCION, PRESENTACION: ENVASE X 250 mL, TIPO: MONODROGA | H58: NO | I58: ='Necesidades Trimestrales'!F60 -> FRASCO | J58: ='Necesidades Trimestrales'!H60 -> 13840 | K58: ='Necesidades Trimestrales'!#REF! -> #REF!
A60: Costo total estimado: CUARENTA Y SIETE MILLONES QUINIENTOS NOVENTA Y SEIS MIL OCHOCIENTOS NOVENTA con 00/100. | J60: =SUMPRODUCT(J12:J59,K12:K59) -> #REF!

Sheet Autor Gastar DPFARMACIA
A1: EJERCICIO: | D1: ='Necesidades Trimestrales'!C6 -> 2022 | P1: AUTORIZACION PARA GASTAR
A4: JURISDICCIÓN: | G4: =' NotaPedido DPFARMACIA'!D3 -> 040 - Ministerio de Salud
A5: SAF: | G5: =' NotaPedido DPFARMACIA'!D4 -> 011 - Direccion Provincial de Administracion - MS
A6: UNIDAD EJECUTORA: | G6: =' NotaPedido DPFARMACIA'!D5 -> 469 - Direccion Provincial de Farmacia e Insumos
A7: DEPENDENCIA SOLICITANTE: | G7: =' NotaPedido DPFARMACIA'!D6 -> 469 - Direccion Provincial de Farmacia e Insumos
A8: AUTORIZACIÓN:
A9: Señor Jefe de Servicio Administrativo Financiero:
A10: ="Autorizo la realización de los trámites correspondientes, a fin de proveer a este Organismo los bienes y/o servicios que se detallan en Nota de Pedido N° " & ' NotaPedido DPFARMACIA'!K1&", afectando la erogación resultante a los créditos presupuestarios aprobados a favor de esta Unidad Ejecutora, conforme al siguiente detalle:" -> Autorizo la realización de los trámites correspondientes, a fin de proveer a este Organismo los bienes y/o servicios que se detallan en Nota de Pedido N° 16/2022, afectando la erogación resultante a los créditos presupuestarios aprobados a favor de esta Unidad Ejecutora, conforme al siguiente detalle:
A12: IMPUTACIÓN PRESUPUESTARIA
A13: CÓDIGO | O13: DENOMINACIÓN DE LA PARTIDA PRESUPUESTARIA | Q13: IMPORTE
A14: PR | B14: SB | C14: PY | D14: AC | E14: OB | F14: UG | G14: FIN | H14: FUN | I14: I | J14: P | K14: P | L14: SubP | M14: M | N14: FF
A15: 30 | D15: 1 | F15: 4901 | G15: 3 | H15: 1 | I15: 2 | J15: 5 | K15: 2 | M15: 1 | N15: 1.1 | O15: PRODUCTOS FARMACEUTICOS Y MEDICINALES | Q15: =' NotaPedido DPFARMACIA'!J60 -> #REF!
A23: TOTAL DE PESOS: CUARENTA Y SIETE MILLONES QUINIENTOS NOVENTA Y SEIS MIL OCHOCIENTOS NOVENTA con 00/100. | Q23: =SUM(Q15:Q22) -> #REF!
A25: JUSTIFICACIÓN:
A26: =' NotaPedido DPFARMACIA'!D8 -> Adquisición de TERAPIA ANTIINFECCIOSA SISTEMICA/SUEROS INMUNES E INMUNOGLOBULINAS Y MEDIOS DE CONTRASTES /ANALGESICOS ANTINFLAMATORIOS /MIORRELAJANTES/ANESTESICOS/ANALGESICOS OPIACIOS

Sheet  NotaPedido DPSAME
A1: NOTA DE PEDIDO | J1: N° | K1: 13/2022
A3: JURISDICCIÓN: | D3: ='Necesidades Trimestrales'!C4 -> 040 - Ministerio de Salud
A4: SAF: | D4: ='Necesidades Trimestrales'!C5 -> 011 - Direccion Provincial de Administracion - MS
A5: UNIDAD EJECUTORA: | D5: 748 - Direccion Provincial Sistema de Atencion Medica de Emergencia
A6: DEPENDENCIA SOLICITANTE: | D6: 748 - Direccion Provincial Sistema de Atencion Medica de Emergencia
A7: PERIODO UTILIZACIÓN: | D7: Semestral
A8: OBJETO: | D8: Adquisición de TERAPIA ANTIINFECCIOSA SISTEMICA/SUEROS INMUNES E INMUNOGLOBULINAS Y MEDIOS DE CONTRASTES /ANALGESICOS ANTINFLAMATORIOS /MIORRELAJANTES/ANESTESICOS/ANALGESICOS OPIACIOS
A10: Ítem | B10: Codigo Item | C10: DESCRIPCIÓN | H10: Adjunta Detalle Técnico | I10: Unidad Medida | J10: Precio Unitario Estimado | K10: Cantidad Solicitada
A12: 1 | B12: ='Necesidades Trimestrales'!B11 -> 2.5.2-1724.16 | C12: ='Necesidades Trimestrales'!E11 -> ANALGESICOS ; TIPO: MONODROGA, DROGA GENERICA: ACIDO ACETILSALICILICO, PRESENTACION: 100 mGr, FORMA FARMACEUTICA: COMPRIMIDO | H12: NO | I12: ='Necesidades Trimestrales'!F11 -> COMPRIMIDO | J12: ='Necesidades Trimestrales'!H11 -> 1.55 | K12: ='Necesidades Trimestrales'!#REF! -> #REF!
A13: 2 | B13: ='Necesidades Trimestrales'!B29 -> 2.5.2-1724.140 | C13: ='Necesidades Trimestrales'!E29 -> ANALGESICOS ; TIPO: MONODROGA, DROGA GENERICA: DICLOFENAC X 75 MG, FORMA FARMACEUTICA: COMPRIMIDO, PRESENTACION: UNIDAD | H13: NO | I13: ='Necesidades Trimestrales'!F29 -> COMPRIMIDO | J13: ='Necesidades Trimestrales'!H29 -> 3.05 | K13: ='Necesidades Trimestrales'!#REF! -> #REF!
A14: 3 | B14: ='Necesidades Trimestrales'!B30 -> 2.5.2-1724.117 | C14: ='Necesidades Trimestrales'!E30 -> ANALGESICOS ; TIPO: ASOCIACION, DROGA GENERICA: DICLOFENAC SODICO, FORMA FARMACEUTICA: AMPOLLA, PRESENTACION: 3 Ml | H14: NO | I14: ='Necesidades Trimestrales'!F30 -> AMPOLLA | J14: ='Necesidades Trimestrales'!H30 -> 35.9 | K14: ='Necesidades Trimestrales'!#REF! -> #REF!
A15: 4 | B15: ='Necesidades Trimestrales'!B31 -> 2.5.2-1724.208 | C15: ='Necesidades Trimestrales'!E31 -> ANALGESICOS ; TIPO: MONODROGA, DROGA GENERICA: DIPIRONA SODICA 1 GR, FORMA FARMACEUTICA: AMPOLLA, PRESENTACION: 2 mL | H15: NO | I15: ='Necesidades Trimestrales'!F31 -> AMPOLLA | J15: ='Necesidades Trimestrales'!H31 -> 38.5 | K15: ='Necesidades Trimestrales'!#REF! -> #REF!
A16: 5 | B16: ='Necesidades Trimestrales'!B37 -> 2.5.2-1724.163 | C16: ='Necesidades Trimestrales'!E37 -> ANALGESICOS ; TIPO: MONODROGA, DROGA GENERICA: IBUPROFENO 2%, FORMA FARMACEUTICA: SUSPENSION, PRESENTACION: ENVASE X 90 mL | H16: NO | I16: ='Necesidades Trimestrales'!F37 -> FRASCO | J16: ='Necesidades Trimestrales'!H37 -> 85 | K16: ='Necesidades Trimestrales'!#REF! -> #REF!
A17: 6 | B17: ='Necesidades Trimestrales'!B39 -> 2.5.2-1725.68 | C17: ='Necesidades Trimestrales'!E39 -> ANTIINFLAMATORIOS NO ESTEROIDE; TIPO: MONODROGA, DROGA GENERICA: IBUPROFENO, FORMA FARMACEUTICA: COMPRIMIDO, PRESENTACION: 400 mGr | H17: NO | I17: ='Necesidades Trimestrales'!F39 -> COMPRIMIDO | J17: ='Necesidades Trimestrales'!H39 -> 4.8 | K17: ='Necesidades Trimestrales'!#REF! -> #REF!
A18: 7 | B18: ='Necesidades Trimestrales'!B40 -> 2.5.2-1725.49 | C18: ='Necesidades Trimestrales'!E40 -> ANTIINFLAMATORIOS NO ESTEROIDE; DROGA GENERICA: KETOROLAC, FORMA FARMACEUTICA: COMPRIMIDO, PRESENTACION: 10 mGr, TIPO: MONODROGA | H18: NO | I18: ='Necesidades Trimestrales'!F40 -> COMPRIMIDO | J18: ='Necesidades Trimestrales'!H40 -> 3.3 | K18: ='Necesidades Trimestrales'!#REF! -> #REF!
A19: 8 | B19: ='Necesidades Trimestrales'!B41 -> 2.5.2-1724.23 | C19: ='Necesidades Trimestrales'!E41 -> ANALGESICOS ; TIPO: MONODROGA, DROGA GENERICA: KETOROLAC, FORMA FARMACEUTICA: AMPOLLA, PRESENTACION: 30 mGr | H19: NO | I19: ='Necesidades Trimestrales'!F41 -> AMPOLLA | J19: ='Necesidades Trimestrales'!H41 -> 56 | K19: ='Necesidades Trimestrales'!#REF! -> #REF!
A20: 9 | B20: ='Necesidades Trimestrales'!B43 -> 2.5.2-1883.136 | C20: ='Necesidades Trimestrales'!E43 -> ANESTESICOS LOCALES; TIPO: MONODROGA, DROGA GENERICA: LIDOCAINA 2% S/EPINEFRINA, FORMA FARMACEUTICA: FRASCO AMPOLLA, PRESENTACION: ENVASE X 20 mL | H20: NO | I20: ='Necesidades Trimestrales'!F43 -> AMPOLLA | J20: ='Necesidades Trimestrales'!H43 -> 325 | K20: ='Necesidades Trimestrales'!#REF! -> #REF!
A21: 10 | B21: ='Necesidades Trimestrales'!B49 -> 2.5.2-1870.15 | C21: ='Necesidades Trimestrales'!E49 -> HIPNOTICOS; TIPO: MONODROGA, DROGA GENERICA: MIDAZOLAM 15 mGr, FORMA FARMACEUTICA: AMPOLLA, PRESENTACION: ENVASE X 3 mL | H21: NO | I21: ='Necesidades Trimestrales'!F49 -> AMPOLLA | J21: ='Necesidades Trimestrales'!H49 -> 159 | K21: ='Necesidades Trimestrales'!#REF! -> #REF!
A22: 11 | B22: ='Necesidades Trimestrales'!B52 -> 2.5.2-1724.243 | C22: ='Necesidades Trimestrales'!E52 -> ANALGESICOS ; TIPO: MONODROGA, DROGA GENERICA: PARACETAMOL 1 GR, FORMA FARMACEUTICA: COMPRIMIDO, PRESENTACION: UNIDAD | H22: NO | I22: ='Necesidades Trimestrales'!F52 -> COMPRIMIDO | J22: ='Necesidades Trimestrales'!H52 -> 9.8 | K22: ='Necesidades Trimestrales'!#REF! -> #REF!
A24: Costo total estimado: NOVENTA Y TRES MIL NOVENTA con 00/100. | J24: =SUMPRODUCT(J12:J23,K12:K23) -> #REF!

Sheet Autor Gastar DPSAME
A1: EJERCICIO: | D1: ='Necesidades Trimestrales'!C6 -> 2022 | P1: AUTORIZACION PARA GASTAR
A4: JURISDICCIÓN: | G4: =' NotaPedido DPSAME'!D3 -> 040 - Ministerio de Salud
A5: SAF: | G5: =' NotaPedido DPSAME'!D4 -> 011 - Direccion Provincial de Administracion - MS
A6: UNIDAD EJECUTORA: | G6: =' NotaPedido DPSAME'!D5 -> 748 - Direccion Provincial Sistema de Atencion Medica de Emergencia
A7: DEPENDENCIA SOLICITANTE: | G7: =' NotaPedido DPSAME'!D6 -> 748 - Direccion Provincial Sistema de Atencion Medica de Emergencia
A8: AUTORIZACIÓN:
A9: Señor Jefe de Servicio Administrativo Financiero:
A10: ="Autorizo la realización de los trámites correspondientes, a fin de proveer a este Organismo los bienes y/o servicios que se detallan en Nota de Pedido N° " & ' NotaPedido DPSAME'!K1&", afectando la erogación resultante a los créditos presupuestarios aprobados a favor de esta Unidad Ejecutora, conforme al siguiente detalle:" -> Autorizo la realización de los trámites correspondientes, a fin de proveer a este Organismo los bienes y/o servicios que se detallan en Nota de Pedido N° 13/2022, afectando la erogación resultante a los créditos presupuestarios aprobados a favor de esta Unidad Ejecutora, conforme al siguiente detalle:
A12: IMPUTACIÓN PRESUPUESTARIA
A13: CÓDIGO | O13: DENOMINACIÓN DE LA PARTIDA PRESUPUESTARIA | Q13: IMPORTE
A14: PR | B14: SB | C14: PY | D14: AC | E14: OB | F14: UG | G14: FIN | H14: FUN | I14: I | J14: P | K14: P | L14: SubP | M14: M | N14: FF
A15: 31 | D15: 1 | F15: 4901 | G15: 3 | H15: 1 | I15: 2 | J15: 5 | K15: 2 | M15: 1 | N15: 1.1 | O15: PRODUCTOS FARMACEUTICOS Y MEDICINALES | Q15: =' NotaPedido DPSAME'!J24 -> #REF!
A23: TOTAL DE PESOS: NOVENTA Y TRES MIL NOVENTA con 00/100. | Q23: =SUM(Q15:Q22) -> #REF!
A25: JUSTIFICACIÓN:
A26: =' NotaPedido DPSAME'!D8 -> Adquisición de TERAPIA ANTIINFECCIOSA SISTEMICA/SUEROS INMUNES E INMUNOGLOBULINAS Y MEDIOS DE CONTRASTES /ANALGESICOS ANTINFLAMATORIOS /MIORRELAJANTES/ANESTESICOS/ANALGESICOS OPIACIOS
