Workbook

Sheet Necesidades Trimestrales
B2: Pedido de Necesidades Trimestrales
A4: JURISDICCION: | C4: 40 - Ministerio de Salud
A5: SAF N°: | C5: 24 - Direccion de Administracion del Hospital Interzonal de Niños
A6: EJERCICIO: | C6: 2022
A7: TRIMESTRE: | C7: 3
A9: ID | B9: CODIGO ITEM | C9: RUBRO DE COMPRA | D9: I.P.P. | E9: DESCRIPCION | F9: UNIDAD DE MEDIDA | G9: CANTIDAD | H9: PRECIO UNITARIO ESTIMADO | I9: IMPORTE TOTAL ESTIMADO
A10: 1 | B10: 2.9.4-588.68 | C10: BAZAR Y MENAJE | D10: 294 | E10: VASOS PLASTICOS DESCARTABLES; MATERIAL: POLIESTIRENO, MOTIVO: LISO, CAPACIDAD: 250 CM3, PRESENTACION: BOLSA X 100 UN, TIPO: BLANCO | F10: BOLSA | G10: 240 | H10: 2160 | I10: =H10*G10 -> 518400
A11: 2 | B11: 2.9.4-690.15 | C11: BAZAR Y MENAJE | D11: 294 | E11: CUCHARAS; TIPO: DE MESA, MATERIAL: PLASTICO | F11: UNIDAD | G11: 8000 | H11: 8 | I11: =G11*H11 -> 64000
A12: 3 | B12: 2.9.4-689.15 | C12: BAZAR Y MENAJE | D12: 294 | E12: CUCHILLOS; TIPO: DE MESA, MATERIAL: PLASTICO | F12: UNIDAD | G12: 5000 | H12: 5.5 | I12: =G12*H12 -> 27500
A13: 4 | B13: 2.9.4-692.10 | C13: BAZAR Y MENAJE | D13: 294 | E13: TENEDORES; TIPO: DE MESA, MATERIAL: PLASTICO | F13: UNIDAD | G13: 8000 | H13: 5.5 | I13: =G13*H13 -> 44000
A14: 5 | B14: 2.9.4-588.67 | C14: BAZAR Y MENAJE | D14: 294 | E14: VASOS PLASTICOS DESCARTABLES; MATERIAL: POLIPROPILENO, MOTIVO: LISO C/TAPA, CAPACIDAD: 500 CM3, PRESENTACION: ENVASE X 50, TIPO: ESTRIADO | F14: PAQUETE | G14: 40 | H14: 1500 | I14: =G14*H14 -> 60000
A15: 6 | B15: 2.9.4-588.50 | C15: BAZAR Y MENAJE | D15: 294 | E15: VASOS PLASTICOS DESCARTABLES; MATERIAL: POLIETILENO, CAPACIDAD: 220 CM3, PRESENTACION: PAQUETE X 100 UN, TIPO: BLANCO, MOTIVO: LISO | F15: PAQUETE | G15: 240 | H15: 900 | I15: =G15*H15 -> 216000
A16: 7 | B16: 2.3.4-938.13 | C16: BAZAR Y MENAJE | D16: 234 | E16: SERVILLETAS DE PAPEL; PRESENTACION: PAQUETE X 100, DIMENSION: 24 X 24 Cm, COLOR: BLANCO, MOTIVO: SIN VALOR, TIPO: LISAS | F16: PAQUETE | G16: 50 | H16: 240 | I16: =G16*H16 -> 12000
A17: 8 | B17: 2.3.4-5442.12 | C17: BAZAR Y MENAJE | D17: 234 | E17: ROLLOS P/COCINA; DIMENSION: 0,33 X 400 M, PRESENTACION: BOBINA | F17: BOBINA | G17: 40 | H17: 2500 | I17: =G17*H17 -> 100000
A18: 9 | B18: 2.9.4-4743.23 | C18: BAZAR Y MENAJE | D18: 294 | E18: BANDEJA P/TRANSP. DE ALIMENTO; DIMENSION: 18 X 14 X 4 Cm, TIPO: RECTANGULAR CON TAPA, MATERIAL: ALUMINIO, CAPACIDAD: 750 CM2 | F18: UNIDAD | G18: 36000 | H18: 40 | I18: =G18*H18 -> 1440000
A19: 10 | B19: 2.9.5-5755.16 | C19: PROD. MEDICO/FARMACEUTICOS/LAB | D19: 258 | E19: FILMS AUTOADHERENTES; TIPO: TRANSPARENTE, MATERIAL: POLIETILENO, PRESENTACION: ENVASE X 300 M, ANCHO: 38 Cm | F19: UNIDAD | G19: 20 | H19: 4100 | I19: =G19*H19 -> 82000
A20: 11 | B20: 2.5.8-3977.78 | C20: FERRETERIA | D20: 258 | E20: BOLSAS DE POLIETILENO; TAMAÑO: 20 X 30 Cm, ESPESOR: 30 mm, PRESENTACION: ENVASE X 100 UN | F20: ROLLO | G20: 20 | H20: 2100 | I20: =G20*H20 -> 42000
A21: 12 | B21: 2.5.8-3977.63 | C21: FERRETERIA | D21: 258 | E21: BOLSAS DE POLIETILENO; TAMAÑO: 35 X 45 Cm, ESPESOR: 30 Mn, PRESENTACION: ROLLO X 150 UN | F21: ROLLO | G21: 20 | H21: 2100 | I21: =G21*H21 -> 42000
B23: Especificidades Item N° 1:
B24: Descripción técnica: CON TAPA.
B25: Especificidades Item N° 2:
B26: Descripción técnica: SOPERAS, REFORZADAS DESCARTABLES.
B27: Especificidades Item N° 3 y 4:
B28: Descripción técnica: REFORZADOS DESCARTABLES.
B29: Especificidades Item N° 11 y 12:
B30: Descripción técnica: ROLLO DE BOLSAS DE ARRANQUE.
B31: Plazos y lugares de entrega
B32: Lugar de Entrega: SERVICIO DE ALIMENTACION Y DIETOTERAPIA -HOSPITAL INT. DE NIÑOS – AV. VIRGEN DEL VALLE N° 1050-CATAMARCA DE 8:00 A 12:00HS., DEBIENDO CORRER LOS GASTOS DE FLETES, ACARREO, CARGA, DESCARGA Y SEGURO A CARGO DEL ADJUDICATARIO.
B34: Plazo de entrega: Dentro de los Diez (10) días habiles de notificada la Orden de Compra
B35: Mantenimiento de Oferta: Cuarenta y cinco (45) dias habiles
B36: Forma de Pago: Treinta (30) dias habiles.

Sheet  NotaPedido
A1: NOTA DE PEDIDO | J1: N° | K1: 066/2022
A3: JURISDICCIÓN: | D3: ='Necesidades Trimestrales'!C4 -> 40 - Ministerio de Salud
A4: SAF: | D4: ='Necesidades Trimestrales'!C5 -> 24 - Direccion de Administracion del Hospital Interzonal de Niños
A5: UNIDAD EJECUTORA: | D5: 24 - Direccion de Administracion del Hospital Interzonal de Niños
A6: DEPENDENCIA SOLICITANTE: | D6: Servicio de Alimentacion y Dietoterapia
A7: PERIODO UTILIZACIÓN: | D7: ='Necesidades Trimestrales'!C7 & "° Trimestre - Año " & 'Necesidades Trimestrales'!C6 -> 3° Trimestre - Año 2022
A8: OBJETO: | D8: Adquisición de Descartables de Cocina
A10: Ítem | B10: Codigo Item | C10: DESCRIPCIÓN | H10: Adjunta Detalle Técnico | I10: Unidad Medida | J10: Precio Unitario Estimado | K10: Cantidad Solicitada
A12: 1 | B12: ='Necesidades Trimestrales'!B10 -> 2.9.4-588.68 | C12: ='Necesidades Trimestrales'!E10 -> VASOS PLASTICOS DESCARTABLES; MATERIAL: POLIESTIRENO, MOTIVO: LISO, CAPACIDAD: 250 CM3, PRESENTACION: BOLSA X 100 UN, TIPO: BLANCO | H12: SI | I12: ='Necesidades Trimestrales'!F10 -> BOLSA | J12: ='Necesidades Trimestrales'!H10 -> 2160 | K12: ='Necesidades Trimestrales'!G10 -> 240
A13: 2 | B13: ='Necesidades Trimestrales'!B11 -> 2.9.4-690.15 | C13: ='Necesidades Trimestrales'!E11 -> CUCHARAS; TIPO: DE MESA, MATERIAL: PLASTICO | H13: SI | I13: ='Necesidades Trimestrales'!F11 -> UNIDAD | J13: ='Necesidades Trimestrales'!H11 -> 8 | K13: ='Necesidades Trimestrales'!G11 -> 8000
A14: 3 | B14: ='Necesidades Trimestrales'!B12 -> 2.9.4-689.15 | C14: ='Necesidades Trimestrales'!E12 -> CUCHILLOS; TIPO: DE MESA, MATERIAL: PLASTICO | H14: SI | I14: ='Necesidades Trimestrales'!F12 -> UNIDAD | J14: ='Necesidades Trimestrales'!H12 -> 5.5 | K14: ='Necesidades Trimestrales'!G12 -> 5000
A15: 4 | B15: ='Necesidades Trimestrales'!B13 -> 2.9.4-692.10 | C15: ='Necesidades Trimestrales'!E13 -> TENEDORES; TIPO: DE MESA, MATERIAL: PLASTICO | H15: SI | I15: ='Necesidades Trimestrales'!F13 -> UNIDAD | J15: ='Necesidades Trimestrales'!H13 -> 5.5 | K15: ='Necesidades Trimestrales'!G13 -> 8000
A16: 5 | B16: ='Necesidades Trimestrales'!B14 -> 2.9.4-588.67 | C16: ='Necesidades Trimestrales'!E14 -> VASOS PLASTICOS DESCARTABLES; MATERIAL: POLIPROPILENO, MOTIVO: LISO C/TAPA, CAPACIDAD: 500 CM3, PRESENTACION: ENVASE X 50, TIPO: ESTRIADO | H16: NO | I16: ='Necesidades Trimestrales'!F14 -> PAQUETE | J16: ='Necesidades Trimestrales'!H14 -> 1500 | K16: ='Necesidades Trimestrales'!G14 -> 40
A17: 6 | B17: ='Necesidades Trimestrales'!B15 -> 2.9.4-588.50 | C17: ='Necesidades Trimestrales'!E15 -> VASOS PLASTICOS DESCARTABLES; MATERIAL: POLIETILENO, CAPACIDAD: 220 CM3, PRESENTACION: PAQUETE X 100 UN, TIPO: BLANCO, MOTIVO: LISO | H17: NO | I17: ='Necesidades Trimestrales'!F15 -> PAQUETE | J17: ='Necesidades Trimestrales'!H15 -> 900 | K17: ='Necesidades Trimestrales'!G15 -> 240
A18: 7 | B18: ='Necesidades Trimestrales'!B16 -> 2.3.4-938.13 | C18: ='Necesidades Trimestrales'!E16 -> SERVILLETAS DE PAPEL; PRESENTACION: PAQUETE X 100, DIMENSION: 24 X 24 Cm, COLOR: BLANCO, MOTIVO: SIN VALOR, TIPO: LISAS | H18: NO | I18: ='Necesidades Trimestrales'!F16 -> PAQUETE | J18: ='Necesidades Trimestrales'!H16 -> 240 | K18: ='Necesidades Trimestrales'!G16 -> 50
A19: 8 | B19: ='Necesidades Trimestrales'!B17 -> 2.3.4-5442.12 | C19: ='Necesidades Trimestrales'!E17 -> ROLLOS P/COCINA; DIMENSION: 0,33 X 400 M, PRESENTACION: BOBINA | H19: NO | I19: ='Necesidades Trimestrales'!F17 -> BOBINA | J19: ='Necesidades Trimestrales'!H17 -> 2500 | K19: ='Necesidades Trimestrales'!G17 -> 40
A20: 9 | B20: ='Necesidades Trimestrales'!B18 -> 2.9.4-4743.23 | C20: ='Necesidades Trimestrales'!E18 -> BANDEJA P/TRANSP. DE ALIMENTO; DIMENSION: 18 X 14 X 4 Cm, TIPO: RECTANGULAR CON TAPA, MATERIAL: ALUMINIO, CAPACIDAD: 750 CM2 | H20: NO | I20: ='Necesidades Trimestrales'!F18 -> UNIDAD | J20: ='Necesidades Trimestrales'!H18 -> 40 | K20: ='Necesidades Trimestrales'!G18 -> 36000
A21: 10 | B21: ='Necesidades Trimestrales'!B19 -> 2.9.5-5755.16 | C21: ='Necesidades Trimestrales'!E19 -> FILMS AUTOADHERENTES; TIPO: TRANSPARENTE, MATERIAL: POLIETILENO, PRESENTACION: ENVASE X 300 M, ANCHO: 38 Cm | H21: NO | I21: ='Necesidades Trimestrales'!F19 -> UNIDAD | J21: ='Necesidades Trimestrales'!H19 -> 4100 | K21: ='Necesidades Trimestrales'!G19 -> 20
A22: 11 | B22: ='Necesidades Trimestrales'!B20 -> 2.5.8-3977.78 | C22: ='Necesidades Trimestrales'!E20 -> BOLSAS DE POLIETILENO; TAMAÑO: 20 X 30 Cm, ESPESOR: 30 mm, PRESENTACION: ENVASE X 100 UN | H22: SI | I22: ='Necesidades Trimestrales'!F20 -> ROLLO | J22: ='Necesidades Trimestrales'!H20 -> 2100 | K22: ='Necesidades Trimestrales'!G20 -> 20
A23: 12 | B23: ='Necesidades Trimestrales'!B21 -> 2.5.8-3977.63 | C23: ='Necesidades Trimestrales'!E21 -> BOLSAS DE POLIETILENO; TAMAÑO: 35 X 45 Cm, ESPESOR: 30 Mn, PRESENTACION: ROLLO X 150 UN | H23: SI | I23: ='Necesidades Trimestrales'!F21 -> ROLLO | J23: ='Necesidades Trimestrales'!H21 -> 2100 | K23: ='Necesidades Trimestrales'!G21 -> 20
A24: Costo total estimado: Dos Millones Seiscientos Cuarenta y Siete Mil Novecientos con 00/100. | J24: =SUMPRODUCT(J12:J23,K12:K23) -> 2647900

Sheet Autor Gastar
A1: EJERCICIO: | D1: ='Necesidades Trimestrales'!C6 -> 2022 | P1: AUTORIZACION PARA GASTAR
A4: JURISDICCIÓN: | G4: =' NotaPedido'!D3 -> 40 - Ministerio de Salud
A5: SAF: | G5: =' NotaPedido'!D4 -> 24 - Direccion de Administracion del Hospital Interzonal de Niños
A6: UNIDAD EJECUTORA: | G6: =' NotaPedido'!D5 -> 24 - Direccion de Administracion del Hospital Interzonal de Niños
A7: DEPENDENCIA SOLICITANTE: | G7: =' NotaPedido'!D6 -> Servicio de Alimentacion y Dietoterapia
A8: AUTORIZACIÓN:
A9: Señor Jefe de Servicio Administrativo Financiero:
A10: ="Autorizo la realización de los trámites correspondientes, a fin de proveer a este Organismo los bienes y/o servicios que se detallan en Nota de Pedido N° " & ' NotaPedido'!K1&", afectando la erogación resultante a los créditos presupuestarios aprobados a favor de esta Unidad Ejecutora, conforme al siguiente detalle:" -> Autorizo la realización de los trámites correspondientes, a fin de proveer a este Organismo los bienes y/o servicios que se detallan en Nota de Pedido N° 066/2022, afectando la erogación resultante a los créditos presupuestarios aprobados a favor de esta Unidad Ejecutora, conforme al siguiente detalle:
A12: IMPUTACIÓN PRESUPUESTARIA
A13: CÓDIGO | O13: DENOMINACIÓN DE LA PARTIDA PRESUPUESTARIA | Q13: IMPORTE
A14: PR | B14: SB | C14: PY | D14: AC | E14: OB | F14: UG | G14: FIN | H14: FUN | I14: I | J14: P | K14: P | L14: SubP | M14: M | N14: FF
A15: 36 | D15: 1 | F15: 4901 | G15: 3 | H15: 310 | I15: =LEFT('Necesidades Trimestrales'!D10,1) -> 2 | J15: 3 | K15: 4 | M15: 1 | N15: 1.1 | O15: Productos de Papel y Carton | Q15: 112000
A16: 36 | D16: 1 | F16: 4901 | G16: 3 | H16: 310 | I16: =LEFT('Necesidades Trimestrales'!D11,1) -> 2 | J16: 5 | K16: 8 | M16: 1 | N16: 1.1 | O16: Productos de Material Plastico | Q16: 166000
A17: 36 | D17: 1 | F17: 4901 | G17: 3 | H17: 310 | I17: 2 | J17: 9 | K17: 4 | M17: 1 | N17: 1.1 | O17: Utensilios de Cocina y Comedor | Q17: 2369900
A23: TOTAL DE PESOS: DOS MILLONES SEISCIENTOS CUARENTA Y SIETE MIL NOVECIENTOS CON 00/100. | Q23: =SUM(Q15:Q22) -> 2647900
A25: JUSTIFICACIÓN:
A26: Para la adquisición de Descartables de Cocina destinados al servico de Alimentacion y Dietoterapia del Hospital Interzonal de Niños Eva Peron, para el normal funcionamiento del organismo.
