Workbook

Sheet Necesidades Trimestrales
B2: Pedido de Necesidades Trimestrales
A4: JURISDICCION: | C4: 90 - Ministerio de Seguridad
A5: SAF N°: | C5: 7- Dirección Provincial de Administración de la Policía de la Provincia de Catamarca
A6: EJERCICIO: | C6: 2022
A7: TRIMESTRE: | C7: 2
A9: ID | B9: CODIGO ITEM | C9: DESCRIPCION | D9: UNIDAD DE MEDIDA | E9: CANTIDAD | F9: PRECIO UNITARIO ESTIMADO | G9: IMPORTE TOTAL ESTIMADO
A10: 1 | B10: 2.1.1-481.38 | C10: AZUCARES; TIPO: "A" COMUN, ESTADO: MOLIDA, PESO: 1 Kg, MATERIAL ENVASE: PLASTICO, CERTIFICADO FORESTAL (GFS): SIN, ELEM. TRANSPORTE: SIN, MATERIAL ELEM. TRANSPORTE: SIN | D10: UNIDAD | E10: 2000 | F10: 120 | G10: =(E10*F10) -> 240000
A11: 2 | B11: 2.1.1-454.25 | C11: YERBAS; PALO: CON, PESO: 1 Kg, MATERIAL ENVASE : PAPEL, CERTIFICADO FORESTAL (GFS): CON, ELEM. TRANSPORTE: SIN, MATERIAL ELEM. TRANSPORTE: SIN, LIBRE DE GLUTEN: SI | D11: UNIDAD | E11: 900 | F11: 480 | G11: =(E11*F11) -> 432000
A12: 3 | B12: 2.1.1-439.67 | C12: ACEITES COMESTIBLES; TIPO: GIRASOL, PRESENTACION: ENVASE X 900 CM3, MATERIAL ENVASE: PLASTICO 1 (PET), ELEM. TRANSPORTE: SIN, MATERIAL ELEM. TRANSPORTE : SIN, LIBRE DE GLUTEN: NO | D12: UNIDAD | E12: 600 | F12: 395 | G12: =(E12*F12) -> 237000
A13: 4 | B13: 2.1.1-708.23 | C13: CONSERVAS PESCADO Y FRUTOS MAR; ESTADO: AL NATURAL, PESO: 380 GR, ENVASE: LATA, TIPO: CABALLA, ESPECIE: CABALLA | D13: UNIDAD | E13: 800 | F13: 520 | G13: =(E13*F13) -> 416000
A14: 5 | B14: 2.1.1-6546.5 | C14: VERDURAS Y HORTALIZAS; PRESENTACION: BOTELLA, VARIEDAD: TOMATE PERITA, ESTADO: TRITURADO, PESO: 970 GR | D14: UNIDAD | E14: 500 | F14: 230 | G14: =(E14*F14) -> 115000
A15: 6 | B15: 2.1.1-6547.84 | C15: LEGUMBRES; VARIEDAD: ARVEJAS, ESTADO: CONSERVA, PRESENTACION: LATA, PESO: 350 GR, MATERIAL ENVASE: METAL, ELEM. TRANSPORTE: SIN, MATERIAL ELEM. TRANSPORTE: SIN, LIBRE DE GLUTEN: NO | D15: UNIDAD | E15: 500 | F15: 75 | G15: =(E15*F15) -> 37500
A16: 7 | B16: 2.1.1-2868.78 | C16: FIDEOS SECOS; LIBRE DE GLUTEN: NO, CERTIFICADO FORESTAL (GFS): SIN, MATERIAL ELEM. TRANSPORTE: SIN, ELEM. TRANSPORTE: SIN, MATERIAL ENVASE: POLIETILENO, PRESENTACION: ENVASE X 500 GR, RELLENO: SIN, VARIEDAD: TALLARIN | D16: UNIDAD | E16: 800 | F16: 90 | G16: =(E16*F16) -> 72000
A17: 8 | B17: 2.1.1-2868.76 | C17: FIDEOS SECOS; LIBRE DE GLUTEN: NO, CERTIFICADO FORESTAL (GFS): SIN, MATERIAL ELEM. TRANSPORTE: SIN, ELEM. TRANSPORTE: SIN, MATERIAL ENVASE: POLIETILENO, PRESENTACION: ENVASE X 500 GR, RELLENO: SIN, VARIEDAD: GUISERO | D17: UNIDAD | E17: 800 | F17: 90 | G17: =(E17*F17) -> 72000
A18: 9 | B18: 2.1.1-2868.77 | C18: FIDEOS SECOS; LIBRE DE GLUTEN: NO, CERTIFICADO FORESTAL (GFS): SIN, MATERIAL ELEM. TRANSPORTE: SIN, ELEM. TRANSPORTE: SIN, MATERIAL ENVASE: POLIETILENO, PRESENTACION: ENVASE X 500 GR, RELLENO: SIN, VARIEDAD: SOPERO | D18: UNIDAD | E18: 800 | F18: 90 | G18: =(E18*F18) -> 72000
A19: 10 | B19: 2.1.1-435.60 | C19: ARROZ; TIPO GRANO: LARGO-FINO, TIPO: BLANCO, PROCESO: SIN CASCARA, PRESENTACION: BOLSA X 1 Kg, MATERIAL ENVASE: PLASTICO, CERTIFICADO FORESTAL (GFS): SIN, ELEM. TRANSPORTE: SIN, MATERIAL ELEM. TRANSPORTE: SIN, LIBRE DE GLUTEN: SI | D19: UNIDAD | E19: 2000 | F19: 120 | G19: =(E19*F19) -> 240000
A20: 11 | B20: 2.1.1-514.2 | C20: SAL DE MESA; CONSISTENCIA: FINA, PESO: 500 GR, TIPO: SIN VALOR, ENVASE: PAQUETE | D20: UNIDAD | E20: 300 | F20: 50 | G20: =(E20*F20) -> 15000
A21: 12 | B21: 2.1.1-514.14 | C21: SAL DE MESA; ENVASE: BOLSA, PESO: 5 Kg, CONSISTENCIA: GRUESA, TIPO: SIN VALOR | D21: UNIDAD | E21: 300 | F21: 500 | G21: =(E21*F21) -> 150000
... A47: 38 | B47: 2.1.1-489.68 | C47: ESPECIAS; PRESENTACION: BOLSA DE 1 Kg, TIPO: AJI MOLIDO | D47: UNIDAD | E47: 50 | F47: 900 | G47: =(E47*F47) -> 45000
G48: =SUM(G10:G47) -> 5781400
B49: Especificidades:
C50: DESCRIPCION ITEM 35: ENVASE BOLSA
C51: DESCRIPCION ITEM 36: PRESENTACION SAQUITOS
C52: ITEM 1 AL 38 : Se requieren las siguientes consideraciones en los alimentos no perecederos: “Todos los productos deberán presentar en el envase el rótulo bien legible y responder a toda la información establecida en el Código Alimentario Argentino – Cap. V: “Normas para la Rotulación y Publicidad de Alimentos”. ANEXO Reglamento Técnico MERCOSUR para la rotulación de Alimentos Envasados – Inciso 5: Información Obligatoria: Denominación de venta del alimento; Lista de ingredientes; Contenidos netos; Identificación del origen; Nombre o razón social y dirección del importador, para alimentos importados; Identificación del lote; Fecha de duración mínima; Instrucción de uso del alimento, cuando corresponda. La fecha de vencimiento de los productos adjudicados debe ser mayor a 6 (seis) meses al momento de ser bajada en el lugar de entrega y responder a las marcas y características presentadas en la oferta de la presente contratación. Además, debe presentarse el envase en óptimas condiciones de higiene e integridad del mismo.
B58: Plazos y lugares de entrega
C59: a) LUGAR DE ENTREGA: En la Escuela de Cadetes de Policía– sito en Av. Acosta Villafañez al 1.500 de la ciudad de San Fernando del Valle de Catamarca. b) FORMA DE LA ENTREGA: Libre de flete, acarreo y embalaje, como así también, de todo riesgo de pérdida o destrucción total o parcial, por causas ajenas a la Institución. c) PLAZO DE ENTREGA: Las entregas se realizarán a requerimiento de acuerdo, a las Solicitudes de Provisión que se realicen. Se estima emitir una cantidad aproximada de 2 (Dos) Solicitudes de Provisión de 1/2 aprox. de la cantidad solicitada, en un plazo de 2 (Dos) meses: 1° Solic.de Provisión: aprox.a los 2 (Dos) dias hábiles de la firma del instrumento contractual, 2° Solic.de Provisión: al mes de la firma del instrumento contractual. Plazo de cumplimiento de cada Solicitud de Provisión: a los 5 días hábiles de notificada la misma, según necesidades del Organismo solicitante. Forma de Pago: Se solicita Pagos parciales por cada Solicitud de Provisión emitida, una vez finalizada la entrega de las cantidades contenidas en la misma.
B61: Calidad Minima esperada
C62: Que cumpla con lo solicitado en forma íntegra. Presentar muestras para los ítems 1 al 38, en su envase original, en el cual se pueda observar de forma clara la marca del mismo y sus características. La recepción de las muestras se realizará en el Departamento Logística (D-4) de la Policía de Catamarca, hasta el momentos de la apertura, sito en Ruta Provincial N° 33-sumalao-Valle Viejo. Provincia de Catamarca. Las muestras deben estar debidamente rotuladas por ítems e identificando claramente el oferente cotizante. No se aceptan muestras distinto a lo cotizado.
B65: Mantenimiento
C66: 30 días
B67: Garantia
C68: *

Sheet  NotaPedido
A1: NOTA DE PEDIDO | J1: N° | K1: 81/2021
A3: JURISDICCIÓN: | D3: ='Necesidades Trimestrales'!C4 -> 90 - Ministerio de Seguridad
A4: SAF: | D4: ='Necesidades Trimestrales'!C5 -> 7- Dirección Provincial de Administración de la Policía de la Provincia de Catamarca
A5: UNIDAD EJECUTORA: | D5: Policía de la Provincia de Catamarca
A6: DEPENDENCIA SOLICITANTE: | D6: División Intendencia, Departamento Logística
A7: PERIODO UTILIZACIÓN: | D7: 3er trimestre Año 2021.-
A8: OBJETO: | D8: Adquisición de Uniformes de Fajina para el personal policial.
A10: Ítem | B10: Codigo Item | C10: DESCRIPCIÓN | H10: Adjunta Detalle Técnico | I10: Unidad Medida | J10: Precio Unitario Estimado | K10: Cantidad Solicitada
A12: 1 | B12: ='Necesidades Trimestrales'!#REF! -> #REF! | C12: ='Necesidades Trimestrales'!#REF! -> #REF! | H12: SI | I12: ='Necesidades Trimestrales'!#REF! -> #REF! | J12: ='Necesidades Trimestrales'!#REF! -> #REF! | K12: ='Necesidades Trimestrales'!#REF! -> #REF!
B13: ='Necesidades Trimestrales'!#REF! -> #REF! | C13: ='Necesidades Trimestrales'!#REF! -> #REF! | H13: SI | I13: ='Necesidades Trimestrales'!#REF! -> #REF! | J13: ='Necesidades Trimestrales'!#REF! -> #REF! | K13: ='Necesidades Trimestrales'!#REF! -> #REF!
A14: 3 | B14: ='Necesidades Trimestrales'!#REF! -> #REF! | C14: ='Necesidades Trimestrales'!#REF! -> #REF! | H14: SI | I14: ='Necesidades Trimestrales'!#REF! -> #REF! | J14: ='Necesidades Trimestrales'!#REF! -> #REF! | K14: ='Necesidades Trimestrales'!#REF! -> #REF!
A15: Costo total estimado: Pesos Cinco Millones Doscientos Mil con 00/100.- | J15: ='Necesidades Trimestrales'!G14 -> 115000

Sheet Autor Gastar
A1: EJERCICIO: | D1: ='Necesidades Trimestrales'!C6 -> 2022 | P1: AUTORIZACION PARA GASTAR
A4: JURISDICCIÓN: | G4: =' NotaPedido'!D3 -> 90 - Ministerio de Seguridad
A5: SAF: | G5: =' NotaPedido'!D4 -> 7- Dirección Provincial de Administración de la Policía de la Provincia de Catamarca
A6: UNIDAD EJECUTORA: | G6: =' NotaPedido'!D5 -> Policía de la Provincia de Catamarca
A7: DEPENDENCIA SOLICITANTE: | G7: =' NotaPedido'!D6 -> División Intendencia, Departamento Logística
A8: AUTORIZACIÓN:
A9: Señor Jefe de Servicio Administrativo Financiero:
A10: ="Autorizo la realización de los trámites correspondientes, a fin de proveer a este Organismo los bienes y/o servicios que se detallan en Nota de Pedido N° " &' NotaPedido'!K1&", afectando la erogación resultante a los créditos presupuestarios aprobados a favor de esta Unidad Ejecutora, conforme al siguiente detalle:" -> Autorizo la realización de los trámites correspondientes, a fin de proveer a este Organismo los bienes y/o servicios que se detallan en Nota de Pedido N° 81/2021, afectando la erogación resultante a los créditos presupuestarios aprobados a favor de esta Unidad Ejecutora, conforme al siguiente detalle:
A12: IMPUTACIÓN PRESUPUESTARIA
A13: CÓDIGO | O13: DENOMINACIÓN DE LA PARTIDA PRESUPUESTARIA | Q13: IMPORTE
A14: PR | B14: SB | C14: PY | D14: AC | E14: OB | F14: UG | G14: FIN | H14: FUN | I14: I | J14: P | K14: P | L14: SubP | M14: M | N14: FF
A15: 16 | B15: 0 | C15: 0 | D15: 1 | E15: 0 | F15: 10 | G15: 2 | H15: 210 | I15: 2 | J15: 9 | K15: 1 | L15: 0 | M15: 1 | N15: 1.1 | O15: ='Necesidades Trimestrales'!#REF! -> #REF! | Q15: =' NotaPedido'!J15 -> 115000
A16: TOTAL DE PESOS: Treinta y Cuatro Mil Novecientos Cincuenta con 00/100.- | Q16: =Q15 -> 115000
A18: JUSTIFICACIÓN:
A19: =' NotaPedido'!D8 -> Adquisición de Uniformes de Fajina para el personal policial.
