Workbook

Sheet Necesidades Trimestrales
B2: Pedido de Necesidades Trimestrales
A4: JURISDICCION: | C4: 040 - Ministerio de Salud
A5: SAF N°: | C5: 024 - Hospital Interzonal de Niños
A6: EJERCICIO: | C6: 2021
A7: TRIMESTRE: | C7: 2
A9: ID | B9: CODIGO ITEM | C9: RUBRO DE COMPRA | D9: I.P.P. | E9: DESCRIPCION | F9: UNIDAD DE MEDIDA | G9: CANTIDAD | H9: PRECIO UNITARIO ESTIMADO | I9: IMPORTE TOTAL ESTIMADO
A10: 1 | C10: PROD. MEDICO/ FARMACEUTICOS/LAB | D10: 2.9.5 | E10: AEROCAMARA C/ MASCARA PEDIATRICA | F10: unidad | G10: 2000 | H10: 230 | I10: =G10*H10 -> 460000
A11: 2 | C11: PROD. MEDICO/ FARMACEUTICOS/LAB | D11: 2.9.5 | E11: AGUJA ESPINAL 18 G X 3-1/2 | F11: unidad | G11: 50 | H11: 520 | I11: =G11*H11 -> 26000
A12: 3 | C12: PROD. MEDICO/ FARMACEUTICOS/LAB | D12: 2.9.5 | E12: AGUJA ESPINAL 19 G 3-1/2 | F12: unidad | G12: 50 | H12: 520 | I12: =G12*H12 -> 26000
A13: 4 | C13: PROD. MEDICO/ FARMACEUTICOS/LAB | D13: 2.9.5 | E13: AGUJA ESPINA Nº 20 | F13: unidad | G13: 50 | H13: 230 | I13: =G13*H13 -> 11500
A14: 5 | C14: PROD. MEDICO/ FARMACEUTICOS/LAB | D14: 2.9.5 | E14: AGUJA ESPINAL 22 G X 1 | F14: unidad | G14: 50 | H14: 520 | I14: =G14*H14 -> 26000
A15: 6 | C15: PROD. MEDICO/ FARMACEUTICOS/LAB | D15: 2.9.5 | E15: Aguja ESPINAL 23 G 3 1/2 | F15: unidad | G15: 50 | H15: 520 | I15: =G15*H15 -> 26000
A16: 7 | C16: PROD. MEDICO/ FARMACEUTICOS/LAB | D16: 2.9.5 | E16: Aguja ESPINAL 25 G 3 1/2 | F16: unidad | G16: 50 | H16: 520 | I16: =G16*H16 -> 26000
A17: 8 | C17: PROD. MEDICO/ FARMACEUTICOS/LAB | D17: 2.9.5 | E17: AGUJA ESPINAL 25G 31/2 PUNTA LAPIZ | F17: unidad | G17: 50 | H17: 520 | I17: =G17*H17 -> 26000
A18: 9 | C18: PROD. MEDICO/ FARMACEUTICOS/LAB | D18: 2.9.5 | E18: Aguja ESPINAL 26 G 31/2 | F18: unidad | G18: 50 | H18: 520 | I18: =G18*H18 -> 26000
A19: 10 | C19: PROD. MEDICO/ FARMACEUTICOS/LAB | D19: 2.9.5 | E19: Aguja ESPINAL 26 G 31/2 PUNTA LAPIZ | F19: unidad | G19: 50 | H19: 520 | I19: =G19*H19 -> 26000
A20: 11 | C20: PROD. MEDICO/ FARMACEUTICOS/LAB | D20: 2.9.5 | E20: Aguja ESPINAL 27 G 3 1/2 | F20: unidad | G20: 50 | H20: 520 | I20: =G20*H20 -> 26000
A21: 12 | C21: PROD. MEDICO/ FARMACEUTICOS/LAB | D21: 2.9.5 | E21: AGUJA ESPINAL 27G 3 1/2 PUNTA LAPIZ | F21: unidad | G21: 200 | H21: 520 | I21: =G21*H21 -> 104000
... A186: 177 | C186: PROD. MEDICO/ FARMACEUTICOS/LAB | D186: 2.9.5 | E186: VENDA COBAN 10CM | F186: unidad | G186: 50 | H186: 230 | I186: =G186*H186 -> 11500
B188: Plazos y lugares de entrega
B189: Lugar de Entrega: SERVICIO DE FARMACIA -HOSPITAL INT. DE NIÑOS – AV. VIRGEN DEL VALLE N° 1050-CATAMARCA DE 8:00 A 12:00HS., DEBIENDO CORRER LOS GASTOS DE FLETES, ACARREO, CARGA, DESCARGA Y SEGURO A CARGO DEL ADJUDICATARIO.
B191: Plazo de entrega: Dentro de los 20 días corridos de notificada la Orden de Compra.
B192: Mantenimiento: 45 dias habiles
B194: Especificidades Item N° 77:
B195: Descripción técnica
B196: JUEGO DE TRANSDUCTOR SENCILLO T/DTX PLUS DT4812-BD MARCA EDWARDS
B198: Especificidades Item N° 106-107:
B199: Descripción técnica
B200: TIPO "ELEFIX", PASTA PARA EEG CONDUCTORA Y ADHESIVA DE ELECTRODOS.
B203: Especificidades Item N° 144:
B204: Descripción técnica
... B213: VENDA COBAN 10CM TIPO 3M

Sheet  NotaPedido
A1: NOTA DE PEDIDO | J1: N° | K1: 110/2021
A3: JURISDICCIÓN: | D3: ='Necesidades Trimestrales'!C4 -> 040 - Ministerio de Salud
A4: SAF: | D4: ='Necesidades Trimestrales'!C5 -> 024 - Hospital Interzonal de Niños
A5: UNIDAD EJECUTORA: | D5: 024 - Hospital Interzonal de Niños
A6: DEPENDENCIA SOLICITANTE: | D6: Servicio de Farmacia
A7: PERIODO UTILIZACIÓN: | D7: ='Necesidades Trimestrales'!C7 & "° Trimestre - Año " & 'Necesidades Trimestrales'!C6 -> 2° Trimestre - Año 2021
A8: OBJETO: | D8: Descartables Desiertos
A10: Ítem | B10: Codigo Item | C10: DESCRIPCIÓN | H10: Adjunta Detalle Técnico | I10: Unidad Medida | J10: Precio Unitario Estimado | K10: Cantidad Solicitada
A12: 1 | C12: ='Necesidades Trimestrales'!E10 -> AEROCAMARA C/ MASCARA PEDIATRICA | H12: NO | I12: ='Necesidades Trimestrales'!F10 -> unidad | J12: ='Necesidades Trimestrales'!H10 -> 230 | K12: ='Necesidades Trimestrales'!G10 -> 2000
A13: 2 | C13: ='Necesidades Trimestrales'!E11 -> AGUJA ESPINAL 18 G X 3-1/2 | H13: NO | I13: ='Necesidades Trimestrales'!F11 -> unidad | J13: ='Necesidades Trimestrales'!H11 -> 520 | K13: ='Necesidades Trimestrales'!G11 -> 50
A14: 3 | C14: ='Necesidades Trimestrales'!E12 -> AGUJA ESPINAL 19 G 3-1/2 | H14: NO | I14: ='Necesidades Trimestrales'!F12 -> unidad | J14: ='Necesidades Trimestrales'!H12 -> 520 | K14: ='Necesidades Trimestrales'!G12 -> 50
A15: 4 | C15: ='Necesidades Trimestrales'!E13 -> AGUJA ESPINA Nº 20 | H15: NO | I15: ='Necesidades Trimestrales'!F13 -> unidad | J15: ='Necesidades Trimestrales'!H13 -> 230 | K15: ='Necesidades Trimestrales'!G13 -> 50
A16: 5 | C16: ='Necesidades Trimestrales'!E14 -> AGUJA ESPINAL 22 G X 1 | H16: NO | I16: ='Necesidades Trimestrales'!F14 -> unidad | J16: ='Necesidades Trimestrales'!H14 -> 520 | K16: ='Necesidades Trimestrales'!G14 -> 50
A17: 6 | C17: ='Necesidades Trimestrales'!E15 -> Aguja ESPINAL 23 G 3 1/2 | H17: NO | I17: ='Necesidades Trimestrales'!F15 -> unidad | J17: ='Necesidades Trimestrales'!H15 -> 520 | K17: ='Necesidades Trimestrales'!G15 -> 50
A18: 7 | C18: ='Necesidades Trimestrales'!E16 -> Aguja ESPINAL 25 G 3 1/2 | H18: NO | I18: ='Necesidades Trimestrales'!F16 -> unidad | J18: ='Necesidades Trimestrales'!H16 -> 520 | K18: ='Necesidades Trimestrales'!G16 -> 50
A19: 8 | C19: ='Necesidades Trimestrales'!E17 -> AGUJA ESPINAL 25G 31/2 PUNTA LAPIZ | H19: NO | I19: ='Necesidades Trimestrales'!F17 -> unidad | J19: ='Necesidades Trimestrales'!H17 -> 520 | K19: ='Necesidades Trimestrales'!G17 -> 50
A20: 9 | C20: ='Necesidades Trimestrales'!E18 -> Aguja ESPINAL 26 G 31/2 | H20: NO | I20: ='Necesidades Trimestrales'!F18 -> unidad | J20: ='Necesidades Trimestrales'!H18 -> 520 | K20: ='Necesidades Trimestrales'!G18 -> 50
A21: 10 | C21: ='Necesidades Trimestrales'!E19 -> Aguja ESPINAL 26 G 31/2 PUNTA LAPIZ | H21: NO | I21: ='Necesidades Trimestrales'!F19 -> unidad | J21: ='Necesidades Trimestrales'!H19 -> 520 | K21: ='Necesidades Trimestrales'!G19 -> 50
A22: 11 | C22: ='Necesidades Trimestrales'!E20 -> Aguja ESPINAL 27 G 3 1/2 | H22: NO | I22: ='Necesidades Trimestrales'!F20 -> unidad | J22: ='Necesidades Trimestrales'!H20 -> 520 | K22: ='Necesidades Trimestrales'!G20 -> 50
A23: 12 | C23: ='Necesidades Trimestrales'!E21 -> AGUJA ESPINAL 27G 3 1/2 PUNTA LAPIZ | H23: NO | I23: ='Necesidades Trimestrales'!F21 -> unidad | J23: ='Necesidades Trimestrales'!H21 -> 520 | K23: ='Necesidades Trimestrales'!G21 -> 200
... A188: 177 | C188: ='Necesidades Trimestrales'!E186 -> VENDA COBAN 10CM | H188: NO | I188: ='Necesidades Trimestrales'!F186 -> unidad | J188: ='Necesidades Trimestrales'!H186 -> 230 | K188: ='Necesidades Trimestrales'!G186 -> 50
A189: Costo total estimado: Nueve Millones doscientos catorce Mil Doscientos setenta y siete Con 00/100. | J189: =SUMPRODUCT(J12:J188,K12:K188) -> 9214277

Sheet Autor Gastar
A1: EJERCICIO: | D1: ='Necesidades Trimestrales'!C6 -> 2021 | P1: AUTORIZACION PARA GASTAR
A4: JURISDICCIÓN: | G4: =' NotaPedido'!D3 -> 040 - Ministerio de Salud
A5: SAF: | G5: =' NotaPedido'!D4 -> 024 - Hospital Interzonal de Niños
A6: UNIDAD EJECUTORA: | G6: =' NotaPedido'!D5 -> 024 - Hospital Interzonal de Niños
A7: DEPENDENCIA SOLICITANTE: | G7: Servicio de Farmacia
A8: AUTORIZACIÓN:
A9: Señor Jefe de Servicio Administrativo Financiero:
A10: ="Autorizo la realización de los trámites correspondientes, a fin de proveer a este Organismo los bienes y/o servicios que se detallan en Nota de Pedido N° " & ' NotaPedido'!K1&", afectando la erogación resultante a los créditos presupuestarios aprobados a favor de esta Unidad Ejecutora, conforme al siguiente detalle:" -> Autorizo la realización de los trámites correspondientes, a fin de proveer a este Organismo los bienes y/o servicios que se detallan en Nota de Pedido N° 110/2021, afectando la erogación resultante a los créditos presupuestarios aprobados a favor de esta Unidad Ejecutora, conforme al siguiente detalle:
A12: IMPUTACIÓN PRESUPUESTARIA
A13: CÓDIGO | O13: DENOMINACIÓN DE LA PARTIDA PRESUPUESTARIA | Q13: IMPORTE
A14: PR | B14: SB | C14: PY | D14: AC | E14: OB | F14: UG | G14: FIN | H14: FUN | I14: I | J14: P | K14: P | L14: SubP | M14: M | N14: FF
A15: 36 | D15: 1 | F15: 4901 | G15: 3 | H15: 310 | I15: 2 | J15: 5 | K15: 1 | M15: 1 | N15: 1.1 | O15: COMPUESTOS QUIMICOS | Q15: 330987
A16: 36 | D16: 1 | F16: 4901 | G16: 3 | H16: 310 | I16: 2 | J16: 9 | K16: 5 | M16: 1 | N16: 1.1 | O16: UTILES MENORES MEDICO, QUIRURGICO Y DE LABORATORIO | Q16: 8377890
I17: 2 | J17: 2 | K17: 1 | M17: 1 | N17: 1.1 | Q17: 190000
I18: 2 | J18: 3 | K18: 4 | Q18: 151800
I19: 2 | J19: 5 | K19: 2 | Q19: 89500
I20: 2 | J20: 5 | K20: 8 | Q20: 74100
A22: TOTAL DE PESOS: Nueve Millones doscientos catorce Mil Doscientos setenta y siete CON 00/100. | Q22: =SUM(Q15:Q21) -> 9214277
A24: JUSTIFICACIÓN:
A25: Para la adquisición de DESCARTABLES DESIERTOS destinados al Servicio de Farmacia del Hospital Interzonal de Niños Eva Peron, para el normal funcionamiento del organismo.
