Workbook

Sheet Necesidades Trimestrales
B2: Pedido de Necesidades Trimestrales
A4: JURISDICCION: | C4: 040 - Ministerio de Salud
A5: SAF N°: | C5: 024 - Direccion de Administracion del Hospital Interzonal de Niños
A6: EJERCICIO: | C6: 2022
A7: TRIMESTRE: | C7: 3
A9: ID | B9: CODIGO ITEM | C9: RUBRO DE COMPRA | D9: I.P.P. | E9: DESCRIPCION | F9: UNIDAD DE MEDIDA | G9: CANTIDAD | H9: PRECIO UNITARIO ESTIMADO | I9: IMPORTE TOTAL ESTIMADO
A10: 1 | B10: 2.1.1-4227.28 | C10: PROD. MEDICO/FARMACEUTICOS/LAB | D10: 252 | E10: SUPLEMENTOS DIETARIOS; TIPO: ASOCIACION, DROGA GENERICA: CASEINATO DE SODIO, PRESENTACION: ENVASE X 400 GR | F10: UNIDAD | G10: 100 | H10: 3190 | I10: =H10*G10 -> 319000
A11: 2 | B11: 2.1.1-4227.42 | C11: PROD. MEDICO/FARMACEUTICOS/LAB | D11: 252 | E11: SUPLEMENTOS DIETARIOS; TIPO: ASOCIACIÓN; DROGA GENÉRICA: FÓRMULA LÁCTEA DE INICIO; PRESENTACIÓN: ENVASE X GRS SEGÚN PLIEGO | F11: UNIDAD | G11: 100 | H11: 1400 | I11: =H11*G11 -> 140000
A12: 3 | B12: 2.1.1-4227.43 | C12: PROD. MEDICO/FARMACEUTICOS/LAB | D12: 252 | E12: SUPLEMENTOS DIETARIOS; TIPO: ASOCIACIÓN; DROGA GENÉRICA: FÓRMULA LÁCTEA DE CONTINUACIÓN; PRESENTACIÓN: ENVASE X GRS SEGÚN PLIEGO | F12: UNIDAD | G12: 100 | H12: 1400 | I12: =H12*G12 -> 140000
A13: 4 | B13: 2.1.1-4227.63 | C13: PROD. MEDICO/FARMACEUTICOS/LAB | D13: 252 | E13: SUPLEMENTOS DIETARIOS; TIPO: ASOCIACIÓN; DROGA GENÉRICA: SUPLEMENTO CALÓRICO PEDIÁTRICO; PRESENTACIÓN: ENVASE X GRS SEGÚN PLIEGO | F13: UNIDAD | G13: 50 | H13: 1000 | I13: =H13*G13 -> 50000
A14: 5 | B14: 2.1.1-4227.47 | C14: PROD. MEDICO/FARMACEUTICOS/LAB | D14: 252 | E14: SUPLEMENTOS DIETARIOS; TIPO: ASOCIACION, DROGA GENERICA: PROTEINAS HIDROLIZADAS, PRESENTACION: ENVASE X 400 GR | F14: UNIDAD | G14: 30 | H14: 2680 | I14: =H14*G14 -> 80400
A15: 6 | B15: 2.1.1-4227.46 | C15: PROD. MEDICO/FARMACEUTICOS/LAB | D15: 252 | E15: SUPLEMENTOS DIETARIOS; TIPO: MONODROGA, DROGA GENERICA: MALTODEXTRINA, PRESENTACION: ENVASE X 400 GR | F15: UNIDAD | G15: 50 | H15: 1300 | I15: =H15*G15 -> 65000
A16: 7 | B16: 2.1.1-4227.44 | C16: PROD. MEDICO/FARMACEUTICOS/LAB | D16: 252 | E16: SUPLEMENTOS DIETARIOS; TIPO: ASOCIACION, DROGA GENERICA: FORMULA LACTEA SIN LACTOSA, PRESENTACION: ENVASE X 400 GR | F16: UNIDAD | G16: 100 | H16: 1650 | I16: =H16*G16 -> 165000
B18: Especificidades Item N° 1:
B19: Descripción técnica: BASE CASEINATO DE SODIO HIDROLIZADO , LIBRE DE LACTOSA Y SACAROSA , SIN TACC , TIPO KASS1000
B20: Especificidades Item N° 2:
B21: Descripción técnica: PRESENTACION: ENVASE X 800 GRS.SIN TACC
B22: Especificidades Item N° 3:
B23: Descripción técnica: PRESENTACION: ENVASE X 800 GRS.
B24: Especificidades Item N° 4:
B25: Descripción técnica: SUPLEMENTO CALORICO EN POLVO PARA PEDIATRIA CONTIENE OMEGA 3 Y 6, ADEMAS, DHA Y AA QUE APOYAN EL DESARROLLO CEREBRAL DE 2 A 10 AÑOS, LIBRE DE GLUTEN ,PRESENTACION: LATA X 400 GR ,TIPO PEDIASURE, SABOR A VAINILLA.
B26: Especificidades Item N° 5:
B27: Descripción técnica: FORMULA LACTEA NUTRICIONALMENTE ADECUADA PARA LACTANTES Y NINOS CON ALERGIA A LA PROTEINA DE LECHE DE VACA , CONTIENE ACIDOS GRASOS POLIINSATURADOS DE CADENA LARGA. TIPO NUTRILON PEPTI JUNIOR HE X 400 grs
B28: Especificidades Item N° 6:
B29: Descripción técnica: TIPO POLIMEROSA.
... B35: Forma de Pago: se realizara pago parciales dentro de los treinta (30) dias habiles, debiendo presentar la factura correspondiente a cada entrega prevista.

Sheet  NotaPedido
A1: NOTA DE PEDIDO | J1: N° | K1: 064/2022
A3: JURISDICCIÓN: | D3: ='Necesidades Trimestrales'!C4 -> 040 - Ministerio de Salud
A4: SAF: | D4: ='Necesidades Trimestrales'!C5 -> 024 - Direccion de Administracion del Hospital Interzonal de Niños
A5: UNIDAD EJECUTORA: | D5: 024 - Direccion de Administracion del Hospital Interzonal de Niños
A6: DEPENDENCIA SOLICITANTE: | D6: Servicio de Alimentacion y Dietoterapia
A7: PERIODO UTILIZACIÓN: | D7: ='Necesidades Trimestrales'!C7 & "° Trimestre - Año " & 'Necesidades Trimestrales'!C6 -> 3° Trimestre - Año 2022
A8: OBJETO: | D8: Leches Nutroterapeuticas
A10: Ítem | B10: Codigo Item | C10: DESCRIPCIÓN | H10: Adjunta Detalle Técnico | I10: Unidad Medida | J10: Precio Unitario Estimado | K10: Cantidad Solicitada
A12: 1 | B12: ='Necesidades Trimestrales'!B10 -> 2.1.1-4227.28 | C12: ='Necesidades Trimestrales'!E10 -> SUPLEMENTOS DIETARIOS; TIPO: ASOCIACION, DROGA GENERICA: CASEINATO DE SODIO, PRESENTACION: ENVASE X 400 GR | H12: SI | I12: ='Necesidades Trimestrales'!F10 -> UNIDAD | J12: ='Necesidades Trimestrales'!H10 -> 3190 | K12: ='Necesidades Trimestrales'!G10 -> 100
A13: 2 | B13: ='Necesidades Trimestrales'!B11 -> 2.1.1-4227.42 | C13: ='Necesidades Trimestrales'!E11 -> SUPLEMENTOS DIETARIOS; TIPO: ASOCIACIÓN; DROGA GENÉRICA: FÓRMULA LÁCTEA DE INICIO; PRESENTACIÓN: ENVASE X GRS SEGÚN PLIEGO | H13: SI | I13: ='Necesidades Trimestrales'!F12 -> UNIDAD | J13: ='Necesidades Trimestrales'!H11 -> 1400 | K13: ='Necesidades Trimestrales'!G11 -> 100
A14: 3 | B14: ='Necesidades Trimestrales'!B12 -> 2.1.1-4227.43 | C14: ='Necesidades Trimestrales'!E12 -> SUPLEMENTOS DIETARIOS; TIPO: ASOCIACIÓN; DROGA GENÉRICA: FÓRMULA LÁCTEA DE CONTINUACIÓN; PRESENTACIÓN: ENVASE X GRS SEGÚN PLIEGO | H14: SI | I14: ='Necesidades Trimestrales'!F11 -> UNIDAD | J14: ='Necesidades Trimestrales'!H12 -> 1400 | K14: ='Necesidades Trimestrales'!G12 -> 100
A15: 4 | B15: ='Necesidades Trimestrales'!B13 -> 2.1.1-4227.63 | C15: ='Necesidades Trimestrales'!E13 -> SUPLEMENTOS DIETARIOS; TIPO: ASOCIACIÓN; DROGA GENÉRICA: SUPLEMENTO CALÓRICO PEDIÁTRICO; PRESENTACIÓN: ENVASE X GRS SEGÚN PLIEGO | H15: SI | I15: ='Necesidades Trimestrales'!F15 -> UNIDAD | J15: ='Necesidades Trimestrales'!H13 -> 1000 | K15: ='Necesidades Trimestrales'!G13 -> 50
A16: 5 | B16: ='Necesidades Trimestrales'!B14 -> 2.1.1-4227.47 | C16: ='Necesidades Trimestrales'!E14 -> SUPLEMENTOS DIETARIOS; TIPO: ASOCIACION, DROGA GENERICA: PROTEINAS HIDROLIZADAS, PRESENTACION: ENVASE X 400 GR | H16: SI | I16: ='Necesidades Trimestrales'!F16 -> UNIDAD | J16: ='Necesidades Trimestrales'!H14 -> 2680 | K16: ='Necesidades Trimestrales'!G14 -> 30
A17: 6 | B17: ='Necesidades Trimestrales'!B15 -> 2.1.1-4227.46 | C17: ='Necesidades Trimestrales'!E15 -> SUPLEMENTOS DIETARIOS; TIPO: MONODROGA, DROGA GENERICA: MALTODEXTRINA, PRESENTACION: ENVASE X 400 GR | H17: SI | I17: ='Necesidades Trimestrales'!F14 -> UNIDAD | J17: ='Necesidades Trimestrales'!H15 -> 1300 | K17: ='Necesidades Trimestrales'!G15 -> 50
A18: 7 | B18: ='Necesidades Trimestrales'!B16 -> 2.1.1-4227.44 | C18: ='Necesidades Trimestrales'!E16 -> SUPLEMENTOS DIETARIOS; TIPO: ASOCIACION, DROGA GENERICA: FORMULA LACTEA SIN LACTOSA, PRESENTACION: ENVASE X 400 GR | H18: NO | I18: ='Necesidades Trimestrales'!F15 -> UNIDAD | J18: ='Necesidades Trimestrales'!H16 -> 1650 | K18: ='Necesidades Trimestrales'!G16 -> 100
A19: Costo total estimado: Novecientos Cincuenta y Nueve Mil Cuatrocientos con 00/100. | J19: =SUMPRODUCT(J12:J18,K12:K18) -> 959400

Sheet Autor Gastar
A1: EJERCICIO: | D1: ='Necesidades Trimestrales'!C6 -> 2022 | P1: AUTORIZACION PARA GASTAR
A4: JURISDICCIÓN: | G4: =' NotaPedido'!D3 -> 040 - Ministerio de Salud
A5: SAF: | G5: =' NotaPedido'!D4 -> 024 - Direccion de Administracion del Hospital Interzonal de Niños
A6: UNIDAD EJECUTORA: | G6: =' NotaPedido'!D5 -> 024 - Direccion de Administracion del Hospital Interzonal de Niños
A7: DEPENDENCIA SOLICITANTE: | G7: =' NotaPedido'!D6 -> Servicio de Alimentacion y Dietoterapia
A8: AUTORIZACIÓN:
A9: Señor Jefe de Servicio Administrativo Financiero:
A10: ="Autorizo la realización de los trámites correspondientes, a fin de proveer a este Organismo los bienes y/o servicios que se detallan en Nota de Pedido N° " & ' NotaPedido'!K1&", afectando la erogación resultante a los créditos presupuestarios aprobados a favor de esta Unidad Ejecutora, conforme al siguiente detalle:" -> Autorizo la realización de los trámites correspondientes, a fin de proveer a este Organismo los bienes y/o servicios que se detallan en Nota de Pedido N° 064/2022, afectando la erogación resultante a los créditos presupuestarios aprobados a favor de esta Unidad Ejecutora, conforme al siguiente detalle:
A12: IMPUTACIÓN PRESUPUESTARIA
A13: CÓDIGO | O13: DENOMINACIÓN DE LA PARTIDA PRESUPUESTARIA | Q13: IMPORTE
A14: PR | B14: SB | C14: PY | D14: AC | E14: OB | F14: UG | G14: FIN | H14: FUN | I14: I | J14: P | K14: P | L14: SubP | M14: M | N14: FF
A15: 36 | D15: 1 | F15: 4901 | G15: 3 | H15: 310 | I15: =LEFT('Necesidades Trimestrales'!D10,1) -> 2 | J15: 5 | K15: =RIGHT('Necesidades Trimestrales'!D10,1) -> 2 | M15: 1 | N15: 1.1 | O15: Productos Farmaceuticos y Medicinales | Q15: 959400
A23: TOTAL DE PESOS: NOVECIENTOS CINCUENTA Y NUEVE MIL CUATROCIENTOS CON 00/100. | Q23: =SUM(Q15:Q22) -> 959400
A25: JUSTIFICACIÓN:
A26: Para la adquisición de Leches Nutroterapeuticas destinados al servico de Alimentacion y Dietoterapia del Hospital Interzonal de Niños Eva Peron, para el normal funcionamiento del organismo.
