Workbook

Sheet Necesidades Trimestrales
B2: Pedido de Necesidades Trimestrales
A4: JURISDICCION: | C4: 040 - Ministerio de Salud
A5: SAF N°: | C5: 024 - Direccion de Administracion del Hospital Interzonal de Niños Eva Peron
A6: EJERCICIO: | C6: 2022
A7: TRIMESTRE: | C7: 2
A9: ID | B9: CODIGO ITEM | C9: RUBRO DE COMPRA | D9: I.P.P. | E9: DESCRIPCION | F9: UNIDAD DE MEDIDA | G9: CANTIDAD | H9: PRECIO UNITARIO ESTIMADO | I9: IMPORTE TOTAL ESTIMADO
A10: 1 | B10: 2.5.2-1875.133 | C10: PROD. MEDICO/FARMACEUTICOS/LAB | D10: 252 | E10: ANTIASMATICO BRONCODILATADOR; TIPO: MONODROGA, DROGA GENERICA: N-ACETIL CISTEINA 600 MGR, FORMA FARMACEUTICA: TABLETA EFERVESCENTE, PRESENTACION: UNIDAD | F10: TABLETAS | G10: 300 | H10: 113.3 | I10: =+G10*H10 -> 33990
A11: 2 | B11: 2.5.2-1821.189 | C11: PROD. MEDICO/FARMACEUTICOS/LAB | D11: 252 | E11: ANTIBIOTICOS P/PERSONAS; DROGA GENERICA: ACIDO FUSIDICO 20MG, FORMA FARMACEUTICA: CREMA, PRESENTACION: POMO X 15 GR, TIPO: MONODROGA | F11: ENVASE | G11: 10 | H11: 459 | I11: =+G11*H11 -> 4590
A12: 3 | B12: 2.9.5-427.33 | C12: PROD. MEDICO/FARMACEUTICOS/LAB | D12: 252 | E12: APOSITOS; TIPO: HIDROCOLOIDE, TAMAÑO: 15 X 17,5 Cm | F12: UNIDAD | G12: 100 | H12: 998 | I12: =+G12*H12 -> 99800
A13: 4 | B13: 2.9.5-427.39 | C13: PROD. MEDICO/FARMACEUTICOS/LAB | D13: 252 | E13: APOSITOS; TIPO: HIDROCOLOIDE, TAMAÑO: 10 X 10 Cm | F13: UNIDAD | G13: 100 | H13: 380 | I13: =+G13*H13 -> 38000
A14: 5 | B14: 2.5.2-1855.23 | C14: PROD. MEDICO/FARMACEUTICOS/LAB | D14: 252 | E14: CORTICOESTEROIDES; TIPO: MONODROGA, DROGA GENERICA: BETAMETASONA, FORMA FARMACEUTICA: CREMA, PRESENTACION: 15 GR | F14: ENVASE | G14: 10 | H14: 235 | I14: =+G14*H14 -> 2350
A15: 6 | B15: 2.5.2-1875.134 | C15: PROD. MEDICO/FARMACEUTICOS/LAB | D15: 252 | E15: ANTIASMATICO BRONCODILATADOR; TIPO: MONODROGA, DROGA GENERICA: BUDESONIDE 200 µGR, FORMA FARMACEUTICA: AEROSOL, PRESENTACION: 100 DOSIS | F15: UNIDAD | G15: 300 | H15: 659 | I15: =+G15*H15 -> 197700
A16: 7 | B16: 2.5.2-2476.50 | C16: PROD. MEDICO/FARMACEUTICOS/LAB | D16: 252 | E16: ANTIALERGICOS-ANTIHISTAMINICOS; TIPO: MONODROGA, DROGA GENERICA: BUDESONIDA 1 MG/ML, FORMA FARMACEUTICA: GOTAS, PRESENTACION: ENVASE X 20 mL | F16: ENVASE | G16: 300 | H16: 327 | I16: =+G16*H16 -> 98100
A17: 8 | B17: 2.5.2-1855.7 | C17: PROD. MEDICO/FARMACEUTICOS/LAB | D17: 252 | E17: CORTICOESTEROIDES; TIPO: MONODROGA, DROGA GENERICA: DEXAMETASONA, FORMA FARMACEUTICA: AMPOLLA, PRESENTACION: 8 mGr | F17: AMPOLLA | G17: 5000 | H17: 45 | I17: =+G17*H17 -> 225000
A18: 9 | B18: 2.5.2-2476.74 | C18: PROD. MEDICO/FARMACEUTICOS/LAB | D18: 252 | E18: ANTIALERGICOS-ANTIHISTAMINICOS; TIPO: MONODROGA, DROGA GENERICA: DIFENHIDRAMINA 250 MG, FORMA FARMACEUTICA: JARABE, PRESENTACION: FRASCO X 120 mL | F18: FRASCO | G18: 2000 | H18: 139 | I18: =+G18*H18 -> 278000
A19: 10 | B19: 2.5.2-2476.36 | C19: PROD. MEDICO/FARMACEUTICOS/LAB | D19: 252 | E19: ANTIALERGICOS-ANTIHISTAMINICOS; TIPO: MONODROGA, DROGA GENERICA: DIFENHIDRAMINA, FORMA FARMACEUTICA: COMPRIMIDO, PRESENTACION: 50 mGr | F19: COMPRIMIDO | G19: 400 | H19: 4.65 | I19: =+G19*H19 -> 1860
A20: 11 | B20: 2.5.2-2476.44 | C20: PROD. MEDICO/FARMACEUTICOS/LAB | D20: 252 | E20: ANTIALERGICOS-ANTIHISTAMINICOS; TIPO: MONODROGA, DROGA GENERICA: DIFENHIDRAMINA, FORMA FARMACEUTICA: AMPOLLA, PRESENTACION: 10 mGr | F20: AMPOLLA | G20: 5000 | H20: 55 | I20: =+G20*H20 -> 275000
A21: 12 | B21: 2.5.2-2200.11 | C21: PROD. MEDICO/FARMACEUTICOS/LAB | D21: 252 | E21: CORTICOIDES; DROGA GENERICA: HIDROCORTIZONA 1%, FORMA FARMACEUTICA: CREMA, PRESENTACION: ENVASE X 400 mGr, TIPO: MONODROGA | F21: ENVASE | G21: 20 | H21: 246.72 | I21: =+G21*H21 -> 4934.4
... A35: 26 | B35: 2.5.2-2481.3 | C35: PROD. MEDICO/FARMACEUTICOS/LAB | D35: 252 | E35: LAXANTES; TIPO: MONODROGA, DROGA GENERICA: VASELINA, FORMA FARMACEUTICA: SOLIDO, PRESENTACION: 1000 GR | F35: UNIDAD | G35: 20 | H35: 1260 | I35: =+G35*H35 -> 25200
B37: Especificidades Item N° 23:
B38: Descripción técnica: | C38: CON AEROCAMARA
B40: Plazos y lugares de entrega
B41: Lugar de Entrega: SERVICIO DE FARMACIA -HOSPITAL INT. DE NIÑOS – AV. VIRGEN DEL VALLE N° 1050-CATAMARCA DE 8:00 A 12:00HS., DEBIENDO CORRER LOS GASTOS DE FLETES, ACARREO, CARGA, DESCARGA Y SEGURO A CARGO DEL ADJUDICATARIO.
B43: Plazo de entrega: Dentro de los diez (10) días habiles de notificada la Orden de Compra.
B44: Mantenimiento de Oferta: Cuarenta y Cinco (45) dias habiles.
B45: Forma de Pago: Dentro de los Treinta (30) dias habiles.

Sheet  NotaPedido
A1: NOTA DE PEDIDO | J1: N° | K1: 057/2022
A3: JURISDICCIÓN: | D3: ='Necesidades Trimestrales'!C4 -> 040 - Ministerio de Salud
A4: SAF: | D4: ='Necesidades Trimestrales'!C5 -> 024 - Direccion de Administracion del Hospital Interzonal de Niños Eva Peron
A5: UNIDAD EJECUTORA: | D5: 024 - Direccion de Administracion del Hospital Interzonal de Niños Eva Peron
A6: DEPENDENCIA SOLICITANTE: | D6: Servicio de Farmacia
A7: PERIODO UTILIZACIÓN: | D7: Cuatrimestral
A8: OBJETO: | D8: TERAPIA DERMATOLOGICA/SISTEMA GENITOURINARIO Y HORMONAS SEXUALES /HORMONAS SISTEMICAS /CORTICOIDES SISTEMICOS/RESPIRATORIO/ANTIHISTAMINICOS
A10: Ítem | B10: Codigo Item | C10: DESCRIPCIÓN | H10: Adjunta Detalle Técnico | I10: Unidad Medida | J10: Precio Unitario Estimado | K10: Cantidad Solicitada
A12: 1 | C12: ='Necesidades Trimestrales'!E10 -> ANTIASMATICO BRONCODILATADOR; TIPO: MONODROGA, DROGA GENERICA: N-ACETIL CISTEINA 600 MGR, FORMA FARMACEUTICA: TABLETA EFERVESCENTE, PRESENTACION: UNIDAD | H12: NO | I12: ='Necesidades Trimestrales'!F10 -> TABLETAS | J12: ='Necesidades Trimestrales'!H10 -> 113.3 | K12: ='Necesidades Trimestrales'!G10 -> 300
A13: 2 | C13: ='Necesidades Trimestrales'!E11 -> ANTIBIOTICOS P/PERSONAS; DROGA GENERICA: ACIDO FUSIDICO 20MG, FORMA FARMACEUTICA: CREMA, PRESENTACION: POMO X 15 GR, TIPO: MONODROGA | H13: NO | I13: ='Necesidades Trimestrales'!F11 -> ENVASE | J13: ='Necesidades Trimestrales'!H11 -> 459 | K13: ='Necesidades Trimestrales'!G11 -> 10
A14: 3 | C14: ='Necesidades Trimestrales'!E12 -> APOSITOS; TIPO: HIDROCOLOIDE, TAMAÑO: 15 X 17,5 Cm | H14: NO | I14: ='Necesidades Trimestrales'!F12 -> UNIDAD | J14: ='Necesidades Trimestrales'!H12 -> 998 | K14: ='Necesidades Trimestrales'!G12 -> 100
A15: 4 | C15: ='Necesidades Trimestrales'!E13 -> APOSITOS; TIPO: HIDROCOLOIDE, TAMAÑO: 10 X 10 Cm | H15: NO | I15: ='Necesidades Trimestrales'!F13 -> UNIDAD | J15: ='Necesidades Trimestrales'!H13 -> 380 | K15: ='Necesidades Trimestrales'!G13 -> 100
A16: 5 | C16: ='Necesidades Trimestrales'!E14 -> CORTICOESTEROIDES; TIPO: MONODROGA, DROGA GENERICA: BETAMETASONA, FORMA FARMACEUTICA: CREMA, PRESENTACION: 15 GR | H16: NO | I16: ='Necesidades Trimestrales'!F14 -> ENVASE | J16: ='Necesidades Trimestrales'!H14 -> 235 | K16: ='Necesidades Trimestrales'!G14 -> 10
A17: 6 | C17: ='Necesidades Trimestrales'!E15 -> ANTIASMATICO BRONCODILATADOR; TIPO: MONODROGA, DROGA GENERICA: BUDESONIDE 200 µGR, FORMA FARMACEUTICA: AEROSOL, PRESENTACION: 100 DOSIS | H17: NO | I17: ='Necesidades Trimestrales'!F15 -> UNIDAD | J17: ='Necesidades Trimestrales'!H15 -> 659 | K17: ='Necesidades Trimestrales'!G15 -> 300
A18: 7 | C18: ='Necesidades Trimestrales'!E16 -> ANTIALERGICOS-ANTIHISTAMINICOS; TIPO: MONODROGA, DROGA GENERICA: BUDESONIDA 1 MG/ML, FORMA FARMACEUTICA: GOTAS, PRESENTACION: ENVASE X 20 mL | H18: NO | I18: ='Necesidades Trimestrales'!F16 -> ENVASE | J18: ='Necesidades Trimestrales'!H16 -> 327 | K18: ='Necesidades Trimestrales'!G16 -> 300
A19: 8 | C19: ='Necesidades Trimestrales'!E17 -> CORTICOESTEROIDES; TIPO: MONODROGA, DROGA GENERICA: DEXAMETASONA, FORMA FARMACEUTICA: AMPOLLA, PRESENTACION: 8 mGr | H19: NO | I19: ='Necesidades Trimestrales'!F17 -> AMPOLLA | J19: ='Necesidades Trimestrales'!H17 -> 45 | K19: ='Necesidades Trimestrales'!G17 -> 5000
A20: 9 | C20: ='Necesidades Trimestrales'!E18 -> ANTIALERGICOS-ANTIHISTAMINICOS; TIPO: MONODROGA, DROGA GENERICA: DIFENHIDRAMINA 250 MG, FORMA FARMACEUTICA: JARABE, PRESENTACION: FRASCO X 120 mL | H20: NO | I20: ='Necesidades Trimestrales'!F18 -> FRASCO | J20: ='Necesidades Trimestrales'!H18 -> 139 | K20: ='Necesidades Trimestrales'!G18 -> 2000
A21: 10 | C21: ='Necesidades Trimestrales'!E19 -> ANTIALERGICOS-ANTIHISTAMINICOS; TIPO: MONODROGA, DROGA GENERICA: DIFENHIDRAMINA, FORMA FARMACEUTICA: COMPRIMIDO, PRESENTACION: 50 mGr | H21: NO | I21: ='Necesidades Trimestrales'!F19 -> COMPRIMIDO | J21: ='Necesidades Trimestrales'!H19 -> 4.65 | K21: ='Necesidades Trimestrales'!G19 -> 400
A22: 11 | C22: ='Necesidades Trimestrales'!E20 -> ANTIALERGICOS-ANTIHISTAMINICOS; TIPO: MONODROGA, DROGA GENERICA: DIFENHIDRAMINA, FORMA FARMACEUTICA: AMPOLLA, PRESENTACION: 10 mGr | H22: NO | I22: ='Necesidades Trimestrales'!F20 -> AMPOLLA | J22: ='Necesidades Trimestrales'!H20 -> 55 | K22: ='Necesidades Trimestrales'!G20 -> 5000
A23: 12 | C23: ='Necesidades Trimestrales'!E21 -> CORTICOIDES; DROGA GENERICA: HIDROCORTIZONA 1%, FORMA FARMACEUTICA: CREMA, PRESENTACION: ENVASE X 400 mGr, TIPO: MONODROGA | H23: NO | I23: ='Necesidades Trimestrales'!F21 -> ENVASE | J23: ='Necesidades Trimestrales'!H21 -> 246.72 | K23: ='Necesidades Trimestrales'!G21 -> 20
... A37: 26 | C37: ='Necesidades Trimestrales'!E35 -> LAXANTES; TIPO: MONODROGA, DROGA GENERICA: VASELINA, FORMA FARMACEUTICA: SOLIDO, PRESENTACION: 1000 GR | H37: NO | I37: ='Necesidades Trimestrales'!F35 -> UNIDAD | J37: ='Necesidades Trimestrales'!H35 -> 1260 | K37: ='Necesidades Trimestrales'!G35 -> 20
A38: Costo total estimado Pesos: Tres Millones Cuatrocientos Setenta y Siete Mil Trescientos Ochenta y Nueve Con 40/100. | J38: =SUMPRODUCT(J12:J37,K12:K37) -> 3477389.4

Sheet Autor Gastar
A1: EJERCICIO: | D1: ='Necesidades Trimestrales'!C6 -> 2022 | P1: AUTORIZACION PARA GASTAR
A4: JURISDICCIÓN: | G4: =' NotaPedido'!D3 -> 040 - Ministerio de Salud
A5: SAF: | G5: =' NotaPedido'!D4 -> 024 - Direccion de Administracion del Hospital Interzonal de Niños Eva Peron
A6: UNIDAD EJECUTORA: | G6: =' NotaPedido'!D5 -> 024 - Direccion de Administracion del Hospital Interzonal de Niños Eva Peron
A7: DEPENDENCIA SOLICITANTE: | G7: Servicio de Farmacia
A8: AUTORIZACIÓN:
A9: Señor Jefe de Servicio Administrativo Financiero:
A10: ="Autorizo la realización de los trámites correspondientes, a fin de proveer a este Organismo los bienes que se detallan en Nota de Pedido N° " & ' NotaPedido'!K1&", afectando la erogación resultante a los créditos presupuestarios aprobados a favor de esta Unidad Ejecutora, conforme al siguiente detalle:" -> Autorizo la realización de los trámites correspondientes, a fin de proveer a este Organismo los bienes que se detallan en Nota de Pedido N° 057/2022, afectando la erogación resultante a los créditos presupuestarios aprobados a favor de esta Unidad Ejecutora, conforme al siguiente detalle:
A12: IMPUTACIÓN PRESUPUESTARIA
A13: CÓDIGO | O13: DENOMINACIÓN DE LA PARTIDA PRESUPUESTARIA | Q13: IMPORTE
A14: PR | B14: SB | C14: PY | D14: AC | E14: OB | F14: UG | G14: FIN | H14: FUN | I14: I | J14: P | K14: P | L14: SubP | M14: M | N14: FF
A15: 36 | D15: 1 | F15: 4901 | G15: 3 | H15: 310 | I15: 2 | J15: 5 | K15: 2 | M15: 1 | N15: 1.1 | O15: PRODUCTOS FARMACEUTICOS Y MEDICINALES | Q15: 3477389.4
A21: TOTAL DE PESOS: TRES MILLONES CUATROCIENTOS SETENTA Y SIETE MIL TRESCIENTOS OCHENTA Y NUEVE CON 40/100. | Q21: =SUM(Q15:Q20) -> 3477389.4
A23: JUSTIFICACIÓN:
A24: Para la adquisición de Insumos relacionados a TERAPIA DERMATOLOGICA/ SISTEMA GENITOURINARIO Y HORMONAS SEXUALES / HORMONAS SISTEMICAS / CORTICOIDES SISTEMICOS/ RESPIRATORIO/ ANTIHISTAMINICOS destinados al Servicio de Farmacia del Hospital Interzonal de Niños Eva Peron, para el normal funcionamiento del organismo.
