Workbook

Sheet Necesidades Trimestrales
B2: Pedido de Necesidades Trimestrales
A4: JURISDICCION: | C4: 040 - Ministerio de Salud
A5: SAF N°: | C5: 024 - Hospital Interzonal de Niños
A6: EJERCICIO: | C6: 2020
A7: TRIMESTRE: | C7: 4
A9: ID | B9: CODIGO ITEM | C9: RUBRO DE COMPRA | D9: I.P.P. | E9: DESCRIPCION | F9: UNIDAD DE MEDIDA | G9: CANTIDAD | H9: PRECIO UNITARIO ESTIMADO | I9: IMPORTE TOTAL ESTIMADO
A10: 1 | B10: 2.1.1-6546.154 | C10: ALIMENTOS | D10: 2.1.1 | E10: VERDURAS Y HORTALIZAS; ESTADO: NATURAL, PESO: SIN VALOR, VARIEDAD: AJO, PRESENTACION: UNIDAD | F10: UNIDAD | G10: 400 | H10: 42 | I10: =G10*H10 -> 16800
A11: 2 | B11: 2.1.1-6546.330 | C11: ALIMENTOS | D11: 2.1.1 | E11: VERDURAS Y HORTALIZAS; VARIEDAD: ZAPALLO ANCO, ESTADO: NATURAL, PRESENTACION: UNIDAD, PESO: 1 Kg | F11: KG. | G11: 1000 | H11: 35 | I11: =G11*H11 -> 35000
A12: 3 | B12: 2.1.1-6539.171 | C12: ALIMENTOS | D12: 2.1.1 | E12: FRUTAS; VARIEDAD: BANANA, ESTADO: NATURAL, PRESENTACION: ENVASE X 15 Kg, ELEM. TRANSPORTE: CAJON, MATERIAL ELEM. TRANSPORTE: CARTON | F12: CAJON | G12: 20 | H12: 1350 | I12: =G12*H12 -> 27000
A13: 4 | B13: 2.1.1-6546.207 | C13: ALIMENTOS | D13: 2.1.1 | E13: VERDURAS Y HORTALIZAS; VARIEDAD: BATATA, ESTADO: NATURAL, PRESENTACION: BOLSA, PESO: 10 Kg | F13: BOLSA | G13: 10 | H13: 500 | I13: =G13*H13 -> 5000
A14: 5 | B14: 2.1.1-6546.177 | C14: ALIMENTOS | D14: 2.1.1 | E14: VERDURAS Y HORTALIZAS; VARIEDAD: BERENJENA, ESTADO: NATURAL, PRESENTACION: GRANEL, PESO: SIN VALOR | F14: KG. | G14: 100 | H14: 95 | I14: =G14*H14 -> 9500
A15: 6 | B15: 2.1.1-6546.236 | C15: ALIMENTOS | D15: 2.1.1 | E15: VERDURAS Y HORTALIZAS; VARIEDAD: CEBOLLA, ESTADO: NATURAL, PRESENTACION: BOLSA, PESO: 20 Kg | F15: BOLSA | G15: 100 | H15: 850 | I15: =G15*H15 -> 85000
A16: 7 | B16: 2.1.1-6546.377 | C16: ALIMENTOS | D16: 2.1.1 | E16: VERDURAS Y HORTALIZAS; VARIEDAD: CEBOLLA DE VERDEO, ESTADO: NATURAL, PRESENTACION: CAJON, PESO: 10 Kg, ELEM. TRANSPORTE: CAJON, MATERIAL ELEM. TRANSPORTE: CARTON, LIBRE DE GLUTEN: NO | F16: CAJON | G16: 1 | H16: 1000 | I16: =G16*H16 -> 1000
A17: 8 | B17: 2.1.1-6546.169 | C17: ALIMENTOS | D17: 2.1.1 | E17: VERDURAS Y HORTALIZAS; VARIEDAD: ESPINACA, PRESENTACION: ATADO, ESTADO: NATURAL, PESO: SIN VALOR | F17: UNIDAD | G17: 50 | H17: 31 | I17: =G17*H17 -> 1550
A18: 9 | B18: 2.1.1-6546.374 | C18: ALIMENTOS | D18: 2.1.1 | E18: VERDURAS Y HORTALIZAS; VARIEDAD: LECHUGA ARREPOLLADA, ESTADO: NATURAL, PRESENTACION: A GRANEL, PESO: 300 GR CADA PLANTA, ELEM. TRANSPORTE: SIN, MATERIAL ELEM. TRANSPORTE: SIN, LIBRE DE GLUTEN: SI | F18: UNIDAD | G18: 80 | H18: 42 | I18: =G18*H18 -> 3360
A19: 10 | B19: 2.1.1-6539.173 | C19: ALIMENTOS | D19: 2.1.1 | E19: FRUTAS; VARIEDAD: LIMON, ESTADO: NATURAL, PRESENTACION: ENVASE X 15 Kg, ELEM. TRANSPORTE: CAJON, MATERIAL ELEM. TRANSPORTE: CARTON | F19: CAJON | G19: 5 | H19: 320 | I19: =G19*H19 -> 1600
A20: 11 | B20: 2.1.1-6539.170 | C20: ALIMENTOS | D20: 2.1.1 | E20: FRUTAS; VARIEDAD: MANZANA RED DELICIOSA, ESTADO: NATURAL, PRESENTACION: ENVASE X 15 Kg, ELEM. TRANSPORTE: CAJON, MATERIAL ELEM. TRANSPORTE: CARTON | F20: CAJON | G20: 40 | H20: 1410 | I20: =G20*H20 -> 56400
A21: 12 | B21: 2.1.1-6539.7 | C21: ALIMENTOS | D21: 2.1.1 | E21: FRUTAS; ESTADO: NATURAL, VARIEDAD: NARANJA PARA JUGO, PRESENTACION: A GRANEL, PESO: SIN VALOR | F21: KG. | G21: 400 | H21: 30 | I21: =G21*H21 -> 12000
... A32: 23 | B32: 2.1.1-6546.188 | C32: ALIMENTOS | D32: 2.1.1 | E32: VERDURAS Y HORTALIZAS; ESTADO: NATURAL, PRESENTACION: GRANEL, PESO: SIN VALOR, VARIEDAD: ZAPALLO CRIOLLO | F32: KG. | G32: 150 | H32: 31 | I32: =G32*H32 -> 4650
B34: Plazos y lugares de entrega
B35: Descripción técnica:
C36: ITEM 47: MAPLE POR 30 UNIDADES
C37: ITEM 5: PESO: 1 KG
C38: ITEM 8: PESO: UNIDADES DE PLANTAS (ATADO) DE 300 GRS. APROX.
C39: ITEM 9: PESO: UNIDADES DE PLANTAS (ATADO) DE 300 GRS. APROX.
C40: ITEM 12: PESO: 1KG
C41: ITEM 14: PESO: 1KG
C42: ITEM 16: PESO: UNIDADES DE PLANTA (ATADO) DE 150 GRS. APROX.
C43: ITEM 17: PESO: 1KG
C44: ITEM 23: PESO: 1KG
B45: Lugar de Entrega: SERVICIO DE NUTRICION Y DIETOTERAPIA -HOSPITAL INT. DE NIÑOS EVA PERON – AV. VIRGEN DEL VALLE N° 1050-CATAMARCA DE 8:00 A 12:00HS., DEBIENDO CORRER LOS GASTOS DE FLETES, ACARREO, CARGA, DESCARGA Y SEGURO A CARGO DEL ADJUDICATARIO.
B47: Plazo de mantenimiento de Oferta: 30 Días
B48: Plazo de entrega: Dentro de los 10 días de notificada la Orden de Compra
B50: Condicion de Calidad: El producto ofertado deberá ser provisto en su envase o unidad comercial original, cerrados en fábrica y embalados en cajas que prevean humedad, golpes u otro deterioro que pueda dañar al producto ofertado de acuerdo a lo establecido en ANEXO I - ESPECIFICACIONESTÉCNICAS

Sheet  NotaPedido
A1: NOTA DE PEDIDO | J1: N° | K1: 546/2020
A3: JURISDICCIÓN: | D3: ='Necesidades Trimestrales'!C4 -> 040 - Ministerio de Salud
A4: SAF: | D4: ='Necesidades Trimestrales'!C5 -> 024 - Hospital Interzonal de Niños
A5: UNIDAD EJECUTORA: | D5: 024 - Hospital Interzonal de Niños
A6: DEPENDENCIA SOLICITANTE: | D6: Servicio de Alimentacion y Dietoterapia
A7: PERIODO UTILIZACIÓN: | D7: ='Necesidades Trimestrales'!C7 & "° Trimestre - Año " & 'Necesidades Trimestrales'!C6 -> 4° Trimestre - Año 2020
A8: OBJETO: | D8: Adquisición de Alimentos
A10: Ítem | B10: Codigo Item | C10: DESCRIPCIÓN | H10: Adjunta Detalle Técnico | I10: Unidad Medida | J10: Precio Unitario Estimado | K10: Cantidad Solicitada
A12: 1 | B12: ='Necesidades Trimestrales'!B10 -> 2.1.1-6546.154 | C12: ='Necesidades Trimestrales'!E10 -> VERDURAS Y HORTALIZAS; ESTADO: NATURAL, PESO: SIN VALOR, VARIEDAD: AJO, PRESENTACION: UNIDAD | H12: NO | I12: =+'Necesidades Trimestrales'!F10 -> UNIDAD | J12: =+'Necesidades Trimestrales'!H10 -> 42 | K12: =+'Necesidades Trimestrales'!G10 -> 400
A13: 2 | B13: ='Necesidades Trimestrales'!B11 -> 2.1.1-6546.330 | C13: ='Necesidades Trimestrales'!E11 -> VERDURAS Y HORTALIZAS; VARIEDAD: ZAPALLO ANCO, ESTADO: NATURAL, PRESENTACION: UNIDAD, PESO: 1 Kg | H13: NO | I13: =+'Necesidades Trimestrales'!F11 -> KG. | J13: =+'Necesidades Trimestrales'!H11 -> 35 | K13: =+'Necesidades Trimestrales'!G11 -> 1000
A14: 3 | B14: ='Necesidades Trimestrales'!B12 -> 2.1.1-6539.171 | C14: ='Necesidades Trimestrales'!E12 -> FRUTAS; VARIEDAD: BANANA, ESTADO: NATURAL, PRESENTACION: ENVASE X 15 Kg, ELEM. TRANSPORTE: CAJON, MATERIAL ELEM. TRANSPORTE: CARTON | H14: NO | I14: =+'Necesidades Trimestrales'!F12 -> CAJON | J14: =+'Necesidades Trimestrales'!H12 -> 1350 | K14: =+'Necesidades Trimestrales'!G12 -> 20
A15: 4 | B15: ='Necesidades Trimestrales'!B13 -> 2.1.1-6546.207 | C15: ='Necesidades Trimestrales'!E13 -> VERDURAS Y HORTALIZAS; VARIEDAD: BATATA, ESTADO: NATURAL, PRESENTACION: BOLSA, PESO: 10 Kg | H15: NO | I15: =+'Necesidades Trimestrales'!F13 -> BOLSA | J15: =+'Necesidades Trimestrales'!H13 -> 500 | K15: =+'Necesidades Trimestrales'!G13 -> 10
A16: 5 | B16: ='Necesidades Trimestrales'!B14 -> 2.1.1-6546.177 | C16: ='Necesidades Trimestrales'!E14 -> VERDURAS Y HORTALIZAS; VARIEDAD: BERENJENA, ESTADO: NATURAL, PRESENTACION: GRANEL, PESO: SIN VALOR | H16: NO | I16: =+'Necesidades Trimestrales'!F14 -> KG. | J16: =+'Necesidades Trimestrales'!H14 -> 95 | K16: =+'Necesidades Trimestrales'!G14 -> 100
A17: 6 | B17: ='Necesidades Trimestrales'!B15 -> 2.1.1-6546.236 | C17: ='Necesidades Trimestrales'!E15 -> VERDURAS Y HORTALIZAS; VARIEDAD: CEBOLLA, ESTADO: NATURAL, PRESENTACION: BOLSA, PESO: 20 Kg | H17: NO | I17: =+'Necesidades Trimestrales'!F15 -> BOLSA | J17: =+'Necesidades Trimestrales'!H15 -> 850 | K17: =+'Necesidades Trimestrales'!G15 -> 100
A18: 7 | B18: ='Necesidades Trimestrales'!B16 -> 2.1.1-6546.377 | C18: ='Necesidades Trimestrales'!E16 -> VERDURAS Y HORTALIZAS; VARIEDAD: CEBOLLA DE VERDEO, ESTADO: NATURAL, PRESENTACION: CAJON, PESO: 10 Kg, ELEM. TRANSPORTE: CAJON, MATERIAL ELEM. TRANSPORTE: CARTON, LIBRE DE GLUTEN: NO | H18: NO | I18: =+'Necesidades Trimestrales'!F16 -> CAJON | J18: =+'Necesidades Trimestrales'!H16 -> 1000 | K18: =+'Necesidades Trimestrales'!G16 -> 1
A19: 8 | B19: ='Necesidades Trimestrales'!B17 -> 2.1.1-6546.169 | C19: ='Necesidades Trimestrales'!E17 -> VERDURAS Y HORTALIZAS; VARIEDAD: ESPINACA, PRESENTACION: ATADO, ESTADO: NATURAL, PESO: SIN VALOR | H19: NO | I19: =+'Necesidades Trimestrales'!F17 -> UNIDAD | J19: =+'Necesidades Trimestrales'!H17 -> 31 | K19: =+'Necesidades Trimestrales'!G17 -> 50
A20: 9 | B20: ='Necesidades Trimestrales'!B18 -> 2.1.1-6546.374 | C20: ='Necesidades Trimestrales'!E18 -> VERDURAS Y HORTALIZAS; VARIEDAD: LECHUGA ARREPOLLADA, ESTADO: NATURAL, PRESENTACION: A GRANEL, PESO: 300 GR CADA PLANTA, ELEM. TRANSPORTE: SIN, MATERIAL ELEM. TRANSPORTE: SIN, LIBRE DE GLUTEN: SI | H20: NO | I20: =+'Necesidades Trimestrales'!F18 -> UNIDAD | J20: =+'Necesidades Trimestrales'!H18 -> 42 | K20: =+'Necesidades Trimestrales'!G18 -> 80
A21: 10 | B21: ='Necesidades Trimestrales'!B19 -> 2.1.1-6539.173 | C21: ='Necesidades Trimestrales'!E19 -> FRUTAS; VARIEDAD: LIMON, ESTADO: NATURAL, PRESENTACION: ENVASE X 15 Kg, ELEM. TRANSPORTE: CAJON, MATERIAL ELEM. TRANSPORTE: CARTON | H21: NO | I21: =+'Necesidades Trimestrales'!F19 -> CAJON | J21: =+'Necesidades Trimestrales'!H19 -> 320 | K21: =+'Necesidades Trimestrales'!G19 -> 5
A22: 11 | B22: ='Necesidades Trimestrales'!B20 -> 2.1.1-6539.170 | C22: ='Necesidades Trimestrales'!E20 -> FRUTAS; VARIEDAD: MANZANA RED DELICIOSA, ESTADO: NATURAL, PRESENTACION: ENVASE X 15 Kg, ELEM. TRANSPORTE: CAJON, MATERIAL ELEM. TRANSPORTE: CARTON | H22: NO | I22: =+'Necesidades Trimestrales'!F20 -> CAJON | J22: =+'Necesidades Trimestrales'!H20 -> 1410 | K22: =+'Necesidades Trimestrales'!G20 -> 40
A23: 12 | B23: ='Necesidades Trimestrales'!B21 -> 2.1.1-6539.7 | C23: ='Necesidades Trimestrales'!E21 -> FRUTAS; ESTADO: NATURAL, VARIEDAD: NARANJA PARA JUGO, PRESENTACION: A GRANEL, PESO: SIN VALOR | H23: NO | I23: =+'Necesidades Trimestrales'!F21 -> KG. | J23: =+'Necesidades Trimestrales'!H21 -> 30 | K23: =+'Necesidades Trimestrales'!G21 -> 400
... A34: 23 | B34: ='Necesidades Trimestrales'!B32 -> 2.1.1-6546.188 | C34: ='Necesidades Trimestrales'!E32 -> VERDURAS Y HORTALIZAS; ESTADO: NATURAL, PRESENTACION: GRANEL, PESO: SIN VALOR, VARIEDAD: ZAPALLO CRIOLLO | H34: NO | I34: =+'Necesidades Trimestrales'!F32 -> KG. | J34: =+'Necesidades Trimestrales'!H32 -> 31 | K34: =+'Necesidades Trimestrales'!G32 -> 150
A35: Costo total estimado: QUINIENTOS OCHENTA Y UN MIL DIEZ CON 00/100. | J35: =SUMPRODUCT(J12:J34,K12:K34) -> 581010

Sheet Autor Gastar
A1: EJERCICIO: | D1: ='Necesidades Trimestrales'!C6 -> 2020 | P1: AUTORIZACION PARA GASTAR
A4: JURISDICCIÓN: | G4: =' NotaPedido'!D3 -> 040 - Ministerio de Salud
A5: SAF: | G5: =' NotaPedido'!D4 -> 024 - Hospital Interzonal de Niños
A6: UNIDAD EJECUTORA: | G6: =' NotaPedido'!D5 -> 024 - Hospital Interzonal de Niños
A7: DEPENDENCIA SOLICITANTE: | G7: =' NotaPedido'!D6 -> Servicio de Alimentacion y Dietoterapia
A8: AUTORIZACIÓN:
A9: Señor Jefe de Servicio Administrativo Financiero:
A10: ="Autorizo la realización de los trámites correspondientes, a fin de proveer a este Organismo los bienes y/o servicios que se detallan en Nota de Pedido N° " & ' NotaPedido'!K1&", afectando la erogación resultante a los créditos presupuestarios aprobados a favor de esta Unidad Ejecutora, conforme al siguiente detalle:" -> Autorizo la realización de los trámites correspondientes, a fin de proveer a este Organismo los bienes y/o servicios que se detallan en Nota de Pedido N° 546/2020, afectando la erogación resultante a los créditos presupuestarios aprobados a favor de esta Unidad Ejecutora, conforme al siguiente detalle:
A12: IMPUTACIÓN PRESUPUESTARIA
A13: CÓDIGO | O13: DENOMINACIÓN DE LA PARTIDA PRESUPUESTARIA | Q13: IMPORTE
A14: PR | B14: SB | C14: PY | D14: AC | E14: OB | F14: UG | G14: FIN | H14: FUN | I14: I | J14: P | K14: P | L14: SubP | M14: M | N14: FF
A15: 36 | D15: 1 | F15: 4901 | G15: 3 | H15: 310 | I15: 2 | J15: 1 | K15: 1 | M15: 1 | N15: 1.1 | O15: Alimentos para Personas | Q15: 581010
A23: TOTAL DE PESOS: QUINIENTOS OCHENTA Y UN MIL DIEZ CON 00/100. | Q23: =SUM(Q15:Q22) -> 581010
A25: JUSTIFICACIÓN:
A26: Para la adquisición de Alimentos destinados al servico de Alimentacion y Dietoterapia del Hospital Interzonal de Niños Eva Peron, para el normal funcionamiento del organismo.

Sheet ANEXO I
A1: ANEXO I:
A2: ESPECIFICACIONES TÉCNICAS
A3: CARACTERÍSTICAS GENERALES
A4: REQUISITOS:
A5: • Estabilidad en las entregas, según fechas y horarios pactados.
A6: • Concordancia de los productos, condiciones y cantidades en peso o unidades pedidas, de acuerdo con la compra.
A7: • Tener el vehículo de transporte limpio y desinfectado, tanto en el interior como en el exterior.
A8: • Vestimenta sanitaria (blusa, chaqueta o delantal, pantalón y calzado blanco o de colores claros).
A9: • Los productos procederán de ESTABLECIMIENTOS AUTORIZADOS POR LA AUTORIDAD COMPETENTE.
A10: DOCUMENTACIÓN:
A11: • Registro de habilitación bromatológica del establecimiento.
A12: • Certificado de desinfección.
... A25: • La lechuga y cualquier otra hortaliza de hojas debe estar verde, compacta, fresca (sin indicios de marchitez), limpia y sin tejido oxidado ni hojas dañadas por insectos u otros daños.
