Workbook

Sheet SAF 011
A1: 2022
B2: Pedido de Necesidades Trimestrales
A4: JURISDICCION: | C4: 040 - MINISTERIO DE SALUD
A5: SAF N°: | C5: 011 - DIRECCION PROVINCIAL DE ADMINISTRACION - MINISTERIO DE SALUD
A6: EJERCICIO: | C6: 2022
A7: TRIMESTRE: | C7: CUARTO
A9: ID | B9: CODIGO ITEM | C9: RUBRO DE COMPRA | D9: I.P.P. | E9: DESCRIPCION | F9: UNIDAD DE MEDIDA | G9: CANTIDAD TOTAL | H9: PRECIO UNITARIO ESTIMADO | I9: IMPORTE TOTAL ESTIMADO | J9: ESPECIFICACION TECNICA | L9: 222 | M9: 252 | N9: 256 | O9: 259 | P9: 265 | Q9: 295
A10: 1 | B10: 2.5.6-7104.276 | C10: COMBUSTIBLES Y LUBRICANTES | D10: 256 | E10: ACEITES LUBRICANTES; USO: MAQUINA, PRESENTACION: AEROSOL X 400 CM3, NORMA: MULTIUSO | F10: UNIDAD | G10: 150 | H10: 700 | I10: =+G10*H10 -> 105000 | N10: =+I10 -> 105000
A11: 2 | B11: 2.5.2-3204.13 | C11: PROD. MEDICO/FARMACEUTICOS/LAB | D11: 252 | E11: ACIDO GRABADOR ODONTOLOG.; ESTADO: GEL, PRESENTACION: JERINGA X 12 GR, CAPACIDAD: 12 GR | F11: UNIDAD | G11: 300 | H11: 700 | I11: =+G11*H11 -> 210000 | J11: ACIDO FOSFORICO 37% GEL JERINGA 12 GR | M11: =+I11 -> 210000
A12: 3 | B12: 2.5.2-2327.29 | C12: PROD. MEDICO/FARMACEUTICOS/LAB | D12: 295 | E12: ACRILICOS AUTOCURABLES; TIPO: POLIMERO DE AUTOPOLIMERIZACION, PRESENTACION: FRASCO X 1 Kg | F12: UNIDAD | G12: 6 | H12: 5500 | I12: =+G12*H12 -> 33000 | J12: POLIMERO AUTOCURADO 1 KG T/ NEW POLL | Q12: =+I12 -> 33000
A13: 4 | B13: 2.5.2-6021.4 | C13: PROD. MEDICO/FARMACEUTICOS/LAB | D13: 295 | E13: ACRILICOS TERMOCURABLES; TIPO: POLIMERO, PRESENTACION: ENVASE X 1 Kg | F13: UNIDAD | G13: 15 | H13: 5500 | I13: =+G13*H13 -> 82500 | J13: POLIMERO TERMOCURADO 1 KG T/ NEW POLL | Q13: =+I13 -> 82500
A14: 5 | B14: 2.5.2-5538.8 | C14: PROD. MEDICO/FARMACEUTICOS/LAB | D14: 252 | E14: ADHESIVOS P/ODONTOLOGIA; PRESENTACION: FRASCO X 4,5 mm, TIPO: ADHESIVO+PRIMER, USO: ODONTOLOGICO | F14: UNIDAD | G14: 200 | H14: 1500 | I14: =+G14*H14 -> 300000 | M14: =+I14 -> 300000
A15: 6 | B15: 2.9.5-441.82 | C15: PROD. MEDICO/FARMACEUTICOS/LAB | D15: 295 | E15: AGUJAS QUIRURGICAS; TIPO: CARPULE, ESPECIFICACION: CORTA, UNIDAD VENTA: CAJA X 100, PRESENTACION: CAJA X 100 | F15: CAJA | G15: 200 | H15: 900 | I15: =+G15*H15 -> 180000 | J15: AGUJA CARPULE CORTA 21 MM CAJA X 100 UNID. | Q15: =+I15 -> 180000
A16: 7 | B16: 2.9.5-441.428 | C16: PROD. MEDICO/FARMACEUTICOS/LAB | D16: 295 | E16: AGUJAS QUIRURGICAS; TIPO: CARPULE, ESPECIFICACION: EXTRA CORTAS, PRESENTACION: ENVASE X 100 UN | F16: CAJA | G16: 40 | H16: 900 | I16: =+G16*H16 -> 36000 | J16: AGUJA CARPULE EXTRACORTA 12 MM CAJA X 100 UNID. | Q16: =+I16 -> 36000
A17: 8 | B17: 2.9.5-441.119 | C17: PROD. MEDICO/FARMACEUTICOS/LAB | D17: 295 | E17: AGUJAS QUIRURGICAS; TIPO: CARPULE, ESPECIFICACION: LARGA, PRESENTACION: CAJA X 100, UNIDAD VENTA: CAJA X 100 | F17: CAJA | G17: 40 | H17: 900 | I17: =+G17*H17 -> 36000 | J17: AGUJA CARPULE INTERMEDIA 25 MM CAJA X 100 UNID. | Q17: =+I17 -> 36000
A18: 9 | B18: 2.9.5-470.29 | C18: PROD. MEDICO/FARMACEUTICOS/LAB | D18: 295 | E18: ALGODONES; TIPO: ESTERIL, CAPACIDAD: PAQUETE X 500 ROLLOS, PRESENTACION: ENVASE X 500 | F18: BOLSA | G18: 50 | H18: 700 | I18: =+G18*H18 -> 35000 | J18: ROLLO DE ALGODÓN X 500 UNIDADES (0,375X 1-1/2") ODONTOLOGICO | Q18: =+I18 -> 35000
A19: 10 | B19: 2.5.2-1883.135 | C19: PROD. MEDICO/FARMACEUTICOS/LAB | D19: 252 | E19: ANESTESICOS LOCALES; TIPO: MONODROGA, DROGA GENERICA: LIDOCAINA 5%, FORMA FARMACEUTICA: GEL, PRESENTACION: ENVASE X 18 GR | F19: UNIDAD | G19: 50 | H19: 1800 | I19: =+G19*H19 -> 90000 | J19: ANESTESIA TOPICA LIDOCAINA 5 % X 18 GR | M19: =+I19 -> 90000
A20: 11 | B20: 2.5.2-1883.37 | C20: PROD. MEDICO/FARMACEUTICOS/LAB | D20: 252 | E20: ANESTESICOS LOCALES; TIPO: SIN VALOR, DROGA GENERICA: CLORHIDRATO DE CARTICAINA 4%, FORMA FARMACEUTICA: ANESTUBO CARPULE, PRESENTACION: CAJA X 50 UN | F20: CAJA | G20: 1440 | H20: 4500 | I20: =+G20*H20 -> 6480000 | M20: =+I20 -> 6480000
A21: 12 | B21: 2.5.2-1723.59 | C21: PROD. MEDICO/FARMACEUTICOS/LAB | D21: 252 | E21: ANTISEPTICOS LOCALES P/PERSONA; TIPO: MONODROGA, DROGA GENERICA: EDTAC, FORMA FARMACEUTICA: SOLUCION, PRESENTACION: FRASCO X 20 mL | F21: UNIDAD | G21: 20 | H21: 400 | I21: =+G21*H21 -> 8000 | M21: =+I21 -> 8000
A22: 13 | B22: 2.5.2-1723.53 | C22: PROD. MEDICO/FARMACEUTICOS/LAB | D22: 252 | E22: ANTISEPTICOS LOCALES P/PERSONA; TIPO: MONODROGA, DROGA GENERICA: EUGENOL, FORMA FARMACEUTICA: LIQUIDO, PRESENTACION: FRASCO X 20 mL | F22: UNIDAD | G22: 60 | H22: 700 | I22: =+G22*H22 -> 42000 | M22: =+I22 -> 42000
A23: 14 | B23: 2.5.2-1723.148 | C23: PROD. MEDICO/FARMACEUTICOS/LAB | D23: 252 | E23: ANTISEPTICOS LOCALES P/PERSONA; TIPO: MONODROGA, DROGA GENERICA: IODOFORMO, FORMA FARMACEUTICA: POLVO, PRESENTACION: ENVASE X 20 GR | F23: UNIDAD | G23: 50 | H23: 500 | I23: =+G23*H23 -> 25000 | M23: =+I23 -> 25000
A24: 15 | B24: 2.9.9-3095.4 | C24: INDUMENT TEXTIL Y CONFECCIONES | D24: 222 | E24: BABEROS; TIPO: DESCARTABLE, MATERIAL: FISELINA NO ESTERIL, PRESENTACION: CAJA X 100 UN | F24: CAJA | G24: 200 | H24: 700 | I24: =+G24*H24 -> 140000 | J24: BABEROS DE FRISELINA DESCARTABLE USO ODONTOLOGICO | L24: =+I24 -> 140000
A25: 16 | B25: 2.9.5-5507.2 | C25: PROD. MEDICO/FARMACEUTICOS/LAB | D25: 295 | E25: CADENAS P/BABEROS; MATERIAL : 147 dBV/mPa , USO: ODONTOLOGIA, MATERIAL: METAL | F25: UNIDAD | G25: 50 | H25: 230 | I25: =+G25*H25 -> 11500 | Q25: =+I25 -> 11500
A26: 17 | B26: 2.9.5-2563.4 | C26: PROD. MEDICO/FARMACEUTICOS/LAB | D26: 252 | E26: CARIOSTATICOS; ENVASE: AVIO X 5 mL, PRESENTACION: AVIO X 5 mL | F26: UNIDAD | G26: 100 | H26: 1000 | I26: =+G26*H26 -> 100000 | J26: CARIOSTATICO FLUORSILVER 5 ML REMINERALIZADOR FLUORURO DIAMINO 38 % | M26: =+I26 -> 100000
A27: 18 | B27: 2.5.2-2322.20 | C27: PROD. MEDICO/FARMACEUTICOS/LAB | D27: 252 | E27: CEMENTOS QUIRURGICOS; PRESENTACION: AVIO 13 GRS/11 GRS, TIPO: HIDROXIDO DE CALCIO FRAGUABLE, USO: ODONTOLOGIA | F27: CAJA | G27: 20 | H27: 500 | I27: =+G27*H27 -> 10000 | J27: PASTA DE HIDROXIDO DE CALCIO FOTOPOLIMERIZABLE, AVIO 13/11 GR | M27: =+I27 -> 10000
A28: 19 | B28: 2.5.2-2322.12 | C28: PROD. MEDICO/FARMACEUTICOS/LAB | D28: 252 | E28: CEMENTOS QUIRURGICOS; PRESENTACION: ENVASE X 20 GR, TIPO: GROSSMAN, USO: ODONTOLOGIA | F28: UNIDAD | G28: 50 | H28: 500 | I28: =+G28*H28 -> 25000 | J28: CEMENTO GROSSMAN AVIO 20 G | M28: =+I28 -> 25000
A29: 20 | B29: 2.5.9-1687.7 | C29: PINTURAS | D29: 259 | E29: CERAS; TIPO: ROSA, USO: ODONTOLOGICO, CAPACIDAD: ENVASE X 1 Kg, PRESENTACION: ENVASE X 1 Kg | F29: UNIDAD | G29: 100 | H29: 200 | I29: 20000 | J29: CERA ROSA LAMINA X 1KG USO ODONTOLOGICO | O29: =+I29 -> 20000
A30: 21 | B30: 2.5.9-1687.3 | C30: PINTURAS | D30: 259 | E30: CERAS; TIPO: UTILITY, USO: ODONTOLOGICO, CAPACIDAD: ENVASE X 200 GR, PRESENTACION: ENVASE X 200 GR | F30: UNIDAD | G30: 50 | H30: 1000 | I30: 50000 | J30: CERA UTILITY ROJA X 200 GM USO ODONTOLOGICO UNIDAD | O30: =+I30 -> 50000
A31: 22 | B31: 2.9.5-2567.163 | C31: PROD. MEDICO/FARMACEUTICOS/LAB | D31: 295 | E31: FRESAS P/ODONTOLOGIA; MATERIAL: PIEDRA DE DIAMANTE, NUMERO: 4, LARGO: STANDAR, TIPO: REDONDA FG | F31: UNIDAD | G31: 20 | H31: 300 | I31: =+G31*H31 -> 6000 | Q31: =+I31 -> 6000
A32: 23 | B32: 2.9.5-2567.164 | C32: PROD. MEDICO/FARMACEUTICOS/LAB | D32: 295 | E32: FRESAS P/ODONTOLOGIA; MATERIAL: PIEDRA DE DIAMANTE, NUMERO: 5, LARGO: STANDAR, TIPO: REDONDA FG | F32: UNIDAD | G32: 20 | H32: 300 | I32: =+G32*H32 -> 6000 | Q32: =+I32 -> 6000
A33: 24 | B33: 2.9.5-2567.165 | C33: PROD. MEDICO/FARMACEUTICOS/LAB | D33: 295 | E33: FRESAS P/ODONTOLOGIA; MATERIAL: PIEDRA DE DIAMANTE, NUMERO: 6, LARGO: STANDAR, TIPO: REDONDA FG | F33: UNIDAD | G33: 20 | H33: 300 | I33: =+G33*H33 -> 6000 | Q33: =+I33 -> 6000
A34: 25 | B34: 2.9.5-2567.201 | C34: PROD. MEDICO/FARMACEUTICOS/LAB | D34: 295 | E34: FRESAS P/ODONTOLOGIA; MATERIAL: PIEDRA DE DIAMANTE, NUMERO: SIN, LARGO: STANDAR, TIPO: AGUJA GRANO ULTRA FINO FG | F34: UNIDAD | G34: 100 | H34: 300 | I34: =+G34*H34 -> 30000 | J34: Piedra de diamante aguja grano ultrafino FG numero 296 | Q34: =+I34 -> 30000
A35: 26 | B35: 2.9.5-2567.239 | C35: PROD. MEDICO/FARMACEUTICOS/LAB | D35: 295 | E35: FRESAS P/ODONTOLOGIA; MATERIAL: PIEDRA DE DIAMANTE, NUMERO: SIN, LARGO: STANDAR, TIPO: CILINDRICA FG | F35: UNIDAD | G35: 100 | H35: 300 | I35: =+G35*H35 -> 30000 | J35: Piedra de diamante FG cilindrica numero 109 | Q35: =+I35 -> 30000
A36: 27 | B36: 2.9.5-444.24 | C36: PROD. MEDICO/FARMACEUTICOS/LAB | D36: 295 | E36: HOJAS DE BISTURI; TIPO: CAJA X 100 UN, Nº: 15, NUMERO: 15 | F36: CAJA | G36: 10 | H36: 1200 | I36: =+G36*H36 -> 12000 | Q36: =+I36 -> 12000
A37: 28 | B37: 2.7.5-421.19 | C37: FERRETERIA | D37: 295 | E37: HOJAS DE SIERRA; DIENTES X PULGADA: SIN VALOR, LONG.DE CUERPO: 14 Cm, TIPO: COMUN | F37: UNIDAD | G37: 20 | H37: 200 | I37: =+G37*H37 -> 4000 | J37: Hoja tipo Ney para sierra odontologia- laboratorio longitud 14 cm- ancho 1mm | Q37: =+I37 -> 4000
A38: 29 | B38: 2.9.5-5144.184 | C38: PROD. MEDICO/FARMACEUTICOS/LAB | D38: 295 | E38: INSTRUMENTAL ODONTOLOGICO; DESCARTABLE: NO, PRESENTACION: UNIDAD, TIPO: ALICATE DE CORTE Y MODELADO | F38: UNIDAD | G38: 6 | H38: 4000 | I38: =+G38*H38 -> 24000 | J38: ALICATE DE CORTE P/ PROTESIS | Q38: =+I38 -> 24000
A39: 30 | B39: 2.9.5-5144.177 | C39: PROD. MEDICO/FARMACEUTICOS/LAB | D39: 295 | E39: INSTRUMENTAL ODONTOLOGICO; DESCARTABLE: NO, PRESENTACION: UNIDAD, TIPO: MATRIZ METALICA | F39: UNIDAD | G39: 10 | H39: 500 | I39: =+G39*H39 -> 5000 | J39: MATRIZ DE ACERO 6 MM | Q39: =+I39 -> 5000
A40: 31 | B40: 2.9.5-5144.593 | C40: PROD. MEDICO/FARMACEUTICOS/LAB | D40: 295 | E40: INSTRUMENTAL ODONTOLOGICO; TIPO: CEPILLO DE 4 HILERAS, DESCARTABLE: SI, PRESENTACION: UNIDAD | F40: UNIDAD | G40: 30 | H40: 400 | I40: =+G40*H40 -> 12000 | J40: PARA PULIR PROTESIS | Q40: =+I40 -> 12000
A41: 32 | B41: 2.9.5-5144.481 | C41: PROD. MEDICO/FARMACEUTICOS/LAB | D41: 295 | E41: INSTRUMENTAL ODONTOLOGICO; TIPO: CLIP P/RADIOGRAFIA, DESCARTABLE: NO, PRESENTACION: UNIDAD | F41: UNIDAD | G41: 10 | H41: 1500 | I41: =+G41*H41 -> 15000 | J41: CLIP PARA RX METALICO - CAJA X 7 UNID | Q41: =+I41 -> 15000
A42: 33 | B42: 2.9.5-5144.563 | C42: PROD. MEDICO/FARMACEUTICOS/LAB | D42: 295 | E42: INSTRUMENTAL ODONTOLOGICO; TIPO: COMPRESA P/PLATINA AZUL, DESCARTABLE: SI, PRESENTACION: CAJA X 500 UN | F42: CAJA | G42: 700 | H42: 200 | I42: =+G42*H42 -> 140000 | J42: COMPRESA DESCARTABLE X 500 UNIDADES USO ODONTOLOGICO | Q42: =+I42 -> 140000
A43: 34 | B43: 2.9.5-5144.242 | C43: PROD. MEDICO/FARMACEUTICOS/LAB | D43: 295 | E43: INSTRUMENTAL ODONTOLOGICO; TIPO: CONO CONDENS. LAT. XX FINE, DESCARTABLE: SI, PRESENTACION: CAJA X 120 | F43: CAJA | G43: 100 | H43: 600 | I43: =+G43*H43 -> 60000 | J43: CONOS DE GUTA PERCHA CONDENSACION LATERAL X 120 F | Q43: =+I43 -> 60000
A44: 35 | B44: 2.9.5-5144.242 | C44: PROD. MEDICO/FARMACEUTICOS/LAB | D44: 295 | E44: INSTRUMENTAL ODONTOLOGICO; TIPO: CONO CONDENS. LAT. XX FINE, DESCARTABLE: SI, PRESENTACION: CAJA X 120 | F44: CAJA | G44: 100 | H44: 600 | I44: =+G44*H44 -> 60000 | J44: CONOS DE GUTA PERCHA CONDENSACION LATERAL X 120 FF | Q44: =+I44 -> 60000
A45: 36 | B45: 2.9.5-5144.242 | C45: PROD. MEDICO/FARMACEUTICOS/LAB | D45: 295 | E45: INSTRUMENTAL ODONTOLOGICO; TIPO: CONO CONDENS. LAT. XX FINE, DESCARTABLE: SI, PRESENTACION: CAJA X 120 | F45: CAJA | G45: 100 | H45: 600 | I45: =+G45*H45 -> 60000 | J45: CONOS DE GUTA PERCHA CONDENSACION LATERAL X 120 FM | Q45: =+I45 -> 60000
A46: 37 | B46: 2.9.5-5144.242 | C46: PROD. MEDICO/FARMACEUTICOS/LAB | D46: 295 | E46: INSTRUMENTAL ODONTOLOGICO; TIPO: CONO CONDENS. LAT. XX FINE, DESCARTABLE: SI, PRESENTACION: CAJA X 120 | F46: CAJA | G46: 100 | H46: 600 | I46: =+G46*H46 -> 60000 | J46: CONOS DE GUTA PERCHA CONDENSACION LATERAL X 120 M | Q46: =+I46 -> 60000
A47: 38 | B47: 2.9.5-5144.242 | C47: PROD. MEDICO/FARMACEUTICOS/LAB | D47: 295 | E47: INSTRUMENTAL ODONTOLOGICO; TIPO: CONO CONDENS. LAT. XX FINE, DESCARTABLE: SI, PRESENTACION: CAJA X 120 | F47: CAJA | G47: 100 | H47: 600 | I47: =+G47*H47 -> 60000 | J47: CONOS DE GUTA PERCHA CONDENSACION LATERAL X 120 MF | Q47: =+I47 -> 60000
A48: 39 | B48: 2.9.5-5144.107 | C48: PROD. MEDICO/FARMACEUTICOS/LAB | D48: 295 | E48: INSTRUMENTAL ODONTOLOGICO; TIPO: CONO DE FIELTRO, PRESENTACION: UNIDAD, DESCARTABLE: NO | F48: UNIDAD | G48: 100 | H48: 400 | I48: =+G48*H48 -> 40000 | J48: Conos de fieltro mediano para pulido de protesis | Q48: =+I48 -> 40000
... A64: 55 | B64: 2.9.5-5144.155 | C64: PROD. MEDICO/FARMACEUTICOS/LAB | D64: 295 | E64: INSTRUMENTAL ODONTOLOGICO; TIPO: GOMA SILICONADA P/PIEZA DE MAN, DESCARTABLE: NO, PRESENTACION: UNIDAD | F64: UNIDAD | G64: 100 | H64: 200 | I64: =+G64*H64 -> 20000 | J64: GOMA SILICONADA PARA PROTESIS | Q64: =+I64 -> 20000
A65: 56 | B65: 2.9.5-5144.496 | C65: PROD. MEDICO/FARMACEUTICOS/LAB | D65: 295 | E65: INSTRUMENTAL ODONTOLOGICO; TIPO: JERINGA TRIPLE, DESCARTABLE: NO, PRESENTACION: UNIDAD | F65: UNIDAD | G65: 10 | H65: 4000 | I65: =+G65*H65 -> 40000 | Q65: =+I65 -> 40000
A66: 57 | B66: 2.9.5-5144.10 | C66: PROD. MEDICO/FARMACEUTICOS/LAB | D66: 295 | E66: INSTRUMENTAL ODONTOLOGICO; TIPO: JERINGAS TIPO CARPULE, PRESENTACION: UNIDAD, DESCARTABLE: NO | F66: UNIDAD | G66: 50 | H66: 1500 | I66: =+G66*H66 -> 75000 | Q66: =+I66 -> 75000
A67: 58 | B67: 2.9.5-5144.123 | C67: PROD. MEDICO/FARMACEUTICOS/LAB | D67: 295 | E67: INSTRUMENTAL ODONTOLOGICO; TIPO: LOSETA DE VIDRIO 6 X 8 X 0,5CM, DESCARTABLE: NO, PRESENTACION: UNIDAD | F67: UNIDAD | G67: 30 | H67: 150 | I67: =+G67*H67 -> 4500 | Q67: =+I67 -> 4500
A68: 59 | B68: 2.9.5-5144.9 | C68: PROD. MEDICO/FARMACEUTICOS/LAB | D68: 295 | E68: INSTRUMENTAL ODONTOLOGICO; TIPO: MANGO PARA ESPEJO BUCAL, PRESENTACION: UNIDAD, DESCARTABLE: NO | F68: UNIDAD | G68: 200 | H68: 250 | I68: =+G68*H68 -> 50000 | J68: MANGO PARA ESPEJO METALICO | Q68: =+I68 -> 50000
A69: 60 | B69: 2.9.5-5144.459 | C69: PROD. MEDICO/FARMACEUTICOS/LAB | D69: 295 | E69: INSTRUMENTAL ODONTOLOGICO; TIPO: MATRIZ ACETATO P/FRENTES, DESCARTABLE: SI, PRESENTACION: ENVASE X 96 UN | F69: BLISTER | G69: 30 | H69: 300 | I69: =+G69*H69 -> 9000 | Q69: =+I69 -> 9000
A70: 61 | B70: 2.9.5-5144.518 | C70: PROD. MEDICO/FARMACEUTICOS/LAB | D70: 295 | E70: INSTRUMENTAL ODONTOLOGICO; TIPO: MEMBRANA, DESCARTABLE: SI, PRESENTACION: UNIDAD | F70: UNIDAD | G70: 5 | H70: 2800 | I70: =+G70*H70 -> 14000 | J70: MEMBRANA T/TISSUM 2.0 X 3.0 | Q70: =+I70 -> 14000
A71: 62 | B71: 2.9.5-5144.330 | C71: PROD. MEDICO/FARMACEUTICOS/LAB | D71: 252 | E71: INSTRUMENTAL ODONTOLOGICO; TIPO: MONOMERO AUTOCURABLE, DESCARTABLE: SI, PRESENTACION: ENVASE X 1 L | F71: UNIDAD | G71: 20 | H71: 3500 | I71: =+G71*H71 -> 70000 | J71: MONOMERO AUTOCURADO 1 LT | M71: =+I71 -> 70000
A72: 63 | B72: 2.9.5-5144.331 | C72: PROD. MEDICO/FARMACEUTICOS/LAB | D72: 252 | E72: INSTRUMENTAL ODONTOLOGICO; TIPO: MONOMERO TERMOCURABLE, DESCARTABLE: SI, PRESENTACION: ENVASE X 1 L | F72: UNIDAD | G72: 10 | H72: 3600 | I72: =+G72*H72 -> 36000 | J72: MONOMERO TERMOCURABLE X 1 LT T/ NEW POL | M72: =+I72 -> 36000
A73: 64 | B73: 2.9.5-5144.358 | C73: PROD. MEDICO/FARMACEUTICOS/LAB | D73: 295 | E73: INSTRUMENTAL ODONTOLOGICO; TIPO: PAPEL DE ARTICULAR- FORMA HERR, DESCARTABLE: SI, PRESENTACION: PAQUETE X 12 LIBRITOS | F73: CAJA | G73: 15 | H73: 1200 | I73: =+G73*H73 -> 18000 | J73: PAPEL DE ARTICULAR T/GABRIDENT AZUL CAJA X 12 UN | Q73: =+I73 -> 18000
A74: 65 | B74: 2.9.5-5144.562 | C74: PROD. MEDICO/FARMACEUTICOS/LAB | D74: 265 | E74: INSTRUMENTAL ODONTOLOGICO; TIPO: PIEDRA POMEZ, DESCARTABLE: SI, PRESENTACION: ENVASE X 2 Kg | F74: UNIDAD | G74: 10 | H74: 200 | I74: =+G74*H74 -> 2000 | P74: =+I74 -> 2000
A75: 66 | B75: 2.9.5-5144.462 | C75: PROD. MEDICO/FARMACEUTICOS/LAB | D75: 295 | E75: INSTRUMENTAL ODONTOLOGICO; TIPO: PINCEL MICROBRUSH, DESCARTABLE: SI, PRESENTACION: ENVASE X 100 UN | F75: TUBO | G75: 200 | H75: 400 | I75: =+G75*H75 -> 80000 | Q75: =+I75 -> 80000
A76: 67 | B76: 2.9.5-5144.8 | C76: PROD. MEDICO/FARMACEUTICOS/LAB | D76: 295 | E76: INSTRUMENTAL ODONTOLOGICO; TIPO: PINZA DE ALGODON, DESCARTABLE: NO, PRESENTACION: UNIDAD | F76: UNIDAD | G76: 100 | H76: 300 | I76: =+G76*H76 -> 30000 | Q76: =+I76 -> 30000
A77: 68 | B77: 2.9.5-5144.176 | C77: PROD. MEDICO/FARMACEUTICOS/LAB | D77: 295 | E77: INSTRUMENTAL ODONTOLOGICO; TIPO: PLACA BASE INFERIOR, DESCARTABLE: SIN VALOR, PRESENTACION: ENVASE X 100 | F77: CAJA | G77: 8 | H77: 4100 | I77: =+G77*H77 -> 32800 | J77: PLACA BASE DESCARTABLE INFERIOR X 100 UN | Q77: =+I77 -> 32800
A78: 69 | B78: 2.9.5-5144.175 | C78: PROD. MEDICO/FARMACEUTICOS/LAB | D78: 295 | E78: INSTRUMENTAL ODONTOLOGICO; TIPO: PLACA BASE SUPERIOR, DESCARTABLE: SIN VALOR, PRESENTACION: ENVASE X 100 | F78: CAJA | G78: 8 | H78: 4800 | I78: =+G78*H78 -> 38400 | J78: PLACA BASE DESCARTABLE SUPERIOR X 100 UN | Q78: =+I78 -> 38400
A79: 70 | B79: 2.9.5-5144.195 | C79: PROD. MEDICO/FARMACEUTICOS/LAB | D79: 295 | E79: INSTRUMENTAL ODONTOLOGICO; TIPO: SEPARADOR DE YESO ROSA, DESCARTABLE: SI, PRESENTACION: 1 L | F79: UNIDAD | G79: 30 | H79: 3000 | I79: =+G79*H79 -> 90000 | Q79: =+I79 -> 90000
A80: 71 | B80: 2.9.5-5144.536 | C80: PROD. MEDICO/FARMACEUTICOS/LAB | D80: 295 | E80: INSTRUMENTAL ODONTOLOGICO; TIPO: SUCTOR, DESCARTABLE: SI, PRESENTACION: ENVASE X 100 UN | F80: BOLSA | G80: 80 | H80: 450 | I80: =+G80*H80 -> 36000 | J80: Eyectores Suctores de Saliva - BOLSA X 100 UN | Q80: =+I80 -> 36000
A81: 72 | B81: 2.9.5-5144.568 | C81: PROD. MEDICO/FARMACEUTICOS/LAB | D81: 295 | E81: INSTRUMENTAL ODONTOLOGICO; TIPO: TIRA P/PULIR. COMPOSITE-GR MED, DESCARTABLE: SI, PRESENTACION: ENVASE X 50 UN | F81: BLISTER | G81: 30 | H81: 900 | I81: =+G81*H81 -> 27000 | J81: TIRAS PARA PULIR COMPOSITE X 50 | Q81: =+I81 -> 27000
A82: 73 | B82: 2.9.5-5144.90 | C82: PROD. MEDICO/FARMACEUTICOS/LAB | D82: 295 | E82: INSTRUMENTAL ODONTOLOGICO; TIPO: TIRANERVIOS, DESCARTABLE: NO, PRESENTACION: UNIDAD | F82: BLISTER | G82: 15 | H82: 400 | I82: =+G82*H82 -> 6000 | J82: TIRA NERVIOS 21 mm BLISTER X 12 UNIDADES | Q82: =+I82 -> 6000
A83: 74 | B83: 2.9.5-5144.540 | C83: PROD. MEDICO/FARMACEUTICOS/LAB | D83: 295 | E83: INSTRUMENTAL ODONTOLOGICO; TIPO: VASOS, DESCARTABLE: SI, PRESENTACION: CAJA X 3500 UN | F83: CAJA | G83: 5 | H83: 13000 | I83: =+G83*H83 -> 65000 | Q83: =+I83 -> 65000
A84: 75 | B84: 2.5.2-5143.3 | C84: PROD. MEDICO/FARMACEUTICOS/LAB | D84: 252 | E84: IONOMEROS VITREOS; USO: CEMENTADO, ESTADO: POLVO, PRESENTACION: ENVASE X 10 GR, FORMA DE PRESENTACION: POLVO | F84: UNIDAD | G84: 10 | H84: 2700 | I84: =+G84*H84 -> 27000 | J84: ionomero vitreo cementado para restauracion tipo 2 presentacion 10 gr | M84: =+I84 -> 27000
A85: 76 | B85: 2.5.2-5143.37 | C85: PROD. MEDICO/FARMACEUTICOS/LAB | D85: 252 | E85: IONOMEROS VITREOS; USO: FOTOCURADO, PRESENTACION: AVIO 10 GRS/6 ML, FORMA DE PRESENTACION: POLVO - LIQUIDO | F85: UNIDAD | G85: 40 | H85: 2700 | I85: =+G85*H85 -> 108000 | J85: ionomero vitreo foto para restauracion tipo 2 presentacion 10 gr + 6 ml | M85: =+I85 -> 108000
A86: 77 | B86: 2.9.5-2538.177 | C86: PROD. MEDICO/FARMACEUTICOS/LAB | D86: 295 | E86: LIMAS P/ODONTOLOGIA; MATERIAL: ACERO FLEXIBLE, NUMERO: 15 AL 40, LARGO: 25 mm, TIPO: LISA | F86: CAJA | G86: 30 | H86: 1700 | I86: =+G86*H86 -> 51000 | J86: LIMAS FLEXIBLES 1º SERIE 25 MM X 6 UN | Q86: =+I86 -> 51000
A87: 78 | B87: 2.9.5-2538.164 | C87: PROD. MEDICO/FARMACEUTICOS/LAB | D87: 295 | E87: LIMAS P/ODONTOLOGIA; MATERIAL: ACERO INOXIDABLE, NUMERO: 15 AL 40, LARGO: 21 mm, TIPO: HEDSTROEM | F87: CAJA | G87: 30 | H87: 500 | I87: =+G87*H87 -> 15000 | J87: LIMAS HESTROM X 6 UN | Q87: =+I87 -> 15000
A88: 79 | B88: 2.9.5-2538.169 | C88: PROD. MEDICO/FARMACEUTICOS/LAB | D88: 295 | E88: LIMAS P/ODONTOLOGIA; MATERIAL: ACERO INOXIDABLE, NUMERO: 15 AL 40, LARGO: 21 mm, TIPO: K | F88: CAJA | G88: 30 | H88: 2200 | I88: =+G88*H88 -> 66000 | J88: LIMAS K 1º SERIE 21 MM X 6 UN | Q88: =+I88 -> 66000
A89: 80 | B89: 2.9.5-2538.166 | C89: PROD. MEDICO/FARMACEUTICOS/LAB | D89: 295 | E89: LIMAS P/ODONTOLOGIA; MATERIAL: ACERO INOXIDABLE, NUMERO: 15 AL 40, LARGO: 25 mm, TIPO: HEDSTROEM | F89: CAJA | G89: 30 | H89: 2200 | I89: =+G89*H89 -> 66000 | J89: LIMAS H FILES 1º SERIE 25 MM X 6 UN | Q89: =+I89 -> 66000
A90: 81 | B90: 2.9.5-2538.172 | C90: PROD. MEDICO/FARMACEUTICOS/LAB | D90: 295 | E90: LIMAS P/ODONTOLOGIA; MATERIAL: ACERO INOXIDABLE, NUMERO: 15 AL 40, LARGO: 25 mm, TIPO: K | F90: CAJA | G90: 10 | H90: 1600 | I90: =+G90*H90 -> 16000 | J90: LIMAS K 1º SERIE 25MM X 6 UN | Q90: =+I90 -> 16000
A91: 82 | B91: 2.9.5-2538.170 | C91: PROD. MEDICO/FARMACEUTICOS/LAB | D91: 295 | E91: LIMAS P/ODONTOLOGIA; MATERIAL: ACERO INOXIDABLE, NUMERO: 45 AL 80, LARGO: 21 mm, TIPO: K | F91: CAJA | G91: 10 | H91: 1600 | I91: =+G91*H91 -> 16000 | J91: LIMAS K 2º SERIE 21 MM X 6 UN | Q91: =+I91 -> 16000
A92: 83 | B92: 2.9.5-2538.167 | C92: PROD. MEDICO/FARMACEUTICOS/LAB | D92: 295 | E92: LIMAS P/ODONTOLOGIA; MATERIAL: ACERO INOXIDABLE, NUMERO: 45 AL 80, LARGO: 25 mm, TIPO: HEDSTROEM | F92: CAJA | G92: 30 | H92: 2200 | I92: =+G92*H92 -> 66000 | J92: LIMAS H FILE 2º SERIE 25 MM X 6 UN | Q92: =+I92 -> 66000
A93: 84 | B93: 2.9.5-2538.162 | C93: PROD. MEDICO/FARMACEUTICOS/LAB | D93: 295 | E93: LIMAS P/ODONTOLOGIA; MATERIAL: CARBURO DE TUNGSTENO, NUMERO: 15/40, LARGO: 31 mm, TIPO: K | F93: CAJA | G93: 10 | H93: 1600 | I93: =+G93*H93 -> 16000 | J93: LIMAS K 1º SERIE 31MM X 6 UN | Q93: =+I93 -> 16000
A94: 85 | B94: 2.9.5-2538.161 | C94: PROD. MEDICO/FARMACEUTICOS/LAB | D94: 295 | E94: LIMAS P/ODONTOLOGIA; MATERIAL: CARBURO DE TUNGSTENO, NUMERO: 45/80, LARGO: 25 mm, TIPO: K | F94: CAJA | G94: 10 | H94: 1600 | I94: =+G94*H94 -> 16000 | J94: LIMAS K 2º SERIE 25 MM X 6 UN | Q94: =+I94 -> 16000
A95: 86 | B95: 2.9.5-2538.163 | C95: PROD. MEDICO/FARMACEUTICOS/LAB | D95: 295 | E95: LIMAS P/ODONTOLOGIA; MATERIAL: CARBURO DE TUNGSTENO, NUMERO: 45/80, LARGO: 31 mm, TIPO: K | F95: CAJA | G95: 10 | H95: 1600 | I95: =+G95*H95 -> 16000 | J95: LIMAS K 2º SERIE 31MM X 6 UN | Q95: =+I95 -> 16000
A96: 87 | B96: 2.9.5-5627.9 | C96: PROD. MEDICO/FARMACEUTICOS/LAB | D96: 295 | E96: MANGOS DE BISTURI; TIPO: MANGO DE BISTURI, USO: QUIRURGICO/VARIOS, CAMBIAR HOJAS: SI, NUMERO: 3, MATERIAL: ACERO QUIRURGICO | F96: UNIDAD | G96: 50 | H96: 500 | I96: =+G96*H96 -> 25000 | J96: MANGO DE BISTURI NRO 3 | Q96: =+I96 -> 25000
A97: 88 | B97: 2.5.2-5573.3 | C97: PROD. MEDICO/FARMACEUTICOS/LAB | D97: 252 | E97: PASTAS ODONTOLOGICAS P/PULIR; PRESENTACION: BARRA, TIPO: ALTO BRILLO | F97: UNIDAD | G97: 10 | H97: 500 | I97: 5000 | J97: PASTA TIZA PARA PULIR (BARRA DE ALTO BRILLO) USO ODONTOLOGICO | M97: =+I97 -> 5000
A98: 89 | B98: 2.5.2-3202.2 | C98: PROD. MEDICO/FARMACEUTICOS/LAB | D98: 252 | E98: PASTAS P/IMPRESION DENTAL; PRODUCTO: ALIGINATO KROMOPAN, PRESENTACION: SOBRE X 450 GR, DESCRIPCION: ALGINATO CROMATICO | F98: UNIDAD | G98: 50 | H98: 1500 | I98: =+G98*H98 -> 75000 | J98: ALGINATOS CROMATICO CA37 PAQ. X 450 G | M98: =+I98 -> 75000
A99: 90 | B99: 2.9.5-5514.10 | C99: PROD. MEDICO/FARMACEUTICOS/LAB | D99: 295 | E99: PASTAS P/ODONTOLOGIA; PRESENTACION: JERINGA, USO: SELLADOR, TIPO: COMPOMERO | F99: UNIDAD | G99: 30 | H99: 1400 | I99: =+G99*H99 -> 42000 | J99: SELLADOR DE FOSAS Y FISURAS X 1,5 GM | Q99: =+I99 -> 42000
A100: 91 | B100: 2.9.5-5514.1 | C100: PROD. MEDICO/FARMACEUTICOS/LAB | D100: 252 | E100: PASTAS P/ODONTOLOGIA; TIPO: CON CIRCONES MOLIDOS SIN FLUOR, USO: PULIR, PRESENTACION: ENVASE X 45 GR | F100: UNIDAD | G100: 30 | H100: 1500 | I100: =+G100*H100 -> 45000 | J100: PASTA P/ PULIR GLOSS BRILLO 45 GR | M100: =+I100 -> 45000
A101: 92 | B101: 2.9.5-5514.37 | C101: PROD. MEDICO/FARMACEUTICOS/LAB | D101: 252 | E101: PASTAS P/ODONTOLOGIA; TIPO: HIDROXIDO DE CALCIO FRAGUABLE, USO: PROTECTOR PULPAR INDIRECTO, PRESENTACION: AVIO 13 GRS/11 GRS | F101: CAJA | G101: 100 | H101: 2000 | I101: =+G101*H101 -> 200000 | J101: HIDROXIDO DE CALCIO PASTA/PASTA | M101: =+I101 -> 200000
A102: 93 | B102: 2.9.5-5514.5 | C102: PROD. MEDICO/FARMACEUTICOS/LAB | D102: 252 | E102: PASTAS P/ODONTOLOGIA; USO: FOTOPOLIMERIZACION, TIPO: COMPOSITE HIBRIDO, PRESENTACION: JERINGA X 4 GR | F102: UNIDAD | G102: 80 | H102: 1000 | I102: =+G102*H102 -> 80000 | J102: RESINA A1 JERINGA X 4GR | M102: =+I102 -> 80000
A103: 94 | B103: 2.9.5-5514.5 | C103: PROD. MEDICO/FARMACEUTICOS/LAB | D103: 252 | E103: PASTAS P/ODONTOLOGIA; USO: FOTOPOLIMERIZACION, TIPO: COMPOSITE HIBRIDO, PRESENTACION: JERINGA X 4 GR | F103: UNIDAD | G103: 80 | H103: 1000 | I103: =+G103*H103 -> 80000 | J103: RESINA B2 JERINGA X 4GR | M103: =+I103 -> 80000
A104: 95 | B104: 2.9.5-5514.5 | C104: PROD. MEDICO/FARMACEUTICOS/LAB | D104: 252 | E104: PASTAS P/ODONTOLOGIA; USO: FOTOPOLIMERIZACION, TIPO: COMPOSITE HIBRIDO, PRESENTACION: JERINGA X 4 GR | F104: UNIDAD | G104: 150 | H104: 1000 | I104: =+G104*H104 -> 150000 | J104: RESINA A2 JERINGA X 4GR | M104: =+I104 -> 150000
A105: 96 | B105: 2.9.5-5514.5 | C105: PROD. MEDICO/FARMACEUTICOS/LAB | D105: 252 | E105: PASTAS P/ODONTOLOGIA; USO: FOTOPOLIMERIZACION, TIPO: COMPOSITE HIBRIDO, PRESENTACION: JERINGA X 4 GR | F105: UNIDAD | G105: 150 | H105: 1000 | I105: =+G105*H105 -> 150000 | J105: RESINA A3 JERINGA X 4 GR | M105: =+I105 -> 150000
A106: 97 | B106: 2.9.5-5514.5 | C106: PROD. MEDICO/FARMACEUTICOS/LAB | D106: 252 | E106: PASTAS P/ODONTOLOGIA; USO: FOTOPOLIMERIZACION, TIPO: COMPOSITE HIBRIDO, PRESENTACION: JERINGA X 4 GR | F106: UNIDAD | G106: 80 | H106: 1000 | I106: =+G106*H106 -> 80000 | J106: RESINA A3.5 JERINGA X 4 GR | M106: =+I106 -> 80000
A107: 98 | B107: 2.9.5-5514.12 | C107: PROD. MEDICO/FARMACEUTICOS/LAB | D107: 252 | E107: PASTAS P/ODONTOLOGIA; USO: FOTOPOLIMERIZACION, TIPO: COMPOSITE MICROHIBRIDO, PRESENTACION: JERINGA X 3 GR | F107: UNIDAD | G107: 40 | H107: 1300 | I107: =+G107*H107 -> 52000 | J107: RESINA FLOW A1 | M107: =+I107 -> 52000
A108: 99 | B108: 2.9.5-5514.12 | C108: PROD. MEDICO/FARMACEUTICOS/LAB | D108: 252 | E108: PASTAS P/ODONTOLOGIA; USO: FOTOPOLIMERIZACION, TIPO: COMPOSITE MICROHIBRIDO, PRESENTACION: JERINGA X 3 GR | F108: UNIDAD | G108: 50 | H108: 1300 | I108: =+G108*H108 -> 65000 | J108: RESINA FLOW A2 | M108: =+I108 -> 65000
A109: 100 | B109: 2.9.5-5514.12 | C109: PROD. MEDICO/FARMACEUTICOS/LAB | D109: 252 | E109: PASTAS P/ODONTOLOGIA; USO: FOTOPOLIMERIZACION, TIPO: COMPOSITE MICROHIBRIDO, PRESENTACION: JERINGA X 3 GR | F109: UNIDAD | G109: 50 | H109: 1300 | I109: =+G109*H109 -> 65000 | J109: RESINA FLOW A3 | M109: =+I109 -> 65000
A110: 101 | B110: 2.9.5-5514.22 | C110: PROD. MEDICO/FARMACEUTICOS/LAB | D110: 252 | E110: PASTAS P/ODONTOLOGIA; USO: OBTURACION, TIPO: GUTAPERCHA, PRESENTACION: ENVASE X 25 GR | F110: UNIDAD | G110: 30 | H110: 700 | I110: =+G110*H110 -> 21000 | J110: PASTAS P/ODONTOLOGIA; USO: OBTURACION, TIPO: GUTAPERCHA, PRESENTACION: ENVASE X 25 GR | M110: =+I110 -> 21000
A111: 102 | B111: 2.9.5-5514.7 | C111: PROD. MEDICO/FARMACEUTICOS/LAB | D111: 252 | E111: PASTAS P/ODONTOLOGIA; USO: P/LIMPIEZA, TIPO: SIN FLUOR, PRESENTACION: ENVASE X 45 GR | F111: UNIDAD | G111: 50 | H111: 1050 | I111: =+G111*H111 -> 52500 | J111: TIPO PASTA PROPHY NF | M111: =+I111 -> 52500
A112: 103 | B112: 2.9.5-472.4 | C112: PROD. MEDICO/FARMACEUTICOS/LAB | D112: 295 | E112: PINZAS DE CIRUGIA; TIPO: DISECCION SIN DIENTE, MEDIDA: 13 Cm | F112: UNIDAD | G112: 20 | H112: 400 | I112: =+G112*H112 -> 8000 | J112: PINZA DE DISECCION MANO IZQ | Q112: =+I112 -> 8000
A113: 104 | B113: 2.9.5-472.71 | C113: PROD. MEDICO/FARMACEUTICOS/LAB | D113: 295 | E113: PINZAS DE CIRUGIA; TIPO: PORTA AGUJA, MEDIDA: 15 Cm | F113: UNIDAD | G113: 8 | H113: 1000 | I113: =+G113*H113 -> 8000 | J113: PORTA AGUJA 15 cm | Q113: =+I113 -> 8000
A114: 105 | B114: 2.5.9-945.17 | C114: PROD. MEDICO/FARMACEUTICOS/LAB | D114: 259 | E114: PLACAS RADIOGRAFICAS; SENSIBILIDAD: AL VERDE, DIMENSION: 31 X 41 mm | F114: CAJA | G114: 100 | H114: 3500 | I114: =+G114*H114 -> 350000 | J114: PLACAS RADIOGRAFICAS; P/ODONTOLOGIA X 150 UNIDADES | O114: =+I114 -> 350000
A115: 106 | B115: 2.5.9-2402.6 | C115: PROD. MEDICO/FARMACEUTICOS/LAB | D115: 259 | E115: REVELADORES P/RADIOLOGIA; PRESENTACION: BOTELLA, CAPACIDAD: 480 mL, SENSIBILIDAD: AL VERDE, PROCESO: MANUAL, PROCESO DE UTILIZACION: MANUAL | F115: UNIDAD | G115: 250 | H115: 600 | I115: =+G115*H115 -> 150000 | J115: LIQUIDO REVELADOR T/ROMEK X 480 CC | O115: =+I115 -> 150000
A116: 107 | B116: 2.9.5-2496.26 | C116: PROD. MEDICO/FARMACEUTICOS/LAB | D116: 295 | E116: SUTURAS MECANICAS; TIPO: MONOFILAMENTO 4/0, USO: QUIRURGICO, PRESENTACION: CAJA POR 25 | F116: CAJA | G116: 50 | H116: 2000 | I116: =+G116*H116 -> 100000 | J116: SUTURAS 0/4 | Q116: =+I116 -> 100000
A117: 108 | B117: 2.9.5-2496.30 | C117: PROD. MEDICO/FARMACEUTICOS/LAB | D117: 295 | E117: SUTURAS MECANICAS; TIPO: MONOFILAMENTO NYLON 5.0, USO: QUIRURGICO, PRESENTACION: CAJA X 24 UN | F117: CAJA | G117: 50 | H117: 2000 | I117: =+G117*H117 -> 100000 | J117: SUTURAS 0/5 | Q117: =+I117 -> 100000
...

Sheet NP
A1: NOTA DE PEDIDO | J1: N° | K1: XX/2022
A3: JURISDICCIÓN: | D3: ='SAF 011'!C4 -> 040 - MINISTERIO DE SALUD
A4: SAF: | D4: ='SAF 011'!C5 -> 011 - DIRECCION PROVINCIAL DE ADMINISTRACION - MINISTERIO DE SALUD
A5: UNIDAD EJECUTORA: | D5: 470 - DIRECCION PROVINCIAL DE ODONTOLOGIA
A6: DEPENDENCIA SOLICITANTE: | D6: 470 - DIRECCION PROVINCIAL DE ODONTOLOGIA
A7: PERIODO UTILIZACIÓN: | D7: TRES (3) MESES
A8: OBJETO: | D8: ADQ. RUBRO INSUMOS PARA ODONTOLOGIA
A10: Ítem | B10: Codigo Item | C10: DESCRIPCIÓN | H10: Adjunta Detalle Técnico | I10: Unidad Medida | J10: Precio Unitario Estimado | K10: Cantidad Solicitada
A12: 1 | B12: ='SAF 011'!B10 -> 2.5.6-7104.276 | C12: ='SAF 011'!E10 -> ACEITES LUBRICANTES; USO: MAQUINA, PRESENTACION: AEROSOL X 400 CM3, NORMA: MULTIUSO | H12: NO | I12: ='SAF 011'!F10 -> UNIDAD | J12: ='SAF 011'!H10 -> 700 | K12: ='SAF 011'!G10 -> 150
A13: 2 | B13: ='SAF 011'!B11 -> 2.5.2-3204.13 | C13: ='SAF 011'!E11 -> ACIDO GRABADOR ODONTOLOG.; ESTADO: GEL, PRESENTACION: JERINGA X 12 GR, CAPACIDAD: 12 GR | H13: SI | I13: ='SAF 011'!F11 -> UNIDAD | J13: ='SAF 011'!H11 -> 700 | K13: ='SAF 011'!G11 -> 300
A14: 3 | B14: ='SAF 011'!B12 -> 2.5.2-2327.29 | C14: ='SAF 011'!E12 -> ACRILICOS AUTOCURABLES; TIPO: POLIMERO DE AUTOPOLIMERIZACION, PRESENTACION: FRASCO X 1 Kg | H14: SI | I14: ='SAF 011'!F12 -> UNIDAD | J14: ='SAF 011'!H12 -> 5500 | K14: ='SAF 011'!G12 -> 6
A15: 4 | B15: ='SAF 011'!B13 -> 2.5.2-6021.4 | C15: ='SAF 011'!E13 -> ACRILICOS TERMOCURABLES; TIPO: POLIMERO, PRESENTACION: ENVASE X 1 Kg | H15: SI | I15: ='SAF 011'!F13 -> UNIDAD | J15: ='SAF 011'!H13 -> 5500 | K15: ='SAF 011'!G13 -> 15
A16: 5 | B16: ='SAF 011'!B14 -> 2.5.2-5538.8 | C16: ='SAF 011'!E14 -> ADHESIVOS P/ODONTOLOGIA; PRESENTACION: FRASCO X 4,5 mm, TIPO: ADHESIVO+PRIMER, USO: ODONTOLOGICO | H16: NO | I16: ='SAF 011'!F14 -> UNIDAD | J16: ='SAF 011'!H14 -> 1500 | K16: ='SAF 011'!G14 -> 200
A17: 6 | B17: ='SAF 011'!B15 -> 2.9.5-441.82 | C17: ='SAF 011'!E15 -> AGUJAS QUIRURGICAS; TIPO: CARPULE, ESPECIFICACION: CORTA, UNIDAD VENTA: CAJA X 100, PRESENTACION: CAJA X 100 | H17: SI | I17: ='SAF 011'!F15 -> CAJA | J17: ='SAF 011'!H15 -> 900 | K17: ='SAF 011'!G15 -> 200
A18: 7 | B18: ='SAF 011'!B16 -> 2.9.5-441.428 | C18: ='SAF 011'!E16 -> AGUJAS QUIRURGICAS; TIPO: CARPULE, ESPECIFICACION: EXTRA CORTAS, PRESENTACION: ENVASE X 100 UN | H18: SI | I18: ='SAF 011'!F16 -> CAJA | J18: ='SAF 011'!H16 -> 900 | K18: ='SAF 011'!G16 -> 40
A19: 8 | B19: ='SAF 011'!B17 -> 2.9.5-441.119 | C19: ='SAF 011'!E17 -> AGUJAS QUIRURGICAS; TIPO: CARPULE, ESPECIFICACION: LARGA, PRESENTACION: CAJA X 100, UNIDAD VENTA: CAJA X 100 | H19: SI | I19: ='SAF 011'!F17 -> CAJA | J19: ='SAF 011'!H17 -> 900 | K19: ='SAF 011'!G17 -> 40
A20: 9 | B20: ='SAF 011'!B18 -> 2.9.5-470.29 | C20: ='SAF 011'!E18 -> ALGODONES; TIPO: ESTERIL, CAPACIDAD: PAQUETE X 500 ROLLOS, PRESENTACION: ENVASE X 500 | H20: SI | I20: ='SAF 011'!F18 -> BOLSA | J20: ='SAF 011'!H18 -> 700 | K20: ='SAF 011'!G18 -> 50
A21: 10 | B21: ='SAF 011'!B19 -> 2.5.2-1883.135 | C21: ='SAF 011'!E19 -> ANESTESICOS LOCALES; TIPO: MONODROGA, DROGA GENERICA: LIDOCAINA 5%, FORMA FARMACEUTICA: GEL, PRESENTACION: ENVASE X 18 GR | H21: SI | I21: ='SAF 011'!F19 -> UNIDAD | J21: ='SAF 011'!H19 -> 1800 | K21: ='SAF 011'!G19 -> 50
A22: 11 | B22: ='SAF 011'!B20 -> 2.5.2-1883.37 | C22: ='SAF 011'!E20 -> ANESTESICOS LOCALES; TIPO: SIN VALOR, DROGA GENERICA: CLORHIDRATO DE CARTICAINA 4%, FORMA FARMACEUTICA: ANESTUBO CARPULE, PRESENTACION: CAJA X 50 UN | H22: NO | I22: ='SAF 011'!F20 -> CAJA | J22: ='SAF 011'!H20 -> 4500 | K22: ='SAF 011'!G20 -> 1440
A23: 12 | B23: ='SAF 011'!B21 -> 2.5.2-1723.59 | C23: ='SAF 011'!E21 -> ANTISEPTICOS LOCALES P/PERSONA; TIPO: MONODROGA, DROGA GENERICA: EDTAC, FORMA FARMACEUTICA: SOLUCION, PRESENTACION: FRASCO X 20 mL | H23: NO | I23: ='SAF 011'!F21 -> UNIDAD | J23: ='SAF 011'!H21 -> 400 | K23: ='SAF 011'!G21 -> 20
... A124: 113 | B124: ='SAF 011'!B122 -> 2.5.2-9146.8 | C124: ='SAF 011'!E122 -> YESOS; TIPO: TALLER, PRESENTACION: ENVASE X 25 Kg | H124: SI | I124: ='SAF 011'!F122 -> UNIDAD | J124: ='SAF 011'!H122 -> 2000 | K124: ='SAF 011'!G122 -> 12
A125: Costo total estimado: PESOS DOCE MILLONES OCHOCIENTOS CINCUENTA Y SEIS MIL TRESCIENTOS CON 00/100.- | J125: =SUMPRODUCT(J12:J124,K12:K124) -> 12856300

Sheet APG
A1: EJERCICIO: | D1: 2022 | P1: AUTORIZACION PARA GASTAR
A4: JURISDICCIÓN: | G4: =NP!D3 -> 040 - MINISTERIO DE SALUD
A5: SAF: | G5: =NP!D4 -> 011 - DIRECCION PROVINCIAL DE ADMINISTRACION - MINISTERIO DE SALUD
A6: UNIDAD EJECUTORA: | G6: =NP!D5 -> 470 - DIRECCION PROVINCIAL DE ODONTOLOGIA
A7: DEPENDENCIA SOLICITANTE: | G7: =NP!D6 -> 470 - DIRECCION PROVINCIAL DE ODONTOLOGIA
A8: AUTORIZACIÓN:
A9: Señor Director de Administración o Titular del Servicio Administrativo Financiero:
A10: Autorizo la realización de los trámites correspondientes, a fin de proveer a este Organismo los bienes que se detallan en Nota de Pedido N°....... , afectando la erogación resultante a los créditos presupuestarios aprobados a favor de esta Unidad Ejecutora, conforme al siguiente detalle:
A12: IMPUTACIÓN PRESUPUESTARIA
A13: CÓDIGO | O13: DENOMINACIÓN DE LA PARTIDA PRESUPUESTARIA | Q13: IMPORTE
A14: PR | B14: SB | C14: PY | D14: AC | E14: OB | F14: UG | G14: FIN | H14: FUN | I14: I | J14: P | K14: P | L14: SubP | M14: M | N14: FF
A15: 29 | D15: 1 | F15: 4901 | G15: 3 | H15: 1 | I15: 2 | J15: 2 | K15: 2 | M15: 1 | N15: 1.1 | O15: PRENDAS DE VESTIR | Q15: ='SAF 011'!L123 -> 140000
A16: 29 | D16: 1 | F16: 4901 | G16: 3 | H16: 1 | I16: 2 | J16: 5 | K16: 2 | M16: 1 | N16: 1.1 | O16: PRODUCTOS FARMACEUTICOS Y MEDICINALES | Q16: ='SAF 011'!M123 -> 8663500
A17: 29 | D17: 1 | F17: 4901 | G17: 3 | H17: 1 | I17: 2 | J17: 5 | K17: 6 | M17: 1 | N17: 1.1 | O17: COMBUSTIBLES Y LUBRICANTES | Q17: ='SAF 011'!N123 -> 105000
A18: 29 | D18: 1 | F18: 4901 | G18: 3 | H18: 1 | I18: 2 | J18: 5 | K18: 9 | M18: 1 | N18: 1.1 | O18: OTROS NEP | Q18: ='SAF 011'!O123 -> 570000
A19: 29 | D19: 1 | F19: 4901 | G19: 3 | H19: 1 | I19: 2 | J19: 6 | K19: 5 | M19: 1 | N19: 1.1 | O19: CEMENTO, CAL Y YESO | Q19: ='SAF 011'!P123 -> 53600
A20: 29 | D20: 1 | F20: 4901 | G20: 3 | H20: 1 | I20: 2 | J20: 9 | K20: 5 | M20: 1 | N20: 1.1 | O20: UTILES MENORES MEDICOS, QUIRURGICOS Y DE LABORATORIO | Q20: ='SAF 011'!Q123 -> 3324200
A38: TOTAL DE PESOS: DOCE MILLONES OCHOCIENTOS CINCUENTA Y SEIS MIL TRESCIENTOS CON 00/100.- | Q38: =SUM(Q15:Q37) -> 12856300
A40: JUSTIFICACIÓN:
A41: =NP!D8 -> ADQ. RUBRO INSUMOS PARA ODONTOLOGIA
