Workbook

Sheet Necesidades Trimestrales
B2: Pedido de Necesidades Trimestrales
A4: JURISDICCION: | C4: 040 - MINISTERIO DE SALUD
A5: SAF N°: | C5: 011 - DIRECCION PROVINCIAL DE ADMINISTRACION - MS
A6: EJERCICIO: | C6: 2022
A7: TRIMESTRE: | C7: 2
A9: ID | B9: CODIGO ITEM | C9: RUBRO DE COMPRA | D9: I.P.P. | E9: DESCRIPCION | F9: UNIDAD DE MEDIDA | G9: CANTIDAD | H9: PRECIO UNITARIO ESTIMADO | I9: IMPORTE TOTAL ESTIMADO
A10: 1 | B10: 2.5.2-1875.133 | C10: PROD. MEDICO/FARMACEUTICOS/LAB | D10: 252 | E10: ANTIASMATICO BRONCODILATADOR; TIPO: MONODROGA, DROGA GENERICA: N-ACETIL CISTEINA 600 MGR, FORMA FARMACEUTICA: TABLETA EFERVESCENTE, PRESENTACION: UNIDAD | F10: TABLETAS | G10: 1000 | H10: 113.3 | I10: =+G10*H10 -> 113300
A11: 2 | B11: 2.5.2-1829.25 | C11: PROD. MEDICO/FARMACEUTICOS/LAB | D11: 252 | E11: ANTIVIRALES; TIPO: MONODROGA, DROGA GENERICA: ACICLOVIR 5 %, FORMA FARMACEUTICA: CREMA, PRESENTACION: ENVASE X 5 GR | F11: ENVASE | G11: 100 | H11: 641.47 | I11: =+G11*H11 -> 64147
A12: 3 | B12: 2.5.2-1875.74 | C12: PROD. MEDICO/FARMACEUTICOS/LAB | D12: 252 | E12: ANTIASMATICO BRONCODILATADOR; TIPO: MONODROGA, DROGA GENERICA: AMINOFILINA 240MGR, FORMA FARMACEUTICA: AMPOLLA, PRESENTACION: ENVASE X 10 ML | F12: AMPOLLA | G12: 1200 | H12: 86 | I12: =+G12*H12 -> 103200
A13: 4 | B13: 2.9.5-427.39 | C13: PROD. MEDICO/FARMACEUTICOS/LAB | D13: 252 | E13: APOSITOS; TIPO: HIDROCOLOIDE, TAMAÑO: 10 X 10 Cm | F13: UNIDAD | G13: 100 | H13: 380 | I13: =+G13*H13 -> 38000
A14: 5 | B14: 2.5.2-1855.83 | C14: PROD. MEDICO/FARMACEUTICOS/LAB | D14: 252 | E14: CORTICOESTEROIDES; TIPO: ASOCIACION, DROGA GENERICA: BETAMETASONA ACETATO+FOSFATO, FORMA FARMACEUTICA: AMPOLLA, PRESENTACION: ENVASE X 2 mL | F14: AMPOLLA | G14: 20500 | H14: 447 | I14: =+G14*H14 -> 9163500
A15: 6 | B15: 2.5.2-1875.134 | C15: PROD. MEDICO/FARMACEUTICOS/LAB | D15: 252 | E15: ANTIASMATICO BRONCODILATADOR; TIPO: MONODROGA, DROGA GENERICA: BUDESONIDE 200 µGR, FORMA FARMACEUTICA: AEROSOL, PRESENTACION: 100 DOSIS | F15: UNIDAD | G15: 3000 | H15: 659 | I15: =+G15*H15 -> 1977000
A16: 7 | B16: 2.5.2-2476.50 | C16: PROD. MEDICO/FARMACEUTICOS/LAB | D16: 252 | E16: ANTIALERGICOS-ANTIHISTAMINICOS; TIPO: MONODROGA, DROGA GENERICA: BUDESONIDA 1 MG/ML, FORMA FARMACEUTICA: GOTAS, PRESENTACION: ENVASE X 20 mL | F16: ENVASE | G16: 100 | H16: 327 | I16: =+G16*H16 -> 32700
A17: 8 | B17: 2.5.2-1902.14 | C17: PROD. MEDICO/FARMACEUTICOS/LAB | D17: 252 | E17: DROGAS UTERINAS; TIPO: MONODROGA, DROGA GENERICA: CARBETOCIN 100 MCG, FORMA FARMACEUTICA: AMPOLLA, PRESENTACION: UNIDAD | F17: AMPOLLA | G17: 15 | H17: 5090 | I17: =+G17*H17 -> 76350
A18: 9 | B18: 2.5.2-1855.7 | C18: PROD. MEDICO/FARMACEUTICOS/LAB | D18: 252 | E18: CORTICOESTEROIDES; TIPO: MONODROGA, DROGA GENERICA: DEXAMETASONA, FORMA FARMACEUTICA: AMPOLLA, PRESENTACION: 8 mGr | F18: AMPOLLA | G18: 90400 | H18: 45 | I18: =+G18*H18 -> 4068000
A19: 10 | B19: 2.5.2-2476.74 | C19: PROD. MEDICO/FARMACEUTICOS/LAB | D19: 252 | E19: ANTIALERGICOS-ANTIHISTAMINICOS; TIPO: MONODROGA, DROGA GENERICA: DIFENHIDRAMINA 250 MG, FORMA FARMACEUTICA: JARABE, PRESENTACION: FRASCO X 120 mL | F19: FRASCO | G19: 20000 | H19: 139 | I19: =+G19*H19 -> 2780000
A20: 11 | B20: 2.5.2-2476.36 | C20: PROD. MEDICO/FARMACEUTICOS/LAB | D20: 252 | E20: ANTIALERGICOS-ANTIHISTAMINICOS; TIPO: MONODROGA, DROGA GENERICA: DIFENHIDRAMINA, FORMA FARMACEUTICA: COMPRIMIDO, PRESENTACION: 50 mGr | F20: COMPRIMIDO | G20: 30000 | H20: 4.65 | I20: =+G20*H20 -> 139500
A21: 12 | B21: 2.5.2-2476.44 | C21: PROD. MEDICO/FARMACEUTICOS/LAB | D21: 252 | E21: ANTIALERGICOS-ANTIHISTAMINICOS; TIPO: MONODROGA, DROGA GENERICA: DIFENHIDRAMINA, FORMA FARMACEUTICA: AMPOLLA, PRESENTACION: 10 mGr | F21: AMPOLLA | G21: 35000 | H21: 55 | I21: =+G21*H21 -> 1925000
... A40: 31 | B40: 2.5.2-2481.3 | C40: PROD. MEDICO/FARMACEUTICOS/LAB | D40: 252 | E40: LAXANTES; TIPO: MONODROGA, DROGA GENERICA: VASELINA, FORMA FARMACEUTICA: SOLIDO, PRESENTACION: 1000 GR | F40: UNIDAD | G40: 100 | H40: 1260 | I40: =+G40*H40 -> 126000
A41: TOTAL RUBRO | I41: =SUM(I10:I40) -> 39538492
C43: DETALLE TECNICO Y ESPECIFICACIONES | D43: ANEXO 1-Para oferentes de la Provincia de Catamarca deberán presentar Habilitación Provincial para comercializar el producto que cotizan. 2-Para el resto de oferentes deberán presentar Certificado de Inscripción de ANMAT vigente al momento de la oferta, el mismo deberá ser correspondiente al objeto de la contratación y de encontrarse vencido adjuntar la solicitud de renovación. 3-No se aceptarán ofertas de productos no registrados y autorizada su venta por ANMAT. Se deberá especificar en cada ítem de la propuesta, marca y número de certificado otorgado por dicho ente regulador. 4-Los productos deberán tener un vencimiento posterior a doce (12) meses a partir de la fecha de su recepción.
C45: Plazos de entrega | D45: veinte (20) dias habiles
C47: Lugar de Entrega: | D47: ITEM 1, 2, 3, 4, 5 (20.000 un.), 6, 7, 9 (90.000 un.), 10, 11, 12, 13, 14, 15 (2.000 un.), 16, 17 (3.000 un.), 18, 19, 20, 22, 23, 24, 25, 26, 27, 28, 29, 30, 31 - DIR. PROV. DE FARMACIA - CHACABUCO N° 169 - en el horario de 8:00hs a 12:00hs de lunes a viernes
D48: ITEM 9 (400 un.), 15 (400 un.) - DIR. PROV. SAME - CASEROS N° 864 - en el horario de 8:00hs a 12:00hs de lunes a viernes
D49: ITEM 5 (500 un.), 8, 13 (100 un.), 17 (500 un.), 21 - DIR. PROV. MATERNIDAD, INFANCIA Y ADOLESCENCIA - CHACABUCO N° 169 - en el horario de 8:00hs a 12:00hs de lunes a viernes
C51: Calidad Minima esperada
C53: Mantenimiento | D53: cuarenta y cinco (45) días
B57: Especificidades:
B59: Ítem 29: Con AEROCAMARA
B61: Lugar de Entrega: D.P. DE FARMACIA E INSUMOS DE 08:00 A 12:00HS., DEBIENDO CORRER LOS GASTOS DE FLETES, ACARREO, CARGA, DESCARGA Y SEGURO A CARGO DEL ADJUDICATARIO.
B62: Plazo de entrega: VEINTE (20) DIAS HABILES
B63: Calidad Minima esperada:
B64: Mantenimiento: 45 dias habiles

Sheet  NotaPedido DPFARMACIA
A1: NOTA DE PEDIDO | J1: N° | K1: 17/2022
A3: JURISDICCIÓN: | C3: ='Necesidades Trimestrales'!C4 -> 040 - MINISTERIO DE SALUD
A4: SAF: | C4: ='Necesidades Trimestrales'!C5 -> 011 - DIRECCION PROVINCIAL DE ADMINISTRACION - MS
A5: UNIDAD EJECUTORA: | C5: 469 - DIRECCION PROVINCIAL DE FARMACIA E INSUMOS
A6: DEPENDENCIA SOLICITANTE: | C6: 469 - DIRECCION PROVINCIAL DE FARMACIA E INSUMOS
A7: PERIODO UTILIZACIÓN: | C7: Cuatrimestral
A8: OBJETO: | C8: Adquisición de TERAPIA DERMATOLOGICA/SISTEMA GENITOURINARIO Y HORMONAS SEXUALES /HORMONAS SISTEMICAS /CORTICOIDES SISTEMICOS/RESPIRATORIO/ANTIHISTAMINICOS
A10: Ítem | B10: CODIGO ITEM | C10: DESCRIPCIÓN | H10: Adjunta Detalle Técnico | I10: Unidad Medida | J10: Precio Unitario Estimado | K10: Cantidad Solicitada
A12: 1 | B12: =+'Necesidades Trimestrales'!B10 -> 2.5.2-1875.133 | C12: =+'Necesidades Trimestrales'!E10 -> ANTIASMATICO BRONCODILATADOR; TIPO: MONODROGA, DROGA GENERICA: N-ACETIL CISTEINA 600 MGR, FORMA FARMACEUTICA: TABLETA EFERVESCENTE, PRESENTACION: UNIDAD | H12: NO | I12: =+'Necesidades Trimestrales'!F10 -> TABLETAS | J12: =+'Necesidades Trimestrales'!H10 -> 113.3 | K12: ='Necesidades Trimestrales'!#REF! -> #REF!
A13: 2 | B13: =+'Necesidades Trimestrales'!B11 -> 2.5.2-1829.25 | C13: =+'Necesidades Trimestrales'!E11 -> ANTIVIRALES; TIPO: MONODROGA, DROGA GENERICA: ACICLOVIR 5 %, FORMA FARMACEUTICA: CREMA, PRESENTACION: ENVASE X 5 GR | H13: NO | I13: =+'Necesidades Trimestrales'!F11 -> ENVASE | J13: =+'Necesidades Trimestrales'!H11 -> 641.47 | K13: ='Necesidades Trimestrales'!#REF! -> #REF!
A14: 3 | B14: =+'Necesidades Trimestrales'!B12 -> 2.5.2-1875.74 | C14: =+'Necesidades Trimestrales'!E12 -> ANTIASMATICO BRONCODILATADOR; TIPO: MONODROGA, DROGA GENERICA: AMINOFILINA 240MGR, FORMA FARMACEUTICA: AMPOLLA, PRESENTACION: ENVASE X 10 ML | H14: NO | I14: =+'Necesidades Trimestrales'!F12 -> AMPOLLA | J14: =+'Necesidades Trimestrales'!H12 -> 86 | K14: ='Necesidades Trimestrales'!#REF! -> #REF!
A15: 4 | B15: =+'Necesidades Trimestrales'!B13 -> 2.9.5-427.39 | C15: =+'Necesidades Trimestrales'!E13 -> APOSITOS; TIPO: HIDROCOLOIDE, TAMAÑO: 10 X 10 Cm | H15: NO | I15: =+'Necesidades Trimestrales'!F13 -> UNIDAD | J15: =+'Necesidades Trimestrales'!H13 -> 380 | K15: ='Necesidades Trimestrales'!#REF! -> #REF!
A16: 5 | B16: =+'Necesidades Trimestrales'!B14 -> 2.5.2-1855.83 | C16: =+'Necesidades Trimestrales'!E14 -> CORTICOESTEROIDES; TIPO: ASOCIACION, DROGA GENERICA: BETAMETASONA ACETATO+FOSFATO, FORMA FARMACEUTICA: AMPOLLA, PRESENTACION: ENVASE X 2 mL | H16: NO | I16: =+'Necesidades Trimestrales'!F14 -> AMPOLLA | J16: =+'Necesidades Trimestrales'!H14 -> 447 | K16: ='Necesidades Trimestrales'!#REF! -> #REF!
A17: 6 | B17: =+'Necesidades Trimestrales'!B15 -> 2.5.2-1875.134 | C17: =+'Necesidades Trimestrales'!E15 -> ANTIASMATICO BRONCODILATADOR; TIPO: MONODROGA, DROGA GENERICA: BUDESONIDE 200 µGR, FORMA FARMACEUTICA: AEROSOL, PRESENTACION: 100 DOSIS | H17: NO | I17: =+'Necesidades Trimestrales'!F15 -> UNIDAD | J17: =+'Necesidades Trimestrales'!H15 -> 659 | K17: ='Necesidades Trimestrales'!#REF! -> #REF!
A18: 7 | B18: =+'Necesidades Trimestrales'!B16 -> 2.5.2-2476.50 | C18: =+'Necesidades Trimestrales'!E16 -> ANTIALERGICOS-ANTIHISTAMINICOS; TIPO: MONODROGA, DROGA GENERICA: BUDESONIDA 1 MG/ML, FORMA FARMACEUTICA: GOTAS, PRESENTACION: ENVASE X 20 mL | H18: NO | I18: =+'Necesidades Trimestrales'!F16 -> ENVASE | J18: =+'Necesidades Trimestrales'!H16 -> 327 | K18: ='Necesidades Trimestrales'!#REF! -> #REF!
A19: 8 | B19: =+'Necesidades Trimestrales'!B18 -> 2.5.2-1855.7 | C19: =+'Necesidades Trimestrales'!E18 -> CORTICOESTEROIDES; TIPO: MONODROGA, DROGA GENERICA: DEXAMETASONA, FORMA FARMACEUTICA: AMPOLLA, PRESENTACION: 8 mGr | H19: NO | I19: =+'Necesidades Trimestrales'!F18 -> AMPOLLA | J19: =+'Necesidades Trimestrales'!H18 -> 45 | K19: ='Necesidades Trimestrales'!#REF! -> #REF!
A20: 9 | B20: =+'Necesidades Trimestrales'!B19 -> 2.5.2-2476.74 | C20: =+'Necesidades Trimestrales'!E19 -> ANTIALERGICOS-ANTIHISTAMINICOS; TIPO: MONODROGA, DROGA GENERICA: DIFENHIDRAMINA 250 MG, FORMA FARMACEUTICA: JARABE, PRESENTACION: FRASCO X 120 mL | H20: NO | I20: =+'Necesidades Trimestrales'!F19 -> FRASCO | J20: =+'Necesidades Trimestrales'!H19 -> 139 | K20: ='Necesidades Trimestrales'!#REF! -> #REF!
A21: 10 | B21: =+'Necesidades Trimestrales'!B20 -> 2.5.2-2476.36 | C21: =+'Necesidades Trimestrales'!E20 -> ANTIALERGICOS-ANTIHISTAMINICOS; TIPO: MONODROGA, DROGA GENERICA: DIFENHIDRAMINA, FORMA FARMACEUTICA: COMPRIMIDO, PRESENTACION: 50 mGr | H21: NO | I21: =+'Necesidades Trimestrales'!F20 -> COMPRIMIDO | J21: =+'Necesidades Trimestrales'!H20 -> 4.65 | K21: ='Necesidades Trimestrales'!#REF! -> #REF!
A22: 11 | B22: =+'Necesidades Trimestrales'!B21 -> 2.5.2-2476.44 | C22: =+'Necesidades Trimestrales'!E21 -> ANTIALERGICOS-ANTIHISTAMINICOS; TIPO: MONODROGA, DROGA GENERICA: DIFENHIDRAMINA, FORMA FARMACEUTICA: AMPOLLA, PRESENTACION: 10 mGr | H22: NO | I22: =+'Necesidades Trimestrales'!F21 -> AMPOLLA | J22: =+'Necesidades Trimestrales'!H21 -> 55 | K22: ='Necesidades Trimestrales'!#REF! -> #REF!
A23: 12 | B23: =+'Necesidades Trimestrales'!B22 -> 2.5.2-1853.4 | C23: =+'Necesidades Trimestrales'!E22 -> OCITOCICOS; TIPO: MONODROGA, DROGA GENERICA: ERGONOVINA, PRESENTACION: 0.2 mGr, FORMA FARMACEUTICA: AMPOLLAS | H23: NO | I23: =+'Necesidades Trimestrales'!F22 -> AMPOLLA | J23: =+'Necesidades Trimestrales'!H22 -> 57.8 | K23: ='Necesidades Trimestrales'!#REF! -> #REF!
A24: 13 | B24: =+'Necesidades Trimestrales'!B23 -> 2.5.2-1855.47 | C24: =+'Necesidades Trimestrales'!E23 -> CORTICOESTEROIDES; TIPO: MONODROGA, DROGA GENERICA: HIDROCORTISONA, FORMA FARMACEUTICA: AMPOLLA/FRASCO, PRESENTACION: 100 mGr | H24: NO | I24: =+'Necesidades Trimestrales'!F23 -> AMPOLLA | J24: =+'Necesidades Trimestrales'!H23 -> 120 | K24: ='Necesidades Trimestrales'!#REF! -> #REF!
A25: 14 | B25: =+'Necesidades Trimestrales'!B24 -> 2.5.2-1855.77 | C25: =+'Necesidades Trimestrales'!E24 -> CORTICOESTEROIDES; TIPO: MONODROGA, DROGA GENERICA: HIDROCORTISONA, FORMA FARMACEUTICA: FRASCO AMPOLLA, PRESENTACION: ENVASE X 500 mGr | H25: NO | I25: =+'Necesidades Trimestrales'!F24 -> AMPOLLA | J25: =+'Necesidades Trimestrales'!H24 -> 222 | K25: ='Necesidades Trimestrales'!#REF! -> #REF!
A26: 15 | B26: =+'Necesidades Trimestrales'!B25 -> 2.5.2-1875.9 | C26: =+'Necesidades Trimestrales'!E25 -> ANTIASMATICO BRONCODILATADOR; TIPO: MONODROGA, DROGA GENERICA: BROMURO DE IPRATROPIO, FORMA FARMACEUTICA: SOLUCION, PRESENTACION: 20 mL | H26: NO | I26: =+'Necesidades Trimestrales'!F25 -> GOTERO | J26: =+'Necesidades Trimestrales'!H25 -> 98 | K26: ='Necesidades Trimestrales'!#REF! -> #REF!
A27: 16 | B27: =+'Necesidades Trimestrales'!B26 -> 2.5.2-1902.10 | C27: =+'Necesidades Trimestrales'!E26 -> DROGAS UTERINAS; TIPO: MONODROGA, DROGA GENERICA: ISOXUPRINA 10 mGr, FORMA FARMACEUTICA: AMPOLLA, PRESENTACION: UNIDAD | H27: NO | I27: =+'Necesidades Trimestrales'!F26 -> AMPOLLA | J27: =+'Necesidades Trimestrales'!H26 -> 45 | K27: ='Necesidades Trimestrales'!#REF! -> #REF!
A28: 17 | B28: =+'Necesidades Trimestrales'!B27 -> 2.5.2-9051.3 | C28: =+'Necesidades Trimestrales'!E27 -> LINIMENTOS; NOMBRE DEL PRODUCTO: OLEO CALCAREO, CALIDAD: MEDICINAL, PRESENTACION: ENVASE X 250 CM3 | H28: NO | I28: =+'Necesidades Trimestrales'!F27 -> UNIDAD | J28: =+'Necesidades Trimestrales'!H27 -> 364 | K28: ='Necesidades Trimestrales'!#REF! -> #REF!
A29: 18 | B29: =+'Necesidades Trimestrales'!B28 -> 2.5.2-2476.12 | C29: =+'Necesidades Trimestrales'!E28 -> ANTIALERGICOS-ANTIHISTAMINICOS; TIPO: MONODROGA, DROGA GENERICA: LORATADINA, FORMA FARMACEUTICA: COMPRIMIDO, PRESENTACION: 10 mGr | H29: NO | I29: =+'Necesidades Trimestrales'!F28 -> COMPRIMIDO | J29: =+'Necesidades Trimestrales'!H28 -> 2.99 | K29: ='Necesidades Trimestrales'!#REF! -> #REF!
A30: 19 | B30: =+'Necesidades Trimestrales'!B29 -> 2.5.2-2476.3 | C30: =+'Necesidades Trimestrales'!E29 -> ANTIALERGICOS-ANTIHISTAMINICOS; TIPO: ASOCIACION, DROGA GENERICA: LORATADINA, FORMA FARMACEUTICA: JARABE, PRESENTACION: 60 mL | H30: NO | I30: =+'Necesidades Trimestrales'!F29 -> FRASCO | J30: =+'Necesidades Trimestrales'!H29 -> 230 | K30: ='Necesidades Trimestrales'!#REF! -> #REF!
A31: 20 | B31: =+'Necesidades Trimestrales'!B31 -> 2.5.2-2200.4 | C31: =+'Necesidades Trimestrales'!E31 -> CORTICOIDES; DROGA GENERICA: MEPREDNISONA, FORMA FARMACEUTICA: COMPRIMIDO, PRESENTACION: 4 mGr, TIPO: MONODROGA | H31: NO | I31: =+'Necesidades Trimestrales'!F31 -> COMPRIMIDO | J31: =+'Necesidades Trimestrales'!H31 -> 9.8 | K31: ='Necesidades Trimestrales'!#REF! -> #REF!
A32: 21 | B32: =+'Necesidades Trimestrales'!B32 -> 2.5.2-2200.41 | C32: =+'Necesidades Trimestrales'!E32 -> CORTICOIDES; DROGA GENÉRICA: MEPREDNISONA 4 ML/MG, FORMA FARMACEÚTICA: GOTAS | H32: NO | I32: =+'Necesidades Trimestrales'!F32 -> GOTERO | J32: =+'Necesidades Trimestrales'!H32 -> 315 | K32: ='Necesidades Trimestrales'!#REF! -> #REF!
A33: 22 | B33: =+'Necesidades Trimestrales'!B33 -> 2.5.2-2200.19 | C33: =+'Necesidades Trimestrales'!E33 -> CORTICOIDES; DROGA GENERICA: MEPREDNISONA, FORMA FARMACEUTICA: COMPRIMIDO, PRESENTACION: 40 mGr, TIPO: MONODROGA | H33: NO | I33: =+'Necesidades Trimestrales'!F33 -> COMPRIMIDO | J33: =+'Necesidades Trimestrales'!H33 -> 45 | K33: ='Necesidades Trimestrales'!#REF! -> #REF!
A34: 23 | B34: =+'Necesidades Trimestrales'!B34 -> 2.5.2-1855.105 | C34: =+'Necesidades Trimestrales'!E34 -> CORTICOESTEROIDES; TIPO: MONODROGA, DROGA GENERICA: MEPREDNISONA 8 mGr, FORMA FARMACEUTICA: COMPRIMIDO, PRESENTACION: UNIDAD | H34: NO | I34: =+'Necesidades Trimestrales'!F34 -> COMPRIMIDO | J34: =+'Necesidades Trimestrales'!H34 -> 17.35 | K34: ='Necesidades Trimestrales'!#REF! -> #REF!
A35: 24 | B35: =+'Necesidades Trimestrales'!B35 -> 2.5.2-1821.487 | C35: =+'Necesidades Trimestrales'!E35 -> ANTIBIOTICOS P/PERSONAS; TIPO: MONODROGA, DROGA GENERICA: METRONIDAZOL, FORMA FARMACEUTICA: OVULO, PRESENTACION: UNIDAD | H35: NO | I35: =+'Necesidades Trimestrales'!F35 -> UNIDAD | J35: =+'Necesidades Trimestrales'!H35 -> 47.24 | K35: ='Necesidades Trimestrales'!#REF! -> #REF!
A36: 25 | B36: =+'Necesidades Trimestrales'!B36 -> 2.5.2-1723.122 | C36: =+'Necesidades Trimestrales'!E36 -> ANTISEPTICOS LOCALES P/PERSONA; TIPO: MONODROGA, DROGA GENERICA: NITROFURAZONA, FORMA FARMACEUTICA: APOSITO, PRESENTACION: ENVASE X 20 UN | H36: NO | I36: =+'Necesidades Trimestrales'!F36 -> CAJA | J36: =+'Necesidades Trimestrales'!H36 -> 663 | K36: ='Necesidades Trimestrales'!#REF! -> #REF!
A37: 26 | B37: =+'Necesidades Trimestrales'!B37 -> 2.5.2-1853.2 | C37: =+'Necesidades Trimestrales'!E37 -> OCITOCICOS; TIPO: MONODROGA, DROGA GENERICA: OXITOCINA SINTÉTICA, PRESENTACION: 10 UI, FORMA FARMACEUTICA: AMPOLLA | H37: NO | I37: =+'Necesidades Trimestrales'!F37 -> AMPOLLA | J37: =+'Necesidades Trimestrales'!H37 -> 45 | K37: ='Necesidades Trimestrales'!#REF! -> #REF!
A38: 27 | B38: =+'Necesidades Trimestrales'!B38 -> 2.5.2-1875.55 | C38: =+'Necesidades Trimestrales'!E38 -> ANTIASMATICO BRONCODILATADOR; TIPO: MONODROGA, DROGA GENERICA: SALBUTAMOL, FORMA FARMACEUTICA: AEROSOL, PRESENTACION: 250 DOSIS | H38: SI | I38: =+'Necesidades Trimestrales'!F38 -> UNIDAD | J38: =+'Necesidades Trimestrales'!H38 -> 580 | K38: ='Necesidades Trimestrales'!#REF! -> #REF!
A39: 28 | B39: =+'Necesidades Trimestrales'!B39 -> 2.5.2-1883.189 | C39: =+'Necesidades Trimestrales'!E39 -> ANESTÉSICOS LOCALES; TIPO: ANALGÉSICO LOCAL Y ANTIBACTERIANO, DROGA GENÉRICA: LIDOCAÍNA + SULFADIAZINA + VITAMINA A, FORMA FARMACEÚTICA: CREMA, PRESENTACIÓN: ENVASE X 100 GR | H39: NO | I39: =+'Necesidades Trimestrales'!F39 -> ENVASE | J39: =+'Necesidades Trimestrales'!H39 -> 1120 | K39: ='Necesidades Trimestrales'!#REF! -> #REF!
A40: 29 | B40: =+'Necesidades Trimestrales'!B40 -> 2.5.2-2481.3 | C40: =+'Necesidades Trimestrales'!E40 -> LAXANTES; TIPO: MONODROGA, DROGA GENERICA: VASELINA, FORMA FARMACEUTICA: SOLIDO, PRESENTACION: 1000 GR | H40: NO | I40: =+'Necesidades Trimestrales'!F40 -> UNIDAD | J40: =+'Necesidades Trimestrales'!H40 -> 1260 | K40: ='Necesidades Trimestrales'!#REF! -> #REF!
A42: Costo total estimado: TREINTA MILLONES VEINTIOCHO MIL QUINIENTOS SESENTA Y DOS con 00/100. | J42: =SUMPRODUCT(J12:J40,K12:K40) -> #REF!

Sheet Autor Gastar DPFARMACIA
A1: EJERCICIO: | D1: ='Necesidades Trimestrales'!C6 -> 2022 | P1: AUTORIZACION PARA GASTAR
A4: JURISDICCIÓN: | G4: =' NotaPedido DPFARMACIA'!C3 -> 040 - MINISTERIO DE SALUD
A5: SAF: | G5: =' NotaPedido DPFARMACIA'!C4 -> 011 - DIRECCION PROVINCIAL DE ADMINISTRACION - MS
A6: UNIDAD EJECUTORA: | G6: =' NotaPedido DPFARMACIA'!C5 -> 469 - DIRECCION PROVINCIAL DE FARMACIA E INSUMOS
A7: DEPENDENCIA SOLICITANTE: | G7: =' NotaPedido DPFARMACIA'!C6 -> 469 - DIRECCION PROVINCIAL DE FARMACIA E INSUMOS
A8: AUTORIZACIÓN:
A9: Señor Jefe de Servicio Administrativo Financiero:
A10: ="Autorizo la realización de los trámites correspondientes, a fin de proveer a este Organismo los bienes y/o servicios que se detallan en Nota de Pedido N° " & ' NotaPedido DPFARMACIA'!K1&", afectando la erogación resultante a los créditos presupuestarios aprobados a favor de esta Unidad Ejecutora, conforme al siguiente detalle:" -> Autorizo la realización de los trámites correspondientes, a fin de proveer a este Organismo los bienes y/o servicios que se detallan en Nota de Pedido N° 17/2022, afectando la erogación resultante a los créditos presupuestarios aprobados a favor de esta Unidad Ejecutora, conforme al siguiente detalle:
A12: IMPUTACIÓN PRESUPUESTARIA
A13: CÓDIGO | O13: DENOMINACIÓN DE LA PARTIDA PRESUPUESTARIA | Q13: IMPORTE
A14: PR | B14: SB | C14: PY | D14: AC | E14: OB | F14: UG | G14: FIN | H14: FUN | I14: I | J14: P | K14: P | L14: SubP | M14: M | N14: FF
A15: 30 | D15: 1 | F15: 4901 | G15: 3 | H15: 1 | I15: 2 | J15: 5 | K15: 2 | M15: 1 | N15: 1.1 | O15: PRODUCTOS FARMACEUTICOS Y MEDICINALES | Q15: =' NotaPedido DPFARMACIA'!J42 -> #REF!
A23: TOTAL DE PESOS: TREINTA MILLONES VEINTIOCHO MIL QUINIENTOS SESENTA Y DOS con 00/100. | Q23: =SUM(Q15:Q22) -> #REF!
A25: JUSTIFICACIÓN:
A26: =' NotaPedido DPFARMACIA'!C8 -> Adquisición de TERAPIA DERMATOLOGICA/SISTEMA GENITOURINARIO Y HORMONAS SEXUALES /HORMONAS SISTEMICAS /CORTICOIDES SISTEMICOS/RESPIRATORIO/ANTIHISTAMINICOS

Sheet  NotaPedido DPSAME
A1: NOTA DE PEDIDO | J1: N° | K1: 14/2022
A3: JURISDICCIÓN: | C3: ='Necesidades Trimestrales'!C4 -> 040 - MINISTERIO DE SALUD
A4: SAF: | C4: ='Necesidades Trimestrales'!C5 -> 011 - DIRECCION PROVINCIAL DE ADMINISTRACION - MS
A5: UNIDAD EJECUTORA: | C5: 748 - DIRECCION PROVINCIAL SISTEMA DE ATENCION MEDICA DE EMERGENCIA
A6: DEPENDENCIA SOLICITANTE: | C6: 748 - DIRECCION PROVINCIAL SISTEMA DE ATENCION MEDICA DE EMERGENCIA
A7: PERIODO UTILIZACIÓN: | C7: Cuatrimestral
A8: OBJETO: | C8: Adquisición de TERAPIA DERMATOLOGICA/SISTEMA GENITOURINARIO Y HORMONAS SEXUALES /HORMONAS SISTEMICAS /CORTICOIDES SISTEMICOS/RESPIRATORIO/ANTIHISTAMINICOS
A10: Ítem | B10: CODIGO ITEM | C10: DESCRIPCIÓN | H10: Adjunta Detalle Técnico | I10: Unidad Medida | J10: Precio Unitario Estimado | K10: Cantidad Solicitada
A12: 1 | B12: =+'Necesidades Trimestrales'!B18 -> 2.5.2-1855.7 | C12: =+'Necesidades Trimestrales'!E18 -> CORTICOESTEROIDES; TIPO: MONODROGA, DROGA GENERICA: DEXAMETASONA, FORMA FARMACEUTICA: AMPOLLA, PRESENTACION: 8 mGr | H12: NO | I12: =+'Necesidades Trimestrales'!F18 -> AMPOLLA | J12: =+'Necesidades Trimestrales'!H18 -> 45 | K12: ='Necesidades Trimestrales'!#REF! -> #REF!
A13: 2 | B13: =+'Necesidades Trimestrales'!B24 -> 2.5.2-1855.77 | C13: =+'Necesidades Trimestrales'!E24 -> CORTICOESTEROIDES; TIPO: MONODROGA, DROGA GENERICA: HIDROCORTISONA, FORMA FARMACEUTICA: FRASCO AMPOLLA, PRESENTACION: ENVASE X 500 mGr | H13: NO | I13: =+'Necesidades Trimestrales'!F24 -> AMPOLLA | J13: =+'Necesidades Trimestrales'!H24 -> 222 | K13: ='Necesidades Trimestrales'!#REF! -> #REF!
A15: Costo total estimado: CIENTO SEIS MIL OCHOCIENTOS con 00/100. | J15: =SUMPRODUCT(J12:J14,K12:K14) -> #REF!

Sheet Autor Gastar DPSAME
A1: EJERCICIO: | D1: ='Necesidades Trimestrales'!C6 -> 2022 | P1: AUTORIZACION PARA GASTAR
A4: JURISDICCIÓN: | G4: =' NotaPedido DPSAME'!C3 -> 040 - MINISTERIO DE SALUD
A5: SAF: | G5: =' NotaPedido DPSAME'!C4 -> 011 - DIRECCION PROVINCIAL DE ADMINISTRACION - MS
A6: UNIDAD EJECUTORA: | G6: =' NotaPedido DPSAME'!C5 -> 748 - DIRECCION PROVINCIAL SISTEMA DE ATENCION MEDICA DE EMERGENCIA
A7: DEPENDENCIA SOLICITANTE: | G7: =' NotaPedido DPSAME'!C6 -> 748 - DIRECCION PROVINCIAL SISTEMA DE ATENCION MEDICA DE EMERGENCIA
A8: AUTORIZACIÓN:
A9: Señor Jefe de Servicio Administrativo Financiero:
A10: ="Autorizo la realización de los trámites correspondientes, a fin de proveer a este Organismo los bienes y/o servicios que se detallan en Nota de Pedido N° " & ' NotaPedido DPSAME'!K1&", afectando la erogación resultante a los créditos presupuestarios aprobados a favor de esta Unidad Ejecutora, conforme al siguiente detalle:" -> Autorizo la realización de los trámites correspondientes, a fin de proveer a este Organismo los bienes y/o servicios que se detallan en Nota de Pedido N° 14/2022, afectando la erogación resultante a los créditos presupuestarios aprobados a favor de esta Unidad Ejecutora, conforme al siguiente detalle:
A12: IMPUTACIÓN PRESUPUESTARIA
A13: CÓDIGO | O13: DENOMINACIÓN DE LA PARTIDA PRESUPUESTARIA | Q13: IMPORTE
A14: PR | B14: SB | C14: PY | D14: AC | E14: OB | F14: UG | G14: FIN | H14: FUN | I14: I | J14: P | K14: P | L14: SubP | M14: M | N14: FF
A15: 31 | D15: 1 | F15: 4901 | G15: 3 | H15: 1 | I15: 2 | J15: 5 | K15: 2 | M15: 1 | N15: 1.1 | O15: PRODUCTOS FARMACEUTICOS Y MEDICINALES | Q15: =' NotaPedido DPSAME'!J15 -> #REF!
A23: TOTAL DE PESOS: CIENTO SEIS MIL OCHOCIENTOS con 00/100. | Q23: =SUM(Q15:Q22) -> #REF!
A25: JUSTIFICACIÓN:
A26: =' NotaPedido DPSAME'!C8 -> Adquisición de TERAPIA DERMATOLOGICA/SISTEMA GENITOURINARIO Y HORMONAS SEXUALES /HORMONAS SISTEMICAS /CORTICOIDES SISTEMICOS/RESPIRATORIO/ANTIHISTAMINICOS

Sheet  NotaPedido DPMIA
A1: NOTA DE PEDIDO | J1: N° | K1: 04/2022
A3: JURISDICCIÓN: | C3: ='Necesidades Trimestrales'!C4 -> 040 - MINISTERIO DE SALUD
A4: SAF: | C4: ='Necesidades Trimestrales'!C5 -> 011 - DIRECCION PROVINCIAL DE ADMINISTRACION - MS
A5: UNIDAD EJECUTORA: | C5: 162 - DIRECCION PROVINCIAL MATERNIDAD, INFANCIA Y ADOLESCENCIA
A6: DEPENDENCIA SOLICITANTE: | C6: 162 - DIRECCION PROVINCIAL MATERNIDAD, INFANCIA Y ADOLESCENCIA
A7: PERIODO UTILIZACIÓN: | C7: Cuatrimestral
A8: OBJETO: | C8: Adquisición de TERAPIA DERMATOLOGICA/SISTEMA GENITOURINARIO Y HORMONAS SEXUALES /HORMONAS SISTEMICAS /CORTICOIDES SISTEMICOS/RESPIRATORIO/ANTIHISTAMINICOS
A10: Ítem | B10: CODIGO ITEM | C10: DESCRIPCIÓN | H10: Adjunta Detalle Técnico | I10: Unidad Medida | J10: Precio Unitario Estimado | K10: Cantidad Solicitada
A12: 1 | B12: =+'Necesidades Trimestrales'!B14 -> 2.5.2-1855.83 | C12: =+'Necesidades Trimestrales'!E14 -> CORTICOESTEROIDES; TIPO: ASOCIACION, DROGA GENERICA: BETAMETASONA ACETATO+FOSFATO, FORMA FARMACEUTICA: AMPOLLA, PRESENTACION: ENVASE X 2 mL | H12: NO | I12: =+'Necesidades Trimestrales'!F14 -> AMPOLLA | J12: =+'Necesidades Trimestrales'!H14 -> 447 | K12: ='Necesidades Trimestrales'!#REF! -> #REF!
A13: 2 | B13: =+'Necesidades Trimestrales'!B17 -> 2.5.2-1902.14 | C13: =+'Necesidades Trimestrales'!E17 -> DROGAS UTERINAS; TIPO: MONODROGA, DROGA GENERICA: CARBETOCIN 100 MCG, FORMA FARMACEUTICA: AMPOLLA, PRESENTACION: UNIDAD | H13: NO | I13: =+'Necesidades Trimestrales'!F17 -> AMPOLLA | J13: =+'Necesidades Trimestrales'!H17 -> 5090 | K13: ='Necesidades Trimestrales'!#REF! -> #REF!
A14: 3 | B14: =+'Necesidades Trimestrales'!B22 -> 2.5.2-1853.4 | C14: =+'Necesidades Trimestrales'!E22 -> OCITOCICOS; TIPO: MONODROGA, DROGA GENERICA: ERGONOVINA, PRESENTACION: 0.2 mGr, FORMA FARMACEUTICA: AMPOLLAS | H14: NO | I14: =+'Necesidades Trimestrales'!F22 -> AMPOLLA | J14: =+'Necesidades Trimestrales'!H22 -> 57.8 | K14: ='Necesidades Trimestrales'!#REF! -> #REF!
A15: 4 | B15: =+'Necesidades Trimestrales'!B26 -> 2.5.2-1902.10 | C15: =+'Necesidades Trimestrales'!E26 -> DROGAS UTERINAS; TIPO: MONODROGA, DROGA GENERICA: ISOXUPRINA 10 mGr, FORMA FARMACEUTICA: AMPOLLA, PRESENTACION: UNIDAD | H15: NO | I15: =+'Necesidades Trimestrales'!F26 -> AMPOLLA | J15: =+'Necesidades Trimestrales'!H26 -> 45 | K15: ='Necesidades Trimestrales'!#REF! -> #REF!
A16: 5 | B16: =+'Necesidades Trimestrales'!B30 -> 2.5.2-1850.6 | C16: =+'Necesidades Trimestrales'!E30 -> GESTAGENO; TIPO: MONODROGA, DROGA GENERICA: MEDROXIPROGESTERONA, FORMA FARMACEUTICA: AMPOLLA, PRESENTACION: 150 mGr | H16: NO | I16: =+'Necesidades Trimestrales'!F30 -> AMPOLLA | J16: =+'Necesidades Trimestrales'!H30 -> 605 | K16: ='Necesidades Trimestrales'!#REF! -> #REF!
A18: Costo total estimado: NUEVE MILLONES CUATROCIENTOS TRES MIL CIENTO TREINTA con 00/100. | J18: =SUMPRODUCT(J12:J17,K12:K17) -> #REF!

Sheet Autor Gastar DPMIA
A1: EJERCICIO: | D1: ='Necesidades Trimestrales'!C6 -> 2022 | P1: AUTORIZACION PARA GASTAR
A4: JURISDICCIÓN: | G4: =' NotaPedido DPMIA'!C3 -> 040 - MINISTERIO DE SALUD
A5: SAF: | G5: =' NotaPedido DPMIA'!C4 -> 011 - DIRECCION PROVINCIAL DE ADMINISTRACION - MS
A6: UNIDAD EJECUTORA: | G6: =' NotaPedido DPMIA'!C5 -> 162 - DIRECCION PROVINCIAL MATERNIDAD, INFANCIA Y ADOLESCENCIA
A7: DEPENDENCIA SOLICITANTE: | G7: =' NotaPedido DPMIA'!C6 -> 162 - DIRECCION PROVINCIAL MATERNIDAD, INFANCIA Y ADOLESCENCIA
A8: AUTORIZACIÓN:
A9: Señor Jefe de Servicio Administrativo Financiero:
A10: ="Autorizo la realización de los trámites correspondientes, a fin de proveer a este Organismo los bienes y/o servicios que se detallan en Nota de Pedido N° " & ' NotaPedido DPMIA'!K1&", afectando la erogación resultante a los créditos presupuestarios aprobados a favor de esta Unidad Ejecutora, conforme al siguiente detalle:" -> Autorizo la realización de los trámites correspondientes, a fin de proveer a este Organismo los bienes y/o servicios que se detallan en Nota de Pedido N° 04/2022, afectando la erogación resultante a los créditos presupuestarios aprobados a favor de esta Unidad Ejecutora, conforme al siguiente detalle:
A12: IMPUTACIÓN PRESUPUESTARIA
A13: CÓDIGO | O13: DENOMINACIÓN DE LA PARTIDA PRESUPUESTARIA | Q13: IMPORTE
A14: PR | B14: SB | C14: PY | D14: AC | E14: OB | F14: UG | G14: FIN | H14: FUN | I14: I | J14: P | K14: P | L14: SubP | M14: M | N14: FF
A15: 20 | D15: 1 | F15: 4901 | G15: 3 | H15: 1 | I15: 2 | J15: 5 | K15: 2 | M15: 1 | N15: 1.1 | O15: PRODUCTOS FARMACEUTICOS Y MEDICINALES | Q15: 5360428
A16: 20 | D16: 3 | F16: 4901 | G16: 3 | H16: 1 | I16: 2 | J16: 5 | K16: 2 | M16: 1 | N16: 1.1 | O16: PRODUCTOS FARMACEUTICOS Y MEDICINALES | Q16: 4042702
A23: TOTAL DE PESOS: NUEVE MILLONES CUATROCIENTOS TRES MIL CIENTO TREINTA con 00/100. | Q23: =SUM(Q15:Q22) -> 9403130
A25: JUSTIFICACIÓN:
A26: =' NotaPedido DPMIA'!C8 -> Adquisición de TERAPIA DERMATOLOGICA/SISTEMA GENITOURINARIO Y HORMONAS SEXUALES /HORMONAS SISTEMICAS /CORTICOIDES SISTEMICOS/RESPIRATORIO/ANTIHISTAMINICOS
