Workbook

Sheet Necesidades Trimestrales
B2: Pedido de Necesidades Trimestrales
A4: JURISDICCION: | C4: 040 - Ministerio de Salud
A5: SAF N°: | C5: 011 - DIRECCION PROVINCIAL DE ADMINISTRACION - MS
A6: EJERCICIO: | C6: 2022
A7: TRIMESTRE: | C7: 3
A9: ID | B9: CODIGO ITEM | C9: RUBRO DE COMPRA | D9: I.P.P. | E9: DESCRIPCION | F9: UNIDAD DE MEDIDA | G9: D.P.FARMACIA | H9: TOTAL FARMACIA | I9: D.P.M.I.A. | J9: TOTAL MATERNO | K9: CANTIDAD TOTAL | L9: PRECIO UNITARIO ESTIMADO | M9: IMPORTE TOTAL ESTIMADO
A10: 1 | B10: 2.5.2-1724.154 | C10: PROD. MEDICO/FARMACEUTICOS/LAB | D10: 252 | E10: ANALGESICOS ; TIPO: MONODROGA, DROGA GENERICA: TRAMADOL 50 mGr, FORMA FARMACEUTICA: AMPOLLA, PRESENTACION: UNIDAD | F10: AMPOLLA | G10: 1000 | H10: =+G10*L10 -> 68900 | J10: =+I10*L10 -> 0 | K10: =+G10+I10 -> 1000 | L10: 68.9 | M10: =+K10*L10 -> 68900
A11: 2 | B11: 2.5.2-1821.201 | C11: PROD. MEDICO/FARMACEUTICOS/LAB | D11: 252 | E11: ANTIBIOTICOS P/PERSONAS; TIPO: ANTITUBERCULOSTATICO, DROGA GENERICA: RIFAMPICINA X 2 GR, FORMA FARMACEUTICA: EN SUSPENSION CADA 100 mL, PRESENTACION: FRASCO X 50 Ml | F11: FRASCO | G11: 30 | H11: =+G11*L11 -> 24060 | J11: =+I11*L11 -> 0 | K11: =+G11+I11 -> 30 | L11: 802 | M11: =+K11*L11 -> 24060
A12: 3 | B12: 2.5.2-1724.163 | C12: PROD. MEDICO/FARMACEUTICOS/LAB | D12: 252 | E12: ANALGESICOS ; TIPO: MONODROGA, DROGA GENERICA: IBUPROFENO 2%, FORMA FARMACEUTICA: SUSPENSION, PRESENTACION: ENVASE X 90 mL | F12: FRASCO | G12: 20050 | H12: =+G12*L12 -> 1704250 | K12: =+G12+I12 -> 20050 | L12: 85 | M12: =+K12*L12 -> 1704250
A13: 4 | B13: 2.5.2-1725.68 | C13: PROD. MEDICO/FARMACEUTICOS/LAB | D13: 252 | E13: ANTIINFLAMATORIOS NO ESTEROIDE; TIPO: MONODROGA, DROGA GENERICA: IBUPROFENO, FORMA FARMACEUTICA: COMPRIMIDO, PRESENTACION: 400 mGr | F13: COMPRIMIDO | G13: 150250 | H13: =+G13*L13 -> 763270 | J13: =+I13*L13 -> 0 | K13: =+G13+I13 -> 150250 | L13: 5.08 | M13: =+K13*L13 -> 763270
A14: 5 | B14: 2.9.5-2161.545 | C14: PROD. MEDICO/FARMACEUTICOS/LAB | D14: 295 | E14: CATETERES/SONDAS; NUMERO: SIN, TIPO: TUBO DE LUKEN PARA TOMA DE MUESTRAS | F14: UNIDAD | G14: 50 | H14: =+G14*L14 -> 62500 | J14: =+I14*L14 -> 0 | K14: =+G14+I14 -> 50 | L14: 1250 | M14: =+K14*L14 -> 62500
A15: 6 | B15: 2.5.2-1855.23 | C15: PROD. MEDICO/FARMACEUTICOS/LAB | D15: 252 | E15: CORTICOESTEROIDES; TIPO: MONODROGA, DROGA GENERICA: BETAMETASONA, FORMA FARMACEUTICA: CREMA, PRESENTACION: 15 GR | F15: ENVASE | G15: 5000 | H15: =+G15*L15 -> 1245500 | J15: =+I15*L15 -> 0 | K15: =+G15+I15 -> 5000 | L15: 249.1 | M15: =+K15*L15 -> 1245500
A16: 7 | B16: 2.5.2-2200.6 | C16: PROD. MEDICO/FARMACEUTICOS/LAB | D16: 252 | E16: CORTICOIDES; DROGA GENERICA: HIDROCORTISONA X 1 GR, FORMA FARMACEUTICA: CREMA, PRESENTACION: 15 GR, TIPO: MONODROGA | F16: ENVASE | G16: 2000 | H16: =+G16*L16 -> 523040 | J16: =+I16*L16 -> 0 | K16: =+G16+I16 -> 2000 | L16: 261.52 | M16: =+K16*L16 -> 523040
A17: 8 | B17: 2.5.2-1850.6 | C17: PROD. MEDICO/FARMACEUTICOS/LAB | D17: 252 | E17: GESTAGENO; TIPO: MONODROGA, DROGA GENERICA: MEDROXIPROGESTERONA, FORMA FARMACEUTICA: AMPOLLA, PRESENTACION: 150 mGr | F17: AMPOLLA | H17: =+G17*L17 -> 0 | I17: 3000 | J17: =+I17*L17 -> 1815000 | K17: =+G17+I17 -> 3000 | L17: 605 | M17: =+K17*L17 -> 1815000
A18: 9 | B18: 2.5.2-1895.8 | C18: PROD. MEDICO/FARMACEUTICOS/LAB | D18: 252 | E18: HORMONAS MEDICINALES; TIPO: MONODROGA, DROGA GENERICA: GONADOTROFINA CORIONICA, FORMA FARMACEUTICA: AMPOLLA, PRESENTACION: 5000 UI, USO: SEXUAL | F18: UNIDAD | H18: =+G18*L18 -> 0 | I18: 1000 | J18: =+I18*L18 -> 6450000 | K18: =+G18+I18 -> 1000 | L18: 6450 | M18: =+K18*L18 -> 6450000
A19: 10 | B19: 2.5.2-3097.9 | C19: PROD. MEDICO/FARMACEUTICOS/LAB | D19: 252 | E19: PEDICULICIDAS; DROGA GENERICA: PERMETRINA, FORMA FARMACEUTICA: EMULSION, PRESENTACION: 100 mL | F19: ENVASE | G19: 2000 | H19: =+G19*L19 -> 1916000 | J19: =+I19*L19 -> 0 | K19: =+G19+I19 -> 2000 | L19: 958 | M19: =+K19*L19 -> 1916000
A20: TOTAL RUBRO | H20: =SUM(H10:H19) -> 6307520 | J20: =SUM(J10:J19) -> 8265000 | M20: =SUM(M10:M19) -> 14572520
C22: DETALLE TECNICO Y ESPECIFICACIONES | D22: ANEXO 1-Para oferentes de la Provincia de Catamarca deberán presentar Habilitación Provincial para comercializar el producto que cotizan. 2-Para el resto de oferentes deberán presentar Certificado de Inscripción de ANMAT vigente al momento de la oferta, el mismo deberá ser correspondiente al objeto de la contratación y de encontrarse vencido adjuntar la solicitud de renovación. 3-No se aceptarán ofertas de productos no registrados y autorizada su venta por ANMAT. Se deberá especificar en cada ítem de la propuesta, marca y número de certificado otorgado por dicho ente regulador. 4-Los productos deberán tener un vencimiento posterior a doce (12) meses a partir de la fecha de su recepción.
C24: Plazos de entrega | D24: veinte (20) dias habiles
C26: Lugar de Entrega: | D26: ITEMS 1, 2, 3, 4, 5, 7 y 10 - DIR. PROV. DE FARMACIA E INSUMOS - CHACABUCO N° 169 - en el horario de 8:00hs a 12:00hs de lunes a viernes. DEBIENDO CORRER LOS GASTOS DE FLETES, ACARREO, CARGA, DESCARGA Y SEGURO A CARGO DEL ADJUDICATARIO. | G26: falta item 6
D27: ITEMS 8 y 9 - DIR. PROV. DE MATERNIDAD, INFANCIA Y ADOLESCENCIA - CHACABUCO N° 169 - en el horario de 8:00hs a 12:00hs de lunes a viernes. DEBIENDO CORRER LOS GASTOS DE FLETES, ACARREO, CARGA, DESCARGA Y SEGURO A CARGO DEL ADJUDICATARIO.
C29: Calidad Minima esperada
C31: Mantenimiento | D31: cuarenta y cinco (45) días

Sheet NP FCIA
A1: NOTA DE PEDIDO | J1: N° | K1: xxx/2022
A3: JURISDICCIÓN: | D3: ='Necesidades Trimestrales'!C4 -> 040 - Ministerio de Salud
A4: SAF: | D4: ='Necesidades Trimestrales'!C5 -> 011 - DIRECCION PROVINCIAL DE ADMINISTRACION - MS
A5: UNIDAD EJECUTORA: | D5: 469 - DIRECCION PROVINCIAL DE FARMACIA E INSUMOS
A6: DEPENDENCIA SOLICITANTE: | D6: 469 - DIRECCION PROVINCIAL DE FARMACIA E INSUMOS
A7: PERIODO UTILIZACIÓN: | D7: 3 meses
A8: OBJETO: | D8: Adquisición de Medicamentos y Descartables Desiertos y Fracasados
A10: Ítem | B10: Codigo Item | C10: DESCRIPCIÓN | H10: Adjunta Detalle Técnico | I10: Unidad Medida | J10: Precio Unitario Estimado | K10: Cantidad Solicitada
M11: 252 | N11: 295
A12: 1 | B12: =+'Necesidades Trimestrales'!B10 -> 2.5.2-1724.154 | C12: =+'Necesidades Trimestrales'!E10 -> ANALGESICOS ; TIPO: MONODROGA, DROGA GENERICA: TRAMADOL 50 mGr, FORMA FARMACEUTICA: AMPOLLA, PRESENTACION: UNIDAD | H12: NO | I12: =+'Necesidades Trimestrales'!F10 -> AMPOLLA | J12: =+'Necesidades Trimestrales'!L10 -> 68.9 | K12: ='Necesidades Trimestrales'!G10 -> 1000 | M12: =+J12*K12 -> 68900
A13: 2 | B13: =+'Necesidades Trimestrales'!B11 -> 2.5.2-1821.201 | C13: =+'Necesidades Trimestrales'!E11 -> ANTIBIOTICOS P/PERSONAS; TIPO: ANTITUBERCULOSTATICO, DROGA GENERICA: RIFAMPICINA X 2 GR, FORMA FARMACEUTICA: EN SUSPENSION CADA 100 mL, PRESENTACION: FRASCO X 50 Ml | H13: NO | I13: =+'Necesidades Trimestrales'!F11 -> FRASCO | J13: =+'Necesidades Trimestrales'!L11 -> 802 | K13: ='Necesidades Trimestrales'!G11 -> 30 | M13: =+J13*K13 -> 24060
A14: 3 | B14: =+'Necesidades Trimestrales'!B12 -> 2.5.2-1724.163 | C14: =+'Necesidades Trimestrales'!E12 -> ANALGESICOS ; TIPO: MONODROGA, DROGA GENERICA: IBUPROFENO 2%, FORMA FARMACEUTICA: SUSPENSION, PRESENTACION: ENVASE X 90 mL | H14: NO | I14: =+'Necesidades Trimestrales'!F12 -> FRASCO | J14: =+'Necesidades Trimestrales'!L12 -> 85 | K14: ='Necesidades Trimestrales'!G12 -> 20050 | M14: =+J14*K14 -> 1704250
A15: 4 | B15: =+'Necesidades Trimestrales'!B13 -> 2.5.2-1725.68 | C15: =+'Necesidades Trimestrales'!E13 -> ANTIINFLAMATORIOS NO ESTEROIDE; TIPO: MONODROGA, DROGA GENERICA: IBUPROFENO, FORMA FARMACEUTICA: COMPRIMIDO, PRESENTACION: 400 mGr | H15: NO | I15: =+'Necesidades Trimestrales'!F13 -> COMPRIMIDO | J15: =+'Necesidades Trimestrales'!L13 -> 5.08 | K15: ='Necesidades Trimestrales'!G13 -> 150250 | M15: =+J15*K15 -> 763270
A16: 5 | B16: =+'Necesidades Trimestrales'!B14 -> 2.9.5-2161.545 | C16: =+'Necesidades Trimestrales'!E14 -> CATETERES/SONDAS; NUMERO: SIN, TIPO: TUBO DE LUKEN PARA TOMA DE MUESTRAS | H16: NO | I16: =+'Necesidades Trimestrales'!F14 -> UNIDAD | J16: =+'Necesidades Trimestrales'!L14 -> 1250 | K16: ='Necesidades Trimestrales'!G14 -> 50 | N16: =+J16*K16 -> 62500
A17: 6 | B17: =+'Necesidades Trimestrales'!B15 -> 2.5.2-1855.23 | C17: =+'Necesidades Trimestrales'!E15 -> CORTICOESTEROIDES; TIPO: MONODROGA, DROGA GENERICA: BETAMETASONA, FORMA FARMACEUTICA: CREMA, PRESENTACION: 15 GR | H17: NO | I17: =+'Necesidades Trimestrales'!F15 -> ENVASE | J17: =+'Necesidades Trimestrales'!L15 -> 249.1 | K17: ='Necesidades Trimestrales'!G15 -> 5000 | M17: =+J17*K17 -> 1245500
A18: 7 | B18: =+'Necesidades Trimestrales'!B16 -> 2.5.2-2200.6 | C18: =+'Necesidades Trimestrales'!E16 -> CORTICOIDES; DROGA GENERICA: HIDROCORTISONA X 1 GR, FORMA FARMACEUTICA: CREMA, PRESENTACION: 15 GR, TIPO: MONODROGA | H18: NO | I18: =+'Necesidades Trimestrales'!F16 -> ENVASE | J18: =+'Necesidades Trimestrales'!L16 -> 261.52 | K18: ='Necesidades Trimestrales'!G16 -> 2000 | M18: =+J18*K18 -> 523040
A19: 8 | B19: =+'Necesidades Trimestrales'!B19 -> 2.5.2-3097.9 | C19: =+'Necesidades Trimestrales'!E19 -> PEDICULICIDAS; DROGA GENERICA: PERMETRINA, FORMA FARMACEUTICA: EMULSION, PRESENTACION: 100 mL | H19: NO | I19: =+'Necesidades Trimestrales'!F19 -> ENVASE | J19: =+'Necesidades Trimestrales'!L19 -> 958 | K19: ='Necesidades Trimestrales'!G19 -> 2000 | M19: =+J19*K19 -> 1916000
A20: Costo total estimado: PESOS SEIS MILLONES TRESCIENTOS SIETE MIL QUINIENTOS VEINTE con 00/100. | J20: =SUMPRODUCT(J12:J19,K12:K19) -> 6307520 | M20: =SUM(M12:M19) -> 6245020 | N20: =SUM(N12:N19) -> 62500 | O20: =SUM(M20:N20) -> 6307520

Sheet APG FCIA
A1: EJERCICIO: | D1: ='Necesidades Trimestrales'!C6 -> 2022 | P1: AUTORIZACION PARA GASTAR
A4: JURISDICCIÓN: | G4: ='NP FCIA'!D3 -> 040 - Ministerio de Salud
A5: SAF: | G5: ='NP FCIA'!D4 -> 011 - DIRECCION PROVINCIAL DE ADMINISTRACION - MS
A6: UNIDAD EJECUTORA: | G6: ='NP FCIA'!D5 -> 469 - DIRECCION PROVINCIAL DE FARMACIA E INSUMOS
A7: DEPENDENCIA SOLICITANTE: | G7: ='NP FCIA'!D6 -> 469 - DIRECCION PROVINCIAL DE FARMACIA E INSUMOS
A8: AUTORIZACIÓN:
A9: Señor Jefe de Servicio Administrativo Financiero:
A10: ="Autorizo la realización de los trámites correspondientes, a fin de proveer a este Organismo los bienes y/o servicios que se detallan en Nota de Pedido N° " & 'NP FCIA'!K1&", afectando la erogación resultante a los créditos presupuestarios aprobados a favor de esta Unidad Ejecutora, conforme al siguiente detalle:" -> Autorizo la realización de los trámites correspondientes, a fin de proveer a este Organismo los bienes y/o servicios que se detallan en Nota de Pedido N° xxx/2022, afectando la erogación resultante a los créditos presupuestarios aprobados a favor de esta Unidad Ejecutora, conforme al siguiente detalle:
A12: IMPUTACIÓN PRESUPUESTARIA
A13: CÓDIGO | O13: DENOMINACIÓN DE LA PARTIDA PRESUPUESTARIA | Q13: IMPORTE
A14: PR | B14: SB | C14: PY | D14: AC | E14: OB | F14: UG | G14: FIN | H14: FUN | I14: I | J14: P | K14: P | L14: SubP | M14: M | N14: FF
A15: 30 | D15: 1 | F15: 4901 | G15: 3 | H15: 1 | I15: 2 | J15: 5 | K15: 2 | M15: 1 | N15: 1.1 | O15: Productos Farmacéuticos y Medicinales | Q15: ='NP FCIA'!M20 -> 6245020
A16: 30 | D16: 1 | F16: 4901 | G16: 3 | H16: 1 | I16: 2 | J16: 9 | K16: 5 | M16: 1 | N16: 1.1 | O16: Utiles Menores Medico, Quirurgico y de Laboratorio | Q16: ='NP FCIA'!N20 -> 62500
A22: TOTAL DE PESOS: PESOS SEIS MILLONES TRESCIENTOS SIETE MIL QUINIENTOS VEINTE con 00/100. | Q22: =SUM(Q15:Q21) -> 6307520
A24: JUSTIFICACIÓN:
A25: Para la adquisición de Medicamentos y Descartables Desiertos y Fracasados destinados a la Direccion Provincial de Farmacia e Insumos - MS

Sheet NP DPMIA
A1: NOTA DE PEDIDO | J1: N° | K1: xxx/2022
A3: JURISDICCIÓN: | D3: ='Necesidades Trimestrales'!C4 -> 040 - Ministerio de Salud
A4: SAF: | D4: ='Necesidades Trimestrales'!C5 -> 011 - DIRECCION PROVINCIAL DE ADMINISTRACION - MS
A5: UNIDAD EJECUTORA: | D5: 162 - DIRECCION PROVINCIAL DE MATERNIDAD, INFANCIA Y ADOLESCENCIA
A6: DEPENDENCIA SOLICITANTE: | D6: 162 - DIRECCION PROVINCIAL DE MATERNIDAD, INFANCIA Y ADOLESCENCIA
A7: PERIODO UTILIZACIÓN: | D7: 3 meses
A8: OBJETO: | D8: Adquisición de Medicamentos y Descartables Desiertos y Fracasados
A10: Ítem | B10: Codigo Item | C10: DESCRIPCIÓN | H10: Adjunta Detalle Técnico | I10: Unidad Medida | J10: Precio Unitario Estimado | K10: Cantidad Solicitada
A12: 1 | B12: =+'Necesidades Trimestrales'!B17 -> 2.5.2-1850.6 | C12: =+'Necesidades Trimestrales'!E17 -> GESTAGENO; TIPO: MONODROGA, DROGA GENERICA: MEDROXIPROGESTERONA, FORMA FARMACEUTICA: AMPOLLA, PRESENTACION: 150 mGr | H12: NO | I12: =+'Necesidades Trimestrales'!F17 -> AMPOLLA | J12: =+'Necesidades Trimestrales'!L17 -> 605 | K12: ='Necesidades Trimestrales'!I17 -> 3000
A13: 2 | B13: =+'Necesidades Trimestrales'!B18 -> 2.5.2-1895.8 | C13: =+'Necesidades Trimestrales'!E18 -> HORMONAS MEDICINALES; TIPO: MONODROGA, DROGA GENERICA: GONADOTROFINA CORIONICA, FORMA FARMACEUTICA: AMPOLLA, PRESENTACION: 5000 UI, USO: SEXUAL | H13: NO | I13: =+'Necesidades Trimestrales'!F18 -> UNIDAD | J13: =+'Necesidades Trimestrales'!L18 -> 6450 | K13: ='Necesidades Trimestrales'!I18 -> 1000
A14: Costo total estimado: PESOS OCHO MILLONES DOSCIENTOS SESENTA Y CINCO MIL con 00/100. | J14: =SUMPRODUCT(J12:J13,K12:K13) -> 8265000

Sheet APG DPMIA
A1: EJERCICIO: | D1: ='Necesidades Trimestrales'!C6 -> 2022 | P1: AUTORIZACION PARA GASTAR
A4: JURISDICCIÓN: | G4: ='NP DPMIA'!D3 -> 040 - Ministerio de Salud
A5: SAF: | G5: ='NP DPMIA'!D4 -> 011 - DIRECCION PROVINCIAL DE ADMINISTRACION - MS
A6: UNIDAD EJECUTORA: | G6: ='NP DPMIA'!D5 -> 162 - DIRECCION PROVINCIAL DE MATERNIDAD, INFANCIA Y ADOLESCENCIA
A7: DEPENDENCIA SOLICITANTE: | G7: ='NP DPMIA'!D6 -> 162 - DIRECCION PROVINCIAL DE MATERNIDAD, INFANCIA Y ADOLESCENCIA
A8: AUTORIZACIÓN:
A9: Señor Jefe de Servicio Administrativo Financiero:
A10: ="Autorizo la realización de los trámites correspondientes, a fin de proveer a este Organismo los bienes y/o servicios que se detallan en Nota de Pedido N° " & 'NP DPMIA'!K1&", afectando la erogación resultante a los créditos presupuestarios aprobados a favor de esta Unidad Ejecutora, conforme al siguiente detalle:" -> Autorizo la realización de los trámites correspondientes, a fin de proveer a este Organismo los bienes y/o servicios que se detallan en Nota de Pedido N° xxx/2022, afectando la erogación resultante a los créditos presupuestarios aprobados a favor de esta Unidad Ejecutora, conforme al siguiente detalle:
A12: IMPUTACIÓN PRESUPUESTARIA
A13: CÓDIGO | O13: DENOMINACIÓN DE LA PARTIDA PRESUPUESTARIA | Q13: IMPORTE
A14: PR | B14: SB | C14: PY | D14: AC | E14: OB | F14: UG | G14: FIN | H14: FUN | I14: I | J14: P | K14: P | L14: SubP | M14: M | N14: FF
A15: 20 | D15: 1 | F15: 4901 | G15: 3 | H15: 1 | I15: 2 | J15: 5 | K15: 2 | M15: 1 | N15: 1.1 | O15: Productos Farmacéuticos y Medicinales | Q15: 5200000
A16: 20 | D16: 1 | F16: 4901 | G16: 3 | H16: 1 | I16: 2 | J16: 5 | K16: 2 | M16: 1 | N16: 1.1 | O16: Productos Farmacéuticos y Medicinales | Q16: 3065000
A23: TOTAL DE PESOS: OCHO MILLONES DOSCIENTOS SESENTA Y CINCO MIL con 00/100. | Q23: =SUM(Q15:Q22) -> 8265000
A25: JUSTIFICACIÓN:
A26: Para la adquisición de Medicamentos y Descartables Desiertos y Fracasados destinados a la Direccion Provincial de Maternidad, Infancia y Adolescencia
