Workbook

Sheet Necesidades Trimestrales
B2: Pedido de Necesidades Trimestrales
A4: JURISDICCION: | C4: 040 - Ministerio de Salud
A5: SAF N°: | C5: 024 - Hospital Interzonal de Niños
A6: EJERCICIO: | C6: 2020
A7: TRIMESTRE: | C7: 4
A9: ID | B9: CODIGO ITEM | C9: RUBRO DE COMPRA | D9: I.P.P. | E9: DESCRIPCION | F9: UNIDAD DE MEDIDA | G9: CANTIDAD | H9: PRECIO UNITARIO ESTIMADO | I9: IMPORTE TOTAL ESTIMADO
A10: 1 | B10: 2.9.1-564.5 | C10: ELEMENTOS DE LIMPIEZA | D10: 291 | E10: BALDES DE PLASTICO; CAPACIDAD: 10 L, COLOR: AMARILLO | F10: UNIDAD | G10: 20 | H10: 135 | I10: =H10*G10 -> 2700
A11: 2 | B11: 2.3.4-783.84 | C11: ELEMENTOS DE LIMPIEZA | D11: 234 | E11: TOALLAS DE PAPEL; MATERIAL: FIBRA CELULOSICA, GRAMAJE: 20 GR/M2, DIMENSION: 25 Cm, PRESENTACION: 2 X BOBINA X 400 M | F11: ROLLO | G11: 200 | H11: 490 | I11: =G11*H11 -> 98000
A12: 3 | B12: 2.9.5-1908.29 | C12: PROD. MEDICO/FARMACEUTICOS/LAB | D12: 295 | E12: CEPILLOS P/LABORATORIO; TIPO: P/LIMPIEZA BIBERONES, MATERIAL: CERDA , TAMAÑO: DIAM. 8 | F12: UNIDAD | G12: 30 | H12: 839 | I12: =G12*H12 -> 25170
A13: 4 | B13: 2.9.1-6951.60 | C13: ELEMENTOS DE LIMPIEZA | D13: 291 | E13: LIMPIADORES; TIPO: DESENGRASANTE, PRESENTACION: ENVASE X 5 L | F13: BIDON | G13: 10 | H13: 669.1 | I13: =G13*H13 -> 6691
A14: 5 | B14: 2.5.4-505.92 | C14: ELEMENTOS DE LIMPIEZA | D14: 254 | E14: DESINFECTANTES; PRINCIPIO ACTIVO: 2-FENIFENOL+ETANOL, CONTROL: BACTERIAS, PRESENTACION: ENVASE X 360 CM3 | F14: UNIDAD | G14: 150 | H14: 113.06 | I14: =G14*H14 -> 16959
A15: 6 | B15: 2.9.1-6951.41 | C15: ELEMENTOS DE LIMPIEZA | D15: 291 | E15: LIMPIADORES; TIPO: DESINFECTANTE P/PISO, PRESENTACION: ENVASE X 5 L | F15: BIDON | G15: 400 | H15: 275 | I15: =G15*H15 -> 110000
A16: 7 | B16: 2.9.1-6961.6 | C16: ELEMENTOS DE LIMPIEZA | D16: 291 | E16: ELEM. P/LIMPIEZA SANITARIOS; TIPO: PASTILLA DESODORANTE, PRESENTACION: UNIDAD | F16: UNIDAD | G16: 50 | H16: 40 | I16: =G16*H16 -> 2000
A17: 8 | B17: 2.9.1-6951.214 | C17: ELEMENTOS DE LIMPIEZA | D17: 291 | E17: LIMPIADORES; TIPO: DETERGENTE NEUTRO, PRESENTACION: ENVASE X 5 L | F17: BIDON | G17: 360 | H17: 650 | I17: =G17*H17 -> 234000
A18: 9 | B18: 2.9.1-6952.54 | C18: ELEMENTOS DE LIMPIEZA | D18: 291 | E18: CEPILLOS; TIPO: ESCOBILLON, MATERIAL: PLASTICO | F18: UNIDAD | G18: 15 | H18: 110 | I18: =G18*H18 -> 1650
A19: 10 | B19: 2.1.5-393.19 | C19: ELEMENTOS DE LIMPIEZA | D19: 215 | E19: CABOS DE MADERA; FORMA: RECTO C/ROSCA, APLICACION: ESCOBILLON | F19: UNIDAD | G19: 15 | H19: 45 | I19: =G19*H19 -> 675
A20: 11 | B20: 2.9.1-2030.1 | C20: ELEMENTOS DE LIMPIEZA | D20: 291 | E20: LANAS DE ACERO; PRESENTACION: PAQUETE, CONTENIDO: MADEJA | F20: PAQUETE | G20: 100 | H20: 30 | I20: =G20*H20 -> 3000
A21: 12 | B21: 2.9.1-1164.26 | C21: ELEMENTOS DE LIMPIEZA | D21: 291 | E21: ESPONJAS; USO: LIMPIEZA, ADITAMENTO: SIN VALOR, FORMA: RECTANGULAR, COLOR: AMARILLO, MATERIAL: FIBRA, LARGO X ANCHO X ESP: 9,7 X 5,7 X 3,5 Cm | F21: UNIDAD | G21: 150 | H21: 30 | I21: =G21*H21 -> 4500
A22: 13 | B22: 2.9.1-761.4 | C22: ELEMENTOS DE LIMPIEZA | D22: 291 | E22: GUANTES P/LIMPIEZA; TAMAÑO: EXTRA GRANDE, MATERIAL: LATEX | F22: PAR | G22: 100 | H22: 145 | I22: =G22*H22 -> 14500
... A38: 29 | B38: 2.9.1-646.26 | C38: ELEMENTOS DE LIMPIEZA | D38: 291 | E38: BOLSAS DE RESIDUOS; DIMENSION: 60 X 90 Cm, ESPESOR: 30 mm, PRESENTACION: POR UNIDAD, COLOR: OSCURO | F38: UNIDAD | G38: 30000 | H38: 4.5 | I38: =G38*H38 -> 135000
B40: Plazos y lugares de entrega
B41: Lugar de Entrega: SERVICIO DE ECONOMATO -HOSPITAL INT. DE NIÑOS – AV. VIRGEN DEL VALLE N° 1050-CATAMARCA DE 8:00 A 12:00HS., DEBIENDO CORRER LOS GASTOS DE FLETES, ACARREO, CARGA, DESCARGA Y SEGURO A CARGO DEL ADJUDICATARIO.
B43: Plazo de entrega: Dentro de los 7 días de notificada la Orden de Compra
B44: Mantenimiento
C45: 45 dias habiles
B48: Especificidades Item N° 5:
B50: Descripción técnica
C51: EN AEROSOL
B53: Especificidades Item N° 25:
B55: Descripción técnica
C56: POR 40 PAÑOS

Sheet  NotaPedido
A1: NOTA DE PEDIDO | J1: N° | K1: 505/2020
A3: JURISDICCIÓN: | D3: ='Necesidades Trimestrales'!C4 -> 040 - Ministerio de Salud
A4: SAF: | D4: ='Necesidades Trimestrales'!C5 -> 024 - Hospital Interzonal de Niños
A5: UNIDAD EJECUTORA: | D5: 024 - Hospital Interzonal de Niños
A6: DEPENDENCIA SOLICITANTE: | D6: Servicio de Economato
A7: PERIODO UTILIZACIÓN: | D7: ='Necesidades Trimestrales'!C7 & "° Trimestre - Año " & 'Necesidades Trimestrales'!C6 -> 4° Trimestre - Año 2020
A8: OBJETO: | D8: Adquisición de Articulos de Limpieza
A10: Ítem | B10: Codigo Item | C10: DESCRIPCIÓN | H10: Adjunta Detalle Técnico | I10: Unidad Medida | J10: Precio Unitario Estimado | K10: Cantidad Solicitada
A12: 1 | B12: ='Necesidades Trimestrales'!B10 -> 2.9.1-564.5 | C12: ='Necesidades Trimestrales'!E10 -> BALDES DE PLASTICO; CAPACIDAD: 10 L, COLOR: AMARILLO | H12: NO | I12: ='Necesidades Trimestrales'!F10 -> UNIDAD | J12: ='Necesidades Trimestrales'!H10 -> 135 | K12: ='Necesidades Trimestrales'!G10 -> 20
A13: 2 | B13: ='Necesidades Trimestrales'!B11 -> 2.3.4-783.84 | C13: ='Necesidades Trimestrales'!E11 -> TOALLAS DE PAPEL; MATERIAL: FIBRA CELULOSICA, GRAMAJE: 20 GR/M2, DIMENSION: 25 Cm, PRESENTACION: 2 X BOBINA X 400 M | H13: NO | I13: ='Necesidades Trimestrales'!F11 -> ROLLO | J13: ='Necesidades Trimestrales'!H11 -> 490 | K13: ='Necesidades Trimestrales'!G11 -> 200
A14: 3 | B14: ='Necesidades Trimestrales'!B12 -> 2.9.5-1908.29 | C14: ='Necesidades Trimestrales'!E12 -> CEPILLOS P/LABORATORIO; TIPO: P/LIMPIEZA BIBERONES, MATERIAL: CERDA , TAMAÑO: DIAM. 8 | H14: NO | I14: ='Necesidades Trimestrales'!F12 -> UNIDAD | J14: ='Necesidades Trimestrales'!H12 -> 839 | K14: ='Necesidades Trimestrales'!G12 -> 30
A15: 4 | B15: ='Necesidades Trimestrales'!B13 -> 2.9.1-6951.60 | C15: ='Necesidades Trimestrales'!E13 -> LIMPIADORES; TIPO: DESENGRASANTE, PRESENTACION: ENVASE X 5 L | H15: NO | I15: ='Necesidades Trimestrales'!F13 -> BIDON | J15: ='Necesidades Trimestrales'!H13 -> 669.1 | K15: ='Necesidades Trimestrales'!G13 -> 10
A16: 5 | B16: ='Necesidades Trimestrales'!B14 -> 2.5.4-505.92 | C16: ='Necesidades Trimestrales'!E14 -> DESINFECTANTES; PRINCIPIO ACTIVO: 2-FENIFENOL+ETANOL, CONTROL: BACTERIAS, PRESENTACION: ENVASE X 360 CM3 | H16: NO | I16: ='Necesidades Trimestrales'!F14 -> UNIDAD | J16: ='Necesidades Trimestrales'!H14 -> 113.06 | K16: ='Necesidades Trimestrales'!G14 -> 150
A17: 6 | B17: ='Necesidades Trimestrales'!B15 -> 2.9.1-6951.41 | C17: ='Necesidades Trimestrales'!E15 -> LIMPIADORES; TIPO: DESINFECTANTE P/PISO, PRESENTACION: ENVASE X 5 L | H17: NO | I17: ='Necesidades Trimestrales'!F15 -> BIDON | J17: ='Necesidades Trimestrales'!H15 -> 275 | K17: ='Necesidades Trimestrales'!G15 -> 400
A18: 7 | B18: ='Necesidades Trimestrales'!B16 -> 2.9.1-6961.6 | C18: ='Necesidades Trimestrales'!E16 -> ELEM. P/LIMPIEZA SANITARIOS; TIPO: PASTILLA DESODORANTE, PRESENTACION: UNIDAD | H18: NO | I18: ='Necesidades Trimestrales'!F16 -> UNIDAD | J18: ='Necesidades Trimestrales'!H16 -> 40 | K18: ='Necesidades Trimestrales'!G16 -> 50
A19: 8 | B19: ='Necesidades Trimestrales'!B17 -> 2.9.1-6951.214 | C19: ='Necesidades Trimestrales'!E17 -> LIMPIADORES; TIPO: DETERGENTE NEUTRO, PRESENTACION: ENVASE X 5 L | H19: NO | I19: ='Necesidades Trimestrales'!F17 -> BIDON | J19: ='Necesidades Trimestrales'!H17 -> 650 | K19: ='Necesidades Trimestrales'!G17 -> 360
A20: 9 | B20: ='Necesidades Trimestrales'!B18 -> 2.9.1-6952.54 | C20: ='Necesidades Trimestrales'!E18 -> CEPILLOS; TIPO: ESCOBILLON, MATERIAL: PLASTICO | H20: NO | I20: ='Necesidades Trimestrales'!F18 -> UNIDAD | J20: ='Necesidades Trimestrales'!H18 -> 110 | K20: ='Necesidades Trimestrales'!G18 -> 15
A21: 10 | B21: ='Necesidades Trimestrales'!B19 -> 2.1.5-393.19 | C21: ='Necesidades Trimestrales'!E19 -> CABOS DE MADERA; FORMA: RECTO C/ROSCA, APLICACION: ESCOBILLON | H21: NO | I21: ='Necesidades Trimestrales'!F19 -> UNIDAD | J21: ='Necesidades Trimestrales'!H19 -> 45 | K21: ='Necesidades Trimestrales'!G19 -> 15
A22: 11 | B22: ='Necesidades Trimestrales'!B20 -> 2.9.1-2030.1 | C22: ='Necesidades Trimestrales'!E20 -> LANAS DE ACERO; PRESENTACION: PAQUETE, CONTENIDO: MADEJA | H22: NO | I22: ='Necesidades Trimestrales'!F20 -> PAQUETE | J22: ='Necesidades Trimestrales'!H20 -> 30 | K22: ='Necesidades Trimestrales'!G20 -> 100
A23: 12 | B23: ='Necesidades Trimestrales'!B21 -> 2.9.1-1164.26 | C23: ='Necesidades Trimestrales'!E21 -> ESPONJAS; USO: LIMPIEZA, ADITAMENTO: SIN VALOR, FORMA: RECTANGULAR, COLOR: AMARILLO, MATERIAL: FIBRA, LARGO X ANCHO X ESP: 9,7 X 5,7 X 3,5 Cm | H23: NO | I23: ='Necesidades Trimestrales'!F21 -> UNIDAD | J23: ='Necesidades Trimestrales'!H21 -> 30 | K23: ='Necesidades Trimestrales'!G21 -> 150
... A40: 29 | B40: ='Necesidades Trimestrales'!B38 -> 2.9.1-646.26 | C40: ='Necesidades Trimestrales'!E38 -> BOLSAS DE RESIDUOS; DIMENSION: 60 X 90 Cm, ESPESOR: 30 mm, PRESENTACION: POR UNIDAD, COLOR: OSCURO | H40: NO | I40: ='Necesidades Trimestrales'!F38 -> UNIDAD | J40: ='Necesidades Trimestrales'!H38 -> 4.5 | K40: ='Necesidades Trimestrales'!G38 -> 30000
A41: Costo total estimado: Un Millon Ciento Cinco Mil Doscientos Cincuenta y Cinco con 00/100. | J41: =SUMPRODUCT(J12:J40,K12:K40) -> 1105255

Sheet Autor Gastar
A1: EJERCICIO: | D1: ='Necesidades Trimestrales'!C6 -> 2020 | P1: AUTORIZACION PARA GASTAR
A4: JURISDICCIÓN: | G4: =' NotaPedido'!D3 -> 040 - Ministerio de Salud
A5: SAF: | G5: =' NotaPedido'!D4 -> 024 - Hospital Interzonal de Niños
A6: UNIDAD EJECUTORA: | G6: =' NotaPedido'!D5 -> 024 - Hospital Interzonal de Niños
A7: DEPENDENCIA SOLICITANTE: | G7: =' NotaPedido'!D6 -> Servicio de Economato
A8: AUTORIZACIÓN:
A9: Señor Jefe de Servicio Administrativo Financiero:
A10: ="Autorizo la realización de los trámites correspondientes, a fin de proveer a este Organismo los bienes y/o servicios que se detallan en Nota de Pedido N° " & ' NotaPedido'!K1&", afectando la erogación resultante a los créditos presupuestarios aprobados a favor de esta Unidad Ejecutora, conforme al siguiente detalle:" -> Autorizo la realización de los trámites correspondientes, a fin de proveer a este Organismo los bienes y/o servicios que se detallan en Nota de Pedido N° 505/2020, afectando la erogación resultante a los créditos presupuestarios aprobados a favor de esta Unidad Ejecutora, conforme al siguiente detalle:
A12: IMPUTACIÓN PRESUPUESTARIA
A13: CÓDIGO | O13: DENOMINACIÓN DE LA PARTIDA PRESUPUESTARIA | Q13: IMPORTE
A14: PR | B14: SB | C14: PY | D14: AC | E14: OB | F14: UG | G14: FIN | H14: FUN | I14: I | J14: P | K14: P | L14: SubP | M14: M | N14: FF
A15: 36 | D15: 1 | F15: 4901 | G15: 3 | H15: 310 | I15: =LEFT('Necesidades Trimestrales'!D10,1) -> 2 | J15: =MID('Necesidades Trimestrales'!D10,3,1) -> 1 | K15: 5 | M15: 1 | N15: 1.1 | O15: Madera, Corcho y sus Manufacturas | Q15: 675
A16: 36 | D16: 1 | F16: 4901 | G16: 3 | H16: 310 | I16: =LEFT('Necesidades Trimestrales'!D11,1) -> 2 | J16: 3 | K16: =RIGHT('Necesidades Trimestrales'!D11,1) -> 4 | M16: 1 | N16: 1.1 | O16: Productos de Papel y Carton | Q16: 287150
A17: 36 | D17: 1 | F17: 4901 | G17: 3 | H17: 310 | I17: =LEFT('Necesidades Trimestrales'!D12,1) -> 2 | J17: =MID('Necesidades Trimestrales'!D12,3,1) -> 5 | K17: 4 | M17: 1 | N17: 1.1 | O17: Insecticidas, Fumigantes y Otros | Q17: 16959
A18: 36 | D18: 1 | F18: 4901 | G18: 3 | H18: 310 | I18: =LEFT('Necesidades Trimestrales'!D13,1) -> 2 | J18: 9 | K18: =RIGHT('Necesidades Trimestrales'!D13,1) -> 1 | M18: 1 | N18: 1.1 | O18: Elementos de Limpieza | Q18: 775301
A19: 36 | D19: 1 | F19: 4901 | G19: 3 | H19: 310 | I19: =LEFT('Necesidades Trimestrales'!D14,1) -> 2 | J19: 9 | K19: 5 | M19: 1 | N19: 1.1 | O19: Utiles Menores Medico, Quirurgico y de Laboratorio | Q19: 25170
A23: TOTAL DE PESOS: UN MILLON CIENTO CINCO MIL DOSCIENTOS CINCUENTA Y CINCO CON 00/100. | Q23: =SUM(Q15:Q22) -> 1105255
A25: JUSTIFICACIÓN:
A26: Para la adquisición de Articulos de Limpieza destinados al servico de Economato del Hospital Interzonal de Niños Eva Peron, para el normal funcionamiento del organismo.
