Workbook

Sheet Necesidades Trimestrales
B2: Pedido de Necesidades Trimestrales
A4: JURISDICCION: | C4: 12 -Ministerio de Trabajo y Recursos Humanos
A5: SAF N°: | C5: 22 - Secretaria de Administración del Ministerio de Trabajo y Recursos Humanos
A6: EJERCICIO: | C6: 2021
A7: TRIMESTRE: | C7: 2
A9: ID | B9: CODIGO ITEM | C9: RUBRO DE COMPRA | D9: I.P.P. | E9: DESCRIPCION | F9: UNIDAD DE MEDIDA | G9: CANTIDAD | H9: PRECIO UNITARIO ESTIMADO | I9: IMPORTE TOTAL ESTIMADO
A10: 1 | B10: 2.3.4-5442.13 | C10: BAZAR Y MENAJE | D10: =+LEFT(B10,5) -> 2.3.4 | E10: ROLLOS P/COCINA; DIMENSION: 21 X 20 Cm, PRESENTACION: ENVASE X 3 UN | F10: UNIDAD | G10: 50 | H10: 80 | I10: =+H10*G10 -> 4000
A11: 2 | B11: 2.3.4-783.66 | C11: ELEMENTOS DE LIMPIEZA | D11: =+LEFT(B11,5) -> 2.3.4 | E11: TOALLAS DE PAPEL; MATERIAL: PAPEL GOFRADO, GRAMAJE: SIN VALOR, DIMENSION: ANCHO 20 Cm, PRESENTACION: ROLLO X 304 M | F11: UNIDAD | G11: 20 | H11: 394 | I11: =+H11*G11 -> 7880
A12: 3 | B12: 2.3.4-786.80 | C12: ELEMENTOS DE LIMPIEZA | D12: =+LEFT(B12,5) -> 2.3.4 | E12: PAPEL HIGIENICO; PRESENTACION: PAQUETE X 4, TIPO: ROLLO, ANCHO: 10 Cm, LARGO: 90 M, TIPO DE HOJA: DOBLE | F12: UNIDAD | G12: 50 | H12: 125 | I12: =+H12*G12 -> 6250
A13: 4 | B13: 2.5.4-505.19 | C13: ELEMENTOS DE LIMPIEZA | D13: =+LEFT(B13,5) -> 2.5.4 | E13: DESINFECTANTES; PRESENTACION: ENVASE X 5 L, USO P/CONTROL: BACTERIAS, CAPACIDAD: 5 L, CONTROL: BACTERIAS, PRINCIPIO ACTIVO: HIPOCLORITO DE SODIO | F13: UNIDAD | G13: 10 | H13: 300 | I13: =+H13*G13 -> 3000
A14: 5 | B14: 2.5.4-505.73 | C14: ELEMENTOS DE LIMPIEZA | D14: =+LEFT(B14,5) -> 2.5.4 | E14: DESINFECTANTES; PRINCIPIO ACTIVO: 2-FENILFENOL, CONTROL: BACTERIAS, HONGOS Y VIRUS, PRESENTACION: ENVASE X 360 CM3 | F14: UNIDAD | G14: 30 | H14: 275 | I14: =+H14*G14 -> 8250
A15: 6 | B15: 2.5.4-506.192 | C15: ELEMENTOS DE LIMPIEZA | D15: =+LEFT(B15,5) -> 2.5.4 | E15: INSECTICIDAS; PRINCIPIO ACTIVO: TETRAMETRINA, CONTROL: CUCARACHA, ACCION: CONTROL, PRESENTACION: AEROSOL X 360 CM3 | F15: UNIDAD | G15: 20 | H15: 244 | I15: =+H15*G15 -> 4880
A16: 7 | B16: 2.5.4-506.194 | C16: ELEMENTOS DE LIMPIEZA | D16: =+LEFT(B16,5) -> 2.5.4 | E16: INSECTICIDAS; PRINCIPIO ACTIVO: TETRAMETRINA, CONTROL: HORMIGAS, ACCION: VOLTEO Y RESIDUAL, PRESENTACION: ENVASE X 360 CM3 | F16: UNIDAD | G16: 20 | H16: 194 | I16: =+H16*G16 -> 3880
A17: 8 | B17: 2.5.4-506.209 | C17: ELEMENTOS DE LIMPIEZA | D17: =+LEFT(B17,5) -> 2.5.4 | E17: INSECTICIDAS; PRINCIPIO ACTIVO: DIFETHIALONE 0.0025 %, CONTROL: ROEDORES, ACCION:,: CEBO X 1 Kg | F17: UNIDAD | G17: 8 | H17: 680 | I17: =+H17*G17 -> 5440
A18: 9 | B18: 2.5.4-506.200 | C18: ELEMENTOS DE LIMPIEZA | D18: =+LEFT(B18,5) -> 2.5.4 | E18: INSECTICIDAS; PRINCIPIO ACTIVO: D-FENOTRINA, D-TETRA, PRAL, CONTROL: MOSCAS Y MOSQUITOS, ACCION: INSECTICIDA, PRESENTACION: ENVASE X 360 CM3 | F18: UNIDAD | G18: 30 | H18: 285 | I18: =+H18*G18 -> 8550
A19: 10 | B19: 2.9.1-1156.1 | C19: ELEMENTOS DE LIMPIEZA | D19: =+LEFT(B19,5) -> 2.9.1 | E19: PLUMEROS; PLUMA: SINTETICA, CLASE: SUAVE, MATERIAL MANGO: MADERA, LARGO MANGO: 60 Cm, Nº VUELTAS PENACHO: 6, TIPO: SUAVE | F19: UNIDAD | G19: 15 | H19: 2350 | I19: =+H19*G19 -> 35250
A20: 11 | B20: 2.9.1-1164.18 | C20: ELEMENTOS DE LIMPIEZA | D20: =+LEFT(B20,5) -> 2.9.1 | E20: ESPONJAS; MATERIAL: METAL, USO: PARA COCINA, ADITAMENTO: SIN VALOR, FORMA: REDONDA, LARGO X ANCHO X ESP: ROLLO X 30 GR, COLOR: DORADO | F20: UNIDAD | G20: 20 | H20: 125 | I20: =+H20*G20 -> 2500
A21: 12 | B21: 2.9.1-1164.35 | C21: ELEMENTOS DE LIMPIEZA | D21: =+LEFT(B21,5) -> 2.9.1 | E21: ESPONJAS; MATERIAL: FIBRA, USO: DOMESTICO, ADITAMENTO: FIBRA, FORMA: RECTANGULAR, LARGO X ANCHO X ESP: 10 X 6 X 4 Cm | F21: UNIDAD | G21: 20 | H21: 65 | I21: =+H21*G21 -> 1300
... A50: 41 | B50: 2.9.9-3919.2 | C50: ELEMENTOS DE LIMPIEZA | D50: =+LEFT(B50,5) -> 2.9.9 | E50: DISPENSADOR P/JABON LIQUIDO; MATERIAL: ACRILICO IRROMPIBLE, DIMENSION: 23 X 38 X 7,5 Cm, CAPACIDAD: 375 UN, ACCIONAMIENTO: P/MANOS | F50: UNIDAD | G50: 10 | H50: 967 | I50: =+H50*G50 -> 9670
A51: COSTO ESTIMADO TOTAL: SON PESOS TRESCIENTOS SESENTA Y TRES MIL DOSCIENTOS OCHENTA Y OCHO CON 00/100 | I51: =SUM(I10:I50) -> 363288
B53: Especificidades Item N° 1:
B55: Descripción técnica
B57: Plazos y lugares de entrega
C58: a) LUGAR DE ENTREGA: Pabellón Nº 20 Ministerio de Trabajo y Recursos Humanos (CAPE), sito en Av. Presidente Castillo y Av. Venezuela - Capital - De 08 a 12 horas. b) FORMA DE LA ENTREGA: Libre de flete, acarreo y embalaje, como así también, de todo riesgo de pérdida o destrucción total o parcial, por causas ajenas a la Institución. c) PLAZO DE ENTREGA: El Oferente deberá establecer plazo de entrega de los elementos cotizados, debiendo ser expresado en días hábiles; que no podrá ser superior a cinco (5) días hábiles, contados a partir de la recepción de la comunicación prevista en el Artículo en el Reglamento Parcial N° 2 de la ley 4938.
B60: Calidad Minima esperada
C61: Que cumpla íntegramente con lo solicitado
B62: Mantenimiento
C63: 30 (treinta) días
B64: Garantia

Sheet  NotaPedido
A1: NOTA DE PEDIDO | J1: N° | K1: 007/2021
A3: JURISDICCIÓN: | D3: ='Necesidades Trimestrales'!C4 -> 12 -Ministerio de Trabajo y Recursos Humanos
A4: SAF: | D4: ='Necesidades Trimestrales'!C5 -> 22 - Secretaria de Administración del Ministerio de Trabajo y Recursos Humanos
A5: UNIDAD EJECUTORA: | D5: Secretaria de Administracion
A6: DEPENDENCIA SOLICITANTE: | D6: Secretaria de Administracion
A7: PERIODO UTILIZACIÓN: | D7: ='Necesidades Trimestrales'!C7 & "° Trimestre - Año " & 'Necesidades Trimestrales'!C6 -> 2° Trimestre - Año 2021
A8: OBJETO: | D8: Adquisición de ELEMENTOS DE LIMPIEZA para las distintas dependencias de este Ministerio.
A10: Ítem | B10: Codigo Item | C10: DESCRIPCIÓN | H10: Adjunta Detalle Técnico | I10: Unidad Medida | J10: Precio Unitario Estimado | K10: Cantidad Solicitada
A12: =+'Necesidades Trimestrales'!A10 -> 1 | B12: =+'Necesidades Trimestrales'!B10 -> 2.3.4-5442.13 | C12: =+'Necesidades Trimestrales'!E10 -> ROLLOS P/COCINA; DIMENSION: 21 X 20 Cm, PRESENTACION: ENVASE X 3 UN | H12: NO | I12: =+'Necesidades Trimestrales'!F10 -> UNIDAD | J12: =+'Necesidades Trimestrales'!H10 -> 80 | K12: =+'Necesidades Trimestrales'!G10 -> 50
A13: =+'Necesidades Trimestrales'!A11 -> 2 | B13: =+'Necesidades Trimestrales'!B11 -> 2.3.4-783.66 | C13: =+'Necesidades Trimestrales'!E11 -> TOALLAS DE PAPEL; MATERIAL: PAPEL GOFRADO, GRAMAJE: SIN VALOR, DIMENSION: ANCHO 20 Cm, PRESENTACION: ROLLO X 304 M | H13: NO | I13: =+'Necesidades Trimestrales'!F11 -> UNIDAD | J13: =+'Necesidades Trimestrales'!H11 -> 394 | K13: =+'Necesidades Trimestrales'!G11 -> 20
A14: =+'Necesidades Trimestrales'!A12 -> 3 | B14: =+'Necesidades Trimestrales'!B12 -> 2.3.4-786.80 | C14: =+'Necesidades Trimestrales'!E12 -> PAPEL HIGIENICO; PRESENTACION: PAQUETE X 4, TIPO: ROLLO, ANCHO: 10 Cm, LARGO: 90 M, TIPO DE HOJA: DOBLE | H14: NO | I14: =+'Necesidades Trimestrales'!F12 -> UNIDAD | J14: =+'Necesidades Trimestrales'!H12 -> 125 | K14: =+'Necesidades Trimestrales'!G12 -> 50
A15: =+'Necesidades Trimestrales'!A13 -> 4 | B15: =+'Necesidades Trimestrales'!B13 -> 2.5.4-505.19 | C15: =+'Necesidades Trimestrales'!E13 -> DESINFECTANTES; PRESENTACION: ENVASE X 5 L, USO P/CONTROL: BACTERIAS, CAPACIDAD: 5 L, CONTROL: BACTERIAS, PRINCIPIO ACTIVO: HIPOCLORITO DE SODIO | H15: NO | I15: =+'Necesidades Trimestrales'!F13 -> UNIDAD | J15: =+'Necesidades Trimestrales'!H13 -> 300 | K15: =+'Necesidades Trimestrales'!G13 -> 10
A16: =+'Necesidades Trimestrales'!A14 -> 5 | B16: =+'Necesidades Trimestrales'!B14 -> 2.5.4-505.73 | C16: =+'Necesidades Trimestrales'!E14 -> DESINFECTANTES; PRINCIPIO ACTIVO: 2-FENILFENOL, CONTROL: BACTERIAS, HONGOS Y VIRUS, PRESENTACION: ENVASE X 360 CM3 | H16: NO | I16: =+'Necesidades Trimestrales'!F14 -> UNIDAD | J16: =+'Necesidades Trimestrales'!H14 -> 275 | K16: =+'Necesidades Trimestrales'!G14 -> 30
A17: =+'Necesidades Trimestrales'!A15 -> 6 | B17: =+'Necesidades Trimestrales'!B15 -> 2.5.4-506.192 | C17: =+'Necesidades Trimestrales'!E15 -> INSECTICIDAS; PRINCIPIO ACTIVO: TETRAMETRINA, CONTROL: CUCARACHA, ACCION: CONTROL, PRESENTACION: AEROSOL X 360 CM3 | H17: NO | I17: =+'Necesidades Trimestrales'!F15 -> UNIDAD | J17: =+'Necesidades Trimestrales'!H15 -> 244 | K17: =+'Necesidades Trimestrales'!G15 -> 20
A18: =+'Necesidades Trimestrales'!A16 -> 7 | B18: =+'Necesidades Trimestrales'!B16 -> 2.5.4-506.194 | C18: =+'Necesidades Trimestrales'!E16 -> INSECTICIDAS; PRINCIPIO ACTIVO: TETRAMETRINA, CONTROL: HORMIGAS, ACCION: VOLTEO Y RESIDUAL, PRESENTACION: ENVASE X 360 CM3 | H18: NO | I18: =+'Necesidades Trimestrales'!F16 -> UNIDAD | J18: =+'Necesidades Trimestrales'!H16 -> 194 | K18: =+'Necesidades Trimestrales'!G16 -> 20
A19: =+'Necesidades Trimestrales'!A17 -> 8 | B19: =+'Necesidades Trimestrales'!B17 -> 2.5.4-506.209 | C19: =+'Necesidades Trimestrales'!E17 -> INSECTICIDAS; PRINCIPIO ACTIVO: DIFETHIALONE 0.0025 %, CONTROL: ROEDORES, ACCION:,: CEBO X 1 Kg | H19: NO | I19: =+'Necesidades Trimestrales'!F17 -> UNIDAD | J19: =+'Necesidades Trimestrales'!H17 -> 680 | K19: =+'Necesidades Trimestrales'!G17 -> 8
A20: =+'Necesidades Trimestrales'!A18 -> 9 | B20: =+'Necesidades Trimestrales'!B18 -> 2.5.4-506.200 | C20: =+'Necesidades Trimestrales'!E18 -> INSECTICIDAS; PRINCIPIO ACTIVO: D-FENOTRINA, D-TETRA, PRAL, CONTROL: MOSCAS Y MOSQUITOS, ACCION: INSECTICIDA, PRESENTACION: ENVASE X 360 CM3 | H20: NO | I20: =+'Necesidades Trimestrales'!F18 -> UNIDAD | J20: =+'Necesidades Trimestrales'!H18 -> 285 | K20: =+'Necesidades Trimestrales'!G18 -> 30
A21: =+'Necesidades Trimestrales'!A19 -> 10 | B21: =+'Necesidades Trimestrales'!B19 -> 2.9.1-1156.1 | C21: =+'Necesidades Trimestrales'!E19 -> PLUMEROS; PLUMA: SINTETICA, CLASE: SUAVE, MATERIAL MANGO: MADERA, LARGO MANGO: 60 Cm, Nº VUELTAS PENACHO: 6, TIPO: SUAVE | H21: NO | I21: =+'Necesidades Trimestrales'!F19 -> UNIDAD | J21: =+'Necesidades Trimestrales'!H19 -> 2350 | K21: =+'Necesidades Trimestrales'!G19 -> 15
A22: =+'Necesidades Trimestrales'!A20 -> 11 | B22: =+'Necesidades Trimestrales'!B20 -> 2.9.1-1164.18 | C22: =+'Necesidades Trimestrales'!E20 -> ESPONJAS; MATERIAL: METAL, USO: PARA COCINA, ADITAMENTO: SIN VALOR, FORMA: REDONDA, LARGO X ANCHO X ESP: ROLLO X 30 GR, COLOR: DORADO | H22: NO | I22: =+'Necesidades Trimestrales'!F20 -> UNIDAD | J22: =+'Necesidades Trimestrales'!H20 -> 125 | K22: =+'Necesidades Trimestrales'!G20 -> 20
A23: =+'Necesidades Trimestrales'!A21 -> 12 | B23: =+'Necesidades Trimestrales'!B21 -> 2.9.1-1164.35 | C23: =+'Necesidades Trimestrales'!E21 -> ESPONJAS; MATERIAL: FIBRA, USO: DOMESTICO, ADITAMENTO: FIBRA, FORMA: RECTANGULAR, LARGO X ANCHO X ESP: 10 X 6 X 4 Cm | H23: NO | I23: =+'Necesidades Trimestrales'!F21 -> UNIDAD | J23: =+'Necesidades Trimestrales'!H21 -> 65 | K23: =+'Necesidades Trimestrales'!G21 -> 20
... A52: =+'Necesidades Trimestrales'!A50 -> 41 | B52: =+'Necesidades Trimestrales'!B50 -> 2.9.9-3919.2 | C52: =+'Necesidades Trimestrales'!E50 -> DISPENSADOR P/JABON LIQUIDO; MATERIAL: ACRILICO IRROMPIBLE, DIMENSION: 23 X 38 X 7,5 Cm, CAPACIDAD: 375 UN, ACCIONAMIENTO: P/MANOS | H52: NO | I52: =+'Necesidades Trimestrales'!F50 -> UNIDAD | J52: =+'Necesidades Trimestrales'!H50 -> 967 | K52: =+'Necesidades Trimestrales'!G50 -> 10
A53: =+'Necesidades Trimestrales'!A51:H51 -> COSTO ESTIMADO TOTAL: SON PESOS TRESCIENTOS SESENTA Y TRES MIL DOSCIENTOS OCHENTA Y OCHO CON 00/100 | J53: =SUMPRODUCT(J12:J52,K12:K52) -> 363288

Sheet Autor Gastar
A1: EJERCICIO: | D1: ='Necesidades Trimestrales'!C6 -> 2021 | P1: AUTORIZACION PARA GASTAR
A4: JURISDICCIÓN: | G4: =' NotaPedido'!D3 -> 12 -Ministerio de Trabajo y Recursos Humanos
A5: SAF: | G5: =' NotaPedido'!D4 -> 22 - Secretaria de Administración del Ministerio de Trabajo y Recursos Humanos
A6: UNIDAD EJECUTORA: | G6: Ministerio de Trabajo y Reursos Humanos
A7: DEPENDENCIA SOLICITANTE: | G7: =' NotaPedido'!D6 -> Secretaria de Administracion
A8: AUTORIZACIÓN:
A9: Señor Jefe de Servicio Administrativo Financiero:
A10: ="Autorizo la realización de los trámites correspondientes, a fin de proveer a este Organismo los bienes y/o servicios que se detallan en Nota de Pedido N° " & ' NotaPedido'!K1&", afectando la erogación resultante a los créditos presupuestarios aprobados a favor de esta Unidad Ejecutora, conforme al siguiente detalle:" -> Autorizo la realización de los trámites correspondientes, a fin de proveer a este Organismo los bienes y/o servicios que se detallan en Nota de Pedido N° 007/2021, afectando la erogación resultante a los créditos presupuestarios aprobados a favor de esta Unidad Ejecutora, conforme al siguiente detalle:
A12: IMPUTACIÓN PRESUPUESTARIA
A13: CÓDIGO | O13: DENOMINACIÓN DE LA PARTIDA PRESUPUESTARIA | Q13: IMPORTE
A14: PR | B14: SB | C14: PY | D14: AC | E14: OB | F14: UG | G14: FIN | H14: FUN | I14: I | J14: P | K14: P | L14: SubP | M14: M | N14: FF
A15: 1 | B15: 0 | C15: 0 | D15: 1 | E15: 0 | F15: 4901 | G15: 3 | H15: 6 | I15: 2 | J15: 3 | K15: 4 | L15: 0 | M15: 1 | N15: 1.1 | O15: Productos de Papel y Cartón | Q15: 18130
A16: 1 | B16: 0 | C16: 0 | D16: 1 | E16: 0 | F16: 4901 | G16: 3 | H16: 6 | I16: 2 | J16: 5 | K16: 4 | L16: 0 | M16: 1 | N16: 1.1 | O16: Insecticidas, Fumigantes y Otros | Q16: 34000
A17: 1 | B17: 0 | C17: 0 | D17: 1 | E17: 0 | F17: 4901 | G17: 3 | H17: 6 | I17: 2 | J17: 9 | K17: 1 | L17: 0 | M17: 1 | N17: 1.1 | O17: Elementos de Limpieza | Q17: 142213
A18: 1 | B18: 0 | C18: 0 | D18: 1 | E18: 0 | F18: 4901 | G18: 3 | H18: 6 | I18: 2 | J18: 9 | K18: 9 | L18: 0 | M18: 1 | N18: 1.1 | O18: Otros No Especificados Precedentemente (N.E.P.) | Q18: 16470
A19: 2 | B19: 0 | C19: 0 | D19: 1 | E19: 0 | F19: 4901 | G19: 3 | H19: 6 | I19: 2 | J19: 9 | K19: 1 | L19: 0 | M19: 1 | N19: 1.1 | O19: Elementos de Limpieza | Q19: 50000
A20: 3 | B20: 0 | C20: 0 | D20: 1 | E20: 0 | F20: 4901 | G20: 1 | H20: 3 | I20: 2 | J20: 9 | K20: 1 | L20: 0 | M20: 1 | N20: 1.1 | O20: Elementos de Limpieza | Q20: 50000
A21: 3 | B21: 0 | C21: 0 | D21: 1 | E21: 0 | F21: 4901 | G21: 1 | H21: 3 | I21: 2 | J21: 9 | K21: 9 | L21: 0 | M21: 1 | N21: 1.1 | O21: Otros No Especificados Precedentemente (N.E.P.) | Q21: 8750
A22: 4 | B22: 0 | C22: 0 | D22: 1 | E22: 0 | F22: 4901 | G22: 3 | H22: 4 | I22: 2 | J22: 9 | K22: 1 | L22: 0 | M22: 1 | N22: 1.1 | O22: Elementos de Limpieza | Q22: 20000
A23: 5 | B23: 0 | C23: 0 | D23: 1 | E23: 0 | F23: 4901 | G23: 3 | H23: 6 | I23: 2 | J23: 9 | K23: 9 | L23: 0 | M23: 1 | N23: 1.1 | O23: Otros No Especificados Precedentemente (N.E.P.) | Q23: 1835
A24: 6 | B24: 0 | C24: 0 | D24: 1 | E24: 0 | F24: 4901 | G24: 1 | H24: 3 | I24: 2 | J24: 9 | K24: 1 | L24: 0 | M24: 1 | N24: 1.1 | O24: Elementos de Limpieza | Q24: 10000
A25: 7 | B25: 0 | C25: 0 | D25: 1 | E25: 0 | F25: 4901 | G25: 1 | H25: 3 | I25: 2 | J25: 9 | K25: 1 | L25: 0 | M25: 1 | N25: 1.1 | O25: Elementos de Limpieza | Q25: 10000
A26: 8 | B26: 0 | C26: 0 | D26: 1 | E26: 0 | F26: 4901 | G26: 3 | H26: 6 | I26: 2 | J26: 9 | K26: 9 | L26: 0 | M26: 1 | N26: 1.1 | O26: Otros No Especificados Precedentemente (N.E.P.) | Q26: 1890
A27: =+' NotaPedido'!A53:I53 -> COSTO ESTIMADO TOTAL: SON PESOS TRESCIENTOS SESENTA Y TRES MIL DOSCIENTOS OCHENTA Y OCHO CON 00/100 | Q27: =SUM(Q15:Q26) -> 363288
A29: JUSTIFICACIÓN:
A30: =' NotaPedido'!D8 -> Adquisición de ELEMENTOS DE LIMPIEZA para las distintas dependencias de este Ministerio.
