Workbook

Sheet Necesidades Trimestrales
A1: 2022
B2: Pedido de Necesidades Trimestrales
A4: JURISDICCION: | C4: 040 - Ministerio de Salud
A5: SAF N°: | C5: 011 - DIRECCION PROVINCIAL DE ADMINISTRACION - MS
A6: EJERCICIO: | C6: 2022
A7: TRIMESTRE: | C7: 1
A9: ID | B9: CODIGO ITEM | C9: RUBRO DE COMPRA | D9: I.P.P. | E9: DESCRIPCION | F9: UNIDAD DE MEDIDA | G9: CANTIDAD | H9: PRECIO UNITARIO ESTIMADO | I9: IMPORTE TOTAL ESTIMADO
A10: 1 | B10: 2.5.2-1816.3 | C10: PROD.MEDICO/FARMACEUTICOS/LAB | D10: 2.5.2 | E10: ANTIDIARREICOS; TIPO: MONODROGA, DROGA GENERICA: LOPERAMIDA, FORMA FARMACEUTICA: COMPRIMIDO, PRESENTACION: 2 mGr | F10: comprimido | G10: 2000 | H10: 2.6 | I10: =+G10*H10 -> 5200
A11: 2 | B11: 2.5.2-8078.68 | C11: PROD.MEDICO/FARMACEUTICOS/LAB | D11: 2.5.2 | E11: EXCIPIENTES; TIPO: MONODROGA, PRESENTACION: ENVASE X 1 Kg, COMPUESTO: CARBON ACTIVADO, CONCENTRACION/PUREZA: 100 % | F11: unidad | G11: 5 | H11: 2700 | I11: =+G11*H11 -> 13500
A12: 3 | B12: 2.5.2-1862.1 | C12: PROD.MEDICO/FARMACEUTICOS/LAB | D12: 2.5.2 | E12: HIPOGLUCEMIANTES ORALES; TIPO: MONODROGA, DROGA GENERICA: METFORMINA, FORMA FARMACEUTICA: COMPRIMIDO, PRESENTACION: 500 mGr | F12: comprimido | G12: 20000 | H12: 5 | I12: =+G12*H12 -> 100000
A13: 4 | B13: 2.5.2-1862.16 | C13: PROD.MEDICO/FARMACEUTICOS/LAB | D13: 2.5.2 | E13: HIPOGLUCEMIANTES ORALES; TIPO: MONODROGA, DROGA GENERICA: METFORMINA, FORMA FARMACEUTICA: COMPRIMIDO, PRESENTACION: 850 mGr | F13: comprimido | G13: 30000 | H13: 7.2 | I13: =+G13*H13 -> 216000
A14: 5 | B14: 2.5.2-1901.130 | C14: PROD.MEDICO/FARMACEUTICOS/LAB | D14: 2.5.2 | E14: VITAMINAS; TIPO: MONODROGA, DROGA GENERICA: VITAMINA D3 2000 UI/ML, FORMA FARMACEUTICA: SOLUCION, PRESENTACION: 2 ML | F14: frasco | G14: 500 | H14: 958 | I14: =+G14*H14 -> 479000
A15: 6 | B15: 2.5.2-7404.8 | C15: PROD.MEDICO/FARMACEUTICOS/LAB | D15: 2.5.2 | E15: COAGULANTES P/PERSONAS; TIPO: MONODROGA, DROGA GENERICA: PROTAMINA 50 mGr, FORMA FARMACEUTICA: AMPOLLA, PRESENTACION: ENVASE X 5 mL | F15: ampolla | G15: 50 | H15: 1100 | I15: =+G15*H15 -> 55000
A16: 7 | B16: 2.5.2-1865.11 | C16: PROD.MEDICO/FARMACEUTICOS/LAB | D16: 2.5.2 | E16: ANTIEPILEPTICOS; TIPO: MONODROGA, DROGA GENERICA: CLONAZEPAN, FORMA FARMACEUTICA: COMPRIMIDO, PRESENTACION: 0.50 mGr | F16: comprimido | G16: 6000 | H16: 4.3 | I16: =+G16*H16 -> 25800
A17: 8 | B17: 2.5.2-2233.5 | C17: PROD.MEDICO/FARMACEUTICOS/LAB | D17: 2.5.2 | E17: ANTICONVULSIVANTES; TIPO: MONODROGA, FORMA FARMACEUTICA: COMPRIMIDO, PRESENTACION: 100 mGr, DROGA GENERICA: FENITOINA | F17: comprimido | G17: 50000 | H17: 5.87 | I17: =+G17*H17 -> 293500
A18: 9 | B18: 2.5.2-1839.26 | C18: PROD.MEDICO/FARMACEUTICOS/LAB | D18: 2.5.2 | E18: VASODILATADORES CORONARIOS; TIPO: MONODROGA, DROGA GENERICA: DILTIAZEM CLORHIDRATO 25 mGr, FORMA FARMACEUTICA: AMPOLLA, PRESENTACION: ENVASE X 5 mL | F18: ampolla | G18: 200 | H18: 1850 | I18: =+G18*H18 -> 370000
A19: 10 | B19: 2.5.2-1839.38 | C19: PROD.MEDICO/FARMACEUTICOS/LAB | D19: 2.5.2 | E19: VASODILATADORES CORONARIOS; TIPO: MONODROGA, DROGA GENERICA: DINITRATO DE ISOSORBIDE 5 mGr, FORMA FARMACEUTICA: COMPRIMIDO, PRESENTACION: ENVASE X 30 UN | F19: caja | G19: 5 | H19: 1199 | I19: =+G19*H19 -> 5995
A20: 11 | B20: 2.5.2-1837.64 | C20: PROD.MEDICO/FARMACEUTICOS/LAB | D20: 2.5.2 | E20: HIPOTENSORES; TIPO: MONODROGA, DROGA GENERICA: NITROPRUSIATO DE SODIO, FORMA FARMACEUTICA: FRASCO AMPOLLA, PRESENTACION: ENVASE X 50 mGr | F20: ampolla | G20: 700 | H20: 950 | I20: =+G20*H20 -> 665000
A21: TOTAL RUBRO | I21: =SUM(I10:I20) -> 2228995
C24: DETALLE TECNICO Y ESPECIFICACIONES | D24: ANEXO 1-Para oferentes de la Provincia de Catamarca deberán presentar Habilitación Provincial para comercializar el producto que cotizan. 2-Para el resto de oferentes deberán presentar Certificado de Inscripción de ANMAT vigente al momento de la oferta, el mismo deberá ser correspondiente al objeto de la contratación y de encontrarse vencido adjuntar la solicitud de renovación. 3-No se aceptarán ofertas de productos no registrados y autorizada su venta por ANMAT. Se deberá especificar en cada ítem de la propuesta, marca y número de certificado otorgado por dicho ente regulador. 4-Los productos deberán tener un vencimiento posterior a doce (12) meses a partir de la fecha de su recepción.
C26: Plazos de entrega | D26: veinte (20) dias habiles
C28: Lugar de Entrega: | D28: ITEMS 1, 2, 3, 4, 5, 6, 7, 8, 9 y 11 - DIR. PROV. DE FARMACIA E INSUMOS - CHACABUCO N° 169 - en el horario de 8:00hs a 12:00hs de lunes a viernes
D29: ITEM 10 - DIR. PROV. SIST. DE ATENCION MEDICA DE EMERGENCIA - CASEROS N° 864 - en el horario de 8:00hs a 12:00hs de lunes a viernes
C31: Calidad Minima esperada
C33: Mantenimiento | D33: cuarenta y cinco (45) días
C36: ITEM 10
C37: Especificidades: VASODILATADORES CORONARIOS; TIPO: MONODROGA, DROGA GENERICA: DINITRATO DE ISOSORBIDE 5 mGr, FORMA FARMACEUTICA: COMPRIMIDO, PRESENTACION: ENVASE X 30 UN COMPRIMIDO SUBLINGUAL
C38: Lugar de Entrega: D.P.S.A.M.E. - Caseros N° 864 DE 08:00 A 12:00HS., DEBIENDO CORRER LOS GASTOS DE FLETES, ACARREO, CARGA, DESCARGA Y SEGURO A CARGO DEL ADJUDICATARIO.
C40: Plazo de entrega: veinte (20) dias habiles
C41: Calidad Minima esperada:
C42: Mantenimiento: 45 dias habiles

Sheet NP FARMACIA
A1: NOTA DE PEDIDO | J1: N° | K1: 15/2022
A3: JURISDICCIÓN: | D3: ='Necesidades Trimestrales'!C4 -> 040 - Ministerio de Salud
A4: SAF: | D4: ='Necesidades Trimestrales'!C5 -> 011 - DIRECCION PROVINCIAL DE ADMINISTRACION - MS
A5: UNIDAD EJECUTORA: | D5: 469 - DIRECCION PROVINCIAL DE FARMACIA E INSUMOS
A6: DEPENDENCIA SOLICITANTE: | D6: 469 - DIRECCION PROVINCIAL DE FARMACIA E INSUMOS
A7: PERIODO UTILIZACIÓN: | D7: TRIMESTRAL
A8: OBJETO: | D8: ADQUISICION DE MEDICAMENTOS.
A10: Ítem | B10: Codigo Item | C10: DESCRIPCIÓN | H10: Adjunta Detalle Técnico | I10: Unidad Medida | J10: Precio Unitario Estimado | K10: Cantidad Solicitada
A12: 1 | B12: =+'Necesidades Trimestrales'!B10 -> 2.5.2-1816.3 | C12: =+'Necesidades Trimestrales'!E10 -> ANTIDIARREICOS; TIPO: MONODROGA, DROGA GENERICA: LOPERAMIDA, FORMA FARMACEUTICA: COMPRIMIDO, PRESENTACION: 2 mGr | H12: NO | I12: =+'Necesidades Trimestrales'!F10 -> comprimido | J12: =+'Necesidades Trimestrales'!H10 -> 2.6 | K12: =+'Necesidades Trimestrales'!G10 -> 2000
A13: 2 | B13: =+'Necesidades Trimestrales'!B11 -> 2.5.2-8078.68 | C13: =+'Necesidades Trimestrales'!E11 -> EXCIPIENTES; TIPO: MONODROGA, PRESENTACION: ENVASE X 1 Kg, COMPUESTO: CARBON ACTIVADO, CONCENTRACION/PUREZA: 100 % | H13: NO | I13: =+'Necesidades Trimestrales'!F11 -> unidad | J13: =+'Necesidades Trimestrales'!H11 -> 2700 | K13: =+'Necesidades Trimestrales'!G11 -> 5
A14: 3 | B14: =+'Necesidades Trimestrales'!B12 -> 2.5.2-1862.1 | C14: =+'Necesidades Trimestrales'!E12 -> HIPOGLUCEMIANTES ORALES; TIPO: MONODROGA, DROGA GENERICA: METFORMINA, FORMA FARMACEUTICA: COMPRIMIDO, PRESENTACION: 500 mGr | H14: NO | I14: =+'Necesidades Trimestrales'!F12 -> comprimido | J14: =+'Necesidades Trimestrales'!H12 -> 5 | K14: =+'Necesidades Trimestrales'!G12 -> 20000
A15: 4 | B15: =+'Necesidades Trimestrales'!B13 -> 2.5.2-1862.16 | C15: =+'Necesidades Trimestrales'!E13 -> HIPOGLUCEMIANTES ORALES; TIPO: MONODROGA, DROGA GENERICA: METFORMINA, FORMA FARMACEUTICA: COMPRIMIDO, PRESENTACION: 850 mGr | H15: NO | I15: =+'Necesidades Trimestrales'!F13 -> comprimido | J15: =+'Necesidades Trimestrales'!H13 -> 7.2 | K15: =+'Necesidades Trimestrales'!G13 -> 30000
A16: 5 | B16: =+'Necesidades Trimestrales'!B14 -> 2.5.2-1901.130 | C16: =+'Necesidades Trimestrales'!E14 -> VITAMINAS; TIPO: MONODROGA, DROGA GENERICA: VITAMINA D3 2000 UI/ML, FORMA FARMACEUTICA: SOLUCION, PRESENTACION: 2 ML | H16: NO | I16: =+'Necesidades Trimestrales'!F14 -> frasco | J16: =+'Necesidades Trimestrales'!H14 -> 958 | K16: =+'Necesidades Trimestrales'!G14 -> 500
A17: 6 | B17: =+'Necesidades Trimestrales'!B15 -> 2.5.2-7404.8 | C17: =+'Necesidades Trimestrales'!E15 -> COAGULANTES P/PERSONAS; TIPO: MONODROGA, DROGA GENERICA: PROTAMINA 50 mGr, FORMA FARMACEUTICA: AMPOLLA, PRESENTACION: ENVASE X 5 mL | H17: NO | I17: =+'Necesidades Trimestrales'!F15 -> ampolla | J17: =+'Necesidades Trimestrales'!H15 -> 1100 | K17: =+'Necesidades Trimestrales'!G15 -> 50
A18: 7 | B18: =+'Necesidades Trimestrales'!B16 -> 2.5.2-1865.11 | C18: =+'Necesidades Trimestrales'!E16 -> ANTIEPILEPTICOS; TIPO: MONODROGA, DROGA GENERICA: CLONAZEPAN, FORMA FARMACEUTICA: COMPRIMIDO, PRESENTACION: 0.50 mGr | H18: NO | I18: =+'Necesidades Trimestrales'!F16 -> comprimido | J18: =+'Necesidades Trimestrales'!H16 -> 4.3 | K18: =+'Necesidades Trimestrales'!G16 -> 6000
A19: 8 | B19: =+'Necesidades Trimestrales'!B17 -> 2.5.2-2233.5 | C19: =+'Necesidades Trimestrales'!E17 -> ANTICONVULSIVANTES; TIPO: MONODROGA, FORMA FARMACEUTICA: COMPRIMIDO, PRESENTACION: 100 mGr, DROGA GENERICA: FENITOINA | H19: NO | I19: =+'Necesidades Trimestrales'!F17 -> comprimido | J19: =+'Necesidades Trimestrales'!H17 -> 5.87 | K19: =+'Necesidades Trimestrales'!G17 -> 50000
A20: 9 | B20: =+'Necesidades Trimestrales'!B18 -> 2.5.2-1839.26 | C20: =+'Necesidades Trimestrales'!E18 -> VASODILATADORES CORONARIOS; TIPO: MONODROGA, DROGA GENERICA: DILTIAZEM CLORHIDRATO 25 mGr, FORMA FARMACEUTICA: AMPOLLA, PRESENTACION: ENVASE X 5 mL | H20: NO | I20: =+'Necesidades Trimestrales'!F18 -> ampolla | J20: =+'Necesidades Trimestrales'!H18 -> 1850 | K20: =+'Necesidades Trimestrales'!G18 -> 200
A21: 10 | B21: =+'Necesidades Trimestrales'!B20 -> 2.5.2-1837.64 | C21: =+'Necesidades Trimestrales'!E20 -> HIPOTENSORES; TIPO: MONODROGA, DROGA GENERICA: NITROPRUSIATO DE SODIO, FORMA FARMACEUTICA: FRASCO AMPOLLA, PRESENTACION: ENVASE X 50 mGr | H21: NO | I21: =+'Necesidades Trimestrales'!F20 -> ampolla | J21: =+'Necesidades Trimestrales'!H20 -> 950 | K21: =+'Necesidades Trimestrales'!G20 -> 700
A23: Costo total estimado: DOS MILLONES DOSCIENTOS VEINTITRES MIL con 00/100. | J23: =SUMPRODUCT(J12:J22,K12:K22) -> 2223000

Sheet APG FARMACIA
A1: EJERCICIO: | D1: ='Necesidades Trimestrales'!C6 -> 2022 | P1: AUTORIZACION PARA GASTAR
A4: JURISDICCIÓN: | G4: ='NP FARMACIA'!D3 -> 040 - Ministerio de Salud
A5: SAF: | G5: ='NP FARMACIA'!D4 -> 011 - DIRECCION PROVINCIAL DE ADMINISTRACION - MS
A6: UNIDAD EJECUTORA: | G6: ='NP FARMACIA'!D5 -> 469 - DIRECCION PROVINCIAL DE FARMACIA E INSUMOS
A7: DEPENDENCIA SOLICITANTE: | G7: ='NP FARMACIA'!D6 -> 469 - DIRECCION PROVINCIAL DE FARMACIA E INSUMOS
A8: AUTORIZACIÓN:
A9: Señor Jefe de Servicio Administrativo Financiero:
A10: ="Autorizo la realización de los trámites correspondientes, a fin de proveer a este Organismo los bienes y/o servicios que se detallan en Nota de Pedido N° " & 'NP FARMACIA'!K1&", afectando la erogación resultante a los créditos presupuestarios aprobados a favor de esta Unidad Ejecutora, conforme al siguiente detalle:" -> Autorizo la realización de los trámites correspondientes, a fin de proveer a este Organismo los bienes y/o servicios que se detallan en Nota de Pedido N° 15/2022, afectando la erogación resultante a los créditos presupuestarios aprobados a favor de esta Unidad Ejecutora, conforme al siguiente detalle:
A12: IMPUTACIÓN PRESUPUESTARIA
A13: CÓDIGO | O13: DENOMINACIÓN DE LA PARTIDA PRESUPUESTARIA | Q13: IMPORTE
A14: PR | B14: SB | C14: PY | D14: AC | E14: OB | F14: UG | G14: FIN | H14: FUN | I14: I | J14: P | K14: P | L14: SubP | M14: M | N14: FF
A15: 30 | D15: 1 | F15: 4901 | G15: 3 | H15: 1 | I15: 2 | J15: 5 | K15: 2 | M15: 1 | N15: 1.1 | O15: PRODUCTOS FARMACEUTICOS Y MEDICINALES | Q15: ='NP FARMACIA'!J23 -> 2223000
A23: TOTAL DE PESOS: DOS MILLONES DOSCIENTOS VEINTITRES MIL con 00/100. | Q23: =SUM(Q15:Q22) -> 2223000
A25: JUSTIFICACIÓN:
A26: ='NP FARMACIA'!D8 -> ADQUISICION DE MEDICAMENTOS.

Sheet NP SAME
A1: NOTA DE PEDIDO | J1: N° | K1: 11/2022
A3: JURISDICCIÓN: | D3: ='Necesidades Trimestrales'!C4 -> 040 - Ministerio de Salud
A4: SAF: | D4: ='Necesidades Trimestrales'!C5 -> 011 - DIRECCION PROVINCIAL DE ADMINISTRACION - MS
A5: UNIDAD EJECUTORA: | D5: 748 - DIR. PROV. DEL SISTEMA DE ATENCION MEDICA DE EMERGENCIA
A6: DEPENDENCIA SOLICITANTE: | D6: 748 - DIR. PROV. DEL SISTEMA DE ATENCION MEDICA DE EMERGENCIA
A7: PERIODO UTILIZACIÓN: | D7: TRIMESTRAL
A8: OBJETO: | D8: ADQUISICION DE MEDICAMENTOS.
A10: Ítem | B10: Codigo Item | C10: DESCRIPCIÓN | H10: Adjunta Detalle Técnico | I10: Unidad Medida | J10: Precio Unitario Estimado | K10: Cantidad Solicitada
A12: 1 | B12: =+'Necesidades Trimestrales'!B19 -> 2.5.2-1839.38 | C12: =+'Necesidades Trimestrales'!E19 -> VASODILATADORES CORONARIOS; TIPO: MONODROGA, DROGA GENERICA: DINITRATO DE ISOSORBIDE 5 mGr, FORMA FARMACEUTICA: COMPRIMIDO, PRESENTACION: ENVASE X 30 UN | H12: NO | I12: =+'Necesidades Trimestrales'!F19 -> caja | J12: =+'Necesidades Trimestrales'!H19 -> 1199 | K12: =+'Necesidades Trimestrales'!G19 -> 5
A14: Costo total estimado: CINCO MIL NOVECIENTOS NOVENTA Y CINCO con 00/100. | J14: =SUMPRODUCT(J12:J13,K12:K13) -> 5995

Sheet APG SAME
A1: EJERCICIO: | D1: ='Necesidades Trimestrales'!C6 -> 2022 | P1: AUTORIZACION PARA GASTAR
A4: JURISDICCIÓN: | G4: ='NP SAME'!D3 -> 040 - Ministerio de Salud
A5: SAF: | G5: ='NP SAME'!D4 -> 011 - DIRECCION PROVINCIAL DE ADMINISTRACION - MS
A6: UNIDAD EJECUTORA: | G6: ='NP SAME'!D5 -> 748 - DIR. PROV. DEL SISTEMA DE ATENCION MEDICA DE EMERGENCIA
A7: DEPENDENCIA SOLICITANTE: | G7: ='NP SAME'!D6 -> 748 - DIR. PROV. DEL SISTEMA DE ATENCION MEDICA DE EMERGENCIA
A8: AUTORIZACIÓN:
A9: Señor Jefe de Servicio Administrativo Financiero:
A10: ="Autorizo la realización de los trámites correspondientes, a fin de proveer a este Organismo los bienes y/o servicios que se detallan en Nota de Pedido N° " & 'NP SAME'!K1&", afectando la erogación resultante a los créditos presupuestarios aprobados a favor de esta Unidad Ejecutora, conforme al siguiente detalle:" -> Autorizo la realización de los trámites correspondientes, a fin de proveer a este Organismo los bienes y/o servicios que se detallan en Nota de Pedido N° 11/2022, afectando la erogación resultante a los créditos presupuestarios aprobados a favor de esta Unidad Ejecutora, conforme al siguiente detalle:
A12: IMPUTACIÓN PRESUPUESTARIA
A13: CÓDIGO | O13: DENOMINACIÓN DE LA PARTIDA PRESUPUESTARIA | Q13: IMPORTE
A14: PR | B14: SB | C14: PY | D14: AC | E14: OB | F14: UG | G14: FIN | H14: FUN | I14: I | J14: P | K14: P | L14: SubP | M14: M | N14: FF
A15: 31 | D15: 1 | F15: 4901 | G15: 3 | H15: 1 | I15: 2 | J15: 5 | K15: 2 | M15: 1 | N15: 1.1 | O15: PRODUCTOS FARMACEUTICOS Y MEDICINALES | Q15: ='NP SAME'!J14 -> 5995
A23: TOTAL DE PESOS: CINCO MIL NOVECIENTOS NOVENTA Y CINCO con 00/100. | Q23: =SUM(Q15:Q22) -> 5995
A25: JUSTIFICACIÓN:
A26: ='NP SAME'!D8 -> ADQUISICION DE MEDICAMENTOS.
