Workbook

Sheet Necesidades Trimestrales
B1: Pedido de Necesidades Trimestrales
R2: camionetas c/l
A3: JURISDICCION: | C3: 90 - Ministerio de Seguridad | R3: 58134.323
A4: SAF N°: | C4: 7 - Direccion Provincial de Administracion de la Policia de Catamarca | R4: 54108.007
A5: EJERCICIO: | C5: 2022 | R5: 55772.495
A6: TRIMESTRE: | C6: 2 | R6: 54108.007
K7: PRECIO UNITARIO | L7: CANTIDAD | M7: TOTAL*UNIDAD | N7: CANT VEH | O7: TOTAL | R7: 55772.495
A8: ID | B8: CODIGO ITEM | C8: RUBRO DE COMPRA | D8: I.P.P. | E8: DESCRIPCION | F8: UNIDAD DE MEDIDA | G8: CANTIDAD | H8: PRECIO UNITARIO ESTIMADO | I8: IMPORTE TOTAL ESTIMADO | K8: x año | L8: cant scio | M8: total | N8: unidades | O8: total | R8: 55772.495
A9: 1 | B9: 3.5.4-2065.1 | C9: BANCOS Y SEGUROS | D9: 3.5.4 | E9: SEGURO DE RESPONSABILIDAD; DESCRIPCION: SEGURO DE RESPONSABILIDAD | F9: UNIDAD | G9: 1 | H9: =O9 -> 129298.01 | I9: =H9*G9 -> 129298.01 | K9: 10774.834 | L9: 1 | M9: =K9*L9 -> 10774.834 | N9: 12 | O9: =M9*N9 -> 129298.01 | R9: 60770.107
A10: 2 | B10: 3.5.4-2065.1 | C10: BANCOS Y SEGUROS | D10: 3.5.4 | E10: SEGURO DE RESPONSABILIDAD; DESCRIPCION: SEGURO DE RESPONSABILIDAD | F10: UNIDAD | G10: 1 | H10: =O10 -> 1679193.4 | I10: =H10*G10 -> 1679193.4 | K10: 7176.04 | L10: 1 | M10: =K10*L10 -> 7176.04 | N10: 234 | O10: =M10*N10 -> 1679193.4 | R10: 60770.107
A11: 3 | B11: 3.5.4-2065.1 | C11: BANCOS Y SEGUROS | D11: 3.5.4 | E11: SEGURO DE RESPONSABILIDAD; DESCRIPCION: SEGURO DE RESPONSABILIDAD | F11: UNIDAD | G11: 1 | H11: =O11 -> 1549192.1 | I11: =H11*G11 -> 1549192.1 | K11: =R31 -> 57377.484 | L11: 1 | M11: =K11*L11 -> 57377.484 | N11: 27 | O11: =M11*N11 -> 1549192.1 | R11: 60770.107
A12: 4 | B12: 3.5.4-2065.1 | C12: BANCOS Y SEGUROS | D12: 3.5.4 | E12: SEGURO DE RESPONSABILIDAD; DESCRIPCION: SEGURO DE RESPONSABILIDAD | F12: UNIDAD | G12: 1 | H12: =O12 -> 168000 | I12: =H12*G12 -> 168000 | K12: 56000 | L12: 1 | M12: =K12*L12 -> 56000 | N12: 3 | O12: =M12*N12 -> 168000 | R12: 54108.007
A13: 5 | B13: 3.5.4-2065.1 | C13: BANCOS Y SEGUROS | D13: 3.5.4 | E13: SEGURO DE RESPONSABILIDAD; DESCRIPCION: SEGURO DE RESPONSABILIDAD | F13: UNIDAD | G13: 1 | H13: =O13 -> 48544 | I13: =H13*G13 -> 48544 | K13: 24272 | L13: 1 | M13: =K13*L13 -> 24272 | N13: 2 | O13: =M13*N13 -> 48544 | R13: 60770.107
I14: =SUM(I9:I13) -> 3574227.4 | R14: 60770.107
R15: 60770.107
B16: Especificidades Item N° 1: | R16: 60770.107
C17: CARACTERÍSTICAS: “Seguro Obligatorio de Responsabilidad Civil del Automotor conforme Res. SSN N° 35.863, 36.100 y modificatorias. Responsabilidad Civil con límites, en la República Argentina y países limítrofes: por lesiones y/o muerte y daños a cosas de terceros no transportados por acontecimientos hasta la suma de pesos 6.000.000,00. Extensión a países limítrofes sin cargo” de VEHICULO: AUTOS; TOTAL DE VEHICULOS: 12 (DOCE) que integran el Parque Automotor Policial, cuyos datos se detallan en Anexo. VIGENCIA: desde el 29/06/2022 al 29/06/2023. (ANUAL- 12 MESES) ANEXO I ORDEN 01 AL 12.- | G17: =1600*12 -> 19200 | R17: 51887.307
B18: Especificidades Item N° 2: | G18: =G17*9 -> 172800 | R18: 42308.212
C19: CARACTERÍSTICAS: “Seguro Obligatorio de Responsabilidad Civil del Automotor conforme Res. SSN N° 35.863, 36.100 y modificatorias. Responsabilidad Civil con límites, en la República Argentina y países limítrofes: por lesiones y/o muerte y daños a cosas de terceros no transportados por acontecimientos hasta la suma de pesos 6.000.000,00. Extensión a países limítrofes sin cargo” de VEHICULO: MOTOS; TOTAL DE VEHICULOS: 234 (DOSCIENTOS TREINTA Y DOS) que integran el Parque Automotor Policial, cuyos datos se detallan en Anexo. VIGENCIA: desde el 29/06/2022 al 29/06/2023. (ANUAL- 12 MESES) ANEXO I ORDEN 13 AL 246. | G19: =900*12 -> 10800 | R19: 58694.236
B20: Especificidades Item N° 3: | G20: =G19*71 -> 766800 | R20: 60770.107
C21: CARACTERÍSTICAS: “Seguro Obligatorio de Responsabilidad Civil del Automotor conforme Res. SSN N° 35.863, 36.100 y modificatorias. Responsabilidad Civil con límites, en la República Argentina y países limítrofes: por lesiones y/o muerte y daños a cosas de terceros no transportados por acontecimientos hasta la suma de pesos 6.000.000,00. Extensión a países limítrofes sin cargo Y DAÑOS PARCIALES: seguro para cristales, vidrios Parabrisas. Cubre rotura o rajadura de cristales, vidrios, incluyendo los gastos normales de colocación” de VEHICULO: CAMIONETA; TOTAL DE VEHICULOS: 27 (VEINTISIETE) que integran el Parque Automotor Policial, cuyos datos se detallan en Anexo. VIGENCIA: desde el 29/06/2022 al 29/06/2023. (ANUAL- 12 MESES) ANEXO I ORDEN 247 AL 273. | G21: =3200*12 -> 38400 | R21: 60770.107
B22: Especificidades Item N° 4: | G22: =107*G21 -> 4108800 | R22: 59954.802
C23: CARACTERÍSTICAS: “Seguro Obligatorio de Responsabilidad Civil del Automotor conforme Res. SSN N° 35.863, 36.100 y modificatorias. Responsabilidad Civil con límites, en la República Argentina y países limítrofes: por lesiones y/o muerte y daños a cosas de terceros no transportados por acontecimientos hasta la suma de pesos 6.000.000,00. Extensión a países limítrofes sin cargo” de VEHICULO: UTILITARIO; TOTAL DE VEHICULOS: 03 (TRES) que integran el Parque Automotor Policial, cuyos datos se detallan en Anexo. VIGENCIA: desde el 29/06/2022 al 29/06/2023. (ANUAL- 12 MESES) 274 AL 276. | G23: =1023*12 -> 12276 | R23: 59954.802
B24: Especificidades Item N° 5: | G24: =G23*6 -> 73656 | R24: 59954.802
C25: CARACTERÍSTICAS: “Seguro Obligatorio de Responsabilidad Civil del Automotor conforme Res. SSN N° 35.863, 36.100 y modificatorias. Responsabilidad Civil con límites, en la República Argentina y países limítrofes: por lesiones y/o muerte y daños a cosas de terceros no transportados por acontecimientos hasta la suma de pesos 6.000.000,00. Extensión a países limítrofes sin cargo” de VEHICULO: CAMIONES: TOTAL DE VEHICULOS: 02 (DOS) que integran el Parque Automotor Policial, cuyos datos se detallan en Anexo. VIGENCIA: desde el 29/06/2022 al 29/06/2023. (ANUAL- 12 MESES) ANEXO I ORDEN 277 AL 278. | G25: =G17 -> 19200 | R25: 59954.802
B26: Plazos y lugares de entrega | R26: 59954.802
C27: a) LUGAR DE ENTREGA: SECCION CONTROL PATRIMONIAL (Dpto Logística), sito en Chacabuco N° 809 - Capital - De 08 a 12 horas. b) FORMA DE LA ENTREGA: Las Pólizas deben entregarse detallando el vehículo que está cubriendo el seguro contratado. c) PLAZO DE ENTREGA: El Oferente deberá establecer plazo de entrega de los elementos cotizados, debiendo ser expresado en días hábiles; que no podrá ser superior a cinco (5) días hábiles, contados a partir de la recepción de la comunicación prevista en el Artículo 80° de del Reglamento Parcial N° 2 de la ley 4938. | R27: 63070.666
R28: 47869.617
B29: Calidad Minima esperada | R29: 50881.228
C30: Que cumpla íntegramente con lo solicitado y se extienda a todo y cada uno de los vehiculos desagregados en la planilla anexa a la presente. | R30: =SUM(R3:R29) -> 1549192.1
B31: Mantenimiento | R31: =R30/27 -> 57377.484
C32: 30 (treinta) días
B33: Garantia
C34: *

Sheet  NotaPedido
A1: NOTA DE PEDIDO | J1: N° | K1: 41/2020
A3: JURISDICCIÓN: | D3: ='Necesidades Trimestrales'!#REF! -> #REF!
A4: SAF: | D4: ='Necesidades Trimestrales'!#REF! -> #REF!
A5: UNIDAD EJECUTORA: | D5: Jefatura de Policía de la Provincia de Catamarca
A6: DEPENDENCIA SOLICITANTE: | D6: Sección Control Patrimonial - Dpto. Logistica (D-4)
A7: PERIODO UTILIZACIÓN: | D7: ='Necesidades Trimestrales'!C6 & "° Trimestre - Año " & 'Necesidades Trimestrales'!C5 -> 2° Trimestre - Año 2022
A8: OBJETO: | D8: Renovacion de Seguro Obligatorio de Responsabilidad Civil del Automotor
A10: Ítem | B10: Codigo Item | C10: DESCRIPCIÓN | H10: Adjunta Detalle Técnico | I10: Unidad Medida | J10: Precio Unitario Estimado | K10: Cantidad Solicitada
A12: 1 | B12: ='Necesidades Trimestrales'!B9 -> 3.5.4-2065.1 | C12: ='Necesidades Trimestrales'!E9 -> SEGURO DE RESPONSABILIDAD; DESCRIPCION: SEGURO DE RESPONSABILIDAD | H12: SI | I12: ='Necesidades Trimestrales'!F9 -> UNIDAD | J12: ='Necesidades Trimestrales'!H9 -> 129298.01 | K12: ='Necesidades Trimestrales'!G9 -> 1
A13: Costo total estimado: | D13: Un Millon Quinientos Diecisiete Mil Cientoo Noventa y Nuene con 57/100 | J13: ='Necesidades Trimestrales'!I9 -> 129298.01

Sheet Autor Gastar
A1: EJERCICIO: | D1: ='Necesidades Trimestrales'!C5 -> 2022 | P1: AUTORIZACION PARA GASTAR
A4: JURISDICCIÓN: | G4: =' NotaPedido'!D3 -> #REF!
A5: SAF: | G5: =' NotaPedido'!D4 -> #REF!
A6: UNIDAD EJECUTORA: | G6: =' NotaPedido'!D5 -> Jefatura de Policía de la Provincia de Catamarca
A7: DEPENDENCIA SOLICITANTE: | G7: =' NotaPedido'!D6 -> Sección Control Patrimonial - Dpto. Logistica (D-4)
A8: AUTORIZACIÓN:
A9: Señor Jefe de Servicio Administrativo Financiero:
A10: ="Autorizo la realización de los trámites correspondientes, a fin de proveer a este Organismo los bienes y/o servicios que se detallan en Nota de Pedido N° " & ' NotaPedido'!K1&", afectando la erogación resultante a los créditos presupuestarios aprobados a favor de esta Unidad Ejecutora, conforme al siguiente detalle:" -> Autorizo la realización de los trámites correspondientes, a fin de proveer a este Organismo los bienes y/o servicios que se detallan en Nota de Pedido N° 41/2020, afectando la erogación resultante a los créditos presupuestarios aprobados a favor de esta Unidad Ejecutora, conforme al siguiente detalle:
A12: IMPUTACIÓN PRESUPUESTARIA
A13: CÓDIGO | O13: DENOMINACIÓN DE LA PARTIDA PRESUPUESTARIA | Q13: IMPORTE
A14: PR | B14: SB | C14: PY | D14: AC | E14: OB | F14: UG | G14: FIN | H14: FUN | I14: I | J14: P | K14: P | L14: SubP | M14: M | N14: FF
A15: 16 | B15: 0 | C15: 0 | D15: 1 | E15: 0 | F15: 10 | G15: 2 | H15: 1 | I15: =LEFT('Necesidades Trimestrales'!D9,1) -> 3 | J15: =MID('Necesidades Trimestrales'!D9,3,1) -> 5 | K15: =RIGHT('Necesidades Trimestrales'!D9,1) -> 4 | L15: 0 | M15: 1 | N15: 1.1 | O15: PRIMAS Y GASTOS DE SEGUROS | Q15: ='Necesidades Trimestrales'!I9 -> 129298.01
A16: TOTAL DE PESOS: | Q16: =SUM(Q15) -> 129298.01
A17: =' NotaPedido'!D13 -> Un Millon Quinientos Diecisiete Mil Cientoo Noventa y Nuene con 57/100
A19: JUSTIFICACIÓN:
A20: Para la Renovaciòn de Seguro Obligatorio de Responsabilidad Civil del Automotor para los vehiculos pertenecientes a la Institucion Policial.-
