Workbook

Sheet Necesidades Trimestrales
B2: Pedido de Necesidades Trimestrales
A4: JURISDICCION: | C4: 040 - Ministerio de Salud
A5: SAF N°: | C5: 024 - Hospital Interzonal de Niños
A6: EJERCICIO: | C6: 2021
A7: TRIMESTRE: | C7: 1
A9: ID | B9: CODIGO ITEM | C9: RUBRO DE COMPRA | D9: DESCRIPCION | E9: UNIDAD DE MEDIDA | F9: CANTIDAD | G9: PRECIO UNITARIO ESTIMADO | H9: IMPORTE TOTAL ESTIMADO
A10: 1 | B10: 295 | C10: PROD. MEDICO/FARMACEUTICOS/LAB | D10: AGUJA DESCARTABLE 16/5 | E10: UNIDAD | F10: 22500 | G10: 1.2 | H10: =G10*F10 -> 27000
A11: 2 | B11: 295 | C11: PROD. MEDICO/FARMACEUTICOS/LAB | D11: AGUJA DESCARTABLE 25/8 | E11: UNIDAD | F11: 22500 | G11: 1.2 | H11: =G11*F11 -> 27000
A12: 3 | B12: 295 | C12: PROD. MEDICO/FARMACEUTICOS/LAB | D12: AGUJA DESCARTABLE 40/12 | E12: UNIDAD | F12: 1000 | G12: 1.55 | H12: =G12*F12 -> 1550
A13: 4 | B13: 295 | C13: PROD. MEDICO/FARMACEUTICOS/LAB | D13: AGUJA DESCARTABLE 40/8 | E13: UNIDAD | F13: 15000 | G13: 1.2 | H13: =G13*F13 -> 18000
A14: 5 | B14: 295 | C14: PROD. MEDICO/FARMACEUTICOS/LAB | D14: AGUJA DESCARTABLE 50/8 | E14: UNIDAD | F14: 1000 | G14: 1.55 | H14: =G14*F14 -> 1550
A15: 6 | B15: 295 | C15: PROD. MEDICO/FARMACEUTICOS/LAB | D15: ALGODÓN x 500 GRS.TIPO DONCELLA | E15: UNIDAD | F15: 1000 | G15: 251.1 | H15: =G15*F15 -> 251100
A16: 7 | B16: 295 | C16: PROD. MEDICO/FARMACEUTICOS/LAB | D16: BAJALENGUA X 100 UNIDADES | E16: UNIDAD | F16: 1000 | G16: 110.9 | H16: =G16*F16 -> 110900
A17: 8 | B17: 295 | C17: PROD. MEDICO/FARMACEUTICOS/LAB | D17: BOTAS ALTAS DESCARTABLES DE 30 GRAMOS CON TIRA EL PAR | E17: UNIDAD | F17: 5000 | G17: 35.44 | H17: =G17*F17 -> 177200
A18: 9 | B18: 295 | C18: PROD. MEDICO/FARMACEUTICOS/LAB | D18: BOLSA P/SANGRE TRIPLE T/CPD ADENINA C/SAFMAN 450 ML | E18: UNIDAD | F18: 400 | G18: 888 | H18: =G18*F18 -> 355200
A19: 10 | B19: 295 | C19: PROD. MEDICO/FARMACEUTICOS/LAB | D19: CAMISOLINES DES. SMS CON MANGAS Y PUÑO DE 1,40 MTS. DE LARGO, 30 GRS. COLOR AZUL | E19: UNIDAD | F19: 2000 | G19: 179 | H19: =G19*F19 -> 358000
A20: 11 | B20: 295 | C20: PROD. MEDICO/FARMACEUTICOS/LAB | D20: CATETER INTRAVENOSO Nº 22 TIPO HOSPIRA/BD | E20: UNIDAD | F20: 4000 | G20: 44.95 | H20: =G20*F20 -> 179800
A21: 12 | B21: 295 | C21: PROD. MEDICO/FARMACEUTICOS/LAB | D21: CATETER INTRAVENOSO Nº 24 TIPO HOSPIRA/BD | E21: UNIDAD | F21: 4000 | G21: 44.95 | H21: =G21*F21 -> 179800
... A136: 127 | B136: 295 | C136: PROD. MEDICO/FARMACEUTICOS/LAB | D136: BARBIJOS N95-TIPO 3M | E136: UNIDAD | F136: 3000 | G136: 410 | H136: =G136*F136 -> 1230000
B139: Plazos y lugares de entrega
B140: Lugar de Entrega: SERVICIO DE FARMACIA -HOSPITAL INT. DE NIÑOS – AV. VIRGEN DEL VALLE N° 1050-CATAMARCA DE 8:00 A 12:00HS., DEBIENDO CORRER LOS GASTOS DE FLETES, ACARREO, CARGA, DESCARGA Y SEGURO A CARGO DEL ADJUDICATARIO.
B142: Plazo de entrega: Dentro de los 7 días de notificada la Orden de Compra
B143: Mantenimiento
C144: 45 dias habiles
B146: Caracteristicas Técnicas
B147: Item 43: Tipo Braun
B148: Item 122: De 2tros de capacidad
B149: Item 128: Tipo 3M Respirador contra particulas

Sheet  NotaPedido
A1: NOTA DE PEDIDO | F1: N° | G1: 01-20
A3: JURISDICCIÓN: | D3: ='[1]Necesidades Trimestrales'!C4 -> 040 - Ministerio de Salud
A4: SAF: | D4: ='[1]Necesidades Trimestrales'!C5 -> 024 - Hospital Interzonal de Niños
A5: UNIDAD EJECUTORA: | D5: 024 - Hospital Interzonal de Niños
A6: DEPENDENCIA SOLICITANTE: | D6: Servicio de Farmacia
A7: PERIODO UTILIZACIÓN: | D7: 1° Trimestre 2021
A8: OBJETO: | D8: Adquisición de Descartables
A10: Ítem | B10: Codigo Item | C10: DESCRIPCIÓN | D10: Adjunta Detalle Técnico | E10: Unidad Medida | F10: Precio Unitario Estimado | G10: Cantidad Solicitada
A12: 1 | B12: 295 | C12: =+'Necesidades Trimestrales'!D10 -> AGUJA DESCARTABLE 16/5 | D12: NO | E12: ='Necesidades Trimestrales'!E10 -> UNIDAD | F12: =+'Necesidades Trimestrales'!G10 -> 1.2 | G12: =+'Necesidades Trimestrales'!F10 -> 22500
A13: 2 | B13: 295 | C13: =+'Necesidades Trimestrales'!D11 -> AGUJA DESCARTABLE 25/8 | D13: NO | E13: ='Necesidades Trimestrales'!E11 -> UNIDAD | F13: =+'Necesidades Trimestrales'!G11 -> 1.2 | G13: =+'Necesidades Trimestrales'!F11 -> 22500
A14: 3 | B14: 295 | C14: =+'Necesidades Trimestrales'!D12 -> AGUJA DESCARTABLE 40/12 | D14: NO | E14: ='Necesidades Trimestrales'!E12 -> UNIDAD | F14: =+'Necesidades Trimestrales'!G12 -> 1.55 | G14: =+'Necesidades Trimestrales'!F12 -> 1000
A15: 4 | B15: 295 | C15: =+'Necesidades Trimestrales'!D13 -> AGUJA DESCARTABLE 40/8 | D15: NO | E15: ='Necesidades Trimestrales'!E13 -> UNIDAD | F15: =+'Necesidades Trimestrales'!G13 -> 1.2 | G15: =+'Necesidades Trimestrales'!F13 -> 15000
A16: 5 | B16: 295 | C16: =+'Necesidades Trimestrales'!D14 -> AGUJA DESCARTABLE 50/8 | D16: NO | E16: ='Necesidades Trimestrales'!E14 -> UNIDAD | F16: =+'Necesidades Trimestrales'!G14 -> 1.55 | G16: =+'Necesidades Trimestrales'!F14 -> 1000
A17: 6 | B17: 295 | C17: =+'Necesidades Trimestrales'!D15 -> ALGODÓN x 500 GRS.TIPO DONCELLA | D17: NO | E17: ='Necesidades Trimestrales'!E15 -> UNIDAD | F17: =+'Necesidades Trimestrales'!G15 -> 251.1 | G17: =+'Necesidades Trimestrales'!F15 -> 1000
A18: 7 | B18: 295 | C18: =+'Necesidades Trimestrales'!D16 -> BAJALENGUA X 100 UNIDADES | D18: NO | E18: ='Necesidades Trimestrales'!E16 -> UNIDAD | F18: =+'Necesidades Trimestrales'!G16 -> 110.9 | G18: =+'Necesidades Trimestrales'!F16 -> 1000
A19: 8 | B19: 295 | C19: =+'Necesidades Trimestrales'!D17 -> BOTAS ALTAS DESCARTABLES DE 30 GRAMOS CON TIRA EL PAR | D19: NO | E19: ='Necesidades Trimestrales'!E17 -> UNIDAD | F19: =+'Necesidades Trimestrales'!G17 -> 35.44 | G19: =+'Necesidades Trimestrales'!F17 -> 5000
A20: 9 | B20: 295 | C20: =+'Necesidades Trimestrales'!D18 -> BOLSA P/SANGRE TRIPLE T/CPD ADENINA C/SAFMAN 450 ML | D20: NO | E20: ='Necesidades Trimestrales'!E18 -> UNIDAD | F20: =+'Necesidades Trimestrales'!G18 -> 888 | G20: =+'Necesidades Trimestrales'!F18 -> 400
A21: 10 | B21: 295 | C21: =+'Necesidades Trimestrales'!D19 -> CAMISOLINES DES. SMS CON MANGAS Y PUÑO DE 1,40 MTS. DE LARGO, 30 GRS. COLOR AZUL | D21: NO | E21: ='Necesidades Trimestrales'!E19 -> UNIDAD | F21: =+'Necesidades Trimestrales'!G19 -> 179 | G21: =+'Necesidades Trimestrales'!F19 -> 2000
A22: 11 | B22: 295 | C22: =+'Necesidades Trimestrales'!D20 -> CATETER INTRAVENOSO Nº 22 TIPO HOSPIRA/BD | D22: NO | E22: ='Necesidades Trimestrales'!E20 -> UNIDAD | F22: =+'Necesidades Trimestrales'!G20 -> 44.95 | G22: =+'Necesidades Trimestrales'!F20 -> 4000
A23: 12 | B23: 295 | C23: =+'Necesidades Trimestrales'!D21 -> CATETER INTRAVENOSO Nº 24 TIPO HOSPIRA/BD | D23: NO | E23: ='Necesidades Trimestrales'!E21 -> UNIDAD | F23: =+'Necesidades Trimestrales'!G21 -> 44.95 | G23: =+'Necesidades Trimestrales'!F21 -> 4000
... A138: 127 | B138: 295 | C138: =+'Necesidades Trimestrales'!D136 -> BARBIJOS N95-TIPO 3M | D138: NO | E138: ='Necesidades Trimestrales'!E136 -> UNIDAD | F138: =+'Necesidades Trimestrales'!G136 -> 410 | G138: =+'Necesidades Trimestrales'!F136 -> 3000
A139: COSTO TOTAL ESTIMADO | F139: =SUMPRODUCT(F12:F138,G12:G138) -> 18253938

Sheet Autor Gastar
A1: EJERCICIO: | D1: ='Necesidades Trimestrales'!C6 -> 2021 | P1: AUTORIZACION PARA GASTAR
A4: JURISDICCIÓN: | G4: 040 - Ministerio de Salud
A5: SAF: | G5: 024 - Hospital Interzonal de Niños
A6: UNIDAD EJECUTORA: | G6: 024 - Hospital Interzonal de Niños
A7: DEPENDENCIA SOLICITANTE: | G7: SERV. DE FARMACIA
A8: AUTORIZACIÓN:
A9: Señor Jefe de Servicio Administrativo Financiero:
A10: ="Autorizo la realización de los trámites correspondientes, a fin de proveer a este Organismo los bienes y/o servicios que se detallan en Nota de Pedido N° " & ' NotaPedido'!G1&", afectando la erogación resultante a los créditos presupuestarios aprobados a favor de esta Unidad Ejecutora, conforme al siguiente detalle:" -> Autorizo la realización de los trámites correspondientes, a fin de proveer a este Organismo los bienes y/o servicios que se detallan en Nota de Pedido N° 01-20, afectando la erogación resultante a los créditos presupuestarios aprobados a favor de esta Unidad Ejecutora, conforme al siguiente detalle:
A12: IMPUTACIÓN PRESUPUESTARIA
A13: CÓDIGO | O13: DENOMINACIÓN DE LA PARTIDA PRESUPUESTARIA | Q13: IMPORTE
A14: PR | B14: SB | C14: PY | D14: AC | E14: OB | F14: UG | G14: FIN | H14: FUN | I14: I | J14: P | K14: P | L14: SubP | M14: M | N14: FF
A15: 36 | D15: 1 | F15: 4901 | G15: 3 | H15: 310 | I15: 2 | J15: 5 | K15: 1 | M15: 1 | N15: 1.1 | O15: Compuestos Quimicos | Q15: 1842675
A16: 36 | D16: 1 | F16: 4901 | G16: 3 | H16: 310 | I16: 2 | J16: 9 | K16: 5 | M16: 1 | N16: 1.1 | O16: Utiles Menores Medico, Quirurjico y de Laboratorio | Q16: 16188858
A17: 36 | D17: 1 | F17: 4901 | G17: 3 | H17: 310 | I17: 2 | J17: 9 | K17: 9 | M17: 1 | N17: 1.1 | O17: Otros no Especificados Preced. | Q17: 215035
A18: 36 | D18: 1 | F18: 4901 | G18: 3 | H18: 310 | I18: 2 | J18: 5 | K18: 2 | M18: 1 | N18: 1.1 | O18: Productos Farmaceuticos y Medicinales | Q18: 7370
A22: TOTAL DE PESOS: DIECIOCHO MILLONES DOSCIENTOS CINCUENTA Y TRES MIL NOVECIENTOS TREINTA Y OCHO CON 50/100. | Q22: =SUM(Q15:Q21) -> 18253938
A24: JUSTIFICACIÓN:
A25: Para la adquisición de descartables destinados al servico de Farmacia del Hospital Interzonal de Niños Eva Peron, para el normal funcionamiento del organismo.
