Workbook

Sheet Necesidades Trimestrales
B2: Pedido de Necesidades Trimestrales
A4: JURISDICCION: | C4: 040 - Ministerio de Salud
A5: SAF N°: | C5: 024 - Hospital Interzonal de Niños
A6: EJERCICIO: | C6: 2022
A7: TRIMESTRE: | C7: 1
A9: ID | B9: CODIGO ITEM | C9: RUBRO DE COMPRA | D9: I.P.P. | E9: DESCRIPCION | F9: UNIDAD DE MEDIDA | G9: CANTIDAD | H9: PRECIO UNITARIO ESTIMADO | I9: IMPORTE TOTAL ESTIMADO
A10: 1 | B10: 2.5.1-9009.497 | C10: QUIMICOS | D10: 251 | E10: ACIDOS; COMPUESTO QUIMICO: AC. ACETICO; ESTADO SOLIDO; CALIDAD: FARMACEUTICA; CONCENTRACION/PUREZA 25/30%; PRESENTACION: 5KG | F10: BIDON | G10: 1 | H10: 3300 | I10: =+G10*H10 -> 3300
A11: 2 | B11: 2.5.1-9009.262 | C11: QUIMICOS | D11: 251 | E11: ACIDOS; COMPUESTO QUIMICO: AC. CITRICO, ESTADO: SOLIDO, CALIDAD: BIOLOGIA MOLECULAR, CONCENTRACION/PUREZA: 99,99 %, PRESENTACION: ENVASE X 1 Kg | F11: UNIDAD | G11: 1 | H11: 1560 | I11: =+G11*H11 -> 1560
A12: 3 | B12: 2.5.2-710.4 | C12: PROD. MEDICO/ FARMACEUTICOS/LAB | D12: 252 | E12: AGUA OXIGENADA; CAPACIDAD: 1000 CM3, VOLUMEN: 10, PRESENTACION: ENVASE X 1000 CM3 | F12: BOTELLA | G12: 50 | H12: 128.59 | I12: =+G12*H12 -> 6429.5
A13: 4 | B13: 2.5.2-711.15 | C13: PROD. MEDICO/ FARMACEUTICOS/LAB | D13: 252 | E13: ALCOHOL USO MEDICINAL; PUREZA: 70 %, PRESENTACION: ENVASE X 1 L | F13: BOTELLA | G13: 400 | H13: 189 | I13: =+G13*H13 -> 75600
A14: 5 | B14: 2.5.2-711.29 | C14: PROD. MEDICO/ FARMACEUTICOS/LAB | D14: 252 | E14: ALCOHOL USO MEDICINAL; PUREZA: 70 %, PRESENTACION: ENVASE X 500 mL | F14: BOTELLA | G14: 400 | H14: 109 | I14: =+G14*H14 -> 43600
A15: 6 | B15: 2.5.2-711.1 | C15: PROD. MEDICO/ FARMACEUTICOS/LAB | D15: 252 | E15: ALCOHOL USO MEDICINAL; PUREZA: 96 %, PRESENTACION: ENVASE X 500 CM3, CAPACIDAD: 500 CM3 | F15: BOTELLA | G15: 1000 | H15: 108 | I15: =+G15*H15 -> 108000
A16: 7 | B16: 2.5.2-711.32 | C16: PROD. MEDICO/ FARMACEUTICOS/LAB | D16: 252 | E16: ALCOHOL USO MEDICINAL; PUREZA: 96 %, PRESENTACION: ENVASE X 1000 CM3 | F16: BOTELLA | G16: 500 | H16: 201 | I16: =+G16*H16 -> 100500
A17: 8 | B17: 2.5.1-9065.27 | C17: QUIMICOS | D17: 251 | E17: DESINFECTANTES Y DETERGENTES; PRINCIPIO ACTIVO: AMONIO CUATERNARIO, CALIDAD: COMERCIAL, CONCENTRACION/PUREZA: 99 %, PRESENTACION: ENVASE X 5 L | F17: BIDON | G17: 4 | H17: 9229.2 | I17: =+G17*H17 -> 36916.8
A18: 9 | B18: 2.5.2-1723.172 | C18: PROD. MEDICO/ FARMACEUTICOS/LAB | D18: 252 | E18: ANTISEPTICOS LOCALES P/PERSONA; TIPO: MONODROGA, DROGA GENERICA: CLORHEXIDINA AL 2%, FORMA FARMACEUTICA: SOLUCION ACUOSA, PRESENTACION: ENVASE X 250 ML | F18: FRASCO | G18: 300 | H18: 630 | I18: =+G18*H18 -> 189000
A19: 10 | B19: 2.5.2-1723.166 | C19: PROD. MEDICO/ FARMACEUTICOS/LAB | D19: 252 | E19: ANTISEPTICOS LOCALES P/PERSONA; TIPO: MONODROGA, DROGA GENERICA: CLORHEXIDINA AL 4%, FORMA FARMACEUTICA: JABON MEDICINAL, PRESENTACION: ENVASE X 500 mL | F19: FRASCO | G19: 300 | H19: 570 | I19: =+G19*H19 -> 171000
A20: 11 | B20: 2.5.1-9065.16 | C20: QUIMICOS | D20: 251 | E20: DESINFECTANTES Y DETERGENTES; PRINCIPIO ACTIVO: AMILASA, PROTEASA, LIPASA, CALIDAD: COMERCIAL, CONCENTRACION/PUREZA: 100 %, PRESENTACION: ENVASE X 5 L | F20: BIDON | G20: 30 | H20: 4900.5 | I20: =+G20*H20 -> 147015
A21: 12 | B21: 2.5.1-9065.53 | C21: QUIMICOS | D21: 251 | E21: DESINFECTANTES Y DETERGENTES; PRINCIPIO ACTIVO: GLUTARALDEHIDO CON SULFACTANTE, CALIDAD: BIOLOGIA MOLECULAR, CONCENTRACION/PUREZA: 2 %, PRESENTACION: ENVASE X 4 L | F21: BIDON | G21: 2 | H21: 1680 | I21: =+G21*H21 -> 3360
... A25: 16 | B25: 2.5.2-1723.89 | C25: PROD. MEDICO/ FARMACEUTICOS/LAB | D25: 252 | E25: ANTISEPTICOS LOCALES P/PERSONA; TIPO: MONODROGA, DROGA GENERICA: TINTURA DE IODO FUERTE, FORMA FARMACEUTICA: SOLUCION, PRESENTACION: ENVASE X 1 L | F25: BOTELLA | G25: 4 | H25: 989 | I25: =+G25*H25 -> 3956
B27: Plazos y lugares de entrega
B28: Lugar de Entrega: SERVICIO DE FARMACIA -HOSPITAL INT. DE NIÑOS – AV. VIRGEN DEL VALLE N° 1050-CATAMARCA DE 8:00 A 12:00HS., DEBIENDO CORRER LOS GASTOS DE FLETES, ACARREO, CARGA, DESCARGA Y SEGURO A CARGO DEL ADJUDICATARIO.
B30: Plazo de entrega: Dentro de los veinte (10) días habiles de notificada la Orden de Compra
B31: Mantenimiento de Oferta: 45 dias habiles
B33: Especificidades Item N° 8:
B34: Descripción técnica: USO HOSPITALARIO. Limpiador para areas criticas en base a amonios cuaternarios de 4TA Generacion.Dilucion 2,5 ml/ litro .Aprobacion ANMAT
B37: Especificidades Item N° 11:
B38: Descripción técnica : Detergente trienzimatico (proteada, lipasa y amilasa). Concentración: 3 a 5 ml/litro. Libre de fenoles, Atoxico. Aprobación ANMAT. Proveer 1 válvula dosificadora cada 5 unidades.
B41: Especificidades Item N°13:
B42: Descripción técnica: con valvula atomizadora
B45: Especificidades Item N°14:
B46: Descripción técnica: Entrega de los mismos con envase con atomizador para el preparado.

Sheet  NotaPedido
A1: NOTA DE PEDIDO | J1: N° | K1: 006/2022
A3: JURISDICCIÓN: | D3: ='Necesidades Trimestrales'!C4 -> 040 - Ministerio de Salud
A4: SAF: | D4: ='Necesidades Trimestrales'!C5 -> 024 - Hospital Interzonal de Niños
A5: UNIDAD EJECUTORA: | D5: 024 - Hospital Interzonal de Niños
A6: DEPENDENCIA SOLICITANTE: | D6: Servicio de Farmacia
A7: PERIODO UTILIZACIÓN: | D7: Semestral
A8: OBJETO: | D8: Antisepticos y Desinfectantes
A10: Ítem | B10: Codigo Item | C10: DESCRIPCIÓN | H10: Adjunta Detalle Técnico | I10: Unidad Medida | J10: Precio Unitario Estimado | K10: Cantidad Solicitada
A12: 1 | B12: =+'Necesidades Trimestrales'!B10 -> 2.5.1-9009.497 | C12: ='Necesidades Trimestrales'!E10 -> ACIDOS; COMPUESTO QUIMICO: AC. ACETICO; ESTADO SOLIDO; CALIDAD: FARMACEUTICA; CONCENTRACION/PUREZA 25/30%; PRESENTACION: 5KG | H12: NO | I12: ='Necesidades Trimestrales'!F10 -> BIDON | J12: ='Necesidades Trimestrales'!H10 -> 3300 | K12: ='Necesidades Trimestrales'!G10 -> 1
A13: 2 | B13: =+'Necesidades Trimestrales'!B11 -> 2.5.1-9009.262 | C13: ='Necesidades Trimestrales'!E11 -> ACIDOS; COMPUESTO QUIMICO: AC. CITRICO, ESTADO: SOLIDO, CALIDAD: BIOLOGIA MOLECULAR, CONCENTRACION/PUREZA: 99,99 %, PRESENTACION: ENVASE X 1 Kg | H13: NO | I13: ='Necesidades Trimestrales'!F11 -> UNIDAD | J13: ='Necesidades Trimestrales'!H11 -> 1560 | K13: ='Necesidades Trimestrales'!G11 -> 1
A14: 3 | B14: =+'Necesidades Trimestrales'!B12 -> 2.5.2-710.4 | C14: ='Necesidades Trimestrales'!E12 -> AGUA OXIGENADA; CAPACIDAD: 1000 CM3, VOLUMEN: 10, PRESENTACION: ENVASE X 1000 CM3 | H14: NO | I14: ='Necesidades Trimestrales'!F12 -> BOTELLA | J14: ='Necesidades Trimestrales'!H12 -> 128.59 | K14: ='Necesidades Trimestrales'!G12 -> 50
A15: 4 | B15: =+'Necesidades Trimestrales'!B13 -> 2.5.2-711.15 | C15: ='Necesidades Trimestrales'!E13 -> ALCOHOL USO MEDICINAL; PUREZA: 70 %, PRESENTACION: ENVASE X 1 L | H15: NO | I15: ='Necesidades Trimestrales'!F13 -> BOTELLA | J15: ='Necesidades Trimestrales'!H13 -> 189 | K15: ='Necesidades Trimestrales'!G13 -> 400
A16: 5 | B16: =+'Necesidades Trimestrales'!B14 -> 2.5.2-711.29 | C16: ='Necesidades Trimestrales'!E14 -> ALCOHOL USO MEDICINAL; PUREZA: 70 %, PRESENTACION: ENVASE X 500 mL | H16: NO | I16: ='Necesidades Trimestrales'!F14 -> BOTELLA | J16: ='Necesidades Trimestrales'!H14 -> 109 | K16: ='Necesidades Trimestrales'!G14 -> 400
A17: 6 | B17: =+'Necesidades Trimestrales'!B15 -> 2.5.2-711.1 | C17: ='Necesidades Trimestrales'!E15 -> ALCOHOL USO MEDICINAL; PUREZA: 96 %, PRESENTACION: ENVASE X 500 CM3, CAPACIDAD: 500 CM3 | H17: NO | I17: ='Necesidades Trimestrales'!F15 -> BOTELLA | J17: ='Necesidades Trimestrales'!H15 -> 108 | K17: ='Necesidades Trimestrales'!G15 -> 1000
A18: 7 | B18: =+'Necesidades Trimestrales'!B16 -> 2.5.2-711.32 | C18: ='Necesidades Trimestrales'!E16 -> ALCOHOL USO MEDICINAL; PUREZA: 96 %, PRESENTACION: ENVASE X 1000 CM3 | H18: NO | I18: ='Necesidades Trimestrales'!F16 -> BOTELLA | J18: ='Necesidades Trimestrales'!H16 -> 201 | K18: ='Necesidades Trimestrales'!G16 -> 500
A19: 8 | B19: =+'Necesidades Trimestrales'!B17 -> 2.5.1-9065.27 | C19: ='Necesidades Trimestrales'!E17 -> DESINFECTANTES Y DETERGENTES; PRINCIPIO ACTIVO: AMONIO CUATERNARIO, CALIDAD: COMERCIAL, CONCENTRACION/PUREZA: 99 %, PRESENTACION: ENVASE X 5 L | H19: SI | I19: ='Necesidades Trimestrales'!F17 -> BIDON | J19: ='Necesidades Trimestrales'!H17 -> 9229.2 | K19: ='Necesidades Trimestrales'!G17 -> 4
A20: 9 | B20: =+'Necesidades Trimestrales'!B18 -> 2.5.2-1723.172 | C20: ='Necesidades Trimestrales'!E18 -> ANTISEPTICOS LOCALES P/PERSONA; TIPO: MONODROGA, DROGA GENERICA: CLORHEXIDINA AL 2%, FORMA FARMACEUTICA: SOLUCION ACUOSA, PRESENTACION: ENVASE X 250 ML | H20: NO | I20: ='Necesidades Trimestrales'!F18 -> FRASCO | J20: ='Necesidades Trimestrales'!H18 -> 630 | K20: ='Necesidades Trimestrales'!G18 -> 300
A21: 10 | B21: =+'Necesidades Trimestrales'!B19 -> 2.5.2-1723.166 | C21: ='Necesidades Trimestrales'!E19 -> ANTISEPTICOS LOCALES P/PERSONA; TIPO: MONODROGA, DROGA GENERICA: CLORHEXIDINA AL 4%, FORMA FARMACEUTICA: JABON MEDICINAL, PRESENTACION: ENVASE X 500 mL | H21: NO | I21: ='Necesidades Trimestrales'!F19 -> FRASCO | J21: ='Necesidades Trimestrales'!H19 -> 570 | K21: ='Necesidades Trimestrales'!G19 -> 300
A22: 11 | B22: =+'Necesidades Trimestrales'!B20 -> 2.5.1-9065.16 | C22: ='Necesidades Trimestrales'!E20 -> DESINFECTANTES Y DETERGENTES; PRINCIPIO ACTIVO: AMILASA, PROTEASA, LIPASA, CALIDAD: COMERCIAL, CONCENTRACION/PUREZA: 100 %, PRESENTACION: ENVASE X 5 L | H22: SI | I22: ='Necesidades Trimestrales'!F20 -> BIDON | J22: ='Necesidades Trimestrales'!H20 -> 4900.5 | K22: ='Necesidades Trimestrales'!G20 -> 30
A23: 12 | B23: =+'Necesidades Trimestrales'!B21 -> 2.5.1-9065.53 | C23: ='Necesidades Trimestrales'!E21 -> DESINFECTANTES Y DETERGENTES; PRINCIPIO ACTIVO: GLUTARALDEHIDO CON SULFACTANTE, CALIDAD: BIOLOGIA MOLECULAR, CONCENTRACION/PUREZA: 2 %, PRESENTACION: ENVASE X 4 L | H23: NO | I23: ='Necesidades Trimestrales'!F21 -> BIDON | J23: ='Necesidades Trimestrales'!H21 -> 1680 | K23: ='Necesidades Trimestrales'!G21 -> 2
... A27: 16 | B27: =+'Necesidades Trimestrales'!B25 -> 2.5.2-1723.89 | C27: ='Necesidades Trimestrales'!E25 -> ANTISEPTICOS LOCALES P/PERSONA; TIPO: MONODROGA, DROGA GENERICA: TINTURA DE IODO FUERTE, FORMA FARMACEUTICA: SOLUCION, PRESENTACION: ENVASE X 1 L | H27: NO | I27: ='Necesidades Trimestrales'!F25 -> BOTELLA | J27: ='Necesidades Trimestrales'!H25 -> 989 | K27: ='Necesidades Trimestrales'!G25 -> 4
A28: Costo total estimado: Novecientos Cincuenta y Cinco Mil Novecientos Cuarenta y Siete Con 30/100. | J28: =SUMPRODUCT(J12:J27,K12:K27) -> 955947.3

Sheet Autor Gastar
A1: EJERCICIO: | D1: ='Necesidades Trimestrales'!C6 -> 2022 | P1: AUTORIZACION PARA GASTAR
A4: JURISDICCIÓN: | G4: =' NotaPedido'!D3 -> 040 - Ministerio de Salud
A5: SAF: | G5: =' NotaPedido'!D4 -> 024 - Hospital Interzonal de Niños
A6: UNIDAD EJECUTORA: | G6: =' NotaPedido'!D5 -> 024 - Hospital Interzonal de Niños
A7: DEPENDENCIA SOLICITANTE: | G7: Servicio de Farmacia
A8: AUTORIZACIÓN:
A9: Señor Jefe de Servicio Administrativo Financiero:
A10: ="Autorizo la realización de los trámites correspondientes, a fin de proveer a este Organismo los bienes y/o servicios que se detallan en Nota de Pedido N° " & ' NotaPedido'!K1&", afectando la erogación resultante a los créditos presupuestarios aprobados a favor de esta Unidad Ejecutora, conforme al siguiente detalle:" -> Autorizo la realización de los trámites correspondientes, a fin de proveer a este Organismo los bienes y/o servicios que se detallan en Nota de Pedido N° 006/2022, afectando la erogación resultante a los créditos presupuestarios aprobados a favor de esta Unidad Ejecutora, conforme al siguiente detalle:
A12: IMPUTACIÓN PRESUPUESTARIA
A13: CÓDIGO | O13: DENOMINACIÓN DE LA PARTIDA PRESUPUESTARIA | Q13: IMPORTE
A14: PR | B14: SB | C14: PY | D14: AC | E14: OB | F14: UG | G14: FIN | H14: FUN | I14: I | J14: P | K14: P | L14: SubP | M14: M | N14: FF
A15: 36 | D15: 1 | F15: 4901 | G15: 3 | H15: 310 | I15: 2 | J15: 5 | K15: 1 | M15: 1 | N15: 1.1 | O15: COMPUESTOS QUIMICOS | Q15: 232081.8
A16: 36 | D16: 1 | F16: 4901 | G16: 3 | H16: 310 | I16: 2 | J16: 5 | K16: 2 | M16: 1 | N16: 1.1 | O16: PRODUCTOS FARMACEUTICOS Y MEDICINALES | Q16: 723865.5
A21: TOTAL DE PESOS: NOVECIENTOS CINCUENTA Y CINCO MIL NOVECIENTOS CUARENTA Y SIETE CON 30/100. | Q21: =SUM(Q15:Q20) -> 955947.3
A23: JUSTIFICACIÓN:
A24: Para la adquisición de Antisepticos y Desinfectantes destinados al Servicio de Farmacia del Hospital Interzonal de Niños Eva Peron, para el normal funcionamiento del organismo.
