Workbook

Sheet Necesidades Trimestrales
B2: Pedido de Necesidades Trimestrales
A4: JURISDICCION: | C4: 040 - Ministerio de Salud
A5: SAF N°: | C5: 24 - HOPITAL DE NIÑOS EVA PERON
A6: EJERCICIO: | C6: 2022
A7: TRIMESTRE: | C7: 1
A9: ID | B9: CODIGO ITEM | C9: RUBRO DE COMPRA | D9: I.P.P. | E9: DESCRIPCION | F9: UNIDAD DE MEDIDA | G9: CANTIDAD | H9: PRECIO UNITARIO ESTIMADO | I9: IMPORTE TOTAL ESTIMADO
A10: 1 | B10: 2.5.2-1726.520 | C10: PROD. MEDICO/ FARMACEUTICOS/LAB | D10: 2.5.2 | E10: SOLUCIONES P/MEDICINA; TIPO: AGUA DESTILADA, PRESENTACION: AMPOLLA DE 10 ML | F10: ANPOLLA | G10: 5000 | H10: 32 | I10: =+G10*H10 -> 160000
A11: 2 | B11: 2.5.2-1726.186 | C11: PROD. MEDICO/ FARMACEUTICOS/LAB | D11: 2.5.2 | E11: SOLUCIONES P/MEDICINA; TIPO: AGUA DESTILADA, PRESENTACION: ENVASE X 500 mL | F11: SACHET | G11: 800 | H11: 102.7 | I11: =+G11*H11 -> 82160
A12: 3 | B12: 2.5.2-2183.7 | C12: PROD. MEDICO/ FARMACEUTICOS/LAB | D12: 2.5.2 | E12: EXPANSORES PLASMATICOS; PRINCIPIO ACTIVO: ALBUMINA HUMANA, CONCENTRACION: 20 %, PRESENTACION: 50ML | F12: SACHET | G12: 100 | H12: 2268 | I12: =+G12*H12 -> 226800
A13: 4 | B13: 2.1.1-4227.56 | C13: PROD. MEDICO/ FARMACEUTICOS/LAB | D13: 2.5.2 | E13: SUPLEMENTOS DIETARIOS; TIPO: ASOCIACION, DROGA GENERICA: S. PARENTERAL ADULTO 1501-2000 ML, PRESENTACION: UNIDAD | F13: UNIDAD | G13: 30 | H13: 11198 | I13: =+G13*H13 -> 335940
A14: 5 | B14: 2.5.2-1726.9 | C14: PROD. MEDICO/ FARMACEUTICOS/LAB | D14: 2.5.2 | E14: SOLUCIONES P/MEDICINA; TIPO: BICARBONATO 1 MOLAR, PRESENTACION: SACHET DE 100 mL | F14: SACHET | G14: 300 | H14: 366 | I14: =+G14*H14 -> 109800
A15: 6 | B15: 2.5.2-1726.305 | C15: PROD. MEDICO/ FARMACEUTICOS/LAB | D15: 2.5.2 | E15: SOLUCIONES P/MEDICINA; TIPO: CLORURO DE POTASIO 15 MEQ, PRESENTACION: AMPOLLA DE 5 mL | F15: AMPOLLA | G15: 500 | H15: 29.4 | I15: =+G15*H15 -> 14700
A16: 7 | B16: 2.5.2-1726.519 | C16: PROD. MEDICO/ FARMACEUTICOS/LAB | D16: 2.5.2 | E16: SOLUCIONES P/MEDICINA; PRESENTACION: AMPOLLA X 20 ML, TIPO: CLORURO DE SODIO MOLAR AL 20 % | F16: AMPOLLA | G16: 1000 | H16: 44 | I16: =+G16*H16 -> 44000
A17: 8 | B17: 2.5.2-1726.382 | C17: PROD. MEDICO/ FARMACEUTICOS/LAB | D17: 2.5.2 | E17: SOLUCIONES P/MEDICINA; TIPO: CLORURO DE POTASIO MOLAR, PRESENTACION: ENVASE X 100 mL | F17: SACHET | G17: 1000 | H17: 223 | I17: =+G17*H17 -> 223000
A18: 9 | B18: 2.5.2-2689.7 | C18: PROD. MEDICO/ FARMACEUTICOS/LAB | D18: 2.5.2 | E18: NORMALIZADORES DE CALCEMIA; TIPO: MONODROGA, DROGA GENERICA: GLUCONATO DE CALCIO 10 %, FORMA FARMACEUTICA: AMPOLLA, PRESENTACION: ENVASE X 10 mL | F18: AMPOLLA | G18: 500 | H18: 84 | I18: =+G18*H18 -> 42000
A19: 10 | B19: 2.5.2-1726.378 | C19: PROD. MEDICO/ FARMACEUTICOS/LAB | D19: 2.5.2 | E19: SOLUCIONES P/MEDICINA; TIPO: DEXTROSA AL 50 %, PRESENTACION: ENVASE X 500 mL | F19: SACHET | G19: 50 | H19: 221.95 | I19: =+G19*H19 -> 11097.5
A20: 11 | B20: 2.5.2-1726.14 | C20: PROD. MEDICO/ FARMACEUTICOS/LAB | D20: 2.5.2 | E20: SOLUCIONES P/MEDICINA; PRESENTACION: SACHET X 500 mL, TIPO: DEXTROSA AL 10 % | F20: SACHET | G20: 500 | H20: 118.3 | I20: =+G20*H20 -> 59150
A21: 12 | B21: 2.5.2-1726.24 | C21: PROD. MEDICO/ FARMACEUTICOS/LAB | D21: 2.5.2 | E21: SOLUCIONES P/MEDICINA; TIPO: DEXTROSA AL 5%, PRESENTACION: ENVASE X 500 mL | F21: SACHET | G21: 10000 | H21: 110.6 | I21: =+G21*H21 -> 1106000
... A32: 23 | B32: 2.5.2-1836.10 | C32: PROD. MEDICO/ FARMACEUTICOS/LAB | D32: 2.5.2 | E32: HIPERTENSORES; TIPO: MONODROGA, DROGA GENERICA: ZINC SULFATO, FORMA FARMACEUTICA: AMPOLLAS, PRESENTACION: 5 mL | F32: AMPOLLA | G32: 100 | H32: 2897 | I32: =+G32*H32 -> 289700
B35: Plazos y lugares de entrega
B36: Lugar de Entrega: SERVICIO DE FARMACIA -HOSPITAL INT. DE NIÑOS – AV. VIRGEN DEL VALLE N° 1050-CATAMARCA DE 8:00 A 12:00HS., DEBIENDO CORRER LOS GASTOS DE FLETES, ACARREO, CARGA, DESCARGA Y SEGURO A CARGO DEL ADJUDICATARIO.
B38: Plazo de entrega: Dentro de los diez (10) días habiles de notificada la Orden de Compra
B39: Mantenimiento de Oferta: 45 dias habiles

Sheet  NotaPedido
A1: NOTA DE PEDIDO | J1: N° | K1: 047-2022
A3: JURISDICCIÓN: | D3: ='Necesidades Trimestrales'!C4 -> 040 - Ministerio de Salud
A4: SAF: | D4: ='Necesidades Trimestrales'!C5 -> 24 - HOPITAL DE NIÑOS EVA PERON
A5: UNIDAD EJECUTORA: | D5: =+D4 -> 24 - HOPITAL DE NIÑOS EVA PERON
A6: DEPENDENCIA SOLICITANTE: | D6: =+D5 -> 24 - HOPITAL DE NIÑOS EVA PERON
A7: PERIODO UTILIZACIÓN: | D7: Semestral
A8: OBJETO: | D8: Nutricion y Soluciones que Afectan el Equilibrio Hidroelectrolitico y Soluciones para Dialisis
A10: Ítem | B10: Codigo Item | C10: DESCRIPCIÓN | H10: Adjunta Detalle Técnico | I10: Unidad Medida | J10: Precio Unitario Estimado | K10: Cantidad Solicitada
A12: 1 | B12: ='Necesidades Trimestrales'!B10 -> 2.5.2-1726.520 | C12: =+'Necesidades Trimestrales'!E10 -> SOLUCIONES P/MEDICINA; TIPO: AGUA DESTILADA, PRESENTACION: AMPOLLA DE 10 ML | H12: NO | I12: =+'Necesidades Trimestrales'!F10 -> ANPOLLA | J12: =+'Necesidades Trimestrales'!H10 -> 32 | K12: =+'Necesidades Trimestrales'!G10 -> 5000
A13: 2 | B13: ='Necesidades Trimestrales'!B11 -> 2.5.2-1726.186 | C13: =+'Necesidades Trimestrales'!E11 -> SOLUCIONES P/MEDICINA; TIPO: AGUA DESTILADA, PRESENTACION: ENVASE X 500 mL | H13: NO | I13: =+'Necesidades Trimestrales'!F11 -> SACHET | J13: =+'Necesidades Trimestrales'!H11 -> 102.7 | K13: =+'Necesidades Trimestrales'!G11 -> 800
A14: 3 | B14: ='Necesidades Trimestrales'!B12 -> 2.5.2-2183.7 | C14: =+'Necesidades Trimestrales'!E12 -> EXPANSORES PLASMATICOS; PRINCIPIO ACTIVO: ALBUMINA HUMANA, CONCENTRACION: 20 %, PRESENTACION: 50ML | H14: NO | I14: =+'Necesidades Trimestrales'!F12 -> SACHET | J14: =+'Necesidades Trimestrales'!H12 -> 2268 | K14: =+'Necesidades Trimestrales'!G12 -> 100
A15: 4 | B15: ='Necesidades Trimestrales'!B13 -> 2.1.1-4227.56 | C15: =+'Necesidades Trimestrales'!E13 -> SUPLEMENTOS DIETARIOS; TIPO: ASOCIACION, DROGA GENERICA: S. PARENTERAL ADULTO 1501-2000 ML, PRESENTACION: UNIDAD | H15: NO | I15: =+'Necesidades Trimestrales'!F13 -> UNIDAD | J15: =+'Necesidades Trimestrales'!H13 -> 11198 | K15: =+'Necesidades Trimestrales'!G13 -> 30
A16: 5 | B16: ='Necesidades Trimestrales'!B14 -> 2.5.2-1726.9 | C16: =+'Necesidades Trimestrales'!E14 -> SOLUCIONES P/MEDICINA; TIPO: BICARBONATO 1 MOLAR, PRESENTACION: SACHET DE 100 mL | H16: NO | I16: =+'Necesidades Trimestrales'!F14 -> SACHET | J16: =+'Necesidades Trimestrales'!H14 -> 366 | K16: =+'Necesidades Trimestrales'!G14 -> 300
A17: 6 | B17: ='Necesidades Trimestrales'!B15 -> 2.5.2-1726.305 | C17: =+'Necesidades Trimestrales'!E15 -> SOLUCIONES P/MEDICINA; TIPO: CLORURO DE POTASIO 15 MEQ, PRESENTACION: AMPOLLA DE 5 mL | H17: NO | I17: =+'Necesidades Trimestrales'!F15 -> AMPOLLA | J17: =+'Necesidades Trimestrales'!H15 -> 29.4 | K17: =+'Necesidades Trimestrales'!G15 -> 500
A18: 7 | B18: ='Necesidades Trimestrales'!B16 -> 2.5.2-1726.519 | C18: =+'Necesidades Trimestrales'!E16 -> SOLUCIONES P/MEDICINA; PRESENTACION: AMPOLLA X 20 ML, TIPO: CLORURO DE SODIO MOLAR AL 20 % | H18: NO | I18: =+'Necesidades Trimestrales'!F16 -> AMPOLLA | J18: =+'Necesidades Trimestrales'!H16 -> 44 | K18: =+'Necesidades Trimestrales'!G16 -> 1000
A19: 8 | B19: ='Necesidades Trimestrales'!B17 -> 2.5.2-1726.382 | C19: =+'Necesidades Trimestrales'!E17 -> SOLUCIONES P/MEDICINA; TIPO: CLORURO DE POTASIO MOLAR, PRESENTACION: ENVASE X 100 mL | H19: NO | I19: =+'Necesidades Trimestrales'!F17 -> SACHET | J19: =+'Necesidades Trimestrales'!H17 -> 223 | K19: =+'Necesidades Trimestrales'!G17 -> 1000
A20: 9 | B20: ='Necesidades Trimestrales'!B18 -> 2.5.2-2689.7 | C20: =+'Necesidades Trimestrales'!E18 -> NORMALIZADORES DE CALCEMIA; TIPO: MONODROGA, DROGA GENERICA: GLUCONATO DE CALCIO 10 %, FORMA FARMACEUTICA: AMPOLLA, PRESENTACION: ENVASE X 10 mL | H20: NO | I20: =+'Necesidades Trimestrales'!F18 -> AMPOLLA | J20: =+'Necesidades Trimestrales'!H18 -> 84 | K20: =+'Necesidades Trimestrales'!G18 -> 500
A21: 10 | B21: ='Necesidades Trimestrales'!B19 -> 2.5.2-1726.378 | C21: =+'Necesidades Trimestrales'!E19 -> SOLUCIONES P/MEDICINA; TIPO: DEXTROSA AL 50 %, PRESENTACION: ENVASE X 500 mL | H21: NO | I21: =+'Necesidades Trimestrales'!F19 -> SACHET | J21: =+'Necesidades Trimestrales'!H19 -> 221.95 | K21: =+'Necesidades Trimestrales'!G19 -> 50
A22: 11 | B22: ='Necesidades Trimestrales'!B20 -> 2.5.2-1726.14 | C22: =+'Necesidades Trimestrales'!E20 -> SOLUCIONES P/MEDICINA; PRESENTACION: SACHET X 500 mL, TIPO: DEXTROSA AL 10 % | H22: NO | I22: =+'Necesidades Trimestrales'!F20 -> SACHET | J22: =+'Necesidades Trimestrales'!H20 -> 118.3 | K22: =+'Necesidades Trimestrales'!G20 -> 500
A23: 12 | B23: ='Necesidades Trimestrales'!B21 -> 2.5.2-1726.24 | C23: =+'Necesidades Trimestrales'!E21 -> SOLUCIONES P/MEDICINA; TIPO: DEXTROSA AL 5%, PRESENTACION: ENVASE X 500 mL | H23: NO | I23: =+'Necesidades Trimestrales'!F21 -> SACHET | J23: =+'Necesidades Trimestrales'!H21 -> 110.6 | K23: =+'Necesidades Trimestrales'!G21 -> 10000
... A34: 23 | B34: ='Necesidades Trimestrales'!B32 -> 2.5.2-1836.10 | C34: =+'Necesidades Trimestrales'!E32 -> HIPERTENSORES; TIPO: MONODROGA, DROGA GENERICA: ZINC SULFATO, FORMA FARMACEUTICA: AMPOLLAS, PRESENTACION: 5 mL | H34: NO | I34: =+'Necesidades Trimestrales'!F32 -> AMPOLLA | J34: =+'Necesidades Trimestrales'!H32 -> 2897 | K34: =+'Necesidades Trimestrales'!G32 -> 100
A35: Costo total estimado: Cinco Millones Novecientos Seis mil Setecientos Seis con 00/100. | J35: =SUMPRODUCT(J12:J34,K12:K34) -> 5906706

Sheet Autor Gastar
A1: EJERCICIO: | D1: ='Necesidades Trimestrales'!C6 -> 2022 | P1: AUTORIZACION PARA GASTAR
A4: JURISDICCIÓN: | G4: =' NotaPedido'!D3 -> 040 - Ministerio de Salud
A5: SAF: | G5: =' NotaPedido'!D4 -> 24 - HOPITAL DE NIÑOS EVA PERON
A6: UNIDAD EJECUTORA: | G6: =' NotaPedido'!D5 -> 24 - HOPITAL DE NIÑOS EVA PERON
A7: DEPENDENCIA SOLICITANTE: | G7: =' NotaPedido'!D6 -> 24 - HOPITAL DE NIÑOS EVA PERON
A8: AUTORIZACIÓN:
A9: Señor Jefe de Servicio Administrativo Financiero:
A10: ="Autorizo la realización de los trámites correspondientes, a fin de proveer a este Organismo los bienes y/o servicios que se detallan en Nota de Pedido N° " & ' NotaPedido'!K1&", afectando la erogación resultante a los créditos presupuestarios aprobados a favor de esta Unidad Ejecutora, conforme al siguiente detalle:" -> Autorizo la realización de los trámites correspondientes, a fin de proveer a este Organismo los bienes y/o servicios que se detallan en Nota de Pedido N° 047-2022, afectando la erogación resultante a los créditos presupuestarios aprobados a favor de esta Unidad Ejecutora, conforme al siguiente detalle:
A12: IMPUTACIÓN PRESUPUESTARIA
A13: CÓDIGO | O13: DENOMINACIÓN DE LA PARTIDA PRESUPUESTARIA | Q13: IMPORTE
A14: PR | B14: SB | C14: PY | D14: AC | E14: OB | F14: UG | G14: FIN | H14: FUN | I14: I | J14: P | K14: P | L14: SubP | M14: M | N14: FF
A15: 36 | D15: 1 | F15: 4901 | G15: 3 | H15: 310 | I15: 2 | J15: 5 | K15: 2 | M15: 1 | N15: 1.1 | O15: PRODUCTOS FARMACEUTICOS Y MEDICINALES | Q15: 5906706
A22: TOTAL DE PESOS: Cinco Millones Novecientos Seis mil Setecientos Seis con 00/100. | Q22: =SUM(Q15:Q21) -> 5906706
A24: JUSTIFICACIÓN:
A25: Para la adquisición de Insumos relacionados a la Nutricion y Soluciones que Afectan el Equilibrio Hidroelectrolitico y Soluciones para Dialisis destinados al Servicio de Farmacia del Hospital Interzonal de Niños Eva Peron, para el normal funcionamiento del organismo.
