Workbook

Sheet F. CM
A2: ID | B2: CODIGO DEL ITEM | C2: DESCRIPCION | D2: UNIDAD DE MEDIDA | E2: CANTIDAD SOLICITADA
A3: 1 | B3: 2.9.5-441.470 | C3: AGUJAS QUIRURGICAS; TIPO: TERUMO 21GX1", ESPECIFICACION: 25/8, UNIDAD VENTA: CAJA X 100, PRESENTACION: CAJA X 100 TERUMO | D3: CAJA | E3: 3 | F3: BANCO DE SANGRE
A4: 2 | B4: 2.9.5-470.13 | C4: ALGODONES; TIPO: HIDROFILADO, CAPACIDAD: 500 GR, PRESENTACION: ENVASE X 500 GR | D4: UNIDAD | E4: 20
A5: 3 | B5: 2.9.5-428.21 | C5: BARBIJOS; TIPO: 3 CAPAS | D5: UNIDAD | E5: 1000
A6: 4 | B6: 2.9.5-1909.78 | C6: GUANTES USO MEDICINAL; TIPO: EXAMINACION , TAMAÑO: GRANDE, MATERIAL: LATEX, PRESENTACION: ENVASE X 100 UN | D6: CAJA | E6: 10
A7: 5 | B7: 2.9.5-1909.79 | C7: GUANTES USO MEDICINAL; TIPO: EXAMINACION , TAMAÑO: MEDIANO, MATERIAL: LATEX, PRESENTACION: ENVASE X 100 UN | D7: CAJA | E7: 10
A8: 6 | B8: 2.9.5-1909.195 | C8: GUANTES USO MEDICINAL; TIPO: EXAMINACION, TAMAÑO: S 6/7, MATERIAL: LATEX, PRESENTACION: ENVASE X 100 UN, ESTERIL: NO, TALCO: CON, DESCARTABLE: SI | D8: CAJA | E8: 10
A9: 7 | B9: 2.9.5-2157.60 | C9: JERINGAS DESCARTABLES; CAPACIDAD: 10 mL, AGUJA: SIN, USO: MEDICINAL | D9: UNIDAD | E9: 500
A10: 8 | B10: 2.9.5-8239.1 | C10: CHATAS; MATERIAL: PVC | D10: UNIDAD | E10: 10 | F10: FARMACIA
A11: 9 | B11: 2.9.5-2160.10 | C11: DESCARTADORES DE AGUJAS; BOCA: 2, CAPACIDAD: 2 L, MODELO: P/AGUJAS COLECTA MULTIPLE, MODELO EQUIPO: P/AGUJAS COLECTA MULTIPLE, SISTEMA DE CIERRE: P/AGUJAS COLECTA MULTIPLE | D11: UNIDAD | E11: 100
A12: 10 | B12: 2.9.5-1909.135 | C12: GUANTES USO MEDICINAL; TIPO: ESTERIL, TAMAÑO: 6 1/2 CAÑA LARGA, MATERIAL: LATEX, PRESENTACION: PAR, ESTERIL: SI, TALCO: SIN, DESCARTABLE: SI | D12: UNIDAD | E12: 1000
A13: 11 | B13: 2.9.5-1909.79 | C13: GUANTES USO MEDICINAL; TIPO: EXAMINACION , TAMAÑO: MEDIANO, MATERIAL: LATEX, PRESENTACION: ENVASE X 100 UN | D13: UNIDAD | E13: 2000
A14: 12 | B14: 2.9.5-2157.60 | C14: JERINGAS DESCARTABLES; CAPACIDAD: 10 mL, AGUJA: SIN, USO: MEDICINAL | D14: UNIDAD | E14: 50000
A15: 13 | B15: 2.9.5-461.78 | C15: VENDAS USO MEDICO; TIPO: OVATA, MEDIDA: 10 Cm | D15: UNIDAD | E15: 100
A16: 14 | B16: 2.9.5-2205.31 | C16: PROLONGADORES P/GUIA SUERO; USO: ADMINISTRACION DE SOLUCIONES, MODELO: PT26 LONGITUD: 30 CM | D16: UNIDAD | E16: 80
A17: 15 | B17: 2.9.5-931.49 | C17: TELAS ADHESIVAS; ANCHO: 2,5 Cm, LONG.DE CUERPO: 9 M, TIPO: IMPERMEABLE | D17: UNIDAD | E17: 2000
A18: 16 | B18: 2.9.5-931.9 | C18: TELAS ADHESIVAS; LONG.DE CUERPO: 9 M, ANCHO: 5.00 CM, TIPO: HIPOALERGENICA MACROPOROSA TRANSPARENTE | D18: UNIDAD | E18: 200
A19: 17 | B19: 2.9.5-6526.10 | C19: TUBOS P/MEDICINA; TIPO: DE LATEX, USO: P/DRENAJE, PRESENTACION: M, DIMENSION: 5 X 8 MM | D19: UNIDAD | E19: 10
A20: 18 | B20: 2.9.5-2569.151 | C20: TUBOS TRAQUEALES; TIPO: ENDOTRAQUEAL PEDIATR. S/BALON, Nº: 3, NUMERO: 3 | D20: UNIDAD | E20: 10
A21: 19 | B21: 2.9.5-2569.99 | C21: TUBOS TRAQUEALES; Nº: 3 1/2 S/BALON DESCARTABLE, TIPO: ENDOTRAQUEAL PEDIATRICO PERFOR, NUMERO: 3 1/2 S/BALON DESCARTABLE | D21: UNIDAD | E21: 10
A22: 20 | B22: 2.9.5-461.4 | C22: VENDAS USO MEDICO; TIPO: CAMBRIC, MEDIDA: 7 CM X 3 M | D22: UNIDAD | E22: 100
... A25: 23 | B25: 2.9.5-461.27 | C25: VENDAS USO MEDICO; , MEDIDA: 20 CM X 4 M, TIPO: ENYESADA FRAGUADO RAPIDO GYSOFIX | D25: UNIDAD | E25: 150
A26: 24 | B26: 2.9.5-441.470 | C26: AGUJAS QUIRURGICAS; TIPO: TERUMO 21 GX1", ESPECIFICACION: 25/8, UNIDAD VENTA: CAJA X 100, PRESENTACION: CAJA X 100 | D26: UNIDAD | E26: 300 | F26: LABORATORIO
A27: 25 | B27: 2.9.5-441.471 | C27: AGUJAS QUIRURGICAS; TIPO: TERUMO 25GX5/8", ESPECIFICACION: 16/5, UNIDAD VENTA: CAJA X 100, PRESENTACION: CAJA X 100 | D27: UNIDAD | E27: 90
A28: 26 | B28: 2.9.5-470.13 | C28: ALGODONES; TIPO: HIDROFILADO, CAPACIDAD: 500 GR, PRESENTACION: ENVASE X 500 GR | D28: UNIDAD | E28: 300
A29: 27 | B29: 2.9.5-2160.10 | C29: DESCARTADORES DE AGUJAS; BOCA: 2,CAPACIDAD: 2L, MODELO: P/AGUJAS COLECTA MULTIPLE, MODELO EQUIPO: P/AGUJAS COLECTA MULTIPLE, SISTEMA DE CIERRE: P/AGUJAS COLECTA MULTIPLE | D29: UNIDAD | E29: 90
A30: 28 | B30: 2.9.5-1909.79 | C30: GUANTES USO MEDICINAL; TIPO: EXAMINACION, TAMAÑO: MEDIANO, MATERIAL: LATEX, PRESENTACION: ENVASE X 100 UN | D30: UNIDAD | E30: 150
A31: 29 | B31: 2.9.5-1909.195 | C31: GUANTES USO MEDICINAL; TIPO: EXAMINACION, TAMAÑO: S 6/7, MATERIAL: LATEX, PRESENTACION: ENVASE X 100 UN, ESTERIL: NO, TALCO: CON, DESCARTABLE: SI | D31: UNIDAD | E31: 150
A32: 30 | B32: 2.9.5-1909.172 | C32: GUANTES USO MEDICINAL; TIPO: EXAMINACION, TAMAÑO: S 6/7, MATERIAL: NITRILO, PRESENTACION: ENVASE X 100 UN, ESTERIL: NO, TALCO: SIN, DESCARTABLE: SI | D32: UNIDAD | E32: 30
A33: 31 | B33: 2.9.5-1909.174 | C33: GUANTES USO MEDICINAL; TIPO: EXAMINACION, TAMAÑO: L 8/9, MATERIAL: NITRILO, PRESENTACION: ENVASE X 100 UN, ESTERIL: NO, TALCO: SIN, DESCARTABLE: SI | D33: UNIDAD | E33: 15
A34: 32 | B34: 2.9.5-1909.173 | C34: GUANTES USO MEDICINAL; TIPO: EXAMINACION, TAMAÑO: M 7/8, MATERIAL: NITRILO, PRESENTACION: ENVASE X 100 UN, ESTERIL: NO, TALCO: SIN, DESCARTABLE: SI | D34: UNIDAD | E34: 30
A35: 33 | B35: 2.9.5-1909.169 | C35: GUANTES USO MEDICINAL; TIPO: EXAMINACION, TAMAÑO: L 8/9, MATERIAL: VINILO, PRESENTACION: ENVASE X 100 UN, ESTERIL: NO, TALCO: SIN, DESCARTABLE: SI | D35: UNIDAD | E35: 15
A36: 34 | B36: 2.9.5-1909.168 | C36: GUANTES USO MEDICINAL; TIPO: EXAMINACION, TAMAÑO: M 7/8, MATERIAL: VINILO, PRESENTACION: ENVASE X 100 UN, ESTERIL: NO, TALCO: SIN, DESCARTABLE: SI | D36: UNIDAD | E36: 150
A37: 35 | B37: 2.9.5-2157.60 | C37: JERINGAS DESCARTABLES; CAPACIDAD: 10 ML, AGUJA: SIN, USO: MEDICINAL | D37: UNIDAD | E37: 90
A38: 36 | B38: 2.9.5-2157.67 | C38: JERINGAS DESCARTABLES; CAPACIDAD: 5 CM3, AGUJA: SIN, USO: SIN VALOR | D38: UNIDAD | E38: 150
... A40: 38 | B40: 2.9.5-2562.11 | C40: PORTAOBJETOS P/MICROSCOPIO; MATERIAL: VIDRIO, PRESENTACION: CAJA X 100 UN, TAMAÑO: 25 X 76 X 1,2 MM | D40: UNIDAD | E40: 150
A41: 39 | B41: 2.9.5- 470.13 | C41: ALGODONES; TIPO: HIDROFILADO, CAPACIDAD: 500 GR, PRESENTACION: ENVASE X 500 GR | D41: UNIDAD | E41: 20 | F41: ODONTOLOGIA
A42: 40 | B42: 2.9.5- 446.1 | C42: BAJALENGUAS DESCARTABLES; USO: ADULTOS, PAQUETES DE UNIDADES: X 100, PRESENTACION: X 100 | D42: UNIDAD | E42: 1500
A43: 41 | B43: 2.9.5- 428.21 | C43: BARBIJOS; TIPO: 3 CAPAS | D43: UNIDAD | E43: 1500
A44: 42 | B44: 2.9.5- 428.36 | C44: BARBIJOS; TIPO: COPA N95 SIN VALVULA, MATERIAL: NO TEJIDO, CANTIDAD DE CAPAS: DOS, DESCARTABLE: SI, PRESENTACION: UNIDAD | D44: UNIDAD | E44: 300
A45: 43 | B45: 2.9.5- 4198.170 | C45: ELEMENTOS DESC. P/CIRUGIAS; TIPO: CAMISOLIN HEMORREP. DE 30 GRAMOS CON MANGAS Y PUÑOS ELASTICOS DE 1,4 MTRS DE LARGO, CANTIDAD: POR UNIDAD, PRESENTACION: UNIDAD | D45: UNIDAD | E45: 50
A46: 44 | B46: 2.9.5- 1909.135 | C46: GUANTES USO MEDICINAL; TIPO: ESTERIL, TAMAÑO: 6 1/2 CAÑA LARGA, MATERIAL: LATEX, PRESENTACION: PAR, ESTERIL: SI, TALCO: SIN, DESCARTABLE: SI | D46: UNIDAD | E46: 10
A47: 45 | B47: 2.9.5- 1909.203 | C47: GUANTES USO MEDICINAL; TIPO: ESTERIL, TAMAÑO: 7 CAÑA LARGA, MATERIAL: LATEX, PRESENTACION: PAR, ESTERIL: SI, TALCO: SIN, DESCARTABLE: SI | D47: UNIDAD | E47: 10
A48: 46 | B48: 2.9.5- 1909.195 | C48: GUANTES USO MEDICINAL; TIPO: EXAMINACION, TAMAÑO: S 6/7, MATERIAL: LATEX, PRESENTACION: ENVASE X 100 UN, ESTERIL: NO, TALCO: CON, DESCARTABLE: SI | D48: UNIDAD | E48: 10
A49: 47 | B49: 2.9.5- 1909.174 | C49: GUANTES USO MEDICINAL; TIPO: EXAMINACION, TAMAÑO: L 8/9, MATERIAL: NITRILO, PRESENTACION: ENVASE X 100 UN, ESTERIL: NO, TALCO: SIN, DESCARTABLE: SI | D49: UNIDAD | E49: 10
A50: 48 | B50: 2.9.5- 1909.173 | C50: GUANTES USO MEDICINAL; TIPO: EXAMINACION, TAMAÑO: M 7/8, MATERIAL: NITRILO, PRESENTACION: ENVASE X 100 UN, ESTERIL: NO, TALCO: SIN, DESCARTABLE: SI | D50: UNIDAD | E50: 10
A51: 49 | B51: 2.9.5- 444.24 | C51: HOJAS DE BISTURI; TIPO: CAJA X 100 UN, Nº: 15, NUMERO: 15 | D51: UNIDAD | E51: 4
A52: 50 | B52: 2.9.5-4198.171 | C52: ELEMENTOS DESC. P/CIRUGIAS; TIPO: KIT DE CAMISOLIN 50 GRS CON PUÑO DE ALGODON + COFIA + BOTAS PAR, PRESENTACION: INDIVIDUAL, ESTERIL: NO | D52: UNIDAD | E52: 40

Sheet ACUERDO
A1: Detalle de productos o servicios
A2: N° | B2: Objeto del gasto | C2: Código del ítem | D2: Descripción | E2: Cantidad | F2: UM | G2: Cantidad Farmacia | H2: Importe Farmacia | I2: Cantidad Laboratorio | J2: Importe Laboratorio | K2: Cantidad SAME | L2: Importe SAME | M2: Cantidad CUR | N2: Importe CUR | O2: Cantidad Banco de Sangre | P2: Importe Banco de Sangre | Q2: Cantidad Odontologia | R2: Importe Odontologia | S2: Cantidad Total MS | T2: Precio Unitario | U2: Importe Total
A3: 1 | B3: 2.9.5 | C3: 2.9.5-441.470 | D3: AGUJAS QUIRURGICAS; TIPO: TERUMO 21GX1", ESPECIFICACION: 25/8, UNIDAD VENTA: CAJA X 100, PRESENTACION: CAJA X 100 | E3: 600 | F3: UNIDAD | H3: =+G3*T3 -> 0 | I3: 300 | J3: =+I3*T3 -> 30000 | N3: =+M3*T3 -> 0 | O3: 3 | P3: =+O3*T3 -> 300 | R3: =+Q3*T3 -> 0 | S3: =+G3+I3+K3+M3+O3+Q3 -> 303 | T3: 100 | U3: =+S3*T3 -> 30300
A4: 2 | B4: 2.9.5 | C4: 2.9.5-441.471 | D4: AGUJAS QUIRURGICAS; TIPO: TERUMO 25GX5/8", ESPECIFICACION: 16/5, UNIDAD VENTA: CAJA X 100, PRESENTACION: CAJA X 100 | E4: 105 | F4: UNIDAD | H4: =+G4*T4 -> 0 | I4: 90 | J4: =+I4*T4 -> 9000 | N4: =+M4*T4 -> 0 | P4: =+O4*T4 -> 0 | R4: =+Q4*T4 -> 0 | S4: =+G4+I4+K4+M4+O4+Q4 -> 90 | T4: 100 | U4: =+S4*T4 -> 9000
A5: 3 | B5: 2.9.5 | C5: 2.9.5-441.472 | D5: AGUJAS QUIRURGICAS; TIPO: 25GX5/8", ESPECIFICACION: 16/5, UNIDAD VENTA: CAJA X 100 UN, PRESENTACION: CAJA X 100 UN | E5: 650 | F5: UNIDAD | H5: =+G5*T5 -> 0 | J5: =+I5*T5 -> 0 | N5: =+M5*T5 -> 0 | P5: =+O5*T5 -> 0 | R5: =+Q5*T5 -> 0 | S5: =+G5+I5+K5+M5+O5+Q5 -> 0 | T5: 93 | U5: =+S5*T5 -> 0
A6: 4 | B6: 2.9.5 | C6: 2.9.5-441.92 | D6: AGUJAS QUIRURGICAS; TIPO: DESCARTABLE, ESPECIFICACION: 25 X 0,8, UNIDAD VENTA: CAJA X 100, PRESENTACION: CAJA X 100 | E6: 5500 | F6: UNIDAD | H6: =+G6*T6 -> 0 | J6: =+I6*T6 -> 0 | N6: =+M6*T6 -> 0 | P6: =+O6*T6 -> 0 | R6: =+Q6*T6 -> 0 | S6: =+G6+I6+K6+M6+O6+Q6 -> 0 | T6: 93 | U6: =+S6*T6 -> 0
A7: 5 | B7: 2.9.5 | C7: 2.9.5-441.356 | D7: AGUJAS QUIRURGICAS; TIPO: DESCARTABLE, ESPECIFICACION: 40/12, PRESENTACION: ENVASE X 100 UN | E7: 180 | F7: UNIDAD | H7: =+G7*T7 -> 0 | J7: =+I7*T7 -> 0 | N7: =+M7*T7 -> 0 | P7: =+O7*T7 -> 0 | R7: =+Q7*T7 -> 0 | S7: =+G7+I7+K7+M7+O7+Q7 -> 0 | T7: 93 | U7: =+S7*T7 -> 0
A8: 6 | B8: 2.9.5 | C8: 2.9.5-441.51 | D8: AGUJAS QUIRURGICAS; TIPO: DESCARTABLE, UNIDAD VENTA: 100, ESPECIFICACION: 40/8, PRESENTACION: 100 | E8: 3400 | F8: UNIDAD | H8: =+G8*T8 -> 0 | J8: =+I8*T8 -> 0 | N8: =+M8*T8 -> 0 | P8: =+O8*T8 -> 0 | R8: =+Q8*T8 -> 0 | S8: =+G8+I8+K8+M8+O8+Q8 -> 0 | T8: 93 | U8: =+S8*T8 -> 0
A9: 7 | B9: 2.9.5 | C9: 2.9.5-441.245 | D9: AGUJAS QUIRURGICAS; TIPO: ESTERIL, ESPECIFICACION: 50/8, UNIDAD VENTA: CAJA X 100 UN, PRESENTACION: CAJA X 100 UN | E9: 2555 | F9: UNIDAD
A10: 8 | B10: 2.9.5 | C10: 2.9.5-470.13 | D10: ALGODONES; TIPO: HIDROFILADO, CAPACIDAD: 500 GR, PRESENTACION: ENVASE X 500 GR | E10: 7300 | F10: UNIDAD | H10: =+G10*T10 -> 0 | I10: 300 | J10: =+I10*T10 -> 30000 | N10: =+M10*T10 -> 0 | O10: 20 | P10: =+O10*T10 -> 2000 | Q10: 20 | R10: =+Q10*T10 -> 2000 | S10: =+G10+I10+K10+M10+O10+Q10 -> 340 | T10: 100 | U10: =+S10*T10 -> 34000
A11: 9 | B11: 2.9.5 | C11: 2.9.5-446.1 | D11: BAJALENGUAS DESCARTABLES; USO: ADULTOS, PAQUETES DE UNIDADES: X 100, PRESENTACION: X 100 | E11: 2150 | F11: UNIDAD | H11: =+G11*T11 -> 0 | J11: =+I11*T11 -> 0 | N11: =+M11*T11 -> 0 | P11: =+O11*T11 -> 0 | Q11: 1500 | R11: =+Q11*T11 -> 150000 | S11: =+G11+I11+K11+M11+O11+Q11 -> 1500 | T11: 100 | U11: =+S11*T11 -> 150000
A12: 10 | B12: 2.9.5 | C12: 2.9.5-428.21 | D12: BARBIJOS; TIPO: 3 CAPAS | E12: 1266000 | F12: UNIDAD | H12: =+G12*T12 -> 0 | J12: =+I12*T12 -> 0 | N12: =+M12*T12 -> 0 | O12: 1000 | P12: =+O12*T12 -> 91000 | Q12: 1500 | R12: =+Q12*T12 -> 136500 | S12: =+G12+I12+K12+M12+O12+Q12 -> 2500 | T12: 91 | U12: =+S12*T12 -> 227500
A13: 11 | B13: 2.9.5 | C13: 2.9.5-428.36 | D13: BARBIJOS; TIPO: COPA N95 SIN VALVULA, MATERIAL: NO TEJIDO, CANTIDAD DE CAPAS: DOS, DESCARTABLE: SI, PRESENTACION: UNIDAD | E13: 26800 | F13: UNIDAD | H13: =+G13*T13 -> 0 | J13: =+I13*T13 -> 0 | N13: =+M13*T13 -> 0 | P13: =+O13*T13 -> 0 | Q13: 1500 | R13: =+Q13*T13 -> 139500 | S13: =+G13+I13+K13+M13+O13+Q13 -> 1500 | T13: 93 | U13: =+S13*T13 -> 139500
A14: 12 | B14: 2.9.5 | C14: 2.9.5-4198.9 | D14: ELEMENTOS DESC. P/CIRUGIAS; TIPO: BOTA CAÑA ALTA CON TIRAS, CANTIDAD: 1, PRESENTACION: 1 | E14: 20000 | F14: UNIDAD | H14: =+G14*T14 -> 0 | J14: =+I14*T14 -> 0 | N14: =+M14*T14 -> 0 | P14: =+O14*T14 -> 0 | R14: =+Q14*T14 -> 0 | S14: =+G14+I14+K14+M14+O14+Q14 -> 0 | T14: 91 | U14: =+S14*T14 -> 0
A15: 13 | B15: 2.5.1 | C15: 2.5.1-9004.1319 | D15: SALES; COMPUESTO QUIMICO: CAL SODADA, ESTADO: GRANULADO, CALIDAD: MEDICA, PRESENTACION: ENVASE X 1 KG | E15: 201 | F15: UNIDAD | H15: =+G15*T15 -> 0 | J15: =+I15*T15 -> 0 | N15: =+M15*T15 -> 0 | P15: =+O15*T15 -> 0 | R15: =+Q15*T15 -> 0 | S15: =+G15+I15+K15+M15+O15+Q15 -> 0 | T15: 93 | U15: =+S15*T15 -> 0
A16: 14 | B16: 2.9.5 | C16: 2.9.5-4198.170 | D16: ELEMENTOS DESC. P/CIRUGIAS; TIPO: CAMISOLIN HEMORREP. DE 30 GRAMOS CON MANGAS Y PUÑOS ELASTICOS DE 1,4 MTRS DE LARGO, CANTIDAD: POR UNIDAD, PRESENTACION: UNIDAD | E16: 41000 | F16: UNIDAD | H16: =+G16*T16 -> 0 | J16: =+I16*T16 -> 0 | N16: =+M16*T16 -> 0 | P16: =+O16*T16 -> 0 | Q16: 50 | R16: =+Q16*T16 -> 4550 | S16: =+G16+I16+K16+M16+O16+Q16 -> 50 | T16: 91 | U16: =+S16*T16 -> 4550
A17: 15 | B17: 2.9.5 | C17: 2.9.5-4198.169 | D17: ELEMENTOS DESC. P/CIRUGIAS; TIPO: CAMISOLIN HEMORREP. DE 50 GRAMOS CON MANGAS Y PUÑOS ALGODON DE 1,4 MTRS DE LARGO, CANTIDAD: POR UNIDAD, PRESENTACION: UNIDAD | E17: 51400 | F17: UNIDAD | H17: =+G17*T17 -> 0 | J17: =+I17*T17 -> 0 | N17: =+M17*T17 -> 0 | P17: =+O17*T17 -> 0 | R17: =+Q17*T17 -> 0 | S17: =+G17+I17+K17+M17+O17+Q17 -> 0 | T17: 98 | U17: =+S17*T17 -> 0
A18: 16 | B18: 2.9.5 | C18: 2.9.5-4198.28 | D18: ELEMENTOS DESC. P/CIRUGIAS; TIPO: CEPILLO ESTERIL, CANTIDAD: UNIDAD, PRESENTACION: UNIDAD | E18: 1100 | F18: UNIDAD | H18: =+G18*T18 -> 0 | J18: =+I18*T18 -> 0 | N18: =+M18*T18 -> 0 | P18: =+O18*T18 -> 0 | R18: =+Q18*T18 -> 0 | S18: =+G18+I18+K18+M18+O18+Q18 -> 0 | T18: 93 | U18: =+S18*T18 -> 0
A19: 17 | B19: 2.9.5 | C19: 2.9.5-8239.1 | D19: CHATAS; MATERIAL: PVC | E19: 81 | F19: UNIDAD | G19: 10 | H19: =+G19*T19 -> 930 | J19: =+I19*T19 -> 0 | N19: =+M19*T19 -> 0 | P19: =+O19*T19 -> 0 | R19: =+Q19*T19 -> 0 | S19: =+G19+I19+K19+M19+O19+Q19 -> 10 | T19: 93 | U19: =+S19*T19 -> 930
A20: 18 | B20: 2.9.5 | C20: 2.9.5-8050.1 | D20: CLAMPS UMBILICALES; MATERIAL: PLASTICO, PRESENTACION: UNIDAD | E20: 5000 | F20: UNIDAD | H20: =+G20*T20 -> 0 | J20: =+I20*T20 -> 0 | N20: =+M20*T20 -> 0 | P20: =+O20*T20 -> 0 | R20: =+Q20*T20 -> 0 | S20: =+G20+I20+K20+M20+O20+Q20 -> 0 | T20: 100 | U20: =+S20*T20 -> 0
A21: 19 | B21: 2.2.2 | C21: 2.2.2-915.15 | D21: ROPA DESCARTABLE; ELEMENTO: COFIA, VARIEDAD: CON ELASTICO, ESPECIFICACION: CON ELASTICO | E21: 225000 | F21: UNIDAD | H21: =+G21*T21 -> 0 | J21: =+I21*T21 -> 0 | N21: =+M21*T21 -> 0 | P21: =+O21*T21 -> 0 | R21: =+Q21*T21 -> 0 | S21: =+G21+I21+K21+M21+O21+Q21 -> 0 | T21: 93 | U21: =+S21*T21 -> 0
A22: 20 | B22: 2.9.5 | C22: 2.9.5-2505.24 | D22: BOLSAS COLECTORAS; TIPO: DE ORINA, USO: PEDIATRICO, CAPACIDAD: 100 CM3 | E22: 2000 | F22: UNIDAD | H22: =+G22*T22 -> 0 | J22: =+I22*T22 -> 0 | N22: =+M22*T22 -> 0 | P22: =+O22*T22 -> 0 | R22: =+Q22*T22 -> 0 | S22: =+G22+I22+K22+M22+O22+Q22 -> 0 | T22: 93 | U22: =+S22*T22 -> 0
A23: 21 | B23: 2.9.5 | C23: 2.9.5-9998.1 | D23: RECIPIENTE RECOLECTOR; TIPO: FRASCO, USO: P/ALIMENTACION ENTERAL, CAPACIDAD: 250 ML | E23: 65 | F23: UNIDAD | H23: =+G23*T23 -> 0 | J23: =+I23*T23 -> 0 | N23: =+M23*T23 -> 0 | P23: =+O23*T23 -> 0 | R23: =+Q23*T23 -> 0 | S23: =+G23+I23+K23+M23+O23+Q23 -> 0 | U23: =+S23*T23 -> 0
A24: 22 | B24: 2.9.5 | C24: 2.9.5-466.6 | D24: CUBRECAMILLAS; TIPO: DESCARTABLE DE 30 GRS, CON ELASTICO DE 80 X 210 CM | E24: 505 | F24: UNIDAD | H24: =+G24*T24 -> 0 | J24: =+I24*T24 -> 0 | N24: =+M24*T24 -> 0 | P24: =+O24*T24 -> 0 | R24: =+Q24*T24 -> 0 | S24: =+G24+I24+K24+M24+O24+Q24 -> 0 | T24: 91 | U24: =+S24*T24 -> 0
A25: 23 | B25: 2.9.5 | C25: 2.9.5-2160.10 | D25: DESCARTADORES DE AGUJAS; BOCA: 2, CAPACIDAD: 2 L, MODELO: P/AGUJAS COLECTA MULTIPLE, MODELO EQUIPO: P/AGUJAS COLECTA MULTIPLE, SISTEMA DE CIERRE: P/AGUJAS COLECTA MULTIPLE | E25: 1352 | F25: UNIDAD | G25: 100 | H25: =+G25*T25 -> 9100 | I25: 90 | J25: =+I25*T25 -> 8190 | N25: =+M25*T25 -> 0 | P25: =+O25*T25 -> 0 | R25: =+Q25*T25 -> 0 | S25: =+G25+I25+K25+M25+O25+Q25 -> 190 | T25: 91 | U25: =+S25*T25 -> 17290
A26: 24 | B26: 2.9.5 | C26: 2.9.5-2160.45 | D26: DESCARTADORES DE AGUJAS; BOCA: 2, CAPACIDAD: 8 L, MODELO: P/AGUJAS COLECTA MULTIPLE, MODELO EQUIPO: P/AGUJAS COLECTA MULTIPLE, SISTEMA DE CIERRE: P/AGUJAS COLECTA MULTIPLE | E26: 100 | F26: UNIDAD | H26: =+G26*T26 -> 0 | J26: =+I26*T26 -> 0 | N26: =+M26*T26 -> 0 | P26: =+O26*T26 -> 0 | R26: =+Q26*T26 -> 0 | S26: =+G26+I26+K26+M26+O26+Q26 -> 0 | T26: 91 | U26: =+S26*T26 -> 0
A27: 25 | B27: 2.9.5 | C27: 2.9.5-2225.87 | D27: ELECTRODOS P/MEDICINA; TIPO: ECG, USO: MONITORIZACION, PIN: SIN, AGUJA: SIN, DESCARTABLE: SI | E27: 50000 | F27: UNIDAD | H27: =+G27*T27 -> 0 | J27: =+I27*T27 -> 0 | N27: =+M27*T27 -> 0 | P27: =+O27*T27 -> 0 | R27: =+Q27*T27 -> 0 | S27: =+G27+I27+K27+M27+O27+Q27 -> 0 | T27: 98 | U27: =+S27*T27 -> 0
A28: 26 | B28: 2.9.5 | C28: 2.9.5-448.46 | D28: FRASCOS ESTERILES; CAPACIDAD: 125 mL, PRESENTACION: UNIDAD, GRABADO: SIN, USO: UROCULTIVO | E28: 7000 | F28: UNIDAD | H28: =+G28*T28 -> 0 | J28: =+I28*T28 -> 0 | N28: =+M28*T28 -> 0 | P28: =+O28*T28 -> 0 | R28: =+Q28*T28 -> 0 | S28: =+G28+I28+K28+M28+O28+Q28 -> 0 | T28: 92 | U28: =+S28*T28 -> 0
A29: 27 | B29: 2.9.5 | C29: 2.9.5-5723.1 | D29: ESPATULAS DE AYRE; MATERIAL: MADERA (DESCARTABLE), BOLSA X 100 | E29: 31 | F29: UNIDAD | H29: =+G29*T29 -> 0 | J29: =+I29*T29 -> 0 | N29: =+M29*T29 -> 0 | P29: =+O29*T29 -> 0 | R29: =+Q29*T29 -> 0 | S29: =+G29+I29+K29+M29+O29+Q29 -> 0 | T29: 100 | U29: =+S29*T29 -> 0
A30: 28 | B30: 2.9.5 | C30: 2.9.5-3255.10 | D30: ESPECULOS DESCARTABLES; TIPO: VAGINAL PEQUEÑO, PRESENTACION: UNIDAD, MATERIAL: PLASTICO | E30: 1950 | F30: UNIDAD | H30: =+G30*T30 -> 0 | J30: =+I30*T30 -> 0 | N30: =+M30*T30 -> 0 | P30: =+O30*T30 -> 0 | R30: =+Q30*T30 -> 0 | S30: =+G30+I30+K30+M30+O30+Q30 -> 0 | T30: 93 | U30: =+S30*T30 -> 0
A31: 29 | B31: 2.9.5 | C31: 2.9.5-3255.12 | D31: ESPECULOS DESCARTABLES; TIPO: VAGINAL GRANDE, PRESENTACION: UNIDAD, MATERIAL: PLASTICO | E31: 1250 | F31: UNIDAD | H31: =+G31*T31 -> 0 | J31: =+I31*T31 -> 0 | N31: =+M31*T31 -> 0 | P31: =+O31*T31 -> 0 | R31: =+Q31*T31 -> 0 | S31: =+G31+I31+K31+M31+O31+Q31 -> 0 | T31: 93 | U31: =+S31*T31 -> 0
A32: 30 | B32: 2.9.5 | C32: 2.9.5-3255.11 | D32: ESPECULOS DESCARTABLES; TIPO: VAGINAL MEDIO, PRESENTACION: UNIDAD, MATERIAL: PLASTICO | E32: 3100 | F32: UNIDAD | H32: =+G32*T32 -> 0 | J32: =+I32*T32 -> 0 | N32: =+M32*T32 -> 0 | P32: =+O32*T32 -> 0 | R32: =+Q32*T32 -> 0 | S32: =+G32+I32+K32+M32+O32+Q32 -> 0 | T32: 93 | U32: =+S32*T32 -> 0
A33: 31 | B33: 2.5.2 | C33: 2.5.2-3584.1 | D33: GEL P/ECOGRAFIA; PRESENTACION: ENVASE X 1 Kg | E33: 140 | F33: UNIDAD | H33: =+G33*T33 -> 0 | J33: =+I33*T33 -> 0 | N33: =+M33*T33 -> 0 | P33: =+O33*T33 -> 0 | R33: =+Q33*T33 -> 0 | S33: =+G33+I33+K33+M33+O33+Q33 -> 0 | T33: 93 | U33: =+S33*T33 -> 0
A34: 32 | B34: 2.5.2 | C34: 2.5.2-3584.3 | D34: GEL P/ECOGRAFIA; PRESENTACION: ENVASE X 5 Kg | E34: 30 | F34: UNIDAD | H34: =+G34*T34 -> 0 | J34: =+I34*T34 -> 0 | N34: =+M34*T34 -> 0 | P34: =+O34*T34 -> 0 | R34: =+Q34*T34 -> 0 | S34: =+G34+I34+K34+M34+O34+Q34 -> 0 | T34: 93 | U34: =+S34*T34 -> 0
A35: 33 | B35: 2.9.5 | C35: 2.9.5-1909.224 | D35: GUANTES USO MEDICINAL; TIPO: ESTERIL, TAMAÑO: 7 1/2 CAÑA LARGA, MATERIAL: NITRILO, PRESENTACION: ENVASE X 50 PAR, ESTERIL: SI, TALCO: SIN, DESCARTABLE: SI | E35: 48 | F35: UNIDAD | H35: =+G35*T35 -> 0 | J35: =+I35*T35 -> 0 | N35: =+M35*T35 -> 0 | P35: =+O35*T35 -> 0 | R35: =+Q35*T35 -> 0 | S35: =+G35+I35+K35+M35+O35+Q35 -> 0 | T35: 98 | U35: =+S35*T35 -> 0
A36: 34 | B36: 2.9.5 | C36: 2.9.5-1909.135 | D36: GUANTES USO MEDICINAL; TIPO: ESTERIL, TAMAÑO: 6 1/2 CAÑA LARGA, MATERIAL: LATEX, PRESENTACION: PAR, ESTERIL: SI, TALCO: SIN, DESCARTABLE: SI | E36: 10500 | F36: UNIDAD | G36: 1000 | H36: =+G36*T36 -> 93000 | J36: =+I36*T36 -> 0 | N36: =+M36*T36 -> 0 | P36: =+O36*T36 -> 0 | Q36: 10 | R36: =+Q36*T36 -> 930 | S36: =+G36+I36+K36+M36+O36+Q36 -> 1010 | T36: 93 | U36: =+S36*T36 -> 93930
A37: 35 | B37: 2.9.5 | C37: 2.9.5-1909.203 | D37: GUANTES USO MEDICINAL; TIPO: ESTERIL, TAMAÑO: 7 CAÑA LARGA, MATERIAL: LATEX, PRESENTACION: PAR, ESTERIL: SI, TALCO: SIN, DESCARTABLE: SI | E37: 40000 | F37: UNIDAD | H37: =+G37*T37 -> 0 | J37: =+I37*T37 -> 0 | N37: =+M37*T37 -> 0 | P37: =+O37*T37 -> 0 | Q37: 10 | R37: =+Q37*T37 -> 930 | S37: =+G37+I37+K37+M37+O37+Q37 -> 10 | T37: 93 | U37: =+S37*T37 -> 930
A38: 36 | B38: 2.9.5 | C38: 2.9.5-1909.184 | D38: GUANTES USO MEDICINAL; TIPO: ESTERIL, TAMAÑO: 7 1/2 CAÑA LARGA, MATERIAL: LATEX, PRESENTACION: PAR, ESTERIL: SI, TALCO: SIN, DESCARTABLE: SI | E38: 46000 | F38: UNIDAD | H38: =+G38*T38 -> 0 | J38: =+I38*T38 -> 0 | N38: =+M38*T38 -> 0 | P38: =+O38*T38 -> 0 | R38: =+Q38*T38 -> 0 | S38: =+G38+I38+K38+M38+O38+Q38 -> 0 | T38: 93 | U38: =+S38*T38 -> 0
A39: 37 | B39: 2.9.5 | C39: 2.9.5-1909.202 | D39: GUANTES USO MEDICINAL; TIPO: ESTERIL, TAMAÑO: 8 CAÑA LARGA, MATERIAL: LATEX, PRESENTACION: PAR, ESTERIL: SI, TALCO: SIN, DESCARTABLE: SI | E39: 31300 | F39: UNIDAD | H39: =+G39*T39 -> 0 | J39: =+I39*T39 -> 0 | N39: =+M39*T39 -> 0 | P39: =+O39*T39 -> 0 | R39: =+Q39*T39 -> 0 | S39: =+G39+I39+K39+M39+O39+Q39 -> 0 | T39: 93 | U39: =+S39*T39 -> 0
A40: 38 | B40: 2.9.5 | C40: 2.9.5-1909.223 | D40: GUANTES USO MEDICINAL; TIPO: ESTERIL, TAMAÑO: 8 1/2 CAÑA LARGA, MATERIAL: LATEX, PRESENTACION: PAR, ESTERIL: SI, TALCO: SIN, DESCARTABLE: SI | E40: 9300 | F40: UNIDAD | H40: =+G40*T40 -> 0 | J40: =+I40*T40 -> 0 | N40: =+M40*T40 -> 0 | P40: =+O40*T40 -> 0 | R40: =+Q40*T40 -> 0 | S40: =+G40+I40+K40+M40+O40+Q40 -> 0 | T40: 93 | U40: =+S40*T40 -> 0
A41: 39 | B41: 2.9.5 | C41: 2.9.5-1909.78 | D41: GUANTES USO MEDICINAL; TIPO: EXAMINACION , TAMAÑO: GRANDE, MATERIAL: LATEX, PRESENTACION: ENVASE X 100 UN | E41: 7600 | F41: UNIDAD | H41: =+G41*T41 -> 0 | J41: =+I41*T41 -> 0 | N41: =+M41*T41 -> 0 | O41: 10 | P41: =+O41*T41 -> 930 | R41: =+Q41*T41 -> 0 | S41: =+G41+I41+K41+M41+O41+Q41 -> 10 | T41: 93 | U41: =+S41*T41 -> 930
A42: 40 | B42: 2.9.5 | C42: 2.9.5-1909.79 | D42: GUANTES USO MEDICINAL; TIPO: EXAMINACION , TAMAÑO: MEDIANO, MATERIAL: LATEX, PRESENTACION: ENVASE X 100 UN | E42: 20000 | F42: UNIDAD | G42: 2000 | H42: =+G42*T42 -> 186000 | I42: 150 | J42: =+I42*T42 -> 13950 | N42: =+M42*T42 -> 0 | O42: 10 | P42: =+O42*T42 -> 930 | R42: =+Q42*T42 -> 0 | S42: =+G42+I42+K42+M42+O42+Q42 -> 2160 | T42: 93 | U42: =+S42*T42 -> 200880
A43: 41 | B43: 2.9.5 | C43: 2.9.5-1909.195 | D43: GUANTES USO MEDICINAL; TIPO: EXAMINACION, TAMAÑO: S 6/7, MATERIAL: LATEX, PRESENTACION: ENVASE X 100 UN, ESTERIL: NO, TALCO: CON, DESCARTABLE: SI | E43: 11900 | F43: UNIDAD | H43: =+G43*T43 -> 0 | I43: 150 | J43: =+I43*T43 -> 13950 | N43: =+M43*T43 -> 0 | O43: 10 | P43: =+O43*T43 -> 930 | Q43: 10 | R43: =+Q43*T43 -> 930 | S43: =+G43+I43+K43+M43+O43+Q43 -> 170 | T43: 93 | U43: =+S43*T43 -> 15810
A44: 42 | B44: 2.9.5 | C44: 2.9.5-1909.172 | D44: GUANTES USO MEDICINAL; TIPO: EXAMINACION, TAMAÑO: S 6/7, MATERIAL: NITRILO, PRESENTACION: ENVASE X 100 UN, ESTERIL: NO, TALCO: SIN, DESCARTABLE: SI | E44: 430 | F44: UNIDAD | H44: =+G44*T44 -> 0 | I44: 30 | J44: =+I44*T44 -> 2790 | N44: =+M44*T44 -> 0 | P44: =+O44*T44 -> 0 | R44: =+Q44*T44 -> 0 | S44: =+G44+I44+K44+M44+O44+Q44 -> 30 | T44: 93 | U44: =+S44*T44 -> 2790
A45: 43 | B45: 2.9.5 | C45: 2.9.5-1909.174 | D45: GUANTES USO MEDICINAL; TIPO: EXAMINACION, TAMAÑO: L 8/9, MATERIAL: NITRILO, PRESENTACION: ENVASE X 100 UN, ESTERIL: NO, TALCO: SIN, DESCARTABLE: SI | E45: 703 | F45: UNIDAD | H45: =+G45*T45 -> 0 | I45: 15 | J45: =+I45*T45 -> 1395 | N45: =+M45*T45 -> 0 | P45: =+O45*T45 -> 0 | Q45: 10 | R45: =+Q45*T45 -> 930 | S45: =+G45+I45+K45+M45+O45+Q45 -> 25 | T45: 93 | U45: =+S45*T45 -> 2325
A46: 44 | B46: 2.9.5 | C46: 2.9.5-1909.173 | D46: GUANTES USO MEDICINAL; TIPO: EXAMINACION, TAMAÑO: M 7/8, MATERIAL: NITRILO, PRESENTACION: ENVASE X 100 UN, ESTERIL: NO, TALCO: SIN, DESCARTABLE: SI | E46: 893 | F46: UNIDAD | H46: =+G46*T46 -> 0 | I46: 30 | J46: =+I46*T46 -> 2790 | N46: =+M46*T46 -> 0 | P46: =+O46*T46 -> 0 | Q46: 10 | R46: =+Q46*T46 -> 930 | S46: =+G46+I46+K46+M46+O46+Q46 -> 40 | T46: 93 | U46: =+S46*T46 -> 3720
A47: 45 | B47: 2.9.5 | C47: 2.9.5-1909.169 | D47: GUANTES USO MEDICINAL; TIPO: EXAMINACION, TAMAÑO: L 8/9, MATERIAL: VINILO, PRESENTACION: ENVASE X 100 UN, ESTERIL: NO, TALCO: SIN, DESCARTABLE: SI | E47: 1100 | F47: UNIDAD | H47: =+G47*T47 -> 0 | I47: 15 | J47: =+I47*T47 -> 1395 | N47: =+M47*T47 -> 0 | P47: =+O47*T47 -> 0 | R47: =+Q47*T47 -> 0 | S47: =+G47+I47+K47+M47+O47+Q47 -> 15 | T47: 93 | U47: =+S47*T47 -> 1395
A48: 46 | B48: 2.9.5 | C48: 2.9.5-1909.168 | D48: GUANTES USO MEDICINAL; TIPO: EXAMINACION, TAMAÑO: M 7/8, MATERIAL: VINILO, PRESENTACION: ENVASE X 100 UN, ESTERIL: NO, TALCO: SIN, DESCARTABLE: SI | E48: 100 | F48: UNIDAD | H48: =+G48*T48 -> 0 | I48: 150 | J48: =+I48*T48 -> 13950 | N48: =+M48*T48 -> 0 | P48: =+O48*T48 -> 0 | R48: =+Q48*T48 -> 0 | S48: =+G48+I48+K48+M48+O48+Q48 -> 150 | T48: 93 | U48: =+S48*T48 -> 13950
A49: 47 | B49: 2.9.5 | C49: 2.9.5-2366.2 | D49: HISOPOS; MATERIAL DE EXTREMOS: ALGODON, PRESENTACION: CAJA X 100 | E49: 18 | F49: UNIDAD | H49: =+G49*T49 -> 0 | I49: 100 | J49: =+I49*T49 -> 0 | N49: =+M49*T49 -> 0 | P49: =+O49*T49 -> 0 | R49: =+Q49*T49 -> 0 | S49: =+G49+I49+K49+M49+O49+Q49 -> 100 | U49: =+S49*T49 -> 0
A50: 48 | B50: 2.9.5 | C50: 2.9.5-444.60 | D50: HOJAS DE BISTURI; TIPO: CAJA X 100 UN, Nº: 10, NUMERO: 10 | E50: 10 | F50: UNIDAD | H50: =+G50*T50 -> 0 | J50: =+I50*T50 -> 0 | N50: =+M50*T50 -> 0 | P50: =+O50*T50 -> 0 | R50: =+Q50*T50 -> 0 | S50: =+G50+I50+K50+M50+O50+Q50 -> 0 | T50: 93 | U50: =+S50*T50 -> 0
A51: 49 | B51: 2.9.5 | C51: 2.9.5-444.22 | D51: HOJAS DE BISTURI; TIPO: CAJA X 100 UN, Nº: 11, NUMERO: 11 | E51: 65 | F51: UNIDAD | H51: =+G51*T51 -> 0 | J51: =+I51*T51 -> 0 | N51: =+M51*T51 -> 0 | P51: =+O51*T51 -> 0 | R51: =+Q51*T51 -> 0 | S51: =+G51+I51+K51+M51+O51+Q51 -> 0 | T51: 93 | U51: =+S51*T51 -> 0
A52: 50 | B52: 2.9.5 | C52: 2.9.5-444.24 | D52: HOJAS DE BISTURI; TIPO: CAJA X 100 UN, Nº: 15, NUMERO: 15 | E52: 85 | F52: UNIDAD | H52: =+G52*T52 -> 0 | J52: =+I52*T52 -> 0 | N52: =+M52*T52 -> 0 | P52: =+O52*T52 -> 0 | Q52: 4 | R52: =+Q52*T52 -> 372 | S52: =+G52+I52+K52+M52+O52+Q52 -> 4 | T52: 93 | U52: =+S52*T52 -> 372
A53: 51 | B53: 2.9.5 | C53: 2.9.5-444.31 | D53: HOJAS DE BISTURI; TIPO: CAJA X 100 UN, Nº: 22, NUMERO: 22 | E53: 40 | F53: UNIDAD | H53: =+G53*T53 -> 0 | J53: =+I53*T53 -> 0 | N53: =+M53*T53 -> 0 | P53: =+O53*T53 -> 0 | R53: =+Q53*T53 -> 0 | S53: =+G53+I53+K53+M53+O53+Q53 -> 0 | T53: 93 | U53: =+S53*T53 -> 0
A54: 52 | B54: 2.9.5 | C54: 2.9.5-444.61 | D54: HOJAS DE BISTURI; TIPO: CAJA X 100 UN, Nº: 23, NUMERO: 23 | E54: 15 | F54: UNIDAD | H54: =+G54*T54 -> 0 | J54: =+I54*T54 -> 0 | N54: =+M54*T54 -> 0 | P54: =+O54*T54 -> 0 | R54: =+Q54*T54 -> 0 | S54: =+G54+I54+K54+M54+O54+Q54 -> 0 | T54: 93 | U54: =+S54*T54 -> 0
A55: 53 | B55: 2.9.5 | C55: 2.9.5-444.32 | D55: HOJAS DE BISTURI; TIPO: CAJA X 100 UN, Nº: 24, NUMERO: 24 | E55: 208 | F55: UNIDAD | H55: =+G55*T55 -> 0 | J55: =+I55*T55 -> 0 | N55: =+M55*T55 -> 0 | P55: =+O55*T55 -> 0 | R55: =+Q55*T55 -> 0 | S55: =+G55+I55+K55+M55+O55+Q55 -> 0 | T55: 93 | U55: =+S55*T55 -> 0
A56: 54 | B56: 2.9.5 | C56: 2.9.5-2157.121 | D56: JERINGAS DESCARTABLES; CAPACIDAD: 50 CM3, AGUJA: SIN, USO: TIPO TOMEY | E56: 1300 | F56: UNIDAD | H56: =+G56*T56 -> 0 | J56: =+I56*T56 -> 0 | N56: =+M56*T56 -> 0 | P56: =+O56*T56 -> 0 | R56: =+Q56*T56 -> 0 | S56: =+G56+I56+K56+M56+O56+Q56 -> 0 | T56: 91 | U56: =+S56*T56 -> 0
A57: 55 | B57: 2.9.5 | C57: 2.9.5-2157.60 | D57: JERINGAS DESCARTABLES; CAPACIDAD: 10 mL, AGUJA: SIN, USO: MEDICINAL | E57: 240000 | F57: UNIDAD | G57: 50000 | H57: =+G57*T57 -> 4650000 | I57: 90 | J57: =+I57*T57 -> 8370 | N57: =+M57*T57 -> 0 | O57: 500 | P57: =+O57*T57 -> 46500 | R57: =+Q57*T57 -> 0 | S57: =+G57+I57+K57+M57+O57+Q57 -> 50590 | T57: 93 | U57: =+S57*T57 -> 4704870
A58: 56 | B58: 2.9.5 | C58: 2.9.5-2157.120 | D58: JERINGAS DESCARTABLES; CAPACIDAD: 20 CM3, AGUJA: SIN, USO: MEDICINAL | E58: 25600 | F58: UNIDAD | H58: =+G58*T58 -> 0 | J58: =+I58*T58 -> 0 | N58: =+M58*T58 -> 0 | P58: =+O58*T58 -> 0 | R58: =+Q58*T58 -> 0 | S58: =+G58+I58+K58+M58+O58+Q58 -> 0 | T58: 93 | U58: =+S58*T58 -> 0
A59: 57 | B59: 2.9.5 | C59: 2.9.5-2157.67 | D59: JERINGAS DESCARTABLES; CAPACIDAD: 5 CM3, AGUJA: SIN, USO: SIN VALOR | E59: 380500 | F59: UNIDAD | H59: =+G59*T59 -> 0 | I59: 150 | J59: =+I59*T59 -> 13950 | N59: =+M59*T59 -> 0 | P59: =+O59*T59 -> 0 | R59: =+Q59*T59 -> 0 | S59: =+G59+I59+K59+M59+O59+Q59 -> 150 | T59: 93 | U59: =+S59*T59 -> 13950
A60: 58 | B60: 2.9.5 | C60: 2.9.5-2157.86 | D60: JERINGAS DESCARTABLES; CAPACIDAD: 60 CM3, AGUJA: SIN, USO: SIN VALOR | E60: 7000 | F60: UNIDAD | H60: =+G60*T60 -> 0 | J60: =+I60*T60 -> 0 | N60: =+M60*T60 -> 0 | P60: =+O60*T60 -> 0 | R60: =+Q60*T60 -> 0 | S60: =+G60+I60+K60+M60+O60+Q60 -> 0 | T60: 91 | U60: =+S60*T60 -> 0
A61: 59 | B61: 2.9.5 | C61: 2.9.5-2157.154 | D61: JERINGAS DESCARTABLES; CAPACIDAD: 1 mL, AGUJA: 16/5, USO: INSULINA | E61: 83800 | F61: UNIDAD | H61: =+G61*T61 -> 0 | J61: =+I61*T61 -> 0 | N61: =+M61*T61 -> 0 | P61: =+O61*T61 -> 0 | R61: =+Q61*T61 -> 0 | S61: =+G61+I61+K61+M61+O61+Q61 -> 0 | T61: 93 | U61: =+S61*T61 -> 0
A62: 60 | B62: 2.9.5 | C62: 2.9.5-2157.99 | D62: JERINGAS DESCARTABLES; CAPACIDAD: 1 CM3, AGUJA: SIN, USO: TUBERCULINA | E62: 36500 | F62: UNIDAD | H62: =+G62*T62 -> 0 | J62: =+I62*T62 -> 0 | N62: =+M62*T62 -> 0 | P62: =+O62*T62 -> 0 | R62: =+Q62*T62 -> 0 | S62: =+G62+I62+K62+M62+O62+Q62 -> 0 | T62: 93 | U62: =+S62*T62 -> 0
A63: 61 | B63: 2.9.5 | C63: 2.9.5-2157.140 | D63: JERINGAS DESCARTABLES; CAPACIDAD: 2,5 mL, AGUJA: SIN, USO: MEDICINAL | E63: 40000 | F63: UNIDAD | H63: =+G63*T63 -> 0 | J63: =+I63*T63 -> 0 | N63: =+M63*T63 -> 0 | P63: =+O63*T63 -> 0 | R63: =+Q63*T63 -> 0 | S63: =+G63+I63+K63+M63+O63+Q63 -> 0 | T63: 93 | U63: =+S63*T63 -> 0
A64: 62 | B64: 2.9.5 | C64: 2.9.5-4198.171 | D64: ELEMENTOS DESC. P/CIRUGIAS; TIPO: KIT DE CAMISOLIN 50 GRS CON PUÑO DE ALGODON + COFIA + BOTAS PAR, PRESENTACION: INDIVIDUAL, ESTERIL: NO | E64: 153000 | F64: UNIDAD | H64: =+G64*T64 -> 0 | J64: =+I64*T64 -> 0 | N64: =+M64*T64 -> 0 | P64: =+O64*T64 -> 0 | Q64: 40 | R64: =+Q64*T64 -> 3920 | S64: =+G64+I64+K64+M64+O64+Q64 -> 40 | T64: 98 | U64: =+S64*T64 -> 3920
A65: 63 | B65: 2.9.5 | C65: 2.9.5-6535.9 | D65: MAMADERAS; MATERIAL: VIDRIO BOROSILICATO, TIPO: PYREX, TAPA: CON, VOLUMEN: 75 ML | E65: 288 | F65: UNIDAD | H65: =+G65*T65 -> 0 | J65: =+I65*T65 -> 0 | N65: =+M65*T65 -> 0 | P65: =+O65*T65 -> 0 | R65: =+Q65*T65 -> 0 | S65: =+G65+I65+K65+M65+O65+Q65 -> 0 | T65: 100 | U65: =+S65*T65 -> 0
A66: 64 | B66: 2.9.5 | C66: 2.9.5-6535.3 | D66: MAMADERAS; MATERIAL: VIDRIO BOROSILICATO, TIPO: PYREX, TAPA: CON, VOLUMEN: 250 mL | E66: 788 | F66: UNIDAD | H66: =+G66*T66 -> 0 | J66: =+I66*T66 -> 0 | N66: =+M66*T66 -> 0 | P66: =+O66*T66 -> 0 | R66: =+Q66*T66 -> 0 | S66: =+G66+I66+K66+M66+O66+Q66 -> 0 | T66: 100 | U66: =+S66*T66 -> 0
A67: 65 | B67: 2.9.5 | C67: 2.9.5-1909.96 | D67: GUANTES USO MEDICINAL; TIPO: MANOPLA, TAMAÑO: MEDIANO, MATERIAL: POLIETILENO, PRESENTACION: ENVASE X 100 | E67: 1050 | F67: UNIDAD | H67: =+G67*T67 -> 0 | I67: 150 | J67: =+I67*T67 -> 13950 | N67: =+M67*T67 -> 0 | P67: =+O67*T67 -> 0 | R67: =+Q67*T67 -> 0 | S67: =+G67+I67+K67+M67+O67+Q67 -> 150 | T67: 93 | U67: =+S67*T67 -> 13950
A68: 66 | B68: 2.9.5 | C68: 2.9.5-461.78 | D68: VENDAS USO MEDICO; TIPO: OVATA, MEDIDA: 10 Cm | E68: 910 | F68: UNIDAD | G68: 100 | H68: =+G68*T68 -> 10000 | J68: =+I68*T68 -> 0 | N68: =+M68*T68 -> 0 | P68: =+O68*T68 -> 0 | R68: =+Q68*T68 -> 0 | S68: =+G68+I68+K68+M68+O68+Q68 -> 100 | T68: 100 | U68: =+S68*T68 -> 10000
A69: 67 | B69: 2.9.5 | C69: 2.9.5-461.80 | D69: VENDAS USO MEDICO; TIPO: OVATA, MEDIDA: 15 Cm | E69: 1410 | F69: UNIDAD | H69: =+G69*T69 -> 0 | J69: =+I69*T69 -> 0 | N69: =+M69*T69 -> 0 | P69: =+O69*T69 -> 0 | R69: =+Q69*T69 -> 0 | S69: =+G69+I69+K69+M69+O69+Q69 -> 0 | T69: 95.21 | U69: =+S69*T69 -> 0
A70: 68 | B70: 2.9.5 | C70: 2.9.5-461.88 | D70: VENDAS USO MEDICO; TIPO: OVATA, MEDIDA: 20 Cm | E70: 1400 | F70: UNIDAD | H70: =+G70*T70 -> 0 | J70: =+I70*T70 -> 0 | N70: =+M70*T70 -> 0 | P70: =+O70*T70 -> 0 | R70: =+Q70*T70 -> 0 | S70: =+G70+I70+K70+M70+O70+Q70 -> 0 | T70: 100 | U70: =+S70*T70 -> 0
A71: 69 | B71: 2.9.9 | C71: 2.9.9-2504.21 | D71: PAÑALES; USO: ADULTO, TIPO: DESCARTABLE XG | E71: 33000 | F71: UNIDAD | H71: =+G71*T71 -> 0 | J71: =+I71*T71 -> 0 | N71: =+M71*T71 -> 0 | P71: =+O71*T71 -> 0 | R71: =+Q71*T71 -> 0 | S71: =+G71+I71+K71+M71+O71+Q71 -> 0 | T71: 93 | U71: =+S71*T71 -> 0
A72: 70 | B72: 2.9.9 | C72: 2.9.9-2504.9 | D72: PAÑALES; TIPO: DESCARTABLE, USO: NIÑO PREMATURO 0,8 A 1,3 Kg | E72: 3000 | F72: UNIDAD | H72: =+G72*T72 -> 0 | J72: =+I72*T72 -> 0 | N72: =+M72*T72 -> 0 | P72: =+O72*T72 -> 0 | R72: =+Q72*T72 -> 0 | S72: =+G72+I72+K72+M72+O72+Q72 -> 0 | T72: 91 | U72: =+S72*T72 -> 0
A73: 71 | B73: 2.9.9 | C73: 2.9.9-2504.11 | D73: PAÑALES; TIPO: DESCARTABLE, USO: NIÑOS EXTRAGRANDE 12 A 15 Kg | E73: 1500 | F73: UNIDAD | H73: =+G73*T73 -> 0 | J73: =+I73*T73 -> 0 | N73: =+M73*T73 -> 0 | P73: =+O73*T73 -> 0 | R73: =+Q73*T73 -> 0 | S73: =+G73+I73+K73+M73+O73+Q73 -> 0 | T73: 91 | U73: =+S73*T73 -> 0
A74: 72 | B74: 2.9.9 | C74: 2.9.9-2504.13 | D74: PAÑALES; TIPO: DESCARTABLE, USO: GRANDE 9 A 12,5 Kg | E74: 1500 | F74: UNIDAD | H74: =+G74*T74 -> 0 | J74: =+I74*T74 -> 0 | N74: =+M74*T74 -> 0 | P74: =+O74*T74 -> 0 | R74: =+Q74*T74 -> 0 | S74: =+G74+I74+K74+M74+O74+Q74 -> 0 | T74: 93 | U74: =+S74*T74 -> 0
A75: 73 | B75: 2.9.9 | C75: 2.9.9-2504.3 | D75: PAÑALES; TIPO: DESCARTABLE, USO: NIÑOS MEDIANOS (5 A 11 KG) | E75: 2000 | F75: UNIDAD | H75: =+G75*T75 -> 0 | J75: =+I75*T75 -> 0 | N75: =+M75*T75 -> 0 | P75: =+O75*T75 -> 0 | R75: =+Q75*T75 -> 0 | S75: =+G75+I75+K75+M75+O75+Q75 -> 0 | T75: 93 | U75: =+S75*T75 -> 0
A76: 74 | B76: 2.9.9 | C76: 2.9.9-2504.2 | D76: PAÑALES; TIPO: DESCARTABLE, USO: NIÑOS PEQUEÑOS (3 A 6 KG) | E76: 31000 | F76: UNIDAD | H76: =+G76*T76 -> 0 | J76: =+I76*T76 -> 0 | N76: =+M76*T76 -> 0 | P76: =+O76*T76 -> 0 | R76: =+Q76*T76 -> 0 | S76: =+G76+I76+K76+M76+O76+Q76 -> 0 | T76: 93 | U76: =+S76*T76 -> 0
A77: 75 | B77: 2.9.5 | C77: 2.9.5-2562.11 | D77: PORTAOBJETOS P/MICROSCOPIO; MATERIAL: VIDRIO, PRESENTACION: CAJA X 100 UN, TAMAÑO: 25 X 76 X 1,2 mm | E77: 40 | F77: UNIDAD | H77: =+G77*T77 -> 0 | I77: 150 | J77: =+I77*T77 -> 13650 | N77: =+M77*T77 -> 0 | P77: =+O77*T77 -> 0 | R77: =+Q77*T77 -> 0 | S77: =+G77+I77+K77+M77+O77+Q77 -> 150 | T77: 91 | U77: =+S77*T77 -> 13650
A78: 76 | B78: 2.9.5 | C78: 2.9.5-2205.30 | D78: PROLONGADORES P/GUIA SUERO; USO: ADMINISTRACION DE SOLUCIONES, MODELO: PT26 LONGITUD: 150 CM | E78: 4000 | F78: UNIDAD | H78: =+G78*T78 -> 0 | J78: =+I78*T78 -> 0 | N78: =+M78*T78 -> 0 | P78: =+O78*T78 -> 0 | R78: =+Q78*T78 -> 0 | S78: =+G78+I78+K78+M78+O78+Q78 -> 0 | T78: 93 | U78: =+S78*T78 -> 0
A79: 77 | B79: 2.9.5 | C79: 2.9.5-2205.31 | D79: PROLONGADORES P/GUIA SUERO; USO: ADMINISTRACION DE SOLUCIONES, MODELO: PT26 LONGITUD: 30 CM | E79: 1000 | F79: UNIDAD | G79: 80 | H79: =+G79*T79 -> 7440 | J79: =+I79*T79 -> 0 | N79: =+M79*T79 -> 0 | P79: =+O79*T79 -> 0 | R79: =+Q79*T79 -> 0 | S79: =+G79+I79+K79+M79+O79+Q79 -> 80 | T79: 93 | U79: =+S79*T79 -> 7440
A80: 78 | B80: 2.9.5 | C80: 2.9.5-2205.32 | D80: PROLONGADORES P/GUIA SUERO; USO: ADMINISTRACION DE SOLUCIONES, MODELO: PT26 LONGITUD: 50 CM | E80: 2500 | F80: UNIDAD | H80: =+G80*T80 -> 0 | J80: =+I80*T80 -> 0 | N80: =+M80*T80 -> 0 | P80: =+O80*T80 -> 0 | R80: =+Q80*T80 -> 0 | S80: =+G80+I80+K80+M80+O80+Q80 -> 0 | T80: 93 | U80: =+S80*T80 -> 0
A81: 79 | B81: 2.9.5 | C81: 2.9.5-7843.5 | D81: BRAZALETES P/MEDICINA; MATERIAL: PLASTICO, USO: IDENTIFICACION MADRE - HIJO, TIPO: IDENTIFICATORIA | E81: 2500 | F81: UNIDAD | H81: =+G81*T81 -> 0 | J81: =+I81*T81 -> 0 | N81: =+M81*T81 -> 0 | P81: =+O81*T81 -> 0 | R81: =+Q81*T81 -> 0 | S81: =+G81+I81+K81+M81+O81+Q81 -> 0 | T81: 91 | U81: =+S81*T81 -> 0
A82: 80 | B82: 2.9.5 | C82: 2.9.5-2161.542 | D82: CATETERES/SONDAS; NUMERO: K-26P, TIPO: NASOGASTRICA C/REGULADOR | E82: 5600 | F82: UNIDAD | H82: =+G82*T82 -> 0 | J82: =+I82*T82 -> 0 | N82: =+M82*T82 -> 0 | P82: =+O82*T82 -> 0 | R82: =+Q82*T82 -> 0 | S82: =+G82+I82+K82+M82+O82+Q82 -> 0 | T82: 91 | U82: =+S82*T82 -> 0
A83: 81 | B83: 2.9.5 | C83: 2.9.5-2161.543 | D83: CATETERES/SONDAS; NUMERO: K-28P, TIPO: NASOGASTRICA C/REGULADOR | E83: 5600 | F83: UNIDAD | H83: =+G83*T83 -> 0 | J83: =+I83*T83 -> 0 | N83: =+M83*T83 -> 0 | P83: =+O83*T83 -> 0 | R83: =+Q83*T83 -> 0 | S83: =+G83+I83+K83+M83+O83+Q83 -> 0 | T83: 93 | U83: =+S83*T83 -> 0
A84: 82 | B84: 2.9.5 | C84: 2.9.5-2161.160 | D84: CATETERES/SONDAS; NUMERO: K32P, TIPO: ASPIRACION SECRECIONES | E84: 23000 | F84: UNIDAD | H84: =+G84*T84 -> 0 | J84: =+I84*T84 -> 0 | N84: =+M84*T84 -> 0 | P84: =+O84*T84 -> 0 | R84: =+Q84*T84 -> 0 | S84: =+G84+I84+K84+M84+O84+Q84 -> 0 | T84: 93 | U84: =+S84*T84 -> 0
A85: 83 | B85: 2.9.5 | C85: 2.9.5-2161.544 | D85: CATETERES/SONDAS; NUMERO: K-29P, TIPO: NASOGASTRICA C/REGULADOR | E85: 3800 | F85: UNIDAD | H85: =+G85*T85 -> 0 | J85: =+I85*T85 -> 0 | N85: =+M85*T85 -> 0 | P85: =+O85*T85 -> 0 | R85: =+Q85*T85 -> 0 | S85: =+G85+I85+K85+M85+O85+Q85 -> 0 | T85: 93 | U85: =+S85*T85 -> 0
A86: 84 | B86: 2.9.5 | C86: 2.9.5-2161.501 | D86: CATETERES/SONDAS; NUMERO: K-30, TIPO: NASOGASTRICA C/REGULADOR | E86: 1750 | F86: UNIDAD | H86: =+G86*T86 -> 0 | J86: =+I86*T86 -> 0 | N86: =+M86*T86 -> 0 | P86: =+O86*T86 -> 0 | R86: =+Q86*T86 -> 0 | S86: =+G86+I86+K86+M86+O86+Q86 -> 0 | T86: 93 | U86: =+S86*T86 -> 0
A87: 85 | B87: 2.9.5 | C87: 2.9.5-2161.181 | D87: CATETERES/SONDAS; NUMERO: K-31P, TIPO: NASOGASTRICA C/REGULADOR | E87: 2250 | F87: UNIDAD | H87: =+G87*T87 -> 0 | J87: =+I87*T87 -> 0 | N87: =+M87*T87 -> 0 | P87: =+O87*T87 -> 0 | R87: =+Q87*T87 -> 0 | S87: =+G87+I87+K87+M87+O87+Q87 -> 0 | T87: 93 | U87: =+S87*T87 -> 0
A88: 86 | B88: 2.9.5 | C88: 2.9.5-2161.500 | D88: CATETERES/SONDAS; NUMERO: K-33, TIPO: NASOGASTRICA C/REGULADOR | E88: 5750 | F88: UNIDAD | H88: =+G88*T88 -> 0 | J88: =+I88*T88 -> 0 | N88: =+M88*T88 -> 0 | P88: =+O88*T88 -> 0 | R88: =+Q88*T88 -> 0 | S88: =+G88+I88+K88+M88+O88+Q88 -> 0 | T88: 93 | U88: =+S88*T88 -> 0
A89: 87 | B89: 2.9.5 | C89: 2.9.5-2161.189 | D89: CATETERES/SONDAS; NUMERO: K-35P, TIPO: NASOGASTRICA C/REGULADOR | E89: 5500 | F89: UNIDAD | H89: =+G89*T89 -> 0 | J89: =+I89*T89 -> 0 | N89: =+M89*T89 -> 0 | P89: =+O89*T89 -> 0 | R89: =+Q89*T89 -> 0 | S89: =+G89+I89+K89+M89+O89+Q89 -> 0 | T89: 93 | U89: =+S89*T89 -> 0
A90: 88 | B90: 2.9.5 | C90: 2.9.5-2161.545 | D90: CATETERES/SONDAS; NUMERO: SIN, TIPO: TUBO DE LUKEN PARA TOMA DE MUESTRAS | E90: 3740 | F90: UNIDAD | H90: =+G90*T90 -> 0 | J90: =+I90*T90 -> 0 | N90: =+M90*T90 -> 0 | P90: =+O90*T90 -> 0 | R90: =+Q90*T90 -> 0 | S90: =+G90+I90+K90+M90+O90+Q90 -> 0 | U90: =+S90*T90 -> 0
A91: 89 | B91: 2.9.5 | C91: 2.9.5-931.49 | D91: TELAS ADHESIVAS; ANCHO: 2,5 Cm, LONG.DE CUERPO: 9 M, TIPO: IMPERMEABLE | E91: 12506 | F91: UNIDAD | G91: 2000 | H91: =+G91*T91 -> 186000 | J91: =+I91*T91 -> 0 | N91: =+M91*T91 -> 0 | P91: =+O91*T91 -> 0 | R91: =+Q91*T91 -> 0 | S91: =+G91+I91+K91+M91+O91+Q91 -> 2000 | T91: 93 | U91: =+S91*T91 -> 186000
A92: 90 | B92: 2.9.5 | C92: 2.9.5-931.36 | D92: TELAS ADHESIVAS; ANCHO: 5 Cm, LONG.DE CUERPO: 9 M, TIPO: IMPERMEABLE | E92: 8200 | F92: UNIDAD | H92: =+G92*T92 -> 0 | J92: =+I92*T92 -> 0 | N92: =+M92*T92 -> 0 | P92: =+O92*T92 -> 0 | R92: =+Q92*T92 -> 0 | S92: =+G92+I92+K92+M92+O92+Q92 -> 0 | T92: 93 | U92: =+S92*T92 -> 0
A93: 91 | B93: 2.9.5 | C93: 2.9.5-931.47 | D93: TELAS ADHESIVAS; ANCHO: 2,5 Cm, LONG.DE CUERPO: 9 M, TIPO: HIPOALERGICA MICROPOROSA | E93: 1700 | F93: UNIDAD | H93: =+G93*T93 -> 0 | J93: =+I93*T93 -> 0 | N93: =+M93*T93 -> 0 | P93: =+O93*T93 -> 0 | R93: =+Q93*T93 -> 0 | S93: =+G93+I93+K93+M93+O93+Q93 -> 0 | T93: 93 | U93: =+S93*T93 -> 0
A94: 92 | B94: 2.9.5 | C94: 2.9.5-931.21 | D94: TELAS ADHESIVAS; ANCHO: 5.00 CM, LONG.DE CUERPO: 9 M, TIPO: HIPOALERGENICA MICROPOROSA | E94: 1000 | F94: UNIDAD | H94: =+G94*T94 -> 0 | J94: =+I94*T94 -> 0 | N94: =+M94*T94 -> 0 | P94: =+O94*T94 -> 0 | R94: =+Q94*T94 -> 0 | S94: =+G94+I94+K94+M94+O94+Q94 -> 0 | T94: 93 | U94: =+S94*T94 -> 0
A95: 93 | B95: 2.9.5 | C95: 2.9.5-931.48 | D95: TELAS ADHESIVAS; ANCHO: 2,5 CM, LONG.DE CUERPO: 9 M, TIPO: HIPOALERGENICA MACROPOROSA TRANSPARENTE | E95: 2700 | F95: UNIDAD | H95: =+G95*T95 -> 0 | J95: =+I95*T95 -> 0 | N95: =+M95*T95 -> 0 | P95: =+O95*T95 -> 0 | R95: =+Q95*T95 -> 0 | S95: =+G95+I95+K95+M95+O95+Q95 -> 0 | T95: 93 | U95: =+S95*T95 -> 0
A96: 94 | B96: 2.9.5 | C96: 2.9.5-931.9 | D96: TELAS ADHESIVAS; LONG.DE CUERPO: 9 M, ANCHO: 5.00 CM, TIPO: HIPOALERGENICA MACROPOROSA TRANSPARENTE | E96: 800 | F96: UNIDAD | G96: 200 | H96: =+G96*T96 -> 18600 | J96: =+I96*T96 -> 0 | N96: =+M96*T96 -> 0 | P96: =+O96*T96 -> 0 | R96: =+Q96*T96 -> 0 | S96: =+G96+I96+K96+M96+O96+Q96 -> 200 | T96: 93 | U96: =+S96*T96 -> 18600
A97: 95 | B97: 2.9.5 | C97: 2.9.5-3751.41 | D97: TERMOMETROS MEDICINALES; TIPO: DIGITAL, ESCALA: GRADO CENTIGRADO, RANGO DE TEMPERATURA: 35,5 A 42 °C | E97: 620 | F97: UNIDAD | H97: =+G97*T97 -> 0 | J97: =+I97*T97 -> 0 | N97: =+M97*T97 -> 0 | P97: =+O97*T97 -> 0 | R97: =+Q97*T97 -> 0 | S97: =+G97+I97+K97+M97+O97+Q97 -> 0 | T97: 91 | U97: =+S97*T97 -> 0
A98: 96 | B98: 2.9.9 | C98: 2.9.9-7939.1 | D98: TETINAS; MATERIAL: SILICONA, TAMAÑO MAMADERA: 250 CM3, NUMERO: 1 | E98: 150 | F98: UNIDAD | H98: =+G98*T98 -> 0 | J98: =+I98*T98 -> 0 | N98: =+M98*T98 -> 0 | P98: =+O98*T98 -> 0 | R98: =+Q98*T98 -> 0 | S98: =+G98+I98+K98+M98+O98+Q98 -> 0 | T98: 91 | U98: =+S98*T98 -> 0
A99: 97 | B99: 2.9.9 | C99: 2.9.9-7939.3 | D99: TETINAS; MATERIAL: SILICONA, TAMAÑO MAMADERA: 500 CM3, NUMERO: 2 | E99: 300 | F99: UNIDAD | H99: =+G99*T99 -> 0 | J99: =+I99*T99 -> 0 | N99: =+M99*T99 -> 0 | P99: =+O99*T99 -> 0 | R99: =+Q99*T99 -> 0 | S99: =+G99+I99+K99+M99+O99+Q99 -> 0 | T99: 91 | U99: =+S99*T99 -> 0
A100: 98 | B100: 2.9.9 | C100: 2.9.9-7939.4 | D100: TETINAS; MATERIAL: SILICONA, TAMAÑO MAMADERA: PIPETA PASTEUR, NUMERO: 3 | E100: 100 | F100: UNIDAD | H100: =+G100*T100 -> 0 | J100: =+I100*T100 -> 0 | N100: =+M100*T100 -> 0 | P100: =+O100*T100 -> 0 | R100: =+Q100*T100 -> 0 | S100: =+G100+I100+K100+M100+O100+Q100 -> 0 | T100: 91 | U100: =+S100*T100 -> 0
...

Sheet NP FCIA
A1: NOTA DE PEDIDO | J1: N° | K1: 018/2022
A3: JURISDICCIÓN: | D3: 040 - MINISTERIO DE SALUD
A4: SAF: | D4: 011 - DIRECCION PROVINCIAL DE ADMINISTRACION - MS
A5: UNIDAD EJECUTORA: | D5: DIRECCION PROVINCIAL DE FARMACIA E INSUMOS
A6: DEPENDENCIA SOLICITANTE: | D6: DIRECCION PROVINCIAL DE FARMACIA E INSUMOS
A7: PERIODO UTILIZACIÓN: | D7: UN (1) MES
A8: OBJETO: | D8: ACUERDO MARCO PEDIDO DE INSUMOS COMUNES
A10: Ítem | B10: Codigo Item | C10: DESCRIPCIÓN | H10: Adjunta Detalle Técnico | I10: Unidad Medida | J10: Precio Unitario Estimado | K10: Cantidad Solicitada
A12: 17 | B12: =ACUERDO!C19 -> 2.9.5-8239.1 | C12: =ACUERDO!D19 -> CHATAS; MATERIAL: PVC | H12: NO | I12: =ACUERDO!F19 -> UNIDAD | J12: =ACUERDO!T19 -> 93 | K12: =ACUERDO!G19 -> 10
A13: 23 | B13: =ACUERDO!C25 -> 2.9.5-2160.10 | C13: =ACUERDO!D25 -> DESCARTADORES DE AGUJAS; BOCA: 2, CAPACIDAD: 2 L, MODELO: P/AGUJAS COLECTA MULTIPLE, MODELO EQUIPO: P/AGUJAS COLECTA MULTIPLE, SISTEMA DE CIERRE: P/AGUJAS COLECTA MULTIPLE | H13: NO | I13: =ACUERDO!F25 -> UNIDAD | J13: =ACUERDO!T25 -> 91 | K13: =ACUERDO!G25 -> 100
A14: 34 | B14: =ACUERDO!C36 -> 2.9.5-1909.135 | C14: =ACUERDO!D36 -> GUANTES USO MEDICINAL; TIPO: ESTERIL, TAMAÑO: 6 1/2 CAÑA LARGA, MATERIAL: LATEX, PRESENTACION: PAR, ESTERIL: SI, TALCO: SIN, DESCARTABLE: SI | H14: NO | I14: =ACUERDO!F36 -> UNIDAD | J14: =ACUERDO!T36 -> 93 | K14: =ACUERDO!G36 -> 1000
A15: 40 | B15: =ACUERDO!C42 -> 2.9.5-1909.79 | C15: =ACUERDO!D42 -> GUANTES USO MEDICINAL; TIPO: EXAMINACION , TAMAÑO: MEDIANO, MATERIAL: LATEX, PRESENTACION: ENVASE X 100 UN | H15: NO | I15: =ACUERDO!F42 -> UNIDAD | J15: =ACUERDO!T42 -> 93 | K15: =ACUERDO!G42 -> 2000
A16: 55 | B16: =ACUERDO!C57 -> 2.9.5-2157.60 | C16: =ACUERDO!D57 -> JERINGAS DESCARTABLES; CAPACIDAD: 10 mL, AGUJA: SIN, USO: MEDICINAL | H16: NO | I16: =ACUERDO!F57 -> UNIDAD | J16: =ACUERDO!T57 -> 93 | K16: =ACUERDO!G57 -> 50000
A17: 66 | B17: =ACUERDO!C68 -> 2.9.5-461.78 | C17: =ACUERDO!D68 -> VENDAS USO MEDICO; TIPO: OVATA, MEDIDA: 10 Cm | H17: NO | I17: =ACUERDO!F68 -> UNIDAD | J17: =ACUERDO!T68 -> 100 | K17: =ACUERDO!G68 -> 100
A18: 77 | B18: =ACUERDO!C79 -> 2.9.5-2205.31 | C18: =ACUERDO!D79 -> PROLONGADORES P/GUIA SUERO; USO: ADMINISTRACION DE SOLUCIONES, MODELO: PT26 LONGITUD: 30 CM | H18: NO | I18: =ACUERDO!F79 -> UNIDAD | J18: =ACUERDO!T79 -> 93 | K18: =ACUERDO!G79 -> 80
A19: 89 | B19: =ACUERDO!C91 -> 2.9.5-931.49 | C19: =ACUERDO!D91 -> TELAS ADHESIVAS; ANCHO: 2,5 Cm, LONG.DE CUERPO: 9 M, TIPO: IMPERMEABLE | H19: NO | I19: =ACUERDO!F91 -> UNIDAD | J19: =ACUERDO!T91 -> 93 | K19: =ACUERDO!G91 -> 2000
A20: 94 | B20: =ACUERDO!C96 -> 2.9.5-931.9 | C20: =ACUERDO!D96 -> TELAS ADHESIVAS; LONG.DE CUERPO: 9 M, ANCHO: 5.00 CM, TIPO: HIPOALERGENICA MACROPOROSA TRANSPARENTE | H20: NO | I20: =ACUERDO!F96 -> UNIDAD | J20: =ACUERDO!T96 -> 93 | K20: =ACUERDO!G96 -> 200
A21: 100 | B21: =ACUERDO!C102 -> 2.9.5-6526.10 | C21: =ACUERDO!D102 -> TUBOS P/MEDICINA; TIPO: DE LATEX, USO: P/DRENAJE, PRESENTACION: M, DIMENSION: 5 X 8 MM | H21: NO | I21: =ACUERDO!F102 -> UNIDAD | J21: =ACUERDO!T102 -> 91 | K21: =ACUERDO!G102 -> 10
A22: 121 | B22: =ACUERDO!C123 -> 2.9.5-2569.151 | C22: =ACUERDO!D123 -> TUBOS TRAQUEALES; TIPO: ENDOTRAQUEAL PEDIATR. S/BALON, Nº: 3, NUMERO: 3 | H22: NO | I22: =ACUERDO!F123 -> UNIDAD | J22: =ACUERDO!T123 -> 93 | K22: =ACUERDO!G123 -> 10
A23: 122 | B23: =ACUERDO!C124 -> 2.9.5-2569.99 | C23: =ACUERDO!D124 -> TUBOS TRAQUEALES; Nº: 3 1/2 S/BALON DESCARTABLE, TIPO: ENDOTRAQUEAL PEDIATRICO PERFOR, NUMERO: 3 1/2 S/BALON DESCARTABLE | H23: NO | I23: =ACUERDO!F124 -> UNIDAD | J23: =ACUERDO!T124 -> 93 | K23: =ACUERDO!G124 -> 10
A24: 127 | B24: =ACUERDO!C129 -> 2.9.5-461.4 | C24: =ACUERDO!D129 -> VENDAS USO MEDICO; TIPO: CAMBRIC, MEDIDA: 7 CM X 3 M | H24: NO | I24: =ACUERDO!F129 -> UNIDAD | J24: =ACUERDO!T129 -> 100 | K24: =ACUERDO!G129 -> 100
A25: 130 | B25: =ACUERDO!C132 -> 2.9.5-461.29 | C25: =ACUERDO!D132 -> VENDAS USO MEDICO; MEDIDA: 10 CM X 4 M, TIPO: ENYESADA FRAGUADO RAPIDO GYSOFIX | H25: NO | I25: =ACUERDO!F132 -> UNIDAD | J25: =ACUERDO!T132 -> 93 | K25: =ACUERDO!G132 -> 300
A26: 131 | B26: =ACUERDO!C133 -> 2.9.5-461.28 | C26: =ACUERDO!D133 -> VENDAS USO MEDICO; MEDIDA: 15 CM X 4 M, TIPO: ENYESADA FRAGUADO RAPIDO GYSOFIX | H26: NO | I26: =ACUERDO!F133 -> UNIDAD | J26: =ACUERDO!T133 -> 93 | K26: =ACUERDO!G133 -> 500
A27: 132 | B27: =ACUERDO!C134 -> 2.9.5-461.27 | C27: =ACUERDO!D134 -> VENDAS USO MEDICO; , MEDIDA: 20 CM X 4 M, TIPO: ENYESADA FRAGUADO RAPIDO GYSOFIX | H27: NO | I27: =ACUERDO!F134 -> UNIDAD | J27: =ACUERDO!T134 -> 93 | K27: =ACUERDO!G134 -> 150
A29: Costo total estimado: PESOS CINCO MILLONES DOSCIENTO SESENTA Y DOS MIL CIENTO NOVENTA CON 00/100.- | J29: =SUMPRODUCT(J12:J27,K12:K27) -> 5262190

Sheet APG FCIA
A1: EJERCICIO: | D1: 2022 | P1: AUTORIZACION PARA GASTAR
A4: JURISDICCIÓN: | G4: ='NP FCIA'!D3 -> 040 - MINISTERIO DE SALUD
A5: SAF: | G5: ='NP FCIA'!D4 -> 011 - DIRECCION PROVINCIAL DE ADMINISTRACION - MS
A6: UNIDAD EJECUTORA: | G6: ='NP FCIA'!D5 -> DIRECCION PROVINCIAL DE FARMACIA E INSUMOS
A7: DEPENDENCIA SOLICITANTE: | G7: ='NP FCIA'!D6 -> DIRECCION PROVINCIAL DE FARMACIA E INSUMOS
A8: AUTORIZACIÓN:
A9: Señor Director de Administración o Titular del Servicio Administrativo Financiero:
A10: Autorizo la realización de los trámites correspondientes, a fin de proveer a este Organismo los bienes que se detallan en Nota de Pedido N° 018/2022 , afectando la erogación resultante a los créditos presupuestarios aprobados a favor de esta Unidad Ejecutora, conforme al siguiente detalle:
A12: IMPUTACIÓN PRESUPUESTARIA
A13: CÓDIGO | O13: DENOMINACIÓN DE LA PARTIDA PRESUPUESTARIA | Q13: IMPORTE
A14: PR | B14: SB | C14: PY | D14: AC | E14: OB | F14: UG | G14: FIN | H14: FUN | I14: I | J14: P | K14: P | L14: SubP | M14: M | N14: FF
A15: 30 | D15: 1 | F15: 4901 | G15: 3 | H15: 1 | I15: 2 | J15: 9 | K15: 5 | M15: 1 | N15: 1.1 | O15: UTILES MENORES MEDICOS, QUIRURGICOS Y DE LABORATORIO | Q15: ='NP FCIA'!J29 -> 5262190
A38: TOTAL DE PESOS: CINCO MILLONES DOSCIENTO SESENTA Y DOS MIL CIENTO NOVENTA CON 00/100.- | Q38: =SUM(Q15:Q37) -> 5262190
A40: JUSTIFICACIÓN:
A41: ='NP FCIA'!D8 -> ACUERDO MARCO PEDIDO DE INSUMOS COMUNES
N125: 91

Sheet NP LAB
A1: NOTA DE PEDIDO | J1: N° | K1: 008/2022
A3: JURISDICCIÓN: | D3: 040 - MINISTERIO DE SALUD
A4: SAF: | D4: 011 - DIRECCION PROVINCIAL DE ADMINISTRACION - MS
A5: UNIDAD EJECUTORA: | D5: DIRECCION PROVINCIAL DE LABORATORIO
A6: DEPENDENCIA SOLICITANTE: | D6: DIRECCION PROVINCIAL DE LABORATORIO
A7: PERIODO UTILIZACIÓN: | D7: UN (1) MES
A8: OBJETO: | D8: ACUERDO MARCO PEDIDO DE INSUMOS COMUNES
A10: Ítem | B10: Codigo Item | C10: DESCRIPCIÓN | H10: Adjunta Detalle Técnico | I10: Unidad Medida | J10: Precio Unitario Estimado | K10: Cantidad Solicitada
A12: 1 | B12: =ACUERDO!C3 -> 2.9.5-441.470 | C12: =ACUERDO!D3 -> AGUJAS QUIRURGICAS; TIPO: TERUMO 21GX1", ESPECIFICACION: 25/8, UNIDAD VENTA: CAJA X 100, PRESENTACION: CAJA X 100 | H12: NO | I12: =ACUERDO!F3 -> UNIDAD | J12: =ACUERDO!T3 -> 100 | K12: =ACUERDO!I3 -> 300
A13: 2 | B13: =ACUERDO!C4 -> 2.9.5-441.471 | C13: =ACUERDO!D4 -> AGUJAS QUIRURGICAS; TIPO: TERUMO 25GX5/8", ESPECIFICACION: 16/5, UNIDAD VENTA: CAJA X 100, PRESENTACION: CAJA X 100 | H13: NO | I13: =ACUERDO!F4 -> UNIDAD | J13: =ACUERDO!T4 -> 100 | K13: =ACUERDO!I4 -> 90
A14: 8 | B14: =ACUERDO!C10 -> 2.9.5-470.13 | C14: =ACUERDO!D10 -> ALGODONES; TIPO: HIDROFILADO, CAPACIDAD: 500 GR, PRESENTACION: ENVASE X 500 GR | H14: NO | I14: =ACUERDO!F10 -> UNIDAD | J14: =ACUERDO!T10 -> 100 | K14: =ACUERDO!I10 -> 300
A15: 23 | B15: =ACUERDO!C25 -> 2.9.5-2160.10 | C15: =ACUERDO!D25 -> DESCARTADORES DE AGUJAS; BOCA: 2, CAPACIDAD: 2 L, MODELO: P/AGUJAS COLECTA MULTIPLE, MODELO EQUIPO: P/AGUJAS COLECTA MULTIPLE, SISTEMA DE CIERRE: P/AGUJAS COLECTA MULTIPLE | H15: NO | I15: =ACUERDO!F25 -> UNIDAD | J15: =ACUERDO!T25 -> 91 | K15: =ACUERDO!I25 -> 90
A16: 40 | B16: =ACUERDO!C42 -> 2.9.5-1909.79 | C16: =ACUERDO!D42 -> GUANTES USO MEDICINAL; TIPO: EXAMINACION , TAMAÑO: MEDIANO, MATERIAL: LATEX, PRESENTACION: ENVASE X 100 UN | H16: NO | I16: =ACUERDO!F42 -> UNIDAD | J16: =ACUERDO!T42 -> 93 | K16: =ACUERDO!I42 -> 150
A17: 41 | B17: =ACUERDO!C43 -> 2.9.5-1909.195 | C17: =ACUERDO!D43 -> GUANTES USO MEDICINAL; TIPO: EXAMINACION, TAMAÑO: S 6/7, MATERIAL: LATEX, PRESENTACION: ENVASE X 100 UN, ESTERIL: NO, TALCO: CON, DESCARTABLE: SI | H17: NO | I17: =ACUERDO!F43 -> UNIDAD | J17: =ACUERDO!T43 -> 93 | K17: =ACUERDO!I43 -> 150
A18: 42 | B18: =ACUERDO!C44 -> 2.9.5-1909.172 | C18: =ACUERDO!D44 -> GUANTES USO MEDICINAL; TIPO: EXAMINACION, TAMAÑO: S 6/7, MATERIAL: NITRILO, PRESENTACION: ENVASE X 100 UN, ESTERIL: NO, TALCO: SIN, DESCARTABLE: SI | H18: NO | I18: =ACUERDO!F44 -> UNIDAD | J18: =ACUERDO!T44 -> 93 | K18: =ACUERDO!I44 -> 30
A19: 43 | B19: =ACUERDO!C45 -> 2.9.5-1909.174 | C19: =ACUERDO!D45 -> GUANTES USO MEDICINAL; TIPO: EXAMINACION, TAMAÑO: L 8/9, MATERIAL: NITRILO, PRESENTACION: ENVASE X 100 UN, ESTERIL: NO, TALCO: SIN, DESCARTABLE: SI | H19: NO | I19: =ACUERDO!F45 -> UNIDAD | J19: =ACUERDO!T45 -> 93 | K19: =ACUERDO!I45 -> 15
A20: 44 | B20: =ACUERDO!C46 -> 2.9.5-1909.173 | C20: =ACUERDO!D46 -> GUANTES USO MEDICINAL; TIPO: EXAMINACION, TAMAÑO: M 7/8, MATERIAL: NITRILO, PRESENTACION: ENVASE X 100 UN, ESTERIL: NO, TALCO: SIN, DESCARTABLE: SI | H20: NO | I20: =ACUERDO!F46 -> UNIDAD | J20: =ACUERDO!T46 -> 93 | K20: =ACUERDO!I46 -> 30
A21: 45 | B21: =ACUERDO!C47 -> 2.9.5-1909.169 | C21: =ACUERDO!D47 -> GUANTES USO MEDICINAL; TIPO: EXAMINACION, TAMAÑO: L 8/9, MATERIAL: VINILO, PRESENTACION: ENVASE X 100 UN, ESTERIL: NO, TALCO: SIN, DESCARTABLE: SI | H21: NO | I21: =ACUERDO!F47 -> UNIDAD | J21: =ACUERDO!T47 -> 93 | K21: =ACUERDO!I47 -> 15
A22: 46 | B22: =ACUERDO!C48 -> 2.9.5-1909.168 | C22: =ACUERDO!D48 -> GUANTES USO MEDICINAL; TIPO: EXAMINACION, TAMAÑO: M 7/8, MATERIAL: VINILO, PRESENTACION: ENVASE X 100 UN, ESTERIL: NO, TALCO: SIN, DESCARTABLE: SI | H22: NO | I22: =ACUERDO!F48 -> UNIDAD | J22: =ACUERDO!T48 -> 93 | K22: =ACUERDO!I48 -> 150
A23: 55 | B23: =ACUERDO!C57 -> 2.9.5-2157.60 | C23: =ACUERDO!D57 -> JERINGAS DESCARTABLES; CAPACIDAD: 10 mL, AGUJA: SIN, USO: MEDICINAL | H23: NO | I23: =ACUERDO!F57 -> UNIDAD | J23: =ACUERDO!T57 -> 93 | K23: =ACUERDO!I57 -> 90
A24: 57 | B24: =ACUERDO!C59 -> 2.9.5-2157.67 | C24: =ACUERDO!D59 -> JERINGAS DESCARTABLES; CAPACIDAD: 5 CM3, AGUJA: SIN, USO: SIN VALOR | H24: NO | I24: =ACUERDO!F59 -> UNIDAD | J24: =ACUERDO!T59 -> 93 | K24: =ACUERDO!I59 -> 150
A25: 65 | B25: =ACUERDO!C67 -> 2.9.5-1909.96 | C25: =ACUERDO!D67 -> GUANTES USO MEDICINAL; TIPO: MANOPLA, TAMAÑO: MEDIANO, MATERIAL: POLIETILENO, PRESENTACION: ENVASE X 100 | H25: NO | I25: =ACUERDO!F67 -> UNIDAD | J25: =ACUERDO!T67 -> 93 | K25: =ACUERDO!I67 -> 150
A26: 75 | B26: =ACUERDO!C77 -> 2.9.5-2562.11 | C26: =ACUERDO!D77 -> PORTAOBJETOS P/MICROSCOPIO; MATERIAL: VIDRIO, PRESENTACION: CAJA X 100 UN, TAMAÑO: 25 X 76 X 1,2 mm | H26: NO | I26: =ACUERDO!F77 -> UNIDAD | J26: =ACUERDO!T77 -> 91 | K26: =ACUERDO!I77 -> 150
A28: Costo total estimado: PESOS CIENTO SETENTA Y SIETE MIL TRESCIENTOS TREINTA CON 00/100.- | J28: =SUMPRODUCT(J12:J26,K12:K26) -> 177330

Sheet APG LAB
A1: EJERCICIO: | D1: 2022 | P1: AUTORIZACION PARA GASTAR
A4: JURISDICCIÓN: | G4: ='NP LAB'!D3 -> 040 - MINISTERIO DE SALUD
A5: SAF: | G5: ='NP LAB'!D4 -> 011 - DIRECCION PROVINCIAL DE ADMINISTRACION - MS
A6: UNIDAD EJECUTORA: | G6: ='NP LAB'!D5 -> DIRECCION PROVINCIAL DE LABORATORIO
A7: DEPENDENCIA SOLICITANTE: | G7: ='NP LAB'!D6 -> DIRECCION PROVINCIAL DE LABORATORIO
A8: AUTORIZACIÓN:
A9: Señor Director de Administración o Titular del Servicio Administrativo Financiero:
A10: Autorizo la realización de los trámites correspondientes, a fin de proveer a este Organismo los bienes que se detallan en Nota de Pedido N° 008/2022 , afectando la erogación resultante a los créditos presupuestarios aprobados a favor de esta Unidad Ejecutora, conforme al siguiente detalle:
A12: IMPUTACIÓN PRESUPUESTARIA
A13: CÓDIGO | O13: DENOMINACIÓN DE LA PARTIDA PRESUPUESTARIA | Q13: IMPORTE
A14: PR | B14: SB | C14: PY | D14: AC | E14: OB | F14: UG | G14: FIN | H14: FUN | I14: I | J14: P | K14: P | L14: SubP | M14: M | N14: FF
A15: 62 | D15: 1 | F15: 4901 | G15: 3 | H15: 1 | I15: 2 | J15: 9 | K15: 5 | M15: 1 | N15: 1.1 | O15: UTILES MENORES MEDICOS, QUIRURGICOS Y DE LABORATORIO | Q15: ='NP LAB'!J28 -> 177330
A38: TOTAL DE PESOS: CIENTO SETENTA Y SIETE MIL TRESCIENTOS TREINTA CON 00/100.- | Q38: =SUM(Q15:Q37) -> 177330
A40: JUSTIFICACIÓN:
A41: ='NP LAB'!D8 -> ACUERDO MARCO PEDIDO DE INSUMOS COMUNES
N125: 91

Sheet NP BS
A1: NOTA DE PEDIDO | J1: N° | K1: 011/2022
A3: JURISDICCIÓN: | D3: 040 - MINISTERIO DE SALUD
A4: SAF: | D4: 011 - DIRECCION PROVINCIAL DE ADMINISTRACION - MS
A5: UNIDAD EJECUTORA: | D5: DIRECCION PROVINCIAL BANCO DE SANGRE
A6: DEPENDENCIA SOLICITANTE: | D6: DIRECCION PROVINCIAL BANCO DE SANGRE
A7: PERIODO UTILIZACIÓN: | D7: UN (1) MES
A8: OBJETO: | D8: ACUERDO MARCO PEDIDO DE INSUMOS COMUNES
A10: Ítem | B10: Codigo Item | C10: DESCRIPCIÓN | H10: Adjunta Detalle Técnico | I10: Unidad Medida | J10: Precio Unitario Estimado | K10: Cantidad Solicitada
A12: 1 | B12: =ACUERDO!C3 -> 2.9.5-441.470 | C12: =ACUERDO!D3 -> AGUJAS QUIRURGICAS; TIPO: TERUMO 21GX1", ESPECIFICACION: 25/8, UNIDAD VENTA: CAJA X 100, PRESENTACION: CAJA X 100 | H12: NO | I12: =ACUERDO!F3 -> UNIDAD | J12: =ACUERDO!T3 -> 100 | K12: =ACUERDO!O3 -> 3
A13: 8 | B13: =ACUERDO!C10 -> 2.9.5-470.13 | C13: =ACUERDO!D10 -> ALGODONES; TIPO: HIDROFILADO, CAPACIDAD: 500 GR, PRESENTACION: ENVASE X 500 GR | H13: NO | I13: =ACUERDO!F10 -> UNIDAD | J13: =ACUERDO!T10 -> 100 | K13: =ACUERDO!O10 -> 20
A14: 10 | B14: =ACUERDO!C12 -> 2.9.5-428.21 | C14: =ACUERDO!D12 -> BARBIJOS; TIPO: 3 CAPAS | H14: NO | I14: =ACUERDO!F12 -> UNIDAD | J14: =ACUERDO!T12 -> 91 | K14: =ACUERDO!O12 -> 1000
A15: 39 | B15: =ACUERDO!C41 -> 2.9.5-1909.78 | C15: =ACUERDO!D41 -> GUANTES USO MEDICINAL; TIPO: EXAMINACION , TAMAÑO: GRANDE, MATERIAL: LATEX, PRESENTACION: ENVASE X 100 UN | H15: NO | I15: =ACUERDO!F41 -> UNIDAD | J15: =ACUERDO!T41 -> 93 | K15: =ACUERDO!O41 -> 10
A16: 40 | B16: =ACUERDO!C42 -> 2.9.5-1909.79 | C16: =ACUERDO!D42 -> GUANTES USO MEDICINAL; TIPO: EXAMINACION , TAMAÑO: MEDIANO, MATERIAL: LATEX, PRESENTACION: ENVASE X 100 UN | H16: NO | I16: =ACUERDO!F42 -> UNIDAD | J16: =ACUERDO!T42 -> 93 | K16: =ACUERDO!O42 -> 10
A17: 41 | B17: =ACUERDO!C43 -> 2.9.5-1909.195 | C17: =ACUERDO!D43 -> GUANTES USO MEDICINAL; TIPO: EXAMINACION, TAMAÑO: S 6/7, MATERIAL: LATEX, PRESENTACION: ENVASE X 100 UN, ESTERIL: NO, TALCO: CON, DESCARTABLE: SI | H17: NO | I17: =ACUERDO!F43 -> UNIDAD | J17: =ACUERDO!T43 -> 93 | K17: =ACUERDO!O43 -> 10
A18: 55 | B18: =ACUERDO!C57 -> 2.9.5-2157.60 | C18: =ACUERDO!D57 -> JERINGAS DESCARTABLES; CAPACIDAD: 10 mL, AGUJA: SIN, USO: MEDICINAL | H18: NO | I18: =ACUERDO!F57 -> UNIDAD | J18: =ACUERDO!T57 -> 93 | K18: =ACUERDO!O57 -> 500
A20: Costo total estimado: PESOS CIENTO CUARENTA Y DOS MIL QUINIENTOS NOVENTA CON 00/100.- | J20: =SUMPRODUCT(J12:J18,K12:K18) -> 142590

Sheet APG BS
A1: EJERCICIO: | D1: 2022 | P1: AUTORIZACION PARA GASTAR
A4: JURISDICCIÓN: | G4: ='NP BS'!D3 -> 040 - MINISTERIO DE SALUD
A5: SAF: | G5: ='NP BS'!D4 -> 011 - DIRECCION PROVINCIAL DE ADMINISTRACION - MS
A6: UNIDAD EJECUTORA: | G6: ='NP BS'!D5 -> DIRECCION PROVINCIAL BANCO DE SANGRE
A7: DEPENDENCIA SOLICITANTE: | G7: ='NP BS'!D6 -> DIRECCION PROVINCIAL BANCO DE SANGRE
A8: AUTORIZACIÓN:
A9: Señor Director de Administración o Titular del Servicio Administrativo Financiero:
A10: Autorizo la realización de los trámites correspondientes, a fin de proveer a este Organismo los bienes que se detallan en Nota de Pedido N° 011/2022 , afectando la erogación resultante a los créditos presupuestarios aprobados a favor de esta Unidad Ejecutora, conforme al siguiente detalle:
A12: IMPUTACIÓN PRESUPUESTARIA
A13: CÓDIGO | O13: DENOMINACIÓN DE LA PARTIDA PRESUPUESTARIA | Q13: IMPORTE
A14: PR | B14: SB | C14: PY | D14: AC | E14: OB | F14: UG | G14: FIN | H14: FUN | I14: I | J14: P | K14: P | L14: SubP | M14: M | N14: FF
A15: 27 | D15: 1 | F15: 4901 | G15: 3 | H15: 1 | I15: 2 | J15: 9 | K15: 5 | M15: 1 | N15: 1.1 | O15: UTILES MENORES MEDICOS, QUIRURGICOS Y DE LABORATORIO | Q15: ='NP BS'!J20 -> 142590
A38: TOTAL DE PESOS: CIENTO CUARENTA Y DOS MIL QUINIENTOS NOVENTA CON 00/100.- | Q38: =SUM(Q15:Q37) -> 142590
A40: JUSTIFICACIÓN:
A41: ='NP BS'!D8 -> ACUERDO MARCO PEDIDO DE INSUMOS COMUNES
N125: 91

Sheet NP DPO
A1: NOTA DE PEDIDO | J1: N° | K1: 006/2022
A3: JURISDICCIÓN: | D3: 040 - MINISTERIO DE SALUD
A4: SAF: | D4: 011 - DIRECCION PROVINCIAL DE ADMINISTRACION - MS
A5: UNIDAD EJECUTORA: | D5: DIRECCION PROVINCIAL DE ODONTOLOGIA
A6: DEPENDENCIA SOLICITANTE: | D6: DIRECCION PROVINCIAL DE ODONTOLOGIA
A7: PERIODO UTILIZACIÓN: | D7: UN (1) MES
A8: OBJETO: | D8: ACUERDO MARCO PEDIDO DE INSUMOS COMUNES
A10: Ítem | B10: Codigo Item | C10: DESCRIPCIÓN | H10: Adjunta Detalle Técnico | I10: Unidad Medida | J10: Precio Unitario Estimado | K10: Cantidad Solicitada
A12: 8 | B12: =ACUERDO!C10 -> 2.9.5-470.13 | C12: =ACUERDO!D10 -> ALGODONES; TIPO: HIDROFILADO, CAPACIDAD: 500 GR, PRESENTACION: ENVASE X 500 GR | H12: NO | I12: =ACUERDO!F10 -> UNIDAD | J12: =ACUERDO!T10 -> 100 | K12: =ACUERDO!Q10 -> 20
A13: 9 | B13: =ACUERDO!C11 -> 2.9.5-446.1 | C13: =ACUERDO!D11 -> BAJALENGUAS DESCARTABLES; USO: ADULTOS, PAQUETES DE UNIDADES: X 100, PRESENTACION: X 100 | H13: NO | I13: =ACUERDO!F11 -> UNIDAD | J13: =ACUERDO!T11 -> 100 | K13: =ACUERDO!Q11 -> 1500
A14: 10 | B14: =ACUERDO!C12 -> 2.9.5-428.21 | C14: =ACUERDO!D12 -> BARBIJOS; TIPO: 3 CAPAS | H14: NO | I14: =ACUERDO!F12 -> UNIDAD | J14: =ACUERDO!T12 -> 91 | K14: =ACUERDO!Q12 -> 1500
A15: 11 | B15: =ACUERDO!C13 -> 2.9.5-428.36 | C15: =ACUERDO!D13 -> BARBIJOS; TIPO: COPA N95 SIN VALVULA, MATERIAL: NO TEJIDO, CANTIDAD DE CAPAS: DOS, DESCARTABLE: SI, PRESENTACION: UNIDAD | H15: NO | I15: =ACUERDO!F13 -> UNIDAD | J15: =ACUERDO!T13 -> 93 | K15: =ACUERDO!Q13 -> 1500
A16: 14 | B16: =ACUERDO!C16 -> 2.9.5-4198.170 | C16: =ACUERDO!D16 -> ELEMENTOS DESC. P/CIRUGIAS; TIPO: CAMISOLIN HEMORREP. DE 30 GRAMOS CON MANGAS Y PUÑOS ELASTICOS DE 1,4 MTRS DE LARGO, CANTIDAD: POR UNIDAD, PRESENTACION: UNIDAD | H16: NO | I16: =ACUERDO!F16 -> UNIDAD | J16: =ACUERDO!T16 -> 91 | K16: =ACUERDO!Q16 -> 50
A17: 34 | B17: =ACUERDO!C36 -> 2.9.5-1909.135 | C17: =ACUERDO!D36 -> GUANTES USO MEDICINAL; TIPO: ESTERIL, TAMAÑO: 6 1/2 CAÑA LARGA, MATERIAL: LATEX, PRESENTACION: PAR, ESTERIL: SI, TALCO: SIN, DESCARTABLE: SI | H17: NO | I17: =ACUERDO!F36 -> UNIDAD | J17: =ACUERDO!T36 -> 93 | K17: =ACUERDO!Q36 -> 10
A18: 35 | B18: =ACUERDO!C37 -> 2.9.5-1909.203 | C18: =ACUERDO!D37 -> GUANTES USO MEDICINAL; TIPO: ESTERIL, TAMAÑO: 7 CAÑA LARGA, MATERIAL: LATEX, PRESENTACION: PAR, ESTERIL: SI, TALCO: SIN, DESCARTABLE: SI | H18: NO | I18: =ACUERDO!F37 -> UNIDAD | J18: =ACUERDO!T37 -> 93 | K18: =ACUERDO!Q37 -> 10
A19: 41 | B19: =ACUERDO!C43 -> 2.9.5-1909.195 | C19: =ACUERDO!D43 -> GUANTES USO MEDICINAL; TIPO: EXAMINACION, TAMAÑO: S 6/7, MATERIAL: LATEX, PRESENTACION: ENVASE X 100 UN, ESTERIL: NO, TALCO: CON, DESCARTABLE: SI | H19: NO | I19: =ACUERDO!F43 -> UNIDAD | J19: =ACUERDO!T43 -> 93 | K19: =ACUERDO!Q43 -> 10
A20: 43 | B20: =ACUERDO!C45 -> 2.9.5-1909.174 | C20: =ACUERDO!D45 -> GUANTES USO MEDICINAL; TIPO: EXAMINACION, TAMAÑO: L 8/9, MATERIAL: NITRILO, PRESENTACION: ENVASE X 100 UN, ESTERIL: NO, TALCO: SIN, DESCARTABLE: SI | H20: NO | I20: =ACUERDO!F45 -> UNIDAD | J20: =ACUERDO!T45 -> 93 | K20: =ACUERDO!Q45 -> 10
A21: 44 | B21: =ACUERDO!C46 -> 2.9.5-1909.173 | C21: =ACUERDO!D46 -> GUANTES USO MEDICINAL; TIPO: EXAMINACION, TAMAÑO: M 7/8, MATERIAL: NITRILO, PRESENTACION: ENVASE X 100 UN, ESTERIL: NO, TALCO: SIN, DESCARTABLE: SI | H21: NO | I21: =ACUERDO!F46 -> UNIDAD | J21: =ACUERDO!T46 -> 93 | K21: =ACUERDO!Q46 -> 10
A22: 50 | B22: =ACUERDO!C52 -> 2.9.5-444.24 | C22: =ACUERDO!D52 -> HOJAS DE BISTURI; TIPO: CAJA X 100 UN, Nº: 15, NUMERO: 15 | H22: NO | I22: =ACUERDO!F52 -> UNIDAD | J22: =ACUERDO!T52 -> 93 | K22: =ACUERDO!Q52 -> 4
A23: 62 | B23: =ACUERDO!C64 -> 2.9.5-4198.171 | C23: =ACUERDO!D64 -> ELEMENTOS DESC. P/CIRUGIAS; TIPO: KIT DE CAMISOLIN 50 GRS CON PUÑO DE ALGODON + COFIA + BOTAS PAR, PRESENTACION: INDIVIDUAL, ESTERIL: NO | H23: NO | I23: =ACUERDO!F64 -> UNIDAD | J23: =ACUERDO!T64 -> 98 | K23: =ACUERDO!Q64 -> 40
A25: Costo total estimado: PESOS CUATROCIENTOS CUARENTA Y UN MIL CUATROCIENTOS NOVENTA Y DOS CON 00/100.- | J25: =SUMPRODUCT(J12:J23,K12:K23) -> 441492

Sheet APG DPO
A1: EJERCICIO: | D1: 2022 | P1: AUTORIZACION PARA GASTAR
A4: JURISDICCIÓN: | G4: ='NP DPO'!D3 -> 040 - MINISTERIO DE SALUD
A5: SAF: | G5: ='NP DPO'!D4 -> 011 - DIRECCION PROVINCIAL DE ADMINISTRACION - MS
A6: UNIDAD EJECUTORA: | G6: ='NP DPO'!D5 -> DIRECCION PROVINCIAL DE ODONTOLOGIA
A7: DEPENDENCIA SOLICITANTE: | G7: ='NP DPO'!D6 -> DIRECCION PROVINCIAL DE ODONTOLOGIA
A8: AUTORIZACIÓN:
A9: Señor Director de Administración o Titular del Servicio Administrativo Financiero:
A10: Autorizo la realización de los trámites correspondientes, a fin de proveer a este Organismo los bienes que se detallan en Nota de Pedido N° 006/2022 , afectando la erogación resultante a los créditos presupuestarios aprobados a favor de esta Unidad Ejecutora, conforme al siguiente detalle:
A12: IMPUTACIÓN PRESUPUESTARIA
A13: CÓDIGO | O13: DENOMINACIÓN DE LA PARTIDA PRESUPUESTARIA | Q13: IMPORTE
A14: PR | B14: SB | C14: PY | D14: AC | E14: OB | F14: UG | G14: FIN | H14: FUN | I14: I | J14: P | K14: P | L14: SubP | M14: M | N14: FF
A15: 29 | D15: 1 | F15: 4901 | G15: 3 | H15: 1 | I15: 2 | J15: 9 | K15: 5 | M15: 1 | N15: 1.1 | O15: UTILES MENORES MEDICOS, QUIRURGICOS Y DE LABORATORIO | Q15: ='NP DPO'!J25 -> 441492
A38: TOTAL DE PESOS: CUATROCIENTOS CUARENTA Y UN MIL CUATROCIENTOS NOVENTA Y DOS CON 00/100.- | Q38: =SUM(Q15:Q37) -> 441492
A40: JUSTIFICACIÓN:
A41: ='NP DPO'!D8 -> ACUERDO MARCO PEDIDO DE INSUMOS COMUNES
N125: 91
